Workbook
Name BSR【站点】: 运营数据表!#REF!
Name 站点: 站点目录!$A$2:$A$11

Sheet 表格使用说明
A2: 1. 数据导入
A3: ① | B3: 业绩报告
B4: 下载路径：亚马逊卖家后台>Business Report>Child Asin Report (筛选当天数据)
A6: ② | B6: Base
B7: 将所在站点销售的产品信息（站点，品名，ASIN,SKU）登记到这个BASE表中
A9: ③ | B9: 站点目录（二级目录）
B10: 将所在站点销售的产品品名进行登记
A14: ④ | B14: 广告数据 | C14: 从广告报表直接导出全部复制到本栏

Sheet 运营数据表
A1: 2022 | B1: 年份 | C1: 10 | D1: 月份 | E1: 7 | F1: 日期
A3: 运营数据表 | C3: =DATE($A$1,$C$1,$E$1) -> 44841 | D3: =DATE(YEAR(C3),MONTH(C3),DAY(C3)+1) -> 44842 | E3: =DATE(YEAR(D3),MONTH(D3),DAY(D3)+1) -> 44843 | F3: =DATE(YEAR(E3),MONTH(E3),DAY(E3)+1) -> 44844 | G3: =DATE(YEAR(F3),MONTH(F3),DAY(F3)+1) -> 44845 | H3: =DATE(YEAR(G3),MONTH(G3),DAY(G3)+1) -> 44846 | I3: =DATE(YEAR(H3),MONTH(H3),DAY(H3)+1) -> 44847 | J3: =WEEKNUM(C3,2)&"周" -> 41周 | K3: =DATE(YEAR(C3),MONTH(C3),DAY(C3)-1) -> 44840 | L3: =DATE(YEAR(K3),MONTH(K3),DAY(K3)-1) -> 44839 | M3: =DATE(YEAR(L3),MONTH(L3),DAY(L3)-1) -> 44838 | N3: =DATE(YEAR(M3),MONTH(M3),DAY(M3)-1) -> 44837 | O3: =DATE(YEAR(N3),MONTH(N3),DAY(N3)-1) -> 44836 | P3: =DATE(YEAR(O3),MONTH(O3),DAY(O3)-1) -> 44835 | Q3: =DATE(YEAR(P3),MONTH(P3),DAY(P3)-1) -> 44834 | R3: =WEEKNUM(K3,2)-1&"周" -> 40周 | S3: 周环比
C4: ="星期"&WEEKDAY(C3,2) -> 星期5 | D4: ="星期"&WEEKDAY(D3,2) -> 星期6 | E4: ="星期"&WEEKDAY(E3,2) -> 星期7 | F4: ="星期"&WEEKDAY(F3,2) -> 星期1 | G4: ="星期"&WEEKDAY(G3,2) -> 星期2 | H4: ="星期"&WEEKDAY(H3,2) -> 星期3 | I4: ="星期"&WEEKDAY(I3,2) -> 星期4 | K4: ="星期"&WEEKDAY(K3,2) -> 星期4 | L4: ="星期"&WEEKDAY(L3,2) -> 星期3 | M4: ="星期"&WEEKDAY(M3,2) -> 星期2 | N4: ="星期"&WEEKDAY(N3,2) -> 星期1 | O4: ="星期"&WEEKDAY(O3,2) -> 星期7 | P4: ="星期"&WEEKDAY(P3,2) -> 星期6 | Q4: ="星期"&WEEKDAY(Q3,2) -> 星期5
A5: 销售站点 | B5: 总浏览量/PV | C5: {=IFERROR(VLOOKUP(C$3&$A6&$A9,IF({1,0},业绩报告!$A$2:$A$8229&业绩报告!$B$2:$B$8229&业绩报告!$C$2:$C$8229,业绩报告!$F$2:$F$8229),2,0),"")} -> 571 | D5: {=IFERROR(VLOOKUP(D$3&$A6&$A9,IF({1,0},业绩报告!$A$2:$A$8229&业绩报告!$B$2:$B$8229&业绩报告!$C$2:$C$8229,业绩报告!$F$2:$F$8229),2,0),"")} -> 534 | E5: {=IFERROR(VLOOKUP(E$3&$A6&$A9,IF({1,0},业绩报告!$A$2:$A$8229&业绩报告!$B$2:$B$8229&业绩报告!$C$2:$C$8229,业绩报告!$F$2:$F$8229),2,0),"")} -> 668 | F5: {=IFERROR(VLOOKUP(F$3&$A6&$A9,IF({1,0},业绩报告!$A$2:$A$8229&业绩报告!$B$2:$B$8229&业绩报告!$C$2:$C$8229,业绩报告!$F$2:$F$8229),2,0),"")} -> 506 | G5: {=IFERROR(VLOOKUP(G$3&$A6&$A9,IF({1,0},业绩报告!$A$2:$A$8229&业绩报告!$B$2:$B$8229&业绩报告!$C$2:$C$8229,业绩报告!$F$2:$F$8229),2,0),"")} -> 533 | H5: {=IFERROR(VLOOKUP(H$3&$A6&$A9,IF({1,0},业绩报告!$A$2:$A$8229&业绩报告!$B$2:$B$8229&业绩报告!$C$2:$C$8229,业绩报告!$F$2:$F$8229),2,0),"")} -> 0 | I5: {=IFERROR(VLOOKUP(I$3&$A6&$A9,IF({1,0},业绩报告!$A$2:$A$8229&业绩报告!$B$2:$B$8229&业绩报告!$C$2:$C$8229,业绩报告!$F$2:$F$8229),2,0),"")} -> 0 | J5: =SUM(C5:I5) -> 2812 | K5: {=IFERROR(VLOOKUP(K$3&$A6&$A9,IF({1,0},业绩报告!$A$2:$A$8229&业绩报告!$B$2:$B$8229&业绩报告!$C$2:$C$8229,业绩报告!$F$2:$F$8229),2,0),"")} -> 895 | L5: {=IFERROR(VLOOKUP(L$3&$A6&$A9,IF({1,0},业绩报告!$A$2:$A$8229&业绩报告!$B$2:$B$8229&业绩报告!$C$2:$C$8229,业绩报告!$F$2:$F$8229),2,0),"")} -> 827 | M5: {=IFERROR(VLOOKUP(M$3&$A6&$A9,IF({1,0},业绩报告!$A$2:$A$8229&业绩报告!$B$2:$B$8229&业绩报告!$C$2:$C$8229,业绩报告!$F$2:$F$8229),2,0),"")} -> 639 | N5: {=IFERROR(VLOOKUP(N$3&$A6&$A9,IF({1,0},业绩报告!$A$2:$A$8229&业绩报告!$B$2:$B$8229&业绩报告!$C$2:$C$8229,业绩报告!$F$2:$F$8229),2,0),"")} -> 812 | O5: {=IFERROR(VLOOKUP(O$3&$A6&$A9,IF({1,0},业绩报告!$A$2:$A$8229&业绩报告!$B$2:$B$8229&业绩报告!$C$2:$C$8229,业绩报告!$F$2:$F$8229),2,0),"")} -> 947 | P5: {=IFERROR(VLOOKUP(P$3&$A6&$A9,IF({1,0},业绩报告!$A$2:$A$8229&业绩报告!$B$2:$B$8229&业绩报告!$C$2:$C$8229,业绩报告!$F$2:$F$8229),2,0),"")} -> 555 | Q5: {=IFERROR(VLOOKUP(Q$3&$A6&$A9,IF({1,0},业绩报告!$A$2:$A$8229&业绩报告!$B$2:$B$8229&业绩报告!$C$2:$C$8229,业绩报告!$F$2:$F$8229),2,0),"")} -> 391 | R5: =SUM(K5:Q5) -> 5066
A6: US | B6: 访客数/UV | C6: {=IFERROR(VLOOKUP(C$3&$A6&$A9,IF({1,0},业绩报告!$A$2:$A$8229&业绩报告!$B$2:$B$8229&业绩报告!$C$2:$C$8229,业绩报告!$E$2:$E$8229),2,0),"")} -> 426 | D6: {=IFERROR(VLOOKUP(D$3&$A6&$A9,IF({1,0},业绩报告!$A$2:$A$8229&业绩报告!$B$2:$B$8229&业绩报告!$C$2:$C$8229,业绩报告!$E$2:$E$8229),2,0),"")} -> 404 | E6: {=IFERROR(VLOOKUP(E$3&$A6&$A9,IF({1,0},业绩报告!$A$2:$A$8229&业绩报告!$B$2:$B$8229&业绩报告!$C$2:$C$8229,业绩报告!$E$2:$E$8229),2,0),"")} -> 486 | F6: {=IFERROR(VLOOKUP(F$3&$A6&$A9,IF({1,0},业绩报告!$A$2:$A$8229&业绩报告!$B$2:$B$8229&业绩报告!$C$2:$C$8229,业绩报告!$E$2:$E$8229),2,0),"")} -> 385 | G6: {=IFERROR(VLOOKUP(G$3&$A6&$A9,IF({1,0},业绩报告!$A$2:$A$8229&业绩报告!$B$2:$B$8229&业绩报告!$C$2:$C$8229,业绩报告!$E$2:$E$8229),2,0),"")} -> 406 | H6: {=IFERROR(VLOOKUP(H$3&$A6&$A9,IF({1,0},业绩报告!$A$2:$A$8229&业绩报告!$B$2:$B$8229&业绩报告!$C$2:$C$8229,业绩报告!$E$2:$E$8229),2,0),"")} -> 0 | I6: {=IFERROR(VLOOKUP(I$3&$A6&$A9,IF({1,0},业绩报告!$A$2:$A$8229&业绩报告!$B$2:$B$8229&业绩报告!$C$2:$C$8229,业绩报告!$E$2:$E$8229),2,0),"")} -> 0 | J6: =SUM(C6:I6) -> 2107 | K6: {=IFERROR(VLOOKUP(K$3&$A6&$A9,IF({1,0},业绩报告!$A$2:$A$8229&业绩报告!$B$2:$B$8229&业绩报告!$C$2:$C$8229,业绩报告!$E$2:$E$8229),2,0),"")} -> 677 | L6: {=IFERROR(VLOOKUP(L$3&$A6&$A9,IF({1,0},业绩报告!$A$2:$A$8229&业绩报告!$B$2:$B$8229&业绩报告!$C$2:$C$8229,业绩报告!$E$2:$E$8229),2,0),"")} -> 632 | M6: {=IFERROR(VLOOKUP(M$3&$A6&$A9,IF({1,0},业绩报告!$A$2:$A$8229&业绩报告!$B$2:$B$8229&业绩报告!$C$2:$C$8229,业绩报告!$E$2:$E$8229),2,0),"")} -> 474 | N6: {=IFERROR(VLOOKUP(N$3&$A6&$A9,IF({1,0},业绩报告!$A$2:$A$8229&业绩报告!$B$2:$B$8229&业绩报告!$C$2:$C$8229,业绩报告!$E$2:$E$8229),2,0),"")} -> 631 | O6: {=IFERROR(VLOOKUP(O$3&$A6&$A9,IF({1,0},业绩报告!$A$2:$A$8229&业绩报告!$B$2:$B$8229&业绩报告!$C$2:$C$8229,业绩报告!$E$2:$E$8229),2,0),"")} -> 689 | P6: {=IFERROR(VLOOKUP(P$3&$A6&$A9,IF({1,0},业绩报告!$A$2:$A$8229&业绩报告!$B$2:$B$8229&业绩报告!$C$2:$C$8229,业绩报告!$E$2:$E$8229),2,0),"")} -> 386 | Q6: {=IFERROR(VLOOKUP(Q$3&$A6&$A9,IF({1,0},业绩报告!$A$2:$A$8229&业绩报告!$B$2:$B$8229&业绩报告!$C$2:$C$8229,业绩报告!$E$2:$E$8229),2,0),"")} -> 303 | R6: =SUM(K6:Q6) -> 3792
A7: US | B7: 自然浏览量/pv | C7: =C5-C81 -> 495 | D7: =D5-D81 -> 475 | E7: =E5-E81 -> 581 | F7: =F5-F81 -> 431 | G7: =G5-G81 -> 442 | H7: =H5-H81 -> -98 | I7: =I5-I81 -> 0 | J7: =J5-J81 -> 2326 | ... R7: =R5-R81 -> 4413
A8: 产品名 | B8: 总销量 | C8: {=IFERROR(VLOOKUP(C$3&$A6&$A9,IF({1,0},业绩报告!$A$2:$A$8229&业绩报告!$B$2:$B$8229&业绩报告!$C$2:$C$8229,业绩报告!$G$2:$G$8229),2,0),"")} -> 31 | D8: {=IFERROR(VLOOKUP(D$3&$A6&$A9,IF({1,0},业绩报告!$A$2:$A$8229&业绩报告!$B$2:$B$8229&业绩报告!$C$2:$C$8229,业绩报告!$G$2:$G$8229),2,0),"")} -> 27 | E8: {=IFERROR(VLOOKUP(E$3&$A6&$A9,IF({1,0},业绩报告!$A$2:$A$8229&业绩报告!$B$2:$B$8229&业绩报告!$C$2:$C$8229,业绩报告!$G$2:$G$8229),2,0),"")} -> 18 | F8: {=IFERROR(VLOOKUP(F$3&$A6&$A9,IF({1,0},业绩报告!$A$2:$A$8229&业绩报告!$B$2:$B$8229&业绩报告!$C$2:$C$8229,业绩报告!$G$2:$G$8229),2,0),"")} -> 27 | G8: {=IFERROR(VLOOKUP(G$3&$A6&$A9,IF({1,0},业绩报告!$A$2:$A$8229&业绩报告!$B$2:$B$8229&业绩报告!$C$2:$C$8229,业绩报告!$G$2:$G$8229),2,0),"")} -> 44 | H8: {=IFERROR(VLOOKUP(H$3&$A6&$A9,IF({1,0},业绩报告!$A$2:$A$8229&业绩报告!$B$2:$B$8229&业绩报告!$C$2:$C$8229,业绩报告!$G$2:$G$8229),2,0),"")} -> 55 | I8: {=IFERROR(VLOOKUP(I$3&$A6&$A9,IF({1,0},业绩报告!$A$2:$A$8229&业绩报告!$B$2:$B$8229&业绩报告!$C$2:$C$8229,业绩报告!$G$2:$G$8229),2,0),"")} -> 0 | J8: =SUM(C8:I8) -> 202 | K8: {=IFERROR(VLOOKUP(K$3&$A6&$A9,IF({1,0},业绩报告!$A$2:$A$8229&业绩报告!$B$2:$B$8229&业绩报告!$C$2:$C$8229,业绩报告!$G$2:$G$8229),2,0),"")} -> 31 | L8: {=IFERROR(VLOOKUP(L$3&$A6&$A9,IF({1,0},业绩报告!$A$2:$A$8229&业绩报告!$B$2:$B$8229&业绩报告!$C$2:$C$8229,业绩报告!$G$2:$G$8229),2,0),"")} -> 28 | M8: {=IFERROR(VLOOKUP(M$3&$A6&$A9,IF({1,0},业绩报告!$A$2:$A$8229&业绩报告!$B$2:$B$8229&业绩报告!$C$2:$C$8229,业绩报告!$G$2:$G$8229),2,0),"")} -> 36 | N8: {=IFERROR(VLOOKUP(N$3&$A6&$A9,IF({1,0},业绩报告!$A$2:$A$8229&业绩报告!$B$2:$B$8229&业绩报告!$C$2:$C$8229,业绩报告!$G$2:$G$8229),2,0),"")} -> 39 | O8: {=IFERROR(VLOOKUP(O$3&$A6&$A9,IF({1,0},业绩报告!$A$2:$A$8229&业绩报告!$B$2:$B$8229&业绩报告!$C$2:$C$8229,业绩报告!$G$2:$G$8229),2,0),"")} -> 38 | P8: {=IFERROR(VLOOKUP(P$3&$A6&$A9,IF({1,0},业绩报告!$A$2:$A$8229&业绩报告!$B$2:$B$8229&业绩报告!$C$2:$C$8229,业绩报告!$G$2:$G$8229),2,0),"")} -> 29 | Q8: {=IFERROR(VLOOKUP(Q$3&$A6&$A9,IF({1,0},业绩报告!$A$2:$A$8229&业绩报告!$B$2:$B$8229&业绩报告!$C$2:$C$8229,业绩报告!$G$2:$G$8229),2,0),"")} -> 23 | R8: =SUM(K8:Q8) -> 224
A9: 按压皂液器 | B9: 转化率 | C9: =IFERROR(C8/C6,"0") -> 0.072769953 | D9: =IFERROR(D8/D6,"0") -> 0.066831683 | E9: =IFERROR(E8/E6,"0") -> 0.037037037 | F9: =IFERROR(F8/F6,"0") -> 0.07012987 | G9: =IFERROR(G8/G6,"0") -> 0.10837438 | H9: =IFERROR(H8/H6,"0") -> 0 | I9: =IFERROR(I8/I6,"0") -> 0 | J9: =IFERROR(J8/J6,"0") -> 0.095870907 | ... R9: =IFERROR(R8/R6,"0") -> 0.05907173
A10: {=VLOOKUP($A$6&$A$9,IF({1,0},base!$C$2:$C$13&base!$D$2:$D$13,base!$F$2:$F$13),2,0)} -> B0B17717D3 | B10: 销售额 | C10: {=IFERROR(VLOOKUP(C$3&$A6&$A9,IF({1,0},业绩报告!$A$2:$A$8229&业绩报告!$B$2:$B$8229&业绩报告!$C$2:$C$8229,业绩报告!$H$2:$H$8229),2,0),"")} -> 371.69 | D10: {=IFERROR(VLOOKUP(D$3&$A6&$A9,IF({1,0},业绩报告!$A$2:$A$8229&业绩报告!$B$2:$B$8229&业绩报告!$C$2:$C$8229,业绩报告!$H$2:$H$8229),2,0),"")} -> 323.73 | E10: {=IFERROR(VLOOKUP(E$3&$A6&$A9,IF({1,0},业绩报告!$A$2:$A$8229&业绩报告!$B$2:$B$8229&业绩报告!$C$2:$C$8229,业绩报告!$H$2:$H$8229),2,0),"")} -> 215.82 | F10: {=IFERROR(VLOOKUP(F$3&$A6&$A9,IF({1,0},业绩报告!$A$2:$A$8229&业绩报告!$B$2:$B$8229&业绩报告!$C$2:$C$8229,业绩报告!$H$2:$H$8229),2,0),"")} -> 323.73 | G10: {=IFERROR(VLOOKUP(G$3&$A6&$A9,IF({1,0},业绩报告!$A$2:$A$8229&业绩报告!$B$2:$B$8229&业绩报告!$C$2:$C$8229,业绩报告!$H$2:$H$8229),2,0),"")} -> 429.16 | H10: {=IFERROR(VLOOKUP(H$3&$A6&$A9,IF({1,0},业绩报告!$A$2:$A$8229&业绩报告!$B$2:$B$8229&业绩报告!$C$2:$C$8229,业绩报告!$H$2:$H$8229),2,0),"")} -> 539.45 | I10: {=IFERROR(VLOOKUP(I$3&$A6&$A9,IF({1,0},业绩报告!$A$2:$A$8229&业绩报告!$B$2:$B$8229&业绩报告!$C$2:$C$8229,业绩报告!$H$2:$H$8229),2,0),"")} -> 0 | J10: =IFERROR(SUM(C10:I10),"0") -> 2203.58 | K10: {=IFERROR(VLOOKUP(K$3&$A6&$A9,IF({1,0},业绩报告!$A$2:$A$8229&业绩报告!$B$2:$B$8229&业绩报告!$C$2:$C$8229,业绩报告!$H$2:$H$8229),2,0),"")} -> 371.69 | L10: {=IFERROR(VLOOKUP(L$3&$A6&$A9,IF({1,0},业绩报告!$A$2:$A$8229&业绩报告!$B$2:$B$8229&业绩报告!$C$2:$C$8229,业绩报告!$H$2:$H$8229),2,0),"")} -> 335.72 | M10: {=IFERROR(VLOOKUP(M$3&$A6&$A9,IF({1,0},业绩报告!$A$2:$A$8229&业绩报告!$B$2:$B$8229&业绩报告!$C$2:$C$8229,业绩报告!$H$2:$H$8229),2,0),"")} -> 431.64 | N10: {=IFERROR(VLOOKUP(N$3&$A6&$A9,IF({1,0},业绩报告!$A$2:$A$8229&业绩报告!$B$2:$B$8229&业绩报告!$C$2:$C$8229,业绩报告!$H$2:$H$8229),2,0),"")} -> 467.61 | O10: {=IFERROR(VLOOKUP(O$3&$A6&$A9,IF({1,0},业绩报告!$A$2:$A$8229&业绩报告!$B$2:$B$8229&业绩报告!$C$2:$C$8229,业绩报告!$H$2:$H$8229),2,0),"")} -> 455.62 | P10: {=IFERROR(VLOOKUP(P$3&$A6&$A9,IF({1,0},业绩报告!$A$2:$A$8229&业绩报告!$B$2:$B$8229&业绩报告!$C$2:$C$8229,业绩报告!$H$2:$H$8229),2,0),"")} -> 347.71 | Q10: {=IFERROR(VLOOKUP(Q$3&$A6&$A9,IF({1,0},业绩报告!$A$2:$A$8229&业绩报告!$B$2:$B$8229&业绩报告!$C$2:$C$8229,业绩报告!$H$2:$H$8229),2,0),"")} -> 275.77 | R10: =K10+L10+M10+N10+O10+P10+Q10 -> 2685.76
B11: 自然单 | C11: =C8-C82 -> 28 | D11: =D8-D82 -> 27 | E11: =E8-E82 -> 12 | F11: =F8-F82 -> 22 | G11: =G8-G82 -> 40 | H11: =H8-H82 -> 48 | I11: =I8-I82 -> 0 | J11: =SUM(C11:I11) -> 177 | K11: =K8-K82 -> 30 | L11: =L8-L82 -> 21 | M11: =M8-M82 -> 26 | N11: =N8-N82 -> 28 | O11: =O8-O82 -> 28 | P11: =P8-P82 -> 20 | Q11: =Q8-Q82 -> 18
B12: 售价 | C12: {=IFERROR(VLOOKUP(C$3&$A6&$A9,IF({1,0},业绩报告!$A$2:$A$8229&业绩报告!$B$2:$B$8229&业绩报告!$C$2:$C$8229,业绩报告!$I$2:$I$8229),2,0),"")} -> 11.99 | D12: {=IFERROR(VLOOKUP(D$3&$A6&$A9,IF({1,0},业绩报告!$A$2:$A$8229&业绩报告!$B$2:$B$8229&业绩报告!$C$2:$C$8229,业绩报告!$I$2:$I$8229),2,0),"")} -> 11.99 | E12: {=IFERROR(VLOOKUP(E$3&$A6&$A9,IF({1,0},业绩报告!$A$2:$A$8229&业绩报告!$B$2:$B$8229&业绩报告!$C$2:$C$8229,业绩报告!$I$2:$I$8229),2,0),"")} -> 11.99 | F12: {=IFERROR(VLOOKUP(F$3&$A6&$A9,IF({1,0},业绩报告!$A$2:$A$8229&业绩报告!$B$2:$B$8229&业绩报告!$C$2:$C$8229,业绩报告!$I$2:$I$8229),2,0),"")} -> 11.99 | G12: {=IFERROR(VLOOKUP(G$3&$A6&$A9,IF({1,0},业绩报告!$A$2:$A$8229&业绩报告!$B$2:$B$8229&业绩报告!$C$2:$C$8229,业绩报告!$I$2:$I$8229),2,0),"")} -> 9.59 | H12: {=IFERROR(VLOOKUP(H$3&$A6&$A9,IF({1,0},业绩报告!$A$2:$A$8229&业绩报告!$B$2:$B$8229&业绩报告!$C$2:$C$8229,业绩报告!$I$2:$I$8229),2,0),"")} -> 9.59 | I12: {=IFERROR(VLOOKUP(I$3&$A6&$A9,IF({1,0},业绩报告!$A$2:$A$8229&业绩报告!$B$2:$B$8229&业绩报告!$C$2:$C$8229,业绩报告!$I$2:$I$8229),2,0),"")} -> 11.99 | J12: =AVERAGE(C12:I12) -> 11.304286 | K12: {=IFERROR(VLOOKUP(K$3&$A6&$A9,IF({1,0},业绩报告!$A$2:$A$8229&业绩报告!$B$2:$B$8229&业绩报告!$C$2:$C$8229,业绩报告!$I$2:$I$8229),2,0),"")} -> 11.99 | L12: {=IFERROR(VLOOKUP(L$3&$A6&$A9,IF({1,0},业绩报告!$A$2:$A$8229&业绩报告!$B$2:$B$8229&业绩报告!$C$2:$C$8229,业绩报告!$I$2:$I$8229),2,0),"")} -> 11.99 | M12: {=IFERROR(VLOOKUP(M$3&$A6&$A9,IF({1,0},业绩报告!$A$2:$A$8229&业绩报告!$B$2:$B$8229&业绩报告!$C$2:$C$8229,业绩报告!$I$2:$I$8229),2,0),"")} -> 11.99 | N12: {=IFERROR(VLOOKUP(N$3&$A6&$A9,IF({1,0},业绩报告!$A$2:$A$8229&业绩报告!$B$2:$B$8229&业绩报告!$C$2:$C$8229,业绩报告!$I$2:$I$8229),2,0),"")} -> 11.99 | O12: {=IFERROR(VLOOKUP(O$3&$A6&$A9,IF({1,0},业绩报告!$A$2:$A$8229&业绩报告!$B$2:$B$8229&业绩报告!$C$2:$C$8229,业绩报告!$I$2:$I$8229),2,0),"")} -> 11.99 | P12: {=IFERROR(VLOOKUP(P$3&$A6&$A9,IF({1,0},业绩报告!$A$2:$A$8229&业绩报告!$B$2:$B$8229&业绩报告!$C$2:$C$8229,业绩报告!$I$2:$I$8229),2,0),"")} -> 11.99 | Q12: {=IFERROR(VLOOKUP(Q$3&$A6&$A9,IF({1,0},业绩报告!$A$2:$A$8229&业绩报告!$B$2:$B$8229&业绩报告!$C$2:$C$8229,业绩报告!$I$2:$I$8229),2,0),"")} -> 11.99
B13: 评分 | C13: {=IFERROR(VLOOKUP(C$3&$A6&$A9,IF({1,0},业绩报告!$A$2:$A$8229&业绩报告!$B$2:$B$8229&业绩报告!$C$2:$C$8229,业绩报告!$J$2:$J$8229),2,0),"")} -> 4.4 | D13: {=IFERROR(VLOOKUP(D$3&$A6&$A9,IF({1,0},业绩报告!$A$2:$A$8229&业绩报告!$B$2:$B$8229&业绩报告!$C$2:$C$8229,业绩报告!$J$2:$J$8229),2,0),"")} -> 4.5 | E13: {=IFERROR(VLOOKUP(E$3&$A6&$A9,IF({1,0},业绩报告!$A$2:$A$8229&业绩报告!$B$2:$B$8229&业绩报告!$C$2:$C$8229,业绩报告!$J$2:$J$8229),2,0),"")} -> 4.5 | F13: {=IFERROR(VLOOKUP(F$3&$A6&$A9,IF({1,0},业绩报告!$A$2:$A$8229&业绩报告!$B$2:$B$8229&业绩报告!$C$2:$C$8229,业绩报告!$J$2:$J$8229),2,0),"")} -> 4.4 | G13: {=IFERROR(VLOOKUP(G$3&$A6&$A9,IF({1,0},业绩报告!$A$2:$A$8229&业绩报告!$B$2:$B$8229&业绩报告!$C$2:$C$8229,业绩报告!$J$2:$J$8229),2,0),"")} -> 4.5 | H13: {=IFERROR(VLOOKUP(H$3&$A6&$A9,IF({1,0},业绩报告!$A$2:$A$8229&业绩报告!$B$2:$B$8229&业绩报告!$C$2:$C$8229,业绩报告!$J$2:$J$8229),2,0),"")} -> 4.5 | I13: {=IFERROR(VLOOKUP(I$3&$A6&$A9,IF({1,0},业绩报告!$A$2:$A$8229&业绩报告!$B$2:$B$8229&业绩报告!$C$2:$C$8229,业绩报告!$J$2:$J$8229),2,0),"")} -> 4.5 | J13: =AVERAGE(C13:I13) -> 4.4714286 | K13: {=IFERROR(VLOOKUP(K$3&$A6&$A9,IF({1,0},业绩报告!$A$2:$A$8229&业绩报告!$B$2:$B$8229&业绩报告!$C$2:$C$8229,业绩报告!$J$2:$J$8229),2,0),"")} -> 4.5 | L13: {=IFERROR(VLOOKUP(L$3&$A6&$A9,IF({1,0},业绩报告!$A$2:$A$8229&业绩报告!$B$2:$B$8229&业绩报告!$C$2:$C$8229,业绩报告!$J$2:$J$8229),2,0),"")} -> 4.5 | M13: {=IFERROR(VLOOKUP(M$3&$A6&$A9,IF({1,0},业绩报告!$A$2:$A$8229&业绩报告!$B$2:$B$8229&业绩报告!$C$2:$C$8229,业绩报告!$J$2:$J$8229),2,0),"")} -> 4.5 | N13: {=IFERROR(VLOOKUP(N$3&$A6&$A9,IF({1,0},业绩报告!$A$2:$A$8229&业绩报告!$B$2:$B$8229&业绩报告!$C$2:$C$8229,业绩报告!$J$2:$J$8229),2,0),"")} -> 4.5 | O13: {=IFERROR(VLOOKUP(O$3&$A6&$A9,IF({1,0},业绩报告!$A$2:$A$8229&业绩报告!$B$2:$B$8229&业绩报告!$C$2:$C$8229,业绩报告!$J$2:$J$8229),2,0),"")} -> 4.5 | P13: {=IFERROR(VLOOKUP(P$3&$A6&$A9,IF({1,0},业绩报告!$A$2:$A$8229&业绩报告!$B$2:$B$8229&业绩报告!$C$2:$C$8229,业绩报告!$J$2:$J$8229),2,0),"")} -> 4.4 | Q13: {=IFERROR(VLOOKUP(Q$3&$A6&$A9,IF({1,0},业绩报告!$A$2:$A$8229&业绩报告!$B$2:$B$8229&业绩报告!$C$2:$C$8229,业绩报告!$J$2:$J$8229),2,0),"")} -> 4.5
B14: 评论数 | C14: {=IFERROR(VLOOKUP(C$3&$A6&$A9,IF({1,0},业绩报告!$A$2:$A$8229&业绩报告!$B$2:$B$8229&业绩报告!$C$2:$C$8229,业绩报告!$K$2:$K$8229),2,0),"")} -> 120 | D14: {=IFERROR(VLOOKUP(D$3&$A6&$A9,IF({1,0},业绩报告!$A$2:$A$8229&业绩报告!$B$2:$B$8229&业绩报告!$C$2:$C$8229,业绩报告!$K$2:$K$8229),2,0),"")} -> 122 | E14: {=IFERROR(VLOOKUP(E$3&$A6&$A9,IF({1,0},业绩报告!$A$2:$A$8229&业绩报告!$B$2:$B$8229&业绩报告!$C$2:$C$8229,业绩报告!$K$2:$K$8229),2,0),"")} -> 123 | F14: {=IFERROR(VLOOKUP(F$3&$A6&$A9,IF({1,0},业绩报告!$A$2:$A$8229&业绩报告!$B$2:$B$8229&业绩报告!$C$2:$C$8229,业绩报告!$K$2:$K$8229),2,0),"")} -> 126 | G14: {=IFERROR(VLOOKUP(G$3&$A6&$A9,IF({1,0},业绩报告!$A$2:$A$8229&业绩报告!$B$2:$B$8229&业绩报告!$C$2:$C$8229,业绩报告!$K$2:$K$8229),2,0),"")} -> 132 | H14: {=IFERROR(VLOOKUP(H$3&$A6&$A9,IF({1,0},业绩报告!$A$2:$A$8229&业绩报告!$B$2:$B$8229&业绩报告!$C$2:$C$8229,业绩报告!$K$2:$K$8229),2,0),"")} -> 137 | I14: {=IFERROR(VLOOKUP(I$3&$A6&$A9,IF({1,0},业绩报告!$A$2:$A$8229&业绩报告!$B$2:$B$8229&业绩报告!$C$2:$C$8229,业绩报告!$K$2:$K$8229),2,0),"")} -> 137 | J14: =AVERAGE(C14:I14) -> 128.14286 | K14: {=IFERROR(VLOOKUP(K$3&$A6&$A9,IF({1,0},业绩报告!$A$2:$A$8229&业绩报告!$B$2:$B$8229&业绩报告!$C$2:$C$8229,业绩报告!$K$2:$K$8229),2,0),"")} -> 119 | L14: {=IFERROR(VLOOKUP(L$3&$A6&$A9,IF({1,0},业绩报告!$A$2:$A$8229&业绩报告!$B$2:$B$8229&业绩报告!$C$2:$C$8229,业绩报告!$K$2:$K$8229),2,0),"")} -> 118 | M14: {=IFERROR(VLOOKUP(M$3&$A6&$A9,IF({1,0},业绩报告!$A$2:$A$8229&业绩报告!$B$2:$B$8229&业绩报告!$C$2:$C$8229,业绩报告!$K$2:$K$8229),2,0),"")} -> 118 | N14: {=IFERROR(VLOOKUP(N$3&$A6&$A9,IF({1,0},业绩报告!$A$2:$A$8229&业绩报告!$B$2:$B$8229&业绩报告!$C$2:$C$8229,业绩报告!$K$2:$K$8229),2,0),"")} -> 118 | O14: {=IFERROR(VLOOKUP(O$3&$A6&$A9,IF({1,0},业绩报告!$A$2:$A$8229&业绩报告!$B$2:$B$8229&业绩报告!$C$2:$C$8229,业绩报告!$K$2:$K$8229),2,0),"")} -> 115 | P14: {=IFERROR(VLOOKUP(P$3&$A6&$A9,IF({1,0},业绩报告!$A$2:$A$8229&业绩报告!$B$2:$B$8229&业绩报告!$C$2:$C$8229,业绩报告!$K$2:$K$8229),2,0),"")} -> 113 | Q14: {=IFERROR(VLOOKUP(Q$3&$A6&$A9,IF({1,0},业绩报告!$A$2:$A$8229&业绩报告!$B$2:$B$8229&业绩报告!$C$2:$C$8229,业绩报告!$K$2:$K$8229),2,0),"")} -> 111
B15: 大类 | C15: {=IFERROR(VLOOKUP(C$3&$A6&$A9,IF({1,0},业绩报告!$A$2:$A$8229&业绩报告!$B$2:$B$8229&业绩报告!$C$2:$C$8229,业绩报告!$L$2:$L$8229),2,0),"")} -> Home & Kitchen | D15: {=IFERROR(VLOOKUP(D$3&$A6&$A9,IF({1,0},业绩报告!$A$2:$A$8229&业绩报告!$B$2:$B$8229&业绩报告!$C$2:$C$8229,业绩报告!$L$2:$L$8229),2,0),"")} -> Home & Kitchen | E15: {=IFERROR(VLOOKUP(E$3&$A6&$A9,IF({1,0},业绩报告!$A$2:$A$8229&业绩报告!$B$2:$B$8229&业绩报告!$C$2:$C$8229,业绩报告!$L$2:$L$8229),2,0),"")} -> Home & Kitchen | F15: {=IFERROR(VLOOKUP(F$3&$A6&$A9,IF({1,0},业绩报告!$A$2:$A$8229&业绩报告!$B$2:$B$8229&业绩报告!$C$2:$C$8229,业绩报告!$L$2:$L$8229),2,0),"")} -> Home & Kitchen | G15: {=IFERROR(VLOOKUP(G$3&$A6&$A9,IF({1,0},业绩报告!$A$2:$A$8229&业绩报告!$B$2:$B$8229&业绩报告!$C$2:$C$8229,业绩报告!$L$2:$L$8229),2,0),"")} -> Home & Kitchen | H15: {=IFERROR(VLOOKUP(H$3&$A6&$A9,IF({1,0},业绩报告!$A$2:$A$8229&业绩报告!$B$2:$B$8229&业绩报告!$C$2:$C$8229,业绩报告!$L$2:$L$8229),2,0),"")} -> Home & Kitchen | I15: {=IFERROR(VLOOKUP(I$3&$A6&$A9,IF({1,0},业绩报告!$A$2:$A$8229&业绩报告!$B$2:$B$8229&业绩报告!$C$2:$C$8229,业绩报告!$L$2:$L$8229),2,0),"")} -> Home & Kitchen | K15: {=IFERROR(VLOOKUP(K$3&$A6&$A9,IF({1,0},业绩报告!$A$2:$A$8229&业绩报告!$B$2:$B$8229&业绩报告!$C$2:$C$8229,业绩报告!$L$2:$L$8229),2,0),"")} -> Home & Kitchen | L15: {=IFERROR(VLOOKUP(L$3&$A6&$A9,IF({1,0},业绩报告!$A$2:$A$8229&业绩报告!$B$2:$B$8229&业绩报告!$C$2:$C$8229,业绩报告!$L$2:$L$8229),2,0),"")} -> Home & Kitchen | M15: {=IFERROR(VLOOKUP(M$3&$A6&$A9,IF({1,0},业绩报告!$A$2:$A$8229&业绩报告!$B$2:$B$8229&业绩报告!$C$2:$C$8229,业绩报告!$L$2:$L$8229),2,0),"")} -> Home & Kitchen | N15: {=IFERROR(VLOOKUP(N$3&$A6&$A9,IF({1,0},业绩报告!$A$2:$A$8229&业绩报告!$B$2:$B$8229&业绩报告!$C$2:$C$8229,业绩报告!$L$2:$L$8229),2,0),"")} -> Home & Kitchen | O15: {=IFERROR(VLOOKUP(O$3&$A6&$A9,IF({1,0},业绩报告!$A$2:$A$8229&业绩报告!$B$2:$B$8229&业绩报告!$C$2:$C$8229,业绩报告!$L$2:$L$8229),2,0),"")} -> Home & Kitchen | P15: {=IFERROR(VLOOKUP(P$3&$A6&$A9,IF({1,0},业绩报告!$A$2:$A$8229&业绩报告!$B$2:$B$8229&业绩报告!$C$2:$C$8229,业绩报告!$L$2:$L$8229),2,0),"")} -> Home & Kitchen | Q15: {=IFERROR(VLOOKUP(Q$3&$A6&$A9,IF({1,0},业绩报告!$A$2:$A$8229&业绩报告!$B$2:$B$8229&业绩报告!$C$2:$C$8229,业绩报告!$L$2:$L$8229),2,0),"")} -> Home & Kitchen
B16: 大类排名 | C16: {=IFERROR(VLOOKUP(C$3&$A6&$A9,IF({1,0},业绩报告!$A$2:$A$8229&业绩报告!$B$2:$B$8229&业绩报告!$C$2:$C$8229,业绩报告!$M$2:$M$8229),2,0),"")} -> 24893 | D16: {=IFERROR(VLOOKUP(D$3&$A6&$A9,IF({1,0},业绩报告!$A$2:$A$8229&业绩报告!$B$2:$B$8229&业绩报告!$C$2:$C$8229,业绩报告!$M$2:$M$8229),2,0),"")} -> 28,871 | E16: {=IFERROR(VLOOKUP(E$3&$A6&$A9,IF({1,0},业绩报告!$A$2:$A$8229&业绩报告!$B$2:$B$8229&业绩报告!$C$2:$C$8229,业绩报告!$M$2:$M$8229),2,0),"")} -> 35,650 | F16: {=IFERROR(VLOOKUP(F$3&$A6&$A9,IF({1,0},业绩报告!$A$2:$A$8229&业绩报告!$B$2:$B$8229&业绩报告!$C$2:$C$8229,业绩报告!$M$2:$M$8229),2,0),"")} -> 37,224 | G16: {=IFERROR(VLOOKUP(G$3&$A6&$A9,IF({1,0},业绩报告!$A$2:$A$8229&业绩报告!$B$2:$B$8229&业绩报告!$C$2:$C$8229,业绩报告!$M$2:$M$8229),2,0),"")} -> 27283 | H16: {=IFERROR(VLOOKUP(H$3&$A6&$A9,IF({1,0},业绩报告!$A$2:$A$8229&业绩报告!$B$2:$B$8229&业绩报告!$C$2:$C$8229,业绩报告!$M$2:$M$8229),2,0),"")} -> 28347 | I16: {=IFERROR(VLOOKUP(I$3&$A6&$A9,IF({1,0},业绩报告!$A$2:$A$8229&业绩报告!$B$2:$B$8229&业绩报告!$C$2:$C$8229,业绩报告!$M$2:$M$8229),2,0),"")} -> 27877 | J16: =AVERAGE(C16:I16) -> #DIV/0! | K16: {=IFERROR(VLOOKUP(K$3&$A6&$A9,IF({1,0},业绩报告!$A$2:$A$8229&业绩报告!$B$2:$B$8229&业绩报告!$C$2:$C$8229,业绩报告!$M$2:$M$8229),2,0),"")} -> 25634 | L16: {=IFERROR(VLOOKUP(L$3&$A6&$A9,IF({1,0},业绩报告!$A$2:$A$8229&业绩报告!$B$2:$B$8229&业绩报告!$C$2:$C$8229,业绩报告!$M$2:$M$8229),2,0),"")} -> 29860 | M16: {=IFERROR(VLOOKUP(M$3&$A6&$A9,IF({1,0},业绩报告!$A$2:$A$8229&业绩报告!$B$2:$B$8229&业绩报告!$C$2:$C$8229,业绩报告!$M$2:$M$8229),2,0),"")} -> 25653 | N16: {=IFERROR(VLOOKUP(N$3&$A6&$A9,IF({1,0},业绩报告!$A$2:$A$8229&业绩报告!$B$2:$B$8229&业绩报告!$C$2:$C$8229,业绩报告!$M$2:$M$8229),2,0),"")} -> 30720 | O16: {=IFERROR(VLOOKUP(O$3&$A6&$A9,IF({1,0},业绩报告!$A$2:$A$8229&业绩报告!$B$2:$B$8229&业绩报告!$C$2:$C$8229,业绩报告!$M$2:$M$8229),2,0),"")} -> 36802 | P16: {=IFERROR(VLOOKUP(P$3&$A6&$A9,IF({1,0},业绩报告!$A$2:$A$8229&业绩报告!$B$2:$B$8229&业绩报告!$C$2:$C$8229,业绩报告!$M$2:$M$8229),2,0),"")} -> 36727 | Q16: {=IFERROR(VLOOKUP(Q$3&$A6&$A9,IF({1,0},业绩报告!$A$2:$A$8229&业绩报告!$B$2:$B$8229&业绩报告!$C$2:$C$8229,业绩报告!$M$2:$M$8229),2,0),"")} -> 37166 | R16: =AVERAGE(K16:Q16) -> 25643.5
B17: 小类 | C17: {=IFERROR(VLOOKUP(C$3&$A6&$A9,IF({1,0},业绩报告!$A$2:$A$8229&业绩报告!$B$2:$B$8229&业绩报告!$C$2:$C$8229,业绩报告!$N$2:$N$8229),2,0),"")} -> Bathroom Countertop Soap Dispensers | D17: {=IFERROR(VLOOKUP(D$3&$A6&$A9,IF({1,0},业绩报告!$A$2:$A$8229&业绩报告!$B$2:$B$8229&业绩报告!$C$2:$C$8229,业绩报告!$N$2:$N$8229),2,0),"")} -> Bathroom Countertop Soap Dispensers | E17: {=IFERROR(VLOOKUP(E$3&$A6&$A9,IF({1,0},业绩报告!$A$2:$A$8229&业绩报告!$B$2:$B$8229&业绩报告!$C$2:$C$8229,业绩报告!$N$2:$N$8229),2,0),"")} -> Bathroom Countertop Soap Dispensers | F17: {=IFERROR(VLOOKUP(F$3&$A6&$A9,IF({1,0},业绩报告!$A$2:$A$8229&业绩报告!$B$2:$B$8229&业绩报告!$C$2:$C$8229,业绩报告!$N$2:$N$8229),2,0),"")} -> Bathroom Countertop Soap Dispensers | G17: {=IFERROR(VLOOKUP(G$3&$A6&$A9,IF({1,0},业绩报告!$A$2:$A$8229&业绩报告!$B$2:$B$8229&业绩报告!$C$2:$C$8229,业绩报告!$N$2:$N$8229),2,0),"")} -> Bathroom Countertop Soap Dispensers | H17: {=IFERROR(VLOOKUP(H$3&$A6&$A9,IF({1,0},业绩报告!$A$2:$A$8229&业绩报告!$B$2:$B$8229&业绩报告!$C$2:$C$8229,业绩报告!$N$2:$N$8229),2,0),"")} -> Bathroom Countertop Soap Dispensers | I17: {=IFERROR(VLOOKUP(I$3&$A6&$A9,IF({1,0},业绩报告!$A$2:$A$8229&业绩报告!$B$2:$B$8229&业绩报告!$C$2:$C$8229,业绩报告!$N$2:$N$8229),2,0),"")} -> Bathroom Countertop Soap Dispensers | K17: {=IFERROR(VLOOKUP(K$3&$A6&$A9,IF({1,0},业绩报告!$A$2:$A$8229&业绩报告!$B$2:$B$8229&业绩报告!$C$2:$C$8229,业绩报告!$N$2:$N$8229),2,0),"")} -> Bathroom Countertop Soap Dispensers | L17: {=IFERROR(VLOOKUP(L$3&$A6&$A9,IF({1,0},业绩报告!$A$2:$A$8229&业绩报告!$B$2:$B$8229&业绩报告!$C$2:$C$8229,业绩报告!$N$2:$N$8229),2,0),"")} -> Bathroom Countertop Soap Dispensers | M17: {=IFERROR(VLOOKUP(M$3&$A6&$A9,IF({1,0},业绩报告!$A$2:$A$8229&业绩报告!$B$2:$B$8229&业绩报告!$C$2:$C$8229,业绩报告!$N$2:$N$8229),2,0),"")} -> Bathroom Countertop Soap Dispensers | N17: {=IFERROR(VLOOKUP(N$3&$A6&$A9,IF({1,0},业绩报告!$A$2:$A$8229&业绩报告!$B$2:$B$8229&业绩报告!$C$2:$C$8229,业绩报告!$N$2:$N$8229),2,0),"")} -> Bathroom Countertop Soap Dispensers | O17: {=IFERROR(VLOOKUP(O$3&$A6&$A9,IF({1,0},业绩报告!$A$2:$A$8229&业绩报告!$B$2:$B$8229&业绩报告!$C$2:$C$8229,业绩报告!$N$2:$N$8229),2,0),"")} -> Bathroom Countertop Soap Dispensers | P17: {=IFERROR(VLOOKUP(P$3&$A6&$A9,IF({1,0},业绩报告!$A$2:$A$8229&业绩报告!$B$2:$B$8229&业绩报告!$C$2:$C$8229,业绩报告!$N$2:$N$8229),2,0),"")} -> Bathroom Countertop Soap Dispensers | Q17: {=IFERROR(VLOOKUP(Q$3&$A6&$A9,IF({1,0},业绩报告!$A$2:$A$8229&业绩报告!$B$2:$B$8229&业绩报告!$C$2:$C$8229,业绩报告!$N$2:$N$8229),2,0),"")} -> Bathroom Countertop Soap Dispensers
B18: 小类排名 | C18: {=IFERROR(VLOOKUP(C$3&$A6&$A9,IF({1,0},业绩报告!$A$2:$A$8229&业绩报告!$B$2:$B$8229&业绩报告!$C$2:$C$8229,业绩报告!$O$2:$O$8229),2,0),"")} -> 67 | D18: {=IFERROR(VLOOKUP(D$3&$A6&$A9,IF({1,0},业绩报告!$A$2:$A$8229&业绩报告!$B$2:$B$8229&业绩报告!$C$2:$C$8229,业绩报告!$O$2:$O$8229),2,0),"")} -> 80 | E18: {=IFERROR(VLOOKUP(E$3&$A6&$A9,IF({1,0},业绩报告!$A$2:$A$8229&业绩报告!$B$2:$B$8229&业绩报告!$C$2:$C$8229,业绩报告!$O$2:$O$8229),2,0),"")} -> 98 | F18: {=IFERROR(VLOOKUP(F$3&$A6&$A9,IF({1,0},业绩报告!$A$2:$A$8229&业绩报告!$B$2:$B$8229&业绩报告!$C$2:$C$8229,业绩报告!$O$2:$O$8229),2,0),"")} -> 99 | G18: {=IFERROR(VLOOKUP(G$3&$A6&$A9,IF({1,0},业绩报告!$A$2:$A$8229&业绩报告!$B$2:$B$8229&业绩报告!$C$2:$C$8229,业绩报告!$O$2:$O$8229),2,0),"")} -> 76 | H18: {=IFERROR(VLOOKUP(H$3&$A6&$A9,IF({1,0},业绩报告!$A$2:$A$8229&业绩报告!$B$2:$B$8229&业绩报告!$C$2:$C$8229,业绩报告!$O$2:$O$8229),2,0),"")} -> 81 | I18: {=IFERROR(VLOOKUP(I$3&$A6&$A9,IF({1,0},业绩报告!$A$2:$A$8229&业绩报告!$B$2:$B$8229&业绩报告!$C$2:$C$8229,业绩报告!$O$2:$O$8229),2,0),"")} -> 76 | J18: =AVERAGE(C18:I18) -> 82.428571 | K18: {=IFERROR(VLOOKUP(K$3&$A6&$A9,IF({1,0},业绩报告!$A$2:$A$8229&业绩报告!$B$2:$B$8229&业绩报告!$C$2:$C$8229,业绩报告!$O$2:$O$8229),2,0),"")} -> 77 | L18: {=IFERROR(VLOOKUP(L$3&$A6&$A9,IF({1,0},业绩报告!$A$2:$A$8229&业绩报告!$B$2:$B$8229&业绩报告!$C$2:$C$8229,业绩报告!$O$2:$O$8229),2,0),"")} -> 82 | M18: {=IFERROR(VLOOKUP(M$3&$A6&$A9,IF({1,0},业绩报告!$A$2:$A$8229&业绩报告!$B$2:$B$8229&业绩报告!$C$2:$C$8229,业绩报告!$O$2:$O$8229),2,0),"")} -> 73 | N18: {=IFERROR(VLOOKUP(N$3&$A6&$A9,IF({1,0},业绩报告!$A$2:$A$8229&业绩报告!$B$2:$B$8229&业绩报告!$C$2:$C$8229,业绩报告!$O$2:$O$8229),2,0),"")} -> 83 | O18: {=IFERROR(VLOOKUP(O$3&$A6&$A9,IF({1,0},业绩报告!$A$2:$A$8229&业绩报告!$B$2:$B$8229&业绩报告!$C$2:$C$8229,业绩报告!$O$2:$O$8229),2,0),"")} -> 97 | P18: {=IFERROR(VLOOKUP(P$3&$A6&$A9,IF({1,0},业绩报告!$A$2:$A$8229&业绩报告!$B$2:$B$8229&业绩报告!$C$2:$C$8229,业绩报告!$O$2:$O$8229),2,0),"")} -> 102 | Q18: {=IFERROR(VLOOKUP(Q$3&$A6&$A9,IF({1,0},业绩报告!$A$2:$A$8229&业绩报告!$B$2:$B$8229&业绩报告!$C$2:$C$8229,业绩报告!$O$2:$O$8229),2,0),"")} -> 110
B19: 关键词1 | C19: {=IFERROR(VLOOKUP(C$3&$A6&$A9,IF({1,0},业绩报告!$A$2:$A$8229&业绩报告!$B$2:$B$8229&业绩报告!$C$2:$C$8229,业绩报告!$P$2:$P$8229),2,0),"")} -> 0 | D19: {=IFERROR(VLOOKUP(D$3&$A6&$A9,IF({1,0},业绩报告!$A$2:$A$8229&业绩报告!$B$2:$B$8229&业绩报告!$C$2:$C$8229,业绩报告!$P$2:$P$8229),2,0),"")} -> 0 | E19: {=IFERROR(VLOOKUP(E$3&$A6&$A9,IF({1,0},业绩报告!$A$2:$A$8229&业绩报告!$B$2:$B$8229&业绩报告!$C$2:$C$8229,业绩报告!$P$2:$P$8229),2,0),"")} -> 0 | F19: {=IFERROR(VLOOKUP(F$3&$A6&$A9,IF({1,0},业绩报告!$A$2:$A$8229&业绩报告!$B$2:$B$8229&业绩报告!$C$2:$C$8229,业绩报告!$P$2:$P$8229),2,0),"")} -> 0 | G19: {=IFERROR(VLOOKUP(G$3&$A6&$A9,IF({1,0},业绩报告!$A$2:$A$8229&业绩报告!$B$2:$B$8229&业绩报告!$C$2:$C$8229,业绩报告!$P$2:$P$8229),2,0),"")} -> 0 | H19: {=IFERROR(VLOOKUP(H$3&$A6&$A9,IF({1,0},业绩报告!$A$2:$A$8229&业绩报告!$B$2:$B$8229&业绩报告!$C$2:$C$8229,业绩报告!$P$2:$P$8229),2,0),"")} -> 0 | I19: {=IFERROR(VLOOKUP(I$3&$A6&$A9,IF({1,0},业绩报告!$A$2:$A$8229&业绩报告!$B$2:$B$8229&业绩报告!$C$2:$C$8229,业绩报告!$P$2:$P$8229),2,0),"")} -> 0 | K19: {=IFERROR(VLOOKUP(K$3&$A6&$A9,IF({1,0},业绩报告!$A$2:$A$8229&业绩报告!$B$2:$B$8229&业绩报告!$C$2:$C$8229,业绩报告!$P$2:$P$8229),2,0),"")} -> 0 | L19: {=IFERROR(VLOOKUP(L$3&$A6&$A9,IF({1,0},业绩报告!$A$2:$A$8229&业绩报告!$B$2:$B$8229&业绩报告!$C$2:$C$8229,业绩报告!$P$2:$P$8229),2,0),"")} -> 0 | M19: {=IFERROR(VLOOKUP(M$3&$A6&$A9,IF({1,0},业绩报告!$A$2:$A$8229&业绩报告!$B$2:$B$8229&业绩报告!$C$2:$C$8229,业绩报告!$P$2:$P$8229),2,0),"")} -> 0 | N19: {=IFERROR(VLOOKUP(N$3&$A6&$A9,IF({1,0},业绩报告!$A$2:$A$8229&业绩报告!$B$2:$B$8229&业绩报告!$C$2:$C$8229,业绩报告!$P$2:$P$8229),2,0),"")} -> 0 | O19: {=IFERROR(VLOOKUP(O$3&$A6&$A9,IF({1,0},业绩报告!$A$2:$A$8229&业绩报告!$B$2:$B$8229&业绩报告!$C$2:$C$8229,业绩报告!$P$2:$P$8229),2,0),"")} -> 0 | P19: {=IFERROR(VLOOKUP(P$3&$A6&$A9,IF({1,0},业绩报告!$A$2:$A$8229&业绩报告!$B$2:$B$8229&业绩报告!$C$2:$C$8229,业绩报告!$P$2:$P$8229),2,0),"")} -> 0 | Q19: {=IFERROR(VLOOKUP(Q$3&$A6&$A9,IF({1,0},业绩报告!$A$2:$A$8229&业绩报告!$B$2:$B$8229&业绩报告!$C$2:$C$8229,业绩报告!$P$2:$P$8229),2,0),"")} -> 0
B20: 自然位1 | C20: {=IFERROR(VLOOKUP(C$3&$A6&$A9,IF({1,0},业绩报告!$A$2:$A$8229&业绩报告!$B$2:$B$8229&业绩报告!$C$2:$C$8229,业绩报告!$Q$2:$Q$8229),2,0),"")} -> 0 | D20: {=IFERROR(VLOOKUP(D$3&$A6&$A9,IF({1,0},业绩报告!$A$2:$A$8229&业绩报告!$B$2:$B$8229&业绩报告!$C$2:$C$8229,业绩报告!$Q$2:$Q$8229),2,0),"")} -> 0 | E20: {=IFERROR(VLOOKUP(E$3&$A6&$A9,IF({1,0},业绩报告!$A$2:$A$8229&业绩报告!$B$2:$B$8229&业绩报告!$C$2:$C$8229,业绩报告!$Q$2:$Q$8229),2,0),"")} -> 0 | F20: {=IFERROR(VLOOKUP(F$3&$A6&$A9,IF({1,0},业绩报告!$A$2:$A$8229&业绩报告!$B$2:$B$8229&业绩报告!$C$2:$C$8229,业绩报告!$Q$2:$Q$8229),2,0),"")} -> 0 | G20: {=IFERROR(VLOOKUP(G$3&$A6&$A9,IF({1,0},业绩报告!$A$2:$A$8229&业绩报告!$B$2:$B$8229&业绩报告!$C$2:$C$8229,业绩报告!$Q$2:$Q$8229),2,0),"")} -> 0 | H20: {=IFERROR(VLOOKUP(H$3&$A6&$A9,IF({1,0},业绩报告!$A$2:$A$8229&业绩报告!$B$2:$B$8229&业绩报告!$C$2:$C$8229,业绩报告!$Q$2:$Q$8229),2,0),"")} -> 0 | I20: {=IFERROR(VLOOKUP(I$3&$A6&$A9,IF({1,0},业绩报告!$A$2:$A$8229&业绩报告!$B$2:$B$8229&业绩报告!$C$2:$C$8229,业绩报告!$Q$2:$Q$8229),2,0),"")} -> 0 | K20: {=IFERROR(VLOOKUP(K$3&$A6&$A9,IF({1,0},业绩报告!$A$2:$A$8229&业绩报告!$B$2:$B$8229&业绩报告!$C$2:$C$8229,业绩报告!$Q$2:$Q$8229),2,0),"")} -> 0 | L20: {=IFERROR(VLOOKUP(L$3&$A6&$A9,IF({1,0},业绩报告!$A$2:$A$8229&业绩报告!$B$2:$B$8229&业绩报告!$C$2:$C$8229,业绩报告!$Q$2:$Q$8229),2,0),"")} -> 0 | M20: {=IFERROR(VLOOKUP(M$3&$A6&$A9,IF({1,0},业绩报告!$A$2:$A$8229&业绩报告!$B$2:$B$8229&业绩报告!$C$2:$C$8229,业绩报告!$Q$2:$Q$8229),2,0),"")} -> 0 | N20: {=IFERROR(VLOOKUP(N$3&$A6&$A9,IF({1,0},业绩报告!$A$2:$A$8229&业绩报告!$B$2:$B$8229&业绩报告!$C$2:$C$8229,业绩报告!$Q$2:$Q$8229),2,0),"")} -> 0 | O20: {=IFERROR(VLOOKUP(O$3&$A6&$A9,IF({1,0},业绩报告!$A$2:$A$8229&业绩报告!$B$2:$B$8229&业绩报告!$C$2:$C$8229,业绩报告!$Q$2:$Q$8229),2,0),"")} -> 0 | P20: {=IFERROR(VLOOKUP(P$3&$A6&$A9,IF({1,0},业绩报告!$A$2:$A$8229&业绩报告!$B$2:$B$8229&业绩报告!$C$2:$C$8229,业绩报告!$Q$2:$Q$8229),2,0),"")} -> 0 | Q20: {=IFERROR(VLOOKUP(Q$3&$A6&$A9,IF({1,0},业绩报告!$A$2:$A$8229&业绩报告!$B$2:$B$8229&业绩报告!$C$2:$C$8229,业绩报告!$Q$2:$Q$8229),2,0),"")} -> 0
B21: 广告位1 | C21: {=IFERROR(VLOOKUP(C$3&$A6&$A9,IF({1,0},业绩报告!$A$2:$A$8229&业绩报告!$B$2:$B$8229&业绩报告!$C$2:$C$8229,业绩报告!$R$2:$R$8229),2,0),"")} -> 0 | D21: {=IFERROR(VLOOKUP(D$3&$A6&$A9,IF({1,0},业绩报告!$A$2:$A$8229&业绩报告!$B$2:$B$8229&业绩报告!$C$2:$C$8229,业绩报告!$R$2:$R$8229),2,0),"")} -> 0 | E21: {=IFERROR(VLOOKUP(E$3&$A6&$A9,IF({1,0},业绩报告!$A$2:$A$8229&业绩报告!$B$2:$B$8229&业绩报告!$C$2:$C$8229,业绩报告!$R$2:$R$8229),2,0),"")} -> 0 | F21: {=IFERROR(VLOOKUP(F$3&$A6&$A9,IF({1,0},业绩报告!$A$2:$A$8229&业绩报告!$B$2:$B$8229&业绩报告!$C$2:$C$8229,业绩报告!$R$2:$R$8229),2,0),"")} -> 0 | G21: {=IFERROR(VLOOKUP(G$3&$A6&$A9,IF({1,0},业绩报告!$A$2:$A$8229&业绩报告!$B$2:$B$8229&业绩报告!$C$2:$C$8229,业绩报告!$R$2:$R$8229),2,0),"")} -> 0 | H21: {=IFERROR(VLOOKUP(H$3&$A6&$A9,IF({1,0},业绩报告!$A$2:$A$8229&业绩报告!$B$2:$B$8229&业绩报告!$C$2:$C$8229,业绩报告!$R$2:$R$8229),2,0),"")} -> 0 | I21: {=IFERROR(VLOOKUP(I$3&$A6&$A9,IF({1,0},业绩报告!$A$2:$A$8229&业绩报告!$B$2:$B$8229&业绩报告!$C$2:$C$8229,业绩报告!$R$2:$R$8229),2,0),"")} -> 0 | K21: {=IFERROR(VLOOKUP(K$3&$A6&$A9,IF({1,0},业绩报告!$A$2:$A$8229&业绩报告!$B$2:$B$8229&业绩报告!$C$2:$C$8229,业绩报告!$R$2:$R$8229),2,0),"")} -> 0 | L21: {=IFERROR(VLOOKUP(L$3&$A6&$A9,IF({1,0},业绩报告!$A$2:$A$8229&业绩报告!$B$2:$B$8229&业绩报告!$C$2:$C$8229,业绩报告!$R$2:$R$8229),2,0),"")} -> 0 | M21: {=IFERROR(VLOOKUP(M$3&$A6&$A9,IF({1,0},业绩报告!$A$2:$A$8229&业绩报告!$B$2:$B$8229&业绩报告!$C$2:$C$8229,业绩报告!$R$2:$R$8229),2,0),"")} -> 0 | N21: {=IFERROR(VLOOKUP(N$3&$A6&$A9,IF({1,0},业绩报告!$A$2:$A$8229&业绩报告!$B$2:$B$8229&业绩报告!$C$2:$C$8229,业绩报告!$R$2:$R$8229),2,0),"")} -> 0 | O21: {=IFERROR(VLOOKUP(O$3&$A6&$A9,IF({1,0},业绩报告!$A$2:$A$8229&业绩报告!$B$2:$B$8229&业绩报告!$C$2:$C$8229,业绩报告!$R$2:$R$8229),2,0),"")} -> 0 | P21: {=IFERROR(VLOOKUP(P$3&$A6&$A9,IF({1,0},业绩报告!$A$2:$A$8229&业绩报告!$B$2:$B$8229&业绩报告!$C$2:$C$8229,业绩报告!$R$2:$R$8229),2,0),"")} -> 0 | Q21: {=IFERROR(VLOOKUP(Q$3&$A6&$A9,IF({1,0},业绩报告!$A$2:$A$8229&业绩报告!$B$2:$B$8229&业绩报告!$C$2:$C$8229,业绩报告!$R$2:$R$8229),2,0),"")} -> 0
B22: 关键词2 | C22: {=IFERROR(VLOOKUP(C$3&$A6&$A9,IF({1,0},业绩报告!$A$2:$A$8229&业绩报告!$B$2:$B$8229&业绩报告!$C$2:$C$8229,业绩报告!$S$2:$S$8229),2,0),"")} -> 0 | D22: {=IFERROR(VLOOKUP(D$3&$A6&$A9,IF({1,0},业绩报告!$A$2:$A$8229&业绩报告!$B$2:$B$8229&业绩报告!$C$2:$C$8229,业绩报告!$S$2:$S$8229),2,0),"")} -> 0 | E22: {=IFERROR(VLOOKUP(E$3&$A6&$A9,IF({1,0},业绩报告!$A$2:$A$8229&业绩报告!$B$2:$B$8229&业绩报告!$C$2:$C$8229,业绩报告!$S$2:$S$8229),2,0),"")} -> 0 | F22: {=IFERROR(VLOOKUP(F$3&$A6&$A9,IF({1,0},业绩报告!$A$2:$A$8229&业绩报告!$B$2:$B$8229&业绩报告!$C$2:$C$8229,业绩报告!$S$2:$S$8229),2,0),"")} -> 0 | G22: {=IFERROR(VLOOKUP(G$3&$A6&$A9,IF({1,0},业绩报告!$A$2:$A$8229&业绩报告!$B$2:$B$8229&业绩报告!$C$2:$C$8229,业绩报告!$S$2:$S$8229),2,0),"")} -> 0 | H22: {=IFERROR(VLOOKUP(H$3&$A6&$A9,IF({1,0},业绩报告!$A$2:$A$8229&业绩报告!$B$2:$B$8229&业绩报告!$C$2:$C$8229,业绩报告!$S$2:$S$8229),2,0),"")} -> 0 | I22: {=IFERROR(VLOOKUP(I$3&$A6&$A9,IF({1,0},业绩报告!$A$2:$A$8229&业绩报告!$B$2:$B$8229&业绩报告!$C$2:$C$8229,业绩报告!$S$2:$S$8229),2,0),"")} -> 0 | K22: {=IFERROR(VLOOKUP(K$3&$A6&$A9,IF({1,0},业绩报告!$A$2:$A$8229&业绩报告!$B$2:$B$8229&业绩报告!$C$2:$C$8229,业绩报告!$S$2:$S$8229),2,0),"")} -> 0 | L22: {=IFERROR(VLOOKUP(L$3&$A6&$A9,IF({1,0},业绩报告!$A$2:$A$8229&业绩报告!$B$2:$B$8229&业绩报告!$C$2:$C$8229,业绩报告!$S$2:$S$8229),2,0),"")} -> 0 | M22: {=IFERROR(VLOOKUP(M$3&$A6&$A9,IF({1,0},业绩报告!$A$2:$A$8229&业绩报告!$B$2:$B$8229&业绩报告!$C$2:$C$8229,业绩报告!$S$2:$S$8229),2,0),"")} -> 0 | N22: {=IFERROR(VLOOKUP(N$3&$A6&$A9,IF({1,0},业绩报告!$A$2:$A$8229&业绩报告!$B$2:$B$8229&业绩报告!$C$2:$C$8229,业绩报告!$S$2:$S$8229),2,0),"")} -> 0 | O22: {=IFERROR(VLOOKUP(O$3&$A6&$A9,IF({1,0},业绩报告!$A$2:$A$8229&业绩报告!$B$2:$B$8229&业绩报告!$C$2:$C$8229,业绩报告!$S$2:$S$8229),2,0),"")} -> 0 | P22: {=IFERROR(VLOOKUP(P$3&$A6&$A9,IF({1,0},业绩报告!$A$2:$A$8229&业绩报告!$B$2:$B$8229&业绩报告!$C$2:$C$8229,业绩报告!$S$2:$S$8229),2,0),"")} -> 0 | Q22: {=IFERROR(VLOOKUP(Q$3&$A6&$A9,IF({1,0},业绩报告!$A$2:$A$8229&业绩报告!$B$2:$B$8229&业绩报告!$C$2:$C$8229,业绩报告!$S$2:$S$8229),2,0),"")} -> 0
B23: 自然位2 | C23: {=IFERROR(VLOOKUP(C$3&$A6&$A9,IF({1,0},业绩报告!$A$2:$A$8229&业绩报告!$B$2:$B$8229&业绩报告!$C$2:$C$8229,业绩报告!$T$2:$T$8229),2,0),"")} -> 0 | D23: {=IFERROR(VLOOKUP(D$3&$A6&$A9,IF({1,0},业绩报告!$A$2:$A$8229&业绩报告!$B$2:$B$8229&业绩报告!$C$2:$C$8229,业绩报告!$T$2:$T$8229),2,0),"")} -> 0 | E23: {=IFERROR(VLOOKUP(E$3&$A6&$A9,IF({1,0},业绩报告!$A$2:$A$8229&业绩报告!$B$2:$B$8229&业绩报告!$C$2:$C$8229,业绩报告!$T$2:$T$8229),2,0),"")} -> 0 | F23: {=IFERROR(VLOOKUP(F$3&$A6&$A9,IF({1,0},业绩报告!$A$2:$A$8229&业绩报告!$B$2:$B$8229&业绩报告!$C$2:$C$8229,业绩报告!$T$2:$T$8229),2,0),"")} -> 0 | G23: {=IFERROR(VLOOKUP(G$3&$A6&$A9,IF({1,0},业绩报告!$A$2:$A$8229&业绩报告!$B$2:$B$8229&业绩报告!$C$2:$C$8229,业绩报告!$T$2:$T$8229),2,0),"")} -> 0 | H23: {=IFERROR(VLOOKUP(H$3&$A6&$A9,IF({1,0},业绩报告!$A$2:$A$8229&业绩报告!$B$2:$B$8229&业绩报告!$C$2:$C$8229,业绩报告!$T$2:$T$8229),2,0),"")} -> 0 | I23: {=IFERROR(VLOOKUP(I$3&$A6&$A9,IF({1,0},业绩报告!$A$2:$A$8229&业绩报告!$B$2:$B$8229&业绩报告!$C$2:$C$8229,业绩报告!$T$2:$T$8229),2,0),"")} -> 0 | K23: {=IFERROR(VLOOKUP(K$3&$A6&$A9,IF({1,0},业绩报告!$A$2:$A$8229&业绩报告!$B$2:$B$8229&业绩报告!$C$2:$C$8229,业绩报告!$T$2:$T$8229),2,0),"")} -> 0 | L23: {=IFERROR(VLOOKUP(L$3&$A6&$A9,IF({1,0},业绩报告!$A$2:$A$8229&业绩报告!$B$2:$B$8229&业绩报告!$C$2:$C$8229,业绩报告!$T$2:$T$8229),2,0),"")} -> 0 | M23: {=IFERROR(VLOOKUP(M$3&$A6&$A9,IF({1,0},业绩报告!$A$2:$A$8229&业绩报告!$B$2:$B$8229&业绩报告!$C$2:$C$8229,业绩报告!$T$2:$T$8229),2,0),"")} -> 0 | N23: {=IFERROR(VLOOKUP(N$3&$A6&$A9,IF({1,0},业绩报告!$A$2:$A$8229&业绩报告!$B$2:$B$8229&业绩报告!$C$2:$C$8229,业绩报告!$T$2:$T$8229),2,0),"")} -> 0 | O23: {=IFERROR(VLOOKUP(O$3&$A6&$A9,IF({1,0},业绩报告!$A$2:$A$8229&业绩报告!$B$2:$B$8229&业绩报告!$C$2:$C$8229,业绩报告!$T$2:$T$8229),2,0),"")} -> 0 | P23: {=IFERROR(VLOOKUP(P$3&$A6&$A9,IF({1,0},业绩报告!$A$2:$A$8229&业绩报告!$B$2:$B$8229&业绩报告!$C$2:$C$8229,业绩报告!$T$2:$T$8229),2,0),"")} -> 0 | Q23: {=IFERROR(VLOOKUP(Q$3&$A6&$A9,IF({1,0},业绩报告!$A$2:$A$8229&业绩报告!$B$2:$B$8229&业绩报告!$C$2:$C$8229,业绩报告!$T$2:$T$8229),2,0),"")} -> 0
B24: 广告位2 | C24: {=IFERROR(VLOOKUP(C$3&$A6&$A9,IF({1,0},业绩报告!$A$2:$A$8229&业绩报告!$B$2:$B$8229&业绩报告!$C$2:$C$8229,业绩报告!$U$2:$U$8229),2,0),"")} -> 0 | D24: {=IFERROR(VLOOKUP(D$3&$A6&$A9,IF({1,0},业绩报告!$A$2:$A$8229&业绩报告!$B$2:$B$8229&业绩报告!$C$2:$C$8229,业绩报告!$U$2:$U$8229),2,0),"")} -> 0 | E24: {=IFERROR(VLOOKUP(E$3&$A6&$A9,IF({1,0},业绩报告!$A$2:$A$8229&业绩报告!$B$2:$B$8229&业绩报告!$C$2:$C$8229,业绩报告!$U$2:$U$8229),2,0),"")} -> 0 | F24: {=IFERROR(VLOOKUP(F$3&$A6&$A9,IF({1,0},业绩报告!$A$2:$A$8229&业绩报告!$B$2:$B$8229&业绩报告!$C$2:$C$8229,业绩报告!$U$2:$U$8229),2,0),"")} -> 0 | G24: {=IFERROR(VLOOKUP(G$3&$A6&$A9,IF({1,0},业绩报告!$A$2:$A$8229&业绩报告!$B$2:$B$8229&业绩报告!$C$2:$C$8229,业绩报告!$U$2:$U$8229),2,0),"")} -> 0 | H24: {=IFERROR(VLOOKUP(H$3&$A6&$A9,IF({1,0},业绩报告!$A$2:$A$8229&业绩报告!$B$2:$B$8229&业绩报告!$C$2:$C$8229,业绩报告!$U$2:$U$8229),2,0),"")} -> 0 | I24: {=IFERROR(VLOOKUP(I$3&$A6&$A9,IF({1,0},业绩报告!$A$2:$A$8229&业绩报告!$B$2:$B$8229&业绩报告!$C$2:$C$8229,业绩报告!$U$2:$U$8229),2,0),"")} -> 0 | K24: {=IFERROR(VLOOKUP(K$3&$A6&$A9,IF({1,0},业绩报告!$A$2:$A$8229&业绩报告!$B$2:$B$8229&业绩报告!$C$2:$C$8229,业绩报告!$U$2:$U$8229),2,0),"")} -> 0 | L24: {=IFERROR(VLOOKUP(L$3&$A6&$A9,IF({1,0},业绩报告!$A$2:$A$8229&业绩报告!$B$2:$B$8229&业绩报告!$C$2:$C$8229,业绩报告!$U$2:$U$8229),2,0),"")} -> 0 | M24: {=IFERROR(VLOOKUP(M$3&$A6&$A9,IF({1,0},业绩报告!$A$2:$A$8229&业绩报告!$B$2:$B$8229&业绩报告!$C$2:$C$8229,业绩报告!$U$2:$U$8229),2,0),"")} -> 0 | N24: {=IFERROR(VLOOKUP(N$3&$A6&$A9,IF({1,0},业绩报告!$A$2:$A$8229&业绩报告!$B$2:$B$8229&业绩报告!$C$2:$C$8229,业绩报告!$U$2:$U$8229),2,0),"")} -> 0 | O24: {=IFERROR(VLOOKUP(O$3&$A6&$A9,IF({1,0},业绩报告!$A$2:$A$8229&业绩报告!$B$2:$B$8229&业绩报告!$C$2:$C$8229,业绩报告!$U$2:$U$8229),2,0),"")} -> 0 | P24: {=IFERROR(VLOOKUP(P$3&$A6&$A9,IF({1,0},业绩报告!$A$2:$A$8229&业绩报告!$B$2:$B$8229&业绩报告!$C$2:$C$8229,业绩报告!$U$2:$U$8229),2,0),"")} -> 0 | Q24: {=IFERROR(VLOOKUP(Q$3&$A6&$A9,IF({1,0},业绩报告!$A$2:$A$8229&业绩报告!$B$2:$B$8229&业绩报告!$C$2:$C$8229,业绩报告!$U$2:$U$8229),2,0),"")} -> 0
B25: 关键词3 | C25: {=IFERROR(VLOOKUP(C$3&$A6&$A9,IF({1,0},业绩报告!$A$2:$A$8229&业绩报告!$B$2:$B$8229&业绩报告!$C$2:$C$8229,业绩报告!$V$2:$V$8229),2,0),"")} -> 0 | D25: {=IFERROR(VLOOKUP(D$3&$A6&$A9,IF({1,0},业绩报告!$A$2:$A$8229&业绩报告!$B$2:$B$8229&业绩报告!$C$2:$C$8229,业绩报告!$V$2:$V$8229),2,0),"")} -> 0 | E25: {=IFERROR(VLOOKUP(E$3&$A6&$A9,IF({1,0},业绩报告!$A$2:$A$8229&业绩报告!$B$2:$B$8229&业绩报告!$C$2:$C$8229,业绩报告!$V$2:$V$8229),2,0),"")} -> 0 | F25: {=IFERROR(VLOOKUP(F$3&$A6&$A9,IF({1,0},业绩报告!$A$2:$A$8229&业绩报告!$B$2:$B$8229&业绩报告!$C$2:$C$8229,业绩报告!$V$2:$V$8229),2,0),"")} -> 0 | G25: {=IFERROR(VLOOKUP(G$3&$A6&$A9,IF({1,0},业绩报告!$A$2:$A$8229&业绩报告!$B$2:$B$8229&业绩报告!$C$2:$C$8229,业绩报告!$V$2:$V$8229),2,0),"")} -> 0 | H25: {=IFERROR(VLOOKUP(H$3&$A6&$A9,IF({1,0},业绩报告!$A$2:$A$8229&业绩报告!$B$2:$B$8229&业绩报告!$C$2:$C$8229,业绩报告!$V$2:$V$8229),2,0),"")} -> 0 | I25: {=IFERROR(VLOOKUP(I$3&$A6&$A9,IF({1,0},业绩报告!$A$2:$A$8229&业绩报告!$B$2:$B$8229&业绩报告!$C$2:$C$8229,业绩报告!$V$2:$V$8229),2,0),"")} -> 0 | K25: {=IFERROR(VLOOKUP(K$3&$A6&$A9,IF({1,0},业绩报告!$A$2:$A$8229&业绩报告!$B$2:$B$8229&业绩报告!$C$2:$C$8229,业绩报告!$V$2:$V$8229),2,0),"")} -> 0 | L25: {=IFERROR(VLOOKUP(L$3&$A6&$A9,IF({1,0},业绩报告!$A$2:$A$8229&业绩报告!$B$2:$B$8229&业绩报告!$C$2:$C$8229,业绩报告!$V$2:$V$8229),2,0),"")} -> 0 | M25: {=IFERROR(VLOOKUP(M$3&$A6&$A9,IF({1,0},业绩报告!$A$2:$A$8229&业绩报告!$B$2:$B$8229&业绩报告!$C$2:$C$8229,业绩报告!$V$2:$V$8229),2,0),"")} -> 0 | N25: {=IFERROR(VLOOKUP(N$3&$A6&$A9,IF({1,0},业绩报告!$A$2:$A$8229&业绩报告!$B$2:$B$8229&业绩报告!$C$2:$C$8229,业绩报告!$V$2:$V$8229),2,0),"")} -> 0 | O25: {=IFERROR(VLOOKUP(O$3&$A6&$A9,IF({1,0},业绩报告!$A$2:$A$8229&业绩报告!$B$2:$B$8229&业绩报告!$C$2:$C$8229,业绩报告!$V$2:$V$8229),2,0),"")} -> 0 | P25: {=IFERROR(VLOOKUP(P$3&$A6&$A9,IF({1,0},业绩报告!$A$2:$A$8229&业绩报告!$B$2:$B$8229&业绩报告!$C$2:$C$8229,业绩报告!$V$2:$V$8229),2,0),"")} -> 0 | Q25: {=IFERROR(VLOOKUP(Q$3&$A6&$A9,IF({1,0},业绩报告!$A$2:$A$8229&业绩报告!$B$2:$B$8229&业绩报告!$C$2:$C$8229,业绩报告!$V$2:$V$8229),2,0),"")} -> 0
B26: 自然位3 | C26: {=IFERROR(VLOOKUP(C$3&$A6&$A9,IF({1,0},业绩报告!$A$2:$A$8229&业绩报告!$B$2:$B$8229&业绩报告!$C$2:$C$8229,业绩报告!$W$2:$W$8229),2,0),"")} -> 0 | D26: {=IFERROR(VLOOKUP(D$3&$A6&$A9,IF({1,0},业绩报告!$A$2:$A$8229&业绩报告!$B$2:$B$8229&业绩报告!$C$2:$C$8229,业绩报告!$W$2:$W$8229),2,0),"")} -> 0 | E26: {=IFERROR(VLOOKUP(E$3&$A6&$A9,IF({1,0},业绩报告!$A$2:$A$8229&业绩报告!$B$2:$B$8229&业绩报告!$C$2:$C$8229,业绩报告!$W$2:$W$8229),2,0),"")} -> 0 | F26: {=IFERROR(VLOOKUP(F$3&$A6&$A9,IF({1,0},业绩报告!$A$2:$A$8229&业绩报告!$B$2:$B$8229&业绩报告!$C$2:$C$8229,业绩报告!$W$2:$W$8229),2,0),"")} -> 0 | G26: {=IFERROR(VLOOKUP(G$3&$A6&$A9,IF({1,0},业绩报告!$A$2:$A$8229&业绩报告!$B$2:$B$8229&业绩报告!$C$2:$C$8229,业绩报告!$W$2:$W$8229),2,0),"")} -> 0 | H26: {=IFERROR(VLOOKUP(H$3&$A6&$A9,IF({1,0},业绩报告!$A$2:$A$8229&业绩报告!$B$2:$B$8229&业绩报告!$C$2:$C$8229,业绩报告!$W$2:$W$8229),2,0),"")} -> 0 | I26: {=IFERROR(VLOOKUP(I$3&$A6&$A9,IF({1,0},业绩报告!$A$2:$A$8229&业绩报告!$B$2:$B$8229&业绩报告!$C$2:$C$8229,业绩报告!$W$2:$W$8229),2,0),"")} -> 0 | K26: {=IFERROR(VLOOKUP(K$3&$A6&$A9,IF({1,0},业绩报告!$A$2:$A$8229&业绩报告!$B$2:$B$8229&业绩报告!$C$2:$C$8229,业绩报告!$W$2:$W$8229),2,0),"")} -> 0 | L26: {=IFERROR(VLOOKUP(L$3&$A6&$A9,IF({1,0},业绩报告!$A$2:$A$8229&业绩报告!$B$2:$B$8229&业绩报告!$C$2:$C$8229,业绩报告!$W$2:$W$8229),2,0),"")} -> 0 | M26: {=IFERROR(VLOOKUP(M$3&$A6&$A9,IF({1,0},业绩报告!$A$2:$A$8229&业绩报告!$B$2:$B$8229&业绩报告!$C$2:$C$8229,业绩报告!$W$2:$W$8229),2,0),"")} -> 0 | N26: {=IFERROR(VLOOKUP(N$3&$A6&$A9,IF({1,0},业绩报告!$A$2:$A$8229&业绩报告!$B$2:$B$8229&业绩报告!$C$2:$C$8229,业绩报告!$W$2:$W$8229),2,0),"")} -> 0 | O26: {=IFERROR(VLOOKUP(O$3&$A6&$A9,IF({1,0},业绩报告!$A$2:$A$8229&业绩报告!$B$2:$B$8229&业绩报告!$C$2:$C$8229,业绩报告!$W$2:$W$8229),2,0),"")} -> 0 | P26: {=IFERROR(VLOOKUP(P$3&$A6&$A9,IF({1,0},业绩报告!$A$2:$A$8229&业绩报告!$B$2:$B$8229&业绩报告!$C$2:$C$8229,业绩报告!$W$2:$W$8229),2,0),"")} -> 0 | Q26: {=IFERROR(VLOOKUP(Q$3&$A6&$A9,IF({1,0},业绩报告!$A$2:$A$8229&业绩报告!$B$2:$B$8229&业绩报告!$C$2:$C$8229,业绩报告!$W$2:$W$8229),2,0),"")} -> 0
B27: 广告位3 | C27: {=IFERROR(VLOOKUP(C$3&$A6&$A9,IF({1,0},业绩报告!$A$2:$A$8229&业绩报告!$B$2:$B$8229&业绩报告!$C$2:$C$8229,业绩报告!$X$2:$X$8229),2,0),"")} -> 0 | D27: {=IFERROR(VLOOKUP(D$3&$A6&$A9,IF({1,0},业绩报告!$A$2:$A$8229&业绩报告!$B$2:$B$8229&业绩报告!$C$2:$C$8229,业绩报告!$X$2:$X$8229),2,0),"")} -> 0 | E27: {=IFERROR(VLOOKUP(E$3&$A6&$A9,IF({1,0},业绩报告!$A$2:$A$8229&业绩报告!$B$2:$B$8229&业绩报告!$C$2:$C$8229,业绩报告!$X$2:$X$8229),2,0),"")} -> 0 | F27: {=IFERROR(VLOOKUP(F$3&$A6&$A9,IF({1,0},业绩报告!$A$2:$A$8229&业绩报告!$B$2:$B$8229&业绩报告!$C$2:$C$8229,业绩报告!$X$2:$X$8229),2,0),"")} -> 0 | G27: {=IFERROR(VLOOKUP(G$3&$A6&$A9,IF({1,0},业绩报告!$A$2:$A$8229&业绩报告!$B$2:$B$8229&业绩报告!$C$2:$C$8229,业绩报告!$X$2:$X$8229),2,0),"")} -> 0 | H27: {=IFERROR(VLOOKUP(H$3&$A6&$A9,IF({1,0},业绩报告!$A$2:$A$8229&业绩报告!$B$2:$B$8229&业绩报告!$C$2:$C$8229,业绩报告!$X$2:$X$8229),2,0),"")} -> 0 | I27: {=IFERROR(VLOOKUP(I$3&$A6&$A9,IF({1,0},业绩报告!$A$2:$A$8229&业绩报告!$B$2:$B$8229&业绩报告!$C$2:$C$8229,业绩报告!$X$2:$X$8229),2,0),"")} -> 0 | K27: {=IFERROR(VLOOKUP(K$3&$A6&$A9,IF({1,0},业绩报告!$A$2:$A$8229&业绩报告!$B$2:$B$8229&业绩报告!$C$2:$C$8229,业绩报告!$X$2:$X$8229),2,0),"")} -> 0 | L27: {=IFERROR(VLOOKUP(L$3&$A6&$A9,IF({1,0},业绩报告!$A$2:$A$8229&业绩报告!$B$2:$B$8229&业绩报告!$C$2:$C$8229,业绩报告!$X$2:$X$8229),2,0),"")} -> 0 | M27: {=IFERROR(VLOOKUP(M$3&$A6&$A9,IF({1,0},业绩报告!$A$2:$A$8229&业绩报告!$B$2:$B$8229&业绩报告!$C$2:$C$8229,业绩报告!$X$2:$X$8229),2,0),"")} -> 0 | N27: {=IFERROR(VLOOKUP(N$3&$A6&$A9,IF({1,0},业绩报告!$A$2:$A$8229&业绩报告!$B$2:$B$8229&业绩报告!$C$2:$C$8229,业绩报告!$X$2:$X$8229),2,0),"")} -> 0 | O27: {=IFERROR(VLOOKUP(O$3&$A6&$A9,IF({1,0},业绩报告!$A$2:$A$8229&业绩报告!$B$2:$B$8229&业绩报告!$C$2:$C$8229,业绩报告!$X$2:$X$8229),2,0),"")} -> 0 | P27: {=IFERROR(VLOOKUP(P$3&$A6&$A9,IF({1,0},业绩报告!$A$2:$A$8229&业绩报告!$B$2:$B$8229&业绩报告!$C$2:$C$8229,业绩报告!$X$2:$X$8229),2,0),"")} -> 0 | Q27: {=IFERROR(VLOOKUP(Q$3&$A6&$A9,IF({1,0},业绩报告!$A$2:$A$8229&业绩报告!$B$2:$B$8229&业绩报告!$C$2:$C$8229,业绩报告!$X$2:$X$8229),2,0),"")} -> 0
B28: 关键词4 | C28: {=IFERROR(VLOOKUP(C$3&$A6&$A9,IF({1,0},业绩报告!$A$2:$A$8229&业绩报告!$B$2:$B$8229&业绩报告!$C$2:$C$8229,业绩报告!$Y$2:$Y$8229),2,0),"")} -> 0 | D28: {=IFERROR(VLOOKUP(D$3&$A6&$A9,IF({1,0},业绩报告!$A$2:$A$8229&业绩报告!$B$2:$B$8229&业绩报告!$C$2:$C$8229,业绩报告!$Y$2:$Y$8229),2,0),"")} -> 0 | E28: {=IFERROR(VLOOKUP(E$3&$A6&$A9,IF({1,0},业绩报告!$A$2:$A$8229&业绩报告!$B$2:$B$8229&业绩报告!$C$2:$C$8229,业绩报告!$Y$2:$Y$8229),2,0),"")} -> 0 | F28: {=IFERROR(VLOOKUP(F$3&$A6&$A9,IF({1,0},业绩报告!$A$2:$A$8229&业绩报告!$B$2:$B$8229&业绩报告!$C$2:$C$8229,业绩报告!$Y$2:$Y$8229),2,0),"")} -> 0 | G28: {=IFERROR(VLOOKUP(G$3&$A6&$A9,IF({1,0},业绩报告!$A$2:$A$8229&业绩报告!$B$2:$B$8229&业绩报告!$C$2:$C$8229,业绩报告!$Y$2:$Y$8229),2,0),"")} -> 0 | H28: {=IFERROR(VLOOKUP(H$3&$A6&$A9,IF({1,0},业绩报告!$A$2:$A$8229&业绩报告!$B$2:$B$8229&业绩报告!$C$2:$C$8229,业绩报告!$Y$2:$Y$8229),2,0),"")} -> 0 | I28: {=IFERROR(VLOOKUP(I$3&$A6&$A9,IF({1,0},业绩报告!$A$2:$A$8229&业绩报告!$B$2:$B$8229&业绩报告!$C$2:$C$8229,业绩报告!$Y$2:$Y$8229),2,0),"")} -> 0 | K28: {=IFERROR(VLOOKUP(K$3&$A6&$A9,IF({1,0},业绩报告!$A$2:$A$8229&业绩报告!$B$2:$B$8229&业绩报告!$C$2:$C$8229,业绩报告!$Y$2:$Y$8229),2,0),"")} -> 0 | L28: {=IFERROR(VLOOKUP(L$3&$A6&$A9,IF({1,0},业绩报告!$A$2:$A$8229&业绩报告!$B$2:$B$8229&业绩报告!$C$2:$C$8229,业绩报告!$Y$2:$Y$8229),2,0),"")} -> 0 | M28: {=IFERROR(VLOOKUP(M$3&$A6&$A9,IF({1,0},业绩报告!$A$2:$A$8229&业绩报告!$B$2:$B$8229&业绩报告!$C$2:$C$8229,业绩报告!$Y$2:$Y$8229),2,0),"")} -> 0 | N28: {=IFERROR(VLOOKUP(N$3&$A6&$A9,IF({1,0},业绩报告!$A$2:$A$8229&业绩报告!$B$2:$B$8229&业绩报告!$C$2:$C$8229,业绩报告!$Y$2:$Y$8229),2,0),"")} -> 0 | O28: {=IFERROR(VLOOKUP(O$3&$A6&$A9,IF({1,0},业绩报告!$A$2:$A$8229&业绩报告!$B$2:$B$8229&业绩报告!$C$2:$C$8229,业绩报告!$Y$2:$Y$8229),2,0),"")} -> 0 | P28: {=IFERROR(VLOOKUP(P$3&$A6&$A9,IF({1,0},业绩报告!$A$2:$A$8229&业绩报告!$B$2:$B$8229&业绩报告!$C$2:$C$8229,业绩报告!$Y$2:$Y$8229),2,0),"")} -> 0 | Q28: {=IFERROR(VLOOKUP(Q$3&$A6&$A9,IF({1,0},业绩报告!$A$2:$A$8229&业绩报告!$B$2:$B$8229&业绩报告!$C$2:$C$8229,业绩报告!$Y$2:$Y$8229),2,0),"")} -> 0
B29: 自然位4 | C29: {=IFERROR(VLOOKUP(C$3&$A6&$A9,IF({1,0},业绩报告!$A$2:$A$8229&业绩报告!$B$2:$B$8229&业绩报告!$C$2:$C$8229,业绩报告!$Z$2:$Z$8229),2,0),"")} -> 0 | D29: {=IFERROR(VLOOKUP(D$3&$A6&$A9,IF({1,0},业绩报告!$A$2:$A$8229&业绩报告!$B$2:$B$8229&业绩报告!$C$2:$C$8229,业绩报告!$Z$2:$Z$8229),2,0),"")} -> 0 | E29: {=IFERROR(VLOOKUP(E$3&$A6&$A9,IF({1,0},业绩报告!$A$2:$A$8229&业绩报告!$B$2:$B$8229&业绩报告!$C$2:$C$8229,业绩报告!$Z$2:$Z$8229),2,0),"")} -> 0 | F29: {=IFERROR(VLOOKUP(F$3&$A6&$A9,IF({1,0},业绩报告!$A$2:$A$8229&业绩报告!$B$2:$B$8229&业绩报告!$C$2:$C$8229,业绩报告!$Z$2:$Z$8229),2,0),"")} -> 0 | G29: {=IFERROR(VLOOKUP(G$3&$A6&$A9,IF({1,0},业绩报告!$A$2:$A$8229&业绩报告!$B$2:$B$8229&业绩报告!$C$2:$C$8229,业绩报告!$Z$2:$Z$8229),2,0),"")} -> 0 | H29: {=IFERROR(VLOOKUP(H$3&$A6&$A9,IF({1,0},业绩报告!$A$2:$A$8229&业绩报告!$B$2:$B$8229&业绩报告!$C$2:$C$8229,业绩报告!$Z$2:$Z$8229),2,0),"")} -> 0 | I29: {=IFERROR(VLOOKUP(I$3&$A6&$A9,IF({1,0},业绩报告!$A$2:$A$8229&业绩报告!$B$2:$B$8229&业绩报告!$C$2:$C$8229,业绩报告!$Z$2:$Z$8229),2,0),"")} -> 0 | K29: {=IFERROR(VLOOKUP(K$3&$A6&$A9,IF({1,0},业绩报告!$A$2:$A$8229&业绩报告!$B$2:$B$8229&业绩报告!$C$2:$C$8229,业绩报告!$Z$2:$Z$8229),2,0),"")} -> 0 | L29: {=IFERROR(VLOOKUP(L$3&$A6&$A9,IF({1,0},业绩报告!$A$2:$A$8229&业绩报告!$B$2:$B$8229&业绩报告!$C$2:$C$8229,业绩报告!$Z$2:$Z$8229),2,0),"")} -> 0 | M29: {=IFERROR(VLOOKUP(M$3&$A6&$A9,IF({1,0},业绩报告!$A$2:$A$8229&业绩报告!$B$2:$B$8229&业绩报告!$C$2:$C$8229,业绩报告!$Z$2:$Z$8229),2,0),"")} -> 0 | N29: {=IFERROR(VLOOKUP(N$3&$A6&$A9,IF({1,0},业绩报告!$A$2:$A$8229&业绩报告!$B$2:$B$8229&业绩报告!$C$2:$C$8229,业绩报告!$Z$2:$Z$8229),2,0),"")} -> 0 | O29: {=IFERROR(VLOOKUP(O$3&$A6&$A9,IF({1,0},业绩报告!$A$2:$A$8229&业绩报告!$B$2:$B$8229&业绩报告!$C$2:$C$8229,业绩报告!$Z$2:$Z$8229),2,0),"")} -> 0 | P29: {=IFERROR(VLOOKUP(P$3&$A6&$A9,IF({1,0},业绩报告!$A$2:$A$8229&业绩报告!$B$2:$B$8229&业绩报告!$C$2:$C$8229,业绩报告!$Z$2:$Z$8229),2,0),"")} -> 0 | Q29: {=IFERROR(VLOOKUP(Q$3&$A6&$A9,IF({1,0},业绩报告!$A$2:$A$8229&业绩报告!$B$2:$B$8229&业绩报告!$C$2:$C$8229,业绩报告!$Z$2:$Z$8229),2,0),"")} -> 0
B30: 广告位4 | C30: {=IFERROR(VLOOKUP(C$3&$A6&$A9,IF({1,0},业绩报告!$A$2:$A$8229&业绩报告!$B$2:$B$8229&业绩报告!$C$2:$C$8229,业绩报告!$AA$2:$AA$8229),2,0),"")} -> 0 | D30: {=IFERROR(VLOOKUP(D$3&$A6&$A9,IF({1,0},业绩报告!$A$2:$A$8229&业绩报告!$B$2:$B$8229&业绩报告!$C$2:$C$8229,业绩报告!$AA$2:$AA$8229),2,0),"")} -> 0 | E30: {=IFERROR(VLOOKUP(E$3&$A6&$A9,IF({1,0},业绩报告!$A$2:$A$8229&业绩报告!$B$2:$B$8229&业绩报告!$C$2:$C$8229,业绩报告!$AA$2:$AA$8229),2,0),"")} -> 0 | F30: {=IFERROR(VLOOKUP(F$3&$A6&$A9,IF({1,0},业绩报告!$A$2:$A$8229&业绩报告!$B$2:$B$8229&业绩报告!$C$2:$C$8229,业绩报告!$AA$2:$AA$8229),2,0),"")} -> 0 | G30: {=IFERROR(VLOOKUP(G$3&$A6&$A9,IF({1,0},业绩报告!$A$2:$A$8229&业绩报告!$B$2:$B$8229&业绩报告!$C$2:$C$8229,业绩报告!$AA$2:$AA$8229),2,0),"")} -> 0 | H30: {=IFERROR(VLOOKUP(H$3&$A6&$A9,IF({1,0},业绩报告!$A$2:$A$8229&业绩报告!$B$2:$B$8229&业绩报告!$C$2:$C$8229,业绩报告!$AA$2:$AA$8229),2,0),"")} -> 0 | I30: {=IFERROR(VLOOKUP(I$3&$A6&$A9,IF({1,0},业绩报告!$A$2:$A$8229&业绩报告!$B$2:$B$8229&业绩报告!$C$2:$C$8229,业绩报告!$AA$2:$AA$8229),2,0),"")} -> 0 | K30: {=IFERROR(VLOOKUP(K$3&$A6&$A9,IF({1,0},业绩报告!$A$2:$A$8229&业绩报告!$B$2:$B$8229&业绩报告!$C$2:$C$8229,业绩报告!$AA$2:$AA$8229),2,0),"")} -> 0 | L30: {=IFERROR(VLOOKUP(L$3&$A6&$A9,IF({1,0},业绩报告!$A$2:$A$8229&业绩报告!$B$2:$B$8229&业绩报告!$C$2:$C$8229,业绩报告!$AA$2:$AA$8229),2,0),"")} -> 0 | M30: {=IFERROR(VLOOKUP(M$3&$A6&$A9,IF({1,0},业绩报告!$A$2:$A$8229&业绩报告!$B$2:$B$8229&业绩报告!$C$2:$C$8229,业绩报告!$AA$2:$AA$8229),2,0),"")} -> 0 | N30: {=IFERROR(VLOOKUP(N$3&$A6&$A9,IF({1,0},业绩报告!$A$2:$A$8229&业绩报告!$B$2:$B$8229&业绩报告!$C$2:$C$8229,业绩报告!$AA$2:$AA$8229),2,0),"")} -> 0 | O30: {=IFERROR(VLOOKUP(O$3&$A6&$A9,IF({1,0},业绩报告!$A$2:$A$8229&业绩报告!$B$2:$B$8229&业绩报告!$C$2:$C$8229,业绩报告!$AA$2:$AA$8229),2,0),"")} -> 0 | P30: {=IFERROR(VLOOKUP(P$3&$A6&$A9,IF({1,0},业绩报告!$A$2:$A$8229&业绩报告!$B$2:$B$8229&业绩报告!$C$2:$C$8229,业绩报告!$AA$2:$AA$8229),2,0),"")} -> 0 | Q30: {=IFERROR(VLOOKUP(Q$3&$A6&$A9,IF({1,0},业绩报告!$A$2:$A$8229&业绩报告!$B$2:$B$8229&业绩报告!$C$2:$C$8229,业绩报告!$AA$2:$AA$8229),2,0),"")} -> 0
B31: 关键词5 | C31: {=IFERROR(VLOOKUP(C$3&$A6&$A9,IF({1,0},业绩报告!$A$2:$A$8229&业绩报告!$B$2:$B$8229&业绩报告!$C$2:$C$8229,业绩报告!$AB$2:$AB$8229),2,0),"")} -> 0 | D31: {=IFERROR(VLOOKUP(D$3&$A6&$A9,IF({1,0},业绩报告!$A$2:$A$8229&业绩报告!$B$2:$B$8229&业绩报告!$C$2:$C$8229,业绩报告!$AB$2:$AB$8229),2,0),"")} -> 0 | E31: {=IFERROR(VLOOKUP(E$3&$A6&$A9,IF({1,0},业绩报告!$A$2:$A$8229&业绩报告!$B$2:$B$8229&业绩报告!$C$2:$C$8229,业绩报告!$AB$2:$AB$8229),2,0),"")} -> 0 | F31: {=IFERROR(VLOOKUP(F$3&$A6&$A9,IF({1,0},业绩报告!$A$2:$A$8229&业绩报告!$B$2:$B$8229&业绩报告!$C$2:$C$8229,业绩报告!$AB$2:$AB$8229),2,0),"")} -> 0 | G31: {=IFERROR(VLOOKUP(G$3&$A6&$A9,IF({1,0},业绩报告!$A$2:$A$8229&业绩报告!$B$2:$B$8229&业绩报告!$C$2:$C$8229,业绩报告!$AB$2:$AB$8229),2,0),"")} -> 0 | H31: {=IFERROR(VLOOKUP(H$3&$A6&$A9,IF({1,0},业绩报告!$A$2:$A$8229&业绩报告!$B$2:$B$8229&业绩报告!$C$2:$C$8229,业绩报告!$AB$2:$AB$8229),2,0),"")} -> 0 | I31: {=IFERROR(VLOOKUP(I$3&$A6&$A9,IF({1,0},业绩报告!$A$2:$A$8229&业绩报告!$B$2:$B$8229&业绩报告!$C$2:$C$8229,业绩报告!$AB$2:$AB$8229),2,0),"")} -> 0 | K31: {=IFERROR(VLOOKUP(K$3&$A6&$A9,IF({1,0},业绩报告!$A$2:$A$8229&业绩报告!$B$2:$B$8229&业绩报告!$C$2:$C$8229,业绩报告!$AB$2:$AB$8229),2,0),"")} -> 0 | L31: {=IFERROR(VLOOKUP(L$3&$A6&$A9,IF({1,0},业绩报告!$A$2:$A$8229&业绩报告!$B$2:$B$8229&业绩报告!$C$2:$C$8229,业绩报告!$AB$2:$AB$8229),2,0),"")} -> 0 | M31: {=IFERROR(VLOOKUP(M$3&$A6&$A9,IF({1,0},业绩报告!$A$2:$A$8229&业绩报告!$B$2:$B$8229&业绩报告!$C$2:$C$8229,业绩报告!$AB$2:$AB$8229),2,0),"")} -> 0 | N31: {=IFERROR(VLOOKUP(N$3&$A6&$A9,IF({1,0},业绩报告!$A$2:$A$8229&业绩报告!$B$2:$B$8229&业绩报告!$C$2:$C$8229,业绩报告!$AB$2:$AB$8229),2,0),"")} -> 0 | O31: {=IFERROR(VLOOKUP(O$3&$A6&$A9,IF({1,0},业绩报告!$A$2:$A$8229&业绩报告!$B$2:$B$8229&业绩报告!$C$2:$C$8229,业绩报告!$AB$2:$AB$8229),2,0),"")} -> 0 | P31: {=IFERROR(VLOOKUP(P$3&$A6&$A9,IF({1,0},业绩报告!$A$2:$A$8229&业绩报告!$B$2:$B$8229&业绩报告!$C$2:$C$8229,业绩报告!$AB$2:$AB$8229),2,0),"")} -> 0 | Q31: {=IFERROR(VLOOKUP(Q$3&$A6&$A9,IF({1,0},业绩报告!$A$2:$A$8229&业绩报告!$B$2:$B$8229&业绩报告!$C$2:$C$8229,业绩报告!$AB$2:$AB$8229),2,0),"")} -> 0
B32: 自然位5 | C32: {=IFERROR(VLOOKUP(C$3&$A6&$A9,IF({1,0},业绩报告!$A$2:$A$8229&业绩报告!$B$2:$B$8229&业绩报告!$C$2:$C$8229,业绩报告!$AC$2:$AC$8229),2,0),"")} -> 0 | D32: {=IFERROR(VLOOKUP(D$3&$A6&$A9,IF({1,0},业绩报告!$A$2:$A$8229&业绩报告!$B$2:$B$8229&业绩报告!$C$2:$C$8229,业绩报告!$AC$2:$AC$8229),2,0),"")} -> 0 | E32: {=IFERROR(VLOOKUP(E$3&$A6&$A9,IF({1,0},业绩报告!$A$2:$A$8229&业绩报告!$B$2:$B$8229&业绩报告!$C$2:$C$8229,业绩报告!$AC$2:$AC$8229),2,0),"")} -> 0 | F32: {=IFERROR(VLOOKUP(F$3&$A6&$A9,IF({1,0},业绩报告!$A$2:$A$8229&业绩报告!$B$2:$B$8229&业绩报告!$C$2:$C$8229,业绩报告!$AC$2:$AC$8229),2,0),"")} -> 0 | G32: {=IFERROR(VLOOKUP(G$3&$A6&$A9,IF({1,0},业绩报告!$A$2:$A$8229&业绩报告!$B$2:$B$8229&业绩报告!$C$2:$C$8229,业绩报告!$AC$2:$AC$8229),2,0),"")} -> 0 | H32: {=IFERROR(VLOOKUP(H$3&$A6&$A9,IF({1,0},业绩报告!$A$2:$A$8229&业绩报告!$B$2:$B$8229&业绩报告!$C$2:$C$8229,业绩报告!$AC$2:$AC$8229),2,0),"")} -> 0 | I32: {=IFERROR(VLOOKUP(I$3&$A6&$A9,IF({1,0},业绩报告!$A$2:$A$8229&业绩报告!$B$2:$B$8229&业绩报告!$C$2:$C$8229,业绩报告!$AC$2:$AC$8229),2,0),"")} -> 0 | K32: {=IFERROR(VLOOKUP(K$3&$A6&$A9,IF({1,0},业绩报告!$A$2:$A$8229&业绩报告!$B$2:$B$8229&业绩报告!$C$2:$C$8229,业绩报告!$AC$2:$AC$8229),2,0),"")} -> 0 | L32: {=IFERROR(VLOOKUP(L$3&$A6&$A9,IF({1,0},业绩报告!$A$2:$A$8229&业绩报告!$B$2:$B$8229&业绩报告!$C$2:$C$8229,业绩报告!$AC$2:$AC$8229),2,0),"")} -> 0 | M32: {=IFERROR(VLOOKUP(M$3&$A6&$A9,IF({1,0},业绩报告!$A$2:$A$8229&业绩报告!$B$2:$B$8229&业绩报告!$C$2:$C$8229,业绩报告!$AC$2:$AC$8229),2,0),"")} -> 0 | N32: {=IFERROR(VLOOKUP(N$3&$A6&$A9,IF({1,0},业绩报告!$A$2:$A$8229&业绩报告!$B$2:$B$8229&业绩报告!$C$2:$C$8229,业绩报告!$AC$2:$AC$8229),2,0),"")} -> 0 | O32: {=IFERROR(VLOOKUP(O$3&$A6&$A9,IF({1,0},业绩报告!$A$2:$A$8229&业绩报告!$B$2:$B$8229&业绩报告!$C$2:$C$8229,业绩报告!$AC$2:$AC$8229),2,0),"")} -> 0 | P32: {=IFERROR(VLOOKUP(P$3&$A6&$A9,IF({1,0},业绩报告!$A$2:$A$8229&业绩报告!$B$2:$B$8229&业绩报告!$C$2:$C$8229,业绩报告!$AC$2:$AC$8229),2,0),"")} -> 0 | Q32: {=IFERROR(VLOOKUP(Q$3&$A6&$A9,IF({1,0},业绩报告!$A$2:$A$8229&业绩报告!$B$2:$B$8229&业绩报告!$C$2:$C$8229,业绩报告!$AC$2:$AC$8229),2,0),"")} -> 0
B33: 广告位5 | C33: {=IFERROR(VLOOKUP(C$3&$A6&$A9,IF({1,0},业绩报告!$A$2:$A$8229&业绩报告!$B$2:$B$8229&业绩报告!$C$2:$C$8229,业绩报告!$AD$2:$AD$8229),2,0),"")} -> 0 | D33: {=IFERROR(VLOOKUP(D$3&$A6&$A9,IF({1,0},业绩报告!$A$2:$A$8229&业绩报告!$B$2:$B$8229&业绩报告!$C$2:$C$8229,业绩报告!$AD$2:$AD$8229),2,0),"")} -> 0 | E33: {=IFERROR(VLOOKUP(E$3&$A6&$A9,IF({1,0},业绩报告!$A$2:$A$8229&业绩报告!$B$2:$B$8229&业绩报告!$C$2:$C$8229,业绩报告!$AD$2:$AD$8229),2,0),"")} -> 0 | F33: {=IFERROR(VLOOKUP(F$3&$A6&$A9,IF({1,0},业绩报告!$A$2:$A$8229&业绩报告!$B$2:$B$8229&业绩报告!$C$2:$C$8229,业绩报告!$AD$2:$AD$8229),2,0),"")} -> 0 | G33: {=IFERROR(VLOOKUP(G$3&$A6&$A9,IF({1,0},业绩报告!$A$2:$A$8229&业绩报告!$B$2:$B$8229&业绩报告!$C$2:$C$8229,业绩报告!$AD$2:$AD$8229),2,0),"")} -> 0 | H33: {=IFERROR(VLOOKUP(H$3&$A6&$A9,IF({1,0},业绩报告!$A$2:$A$8229&业绩报告!$B$2:$B$8229&业绩报告!$C$2:$C$8229,业绩报告!$AD$2:$AD$8229),2,0),"")} -> 0 | I33: {=IFERROR(VLOOKUP(I$3&$A6&$A9,IF({1,0},业绩报告!$A$2:$A$8229&业绩报告!$B$2:$B$8229&业绩报告!$C$2:$C$8229,业绩报告!$AD$2:$AD$8229),2,0),"")} -> 0 | K33: {=IFERROR(VLOOKUP(K$3&$A6&$A9,IF({1,0},业绩报告!$A$2:$A$8229&业绩报告!$B$2:$B$8229&业绩报告!$C$2:$C$8229,业绩报告!$AD$2:$AD$8229),2,0),"")} -> 0 | L33: {=IFERROR(VLOOKUP(L$3&$A6&$A9,IF({1,0},业绩报告!$A$2:$A$8229&业绩报告!$B$2:$B$8229&业绩报告!$C$2:$C$8229,业绩报告!$AD$2:$AD$8229),2,0),"")} -> 0 | M33: {=IFERROR(VLOOKUP(M$3&$A6&$A9,IF({1,0},业绩报告!$A$2:$A$8229&业绩报告!$B$2:$B$8229&业绩报告!$C$2:$C$8229,业绩报告!$AD$2:$AD$8229),2,0),"")} -> 0 | N33: {=IFERROR(VLOOKUP(N$3&$A6&$A9,IF({1,0},业绩报告!$A$2:$A$8229&业绩报告!$B$2:$B$8229&业绩报告!$C$2:$C$8229,业绩报告!$AD$2:$AD$8229),2,0),"")} -> 0 | O33: {=IFERROR(VLOOKUP(O$3&$A6&$A9,IF({1,0},业绩报告!$A$2:$A$8229&业绩报告!$B$2:$B$8229&业绩报告!$C$2:$C$8229,业绩报告!$AD$2:$AD$8229),2,0),"")} -> 0 | P33: {=IFERROR(VLOOKUP(P$3&$A6&$A9,IF({1,0},业绩报告!$A$2:$A$8229&业绩报告!$B$2:$B$8229&业绩报告!$C$2:$C$8229,业绩报告!$AD$2:$AD$8229),2,0),"")} -> 0 | Q33: {=IFERROR(VLOOKUP(Q$3&$A6&$A9,IF({1,0},业绩报告!$A$2:$A$8229&业绩报告!$B$2:$B$8229&业绩报告!$C$2:$C$8229,业绩报告!$AD$2:$AD$8229),2,0),"")} -> 0
B34: 关键词6 | C34: {=IFERROR(VLOOKUP(C$3&$A6&$A9,IF({1,0},业绩报告!$A$2:$A$8229&业绩报告!$B$2:$B$8229&业绩报告!$C$2:$C$8229,业绩报告!$AE$2:$AE$8229),2,0),"")} -> 0 | D34: {=IFERROR(VLOOKUP(D$3&$A6&$A9,IF({1,0},业绩报告!$A$2:$A$8229&业绩报告!$B$2:$B$8229&业绩报告!$C$2:$C$8229,业绩报告!$AE$2:$AE$8229),2,0),"")} -> 0 | E34: {=IFERROR(VLOOKUP(E$3&$A6&$A9,IF({1,0},业绩报告!$A$2:$A$8229&业绩报告!$B$2:$B$8229&业绩报告!$C$2:$C$8229,业绩报告!$AE$2:$AE$8229),2,0),"")} -> 0 | F34: {=IFERROR(VLOOKUP(F$3&$A6&$A9,IF({1,0},业绩报告!$A$2:$A$8229&业绩报告!$B$2:$B$8229&业绩报告!$C$2:$C$8229,业绩报告!$AE$2:$AE$8229),2,0),"")} -> 0 | G34: {=IFERROR(VLOOKUP(G$3&$A6&$A9,IF({1,0},业绩报告!$A$2:$A$8229&业绩报告!$B$2:$B$8229&业绩报告!$C$2:$C$8229,业绩报告!$AE$2:$AE$8229),2,0),"")} -> 0 | H34: {=IFERROR(VLOOKUP(H$3&$A6&$A9,IF({1,0},业绩报告!$A$2:$A$8229&业绩报告!$B$2:$B$8229&业绩报告!$C$2:$C$8229,业绩报告!$AE$2:$AE$8229),2,0),"")} -> 0 | I34: {=IFERROR(VLOOKUP(I$3&$A6&$A9,IF({1,0},业绩报告!$A$2:$A$8229&业绩报告!$B$2:$B$8229&业绩报告!$C$2:$C$8229,业绩报告!$AE$2:$AE$8229),2,0),"")} -> 0 | K34: {=IFERROR(VLOOKUP(K$3&$A6&$A9,IF({1,0},业绩报告!$A$2:$A$8229&业绩报告!$B$2:$B$8229&业绩报告!$C$2:$C$8229,业绩报告!$AE$2:$AE$8229),2,0),"")} -> 0 | L34: {=IFERROR(VLOOKUP(L$3&$A6&$A9,IF({1,0},业绩报告!$A$2:$A$8229&业绩报告!$B$2:$B$8229&业绩报告!$C$2:$C$8229,业绩报告!$AE$2:$AE$8229),2,0),"")} -> 0 | M34: {=IFERROR(VLOOKUP(M$3&$A6&$A9,IF({1,0},业绩报告!$A$2:$A$8229&业绩报告!$B$2:$B$8229&业绩报告!$C$2:$C$8229,业绩报告!$AE$2:$AE$8229),2,0),"")} -> 0 | N34: {=IFERROR(VLOOKUP(N$3&$A6&$A9,IF({1,0},业绩报告!$A$2:$A$8229&业绩报告!$B$2:$B$8229&业绩报告!$C$2:$C$8229,业绩报告!$AE$2:$AE$8229),2,0),"")} -> 0 | O34: {=IFERROR(VLOOKUP(O$3&$A6&$A9,IF({1,0},业绩报告!$A$2:$A$8229&业绩报告!$B$2:$B$8229&业绩报告!$C$2:$C$8229,业绩报告!$AE$2:$AE$8229),2,0),"")} -> 0 | P34: {=IFERROR(VLOOKUP(P$3&$A6&$A9,IF({1,0},业绩报告!$A$2:$A$8229&业绩报告!$B$2:$B$8229&业绩报告!$C$2:$C$8229,业绩报告!$AE$2:$AE$8229),2,0),"")} -> 0 | Q34: {=IFERROR(VLOOKUP(Q$3&$A6&$A9,IF({1,0},业绩报告!$A$2:$A$8229&业绩报告!$B$2:$B$8229&业绩报告!$C$2:$C$8229,业绩报告!$AE$2:$AE$8229),2,0),"")} -> 0
B35: 自然位6 | C35: {=IFERROR(VLOOKUP(C$3&$A6&$A9,IF({1,0},业绩报告!$A$2:$A$8229&业绩报告!$B$2:$B$8229&业绩报告!$C$2:$C$8229,业绩报告!$AF$2:$AF$8229),2,0),"")} -> 0 | D35: {=IFERROR(VLOOKUP(D$3&$A6&$A9,IF({1,0},业绩报告!$A$2:$A$8229&业绩报告!$B$2:$B$8229&业绩报告!$C$2:$C$8229,业绩报告!$AF$2:$AF$8229),2,0),"")} -> 0 | E35: {=IFERROR(VLOOKUP(E$3&$A6&$A9,IF({1,0},业绩报告!$A$2:$A$8229&业绩报告!$B$2:$B$8229&业绩报告!$C$2:$C$8229,业绩报告!$AF$2:$AF$8229),2,0),"")} -> 0 | F35: {=IFERROR(VLOOKUP(F$3&$A6&$A9,IF({1,0},业绩报告!$A$2:$A$8229&业绩报告!$B$2:$B$8229&业绩报告!$C$2:$C$8229,业绩报告!$AF$2:$AF$8229),2,0),"")} -> 0 | G35: {=IFERROR(VLOOKUP(G$3&$A6&$A9,IF({1,0},业绩报告!$A$2:$A$8229&业绩报告!$B$2:$B$8229&业绩报告!$C$2:$C$8229,业绩报告!$AF$2:$AF$8229),2,0),"")} -> 0 | H35: {=IFERROR(VLOOKUP(H$3&$A6&$A9,IF({1,0},业绩报告!$A$2:$A$8229&业绩报告!$B$2:$B$8229&业绩报告!$C$2:$C$8229,业绩报告!$AF$2:$AF$8229),2,0),"")} -> 0 | I35: {=IFERROR(VLOOKUP(I$3&$A6&$A9,IF({1,0},业绩报告!$A$2:$A$8229&业绩报告!$B$2:$B$8229&业绩报告!$C$2:$C$8229,业绩报告!$AF$2:$AF$8229),2,0),"")} -> 0 | K35: {=IFERROR(VLOOKUP(K$3&$A6&$A9,IF({1,0},业绩报告!$A$2:$A$8229&业绩报告!$B$2:$B$8229&业绩报告!$C$2:$C$8229,业绩报告!$AF$2:$AF$8229),2,0),"")} -> 0 | L35: {=IFERROR(VLOOKUP(L$3&$A6&$A9,IF({1,0},业绩报告!$A$2:$A$8229&业绩报告!$B$2:$B$8229&业绩报告!$C$2:$C$8229,业绩报告!$AF$2:$AF$8229),2,0),"")} -> 0 | M35: {=IFERROR(VLOOKUP(M$3&$A6&$A9,IF({1,0},业绩报告!$A$2:$A$8229&业绩报告!$B$2:$B$8229&业绩报告!$C$2:$C$8229,业绩报告!$AF$2:$AF$8229),2,0),"")} -> 0 | N35: {=IFERROR(VLOOKUP(N$3&$A6&$A9,IF({1,0},业绩报告!$A$2:$A$8229&业绩报告!$B$2:$B$8229&业绩报告!$C$2:$C$8229,业绩报告!$AF$2:$AF$8229),2,0),"")} -> 0 | O35: {=IFERROR(VLOOKUP(O$3&$A6&$A9,IF({1,0},业绩报告!$A$2:$A$8229&业绩报告!$B$2:$B$8229&业绩报告!$C$2:$C$8229,业绩报告!$AF$2:$AF$8229),2,0),"")} -> 0 | P35: {=IFERROR(VLOOKUP(P$3&$A6&$A9,IF({1,0},业绩报告!$A$2:$A$8229&业绩报告!$B$2:$B$8229&业绩报告!$C$2:$C$8229,业绩报告!$AF$2:$AF$8229),2,0),"")} -> 0 | Q35: {=IFERROR(VLOOKUP(Q$3&$A6&$A9,IF({1,0},业绩报告!$A$2:$A$8229&业绩报告!$B$2:$B$8229&业绩报告!$C$2:$C$8229,业绩报告!$AF$2:$AF$8229),2,0),"")} -> 0
B36: 广告位6 | C36: {=IFERROR(VLOOKUP(C$3&$A6&$A9,IF({1,0},业绩报告!$A$2:$A$8229&业绩报告!$B$2:$B$8229&业绩报告!$C$2:$C$8229,业绩报告!$AG$2:$AG$8229),2,0),"")} -> 0 | D36: {=IFERROR(VLOOKUP(D$3&$A6&$A9,IF({1,0},业绩报告!$A$2:$A$8229&业绩报告!$B$2:$B$8229&业绩报告!$C$2:$C$8229,业绩报告!$AG$2:$AG$8229),2,0),"")} -> 0 | E36: {=IFERROR(VLOOKUP(E$3&$A6&$A9,IF({1,0},业绩报告!$A$2:$A$8229&业绩报告!$B$2:$B$8229&业绩报告!$C$2:$C$8229,业绩报告!$AG$2:$AG$8229),2,0),"")} -> 0 | F36: {=IFERROR(VLOOKUP(F$3&$A6&$A9,IF({1,0},业绩报告!$A$2:$A$8229&业绩报告!$B$2:$B$8229&业绩报告!$C$2:$C$8229,业绩报告!$AG$2:$AG$8229),2,0),"")} -> 0 | G36: {=IFERROR(VLOOKUP(G$3&$A6&$A9,IF({1,0},业绩报告!$A$2:$A$8229&业绩报告!$B$2:$B$8229&业绩报告!$C$2:$C$8229,业绩报告!$AG$2:$AG$8229),2,0),"")} -> 0 | H36: {=IFERROR(VLOOKUP(H$3&$A6&$A9,IF({1,0},业绩报告!$A$2:$A$8229&业绩报告!$B$2:$B$8229&业绩报告!$C$2:$C$8229,业绩报告!$AG$2:$AG$8229),2,0),"")} -> 0 | I36: {=IFERROR(VLOOKUP(I$3&$A6&$A9,IF({1,0},业绩报告!$A$2:$A$8229&业绩报告!$B$2:$B$8229&业绩报告!$C$2:$C$8229,业绩报告!$AG$2:$AG$8229),2,0),"")} -> 0 | K36: {=IFERROR(VLOOKUP(K$3&$A6&$A9,IF({1,0},业绩报告!$A$2:$A$8229&业绩报告!$B$2:$B$8229&业绩报告!$C$2:$C$8229,业绩报告!$AG$2:$AG$8229),2,0),"")} -> 0 | L36: {=IFERROR(VLOOKUP(L$3&$A6&$A9,IF({1,0},业绩报告!$A$2:$A$8229&业绩报告!$B$2:$B$8229&业绩报告!$C$2:$C$8229,业绩报告!$AG$2:$AG$8229),2,0),"")} -> 0 | M36: {=IFERROR(VLOOKUP(M$3&$A6&$A9,IF({1,0},业绩报告!$A$2:$A$8229&业绩报告!$B$2:$B$8229&业绩报告!$C$2:$C$8229,业绩报告!$AG$2:$AG$8229),2,0),"")} -> 0 | N36: {=IFERROR(VLOOKUP(N$3&$A6&$A9,IF({1,0},业绩报告!$A$2:$A$8229&业绩报告!$B$2:$B$8229&业绩报告!$C$2:$C$8229,业绩报告!$AG$2:$AG$8229),2,0),"")} -> 0 | O36: {=IFERROR(VLOOKUP(O$3&$A6&$A9,IF({1,0},业绩报告!$A$2:$A$8229&业绩报告!$B$2:$B$8229&业绩报告!$C$2:$C$8229,业绩报告!$AG$2:$AG$8229),2,0),"")} -> 0 | P36: {=IFERROR(VLOOKUP(P$3&$A6&$A9,IF({1,0},业绩报告!$A$2:$A$8229&业绩报告!$B$2:$B$8229&业绩报告!$C$2:$C$8229,业绩报告!$AG$2:$AG$8229),2,0),"")} -> 0 | Q36: {=IFERROR(VLOOKUP(Q$3&$A6&$A9,IF({1,0},业绩报告!$A$2:$A$8229&业绩报告!$B$2:$B$8229&业绩报告!$C$2:$C$8229,业绩报告!$AG$2:$AG$8229),2,0),"")} -> 0
B37: 关键词7 | C37: {=IFERROR(VLOOKUP(C$3&$A6&$A9,IF({1,0},业绩报告!$A$2:$A$8229&业绩报告!$B$2:$B$8229&业绩报告!$C$2:$C$8229,业绩报告!$AH$2:$AH$8229),2,0),"")} -> 0 | D37: {=IFERROR(VLOOKUP(D$3&$A6&$A9,IF({1,0},业绩报告!$A$2:$A$8229&业绩报告!$B$2:$B$8229&业绩报告!$C$2:$C$8229,业绩报告!$AH$2:$AH$8229),2,0),"")} -> 0 | E37: {=IFERROR(VLOOKUP(E$3&$A6&$A9,IF({1,0},业绩报告!$A$2:$A$8229&业绩报告!$B$2:$B$8229&业绩报告!$C$2:$C$8229,业绩报告!$AH$2:$AH$8229),2,0),"")} -> 0 | F37: {=IFERROR(VLOOKUP(F$3&$A6&$A9,IF({1,0},业绩报告!$A$2:$A$8229&业绩报告!$B$2:$B$8229&业绩报告!$C$2:$C$8229,业绩报告!$AH$2:$AH$8229),2,0),"")} -> 0 | G37: {=IFERROR(VLOOKUP(G$3&$A6&$A9,IF({1,0},业绩报告!$A$2:$A$8229&业绩报告!$B$2:$B$8229&业绩报告!$C$2:$C$8229,业绩报告!$AH$2:$AH$8229),2,0),"")} -> 0 | H37: {=IFERROR(VLOOKUP(H$3&$A6&$A9,IF({1,0},业绩报告!$A$2:$A$8229&业绩报告!$B$2:$B$8229&业绩报告!$C$2:$C$8229,业绩报告!$AH$2:$AH$8229),2,0),"")} -> 0 | I37: {=IFERROR(VLOOKUP(I$3&$A6&$A9,IF({1,0},业绩报告!$A$2:$A$8229&业绩报告!$B$2:$B$8229&业绩报告!$C$2:$C$8229,业绩报告!$AH$2:$AH$8229),2,0),"")} -> 0 | K37: {=IFERROR(VLOOKUP(I$3&$A6&$A9,IF({1,0},业绩报告!$A$2:$A$8229&业绩报告!$B$2:$B$8229&业绩报告!$C$2:$C$8229,业绩报告!$AH$2:$AH$8229),2,0),"")} -> 0 | L37: {=IFERROR(VLOOKUP(J$3&$A6&$A9,IF({1,0},业绩报告!$A$2:$A$8229&业绩报告!$B$2:$B$8229&业绩报告!$C$2:$C$8229,业绩报告!$AH$2:$AH$8229),2,0),"")} | M37: {=IFERROR(VLOOKUP(K$3&$A6&$A9,IF({1,0},业绩报告!$A$2:$A$8229&业绩报告!$B$2:$B$8229&业绩报告!$C$2:$C$8229,业绩报告!$AH$2:$AH$8229),2,0),"")} -> 0 | N37: {=IFERROR(VLOOKUP(L$3&$A6&$A9,IF({1,0},业绩报告!$A$2:$A$8229&业绩报告!$B$2:$B$8229&业绩报告!$C$2:$C$8229,业绩报告!$AH$2:$AH$8229),2,0),"")} -> 0 | O37: {=IFERROR(VLOOKUP(M$3&$A6&$A9,IF({1,0},业绩报告!$A$2:$A$8229&业绩报告!$B$2:$B$8229&业绩报告!$C$2:$C$8229,业绩报告!$AH$2:$AH$8229),2,0),"")} -> 0 | P37: {=IFERROR(VLOOKUP(N$3&$A6&$A9,IF({1,0},业绩报告!$A$2:$A$8229&业绩报告!$B$2:$B$8229&业绩报告!$C$2:$C$8229,业绩报告!$AH$2:$AH$8229),2,0),"")} -> 0 | Q37: {=IFERROR(VLOOKUP(O$3&$A6&$A9,IF({1,0},业绩报告!$A$2:$A$8229&业绩报告!$B$2:$B$8229&业绩报告!$C$2:$C$8229,业绩报告!$AH$2:$AH$8229),2,0),"")} -> 0
B38: 自然位7 | C38: {=IFERROR(VLOOKUP(C$3&$A6&$A9,IF({1,0},业绩报告!$A$2:$A$8229&业绩报告!$B$2:$B$8229&业绩报告!$C$2:$C$8229,业绩报告!$AI$2:$AI$8229),2,0),"")} -> 0 | D38: {=IFERROR(VLOOKUP(D$3&$A6&$A9,IF({1,0},业绩报告!$A$2:$A$8229&业绩报告!$B$2:$B$8229&业绩报告!$C$2:$C$8229,业绩报告!$AI$2:$AI$8229),2,0),"")} -> 0 | E38: {=IFERROR(VLOOKUP(E$3&$A6&$A9,IF({1,0},业绩报告!$A$2:$A$8229&业绩报告!$B$2:$B$8229&业绩报告!$C$2:$C$8229,业绩报告!$AI$2:$AI$8229),2,0),"")} -> 0 | F38: {=IFERROR(VLOOKUP(F$3&$A6&$A9,IF({1,0},业绩报告!$A$2:$A$8229&业绩报告!$B$2:$B$8229&业绩报告!$C$2:$C$8229,业绩报告!$AI$2:$AI$8229),2,0),"")} -> 0 | G38: {=IFERROR(VLOOKUP(G$3&$A6&$A9,IF({1,0},业绩报告!$A$2:$A$8229&业绩报告!$B$2:$B$8229&业绩报告!$C$2:$C$8229,业绩报告!$AI$2:$AI$8229),2,0),"")} -> 0 | H38: {=IFERROR(VLOOKUP(H$3&$A6&$A9,IF({1,0},业绩报告!$A$2:$A$8229&业绩报告!$B$2:$B$8229&业绩报告!$C$2:$C$8229,业绩报告!$AI$2:$AI$8229),2,0),"")} -> 0 | I38: {=IFERROR(VLOOKUP(I$3&$A6&$A9,IF({1,0},业绩报告!$A$2:$A$8229&业绩报告!$B$2:$B$8229&业绩报告!$C$2:$C$8229,业绩报告!$AI$2:$AI$8229),2,0),"")} -> 0 | K38: {=IFERROR(VLOOKUP(K$3&$A6&$A9,IF({1,0},业绩报告!$A$2:$A$8229&业绩报告!$B$2:$B$8229&业绩报告!$C$2:$C$8229,业绩报告!$AI$2:$AI$8229),2,0),"")} -> 0 | L38: {=IFERROR(VLOOKUP(L$3&$A6&$A9,IF({1,0},业绩报告!$A$2:$A$8229&业绩报告!$B$2:$B$8229&业绩报告!$C$2:$C$8229,业绩报告!$AI$2:$AI$8229),2,0),"")} -> 0 | M38: {=IFERROR(VLOOKUP(M$3&$A6&$A9,IF({1,0},业绩报告!$A$2:$A$8229&业绩报告!$B$2:$B$8229&业绩报告!$C$2:$C$8229,业绩报告!$AI$2:$AI$8229),2,0),"")} -> 0 | N38: {=IFERROR(VLOOKUP(N$3&$A6&$A9,IF({1,0},业绩报告!$A$2:$A$8229&业绩报告!$B$2:$B$8229&业绩报告!$C$2:$C$8229,业绩报告!$AI$2:$AI$8229),2,0),"")} -> 0 | O38: {=IFERROR(VLOOKUP(O$3&$A6&$A9,IF({1,0},业绩报告!$A$2:$A$8229&业绩报告!$B$2:$B$8229&业绩报告!$C$2:$C$8229,业绩报告!$AI$2:$AI$8229),2,0),"")} -> 0 | P38: {=IFERROR(VLOOKUP(P$3&$A6&$A9,IF({1,0},业绩报告!$A$2:$A$8229&业绩报告!$B$2:$B$8229&业绩报告!$C$2:$C$8229,业绩报告!$AI$2:$AI$8229),2,0),"")} -> 0 | Q38: {=IFERROR(VLOOKUP(Q$3&$A6&$A9,IF({1,0},业绩报告!$A$2:$A$8229&业绩报告!$B$2:$B$8229&业绩报告!$C$2:$C$8229,业绩报告!$AI$2:$AI$8229),2,0),"")} -> 0
B39: 广告位7 | C39: {=IFERROR(VLOOKUP(C$3&$A6&$A9,IF({1,0},业绩报告!$A$2:$A$8229&业绩报告!$B$2:$B$8229&业绩报告!$C$2:$C$8229,业绩报告!$AJ$2:$AJ$8229),2,0),"")} -> 0 | D39: {=IFERROR(VLOOKUP(D$3&$A6&$A9,IF({1,0},业绩报告!$A$2:$A$8229&业绩报告!$B$2:$B$8229&业绩报告!$C$2:$C$8229,业绩报告!$AJ$2:$AJ$8229),2,0),"")} -> 0 | E39: {=IFERROR(VLOOKUP(E$3&$A6&$A9,IF({1,0},业绩报告!$A$2:$A$8229&业绩报告!$B$2:$B$8229&业绩报告!$C$2:$C$8229,业绩报告!$AJ$2:$AJ$8229),2,0),"")} -> 0 | F39: {=IFERROR(VLOOKUP(F$3&$A6&$A9,IF({1,0},业绩报告!$A$2:$A$8229&业绩报告!$B$2:$B$8229&业绩报告!$C$2:$C$8229,业绩报告!$AJ$2:$AJ$8229),2,0),"")} -> 0 | G39: {=IFERROR(VLOOKUP(G$3&$A6&$A9,IF({1,0},业绩报告!$A$2:$A$8229&业绩报告!$B$2:$B$8229&业绩报告!$C$2:$C$8229,业绩报告!$AJ$2:$AJ$8229),2,0),"")} -> 0 | H39: {=IFERROR(VLOOKUP(H$3&$A6&$A9,IF({1,0},业绩报告!$A$2:$A$8229&业绩报告!$B$2:$B$8229&业绩报告!$C$2:$C$8229,业绩报告!$AJ$2:$AJ$8229),2,0),"")} -> 0 | I39: {=IFERROR(VLOOKUP(I$3&$A6&$A9,IF({1,0},业绩报告!$A$2:$A$8229&业绩报告!$B$2:$B$8229&业绩报告!$C$2:$C$8229,业绩报告!$AJ$2:$AJ$8229),2,0),"")} -> 0 | K39: {=IFERROR(VLOOKUP(I$3&$A6&$A9,IF({1,0},业绩报告!$A$2:$A$8229&业绩报告!$B$2:$B$8229&业绩报告!$C$2:$C$8229,业绩报告!$AJ$2:$AJ$8229),2,0),"")} -> 0 | L39: {=IFERROR(VLOOKUP(J$3&$A6&$A9,IF({1,0},业绩报告!$A$2:$A$8229&业绩报告!$B$2:$B$8229&业绩报告!$C$2:$C$8229,业绩报告!$AJ$2:$AJ$8229),2,0),"")} | M39: {=IFERROR(VLOOKUP(K$3&$A6&$A9,IF({1,0},业绩报告!$A$2:$A$8229&业绩报告!$B$2:$B$8229&业绩报告!$C$2:$C$8229,业绩报告!$AJ$2:$AJ$8229),2,0),"")} -> 0 | N39: {=IFERROR(VLOOKUP(L$3&$A6&$A9,IF({1,0},业绩报告!$A$2:$A$8229&业绩报告!$B$2:$B$8229&业绩报告!$C$2:$C$8229,业绩报告!$AJ$2:$AJ$8229),2,0),"")} -> 0 | O39: {=IFERROR(VLOOKUP(M$3&$A6&$A9,IF({1,0},业绩报告!$A$2:$A$8229&业绩报告!$B$2:$B$8229&业绩报告!$C$2:$C$8229,业绩报告!$AJ$2:$AJ$8229),2,0),"")} -> 0 | P39: {=IFERROR(VLOOKUP(N$3&$A6&$A9,IF({1,0},业绩报告!$A$2:$A$8229&业绩报告!$B$2:$B$8229&业绩报告!$C$2:$C$8229,业绩报告!$AJ$2:$AJ$8229),2,0),"")} -> 0 | Q39: {=IFERROR(VLOOKUP(O$3&$A6&$A9,IF({1,0},业绩报告!$A$2:$A$8229&业绩报告!$B$2:$B$8229&业绩报告!$C$2:$C$8229,业绩报告!$AJ$2:$AJ$8229),2,0),"")} -> 0
B40: 自动广告曝光量 | C40: {=IFERROR(VLOOKUP(C$3&$A6&$A9,IF({1,0},业绩报告!$A$2:$A$8229&业绩报告!$B$2:$B$8229&业绩报告!$C$2:$C$8229,业绩报告!$AK$2:$AK$8229),2,0),"0")} -> 4202 | D40: {=IFERROR(VLOOKUP(D$3&$A6&$A9,IF({1,0},业绩报告!$A$2:$A$8229&业绩报告!$B$2:$B$8229&业绩报告!$C$2:$C$8229,业绩报告!$AK$2:$AK$8229),2,0),"0")} -> 2534 | E40: {=IFERROR(VLOOKUP(E$3&$A6&$A9,IF({1,0},业绩报告!$A$2:$A$8229&业绩报告!$B$2:$B$8229&业绩报告!$C$2:$C$8229,业绩报告!$AK$2:$AK$8229),2,0),"0")} -> 3156 | F40: {=IFERROR(VLOOKUP(F$3&$A6&$A9,IF({1,0},业绩报告!$A$2:$A$8229&业绩报告!$B$2:$B$8229&业绩报告!$C$2:$C$8229,业绩报告!$AK$2:$AK$8229),2,0),"0")} -> 2257 | G40: {=IFERROR(VLOOKUP(G$3&$A6&$A9,IF({1,0},业绩报告!$A$2:$A$8229&业绩报告!$B$2:$B$8229&业绩报告!$C$2:$C$8229,业绩报告!$AK$2:$AK$8229),2,0),"0")} -> 4057 | H40: {=IFERROR(VLOOKUP(H$3&$A6&$A9,IF({1,0},业绩报告!$A$2:$A$8229&业绩报告!$B$2:$B$8229&业绩报告!$C$2:$C$8229,业绩报告!$AK$2:$AK$8229),2,0),"0")} -> 3915 | I40: {=IFERROR(VLOOKUP(I$3&$A6&$A9,IF({1,0},业绩报告!$A$2:$A$8229&业绩报告!$B$2:$B$8229&业绩报告!$C$2:$C$8229,业绩报告!$AK$2:$AK$8229),2,0),"0")} -> 0 | J40: =SUM(C40:I40) -> 20121 | K40: {=IFERROR(VLOOKUP(K$3&$A6&$A9,IF({1,0},业绩报告!$A$2:$A$8229&业绩报告!$B$2:$B$8229&业绩报告!$C$2:$C$8229,业绩报告!$AK$2:$AK$8229),2,0),"")} -> 4592 | L40: {=IFERROR(VLOOKUP(L$3&$A6&$A9,IF({1,0},业绩报告!$A$2:$A$8229&业绩报告!$B$2:$B$8229&业绩报告!$C$2:$C$8229,业绩报告!$AK$2:$AK$8229),2,0),"")} -> 5606 | M40: {=IFERROR(VLOOKUP(M$3&$A6&$A9,IF({1,0},业绩报告!$A$2:$A$8229&业绩报告!$B$2:$B$8229&业绩报告!$C$2:$C$8229,业绩报告!$AK$2:$AK$8229),2,0),"")} -> 5079 | N40: {=IFERROR(VLOOKUP(N$3&$A6&$A9,IF({1,0},业绩报告!$A$2:$A$8229&业绩报告!$B$2:$B$8229&业绩报告!$C$2:$C$8229,业绩报告!$AK$2:$AK$8229),2,0),"")} -> 5386 | O40: {=IFERROR(VLOOKUP(O$3&$A6&$A9,IF({1,0},业绩报告!$A$2:$A$8229&业绩报告!$B$2:$B$8229&业绩报告!$C$2:$C$8229,业绩报告!$AK$2:$AK$8229),2,0),"")} -> 10642 | P40: {=IFERROR(VLOOKUP(P$3&$A6&$A9,IF({1,0},业绩报告!$A$2:$A$8229&业绩报告!$B$2:$B$8229&业绩报告!$C$2:$C$8229,业绩报告!$AK$2:$AK$8229),2,0),"")} -> 8122 | Q40: {=IFERROR(VLOOKUP(Q$3&$A6&$A9,IF({1,0},业绩报告!$A$2:$A$8229&业绩报告!$B$2:$B$8229&业绩报告!$C$2:$C$8229,业绩报告!$AK$2:$AK$8229),2,0),"")} -> 3567 | R40: =SUM(K40:Q40) -> 42994
B41: 自动广告点击量 | C41: {=IFERROR(VLOOKUP(C$3&$A6&$A9,IF({1,0},业绩报告!$A$2:$A$8229&业绩报告!$B$2:$B$8229&业绩报告!$C$2:$C$8229,业绩报告!$AL$2:$AL$8229),2,0),"0")} -> 28 | D41: {=IFERROR(VLOOKUP(D$3&$A6&$A9,IF({1,0},业绩报告!$A$2:$A$8229&业绩报告!$B$2:$B$8229&业绩报告!$C$2:$C$8229,业绩报告!$AL$2:$AL$8229),2,0),"0")} -> 10 | E41: {=IFERROR(VLOOKUP(E$3&$A6&$A9,IF({1,0},业绩报告!$A$2:$A$8229&业绩报告!$B$2:$B$8229&业绩报告!$C$2:$C$8229,业绩报告!$AL$2:$AL$8229),2,0),"0")} -> 16 | F41: {=IFERROR(VLOOKUP(F$3&$A6&$A9,IF({1,0},业绩报告!$A$2:$A$8229&业绩报告!$B$2:$B$8229&业绩报告!$C$2:$C$8229,业绩报告!$AL$2:$AL$8229),2,0),"0")} -> 19 | G41: {=IFERROR(VLOOKUP(G$3&$A6&$A9,IF({1,0},业绩报告!$A$2:$A$8229&业绩报告!$B$2:$B$8229&业绩报告!$C$2:$C$8229,业绩报告!$AL$2:$AL$8229),2,0),"0")} -> 22 | H41: {=IFERROR(VLOOKUP(H$3&$A6&$A9,IF({1,0},业绩报告!$A$2:$A$8229&业绩报告!$B$2:$B$8229&业绩报告!$C$2:$C$8229,业绩报告!$AL$2:$AL$8229),2,0),"0")} -> 36 | I41: {=IFERROR(VLOOKUP(I$3&$A6&$A9,IF({1,0},业绩报告!$A$2:$A$8229&业绩报告!$B$2:$B$8229&业绩报告!$C$2:$C$8229,业绩报告!$AL$2:$AL$8229),2,0),"0")} -> 0 | J41: =SUM(C41:I41) -> 131 | K41: {=IFERROR(VLOOKUP(K$3&$A6&$A9,IF({1,0},业绩报告!$A$2:$A$8229&业绩报告!$B$2:$B$8229&业绩报告!$C$2:$C$8229,业绩报告!$AL$2:$AL$8229),2,0),"")} -> 30 | L41: {=IFERROR(VLOOKUP(L$3&$A6&$A9,IF({1,0},业绩报告!$A$2:$A$8229&业绩报告!$B$2:$B$8229&业绩报告!$C$2:$C$8229,业绩报告!$AL$2:$AL$8229),2,0),"")} -> 46 | M41: {=IFERROR(VLOOKUP(M$3&$A6&$A9,IF({1,0},业绩报告!$A$2:$A$8229&业绩报告!$B$2:$B$8229&业绩报告!$C$2:$C$8229,业绩报告!$AL$2:$AL$8229),2,0),"")} -> 35 | N41: {=IFERROR(VLOOKUP(N$3&$A6&$A9,IF({1,0},业绩报告!$A$2:$A$8229&业绩报告!$B$2:$B$8229&业绩报告!$C$2:$C$8229,业绩报告!$AL$2:$AL$8229),2,0),"")} -> 41 | O41: {=IFERROR(VLOOKUP(O$3&$A6&$A9,IF({1,0},业绩报告!$A$2:$A$8229&业绩报告!$B$2:$B$8229&业绩报告!$C$2:$C$8229,业绩报告!$AL$2:$AL$8229),2,0),"")} -> 48 | P41: {=IFERROR(VLOOKUP(P$3&$A6&$A9,IF({1,0},业绩报告!$A$2:$A$8229&业绩报告!$B$2:$B$8229&业绩报告!$C$2:$C$8229,业绩报告!$AL$2:$AL$8229),2,0),"")} -> 44 | Q41: {=IFERROR(VLOOKUP(Q$3&$A6&$A9,IF({1,0},业绩报告!$A$2:$A$8229&业绩报告!$B$2:$B$8229&业绩报告!$C$2:$C$8229,业绩报告!$AL$2:$AL$8229),2,0),"")} -> 16 | R41: =SUM(K41:Q41) -> 260
B42: 自动单量 | C42: {=IFERROR(VLOOKUP(C$3&$A6&$A9,IF({1,0},业绩报告!$A$2:$A$8229&业绩报告!$B$2:$B$8229&业绩报告!$C$2:$C$8229,业绩报告!$AN$2:$AN$8229),2,0),"0")} -> 1 | D42: {=IFERROR(VLOOKUP(D$3&$A6&$A9,IF({1,0},业绩报告!$A$2:$A$8229&业绩报告!$B$2:$B$8229&业绩报告!$C$2:$C$8229,业绩报告!$AN$2:$AN$8229),2,0),"0")} -> 0 | E42: {=IFERROR(VLOOKUP(E$3&$A6&$A9,IF({1,0},业绩报告!$A$2:$A$8229&业绩报告!$B$2:$B$8229&业绩报告!$C$2:$C$8229,业绩报告!$AN$2:$AN$8229),2,0),"0")} -> 0 | F42: {=IFERROR(VLOOKUP(F$3&$A6&$A9,IF({1,0},业绩报告!$A$2:$A$8229&业绩报告!$B$2:$B$8229&业绩报告!$C$2:$C$8229,业绩报告!$AN$2:$AN$8229),2,0),"0")} -> 1 | G42: {=IFERROR(VLOOKUP(G$3&$A6&$A9,IF({1,0},业绩报告!$A$2:$A$8229&业绩报告!$B$2:$B$8229&业绩报告!$C$2:$C$8229,业绩报告!$AN$2:$AN$8229),2,0),"0")} -> 1 | H42: {=IFERROR(VLOOKUP(H$3&$A6&$A9,IF({1,0},业绩报告!$A$2:$A$8229&业绩报告!$B$2:$B$8229&业绩报告!$C$2:$C$8229,业绩报告!$AN$2:$AN$8229),2,0),"0")} -> 4 | I42: {=IFERROR(VLOOKUP(I$3&$A6&$A9,IF({1,0},业绩报告!$A$2:$A$8229&业绩报告!$B$2:$B$8229&业绩报告!$C$2:$C$8229,业绩报告!$AN$2:$AN$8229),2,0),"0")} -> 0 | J42: =SUM(C42:I42) -> 7 | K42: {=IFERROR(VLOOKUP(K$3&$A6&$A9,IF({1,0},业绩报告!$A$2:$A$8229&业绩报告!$B$2:$B$8229&业绩报告!$C$2:$C$8229,业绩报告!$AN$2:$AN$8229),2,0),"")} -> 0 | L42: {=IFERROR(VLOOKUP(L$3&$A6&$A9,IF({1,0},业绩报告!$A$2:$A$8229&业绩报告!$B$2:$B$8229&业绩报告!$C$2:$C$8229,业绩报告!$AN$2:$AN$8229),2,0),"")} -> 2 | M42: {=IFERROR(VLOOKUP(M$3&$A6&$A9,IF({1,0},业绩报告!$A$2:$A$8229&业绩报告!$B$2:$B$8229&业绩报告!$C$2:$C$8229,业绩报告!$AN$2:$AN$8229),2,0),"")} -> 3 | N42: {=IFERROR(VLOOKUP(N$3&$A6&$A9,IF({1,0},业绩报告!$A$2:$A$8229&业绩报告!$B$2:$B$8229&业绩报告!$C$2:$C$8229,业绩报告!$AN$2:$AN$8229),2,0),"")} -> 5 | O42: {=IFERROR(VLOOKUP(O$3&$A6&$A9,IF({1,0},业绩报告!$A$2:$A$8229&业绩报告!$B$2:$B$8229&业绩报告!$C$2:$C$8229,业绩报告!$AN$2:$AN$8229),2,0),"")} -> 1 | P42: {=IFERROR(VLOOKUP(P$3&$A6&$A9,IF({1,0},业绩报告!$A$2:$A$8229&业绩报告!$B$2:$B$8229&业绩报告!$C$2:$C$8229,业绩报告!$AN$2:$AN$8229),2,0),"")} -> 3 | Q42: {=IFERROR(VLOOKUP(Q$3&$A6&$A9,IF({1,0},业绩报告!$A$2:$A$8229&业绩报告!$B$2:$B$8229&业绩报告!$C$2:$C$8229,业绩报告!$AN$2:$AN$8229),2,0),"")} -> 0 | R42: =SUM(K42:Q42) -> 14
B43: 自动广告点击率 | C43: {=IFERROR(VLOOKUP(C$3&$A6&$A9,IF({1,0},业绩报告!$A$2:$A$8229&业绩报告!$B$2:$B$8229&业绩报告!$C$2:$C$8229,业绩报告!$AM$2:$AM$8229),2,0),"")} -> 0.0066634936 | D43: {=IFERROR(VLOOKUP(D$3&$A6&$A9,IF({1,0},业绩报告!$A$2:$A$8229&业绩报告!$B$2:$B$8229&业绩报告!$C$2:$C$8229,业绩报告!$AM$2:$AM$8229),2,0),"")} -> 0.0039463299 | E43: {=IFERROR(VLOOKUP(E$3&$A6&$A9,IF({1,0},业绩报告!$A$2:$A$8229&业绩报告!$B$2:$B$8229&业绩报告!$C$2:$C$8229,业绩报告!$AM$2:$AM$8229),2,0),"")} -> 0.0050697085 | F43: {=IFERROR(VLOOKUP(F$3&$A6&$A9,IF({1,0},业绩报告!$A$2:$A$8229&业绩报告!$B$2:$B$8229&业绩报告!$C$2:$C$8229,业绩报告!$AM$2:$AM$8229),2,0),"")} -> 0.0084182543 | G43: {=IFERROR(VLOOKUP(G$3&$A6&$A9,IF({1,0},业绩报告!$A$2:$A$8229&业绩报告!$B$2:$B$8229&业绩报告!$C$2:$C$8229,业绩报告!$AM$2:$AM$8229),2,0),"")} -> 0.0054227262 | H43: {=IFERROR(VLOOKUP(H$3&$A6&$A9,IF({1,0},业绩报告!$A$2:$A$8229&业绩报告!$B$2:$B$8229&业绩报告!$C$2:$C$8229,业绩报告!$AM$2:$AM$8229),2,0),"")} -> 0.0091954023 | I43: {=IFERROR(VLOOKUP(I$3&$A6&$A9,IF({1,0},业绩报告!$A$2:$A$8229&业绩报告!$B$2:$B$8229&业绩报告!$C$2:$C$8229,业绩报告!$AM$2:$AM$8229),2,0),"")} -> 0 | J43: =AVERAGE(C43:I43) -> 0.0064526525 | K43: {=IFERROR(VLOOKUP(K$3&$A6&$A9,IF({1,0},业绩报告!$A$2:$A$8229&业绩报告!$B$2:$B$8229&业绩报告!$C$2:$C$8229,业绩报告!$AM$2:$AM$8229),2,0),"")} -> 0.006533101 | L43: {=IFERROR(VLOOKUP(L$3&$A6&$A9,IF({1,0},业绩报告!$A$2:$A$8229&业绩报告!$B$2:$B$8229&业绩报告!$C$2:$C$8229,业绩报告!$AM$2:$AM$8229),2,0),"")} -> 0.0082054941 | M43: {=IFERROR(VLOOKUP(M$3&$A6&$A9,IF({1,0},业绩报告!$A$2:$A$8229&业绩报告!$B$2:$B$8229&业绩报告!$C$2:$C$8229,业绩报告!$AM$2:$AM$8229),2,0),"")} -> 0.0068911203 | N43: {=IFERROR(VLOOKUP(N$3&$A6&$A9,IF({1,0},业绩报告!$A$2:$A$8229&业绩报告!$B$2:$B$8229&业绩报告!$C$2:$C$8229,业绩报告!$AM$2:$AM$8229),2,0),"")} -> 0.0076123283 | O43: {=IFERROR(VLOOKUP(O$3&$A6&$A9,IF({1,0},业绩报告!$A$2:$A$8229&业绩报告!$B$2:$B$8229&业绩报告!$C$2:$C$8229,业绩报告!$AM$2:$AM$8229),2,0),"")} -> 0.0045104304 | P43: {=IFERROR(VLOOKUP(P$3&$A6&$A9,IF({1,0},业绩报告!$A$2:$A$8229&业绩报告!$B$2:$B$8229&业绩报告!$C$2:$C$8229,业绩报告!$AM$2:$AM$8229),2,0),"")} -> 0.0054173849 | Q43: {=IFERROR(VLOOKUP(Q$3&$A6&$A9,IF({1,0},业绩报告!$A$2:$A$8229&业绩报告!$B$2:$B$8229&业绩报告!$C$2:$C$8229,业绩报告!$AM$2:$AM$8229),2,0),"")} -> 0.0044855621 | R43: =AVERAGE(K43:Q43) -> 0.0062364887
B44: 自动广告转化率 | C44: {=IFERROR(VLOOKUP(C$3&$A6&$A9,IF({1,0},业绩报告!$A$2:$A$8229&业绩报告!$B$2:$B$8229&业绩报告!$C$2:$C$8229,业绩报告!$AO$2:$AO$8229),2,0),"0")} -> 0.035714286 | D44: {=IFERROR(VLOOKUP(D$3&$A6&$A9,IF({1,0},业绩报告!$A$2:$A$8229&业绩报告!$B$2:$B$8229&业绩报告!$C$2:$C$8229,业绩报告!$AO$2:$AO$8229),2,0),"0")} -> 0 | E44: {=IFERROR(VLOOKUP(E$3&$A6&$A9,IF({1,0},业绩报告!$A$2:$A$8229&业绩报告!$B$2:$B$8229&业绩报告!$C$2:$C$8229,业绩报告!$AO$2:$AO$8229),2,0),"0")} -> 0 | F44: {=IFERROR(VLOOKUP(F$3&$A6&$A9,IF({1,0},业绩报告!$A$2:$A$8229&业绩报告!$B$2:$B$8229&业绩报告!$C$2:$C$8229,业绩报告!$AO$2:$AO$8229),2,0),"0")} -> 0.052631579 | G44: {=IFERROR(VLOOKUP(G$3&$A6&$A9,IF({1,0},业绩报告!$A$2:$A$8229&业绩报告!$B$2:$B$8229&业绩报告!$C$2:$C$8229,业绩报告!$AO$2:$AO$8229),2,0),"0")} -> 0.045454545 | H44: {=IFERROR(VLOOKUP(H$3&$A6&$A9,IF({1,0},业绩报告!$A$2:$A$8229&业绩报告!$B$2:$B$8229&业绩报告!$C$2:$C$8229,业绩报告!$AO$2:$AO$8229),2,0),"0")} -> 0.11111111 | I44: {=IFERROR(VLOOKUP(I$3&$A6&$A9,IF({1,0},业绩报告!$A$2:$A$8229&业绩报告!$B$2:$B$8229&业绩报告!$C$2:$C$8229,业绩报告!$AO$2:$AO$8229),2,0),"0")} -> 0 | J44: =AVERAGE(C44:I44) -> 0.040818587 | K44: {=IFERROR(VLOOKUP(K$3&$A6&$A9,IF({1,0},业绩报告!$A$2:$A$8229&业绩报告!$B$2:$B$8229&业绩报告!$C$2:$C$8229,业绩报告!$AO$2:$AO$8229),2,0),"0")} -> 0 | L44: {=IFERROR(VLOOKUP(L$3&$A6&$A9,IF({1,0},业绩报告!$A$2:$A$8229&业绩报告!$B$2:$B$8229&业绩报告!$C$2:$C$8229,业绩报告!$AO$2:$AO$8229),2,0),"0")} -> 0.043478261 | M44: {=IFERROR(VLOOKUP(M$3&$A6&$A9,IF({1,0},业绩报告!$A$2:$A$8229&业绩报告!$B$2:$B$8229&业绩报告!$C$2:$C$8229,业绩报告!$AO$2:$AO$8229),2,0),"0")} -> 0.085714286 | N44: {=IFERROR(VLOOKUP(N$3&$A6&$A9,IF({1,0},业绩报告!$A$2:$A$8229&业绩报告!$B$2:$B$8229&业绩报告!$C$2:$C$8229,业绩报告!$AO$2:$AO$8229),2,0),"0")} -> 0.12195122 | O44: {=IFERROR(VLOOKUP(O$3&$A6&$A9,IF({1,0},业绩报告!$A$2:$A$8229&业绩报告!$B$2:$B$8229&业绩报告!$C$2:$C$8229,业绩报告!$AO$2:$AO$8229),2,0),"0")} -> 0.020833333 | P44: {=IFERROR(VLOOKUP(P$3&$A6&$A9,IF({1,0},业绩报告!$A$2:$A$8229&业绩报告!$B$2:$B$8229&业绩报告!$C$2:$C$8229,业绩报告!$AO$2:$AO$8229),2,0),"0")} -> 0.068181818 | Q44: {=IFERROR(VLOOKUP(Q$3&$A6&$A9,IF({1,0},业绩报告!$A$2:$A$8229&业绩报告!$B$2:$B$8229&业绩报告!$C$2:$C$8229,业绩报告!$AO$2:$AO$8229),2,0),"0")} -> 0 | R44: =AVERAGE(K44:Q44) -> 0.048594131
B45: 自动广告花费 | C45: {=IFERROR(VLOOKUP(C$3&$A6&$A9,IF({1,0},业绩报告!$A$2:$A$8229&业绩报告!$B$2:$B$8229&业绩报告!$C$2:$C$8229,业绩报告!$AP$2:$AP$8229),2,0),"0")} -> 8.14 | D45: {=IFERROR(VLOOKUP(D$3&$A6&$A9,IF({1,0},业绩报告!$A$2:$A$8229&业绩报告!$B$2:$B$8229&业绩报告!$C$2:$C$8229,业绩报告!$AP$2:$AP$8229),2,0),"0")} -> 2.38 | E45: {=IFERROR(VLOOKUP(E$3&$A6&$A9,IF({1,0},业绩报告!$A$2:$A$8229&业绩报告!$B$2:$B$8229&业绩报告!$C$2:$C$8229,业绩报告!$AP$2:$AP$8229),2,0),"0")} -> 3.85 | F45: {=IFERROR(VLOOKUP(F$3&$A6&$A9,IF({1,0},业绩报告!$A$2:$A$8229&业绩报告!$B$2:$B$8229&业绩报告!$C$2:$C$8229,业绩报告!$AP$2:$AP$8229),2,0),"0")} -> 4.75 | G45: {=IFERROR(VLOOKUP(G$3&$A6&$A9,IF({1,0},业绩报告!$A$2:$A$8229&业绩报告!$B$2:$B$8229&业绩报告!$C$2:$C$8229,业绩报告!$AP$2:$AP$8229),2,0),"0")} -> 5.12 | H45: {=IFERROR(VLOOKUP(H$3&$A6&$A9,IF({1,0},业绩报告!$A$2:$A$8229&业绩报告!$B$2:$B$8229&业绩报告!$C$2:$C$8229,业绩报告!$AP$2:$AP$8229),2,0),"0")} -> 8.63 | I45: {=IFERROR(VLOOKUP(I$3&$A6&$A9,IF({1,0},业绩报告!$A$2:$A$8229&业绩报告!$B$2:$B$8229&业绩报告!$C$2:$C$8229,业绩报告!$AP$2:$AP$8229),2,0),"0")} -> 0 | J45: =SUM(C45:I45) -> 32.87 | K45: {=IFERROR(VLOOKUP(K$3&$A6&$A9,IF({1,0},业绩报告!$A$2:$A$8229&业绩报告!$B$2:$B$8229&业绩报告!$C$2:$C$8229,业绩报告!$AP$2:$AP$8229),2,0),"")} -> 8.49 | L45: {=IFERROR(VLOOKUP(L$3&$A6&$A9,IF({1,0},业绩报告!$A$2:$A$8229&业绩报告!$B$2:$B$8229&业绩报告!$C$2:$C$8229,业绩报告!$AP$2:$AP$8229),2,0),"")} -> 14.54 | M45: {=IFERROR(VLOOKUP(M$3&$A6&$A9,IF({1,0},业绩报告!$A$2:$A$8229&业绩报告!$B$2:$B$8229&业绩报告!$C$2:$C$8229,业绩报告!$AP$2:$AP$8229),2,0),"")} -> 10.77 | N45: {=IFERROR(VLOOKUP(N$3&$A6&$A9,IF({1,0},业绩报告!$A$2:$A$8229&业绩报告!$B$2:$B$8229&业绩报告!$C$2:$C$8229,业绩报告!$AP$2:$AP$8229),2,0),"")} -> 11.97 | O45: {=IFERROR(VLOOKUP(O$3&$A6&$A9,IF({1,0},业绩报告!$A$2:$A$8229&业绩报告!$B$2:$B$8229&业绩报告!$C$2:$C$8229,业绩报告!$AP$2:$AP$8229),2,0),"")} -> 14.27 | P45: {=IFERROR(VLOOKUP(P$3&$A6&$A9,IF({1,0},业绩报告!$A$2:$A$8229&业绩报告!$B$2:$B$8229&业绩报告!$C$2:$C$8229,业绩报告!$AP$2:$AP$8229),2,0),"")} -> 13.17 | Q45: {=IFERROR(VLOOKUP(Q$3&$A6&$A9,IF({1,0},业绩报告!$A$2:$A$8229&业绩报告!$B$2:$B$8229&业绩报告!$C$2:$C$8229,业绩报告!$AP$2:$AP$8229),2,0),"")} -> 4.93 | R45: =SUM(K45:Q45) -> 78.14
B46: 自动acos | C46: {=IFERROR(VLOOKUP(C$3&$A6&$A9,IF({1,0},业绩报告!$A$2:$A$8229&业绩报告!$B$2:$B$8229&业绩报告!$C$2:$C$8229,业绩报告!$AR$2:$AR$8229),2,0),"")} -> 0.67889908 | D46: {=IFERROR(VLOOKUP(D$3&$A6&$A9,IF({1,0},业绩报告!$A$2:$A$8229&业绩报告!$B$2:$B$8229&业绩报告!$C$2:$C$8229,业绩报告!$AR$2:$AR$8229),2,0),"")} -> 0 | E46: {=IFERROR(VLOOKUP(E$3&$A6&$A9,IF({1,0},业绩报告!$A$2:$A$8229&业绩报告!$B$2:$B$8229&业绩报告!$C$2:$C$8229,业绩报告!$AR$2:$AR$8229),2,0),"")} -> 0 | F46: {=IFERROR(VLOOKUP(F$3&$A6&$A9,IF({1,0},业绩报告!$A$2:$A$8229&业绩报告!$B$2:$B$8229&业绩报告!$C$2:$C$8229,业绩报告!$AR$2:$AR$8229),2,0),"")} -> 0.39616347 | G46: {=IFERROR(VLOOKUP(G$3&$A6&$A9,IF({1,0},业绩报告!$A$2:$A$8229&业绩报告!$B$2:$B$8229&业绩报告!$C$2:$C$8229,业绩报告!$AR$2:$AR$8229),2,0),"")} -> 0.53388947 | H46: {=IFERROR(VLOOKUP(H$3&$A6&$A9,IF({1,0},业绩报告!$A$2:$A$8229&业绩报告!$B$2:$B$8229&业绩报告!$C$2:$C$8229,业绩报告!$AR$2:$AR$8229),2,0),"")} -> 0.22497393 | I46: {=IFERROR(VLOOKUP(I$3&$A6&$A9,IF({1,0},业绩报告!$A$2:$A$8229&业绩报告!$B$2:$B$8229&业绩报告!$C$2:$C$8229,业绩报告!$AR$2:$AR$8229),2,0),"")} -> 0 | J46: =J45/J47 -> 0.54838172 | K46: {=IFERROR(VLOOKUP(K$3&$A6&$A9,IF({1,0},业绩报告!$A$2:$A$8229&业绩报告!$B$2:$B$8229&业绩报告!$C$2:$C$8229,业绩报告!$AR$2:$AR$8229),2,0),"")} -> 0 | L46: {=IFERROR(VLOOKUP(L$3&$A6&$A9,IF({1,0},业绩报告!$A$2:$A$8229&业绩报告!$B$2:$B$8229&业绩报告!$C$2:$C$8229,业绩报告!$AR$2:$AR$8229),2,0),"")} -> 0.60633862 | M46: {=IFERROR(VLOOKUP(M$3&$A6&$A9,IF({1,0},业绩报告!$A$2:$A$8229&业绩报告!$B$2:$B$8229&业绩报告!$C$2:$C$8229,业绩报告!$AR$2:$AR$8229),2,0),"")} -> 0.29941618 | N46: {=IFERROR(VLOOKUP(N$3&$A6&$A9,IF({1,0},业绩报告!$A$2:$A$8229&业绩报告!$B$2:$B$8229&业绩报告!$C$2:$C$8229,业绩报告!$AR$2:$AR$8229),2,0),"")} -> 0.19966639 | O46: {=IFERROR(VLOOKUP(O$3&$A6&$A9,IF({1,0},业绩报告!$A$2:$A$8229&业绩报告!$B$2:$B$8229&业绩报告!$C$2:$C$8229,业绩报告!$AR$2:$AR$8229),2,0),"")} -> 1.1901585 | P46: {=IFERROR(VLOOKUP(P$3&$A6&$A9,IF({1,0},业绩报告!$A$2:$A$8229&业绩报告!$B$2:$B$8229&业绩报告!$C$2:$C$8229,业绩报告!$AR$2:$AR$8229),2,0),"")} -> 0.36613845 | Q46: {=IFERROR(VLOOKUP(Q$3&$A6&$A9,IF({1,0},业绩报告!$A$2:$A$8229&业绩报告!$B$2:$B$8229&业绩报告!$C$2:$C$8229,业绩报告!$AR$2:$AR$8229),2,0),"")} -> 0 | R46: =R45/R47 -> 0.46550697
B47: 自动广告销售额 | C47: {=IFERROR(VLOOKUP(C$3&$A6&$A9,IF({1,0},业绩报告!$A$2:$A$8229&业绩报告!$B$2:$B$8229&业绩报告!$C$2:$C$8229,业绩报告!$AQ$2:$AQ$8229),2,0),"0")} -> 11.99 | D47: {=IFERROR(VLOOKUP(D$3&$A6&$A9,IF({1,0},业绩报告!$A$2:$A$8229&业绩报告!$B$2:$B$8229&业绩报告!$C$2:$C$8229,业绩报告!$AQ$2:$AQ$8229),2,0),"0")} -> 0 | E47: {=IFERROR(VLOOKUP(E$3&$A6&$A9,IF({1,0},业绩报告!$A$2:$A$8229&业绩报告!$B$2:$B$8229&业绩报告!$C$2:$C$8229,业绩报告!$AQ$2:$AQ$8229),2,0),"0")} -> 0 | F47: =IFERROR(VLOOKUP(F$3&$A6&$A9,IF({1,0},业绩报告!$A$2:$A$8229&业绩报告!$B$2:$B$8229&业绩报告!$C$2:$C$8229,业绩报告!$AQ$2:$AQ$8229),2,0),"0") -> 0 | G47: {=IFERROR(VLOOKUP(G$3&$A6&$A9,IF({1,0},业绩报告!$A$2:$A$8229&业绩报告!$B$2:$B$8229&业绩报告!$C$2:$C$8229,业绩报告!$AQ$2:$AQ$8229),2,0),"0")} -> 9.59 | H47: {=IFERROR(VLOOKUP(H$3&$A6&$A9,IF({1,0},业绩报告!$A$2:$A$8229&业绩报告!$B$2:$B$8229&业绩报告!$C$2:$C$8229,业绩报告!$AQ$2:$AQ$8229),2,0),"0")} -> 38.36 | I47: {=IFERROR(VLOOKUP(I$3&$A6&$A9,IF({1,0},业绩报告!$A$2:$A$8229&业绩报告!$B$2:$B$8229&业绩报告!$C$2:$C$8229,业绩报告!$AQ$2:$AQ$8229),2,0),"0")} -> 0 | J47: =SUM(C47:I47) -> 59.94 | K47: {=IFERROR(VLOOKUP(K$3&$A6&$A9,IF({1,0},业绩报告!$A$2:$A$8229&业绩报告!$B$2:$B$8229&业绩报告!$C$2:$C$8229,业绩报告!$AQ$2:$AQ$8229),2,0),"")} -> 0 | L47: {=IFERROR(VLOOKUP(L$3&$A6&$A9,IF({1,0},业绩报告!$A$2:$A$8229&业绩报告!$B$2:$B$8229&业绩报告!$C$2:$C$8229,业绩报告!$AQ$2:$AQ$8229),2,0),"")} -> 23.98 | M47: {=IFERROR(VLOOKUP(M$3&$A6&$A9,IF({1,0},业绩报告!$A$2:$A$8229&业绩报告!$B$2:$B$8229&业绩报告!$C$2:$C$8229,业绩报告!$AQ$2:$AQ$8229),2,0),"")} -> 35.97 | N47: {=IFERROR(VLOOKUP(N$3&$A6&$A9,IF({1,0},业绩报告!$A$2:$A$8229&业绩报告!$B$2:$B$8229&业绩报告!$C$2:$C$8229,业绩报告!$AQ$2:$AQ$8229),2,0),"")} -> 59.95 | O47: {=IFERROR(VLOOKUP(O$3&$A6&$A9,IF({1,0},业绩报告!$A$2:$A$8229&业绩报告!$B$2:$B$8229&业绩报告!$C$2:$C$8229,业绩报告!$AQ$2:$AQ$8229),2,0),"")} -> 11.99 | P47: {=IFERROR(VLOOKUP(P$3&$A6&$A9,IF({1,0},业绩报告!$A$2:$A$8229&业绩报告!$B$2:$B$8229&业绩报告!$C$2:$C$8229,业绩报告!$AQ$2:$AQ$8229),2,0),"")} -> 35.97 | Q47: {=IFERROR(VLOOKUP(Q$3&$A6&$A9,IF({1,0},业绩报告!$A$2:$A$8229&业绩报告!$B$2:$B$8229&业绩报告!$C$2:$C$8229,业绩报告!$AQ$2:$AQ$8229),2,0),"")} -> 0 | R47: =SUM(K47:Q47) -> 167.86
B48: 视频广告曝光量 | C48: {=IFERROR(VLOOKUP(C$3&$A6&$A9,IF({1,0},业绩报告!$A$2:$A$8229&业绩报告!$B$2:$B$8229&业绩报告!$C$2:$C$8229,业绩报告!$AS$2:$AS$8229),2,0),"")} -> 0 | D48: {=IFERROR(VLOOKUP(D$3&$A6&$A9,IF({1,0},业绩报告!$A$2:$A$8229&业绩报告!$B$2:$B$8229&业绩报告!$C$2:$C$8229,业绩报告!$AS$2:$AS$8229),2,0),"")} -> 0 | E48: {=IFERROR(VLOOKUP(E$3&$A6&$A9,IF({1,0},业绩报告!$A$2:$A$8229&业绩报告!$B$2:$B$8229&业绩报告!$C$2:$C$8229,业绩报告!$AS$2:$AS$8229),2,0),"")} -> 0 | F48: {=IFERROR(VLOOKUP(F$3&$A6&$A9,IF({1,0},业绩报告!$A$2:$A$8229&业绩报告!$B$2:$B$8229&业绩报告!$C$2:$C$8229,业绩报告!$AS$2:$AS$8229),2,0),"")} -> 0 | G48: {=IFERROR(VLOOKUP(G$3&$A6&$A9,IF({1,0},业绩报告!$A$2:$A$8229&业绩报告!$B$2:$B$8229&业绩报告!$C$2:$C$8229,业绩报告!$AS$2:$AS$8229),2,0),"")} -> 0 | H48: {=IFERROR(VLOOKUP(H$3&$A6&$A9,IF({1,0},业绩报告!$A$2:$A$8229&业绩报告!$B$2:$B$8229&业绩报告!$C$2:$C$8229,业绩报告!$AS$2:$AS$8229),2,0),"")} -> 0 | I48: {=IFERROR(VLOOKUP(I$3&$A6&$A9,IF({1,0},业绩报告!$A$2:$A$8229&业绩报告!$B$2:$B$8229&业绩报告!$C$2:$C$8229,业绩报告!$AS$2:$AS$8229),2,0),"")} -> 0 | J48: =SUM(C48:I48) -> 0 | K48: {=IFERROR(VLOOKUP(K$3&$A6&$A9,IF({1,0},业绩报告!$A$2:$A$8229&业绩报告!$B$2:$B$8229&业绩报告!$C$2:$C$8229,业绩报告!$AS$2:$AS$8229),2,0),"")} -> 0 | L48: {=IFERROR(VLOOKUP(L$3&$A6&$A9,IF({1,0},业绩报告!$A$2:$A$8229&业绩报告!$B$2:$B$8229&业绩报告!$C$2:$C$8229,业绩报告!$AS$2:$AS$8229),2,0),"")} -> 0 | M48: {=IFERROR(VLOOKUP(M$3&$A6&$A9,IF({1,0},业绩报告!$A$2:$A$8229&业绩报告!$B$2:$B$8229&业绩报告!$C$2:$C$8229,业绩报告!$AS$2:$AS$8229),2,0),"")} -> 0 | N48: {=IFERROR(VLOOKUP(N$3&$A6&$A9,IF({1,0},业绩报告!$A$2:$A$8229&业绩报告!$B$2:$B$8229&业绩报告!$C$2:$C$8229,业绩报告!$AS$2:$AS$8229),2,0),"")} -> 0 | O48: {=IFERROR(VLOOKUP(O$3&$A6&$A9,IF({1,0},业绩报告!$A$2:$A$8229&业绩报告!$B$2:$B$8229&业绩报告!$C$2:$C$8229,业绩报告!$AS$2:$AS$8229),2,0),"")} -> 0 | P48: {=IFERROR(VLOOKUP(P$3&$A6&$A9,IF({1,0},业绩报告!$A$2:$A$8229&业绩报告!$B$2:$B$8229&业绩报告!$C$2:$C$8229,业绩报告!$AS$2:$AS$8229),2,0),"")} -> 0 | Q48: {=IFERROR(VLOOKUP(Q$3&$A6&$A9,IF({1,0},业绩报告!$A$2:$A$8229&业绩报告!$B$2:$B$8229&业绩报告!$C$2:$C$8229,业绩报告!$AS$2:$AS$8229),2,0),"")} -> 0 | R48: =SUM(K48:Q48) -> 0
B49: 视频广告点击量 | C49: {=IFERROR(VLOOKUP(C$3&$A6&$A9,IF({1,0},业绩报告!$A$2:$A$8229&业绩报告!$B$2:$B$8229&业绩报告!$C$2:$C$8229,业绩报告!$AT$2:$AT$8229),2,0),"")} -> 0 | D49: {=IFERROR(VLOOKUP(D$3&$A6&$A9,IF({1,0},业绩报告!$A$2:$A$8229&业绩报告!$B$2:$B$8229&业绩报告!$C$2:$C$8229,业绩报告!$AT$2:$AT$8229),2,0),"")} -> 0 | E49: {=IFERROR(VLOOKUP(E$3&$A6&$A9,IF({1,0},业绩报告!$A$2:$A$8229&业绩报告!$B$2:$B$8229&业绩报告!$C$2:$C$8229,业绩报告!$AT$2:$AT$8229),2,0),"")} -> 0 | F49: {=IFERROR(VLOOKUP(F$3&$A6&$A9,IF({1,0},业绩报告!$A$2:$A$8229&业绩报告!$B$2:$B$8229&业绩报告!$C$2:$C$8229,业绩报告!$AT$2:$AT$8229),2,0),"")} -> 0 | G49: {=IFERROR(VLOOKUP(G$3&$A6&$A9,IF({1,0},业绩报告!$A$2:$A$8229&业绩报告!$B$2:$B$8229&业绩报告!$C$2:$C$8229,业绩报告!$AT$2:$AT$8229),2,0),"")} -> 0 | H49: {=IFERROR(VLOOKUP(H$3&$A6&$A9,IF({1,0},业绩报告!$A$2:$A$8229&业绩报告!$B$2:$B$8229&业绩报告!$C$2:$C$8229,业绩报告!$AT$2:$AT$8229),2,0),"")} -> 0 | I49: {=IFERROR(VLOOKUP(I$3&$A6&$A9,IF({1,0},业绩报告!$A$2:$A$8229&业绩报告!$B$2:$B$8229&业绩报告!$C$2:$C$8229,业绩报告!$AT$2:$AT$8229),2,0),"")} -> 0 | J49: =SUM(C49:I49) -> 0 | K49: {=IFERROR(VLOOKUP(K$3&$A6&$A9,IF({1,0},业绩报告!$A$2:$A$8229&业绩报告!$B$2:$B$8229&业绩报告!$C$2:$C$8229,业绩报告!$AT$2:$AT$8229),2,0),"")} -> 0 | L49: {=IFERROR(VLOOKUP(L$3&$A6&$A9,IF({1,0},业绩报告!$A$2:$A$8229&业绩报告!$B$2:$B$8229&业绩报告!$C$2:$C$8229,业绩报告!$AT$2:$AT$8229),2,0),"")} -> 0 | M49: {=IFERROR(VLOOKUP(M$3&$A6&$A9,IF({1,0},业绩报告!$A$2:$A$8229&业绩报告!$B$2:$B$8229&业绩报告!$C$2:$C$8229,业绩报告!$AT$2:$AT$8229),2,0),"")} -> 0 | N49: {=IFERROR(VLOOKUP(N$3&$A6&$A9,IF({1,0},业绩报告!$A$2:$A$8229&业绩报告!$B$2:$B$8229&业绩报告!$C$2:$C$8229,业绩报告!$AT$2:$AT$8229),2,0),"")} -> 0 | O49: {=IFERROR(VLOOKUP(O$3&$A6&$A9,IF({1,0},业绩报告!$A$2:$A$8229&业绩报告!$B$2:$B$8229&业绩报告!$C$2:$C$8229,业绩报告!$AT$2:$AT$8229),2,0),"")} -> 0 | P49: {=IFERROR(VLOOKUP(P$3&$A6&$A9,IF({1,0},业绩报告!$A$2:$A$8229&业绩报告!$B$2:$B$8229&业绩报告!$C$2:$C$8229,业绩报告!$AT$2:$AT$8229),2,0),"")} -> 0 | Q49: {=IFERROR(VLOOKUP(Q$3&$A6&$A9,IF({1,0},业绩报告!$A$2:$A$8229&业绩报告!$B$2:$B$8229&业绩报告!$C$2:$C$8229,业绩报告!$AT$2:$AT$8229),2,0),"")} -> 0 | R49: =SUM(K49:Q49) -> 0
B50: 视频单量 | C50: {=IFERROR(VLOOKUP(C$3&$A6&$A9,IF({1,0},业绩报告!$A$2:$A$8229&业绩报告!$B$2:$B$8229&业绩报告!$C$2:$C$8229,业绩报告!$AU$2:$AU$8229),2,0),"")} -> 0 | D50: {=IFERROR(VLOOKUP(D$3&$A6&$A9,IF({1,0},业绩报告!$A$2:$A$8229&业绩报告!$B$2:$B$8229&业绩报告!$C$2:$C$8229,业绩报告!$AU$2:$AU$8229),2,0),"")} -> 0 | E50: {=IFERROR(VLOOKUP(E$3&$A6&$A9,IF({1,0},业绩报告!$A$2:$A$8229&业绩报告!$B$2:$B$8229&业绩报告!$C$2:$C$8229,业绩报告!$AU$2:$AU$8229),2,0),"")} -> 0 | F50: {=IFERROR(VLOOKUP(F$3&$A6&$A9,IF({1,0},业绩报告!$A$2:$A$8229&业绩报告!$B$2:$B$8229&业绩报告!$C$2:$C$8229,业绩报告!$AU$2:$AU$8229),2,0),"")} -> 0 | G50: {=IFERROR(VLOOKUP(G$3&$A6&$A9,IF({1,0},业绩报告!$A$2:$A$8229&业绩报告!$B$2:$B$8229&业绩报告!$C$2:$C$8229,业绩报告!$AU$2:$AU$8229),2,0),"")} -> 0 | H50: {=IFERROR(VLOOKUP(H$3&$A6&$A9,IF({1,0},业绩报告!$A$2:$A$8229&业绩报告!$B$2:$B$8229&业绩报告!$C$2:$C$8229,业绩报告!$AU$2:$AU$8229),2,0),"")} -> 0 | I50: {=IFERROR(VLOOKUP(I$3&$A6&$A9,IF({1,0},业绩报告!$A$2:$A$8229&业绩报告!$B$2:$B$8229&业绩报告!$C$2:$C$8229,业绩报告!$AU$2:$AU$8229),2,0),"")} -> 0 | J50: =SUM(C50:I50) -> 0 | K50: {=IFERROR(VLOOKUP(K$3&$A6&$A9,IF({1,0},业绩报告!$A$2:$A$8229&业绩报告!$B$2:$B$8229&业绩报告!$C$2:$C$8229,业绩报告!$AU$2:$AU$8229),2,0),"")} -> 0 | L50: {=IFERROR(VLOOKUP(L$3&$A6&$A9,IF({1,0},业绩报告!$A$2:$A$8229&业绩报告!$B$2:$B$8229&业绩报告!$C$2:$C$8229,业绩报告!$AU$2:$AU$8229),2,0),"")} -> 0 | M50: {=IFERROR(VLOOKUP(M$3&$A6&$A9,IF({1,0},业绩报告!$A$2:$A$8229&业绩报告!$B$2:$B$8229&业绩报告!$C$2:$C$8229,业绩报告!$AU$2:$AU$8229),2,0),"")} -> 0 | N50: {=IFERROR(VLOOKUP(N$3&$A6&$A9,IF({1,0},业绩报告!$A$2:$A$8229&业绩报告!$B$2:$B$8229&业绩报告!$C$2:$C$8229,业绩报告!$AU$2:$AU$8229),2,0),"")} -> 0 | O50: {=IFERROR(VLOOKUP(O$3&$A6&$A9,IF({1,0},业绩报告!$A$2:$A$8229&业绩报告!$B$2:$B$8229&业绩报告!$C$2:$C$8229,业绩报告!$AU$2:$AU$8229),2,0),"")} -> 0 | P50: {=IFERROR(VLOOKUP(P$3&$A6&$A9,IF({1,0},业绩报告!$A$2:$A$8229&业绩报告!$B$2:$B$8229&业绩报告!$C$2:$C$8229,业绩报告!$AU$2:$AU$8229),2,0),"")} -> 0 | Q50: {=IFERROR(VLOOKUP(Q$3&$A6&$A9,IF({1,0},业绩报告!$A$2:$A$8229&业绩报告!$B$2:$B$8229&业绩报告!$C$2:$C$8229,业绩报告!$AU$2:$AU$8229),2,0),"")} -> 0 | R50: =SUM(K50:Q50) -> 0
B51: 视频广告点击率 | C51: {=IFERROR(VLOOKUP(C$3&$A6&$A9,IF({1,0},业绩报告!$A$2:$A$8229&业绩报告!$B$2:$B$8229&业绩报告!$C$2:$C$8229,业绩报告!$AV$2:$AV$8229),2,0),"")} -> 0 | D51: {=IFERROR(VLOOKUP(D$3&$A6&$A9,IF({1,0},业绩报告!$A$2:$A$8229&业绩报告!$B$2:$B$8229&业绩报告!$C$2:$C$8229,业绩报告!$AV$2:$AV$8229),2,0),"")} -> 0 | E51: {=IFERROR(VLOOKUP(E$3&$A6&$A9,IF({1,0},业绩报告!$A$2:$A$8229&业绩报告!$B$2:$B$8229&业绩报告!$C$2:$C$8229,业绩报告!$AV$2:$AV$8229),2,0),"")} -> 0 | F51: {=IFERROR(VLOOKUP(F$3&$A6&$A9,IF({1,0},业绩报告!$A$2:$A$8229&业绩报告!$B$2:$B$8229&业绩报告!$C$2:$C$8229,业绩报告!$AV$2:$AV$8229),2,0),"")} -> 0 | G51: {=IFERROR(VLOOKUP(G$3&$A6&$A9,IF({1,0},业绩报告!$A$2:$A$8229&业绩报告!$B$2:$B$8229&业绩报告!$C$2:$C$8229,业绩报告!$AV$2:$AV$8229),2,0),"")} -> 0 | H51: {=IFERROR(VLOOKUP(H$3&$A6&$A9,IF({1,0},业绩报告!$A$2:$A$8229&业绩报告!$B$2:$B$8229&业绩报告!$C$2:$C$8229,业绩报告!$AV$2:$AV$8229),2,0),"")} -> 0 | I51: {=IFERROR(VLOOKUP(I$3&$A6&$A9,IF({1,0},业绩报告!$A$2:$A$8229&业绩报告!$B$2:$B$8229&业绩报告!$C$2:$C$8229,业绩报告!$AV$2:$AV$8229),2,0),"")} -> 0 | J51: =AVERAGE(C51:I51) -> #DIV/0! | K51: {=IFERROR(VLOOKUP(K$3&$A6&$A9,IF({1,0},业绩报告!$A$2:$A$8229&业绩报告!$B$2:$B$8229&业绩报告!$C$2:$C$8229,业绩报告!$AV$2:$AV$8229),2,0),"")} -> 0 | L51: {=IFERROR(VLOOKUP(L$3&$A6&$A9,IF({1,0},业绩报告!$A$2:$A$8229&业绩报告!$B$2:$B$8229&业绩报告!$C$2:$C$8229,业绩报告!$AV$2:$AV$8229),2,0),"")} -> 0 | M51: {=IFERROR(VLOOKUP(M$3&$A6&$A9,IF({1,0},业绩报告!$A$2:$A$8229&业绩报告!$B$2:$B$8229&业绩报告!$C$2:$C$8229,业绩报告!$AV$2:$AV$8229),2,0),"")} -> 0 | N51: {=IFERROR(VLOOKUP(N$3&$A6&$A9,IF({1,0},业绩报告!$A$2:$A$8229&业绩报告!$B$2:$B$8229&业绩报告!$C$2:$C$8229,业绩报告!$AV$2:$AV$8229),2,0),"")} -> 0 | O51: {=IFERROR(VLOOKUP(O$3&$A6&$A9,IF({1,0},业绩报告!$A$2:$A$8229&业绩报告!$B$2:$B$8229&业绩报告!$C$2:$C$8229,业绩报告!$AV$2:$AV$8229),2,0),"")} -> 0 | P51: {=IFERROR(VLOOKUP(P$3&$A6&$A9,IF({1,0},业绩报告!$A$2:$A$8229&业绩报告!$B$2:$B$8229&业绩报告!$C$2:$C$8229,业绩报告!$AV$2:$AV$8229),2,0),"")} -> 0 | Q51: {=IFERROR(VLOOKUP(Q$3&$A6&$A9,IF({1,0},业绩报告!$A$2:$A$8229&业绩报告!$B$2:$B$8229&业绩报告!$C$2:$C$8229,业绩报告!$AV$2:$AV$8229),2,0),"")} -> 0 | R51: =AVERAGE(K51:Q51) -> #DIV/0!
B52: 视频广告转化率 | C52: {=IFERROR(VLOOKUP(C$3&$A6&$A9,IF({1,0},业绩报告!$A$2:$A$8229&业绩报告!$B$2:$B$8229&业绩报告!$C$2:$C$8229,业绩报告!$AW$2:$AW$8229),2,0),"")} -> 0 | D52: {=IFERROR(VLOOKUP(D$3&$A6&$A9,IF({1,0},业绩报告!$A$2:$A$8229&业绩报告!$B$2:$B$8229&业绩报告!$C$2:$C$8229,业绩报告!$AW$2:$AW$8229),2,0),"")} -> 0 | E52: {=IFERROR(VLOOKUP(E$3&$A6&$A9,IF({1,0},业绩报告!$A$2:$A$8229&业绩报告!$B$2:$B$8229&业绩报告!$C$2:$C$8229,业绩报告!$AW$2:$AW$8229),2,0),"")} -> 0 | F52: {=IFERROR(VLOOKUP(F$3&$A6&$A9,IF({1,0},业绩报告!$A$2:$A$8229&业绩报告!$B$2:$B$8229&业绩报告!$C$2:$C$8229,业绩报告!$AW$2:$AW$8229),2,0),"")} -> 0 | G52: {=IFERROR(VLOOKUP(G$3&$A6&$A9,IF({1,0},业绩报告!$A$2:$A$8229&业绩报告!$B$2:$B$8229&业绩报告!$C$2:$C$8229,业绩报告!$AW$2:$AW$8229),2,0),"")} -> 0 | H52: {=IFERROR(VLOOKUP(H$3&$A6&$A9,IF({1,0},业绩报告!$A$2:$A$8229&业绩报告!$B$2:$B$8229&业绩报告!$C$2:$C$8229,业绩报告!$AW$2:$AW$8229),2,0),"")} -> 0 | I52: {=IFERROR(VLOOKUP(I$3&$A6&$A9,IF({1,0},业绩报告!$A$2:$A$8229&业绩报告!$B$2:$B$8229&业绩报告!$C$2:$C$8229,业绩报告!$AW$2:$AW$8229),2,0),"")} -> 0 | J52: =AVERAGE(C52:I52) -> #DIV/0! | K52: {=IFERROR(VLOOKUP(K$3&$A6&$A9,IF({1,0},业绩报告!$A$2:$A$8229&业绩报告!$B$2:$B$8229&业绩报告!$C$2:$C$8229,业绩报告!$AW$2:$AW$8229),2,0),"")} -> 0 | L52: {=IFERROR(VLOOKUP(L$3&$A6&$A9,IF({1,0},业绩报告!$A$2:$A$8229&业绩报告!$B$2:$B$8229&业绩报告!$C$2:$C$8229,业绩报告!$AW$2:$AW$8229),2,0),"")} -> 0 | M52: {=IFERROR(VLOOKUP(M$3&$A6&$A9,IF({1,0},业绩报告!$A$2:$A$8229&业绩报告!$B$2:$B$8229&业绩报告!$C$2:$C$8229,业绩报告!$AW$2:$AW$8229),2,0),"")} -> 0 | N52: {=IFERROR(VLOOKUP(N$3&$A6&$A9,IF({1,0},业绩报告!$A$2:$A$8229&业绩报告!$B$2:$B$8229&业绩报告!$C$2:$C$8229,业绩报告!$AW$2:$AW$8229),2,0),"")} -> 0 | O52: {=IFERROR(VLOOKUP(O$3&$A6&$A9,IF({1,0},业绩报告!$A$2:$A$8229&业绩报告!$B$2:$B$8229&业绩报告!$C$2:$C$8229,业绩报告!$AW$2:$AW$8229),2,0),"")} -> 0 | P52: {=IFERROR(VLOOKUP(P$3&$A6&$A9,IF({1,0},业绩报告!$A$2:$A$8229&业绩报告!$B$2:$B$8229&业绩报告!$C$2:$C$8229,业绩报告!$AW$2:$AW$8229),2,0),"")} -> 0 | Q52: {=IFERROR(VLOOKUP(Q$3&$A6&$A9,IF({1,0},业绩报告!$A$2:$A$8229&业绩报告!$B$2:$B$8229&业绩报告!$C$2:$C$8229,业绩报告!$AW$2:$AW$8229),2,0),"")} -> 0 | R52: =AVERAGE(K52:Q52) -> #DIV/0!
B53: 视频广告花费 | C53: {=IFERROR(VLOOKUP(C$3&$A6&$A9,IF({1,0},业绩报告!$A$2:$A$8229&业绩报告!$B$2:$B$8229&业绩报告!$C$2:$C$8229,业绩报告!$AX$2:$AX$8229),2,0),"")} -> 0 | D53: {=IFERROR(VLOOKUP(D$3&$A6&$A9,IF({1,0},业绩报告!$A$2:$A$8229&业绩报告!$B$2:$B$8229&业绩报告!$C$2:$C$8229,业绩报告!$AX$2:$AX$8229),2,0),"")} -> 0 | E53: {=IFERROR(VLOOKUP(E$3&$A6&$A9,IF({1,0},业绩报告!$A$2:$A$8229&业绩报告!$B$2:$B$8229&业绩报告!$C$2:$C$8229,业绩报告!$AX$2:$AX$8229),2,0),"")} -> 0 | F53: {=IFERROR(VLOOKUP(F$3&$A6&$A9,IF({1,0},业绩报告!$A$2:$A$8229&业绩报告!$B$2:$B$8229&业绩报告!$C$2:$C$8229,业绩报告!$AX$2:$AX$8229),2,0),"")} -> 0 | G53: {=IFERROR(VLOOKUP(G$3&$A6&$A9,IF({1,0},业绩报告!$A$2:$A$8229&业绩报告!$B$2:$B$8229&业绩报告!$C$2:$C$8229,业绩报告!$AX$2:$AX$8229),2,0),"")} -> 0 | H53: {=IFERROR(VLOOKUP(H$3&$A6&$A9,IF({1,0},业绩报告!$A$2:$A$8229&业绩报告!$B$2:$B$8229&业绩报告!$C$2:$C$8229,业绩报告!$AX$2:$AX$8229),2,0),"")} -> 0 | I53: {=IFERROR(VLOOKUP(I$3&$A6&$A9,IF({1,0},业绩报告!$A$2:$A$8229&业绩报告!$B$2:$B$8229&业绩报告!$C$2:$C$8229,业绩报告!$AX$2:$AX$8229),2,0),"")} -> 0 | J53: =SUM(C53:I53) -> 0 | K53: {=IFERROR(VLOOKUP(K$3&$A6&$A9,IF({1,0},业绩报告!$A$2:$A$8229&业绩报告!$B$2:$B$8229&业绩报告!$C$2:$C$8229,业绩报告!$AX$2:$AX$8229),2,0),"")} -> 0 | L53: {=IFERROR(VLOOKUP(L$3&$A6&$A9,IF({1,0},业绩报告!$A$2:$A$8229&业绩报告!$B$2:$B$8229&业绩报告!$C$2:$C$8229,业绩报告!$AX$2:$AX$8229),2,0),"")} -> 0 | M53: {=IFERROR(VLOOKUP(M$3&$A6&$A9,IF({1,0},业绩报告!$A$2:$A$8229&业绩报告!$B$2:$B$8229&业绩报告!$C$2:$C$8229,业绩报告!$AX$2:$AX$8229),2,0),"")} -> 0 | N53: {=IFERROR(VLOOKUP(N$3&$A6&$A9,IF({1,0},业绩报告!$A$2:$A$8229&业绩报告!$B$2:$B$8229&业绩报告!$C$2:$C$8229,业绩报告!$AX$2:$AX$8229),2,0),"")} -> 0 | O53: {=IFERROR(VLOOKUP(O$3&$A6&$A9,IF({1,0},业绩报告!$A$2:$A$8229&业绩报告!$B$2:$B$8229&业绩报告!$C$2:$C$8229,业绩报告!$AX$2:$AX$8229),2,0),"")} -> 0 | P53: {=IFERROR(VLOOKUP(P$3&$A6&$A9,IF({1,0},业绩报告!$A$2:$A$8229&业绩报告!$B$2:$B$8229&业绩报告!$C$2:$C$8229,业绩报告!$AX$2:$AX$8229),2,0),"")} -> 0 | Q53: {=IFERROR(VLOOKUP(Q$3&$A6&$A9,IF({1,0},业绩报告!$A$2:$A$8229&业绩报告!$B$2:$B$8229&业绩报告!$C$2:$C$8229,业绩报告!$AX$2:$AX$8229),2,0),"")} -> 0 | R53: =SUM(K53:Q53) -> 0
B54: 视频广告销售额 | C54: {=IFERROR(VLOOKUP(C$3&$A6&$A9,IF({1,0},业绩报告!$A$2:$A$8229&业绩报告!$B$2:$B$8229&业绩报告!$C$2:$C$8229,业绩报告!$AY$2:$AY$8229),2,0),"")} -> 0 | D54: {=IFERROR(VLOOKUP(D$3&$A6&$A9,IF({1,0},业绩报告!$A$2:$A$8229&业绩报告!$B$2:$B$8229&业绩报告!$C$2:$C$8229,业绩报告!$AY$2:$AY$8229),2,0),"")} -> 0 | E54: {=IFERROR(VLOOKUP(E$3&$A6&$A9,IF({1,0},业绩报告!$A$2:$A$8229&业绩报告!$B$2:$B$8229&业绩报告!$C$2:$C$8229,业绩报告!$AY$2:$AY$8229),2,0),"")} -> 0 | F54: {=IFERROR(VLOOKUP(F$3&$A6&$A9,IF({1,0},业绩报告!$A$2:$A$8229&业绩报告!$B$2:$B$8229&业绩报告!$C$2:$C$8229,业绩报告!$AY$2:$AY$8229),2,0),"")} -> 0 | G54: {=IFERROR(VLOOKUP(G$3&$A6&$A9,IF({1,0},业绩报告!$A$2:$A$8229&业绩报告!$B$2:$B$8229&业绩报告!$C$2:$C$8229,业绩报告!$AY$2:$AY$8229),2,0),"")} -> 0 | H54: {=IFERROR(VLOOKUP(H$3&$A6&$A9,IF({1,0},业绩报告!$A$2:$A$8229&业绩报告!$B$2:$B$8229&业绩报告!$C$2:$C$8229,业绩报告!$AY$2:$AY$8229),2,0),"")} -> 0 | I54: {=IFERROR(VLOOKUP(I$3&$A6&$A9,IF({1,0},业绩报告!$A$2:$A$8229&业绩报告!$B$2:$B$8229&业绩报告!$C$2:$C$8229,业绩报告!$AY$2:$AY$8229),2,0),"")} -> 0 | J54: =SUM(C54:I54) -> 0 | K54: {=IFERROR(VLOOKUP(K$3&$A6&$A9,IF({1,0},业绩报告!$A$2:$A$8229&业绩报告!$B$2:$B$8229&业绩报告!$C$2:$C$8229,业绩报告!$AY$2:$AY$8229),2,0),"")} -> 0 | L54: {=IFERROR(VLOOKUP(L$3&$A6&$A9,IF({1,0},业绩报告!$A$2:$A$8229&业绩报告!$B$2:$B$8229&业绩报告!$C$2:$C$8229,业绩报告!$AY$2:$AY$8229),2,0),"")} -> 0 | M54: {=IFERROR(VLOOKUP(M$3&$A6&$A9,IF({1,0},业绩报告!$A$2:$A$8229&业绩报告!$B$2:$B$8229&业绩报告!$C$2:$C$8229,业绩报告!$AY$2:$AY$8229),2,0),"")} -> 0 | N54: {=IFERROR(VLOOKUP(N$3&$A6&$A9,IF({1,0},业绩报告!$A$2:$A$8229&业绩报告!$B$2:$B$8229&业绩报告!$C$2:$C$8229,业绩报告!$AY$2:$AY$8229),2,0),"")} -> 0 | O54: {=IFERROR(VLOOKUP(O$3&$A6&$A9,IF({1,0},业绩报告!$A$2:$A$8229&业绩报告!$B$2:$B$8229&业绩报告!$C$2:$C$8229,业绩报告!$AY$2:$AY$8229),2,0),"")} -> 0 | P54: {=IFERROR(VLOOKUP(P$3&$A6&$A9,IF({1,0},业绩报告!$A$2:$A$8229&业绩报告!$B$2:$B$8229&业绩报告!$C$2:$C$8229,业绩报告!$AY$2:$AY$8229),2,0),"")} -> 0 | Q54: {=IFERROR(VLOOKUP(Q$3&$A6&$A9,IF({1,0},业绩报告!$A$2:$A$8229&业绩报告!$B$2:$B$8229&业绩报告!$C$2:$C$8229,业绩报告!$AY$2:$AY$8229),2,0),"")} -> 0 | R54: =SUM(K54:Q54) -> 0
B55: 视频acos | C55: {=IFERROR(VLOOKUP(C$3&$A6&$A9,IF({1,0},业绩报告!$A$2:$A$8229&业绩报告!$B$2:$B$8229&业绩报告!$C$2:$C$8229,业绩报告!$AZ$2:$AZ$8229),2,0),"")} -> 0 | D55: {=IFERROR(VLOOKUP(D$3&$A6&$A9,IF({1,0},业绩报告!$A$2:$A$8229&业绩报告!$B$2:$B$8229&业绩报告!$C$2:$C$8229,业绩报告!$AZ$2:$AZ$8229),2,0),"")} -> 0 | E55: {=IFERROR(VLOOKUP(E$3&$A6&$A9,IF({1,0},业绩报告!$A$2:$A$8229&业绩报告!$B$2:$B$8229&业绩报告!$C$2:$C$8229,业绩报告!$AZ$2:$AZ$8229),2,0),"")} -> 0 | F55: {=IFERROR(VLOOKUP(F$3&$A6&$A9,IF({1,0},业绩报告!$A$2:$A$8229&业绩报告!$B$2:$B$8229&业绩报告!$C$2:$C$8229,业绩报告!$AZ$2:$AZ$8229),2,0),"")} -> 0 | G55: {=IFERROR(VLOOKUP(G$3&$A6&$A9,IF({1,0},业绩报告!$A$2:$A$8229&业绩报告!$B$2:$B$8229&业绩报告!$C$2:$C$8229,业绩报告!$AZ$2:$AZ$8229),2,0),"")} -> 0 | H55: {=IFERROR(VLOOKUP(H$3&$A6&$A9,IF({1,0},业绩报告!$A$2:$A$8229&业绩报告!$B$2:$B$8229&业绩报告!$C$2:$C$8229,业绩报告!$AZ$2:$AZ$8229),2,0),"")} -> 0 | I55: {=IFERROR(VLOOKUP(I$3&$A6&$A9,IF({1,0},业绩报告!$A$2:$A$8229&业绩报告!$B$2:$B$8229&业绩报告!$C$2:$C$8229,业绩报告!$AZ$2:$AZ$8229),2,0),"")} -> 0 | J55: =J53/J54 -> #DIV/0! | K55: {=IFERROR(VLOOKUP(K$3&$A6&$A9,IF({1,0},业绩报告!$A$2:$A$8229&业绩报告!$B$2:$B$8229&业绩报告!$C$2:$C$8229,业绩报告!$AZ$2:$AZ$8229),2,0),"")} -> 0 | L55: {=IFERROR(VLOOKUP(L$3&$A6&$A9,IF({1,0},业绩报告!$A$2:$A$8229&业绩报告!$B$2:$B$8229&业绩报告!$C$2:$C$8229,业绩报告!$AZ$2:$AZ$8229),2,0),"")} -> 0 | M55: {=IFERROR(VLOOKUP(M$3&$A6&$A9,IF({1,0},业绩报告!$A$2:$A$8229&业绩报告!$B$2:$B$8229&业绩报告!$C$2:$C$8229,业绩报告!$AZ$2:$AZ$8229),2,0),"")} -> 0 | N55: {=IFERROR(VLOOKUP(N$3&$A6&$A9,IF({1,0},业绩报告!$A$2:$A$8229&业绩报告!$B$2:$B$8229&业绩报告!$C$2:$C$8229,业绩报告!$AZ$2:$AZ$8229),2,0),"")} -> 0 | O55: {=IFERROR(VLOOKUP(O$3&$A6&$A9,IF({1,0},业绩报告!$A$2:$A$8229&业绩报告!$B$2:$B$8229&业绩报告!$C$2:$C$8229,业绩报告!$AZ$2:$AZ$8229),2,0),"")} -> 0 | P55: {=IFERROR(VLOOKUP(P$3&$A6&$A9,IF({1,0},业绩报告!$A$2:$A$8229&业绩报告!$B$2:$B$8229&业绩报告!$C$2:$C$8229,业绩报告!$AZ$2:$AZ$8229),2,0),"")} -> 0 | Q55: {=IFERROR(VLOOKUP(Q$3&$A6&$A9,IF({1,0},业绩报告!$A$2:$A$8229&业绩报告!$B$2:$B$8229&业绩报告!$C$2:$C$8229,业绩报告!$AZ$2:$AZ$8229),2,0),"")} -> 0 | R55: =R53/R54 -> #DIV/0!
B56: 精确广告曝光量 | C56: {=IFERROR(VLOOKUP(C$3&$A6&$A9,IF({1,0},业绩报告!$A$2:$A$8229&业绩报告!$B$2:$B$8229&业绩报告!$C$2:$C$8229,业绩报告!$BA$2:$BA$8229),2,0),"")} -> 8368 | D56: {=IFERROR(VLOOKUP(D$3&$A6&$A9,IF({1,0},业绩报告!$A$2:$A$8229&业绩报告!$B$2:$B$8229&业绩报告!$C$2:$C$8229,业绩报告!$BA$2:$BA$8229),2,0),"")} -> 12370 | E56: {=IFERROR(VLOOKUP(E$3&$A6&$A9,IF({1,0},业绩报告!$A$2:$A$8229&业绩报告!$B$2:$B$8229&业绩报告!$C$2:$C$8229,业绩报告!$BA$2:$BA$8229),2,0),"")} -> 16790 | F56: {=IFERROR(VLOOKUP(F$3&$A6&$A9,IF({1,0},业绩报告!$A$2:$A$8229&业绩报告!$B$2:$B$8229&业绩报告!$C$2:$C$8229,业绩报告!$BA$2:$BA$8229),2,0),"")} -> 11080 | G56: {=IFERROR(VLOOKUP(G$3&$A6&$A9,IF({1,0},业绩报告!$A$2:$A$8229&业绩报告!$B$2:$B$8229&业绩报告!$C$2:$C$8229,业绩报告!$BA$2:$BA$8229),2,0),"")} -> 9593 | H56: {=IFERROR(VLOOKUP(H$3&$A6&$A9,IF({1,0},业绩报告!$A$2:$A$8229&业绩报告!$B$2:$B$8229&业绩报告!$C$2:$C$8229,业绩报告!$BA$2:$BA$8229),2,0),"")} -> 10967 | I56: {=IFERROR(VLOOKUP(I$3&$A6&$A9,IF({1,0},业绩报告!$A$2:$A$8229&业绩报告!$B$2:$B$8229&业绩报告!$C$2:$C$8229,业绩报告!$BA$2:$BA$8229),2,0),"")} -> 0 | J56: =SUM(C56:I56) -> 69168 | K56: {=IFERROR(VLOOKUP(K$3&$A6&$A9,IF({1,0},业绩报告!$A$2:$A$8229&业绩报告!$B$2:$B$8229&业绩报告!$C$2:$C$8229,业绩报告!$BA$2:$BA$8229),2,0),"")} -> 9698 | L56: {=IFERROR(VLOOKUP(L$3&$A6&$A9,IF({1,0},业绩报告!$A$2:$A$8229&业绩报告!$B$2:$B$8229&业绩报告!$C$2:$C$8229,业绩报告!$BA$2:$BA$8229),2,0),"")} -> 11641 | M56: {=IFERROR(VLOOKUP(M$3&$A6&$A9,IF({1,0},业绩报告!$A$2:$A$8229&业绩报告!$B$2:$B$8229&业绩报告!$C$2:$C$8229,业绩报告!$BA$2:$BA$8229),2,0),"")} -> 10674 | N56: {=IFERROR(VLOOKUP(N$3&$A6&$A9,IF({1,0},业绩报告!$A$2:$A$8229&业绩报告!$B$2:$B$8229&业绩报告!$C$2:$C$8229,业绩报告!$BA$2:$BA$8229),2,0),"")} -> 10648 | O56: {=IFERROR(VLOOKUP(O$3&$A6&$A9,IF({1,0},业绩报告!$A$2:$A$8229&业绩报告!$B$2:$B$8229&业绩报告!$C$2:$C$8229,业绩报告!$BA$2:$BA$8229),2,0),"")} -> 14073 | P56: {=IFERROR(VLOOKUP(P$3&$A6&$A9,IF({1,0},业绩报告!$A$2:$A$8229&业绩报告!$B$2:$B$8229&业绩报告!$C$2:$C$8229,业绩报告!$BA$2:$BA$8229),2,0),"")} -> 10843 | Q56: {=IFERROR(VLOOKUP(Q$3&$A6&$A9,IF({1,0},业绩报告!$A$2:$A$8229&业绩报告!$B$2:$B$8229&业绩报告!$C$2:$C$8229,业绩报告!$BA$2:$BA$8229),2,0),"")} -> 8088 | R56: =SUM(K56:Q56) -> 75665
B57: 精确广告点击量 | C57: {=IFERROR(VLOOKUP(C$3&$A6&$A9,IF({1,0},业绩报告!$A$2:$A$8229&业绩报告!$B$2:$B$8229&业绩报告!$C$2:$C$8229,业绩报告!$BB$2:$BB$8229),2,0),"")} -> 26 | D57: {=IFERROR(VLOOKUP(D$3&$A6&$A9,IF({1,0},业绩报告!$A$2:$A$8229&业绩报告!$B$2:$B$8229&业绩报告!$C$2:$C$8229,业绩报告!$BB$2:$BB$8229),2,0),"")} -> 26 | E57: {=IFERROR(VLOOKUP(E$3&$A6&$A9,IF({1,0},业绩报告!$A$2:$A$8229&业绩报告!$B$2:$B$8229&业绩报告!$C$2:$C$8229,业绩报告!$BB$2:$BB$8229),2,0),"")} -> 49 | F57: {=IFERROR(VLOOKUP(F$3&$A6&$A9,IF({1,0},业绩报告!$A$2:$A$8229&业绩报告!$B$2:$B$8229&业绩报告!$C$2:$C$8229,业绩报告!$BB$2:$BB$8229),2,0),"")} -> 37 | G57: {=IFERROR(VLOOKUP(G$3&$A6&$A9,IF({1,0},业绩报告!$A$2:$A$8229&业绩报告!$B$2:$B$8229&业绩报告!$C$2:$C$8229,业绩报告!$BB$2:$BB$8229),2,0),"")} -> 46 | H57: {=IFERROR(VLOOKUP(H$3&$A6&$A9,IF({1,0},业绩报告!$A$2:$A$8229&业绩报告!$B$2:$B$8229&业绩报告!$C$2:$C$8229,业绩报告!$BB$2:$BB$8229),2,0),"")} -> 43 | I57: {=IFERROR(VLOOKUP(I$3&$A6&$A9,IF({1,0},业绩报告!$A$2:$A$8229&业绩报告!$B$2:$B$8229&业绩报告!$C$2:$C$8229,业绩报告!$BB$2:$BB$8229),2,0),"")} -> 0 | J57: =SUM(C57:I57) -> 227 | K57: {=IFERROR(VLOOKUP(K$3&$A6&$A9,IF({1,0},业绩报告!$A$2:$A$8229&业绩报告!$B$2:$B$8229&业绩报告!$C$2:$C$8229,业绩报告!$BB$2:$BB$8229),2,0),"")} -> 38 | L57: {=IFERROR(VLOOKUP(L$3&$A6&$A9,IF({1,0},业绩报告!$A$2:$A$8229&业绩报告!$B$2:$B$8229&业绩报告!$C$2:$C$8229,业绩报告!$BB$2:$BB$8229),2,0),"")} -> 45 | M57: {=IFERROR(VLOOKUP(M$3&$A6&$A9,IF({1,0},业绩报告!$A$2:$A$8229&业绩报告!$B$2:$B$8229&业绩报告!$C$2:$C$8229,业绩报告!$BB$2:$BB$8229),2,0),"")} -> 41 | N57: {=IFERROR(VLOOKUP(N$3&$A6&$A9,IF({1,0},业绩报告!$A$2:$A$8229&业绩报告!$B$2:$B$8229&业绩报告!$C$2:$C$8229,业绩报告!$BB$2:$BB$8229),2,0),"")} -> 33 | O57: {=IFERROR(VLOOKUP(O$3&$A6&$A9,IF({1,0},业绩报告!$A$2:$A$8229&业绩报告!$B$2:$B$8229&业绩报告!$C$2:$C$8229,业绩报告!$BB$2:$BB$8229),2,0),"")} -> 40 | P57: {=IFERROR(VLOOKUP(P$3&$A6&$A9,IF({1,0},业绩报告!$A$2:$A$8229&业绩报告!$B$2:$B$8229&业绩报告!$C$2:$C$8229,业绩报告!$BB$2:$BB$8229),2,0),"")} -> 28 | Q57: {=IFERROR(VLOOKUP(Q$3&$A6&$A9,IF({1,0},业绩报告!$A$2:$A$8229&业绩报告!$B$2:$B$8229&业绩报告!$C$2:$C$8229,业绩报告!$BB$2:$BB$8229),2,0),"")} -> 35 | R57: =SUM(K57:Q57) -> 260
B58: 精确单量 | C58: {=IFERROR(VLOOKUP(C$3&$A6&$A9,IF({1,0},业绩报告!$A$2:$A$8229&业绩报告!$B$2:$B$8229&业绩报告!$C$2:$C$8229,业绩报告!$BC$2:$BC$8229),2,0),"")} -> 1 | D58: {=IFERROR(VLOOKUP(D$3&$A6&$A9,IF({1,0},业绩报告!$A$2:$A$8229&业绩报告!$B$2:$B$8229&业绩报告!$C$2:$C$8229,业绩报告!$BC$2:$BC$8229),2,0),"")} -> 0 | E58: {=IFERROR(VLOOKUP(E$3&$A6&$A9,IF({1,0},业绩报告!$A$2:$A$8229&业绩报告!$B$2:$B$8229&业绩报告!$C$2:$C$8229,业绩报告!$BC$2:$BC$8229),2,0),"")} -> 5 | F58: {=IFERROR(VLOOKUP(F$3&$A6&$A9,IF({1,0},业绩报告!$A$2:$A$8229&业绩报告!$B$2:$B$8229&业绩报告!$C$2:$C$8229,业绩报告!$BC$2:$BC$8229),2,0),"")} -> 0 | G58: {=IFERROR(VLOOKUP(G$3&$A6&$A9,IF({1,0},业绩报告!$A$2:$A$8229&业绩报告!$B$2:$B$8229&业绩报告!$C$2:$C$8229,业绩报告!$BC$2:$BC$8229),2,0),"")} -> 1 | H58: {=IFERROR(VLOOKUP(H$3&$A6&$A9,IF({1,0},业绩报告!$A$2:$A$8229&业绩报告!$B$2:$B$8229&业绩报告!$C$2:$C$8229,业绩报告!$BC$2:$BC$8229),2,0),"")} -> 2 | I58: {=IFERROR(VLOOKUP(I$3&$A6&$A9,IF({1,0},业绩报告!$A$2:$A$8229&业绩报告!$B$2:$B$8229&业绩报告!$C$2:$C$8229,业绩报告!$BC$2:$BC$8229),2,0),"")} -> 0 | J58: =SUM(C58:I58) -> 9 | K58: {=IFERROR(VLOOKUP(K$3&$A6&$A9,IF({1,0},业绩报告!$A$2:$A$8229&业绩报告!$B$2:$B$8229&业绩报告!$C$2:$C$8229,业绩报告!$BC$2:$BC$8229),2,0),"")} -> 1 | L58: {=IFERROR(VLOOKUP(L$3&$A6&$A9,IF({1,0},业绩报告!$A$2:$A$8229&业绩报告!$B$2:$B$8229&业绩报告!$C$2:$C$8229,业绩报告!$BC$2:$BC$8229),2,0),"")} -> 2 | M58: {=IFERROR(VLOOKUP(M$3&$A6&$A9,IF({1,0},业绩报告!$A$2:$A$8229&业绩报告!$B$2:$B$8229&业绩报告!$C$2:$C$8229,业绩报告!$BC$2:$BC$8229),2,0),"")} -> 7 | N58: {=IFERROR(VLOOKUP(N$3&$A6&$A9,IF({1,0},业绩报告!$A$2:$A$8229&业绩报告!$B$2:$B$8229&业绩报告!$C$2:$C$8229,业绩报告!$BC$2:$BC$8229),2,0),"")} -> 3 | O58: {=IFERROR(VLOOKUP(O$3&$A6&$A9,IF({1,0},业绩报告!$A$2:$A$8229&业绩报告!$B$2:$B$8229&业绩报告!$C$2:$C$8229,业绩报告!$BC$2:$BC$8229),2,0),"")} -> 6 | P58: {=IFERROR(VLOOKUP(P$3&$A6&$A9,IF({1,0},业绩报告!$A$2:$A$8229&业绩报告!$B$2:$B$8229&业绩报告!$C$2:$C$8229,业绩报告!$BC$2:$BC$8229),2,0),"")} -> 3 | Q58: {=IFERROR(VLOOKUP(Q$3&$A6&$A9,IF({1,0},业绩报告!$A$2:$A$8229&业绩报告!$B$2:$B$8229&业绩报告!$C$2:$C$8229,业绩报告!$BC$2:$BC$8229),2,0),"")} -> 2 | R58: =SUM(K58:Q58) -> 24
B59: 精确广告点击率 | C59: {=IFERROR(VLOOKUP(C$3&$A6&$A9,IF({1,0},业绩报告!$A$2:$A$8229&业绩报告!$B$2:$B$8229&业绩报告!$C$2:$C$8229,业绩报告!$BD$2:$BD$8229),2,0),"")} -> 0.0031070746 | D59: {=IFERROR(VLOOKUP(D$3&$A6&$A9,IF({1,0},业绩报告!$A$2:$A$8229&业绩报告!$B$2:$B$8229&业绩报告!$C$2:$C$8229,业绩报告!$BD$2:$BD$8229),2,0),"")} -> 0.0021018593 | E59: {=IFERROR(VLOOKUP(E$3&$A6&$A9,IF({1,0},业绩报告!$A$2:$A$8229&业绩报告!$B$2:$B$8229&业绩报告!$C$2:$C$8229,业绩报告!$BD$2:$BD$8229),2,0),"")} -> 0.0029184038 | F59: {=IFERROR(VLOOKUP(F$3&$A6&$A9,IF({1,0},业绩报告!$A$2:$A$8229&业绩报告!$B$2:$B$8229&业绩报告!$C$2:$C$8229,业绩报告!$BD$2:$BD$8229),2,0),"")} -> 0.0033393502 | G59: {=IFERROR(VLOOKUP(G$3&$A6&$A9,IF({1,0},业绩报告!$A$2:$A$8229&业绩报告!$B$2:$B$8229&业绩报告!$C$2:$C$8229,业绩报告!$BD$2:$BD$8229),2,0),"")} -> 0.0047951631 | H59: {=IFERROR(VLOOKUP(H$3&$A6&$A9,IF({1,0},业绩报告!$A$2:$A$8229&业绩报告!$B$2:$B$8229&业绩报告!$C$2:$C$8229,业绩报告!$BD$2:$BD$8229),2,0),"")} -> 0.0039208535 | I59: {=IFERROR(VLOOKUP(I$3&$A6&$A9,IF({1,0},业绩报告!$A$2:$A$8229&业绩报告!$B$2:$B$8229&业绩报告!$C$2:$C$8229,业绩报告!$BD$2:$BD$8229),2,0),"")} -> 0 | J59: =AVERAGE(C59:I59) -> 0.0033637841 | K59: {=IFERROR(VLOOKUP(K$3&$A6&$A9,IF({1,0},业绩报告!$A$2:$A$8229&业绩报告!$B$2:$B$8229&业绩报告!$C$2:$C$8229,业绩报告!$BD$2:$BD$8229),2,0),"")} -> 0.0039183337 | L59: {=IFERROR(VLOOKUP(L$3&$A6&$A9,IF({1,0},业绩报告!$A$2:$A$8229&业绩报告!$B$2:$B$8229&业绩报告!$C$2:$C$8229,业绩报告!$BD$2:$BD$8229),2,0),"")} -> 0.0038656473 | M59: {=IFERROR(VLOOKUP(M$3&$A6&$A9,IF({1,0},业绩报告!$A$2:$A$8229&业绩报告!$B$2:$B$8229&业绩报告!$C$2:$C$8229,业绩报告!$BD$2:$BD$8229),2,0),"")} -> 0.0038411092 | N59: {=IFERROR(VLOOKUP(N$3&$A6&$A9,IF({1,0},业绩报告!$A$2:$A$8229&业绩报告!$B$2:$B$8229&业绩报告!$C$2:$C$8229,业绩报告!$BD$2:$BD$8229),2,0),"")} -> 0.0030991736 | O59: {=IFERROR(VLOOKUP(O$3&$A6&$A9,IF({1,0},业绩报告!$A$2:$A$8229&业绩报告!$B$2:$B$8229&业绩报告!$C$2:$C$8229,业绩报告!$BD$2:$BD$8229),2,0),"")} -> 0.0028423222 | P59: {=IFERROR(VLOOKUP(P$3&$A6&$A9,IF({1,0},业绩报告!$A$2:$A$8229&业绩报告!$B$2:$B$8229&业绩报告!$C$2:$C$8229,业绩报告!$BD$2:$BD$8229),2,0),"")} -> 0.0025823112 | Q59: {=IFERROR(VLOOKUP(Q$3&$A6&$A9,IF({1,0},业绩报告!$A$2:$A$8229&业绩报告!$B$2:$B$8229&业绩报告!$C$2:$C$8229,业绩报告!$BD$2:$BD$8229),2,0),"")} -> 0.0043273986 | R59: =R57/R56 -> 0.003436199
B60: 精确广告转化率 | C60: {=IFERROR(VLOOKUP(C$3&$A6&$A9,IF({1,0},业绩报告!$A$2:$A$8229&业绩报告!$B$2:$B$8229&业绩报告!$C$2:$C$8229,业绩报告!$BE$2:$BE$8229),2,0),"")} -> 0.038461538 | D60: {=IFERROR(VLOOKUP(D$3&$A6&$A9,IF({1,0},业绩报告!$A$2:$A$8229&业绩报告!$B$2:$B$8229&业绩报告!$C$2:$C$8229,业绩报告!$BE$2:$BE$8229),2,0),"")} -> 0 | E60: {=IFERROR(VLOOKUP(E$3&$A6&$A9,IF({1,0},业绩报告!$A$2:$A$8229&业绩报告!$B$2:$B$8229&业绩报告!$C$2:$C$8229,业绩报告!$BE$2:$BE$8229),2,0),"")} -> 0.10204082 | F60: {=IFERROR(VLOOKUP(F$3&$A6&$A9,IF({1,0},业绩报告!$A$2:$A$8229&业绩报告!$B$2:$B$8229&业绩报告!$C$2:$C$8229,业绩报告!$BE$2:$BE$8229),2,0),"")} -> 0 | G60: {=IFERROR(VLOOKUP(G$3&$A6&$A9,IF({1,0},业绩报告!$A$2:$A$8229&业绩报告!$B$2:$B$8229&业绩报告!$C$2:$C$8229,业绩报告!$BE$2:$BE$8229),2,0),"")} -> 0.02173913 | H60: {=IFERROR(VLOOKUP(H$3&$A6&$A9,IF({1,0},业绩报告!$A$2:$A$8229&业绩报告!$B$2:$B$8229&业绩报告!$C$2:$C$8229,业绩报告!$BE$2:$BE$8229),2,0),"")} -> 0.046511628 | I60: {=IFERROR(VLOOKUP(I$3&$A6&$A9,IF({1,0},业绩报告!$A$2:$A$8229&业绩报告!$B$2:$B$8229&业绩报告!$C$2:$C$8229,业绩报告!$BE$2:$BE$8229),2,0),"")} -> 0 | J60: =AVERAGE(C60:I60) -> 0.034792186 | K60: {=IFERROR(VLOOKUP(K$3&$A6&$A9,IF({1,0},业绩报告!$A$2:$A$8229&业绩报告!$B$2:$B$8229&业绩报告!$C$2:$C$8229,业绩报告!$BE$2:$BE$8229),2,0),"")} -> 0.026315789 | L60: {=IFERROR(VLOOKUP(L$3&$A6&$A9,IF({1,0},业绩报告!$A$2:$A$8229&业绩报告!$B$2:$B$8229&业绩报告!$C$2:$C$8229,业绩报告!$BE$2:$BE$8229),2,0),"")} -> 0.044444444 | M60: {=IFERROR(VLOOKUP(M$3&$A6&$A9,IF({1,0},业绩报告!$A$2:$A$8229&业绩报告!$B$2:$B$8229&业绩报告!$C$2:$C$8229,业绩报告!$BE$2:$BE$8229),2,0),"")} -> 0.17073171 | N60: {=IFERROR(VLOOKUP(N$3&$A6&$A9,IF({1,0},业绩报告!$A$2:$A$8229&业绩报告!$B$2:$B$8229&业绩报告!$C$2:$C$8229,业绩报告!$BE$2:$BE$8229),2,0),"")} -> 0.090909091 | O60: {=IFERROR(VLOOKUP(O$3&$A6&$A9,IF({1,0},业绩报告!$A$2:$A$8229&业绩报告!$B$2:$B$8229&业绩报告!$C$2:$C$8229,业绩报告!$BE$2:$BE$8229),2,0),"")} -> 0.15 | P60: {=IFERROR(VLOOKUP(P$3&$A6&$A9,IF({1,0},业绩报告!$A$2:$A$8229&业绩报告!$B$2:$B$8229&业绩报告!$C$2:$C$8229,业绩报告!$BE$2:$BE$8229),2,0),"")} -> 0.10714286 | Q60: {=IFERROR(VLOOKUP(Q$3&$A6&$A9,IF({1,0},业绩报告!$A$2:$A$8229&业绩报告!$B$2:$B$8229&业绩报告!$C$2:$C$8229,业绩报告!$BE$2:$BE$8229),2,0),"")} -> 0.057142857 | R60: =R58/R57 -> 0.092307692
B61: 精确广告花费 | C61: {=IFERROR(VLOOKUP(C$3&$A6&$A9,IF({1,0},业绩报告!$A$2:$A$8229&业绩报告!$B$2:$B$8229&业绩报告!$C$2:$C$8229,业绩报告!$BF$2:$BF$8229),2,0),"")} -> 13.63 | D61: {=IFERROR(VLOOKUP(D$3&$A6&$A9,IF({1,0},业绩报告!$A$2:$A$8229&业绩报告!$B$2:$B$8229&业绩报告!$C$2:$C$8229,业绩报告!$BF$2:$BF$8229),2,0),"")} -> 11.7 | E61: {=IFERROR(VLOOKUP(E$3&$A6&$A9,IF({1,0},业绩报告!$A$2:$A$8229&业绩报告!$B$2:$B$8229&业绩报告!$C$2:$C$8229,业绩报告!$BF$2:$BF$8229),2,0),"")} -> 22.99 | F61: {=IFERROR(VLOOKUP(F$3&$A6&$A9,IF({1,0},业绩报告!$A$2:$A$8229&业绩报告!$B$2:$B$8229&业绩报告!$C$2:$C$8229,业绩报告!$BF$2:$BF$8229),2,0),"")} -> 16.85 | G61: {=IFERROR(VLOOKUP(G$3&$A6&$A9,IF({1,0},业绩报告!$A$2:$A$8229&业绩报告!$B$2:$B$8229&业绩报告!$C$2:$C$8229,业绩报告!$BF$2:$BF$8229),2,0),"")} -> 18.59 | H61: {=IFERROR(VLOOKUP(H$3&$A6&$A9,IF({1,0},业绩报告!$A$2:$A$8229&业绩报告!$B$2:$B$8229&业绩报告!$C$2:$C$8229,业绩报告!$BF$2:$BF$8229),2,0),"")} -> 18.9 | I61: {=IFERROR(VLOOKUP(I$3&$A6&$A9,IF({1,0},业绩报告!$A$2:$A$8229&业绩报告!$B$2:$B$8229&业绩报告!$C$2:$C$8229,业绩报告!$BF$2:$BF$8229),2,0),"")} -> 0 | J61: =SUM(C61:I61) -> 102.66 | K61: {=IFERROR(VLOOKUP(K$3&$A6&$A9,IF({1,0},业绩报告!$A$2:$A$8229&业绩报告!$B$2:$B$8229&业绩报告!$C$2:$C$8229,业绩报告!$BF$2:$BF$8229),2,0),"")} -> 18.32 | L61: {=IFERROR(VLOOKUP(L$3&$A6&$A9,IF({1,0},业绩报告!$A$2:$A$8229&业绩报告!$B$2:$B$8229&业绩报告!$C$2:$C$8229,业绩报告!$BF$2:$BF$8229),2,0),"")} -> 22.76 | M61: {=IFERROR(VLOOKUP(M$3&$A6&$A9,IF({1,0},业绩报告!$A$2:$A$8229&业绩报告!$B$2:$B$8229&业绩报告!$C$2:$C$8229,业绩报告!$BF$2:$BF$8229),2,0),"")} -> 23.96 | N61: {=IFERROR(VLOOKUP(N$3&$A6&$A9,IF({1,0},业绩报告!$A$2:$A$8229&业绩报告!$B$2:$B$8229&业绩报告!$C$2:$C$8229,业绩报告!$BF$2:$BF$8229),2,0),"")} -> 17.2 | O61: {=IFERROR(VLOOKUP(O$3&$A6&$A9,IF({1,0},业绩报告!$A$2:$A$8229&业绩报告!$B$2:$B$8229&业绩报告!$C$2:$C$8229,业绩报告!$BF$2:$BF$8229),2,0),"")} -> 18.17 | P61: {=IFERROR(VLOOKUP(P$3&$A6&$A9,IF({1,0},业绩报告!$A$2:$A$8229&业绩报告!$B$2:$B$8229&业绩报告!$C$2:$C$8229,业绩报告!$BF$2:$BF$8229),2,0),"")} -> 15.66 | Q61: {=IFERROR(VLOOKUP(Q$3&$A6&$A9,IF({1,0},业绩报告!$A$2:$A$8229&业绩报告!$B$2:$B$8229&业绩报告!$C$2:$C$8229,业绩报告!$BF$2:$BF$8229),2,0),"")} -> 18.56 | R61: =SUM(K61:Q61) -> 134.63
B62: 精确广告销售额 | C62: {=IFERROR(VLOOKUP(C$3&$A6&$A9,IF({1,0},业绩报告!$A$2:$A$8229&业绩报告!$B$2:$B$8229&业绩报告!$C$2:$C$8229,业绩报告!$BG$2:$BG$8229),2,0),"")} -> 11.99 | D62: {=IFERROR(VLOOKUP(D$3&$A6&$A9,IF({1,0},业绩报告!$A$2:$A$8229&业绩报告!$B$2:$B$8229&业绩报告!$C$2:$C$8229,业绩报告!$BG$2:$BG$8229),2,0),"")} -> 0 | E62: {=IFERROR(VLOOKUP(E$3&$A6&$A9,IF({1,0},业绩报告!$A$2:$A$8229&业绩报告!$B$2:$B$8229&业绩报告!$C$2:$C$8229,业绩报告!$BG$2:$BG$8229),2,0),"")} -> 59.95 | F62: {=IFERROR(VLOOKUP(F$3&$A6&$A9,IF({1,0},业绩报告!$A$2:$A$8229&业绩报告!$B$2:$B$8229&业绩报告!$C$2:$C$8229,业绩报告!$BG$2:$BG$8229),2,0),"")} -> 0 | G62: {=IFERROR(VLOOKUP(G$3&$A6&$A9,IF({1,0},业绩报告!$A$2:$A$8229&业绩报告!$B$2:$B$8229&业绩报告!$C$2:$C$8229,业绩报告!$BG$2:$BG$8229),2,0),"")} -> 9.59 | H62: {=IFERROR(VLOOKUP(H$3&$A6&$A9,IF({1,0},业绩报告!$A$2:$A$8229&业绩报告!$B$2:$B$8229&业绩报告!$C$2:$C$8229,业绩报告!$BG$2:$BG$8229),2,0),"")} -> 19.18 | I62: {=IFERROR(VLOOKUP(I$3&$A6&$A9,IF({1,0},业绩报告!$A$2:$A$8229&业绩报告!$B$2:$B$8229&业绩报告!$C$2:$C$8229,业绩报告!$BG$2:$BG$8229),2,0),"")} -> 0 | J62: =SUM(C62:I62) -> 100.71 | K62: {=IFERROR(VLOOKUP(K$3&$A6&$A9,IF({1,0},业绩报告!$A$2:$A$8229&业绩报告!$B$2:$B$8229&业绩报告!$C$2:$C$8229,业绩报告!$BG$2:$BG$8229),2,0),"")} -> 11.99 | L62: {=IFERROR(VLOOKUP(L$3&$A6&$A9,IF({1,0},业绩报告!$A$2:$A$8229&业绩报告!$B$2:$B$8229&业绩报告!$C$2:$C$8229,业绩报告!$BG$2:$BG$8229),2,0),"")} -> 23.98 | M62: {=IFERROR(VLOOKUP(M$3&$A6&$A9,IF({1,0},业绩报告!$A$2:$A$8229&业绩报告!$B$2:$B$8229&业绩报告!$C$2:$C$8229,业绩报告!$BG$2:$BG$8229),2,0),"")} -> 83.93 | N62: {=IFERROR(VLOOKUP(N$3&$A6&$A9,IF({1,0},业绩报告!$A$2:$A$8229&业绩报告!$B$2:$B$8229&业绩报告!$C$2:$C$8229,业绩报告!$BG$2:$BG$8229),2,0),"")} -> 35.97 | O62: {=IFERROR(VLOOKUP(O$3&$A6&$A9,IF({1,0},业绩报告!$A$2:$A$8229&业绩报告!$B$2:$B$8229&业绩报告!$C$2:$C$8229,业绩报告!$BG$2:$BG$8229),2,0),"")} -> 71.94 | P62: {=IFERROR(VLOOKUP(P$3&$A6&$A9,IF({1,0},业绩报告!$A$2:$A$8229&业绩报告!$B$2:$B$8229&业绩报告!$C$2:$C$8229,业绩报告!$BG$2:$BG$8229),2,0),"")} -> 35.97 | Q62: {=IFERROR(VLOOKUP(Q$3&$A6&$A9,IF({1,0},业绩报告!$A$2:$A$8229&业绩报告!$B$2:$B$8229&业绩报告!$C$2:$C$8229,业绩报告!$BG$2:$BG$8229),2,0),"")} -> 23.98 | R62: =SUM(K62:Q62) -> 287.76
B63: 精确acos | C63: {=IFERROR(VLOOKUP(C$3&$A6&$A9,IF({1,0},业绩报告!$A$2:$A$8229&业绩报告!$B$2:$B$8229&业绩报告!$C$2:$C$8229,业绩报告!$BH$2:$BH$8229),2,0),"")} -> 1.1367807 | D63: {=IFERROR(VLOOKUP(D$3&$A6&$A9,IF({1,0},业绩报告!$A$2:$A$8229&业绩报告!$B$2:$B$8229&业绩报告!$C$2:$C$8229,业绩报告!$BH$2:$BH$8229),2,0),"")} -> 0 | E63: {=IFERROR(VLOOKUP(E$3&$A6&$A9,IF({1,0},业绩报告!$A$2:$A$8229&业绩报告!$B$2:$B$8229&业绩报告!$C$2:$C$8229,业绩报告!$BH$2:$BH$8229),2,0),"")} -> 0.38348624 | F63: {=IFERROR(VLOOKUP(F$3&$A6&$A9,IF({1,0},业绩报告!$A$2:$A$8229&业绩报告!$B$2:$B$8229&业绩报告!$C$2:$C$8229,业绩报告!$BH$2:$BH$8229),2,0),"")} -> 0 | G63: {=IFERROR(VLOOKUP(G$3&$A6&$A9,IF({1,0},业绩报告!$A$2:$A$8229&业绩报告!$B$2:$B$8229&业绩报告!$C$2:$C$8229,业绩报告!$BH$2:$BH$8229),2,0),"")} -> 1.9384776 | H63: {=IFERROR(VLOOKUP(H$3&$A6&$A9,IF({1,0},业绩报告!$A$2:$A$8229&业绩报告!$B$2:$B$8229&业绩报告!$C$2:$C$8229,业绩报告!$BH$2:$BH$8229),2,0),"")} -> 0.98540146 | I63: {=IFERROR(VLOOKUP(I$3&$A6&$A9,IF({1,0},业绩报告!$A$2:$A$8229&业绩报告!$B$2:$B$8229&业绩报告!$C$2:$C$8229,业绩报告!$BH$2:$BH$8229),2,0),"")} -> 0 | J63: =J61/J62 -> 1.0193625 | K63: {=IFERROR(VLOOKUP(K$3&$A6&$A9,IF({1,0},业绩报告!$A$2:$A$8229&业绩报告!$B$2:$B$8229&业绩报告!$C$2:$C$8229,业绩报告!$BH$2:$BH$8229),2,0),"")} -> 1.5279399 | L63: {=IFERROR(VLOOKUP(L$3&$A6&$A9,IF({1,0},业绩报告!$A$2:$A$8229&业绩报告!$B$2:$B$8229&业绩报告!$C$2:$C$8229,业绩报告!$BH$2:$BH$8229),2,0),"")} -> 0.94912427 | M63: {=IFERROR(VLOOKUP(M$3&$A6&$A9,IF({1,0},业绩报告!$A$2:$A$8229&业绩报告!$B$2:$B$8229&业绩报告!$C$2:$C$8229,业绩报告!$BH$2:$BH$8229),2,0),"")} -> 0.28547599 | N63: {=IFERROR(VLOOKUP(N$3&$A6&$A9,IF({1,0},业绩报告!$A$2:$A$8229&业绩报告!$B$2:$B$8229&业绩报告!$C$2:$C$8229,业绩报告!$BH$2:$BH$8229),2,0),"")} -> 0.47817626 | O63: {=IFERROR(VLOOKUP(O$3&$A6&$A9,IF({1,0},业绩报告!$A$2:$A$8229&业绩报告!$B$2:$B$8229&业绩报告!$C$2:$C$8229,业绩报告!$BH$2:$BH$8229),2,0),"")} -> 0.25257159 | P63: {=IFERROR(VLOOKUP(P$3&$A6&$A9,IF({1,0},业绩报告!$A$2:$A$8229&业绩报告!$B$2:$B$8229&业绩报告!$C$2:$C$8229,业绩报告!$BH$2:$BH$8229),2,0),"")} -> 0.4353628 | Q63: {=IFERROR(VLOOKUP(Q$3&$A6&$A9,IF({1,0},业绩报告!$A$2:$A$8229&业绩报告!$B$2:$B$8229&业绩报告!$C$2:$C$8229,业绩报告!$BH$2:$BH$8229),2,0),"")} -> 0.77397832 | R63: =R61/R62 -> 0.46785516
B64: 展示广告展现 | C64: {=IFERROR(VLOOKUP(C$3&$A6&$A9,IF({1,0},业绩报告!$A$2:$A$8229&业绩报告!$B$2:$B$8229&业绩报告!$C$2:$C$8229,业绩报告!$BI$2:$BI$8229),2,0),"")} -> 2864 | D64: {=IFERROR(VLOOKUP(D$3&$A6&$A9,IF({1,0},业绩报告!$A$2:$A$8229&业绩报告!$B$2:$B$8229&业绩报告!$C$2:$C$8229,业绩报告!$BI$2:$BI$8229),2,0),"")} -> 4433 | E64: {=IFERROR(VLOOKUP(E$3&$A6&$A9,IF({1,0},业绩报告!$A$2:$A$8229&业绩报告!$B$2:$B$8229&业绩报告!$C$2:$C$8229,业绩报告!$BI$2:$BI$8229),2,0),"")} -> 3898 | F64: {=IFERROR(VLOOKUP(F$3&$A6&$A9,IF({1,0},业绩报告!$A$2:$A$8229&业绩报告!$B$2:$B$8229&业绩报告!$C$2:$C$8229,业绩报告!$BI$2:$BI$8229),2,0),"")} -> 2743 | G64: {=IFERROR(VLOOKUP(G$3&$A6&$A9,IF({1,0},业绩报告!$A$2:$A$8229&业绩报告!$B$2:$B$8229&业绩报告!$C$2:$C$8229,业绩报告!$BI$2:$BI$8229),2,0),"")} -> 3020 | H64: {=IFERROR(VLOOKUP(H$3&$A6&$A9,IF({1,0},业绩报告!$A$2:$A$8229&业绩报告!$B$2:$B$8229&业绩报告!$C$2:$C$8229,业绩报告!$BI$2:$BI$8229),2,0),"")} -> 2347 | I64: {=IFERROR(VLOOKUP(I$3&$A6&$A9,IF({1,0},业绩报告!$A$2:$A$8229&业绩报告!$B$2:$B$8229&业绩报告!$C$2:$C$8229,业绩报告!$BI$2:$BI$8229),2,0),"")} -> 0 | J64: =SUM(C64:I64) -> 19305 | K64: {=IFERROR(VLOOKUP(K$3&$A6&$A9,IF({1,0},业绩报告!$A$2:$A$8229&业绩报告!$B$2:$B$8229&业绩报告!$C$2:$C$8229,业绩报告!$BI$2:$BI$8229),2,0),"")} -> 1647 | L64: {=IFERROR(VLOOKUP(L$3&$A6&$A9,IF({1,0},业绩报告!$A$2:$A$8229&业绩报告!$B$2:$B$8229&业绩报告!$C$2:$C$8229,业绩报告!$BI$2:$BI$8229),2,0),"")} -> 1597 | M64: {=IFERROR(VLOOKUP(M$3&$A6&$A9,IF({1,0},业绩报告!$A$2:$A$8229&业绩报告!$B$2:$B$8229&业绩报告!$C$2:$C$8229,业绩报告!$BI$2:$BI$8229),2,0),"")} -> 1736 | N64: {=IFERROR(VLOOKUP(N$3&$A6&$A9,IF({1,0},业绩报告!$A$2:$A$8229&业绩报告!$B$2:$B$8229&业绩报告!$C$2:$C$8229,业绩报告!$BI$2:$BI$8229),2,0),"")} -> 1854 | O64: {=IFERROR(VLOOKUP(O$3&$A6&$A9,IF({1,0},业绩报告!$A$2:$A$8229&业绩报告!$B$2:$B$8229&业绩报告!$C$2:$C$8229,业绩报告!$BI$2:$BI$8229),2,0),"")} -> 2778 | P64: {=IFERROR(VLOOKUP(P$3&$A6&$A9,IF({1,0},业绩报告!$A$2:$A$8229&业绩报告!$B$2:$B$8229&业绩报告!$C$2:$C$8229,业绩报告!$BI$2:$BI$8229),2,0),"")} -> 2251 | Q64: {=IFERROR(VLOOKUP(Q$3&$A6&$A9,IF({1,0},业绩报告!$A$2:$A$8229&业绩报告!$B$2:$B$8229&业绩报告!$C$2:$C$8229,业绩报告!$BI$2:$BI$8229),2,0),"")} -> 1604 | R64: =SUM(K64:Q64) -> 13467
B65: 展示广告点击量 | C65: {=IFERROR(VLOOKUP(C$3&$A6&$A9,IF({1,0},业绩报告!$A$2:$A$8229&业绩报告!$B$2:$B$8229&业绩报告!$C$2:$C$8229,业绩报告!$BJ$2:$BJ$8229),2,0),"0")} -> 22 | D65: {=IFERROR(VLOOKUP(D$3&$A6&$A9,IF({1,0},业绩报告!$A$2:$A$8229&业绩报告!$B$2:$B$8229&业绩报告!$C$2:$C$8229,业绩报告!$BJ$2:$BJ$8229),2,0),"0")} -> 23 | E65: {=IFERROR(VLOOKUP(E$3&$A6&$A9,IF({1,0},业绩报告!$A$2:$A$8229&业绩报告!$B$2:$B$8229&业绩报告!$C$2:$C$8229,业绩报告!$BJ$2:$BJ$8229),2,0),"0")} -> 22 | F65: {=IFERROR(VLOOKUP(F$3&$A6&$A9,IF({1,0},业绩报告!$A$2:$A$8229&业绩报告!$B$2:$B$8229&业绩报告!$C$2:$C$8229,业绩报告!$BJ$2:$BJ$8229),2,0),"0")} -> 19 | G65: {=IFERROR(VLOOKUP(G$3&$A6&$A9,IF({1,0},业绩报告!$A$2:$A$8229&业绩报告!$B$2:$B$8229&业绩报告!$C$2:$C$8229,业绩报告!$BJ$2:$BJ$8229),2,0),"0")} -> 23 | H65: {=IFERROR(VLOOKUP(H$3&$A6&$A9,IF({1,0},业绩报告!$A$2:$A$8229&业绩报告!$B$2:$B$8229&业绩报告!$C$2:$C$8229,业绩报告!$BJ$2:$BJ$8229),2,0),"0")} -> 19 | I65: {=IFERROR(VLOOKUP(I$3&$A6&$A9,IF({1,0},业绩报告!$A$2:$A$8229&业绩报告!$B$2:$B$8229&业绩报告!$C$2:$C$8229,业绩报告!$BJ$2:$BJ$8229),2,0),"0")} -> 0 | J65: =SUM(C65:I65) -> 128 | K65: {=IFERROR(VLOOKUP(K$3&$A6&$A9,IF({1,0},业绩报告!$A$2:$A$8229&业绩报告!$B$2:$B$8229&业绩报告!$C$2:$C$8229,业绩报告!$BJ$2:$BJ$8229),2,0),"")} -> 23 | L65: {=IFERROR(VLOOKUP(L$3&$A6&$A9,IF({1,0},业绩报告!$A$2:$A$8229&业绩报告!$B$2:$B$8229&业绩报告!$C$2:$C$8229,业绩报告!$BJ$2:$BJ$8229),2,0),"")} -> 18 | M65: {=IFERROR(VLOOKUP(M$3&$A6&$A9,IF({1,0},业绩报告!$A$2:$A$8229&业绩报告!$B$2:$B$8229&业绩报告!$C$2:$C$8229,业绩报告!$BJ$2:$BJ$8229),2,0),"")} -> 12 | N65: {=IFERROR(VLOOKUP(N$3&$A6&$A9,IF({1,0},业绩报告!$A$2:$A$8229&业绩报告!$B$2:$B$8229&业绩报告!$C$2:$C$8229,业绩报告!$BJ$2:$BJ$8229),2,0),"")} -> 16 | O65: {=IFERROR(VLOOKUP(O$3&$A6&$A9,IF({1,0},业绩报告!$A$2:$A$8229&业绩报告!$B$2:$B$8229&业绩报告!$C$2:$C$8229,业绩报告!$BJ$2:$BJ$8229),2,0),"")} -> 33 | P65: {=IFERROR(VLOOKUP(P$3&$A6&$A9,IF({1,0},业绩报告!$A$2:$A$8229&业绩报告!$B$2:$B$8229&业绩报告!$C$2:$C$8229,业绩报告!$BJ$2:$BJ$8229),2,0),"")} -> 15 | Q65: {=IFERROR(VLOOKUP(Q$3&$A6&$A9,IF({1,0},业绩报告!$A$2:$A$8229&业绩报告!$B$2:$B$8229&业绩报告!$C$2:$C$8229,业绩报告!$BJ$2:$BJ$8229),2,0),"")} -> 16 | R65: =SUM(K65:Q65) -> 133
B66: 展示广告单量 | C66: {=IFERROR(VLOOKUP(C$3&$A6&$A9,IF({1,0},业绩报告!$A$2:$A$8229&业绩报告!$B$2:$B$8229&业绩报告!$C$2:$C$8229,业绩报告!$BK$2:$BK$8229),2,0),"0")} -> 1 | D66: {=IFERROR(VLOOKUP(D$3&$A6&$A9,IF({1,0},业绩报告!$A$2:$A$8229&业绩报告!$B$2:$B$8229&业绩报告!$C$2:$C$8229,业绩报告!$BK$2:$BK$8229),2,0),"0")} -> 0 | E66: {=IFERROR(VLOOKUP(E$3&$A6&$A9,IF({1,0},业绩报告!$A$2:$A$8229&业绩报告!$B$2:$B$8229&业绩报告!$C$2:$C$8229,业绩报告!$BK$2:$BK$8229),2,0),"0")} -> 1 | F66: {=IFERROR(VLOOKUP(F$3&$A6&$A9,IF({1,0},业绩报告!$A$2:$A$8229&业绩报告!$B$2:$B$8229&业绩报告!$C$2:$C$8229,业绩报告!$BK$2:$BK$8229),2,0),"0")} -> 4 | G66: {=IFERROR(VLOOKUP(G$3&$A6&$A9,IF({1,0},业绩报告!$A$2:$A$8229&业绩报告!$B$2:$B$8229&业绩报告!$C$2:$C$8229,业绩报告!$BK$2:$BK$8229),2,0),"0")} -> 2 | H66: {=IFERROR(VLOOKUP(H$3&$A6&$A9,IF({1,0},业绩报告!$A$2:$A$8229&业绩报告!$B$2:$B$8229&业绩报告!$C$2:$C$8229,业绩报告!$BK$2:$BK$8229),2,0),"0")} -> 1 | I66: {=IFERROR(VLOOKUP(I$3&$A6&$A9,IF({1,0},业绩报告!$A$2:$A$8229&业绩报告!$B$2:$B$8229&业绩报告!$C$2:$C$8229,业绩报告!$BK$2:$BK$8229),2,0),"0")} -> 0 | J66: =SUM(C66:I66) -> 9 | K66: {=IFERROR(VLOOKUP(K$3&$A6&$A9,IF({1,0},业绩报告!$A$2:$A$8229&业绩报告!$B$2:$B$8229&业绩报告!$C$2:$C$8229,业绩报告!$BK$2:$BK$8229),2,0),"")} -> 0 | L66: {=IFERROR(VLOOKUP(L$3&$A6&$A9,IF({1,0},业绩报告!$A$2:$A$8229&业绩报告!$B$2:$B$8229&业绩报告!$C$2:$C$8229,业绩报告!$BK$2:$BK$8229),2,0),"")} -> 3 | M66: {=IFERROR(VLOOKUP(M$3&$A6&$A9,IF({1,0},业绩报告!$A$2:$A$8229&业绩报告!$B$2:$B$8229&业绩报告!$C$2:$C$8229,业绩报告!$BK$2:$BK$8229),2,0),"")} -> 0 | N66: {=IFERROR(VLOOKUP(N$3&$A6&$A9,IF({1,0},业绩报告!$A$2:$A$8229&业绩报告!$B$2:$B$8229&业绩报告!$C$2:$C$8229,业绩报告!$BK$2:$BK$8229),2,0),"")} -> 3 | O66: {=IFERROR(VLOOKUP(O$3&$A6&$A9,IF({1,0},业绩报告!$A$2:$A$8229&业绩报告!$B$2:$B$8229&业绩报告!$C$2:$C$8229,业绩报告!$BK$2:$BK$8229),2,0),"")} -> 3 | P66: {=IFERROR(VLOOKUP(P$3&$A6&$A9,IF({1,0},业绩报告!$A$2:$A$8229&业绩报告!$B$2:$B$8229&业绩报告!$C$2:$C$8229,业绩报告!$BK$2:$BK$8229),2,0),"")} -> 3 | Q66: {=IFERROR(VLOOKUP(Q$3&$A6&$A9,IF({1,0},业绩报告!$A$2:$A$8229&业绩报告!$B$2:$B$8229&业绩报告!$C$2:$C$8229,业绩报告!$BK$2:$BK$8229),2,0),"")} -> 3 | R66: =SUM(K66:Q66) -> 15
B67: 展示广告点击率 | C67: {=IFERROR(VLOOKUP(C$3&$A6&$A9,IF({1,0},业绩报告!$A$2:$A$8229&业绩报告!$B$2:$B$8229&业绩报告!$C$2:$C$8229,业绩报告!$BL$2:$BL$8229),2,0),"0")} -> 0.0076815642 | D67: {=IFERROR(VLOOKUP(D$3&$A6&$A9,IF({1,0},业绩报告!$A$2:$A$8229&业绩报告!$B$2:$B$8229&业绩报告!$C$2:$C$8229,业绩报告!$BL$2:$BL$8229),2,0),"0")} -> 0.00518836 | E67: {=IFERROR(VLOOKUP(E$3&$A6&$A9,IF({1,0},业绩报告!$A$2:$A$8229&业绩报告!$B$2:$B$8229&业绩报告!$C$2:$C$8229,业绩报告!$BL$2:$BL$8229),2,0),"0")} -> 0.00564392 | F67: {=IFERROR(VLOOKUP(F$3&$A6&$A9,IF({1,0},业绩报告!$A$2:$A$8229&业绩报告!$B$2:$B$8229&业绩报告!$C$2:$C$8229,业绩报告!$BL$2:$BL$8229),2,0),"0")} -> 0.0069267226 | G67: {=IFERROR(VLOOKUP(G$3&$A6&$A9,IF({1,0},业绩报告!$A$2:$A$8229&业绩报告!$B$2:$B$8229&业绩报告!$C$2:$C$8229,业绩报告!$BL$2:$BL$8229),2,0),"0")} -> 0.007615894 | H67: {=IFERROR(VLOOKUP(H$3&$A6&$A9,IF({1,0},业绩报告!$A$2:$A$8229&业绩报告!$B$2:$B$8229&业绩报告!$C$2:$C$8229,业绩报告!$BL$2:$BL$8229),2,0),"0")} -> 0.008095441 | I67: {=IFERROR(VLOOKUP(I$3&$A6&$A9,IF({1,0},业绩报告!$A$2:$A$8229&业绩报告!$B$2:$B$8229&业绩报告!$C$2:$C$8229,业绩报告!$BL$2:$BL$8229),2,0),"0")} -> 0 | J67: =J65/J64 -> 0.0066304066 | K67: {=IFERROR(VLOOKUP(K$3&$A6&$A9,IF({1,0},业绩报告!$A$2:$A$8229&业绩报告!$B$2:$B$8229&业绩报告!$C$2:$C$8229,业绩报告!$BL$2:$BL$8229),2,0),"")} -> 0.013964784 | L67: {=IFERROR(VLOOKUP(L$3&$A6&$A9,IF({1,0},业绩报告!$A$2:$A$8229&业绩报告!$B$2:$B$8229&业绩报告!$C$2:$C$8229,业绩报告!$BL$2:$BL$8229),2,0),"")} -> 0.011271133 | M67: {=IFERROR(VLOOKUP(M$3&$A6&$A9,IF({1,0},业绩报告!$A$2:$A$8229&业绩报告!$B$2:$B$8229&业绩报告!$C$2:$C$8229,业绩报告!$BL$2:$BL$8229),2,0),"")} -> 0.0069124424 | N67: {=IFERROR(VLOOKUP(N$3&$A6&$A9,IF({1,0},业绩报告!$A$2:$A$8229&业绩报告!$B$2:$B$8229&业绩报告!$C$2:$C$8229,业绩报告!$BL$2:$BL$8229),2,0),"")} -> 0.0086299892 | O67: {=IFERROR(VLOOKUP(O$3&$A6&$A9,IF({1,0},业绩报告!$A$2:$A$8229&业绩报告!$B$2:$B$8229&业绩报告!$C$2:$C$8229,业绩报告!$BL$2:$BL$8229),2,0),"")} -> 0.01187905 | P67: {=IFERROR(VLOOKUP(P$3&$A6&$A9,IF({1,0},业绩报告!$A$2:$A$8229&业绩报告!$B$2:$B$8229&业绩报告!$C$2:$C$8229,业绩报告!$BL$2:$BL$8229),2,0),"")} -> 0.006663705 | Q67: {=IFERROR(VLOOKUP(Q$3&$A6&$A9,IF({1,0},业绩报告!$A$2:$A$8229&业绩报告!$B$2:$B$8229&业绩报告!$C$2:$C$8229,业绩报告!$BL$2:$BL$8229),2,0),"")} -> 0.0099750623 | R67: =R65/R64 -> 0.0098759932
B68: 展示广告转化率 | C68: {=IFERROR(VLOOKUP(C$3&$A6&$A9,IF({1,0},业绩报告!$A$2:$A$8229&业绩报告!$B$2:$B$8229&业绩报告!$C$2:$C$8229,业绩报告!$BM$2:$BM$8229),2,0),"0")} -> 0.045454545 | D68: {=IFERROR(VLOOKUP(D$3&$A6&$A9,IF({1,0},业绩报告!$A$2:$A$8229&业绩报告!$B$2:$B$8229&业绩报告!$C$2:$C$8229,业绩报告!$BM$2:$BM$8229),2,0),"0")} -> 0 | E68: {=IFERROR(VLOOKUP(E$3&$A6&$A9,IF({1,0},业绩报告!$A$2:$A$8229&业绩报告!$B$2:$B$8229&业绩报告!$C$2:$C$8229,业绩报告!$BM$2:$BM$8229),2,0),"0")} -> 0.045454545 | F68: {=IFERROR(VLOOKUP(F$3&$A6&$A9,IF({1,0},业绩报告!$A$2:$A$8229&业绩报告!$B$2:$B$8229&业绩报告!$C$2:$C$8229,业绩报告!$BM$2:$BM$8229),2,0),"0")} -> 0.21052632 | G68: {=IFERROR(VLOOKUP(G$3&$A6&$A9,IF({1,0},业绩报告!$A$2:$A$8229&业绩报告!$B$2:$B$8229&业绩报告!$C$2:$C$8229,业绩报告!$BM$2:$BM$8229),2,0),"0")} -> 0.086956522 | H68: {=IFERROR(VLOOKUP(H$3&$A6&$A9,IF({1,0},业绩报告!$A$2:$A$8229&业绩报告!$B$2:$B$8229&业绩报告!$C$2:$C$8229,业绩报告!$BM$2:$BM$8229),2,0),"0")} -> 0.052631579 | I68: {=IFERROR(VLOOKUP(I$3&$A6&$A9,IF({1,0},业绩报告!$A$2:$A$8229&业绩报告!$B$2:$B$8229&业绩报告!$C$2:$C$8229,业绩报告!$BM$2:$BM$8229),2,0),"0")} -> 0 | J68: =J66/J65 -> 0.0703125 | K68: {=IFERROR(VLOOKUP(K$3&$A6&$A9,IF({1,0},业绩报告!$A$2:$A$8229&业绩报告!$B$2:$B$8229&业绩报告!$C$2:$C$8229,业绩报告!$BM$2:$BM$8229),2,0),"")} -> 0 | L68: {=IFERROR(VLOOKUP(L$3&$A6&$A9,IF({1,0},业绩报告!$A$2:$A$8229&业绩报告!$B$2:$B$8229&业绩报告!$C$2:$C$8229,业绩报告!$BM$2:$BM$8229),2,0),"")} -> 0.16666667 | M68: {=IFERROR(VLOOKUP(M$3&$A6&$A9,IF({1,0},业绩报告!$A$2:$A$8229&业绩报告!$B$2:$B$8229&业绩报告!$C$2:$C$8229,业绩报告!$BM$2:$BM$8229),2,0),"")} -> 0 | N68: {=IFERROR(VLOOKUP(N$3&$A6&$A9,IF({1,0},业绩报告!$A$2:$A$8229&业绩报告!$B$2:$B$8229&业绩报告!$C$2:$C$8229,业绩报告!$BM$2:$BM$8229),2,0),"")} -> 0.1875 | O68: {=IFERROR(VLOOKUP(O$3&$A6&$A9,IF({1,0},业绩报告!$A$2:$A$8229&业绩报告!$B$2:$B$8229&业绩报告!$C$2:$C$8229,业绩报告!$BM$2:$BM$8229),2,0),"")} -> 0.090909091 | P68: {=IFERROR(VLOOKUP(P$3&$A6&$A9,IF({1,0},业绩报告!$A$2:$A$8229&业绩报告!$B$2:$B$8229&业绩报告!$C$2:$C$8229,业绩报告!$BM$2:$BM$8229),2,0),"")} -> 0.2 | Q68: {=IFERROR(VLOOKUP(Q$3&$A6&$A9,IF({1,0},业绩报告!$A$2:$A$8229&业绩报告!$B$2:$B$8229&业绩报告!$C$2:$C$8229,业绩报告!$BM$2:$BM$8229),2,0),"")} -> 0.1875 | R68: =R66/R65 -> 0.11278195
B69: 展示广告花费 | C69: {=IFERROR(VLOOKUP(C$3&$A6&$A9,IF({1,0},业绩报告!$A$2:$A$8229&业绩报告!$B$2:$B$8229&业绩报告!$C$2:$C$8229,业绩报告!$BN$2:$BN$8229),2,0),"0")} -> 10.95 | D69: {=IFERROR(VLOOKUP(D$3&$A6&$A9,IF({1,0},业绩报告!$A$2:$A$8229&业绩报告!$B$2:$B$8229&业绩报告!$C$2:$C$8229,业绩报告!$BN$2:$BN$8229),2,0),"0")} -> 10.28 | E69: {=IFERROR(VLOOKUP(E$3&$A6&$A9,IF({1,0},业绩报告!$A$2:$A$8229&业绩报告!$B$2:$B$8229&业绩报告!$C$2:$C$8229,业绩报告!$BN$2:$BN$8229),2,0),"0")} -> 9.94 | F69: {=IFERROR(VLOOKUP(F$3&$A6&$A9,IF({1,0},业绩报告!$A$2:$A$8229&业绩报告!$B$2:$B$8229&业绩报告!$C$2:$C$8229,业绩报告!$BN$2:$BN$8229),2,0),"0")} -> 9.87 | G69: {=IFERROR(VLOOKUP(G$3&$A6&$A9,IF({1,0},业绩报告!$A$2:$A$8229&业绩报告!$B$2:$B$8229&业绩报告!$C$2:$C$8229,业绩报告!$BN$2:$BN$8229),2,0),"0")} -> 10.1 | H69: {=IFERROR(VLOOKUP(H$3&$A6&$A9,IF({1,0},业绩报告!$A$2:$A$8229&业绩报告!$B$2:$B$8229&业绩报告!$C$2:$C$8229,业绩报告!$BN$2:$BN$8229),2,0),"0")} -> 11.38 | I69: {=IFERROR(VLOOKUP(I$3&$A6&$A9,IF({1,0},业绩报告!$A$2:$A$8229&业绩报告!$B$2:$B$8229&业绩报告!$C$2:$C$8229,业绩报告!$BN$2:$BN$8229),2,0),"0")} -> 0 | J69: =SUM(C69:I69) -> 62.52 | K69: {=IFERROR(VLOOKUP(K$3&$A6&$A9,IF({1,0},业绩报告!$A$2:$A$8229&业绩报告!$B$2:$B$8229&业绩报告!$C$2:$C$8229,业绩报告!$BN$2:$BN$8229),2,0),"")} -> 13.72 | L69: {=IFERROR(VLOOKUP(L$3&$A6&$A9,IF({1,0},业绩报告!$A$2:$A$8229&业绩报告!$B$2:$B$8229&业绩报告!$C$2:$C$8229,业绩报告!$BN$2:$BN$8229),2,0),"")} -> 9.86 | M69: {=IFERROR(VLOOKUP(M$3&$A6&$A9,IF({1,0},业绩报告!$A$2:$A$8229&业绩报告!$B$2:$B$8229&业绩报告!$C$2:$C$8229,业绩报告!$BN$2:$BN$8229),2,0),"")} -> 6.6 | N69: {=IFERROR(VLOOKUP(N$3&$A6&$A9,IF({1,0},业绩报告!$A$2:$A$8229&业绩报告!$B$2:$B$8229&业绩报告!$C$2:$C$8229,业绩报告!$BN$2:$BN$8229),2,0),"")} -> 9.61 | O69: {=IFERROR(VLOOKUP(O$3&$A6&$A9,IF({1,0},业绩报告!$A$2:$A$8229&业绩报告!$B$2:$B$8229&业绩报告!$C$2:$C$8229,业绩报告!$BN$2:$BN$8229),2,0),"")} -> 18.9 | P69: {=IFERROR(VLOOKUP(P$3&$A6&$A9,IF({1,0},业绩报告!$A$2:$A$8229&业绩报告!$B$2:$B$8229&业绩报告!$C$2:$C$8229,业绩报告!$BN$2:$BN$8229),2,0),"")} -> 9.77 | Q69: {=IFERROR(VLOOKUP(Q$3&$A6&$A9,IF({1,0},业绩报告!$A$2:$A$8229&业绩报告!$B$2:$B$8229&业绩报告!$C$2:$C$8229,业绩报告!$BN$2:$BN$8229),2,0),"")} -> 10.45 | R69: =SUM(K69:Q69) -> 78.91
B70: 展示广告销售额 | C70: {=IFERROR(VLOOKUP(C$3&$A6&$A9,IF({1,0},业绩报告!$A$2:$A$8229&业绩报告!$B$2:$B$8229&业绩报告!$C$2:$C$8229,业绩报告!$BO$2:$BO$8229),2,0),"0")} -> 11.99 | D70: {=IFERROR(VLOOKUP(D$3&$A6&$A9,IF({1,0},业绩报告!$A$2:$A$8229&业绩报告!$B$2:$B$8229&业绩报告!$C$2:$C$8229,业绩报告!$BO$2:$BO$8229),2,0),"0")} -> 0 | E70: {=IFERROR(VLOOKUP(E$3&$A6&$A9,IF({1,0},业绩报告!$A$2:$A$8229&业绩报告!$B$2:$B$8229&业绩报告!$C$2:$C$8229,业绩报告!$BO$2:$BO$8229),2,0),"0")} -> 11.99 | F70: {=IFERROR(VLOOKUP(F$3&$A6&$A9,IF({1,0},业绩报告!$A$2:$A$8229&业绩报告!$B$2:$B$8229&业绩报告!$C$2:$C$8229,业绩报告!$BO$2:$BO$8229),2,0),"0")} -> 47.96 | G70: {=IFERROR(VLOOKUP(G$3&$A6&$A9,IF({1,0},业绩报告!$A$2:$A$8229&业绩报告!$B$2:$B$8229&业绩报告!$C$2:$C$8229,业绩报告!$BO$2:$BO$8229),2,0),"0")} -> 19.18 | H70: {=IFERROR(VLOOKUP(H$3&$A6&$A9,IF({1,0},业绩报告!$A$2:$A$8229&业绩报告!$B$2:$B$8229&业绩报告!$C$2:$C$8229,业绩报告!$BO$2:$BO$8229),2,0),"0")} -> 19.18 | I70: {=IFERROR(VLOOKUP(I$3&$A6&$A9,IF({1,0},业绩报告!$A$2:$A$8229&业绩报告!$B$2:$B$8229&业绩报告!$C$2:$C$8229,业绩报告!$BO$2:$BO$8229),2,0),"0")} -> 0 | J70: =SUM(C70:I70) -> 110.3 | K70: {=IFERROR(VLOOKUP(K$3&$A6&$A9,IF({1,0},业绩报告!$A$2:$A$8229&业绩报告!$B$2:$B$8229&业绩报告!$C$2:$C$8229,业绩报告!$BO$2:$BO$8229),2,0),"")} -> 0 | L70: {=IFERROR(VLOOKUP(L$3&$A6&$A9,IF({1,0},业绩报告!$A$2:$A$8229&业绩报告!$B$2:$B$8229&业绩报告!$C$2:$C$8229,业绩报告!$BO$2:$BO$8229),2,0),"")} -> 35.97 | M70: {=IFERROR(VLOOKUP(M$3&$A6&$A9,IF({1,0},业绩报告!$A$2:$A$8229&业绩报告!$B$2:$B$8229&业绩报告!$C$2:$C$8229,业绩报告!$BO$2:$BO$8229),2,0),"")} -> 0 | N70: {=IFERROR(VLOOKUP(N$3&$A6&$A9,IF({1,0},业绩报告!$A$2:$A$8229&业绩报告!$B$2:$B$8229&业绩报告!$C$2:$C$8229,业绩报告!$BO$2:$BO$8229),2,0),"")} -> 35.97 | O70: {=IFERROR(VLOOKUP(O$3&$A6&$A9,IF({1,0},业绩报告!$A$2:$A$8229&业绩报告!$B$2:$B$8229&业绩报告!$C$2:$C$8229,业绩报告!$BO$2:$BO$8229),2,0),"")} -> 35.97 | P70: {=IFERROR(VLOOKUP(P$3&$A6&$A9,IF({1,0},业绩报告!$A$2:$A$8229&业绩报告!$B$2:$B$8229&业绩报告!$C$2:$C$8229,业绩报告!$BO$2:$BO$8229),2,0),"")} -> 35.97 | Q70: {=IFERROR(VLOOKUP(Q$3&$A6&$A9,IF({1,0},业绩报告!$A$2:$A$8229&业绩报告!$B$2:$B$8229&业绩报告!$C$2:$C$8229,业绩报告!$BO$2:$BO$8229),2,0),"")} -> 35.97 | R70: =SUM(K70:Q70) -> 179.85
B71: 展示广告acos | C71: =IFERROR(C69/C70,"0") -> 0.91326105 | D71: =IFERROR(D69/D70,"0") -> 0 | E71: =IFERROR(E69/E70,"0") -> 0.82902419 | F71: =IFERROR(F69/F70,"0") -> 0.2057965 | G71: =IFERROR(G69/G70,"0") -> 0.5265902 | H71: {=IFERROR(H69/H70,"0")} -> 0.59332638 | I71: =IFERROR(I69/I70,"0") -> 0 | J71: =J69/J70 -> 0.56681777 | K71: {=IFERROR(VLOOKUP(K$3&$A6&$A9,IF({1,0},业绩报告!$A$2:$A$8229&业绩报告!$B$2:$B$8229&业绩报告!$C$2:$C$8229,业绩报告!$BP$2:$BP$8229),2,0),"")} | L71: {=IFERROR(VLOOKUP(L$3&$A6&$A9,IF({1,0},业绩报告!$A$2:$A$8229&业绩报告!$B$2:$B$8229&业绩报告!$C$2:$C$8229,业绩报告!$BP$2:$BP$8229),2,0),"")} -> 0.27411732 | M71: {=IFERROR(VLOOKUP(M$3&$A6&$A9,IF({1,0},业绩报告!$A$2:$A$8229&业绩报告!$B$2:$B$8229&业绩报告!$C$2:$C$8229,业绩报告!$BP$2:$BP$8229),2,0),"")} | N71: {=IFERROR(VLOOKUP(N$3&$A6&$A9,IF({1,0},业绩报告!$A$2:$A$8229&业绩报告!$B$2:$B$8229&业绩报告!$C$2:$C$8229,业绩报告!$BP$2:$BP$8229),2,0),"")} -> 0.26716708 | O71: {=IFERROR(VLOOKUP(O$3&$A6&$A9,IF({1,0},业绩报告!$A$2:$A$8229&业绩报告!$B$2:$B$8229&业绩报告!$C$2:$C$8229,业绩报告!$BP$2:$BP$8229),2,0),"")} -> 0.52543786 | P71: {=IFERROR(VLOOKUP(P$3&$A6&$A9,IF({1,0},业绩报告!$A$2:$A$8229&业绩报告!$B$2:$B$8229&业绩报告!$C$2:$C$8229,业绩报告!$BP$2:$BP$8229),2,0),"")} -> 0.27161523 | Q71: {=IFERROR(VLOOKUP(Q$3&$A6&$A9,IF({1,0},业绩报告!$A$2:$A$8229&业绩报告!$B$2:$B$8229&业绩报告!$C$2:$C$8229,业绩报告!$BP$2:$BP$8229),2,0),"")} -> 0.29051988 | R71: =R69/R70 -> 0.43875452
B72: 品类广告展现 | C72: {=IFERROR(VLOOKUP(C$3&$A6&$A9,IF({1,0},业绩报告!$A$2:$A$8229&业绩报告!$B$2:$B$8229&业绩报告!$C$2:$C$8229,业绩报告!$BQ$2:$BQ$8229),2,0),"")} -> 0 | D72: {=IFERROR(VLOOKUP(D$3&$A6&$A9,IF({1,0},业绩报告!$A$2:$A$8229&业绩报告!$B$2:$B$8229&业绩报告!$C$2:$C$8229,业绩报告!$BQ$2:$BQ$8229),2,0),"")} -> 0 | E72: {=IFERROR(VLOOKUP(E$3&$A6&$A9,IF({1,0},业绩报告!$A$2:$A$8229&业绩报告!$B$2:$B$8229&业绩报告!$C$2:$C$8229,业绩报告!$BQ$2:$BQ$8229),2,0),"")} -> 0 | F72: {=IFERROR(VLOOKUP(F$3&$A6&$A9,IF({1,0},业绩报告!$A$2:$A$8229&业绩报告!$B$2:$B$8229&业绩报告!$C$2:$C$8229,业绩报告!$BQ$2:$BQ$8229),2,0),"")} -> 0 | G72: {=IFERROR(VLOOKUP(G$3&$A6&$A9,IF({1,0},业绩报告!$A$2:$A$8229&业绩报告!$B$2:$B$8229&业绩报告!$C$2:$C$8229,业绩报告!$BQ$2:$BQ$8229),2,0),"")} -> 0 | H72: {=IFERROR(VLOOKUP(H$3&$A6&$A9,IF({1,0},业绩报告!$A$2:$A$8229&业绩报告!$B$2:$B$8229&业绩报告!$C$2:$C$8229,业绩报告!$BQ$2:$BQ$8229),2,0),"")} -> 0 | I72: {=IFERROR(VLOOKUP(I$3&$A6&$A9,IF({1,0},业绩报告!$A$2:$A$8229&业绩报告!$B$2:$B$8229&业绩报告!$C$2:$C$8229,业绩报告!$BQ$2:$BQ$8229),2,0),"")} -> 0
B73: 品类广告点击量 | C73: {=IFERROR(VLOOKUP(C$3&$A6&$A9,IF({1,0},业绩报告!$A$2:$A$8229&业绩报告!$B$2:$B$8229&业绩报告!$C$2:$C$8229,业绩报告!$BR$2:$BR$8229),2,0),"0")} -> 0 | D73: {=IFERROR(VLOOKUP(D$3&$A6&$A9,IF({1,0},业绩报告!$A$2:$A$8229&业绩报告!$B$2:$B$8229&业绩报告!$C$2:$C$8229,业绩报告!$BR$2:$BR$8229),2,0),"0")} -> 0 | E73: {=IFERROR(VLOOKUP(E$3&$A6&$A9,IF({1,0},业绩报告!$A$2:$A$8229&业绩报告!$B$2:$B$8229&业绩报告!$C$2:$C$8229,业绩报告!$BR$2:$BR$8229),2,0),"0")} -> 0 | F73: {=IFERROR(VLOOKUP(F$3&$A6&$A9,IF({1,0},业绩报告!$A$2:$A$8229&业绩报告!$B$2:$B$8229&业绩报告!$C$2:$C$8229,业绩报告!$BR$2:$BR$8229),2,0),"0")} -> 0 | G73: {=IFERROR(VLOOKUP(G$3&$A6&$A9,IF({1,0},业绩报告!$A$2:$A$8229&业绩报告!$B$2:$B$8229&业绩报告!$C$2:$C$8229,业绩报告!$BR$2:$BR$8229),2,0),"0")} -> 0 | H73: {=IFERROR(VLOOKUP(H$3&$A6&$A9,IF({1,0},业绩报告!$A$2:$A$8229&业绩报告!$B$2:$B$8229&业绩报告!$C$2:$C$8229,业绩报告!$BR$2:$BR$8229),2,0),"0")} -> 0 | I73: {=IFERROR(VLOOKUP(I$3&$A6&$A9,IF({1,0},业绩报告!$A$2:$A$8229&业绩报告!$B$2:$B$8229&业绩报告!$C$2:$C$8229,业绩报告!$BR$2:$BR$8229),2,0),"0")} -> 0
B74: 品类广告单量 | C74: {=IFERROR(VLOOKUP(C$3&$A6&$A9,IF({1,0},业绩报告!$A$2:$A$8229&业绩报告!$B$2:$B$8229&业绩报告!$C$2:$C$8229,业绩报告!$BS$2:$BS$8229),2,0),"0")} -> 0 | D74: {=IFERROR(VLOOKUP(D$3&$A6&$A9,IF({1,0},业绩报告!$A$2:$A$8229&业绩报告!$B$2:$B$8229&业绩报告!$C$2:$C$8229,业绩报告!$BS$2:$BS$8229),2,0),"0")} -> 0 | E74: {=IFERROR(VLOOKUP(E$3&$A6&$A9,IF({1,0},业绩报告!$A$2:$A$8229&业绩报告!$B$2:$B$8229&业绩报告!$C$2:$C$8229,业绩报告!$BS$2:$BS$8229),2,0),"0")} -> 0 | F74: {=IFERROR(VLOOKUP(F$3&$A6&$A9,IF({1,0},业绩报告!$A$2:$A$8229&业绩报告!$B$2:$B$8229&业绩报告!$C$2:$C$8229,业绩报告!$BS$2:$BS$8229),2,0),"0")} -> 0 | G74: {=IFERROR(VLOOKUP(G$3&$A6&$A9,IF({1,0},业绩报告!$A$2:$A$8229&业绩报告!$B$2:$B$8229&业绩报告!$C$2:$C$8229,业绩报告!$BS$2:$BS$8229),2,0),"0")} -> 0 | H74: {=IFERROR(VLOOKUP(H$3&$A6&$A9,IF({1,0},业绩报告!$A$2:$A$8229&业绩报告!$B$2:$B$8229&业绩报告!$C$2:$C$8229,业绩报告!$BS$2:$BS$8229),2,0),"0")} -> 0 | I74: {=IFERROR(VLOOKUP(I$3&$A6&$A9,IF({1,0},业绩报告!$A$2:$A$8229&业绩报告!$B$2:$B$8229&业绩报告!$C$2:$C$8229,业绩报告!$BS$2:$BS$8229),2,0),"0")} -> 0
B75: 品类广告点击率 | C75: {=IFERROR(VLOOKUP(C$3&$A6&$A9,IF({1,0},业绩报告!$A$2:$A$8229&业绩报告!$B$2:$B$8229&业绩报告!$C$2:$C$8229,业绩报告!$BT$2:$BT$8229),2,0),"0")} -> 0 | D75: {=IFERROR(VLOOKUP(D$3&$A6&$A9,IF({1,0},业绩报告!$A$2:$A$8229&业绩报告!$B$2:$B$8229&业绩报告!$C$2:$C$8229,业绩报告!$BT$2:$BT$8229),2,0),"0")} -> 0 | E75: {=IFERROR(VLOOKUP(E$3&$A6&$A9,IF({1,0},业绩报告!$A$2:$A$8229&业绩报告!$B$2:$B$8229&业绩报告!$C$2:$C$8229,业绩报告!$BT$2:$BT$8229),2,0),"0")} -> 0 | F75: {=IFERROR(VLOOKUP(F$3&$A6&$A9,IF({1,0},业绩报告!$A$2:$A$8229&业绩报告!$B$2:$B$8229&业绩报告!$C$2:$C$8229,业绩报告!$BT$2:$BT$8229),2,0),"0")} -> 0 | G75: {=IFERROR(VLOOKUP(G$3&$A6&$A9,IF({1,0},业绩报告!$A$2:$A$8229&业绩报告!$B$2:$B$8229&业绩报告!$C$2:$C$8229,业绩报告!$BT$2:$BT$8229),2,0),"0")} -> 0 | H75: {=IFERROR(VLOOKUP(H$3&$A6&$A9,IF({1,0},业绩报告!$A$2:$A$8229&业绩报告!$B$2:$B$8229&业绩报告!$C$2:$C$8229,业绩报告!$BT$2:$BT$8229),2,0),"0")} -> 0 | I75: {=IFERROR(VLOOKUP(I$3&$A6&$A9,IF({1,0},业绩报告!$A$2:$A$8229&业绩报告!$B$2:$B$8229&业绩报告!$C$2:$C$8229,业绩报告!$BT$2:$BT$8229),2,0),"0")} -> 0
B76: 品类广告转化率 | C76: {=IFERROR(VLOOKUP(C$3&$A6&$A9,IF({1,0},业绩报告!$A$2:$A$8229&业绩报告!$B$2:$B$8229&业绩报告!$C$2:$C$8229,业绩报告!$BU$2:$BU$8229),2,0),"0")} -> 0 | D76: {=IFERROR(VLOOKUP(D$3&$A6&$A9,IF({1,0},业绩报告!$A$2:$A$8229&业绩报告!$B$2:$B$8229&业绩报告!$C$2:$C$8229,业绩报告!$BU$2:$BU$8229),2,0),"0")} -> 0 | E76: {=IFERROR(VLOOKUP(E$3&$A6&$A9,IF({1,0},业绩报告!$A$2:$A$8229&业绩报告!$B$2:$B$8229&业绩报告!$C$2:$C$8229,业绩报告!$BU$2:$BU$8229),2,0),"0")} -> 0 | F76: {=IFERROR(VLOOKUP(F$3&$A6&$A9,IF({1,0},业绩报告!$A$2:$A$8229&业绩报告!$B$2:$B$8229&业绩报告!$C$2:$C$8229,业绩报告!$BU$2:$BU$8229),2,0),"0")} -> 0 | G76: {=IFERROR(VLOOKUP(G$3&$A6&$A9,IF({1,0},业绩报告!$A$2:$A$8229&业绩报告!$B$2:$B$8229&业绩报告!$C$2:$C$8229,业绩报告!$BU$2:$BU$8229),2,0),"0")} -> 0 | H76: {=IFERROR(VLOOKUP(H$3&$A6&$A9,IF({1,0},业绩报告!$A$2:$A$8229&业绩报告!$B$2:$B$8229&业绩报告!$C$2:$C$8229,业绩报告!$BU$2:$BU$8229),2,0),"0")} -> 0 | I76: {=IFERROR(VLOOKUP(I$3&$A6&$A9,IF({1,0},业绩报告!$A$2:$A$8229&业绩报告!$B$2:$B$8229&业绩报告!$C$2:$C$8229,业绩报告!$BU$2:$BU$8229),2,0),"0")} -> 0
B77: 品类广告花费 | C77: {=IFERROR(VLOOKUP(C$3&$A6&$A9,IF({1,0},业绩报告!$A$2:$A$8229&业绩报告!$B$2:$B$8229&业绩报告!$C$2:$C$8229,业绩报告!$BV$2:$BV$8229),2,0),"0")} -> 0 | D77: {=IFERROR(VLOOKUP(D$3&$A6&$A9,IF({1,0},业绩报告!$A$2:$A$8229&业绩报告!$B$2:$B$8229&业绩报告!$C$2:$C$8229,业绩报告!$BV$2:$BV$8229),2,0),"0")} -> 0 | E77: {=IFERROR(VLOOKUP(E$3&$A6&$A9,IF({1,0},业绩报告!$A$2:$A$8229&业绩报告!$B$2:$B$8229&业绩报告!$C$2:$C$8229,业绩报告!$BV$2:$BV$8229),2,0),"0")} -> 0 | F77: {=IFERROR(VLOOKUP(F$3&$A6&$A9,IF({1,0},业绩报告!$A$2:$A$8229&业绩报告!$B$2:$B$8229&业绩报告!$C$2:$C$8229,业绩报告!$BV$2:$BV$8229),2,0),"0")} -> 0 | G77: {=IFERROR(VLOOKUP(G$3&$A6&$A9,IF({1,0},业绩报告!$A$2:$A$8229&业绩报告!$B$2:$B$8229&业绩报告!$C$2:$C$8229,业绩报告!$BV$2:$BV$8229),2,0),"0")} -> 0 | H77: {=IFERROR(VLOOKUP(H$3&$A6&$A9,IF({1,0},业绩报告!$A$2:$A$8229&业绩报告!$B$2:$B$8229&业绩报告!$C$2:$C$8229,业绩报告!$BV$2:$BV$8229),2,0),"0")} -> 0 | I77: {=IFERROR(VLOOKUP(I$3&$A6&$A9,IF({1,0},业绩报告!$A$2:$A$8229&业绩报告!$B$2:$B$8229&业绩报告!$C$2:$C$8229,业绩报告!$BV$2:$BV$8229),2,0),"0")} -> 0
B78: 品类广告销售额 | C78: {=IFERROR(VLOOKUP(C$3&$A6&$A9,IF({1,0},业绩报告!$A$2:$A$8229&业绩报告!$B$2:$B$8229&业绩报告!$C$2:$C$8229,业绩报告!$BW$2:$BW$8229),2,0),"0")} -> 0 | D78: {=IFERROR(VLOOKUP(D$3&$A6&$A9,IF({1,0},业绩报告!$A$2:$A$8229&业绩报告!$B$2:$B$8229&业绩报告!$C$2:$C$8229,业绩报告!$BW$2:$BW$8229),2,0),"0")} -> 0 | E78: {=IFERROR(VLOOKUP(E$3&$A6&$A9,IF({1,0},业绩报告!$A$2:$A$8229&业绩报告!$B$2:$B$8229&业绩报告!$C$2:$C$8229,业绩报告!$BW$2:$BW$8229),2,0),"0")} -> 0 | F78: {=IFERROR(VLOOKUP(F$3&$A6&$A9,IF({1,0},业绩报告!$A$2:$A$8229&业绩报告!$B$2:$B$8229&业绩报告!$C$2:$C$8229,业绩报告!$BW$2:$BW$8229),2,0),"0")} -> 0 | G78: {=IFERROR(VLOOKUP(G$3&$A6&$A9,IF({1,0},业绩报告!$A$2:$A$8229&业绩报告!$B$2:$B$8229&业绩报告!$C$2:$C$8229,业绩报告!$BW$2:$BW$8229),2,0),"0")} -> 0 | H78: {=IFERROR(VLOOKUP(H$3&$A6&$A9,IF({1,0},业绩报告!$A$2:$A$8229&业绩报告!$B$2:$B$8229&业绩报告!$C$2:$C$8229,业绩报告!$BW$2:$BW$8229),2,0),"0")} -> 0 | I78: {=IFERROR(VLOOKUP(I$3&$A6&$A9,IF({1,0},业绩报告!$A$2:$A$8229&业绩报告!$B$2:$B$8229&业绩报告!$C$2:$C$8229,业绩报告!$BW$2:$BW$8229),2,0),"0")} -> 0
B79: 品类广告acos | C79: {=IFERROR(C77/C78,"0")} -> 0 | D79: {=IFERROR(D77/D78,"0")} -> 0 | E79: {=IFERROR(E77/E78,"0")} -> 0 | F79: {=IFERROR(F77/F78,"0")} -> 0 | G79: {=IFERROR(G77/G78,"0")} -> 0 | H79: {=IFERROR(H77/H78,"0")} -> 0 | I79: {=IFERROR(I77/I78,"0")} -> 0
B80: 广告曝光量（总） | C80: =IFERROR(C40+C48+C56+C64+C72,"0") -> 15434 | D80: =IFERROR(D40+D48+D56+D64+D72,"0") -> 19337 | E80: =IFERROR(E40+E48+E56+E64+E72,"0") -> 23844 | F80: =IFERROR(F40+F48+F56+F64+F72,"0") -> 16080 | G80: =IFERROR(G40+G48+G56+G64+G72,"0") -> 16670 | H80: =IFERROR(H40+H48+H56+H64+H72,"0") -> 17229 | I80: =IFERROR(I40+I48+I56+I64+I72,"0") -> 0 | J80: =I80+H80+G80+F80+E80+D80+C80 -> 108594 | K80: =IFERROR(K40+K48+K56+K64,"0") -> 15937 | L80: =IFERROR(L40+L48+L56+L64+L72,"0") -> 18844 | M80: =IFERROR(M40+M48+M56+M64+M72,"0") -> 17489 | N80: =IFERROR(N40+N48+N56+N64+N72,"0") -> 17888 | O80: =IFERROR(O40+O48+O56+O64+O72,"0") -> 27493 | P80: =IFERROR(P40+P48+P56+P64+P72,"0") -> 21216 | Q80: =IFERROR(Q40+Q48+Q56+Q64+Q72,"0") -> 13259 | R80: =SUM(K80:Q80) -> 132126
B81: 广告点击量（总） | C81: =IFERROR(C41+C49+C57+C65+C73,"0") -> 76 | D81: =IFERROR(D41+D49+D57+D65+D73,"0") -> 59 | E81: =IFERROR(E41+E49+E57+E65+E73,"0") -> 87 | F81: =IFERROR(F41+F49+F57+F65+F73,"0") -> 75 | G81: =IFERROR(G41+G49+G57+G65+G73,"0") -> 91 | H81: =IFERROR(H41+H49+H57+H65+H73,"0") -> 98 | I81: =IFERROR(I41+I49+I57+I65+I73,"0") -> 0 | J81: =I81+H81+G81+F81+E81+D81+C81 -> 486 | K81: =IFERROR(K41+K49+K57+K65,"0") -> 91 | L81: =IFERROR(L41+L49+L57+L65+L73,"0") -> 109 | M81: =IFERROR(M41+M49+M57+M65+M73,"0") -> 88 | N81: =IFERROR(N41+N49+N57+N65+N73,"0") -> 90 | O81: =IFERROR(O41+O49+O57+O65+O73,"0") -> 121 | P81: =IFERROR(P41+P49+P57+P65+P73,"0") -> 87 | Q81: =IFERROR(Q41+Q49+Q57+Q65+Q73,"0") -> 67 | R81: =SUM(K81:Q81) -> 653
B82: 广告单量 | C82: =IFERROR(C42+C50+C58+C66+C74,"0") -> 3 | D82: =IFERROR(D42+D50+D58+D66+D74,"0") -> 0 | E82: =IFERROR(E42+E50+E58+E66+E74,"0") -> 6 | F82: =IFERROR(F42+F50+F58+F66+F74,"0") -> 5 | G82: =IFERROR(G42+G50+G58+G66+G74,"0") -> 4 | H82: =IFERROR(H42+H50+H58+H66+H74,"0") -> 7 | I82: =IFERROR(I42+I50+I58+I66+I74,"0") -> 0 | J82: =I82+H82+G82+F82+E82+D82+C82 -> 25 | K82: =IFERROR(K42+K50+K58,"0") -> 1 | L82: =IFERROR(L42+L50+L58+L66+L74,"0") -> 7 | M82: =IFERROR(M42+M50+M58+M66+M74,"0") -> 10 | N82: =IFERROR(N42+N50+N58+N66+N74,"0") -> 11 | O82: =IFERROR(O42+O50+O58+O66+O74,"0") -> 10 | P82: =IFERROR(P42+P50+P58+P66+P74,"0") -> 9 | Q82: =IFERROR(Q42+Q50+Q58+Q66+Q74,"0") -> 5 | R82: =SUM(K82:Q82) -> 53
B83: 广告点击率（总） | C83: =IFERROR(C81/C80,"0") -> 0.0049241933 | D83: =IFERROR(D81/D80,"0") -> 0.0030511455 | E83: =IFERROR(E81/E80,"0") -> 0.0036487167 | F83: =IFERROR(F81/F80,"0") -> 0.0046641791 | G83: =IFERROR(G81/G80,"0") -> 0.0054589082 | H83: =IFERROR(H81/H80,"0") -> 0.005688084 | I83: =IFERROR(I81/I80,"0") -> 0 | J83: =AVERAGE(C83:I83) -> 0.0045725378 | K83: =IFERROR(K81/K80,"0") -> 0.0057099831 | L83: =IFERROR(L81/L80,"0") -> 0.0057843345 | M83: =IFERROR(M81/M80,"0") -> 0.0050317342 | N83: =IFERROR(N81/N80,"0") -> 0.0050313059 | O83: =IFERROR(O81/O80,"0") -> 0.0044011203 | P83: =IFERROR(P81/P80,"0") -> 0.0041006787 | Q83: =IFERROR(Q81/Q80,"0") -> 0.0050531714 | R83: =AVERAGE(K83:Q83) -> 0.0050160469
B84: 广告转化率（总） | C84: =IFERROR(C82/C81,"0") -> 0.039473684 | D84: =IFERROR(D82/D81,"0") -> 0 | E84: =IFERROR(E82/E81,"0") -> 0.068965517 | F84: =IFERROR(F82/F81,"0") -> 0.066666667 | G84: =IFERROR(G82/G81,"0") -> 0.043956044 | H84: =IFERROR(H82/H81,"0") -> 0.071428571 | I84: =IFERROR(I82/I81,"0") -> 0 | J84: =(C84+D84+E84+F84+G84+H84)/7 -> 0.041498641 | K84: =IFERROR(K82/K81,"0") -> 0.010989011 | L84: =IFERROR(L82/L81,"0") -> 0.064220183 | M84: =IFERROR(M82/M81,"0") -> 0.11363636 | N84: =IFERROR(N82/N81,"0") -> 0.12222222 | O84: =IFERROR(O82/O81,"0") -> 0.082644628 | P84: =IFERROR(P82/P81,"0") -> 0.10344828 | Q84: =IFERROR(Q82/Q81,"0") -> 0.074626866 | R84: =AVERAGE(K84:Q84) -> 0.081683936
B85: 广告花费（总） | C85: =IFERROR(C45+C53+C61+C69+C77,"0") -> 32.72 | D85: =IFERROR(D45+D53+D61+D69+D77,"0") -> 24.36 | E85: =IFERROR(E45+E53+E61+E69+E77,"0") -> 36.78 | F85: =IFERROR(F45+F53+F61+F69+F77,"0") -> 31.47 | G85: =IFERROR(G45+G53+G61+G69+G77,"0") -> 33.81 | H85: =IFERROR(H45+H53+H61+H69+H77,"0") -> 38.91 | I85: =IFERROR(I45+I53+I61+I69+I77,"0") -> 0 | J85: =C85+D85+E85+F85+G85+H85+I85 -> 198.05 | K85: =IFERROR(K45+K53+K61+K69,"0") -> 40.53 | L85: =IFERROR(L45+L53+L61+L69+L77,"0") -> 47.16 | M85: =IFERROR(M45+M53+M61+M69+M77,"0") -> 41.33 | N85: =IFERROR(N45+N53+N61+N69+N77,"0") -> 38.78 | O85: =IFERROR(O45+O53+O61+O69+O77,"0") -> 51.34 | P85: =IFERROR(P45+P53+P61+P69+P77,"0") -> 38.6 | Q85: =IFERROR(Q45+Q53+Q61+Q69+Q77,"0") -> 33.94 | R85: =SUM(K85:Q85) -> 291.68
B86: 广告销售额（总） | C86: =IFERROR(C47+C54+C62+C70+C78,"0") -> 35.97 | D86: =IFERROR(D47+D54+D62+D70+D78,"0") -> 0 | E86: =IFERROR(E47+E54+E62+E70+E78,"0") -> 71.94 | F86: =IFERROR(F47+F54+F62+F70+F78,"0") -> 47.96 | G86: =IFERROR(G47+G54+G62+G70+G78,"0") -> 38.36 | H86: =IFERROR(H47+H54+H62+H70+H78,"0") -> 76.72 | I86: =IFERROR(I47+I54+I62+I70+I78,"0") -> 0 | J86: =IFERROR(J47+J54+J62+J70+J78,"0") -> 270.95 | K86: =IFERROR(K47+K54+K62+K70,"0") -> 11.99 | L86: =IFERROR(L47+L54+L62+L70+L78,"0") -> 83.93 | M86: =IFERROR(M47+M54+M62+M70+M78,"0") -> 119.9 | N86: =IFERROR(N47+N54+N62+N70+N78,"0") -> 131.89 | O86: =IFERROR(O47+O54+O62+O70+O78,"0") -> 119.9 | P86: =IFERROR(P47+P54+P62+P70+P78,"0") -> 107.91 | Q86: =IFERROR(Q47+Q54+Q62+Q70+Q78,"0") -> 59.95 | R86: =SUM(K86:Q86) -> 635.47
B87: acos（总） | C87: =IFERROR(C85/C86,"0") -> 0.90964693 | D87: =IFERROR(D85/D86,"0") -> 0 | E87: =IFERROR(E85/E86,"0") -> 0.51125938 | F87: =IFERROR(F85/F86,"0") -> 0.65617181 | G87: =IFERROR(G85/G86,"0") -> 0.88138686 | H87: =IFERROR(H85/H86,"0") -> 0.50716893 | I87: =IFERROR(I85/I86,"0") -> 0 | J87: =IFERROR(J85/J86,"0") -> 0.73094667 | ... Q87: =IFERROR(Q85/Q86,"0") -> 0.56613845 | R87: =R85/R86 -> 0.45899885
B88: 平均点击花费 | C88: =C85/C81 -> 0.43052632 | D88: =D85/D81 -> 0.41288136 | E88: =E85/E81 -> 0.42275862 | F88: =F85/F81 -> 0.4196 | G88: =G85/G81 -> 0.37153846 | H88: =H85/H81 -> 0.39704082 | I88: =I85/I81 -> #DIV/0! | J88: =J85/J81 -> 0.40751029 | ... R88: =R85/R81 -> 0.44667688
B89: 广告费/总销售额 | C89: =C85/C10 -> 0.088030348 | D89: =D85/D10 -> 0.075247892 | E89: =E85/E10 -> 0.17041979 | F89: =F85/F10 -> 0.097210638 | G89: =G85/G10 -> 0.078781806 | H89: =H85/H10 -> 0.07212902 | I89: =I85/I10 -> #DIV/0! | J89: =J85/J10 -> 0.089876474 | ... R89: =R85/R10 -> 0.10860241
B92: 操作记录 | C92: {=IFERROR(VLOOKUP(C$3&$A6&$A9,IF({1,0},业绩报告!$A$2:$A$8231&业绩报告!$B$2:$B$8231&业绩报告!$C$2:$C$8231,业绩报告!$BY$2:$BY$8231),2,0),"")} -> 0 | D92: {=IFERROR(VLOOKUP(D$3&$A6&$A9,IF({1,0},业绩报告!$A$2:$A$8231&业绩报告!$B$2:$B$8231&业绩报告!$C$2:$C$8231,业绩报告!$BY$2:$BY$8231),2,0),"")} -> 0 | E92: {=IFERROR(VLOOKUP(E$3&$A6&$A9,IF({1,0},业绩报告!$A$2:$A$8231&业绩报告!$B$2:$B$8231&业绩报告!$C$2:$C$8231,业绩报告!$BY$2:$BY$8231),2,0),"")} -> 0 | F92: {=IFERROR(VLOOKUP(F$3&$A6&$A9,IF({1,0},业绩报告!$A$2:$A$8231&业绩报告!$B$2:$B$8231&业绩报告!$C$2:$C$8231,业绩报告!$BY$2:$BY$8231),2,0),"")} -> 0 | G92: {=IFERROR(VLOOKUP(G$3&$A6&$A9,IF({1,0},业绩报告!$A$2:$A$8231&业绩报告!$B$2:$B$8231&业绩报告!$C$2:$C$8231,业绩报告!$BY$2:$BY$8231),2,0),"")} -> 0 | H92: {=IFERROR(VLOOKUP(H$3&$A6&$A9,IF({1,0},业绩报告!$A$2:$A$8231&业绩报告!$B$2:$B$8231&业绩报告!$C$2:$C$8231,业绩报告!$BY$2:$BY$8231),2,0),"")} -> 0 | I92: {=IFERROR(VLOOKUP(I$3&$A6&$A9,IF({1,0},业绩报告!$A$2:$A$8231&业绩报告!$B$2:$B$8231&业绩报告!$C$2:$C$8231,业绩报告!$BY$2:$BY$8231),2,0),"")} -> 0 | K92: {=IFERROR(VLOOKUP(K$3&$A6&$A9,IF({1,0},业绩报告!$A$2:$A$8231&业绩报告!$B$2:$B$8231&业绩报告!$C$2:$C$8231,业绩报告!$BY$2:$BY$8231),2,0),"")} -> 0 | L92: {=IFERROR(VLOOKUP(L$3&$A6&$A9,IF({1,0},业绩报告!$A$2:$A$8231&业绩报告!$B$2:$B$8231&业绩报告!$C$2:$C$8231,业绩报告!$BY$2:$BY$8231),2,0),"")} -> 0 | M92: {=IFERROR(VLOOKUP(M$3&$A6&$A9,IF({1,0},业绩报告!$A$2:$A$8231&业绩报告!$B$2:$B$8231&业绩报告!$C$2:$C$8231,业绩报告!$BY$2:$BY$8231),2,0),"")} -> 0 | N92: {=IFERROR(VLOOKUP(N$3&$A6&$A9,IF({1,0},业绩报告!$A$2:$A$8231&业绩报告!$B$2:$B$8231&业绩报告!$C$2:$C$8231,业绩报告!$BY$2:$BY$8231),2,0),"")} -> 0 | O92: {=IFERROR(VLOOKUP(O$3&$A6&$A9,IF({1,0},业绩报告!$A$2:$A$8231&业绩报告!$B$2:$B$8231&业绩报告!$C$2:$C$8231,业绩报告!$BY$2:$BY$8231),2,0),"")} -> 0 | P92: {=IFERROR(VLOOKUP(P$3&$A6&$A9,IF({1,0},业绩报告!$A$2:$A$8231&业绩报告!$B$2:$B$8231&业绩报告!$C$2:$C$8231,业绩报告!$BY$2:$BY$8231),2,0),"")} -> 0 | Q92: {=IFERROR(VLOOKUP(Q$3&$A6&$A9,IF({1,0},业绩报告!$A$2:$A$8231&业绩报告!$B$2:$B$8231&业绩报告!$C$2:$C$8231,业绩报告!$BY$2:$BY$8231),2,0),"")} -> 0
C93: {=IFERROR(VLOOKUP(C$3&$A6&$A9,IF({1,0},业绩报告!$A$2:$A$8231&业绩报告!$B$2:$B$8231&业绩报告!$C$2:$C$8231,业绩报告!$BZ$2:$BZ$8231),2,0),"")} -> 0 | D93: {=IFERROR(VLOOKUP(D$3&$A6&$A9,IF({1,0},业绩报告!$A$2:$A$8231&业绩报告!$B$2:$B$8231&业绩报告!$C$2:$C$8231,业绩报告!$BZ$2:$BZ$8231),2,0),"")} -> 0 | E93: {=IFERROR(VLOOKUP(E$3&$A6&$A9,IF({1,0},业绩报告!$A$2:$A$8231&业绩报告!$B$2:$B$8231&业绩报告!$C$2:$C$8231,业绩报告!$BZ$2:$BZ$8231),2,0),"")} -> 0 | F93: {=IFERROR(VLOOKUP(F$3&$A6&$A9,IF({1,0},业绩报告!$A$2:$A$8231&业绩报告!$B$2:$B$8231&业绩报告!$C$2:$C$8231,业绩报告!$BZ$2:$BZ$8231),2,0),"")} -> 0 | G93: {=IFERROR(VLOOKUP(G$3&$A6&$A9,IF({1,0},业绩报告!$A$2:$A$8231&业绩报告!$B$2:$B$8231&业绩报告!$C$2:$C$8231,业绩报告!$BZ$2:$BZ$8231),2,0),"")} -> 0 | H93: {=IFERROR(VLOOKUP(H$3&$A6&$A9,IF({1,0},业绩报告!$A$2:$A$8231&业绩报告!$B$2:$B$8231&业绩报告!$C$2:$C$8231,业绩报告!$BZ$2:$BZ$8231),2,0),"")} -> 0 | I93: {=IFERROR(VLOOKUP(I$3&$A6&$A9,IF({1,0},业绩报告!$A$2:$A$8231&业绩报告!$B$2:$B$8231&业绩报告!$C$2:$C$8231,业绩报告!$BZ$2:$BZ$8231),2,0),"")} -> 0 | K93: {=IFERROR(VLOOKUP(K$3&$A6&$A9,IF({1,0},业绩报告!$A$2:$A$8231&业绩报告!$B$2:$B$8231&业绩报告!$C$2:$C$8231,业绩报告!$BZ$2:$BZ$8231),2,0),"")} -> 0 | L93: {=IFERROR(VLOOKUP(L$3&$A6&$A9,IF({1,0},业绩报告!$A$2:$A$8231&业绩报告!$B$2:$B$8231&业绩报告!$C$2:$C$8231,业绩报告!$BZ$2:$BZ$8231),2,0),"")} -> 0 | M93: {=IFERROR(VLOOKUP(M$3&$A6&$A9,IF({1,0},业绩报告!$A$2:$A$8231&业绩报告!$B$2:$B$8231&业绩报告!$C$2:$C$8231,业绩报告!$BZ$2:$BZ$8231),2,0),"")} -> 0 | N93: {=IFERROR(VLOOKUP(N$3&$A6&$A9,IF({1,0},业绩报告!$A$2:$A$8231&业绩报告!$B$2:$B$8231&业绩报告!$C$2:$C$8231,业绩报告!$BZ$2:$BZ$8231),2,0),"")} -> 0 | O93: {=IFERROR(VLOOKUP(O$3&$A6&$A9,IF({1,0},业绩报告!$A$2:$A$8231&业绩报告!$B$2:$B$8231&业绩报告!$C$2:$C$8231,业绩报告!$BZ$2:$BZ$8231),2,0),"")} -> 0 | P93: {=IFERROR(VLOOKUP(P$3&$A6&$A9,IF({1,0},业绩报告!$A$2:$A$8231&业绩报告!$B$2:$B$8231&业绩报告!$C$2:$C$8231,业绩报告!$BZ$2:$BZ$8231),2,0),"")} -> 0 | Q93: {=IFERROR(VLOOKUP(Q$3&$A6&$A9,IF({1,0},业绩报告!$A$2:$A$8231&业绩报告!$B$2:$B$8231&业绩报告!$C$2:$C$8231,业绩报告!$BZ$2:$BZ$8231),2,0),"")} -> 0
C94: {=IFERROR(VLOOKUP(C$3&$A6&$A9,IF({1,0},业绩报告!$A$2:$A$8231&业绩报告!$B$2:$B$8231&业绩报告!$C$2:$C$8231,业绩报告!$CA$2:$CA$8231),2,0),"")} -> 0 | D94: {=IFERROR(VLOOKUP(D$3&$A6&$A9,IF({1,0},业绩报告!$A$2:$A$8231&业绩报告!$B$2:$B$8231&业绩报告!$C$2:$C$8231,业绩报告!$CA$2:$CA$8231),2,0),"")} -> 0 | E94: {=IFERROR(VLOOKUP(E$3&$A6&$A9,IF({1,0},业绩报告!$A$2:$A$8231&业绩报告!$B$2:$B$8231&业绩报告!$C$2:$C$8231,业绩报告!$CA$2:$CA$8231),2,0),"")} -> 0 | F94: {=IFERROR(VLOOKUP(F$3&$A6&$A9,IF({1,0},业绩报告!$A$2:$A$8231&业绩报告!$B$2:$B$8231&业绩报告!$C$2:$C$8231,业绩报告!$CA$2:$CA$8231),2,0),"")} -> 0 | G94: {=IFERROR(VLOOKUP(G$3&$A6&$A9,IF({1,0},业绩报告!$A$2:$A$8231&业绩报告!$B$2:$B$8231&业绩报告!$C$2:$C$8231,业绩报告!$CA$2:$CA$8231),2,0),"")} -> 0 | H94: {=IFERROR(VLOOKUP(H$3&$A6&$A9,IF({1,0},业绩报告!$A$2:$A$8231&业绩报告!$B$2:$B$8231&业绩报告!$C$2:$C$8231,业绩报告!$CA$2:$CA$8231),2,0),"")} -> 0 | I94: {=IFERROR(VLOOKUP(I$3&$A6&$A9,IF({1,0},业绩报告!$A$2:$A$8231&业绩报告!$B$2:$B$8231&业绩报告!$C$2:$C$8231,业绩报告!$CA$2:$CA$8231),2,0),"")} -> 0 | K94: {=IFERROR(VLOOKUP(K$3&$A6&$A9,IF({1,0},业绩报告!$A$2:$A$8231&业绩报告!$B$2:$B$8231&业绩报告!$C$2:$C$8231,业绩报告!$CA$2:$CA$8231),2,0),"")} -> 0 | L94: {=IFERROR(VLOOKUP(L$3&$A6&$A9,IF({1,0},业绩报告!$A$2:$A$8231&业绩报告!$B$2:$B$8231&业绩报告!$C$2:$C$8231,业绩报告!$CA$2:$CA$8231),2,0),"")} -> 0 | M94: {=IFERROR(VLOOKUP(M$3&$A6&$A9,IF({1,0},业绩报告!$A$2:$A$8231&业绩报告!$B$2:$B$8231&业绩报告!$C$2:$C$8231,业绩报告!$CA$2:$CA$8231),2,0),"")} -> 0 | N94: {=IFERROR(VLOOKUP(N$3&$A6&$A9,IF({1,0},业绩报告!$A$2:$A$8231&业绩报告!$B$2:$B$8231&业绩报告!$C$2:$C$8231,业绩报告!$CA$2:$CA$8231),2,0),"")} -> 0 | O94: {=IFERROR(VLOOKUP(O$3&$A6&$A9,IF({1,0},业绩报告!$A$2:$A$8231&业绩报告!$B$2:$B$8231&业绩报告!$C$2:$C$8231,业绩报告!$CA$2:$CA$8231),2,0),"")} -> 0 | P94: {=IFERROR(VLOOKUP(P$3&$A6&$A9,IF({1,0},业绩报告!$A$2:$A$8231&业绩报告!$B$2:$B$8231&业绩报告!$C$2:$C$8231,业绩报告!$CA$2:$CA$8231),2,0),"")} -> 0 | Q94: {=IFERROR(VLOOKUP(Q$3&$A6&$A9,IF({1,0},业绩报告!$A$2:$A$8231&业绩报告!$B$2:$B$8231&业绩报告!$C$2:$C$8231,业绩报告!$CA$2:$CA$8231),2,0),"")} -> 0

Sheet 业绩报告
A1: 日期 | B1: 站点 | C1: 产品 | D1: ASIN | E1: 访客数 | F1: 总流量 | G1: 订单数 | H1: 销售额 | I1: 售价 | J1: 评分 | K1: 评论数 | L1: 大类 | M1: 大类排名 | N1: 小类 | O1: 小类排名 | P1: 关键词1 | Q1: 自然位1 | R1: 广告位1 | S1: 关键词2 | T1: 自然位2 | U1: 广告位2 | V1: 关键词3 | W1: 自然位3 | X1: 广告位3 | Y1: 关键词4 | Z1: 自然位4 | AA1: 广告位4 | AB1: 关键词5 | AC1: 自然位5 | AD1: 广告位5 | AE1: 关键词6 | AF1: 自然位6 | AG1: 广告位6 | AH1: 关键词7 | AI1: 自然位7 | AJ1: 广告位7 | AK1: 自动广告曝光量 | AL1: 自动广告点击量 | AM1: 自动广告点击率 | AN1: 自动单量 | AO1: 自动广告转化率 | AP1: 自动广告花费 | AQ1: 自动销售额 | AR1: 自动acos | AS1: 视频广告曝光量 | AT1: 视频广告点击量 | AU1: 视频单量 | AV1: 视频广告点击率 | AW1: 视频广告转化率 | AX1: 视频广告花费 | AY1: 视频广告销售额 | AZ1: 视频acos | BA1: 精确广告曝光量 | BB1: 精确广告点击量 | BC1: 精确单量 | BD1: 精确广告点击率 | BE1: 精确广告转化率 | BF1: 精确广告花费 | BG1: 精确销售额 | BH1: 精确acos | BI1: 展示广告曝光量 | BJ1: 展示广告点击 | BK1: 展示广告单量 | BL1: 展示广告点击率 | BM1: 展示广告转化率 | BN1: 展示广告花费 | BO1: 展示广告销售额 | BP1: 展示广告acos | BQ1: 品类广告曝光量 | BR1: 品类广告点击 | BS1: 品类广告单量 | BT1: 品类广告点击率 | BU1: 品类广告转化率 | BV1: 品类广告花费 | BW1: 品类广告销售额 | BX1: 品类广告acos | BY1: 操作记录1 | BZ1: 操作记录2 | CA1: 操作记录3
A2: 44728 | B2: US | C2: 按压皂液器 | D2: B0B17717D3 | E2: =SUMIFS('Business report'!$D$2:$D$9442,'Business report'!$A$2:$A$9442,A2,'Business report'!$B$2:$B$9442,B2,'Business report'!$C$2:$C$9442,D2) -> 24 | F2: =SUMIFS('Business report'!$F$2:$F$9442,'Business report'!$A$2:$A$9442,A2,'Business report'!$B$2:$B$9442,B2,'Business report'!$C$2:$C$9442,D2) -> 29 | G2: =SUMIFS('Business report'!$D$2:$D$9442,'Business report'!$A$2:$A$9442,C2,'Business report'!$B$2:$B$9442,D2,'Business report'!$C$2:$C$9442,F2) -> 0 | H2: =SUMIFS('Business report'!$D$2:$D$9442,'Business report'!$A$2:$A$9442,D2,'Business report'!$B$2:$B$9442,E2,'Business report'!$C$2:$C$9442,G2) -> 0 | I2: 11.99 | J2: 0 | K2: 0 | AK2: =IFERROR(VLOOKUP(A2&B2&C2&LEFT($AK$1,2),IF({1,0},广告数据!$A$2:$A$7027&广告数据!$B$2:$B$7027&广告数据!$C$2:$C$7027,广告数据!$D$2:$D$7027),2,0),"") | AL2: {=IFERROR(VLOOKUP(A2&B2&C2&LEFT($AK$1,2),IF({1,0},广告数据!$A$2:$A$7027&广告数据!$B$2:$B$7027&广告数据!$C$2:$C$7027,广告数据!$E$2:$E$7027),2,0),"")} | AM2: =IFERROR(AL2/AK2,"0") -> 0 | AN2: {=IFERROR(VLOOKUP(A2&B2&C2&LEFT($AK$1,2),IF({1,0},广告数据!$A$2:$A$7027&广告数据!$B$2:$B$7027&广告数据!$C$2:$C$7027,广告数据!$I$2:$I$7027),2,0),"")} | AO2: =IFERROR(AN2/AL2,"0") -> 0 | AP2: {=IFERROR(VLOOKUP(A2&B2&C2&LEFT($AK$1,2),IF({1,0},广告数据!$A$2:$A$7027&广告数据!$B$2:$B$7027&广告数据!$C$2:$C$7027,广告数据!$G$2:$G$7027),2,0),"")} | AQ2: {=IFERROR(VLOOKUP(A2&B2&C2&LEFT($AK$1,2),IF({1,0},广告数据!$A$2:$A$7027&广告数据!$B$2:$B$7027&广告数据!$C$2:$C$7027,广告数据!$J$2:$J$7027),2,0),"")} | AR2: =IFERROR(AP2/AQ2,"0") -> 0 | AS2: {=IFERROR(VLOOKUP(A2&B2&C2&LEFT($AS$1,2),IF({1,0},广告数据!$A$2:$A$7027&广告数据!$B$2:$B$7027&广告数据!$C$2:$C$7027,广告数据!$D$2:$D$7027),2,0),"")} | AT2: {=IFERROR(VLOOKUP(A2&B2&C2&LEFT($AS$1,2),IF({1,0},广告数据!$A$2:$A$7027&广告数据!$B$2:$B$7027&广告数据!$C$2:$C$7027,广告数据!$E$2:$E$7027),2,0),"")} | AU2: {=IFERROR(VLOOKUP(A2&B2&C2&LEFT($AS$1,2),IF({1,0},广告数据!$A$2:$A$7027&广告数据!$B$2:$B$7027&广告数据!$C$2:$C$7027,广告数据!$I$2:$I$7027),2,0),"")} | AV2: =IFERROR(AT2/AS2,"0") -> 0 | AW2: =IFERROR(AU2/AT2,"0") -> 0 | AX2: {=IFERROR(VLOOKUP(A2&B2&C2&LEFT($AS$1,2),IF({1,0},广告数据!$A$2:$A$7027&广告数据!$B$2:$B$7027&广告数据!$C$2:$C$7027,广告数据!$G$2:$G$7027),2,0),"")} | AY2: {=IFERROR(VLOOKUP(A2&B2&C2&LEFT($AS$1,2),IF({1,0},广告数据!$A$2:$A$7027&广告数据!$B$2:$B$7027&广告数据!$C$2:$C$7027,广告数据!$J$2:$J$7027),2,0),"")} | AZ2: =IFERROR(AX2/AY2,"0") -> 0 | BA2: {=IFERROR(VLOOKUP(A2&B2&C2&LEFT($BA$1,2),IF({1,0},广告数据!$A$2:$A$7027&广告数据!$B$2:$B$7027&广告数据!$C$2:$C$7027,广告数据!$D$2:$D$7027),2,0),"")} -> 3878 | BB2: {=IFERROR(VLOOKUP(A2&B2&C2&LEFT($BA$1,2),IF({1,0},广告数据!$A$2:$A$7027&广告数据!$B$2:$B$7027&广告数据!$C$2:$C$7027,广告数据!$E$2:$E$7027),2,0),"")} -> 6 | BC2: {=IFERROR(VLOOKUP(A2&B2&C2&LEFT($BA$1,2),IF({1,0},广告数据!$A$2:$A$7027&广告数据!$B$2:$B$7027&广告数据!$C$2:$C$7027,广告数据!$I$2:$I$7027),2,0),"")} -> 0 | BD2: =IFERROR(BB2/BA2,"0") -> 0.0015471893 | BE2: =IFERROR(BC2/BB2,"0") -> 0 | BF2: {=IFERROR(VLOOKUP(A2&B2&C2&LEFT($BA$1,2),IF({1,0},广告数据!$A$2:$A$7027&广告数据!$B$2:$B$7027&广告数据!$C$2:$C$7027,广告数据!$G$2:$G$7027),2,0),"")} -> 8.52 | BG2: {=IFERROR(VLOOKUP(A2&B2&C2&LEFT($BA$1,2),IF({1,0},广告数据!$A$2:$A$7027&广告数据!$B$2:$B$7027&广告数据!$C$2:$C$7027,广告数据!$J$2:$J$7027),2,0),"")} -> 0 | BH2: =IFERROR(BF2/BG2,"0") -> 0 | BI2: {=IFERROR(VLOOKUP(A2&B2&C2&LEFT($BI$1,2),IF({1,0},广告数据!$A$2:$A$7027&广告数据!$B$2:$B$7027&广告数据!$C$2:$C$7027,广告数据!$D$2:$D$7027),2,0),"0")} -> 0 | BJ2: {=IFERROR(VLOOKUP(A2&B2&C2&LEFT($BI$1,2),IF({1,0},广告数据!$A$2:$A$7027&广告数据!$B$2:$B$7027&广告数据!$C$2:$C$7027,广告数据!$E$2:$E$7027),2,0),"0")} -> 0 | BK2: {=IFERROR(VLOOKUP(A2&B2&C2&LEFT($BI$1,2),IF({1,0},广告数据!$A$2:$A$7027&广告数据!$B$2:$B$7027&广告数据!$C$2:$C$7027,广告数据!$I$2:$I$7027),2,0),"0")} -> 0 | BL2: =IFERROR(BJ2/BI2,"0") -> 0 | BM2: =IFERROR(BK2/BJ2,"0") -> 0 | BN2: {=IFERROR(VLOOKUP(A2&B2&C2&LEFT($BI$1,2),IF({1,0},广告数据!$A$2:$A$7027&广告数据!$B$2:$B$7027&广告数据!$C$2:$C$7027,广告数据!$G$2:$G$7027),2,0),"0")} -> 0 | BO2: {=IFERROR(VLOOKUP(A2&B2&C2&LEFT($BI$1,2),IF({1,0},广告数据!$A$2:$A$7027&广告数据!$B$2:$B$7027&广告数据!$C$2:$C$7027,广告数据!$J$2:$J$7027),2,0),"0")} -> 0 | BP2: =IFERROR(BN2/BO2,"") | BQ2: {=IFERROR(VLOOKUP(A2&B2&C2&LEFT($BQ$1,2),IF({1,0},广告数据!$A$2:$A$7027&广告数据!$B$2:$B$7027&广告数据!$C$2:$C$7027,广告数据!$D$2:$D$7027),2,0),"0")} -> 0 | BR2: {=IFERROR(VLOOKUP(A2&B2&C2&LEFT($BQ$1,2),IF({1,0},广告数据!$A$2:$A$7027&广告数据!$B$2:$B$7027&广告数据!$C$2:$C$7027,广告数据!$E$2:$E$7027),2,0),"0")} -> 0 | BS2: {=IFERROR(VLOOKUP(A2&B2&C2&LEFT($BQ$1,2),IF({1,0},广告数据!$A$2:$A$7027&广告数据!$B$2:$B$7027&广告数据!$C$2:$C$7027,广告数据!$I$2:$I$7027),2,0),"0")} -> 0 | BT2: =IFERROR(BR2/BQ2,"0") -> 0 | BU2: =IFERROR(BS2/BR2,"0") -> 0 | BV2: {=IFERROR(VLOOKUP(A2&B2&C2&LEFT($BQ$1,2),IF({1,0},广告数据!$A$2:$A$7027&广告数据!$B$2:$B$7027&广告数据!$C$2:$C$7027,广告数据!$G$2:$G$7027),2,0),"0")} -> 0 | BW2: {=IFERROR(VLOOKUP(A2&B2&C2&LEFT($BQ$1,2),IF({1,0},广告数据!$A$2:$A$7027&广告数据!$B$2:$B$7027&广告数据!$C$2:$C$7027,广告数据!$J$2:$J$7027),2,0),"0")} -> 0 | BY2: 开了15%优惠券 | BZ2: 报了vine，已领取一个 | CA2: 开手动精准广告，预算在15-20美金之间
A3: 44728 | B3: UK | C3: 消毒盒 | D3: B08HD197ZZ | E3: =SUMIFS('Business report'!$D$2:$D$9442,'Business report'!$A$2:$A$9442,A3,'Business report'!$B$2:$B$9442,B3,'Business report'!$C$2:$C$9442,D3) -> 10 | F3: =SUMIFS('Business report'!$F$2:$F$9442,'Business report'!$A$2:$A$9442,A3,'Business report'!$B$2:$B$9442,B3,'Business report'!$C$2:$C$9442,D3) -> 26 | G3: =SUMIFS('Business report'!$D$2:$D$9442,'Business report'!$A$2:$A$9442,C3,'Business report'!$B$2:$B$9442,D3,'Business report'!$C$2:$C$9442,F3) -> 0 | H3: =SUMIFS('Business report'!$D$2:$D$9442,'Business report'!$A$2:$A$9442,D3,'Business report'!$B$2:$B$9442,E3,'Business report'!$C$2:$C$9442,G3) -> 0 | I3: 17.99 | J3: 4 | K3: 32 | BA3: {=IFERROR(VLOOKUP(A3&B3&C3&LEFT($BA$1,2),IF({1,0},广告数据!$A$2:$A$7027&广告数据!$B$2:$B$7027&广告数据!$C$2:$C$7027,广告数据!$D$2:$D$7027),2,0),"")} -> 1257 | BB3: {=IFERROR(VLOOKUP(A3&B3&C3&LEFT($BA$1,2),IF({1,0},广告数据!$A$2:$A$7027&广告数据!$B$2:$B$7027&广告数据!$C$2:$C$7027,广告数据!$E$2:$E$7027),2,0),"")} -> 5 | BC3: {=IFERROR(VLOOKUP(A3&B3&C3&LEFT($BA$1,2),IF({1,0},广告数据!$A$2:$A$7027&广告数据!$B$2:$B$7027&广告数据!$C$2:$C$7027,广告数据!$I$2:$I$7027),2,0),"")} -> 0 | BD3: =IFERROR(BB3/BA3,"0") -> 0.0039777247 | BE3: =IFERROR(BC3/BB3,"0") -> 0 | BF3: {=IFERROR(VLOOKUP(A3&B3&C3&LEFT($BA$1,2),IF({1,0},广告数据!$A$2:$A$7027&广告数据!$B$2:$B$7027&广告数据!$C$2:$C$7027,广告数据!$G$2:$G$7027),2,0),"")} -> 1.18 | BG3: {=IFERROR(VLOOKUP(A3&B3&C3&LEFT($BA$1,2),IF({1,0},广告数据!$A$2:$A$7027&广告数据!$B$2:$B$7027&广告数据!$C$2:$C$7027,广告数据!$J$2:$J$7027),2,0),"")} -> 0 | BH3: =IFERROR(BF3/BG3,"0") -> 0 | BI3: {=IFERROR(VLOOKUP(A3&B3&C3&LEFT($BI$1,2),IF({1,0},广告数据!$A$2:$A$7027&广告数据!$B$2:$B$7027&广告数据!$C$2:$C$7027,广告数据!$D$2:$D$7027),2,0),"0")} -> 0 | BJ3: {=IFERROR(VLOOKUP(A3&B3&C3&LEFT($BI$1,2),IF({1,0},广告数据!$A$2:$A$7027&广告数据!$B$2:$B$7027&广告数据!$C$2:$C$7027,广告数据!$E$2:$E$7027),2,0),"0")} -> 0 | BK3: {=IFERROR(VLOOKUP(A3&B3&C3&LEFT($BI$1,2),IF({1,0},广告数据!$A$2:$A$7027&广告数据!$B$2:$B$7027&广告数据!$C$2:$C$7027,广告数据!$I$2:$I$7027),2,0),"0")} -> 0 | BL3: =IFERROR(BJ3/BI3,"0") -> 0 | BM3: =IFERROR(BK3/BJ3,"0") -> 0 | BN3: {=IFERROR(VLOOKUP(A3&B3&C3&LEFT($BI$1,2),IF({1,0},广告数据!$A$2:$A$7027&广告数据!$B$2:$B$7027&广告数据!$C$2:$C$7027,广告数据!$G$2:$G$7027),2,0),"0")} -> 0 | BO3: {=IFERROR(VLOOKUP(A3&B3&C3&LEFT($BI$1,2),IF({1,0},广告数据!$A$2:$A$7027&广告数据!$B$2:$B$7027&广告数据!$C$2:$C$7027,广告数据!$J$2:$J$7027),2,0),"0")} -> 0 | BP3: =IFERROR(BN3/BO3,"") | BQ3: {=IFERROR(VLOOKUP(A3&B3&C3&LEFT($BQ$1,2),IF({1,0},广告数据!$A$2:$A$7027&广告数据!$B$2:$B$7027&广告数据!$C$2:$C$7027,广告数据!$D$2:$D$7027),2,0),"0")} -> 0 | BR3: {=IFERROR(VLOOKUP(A3&B3&C3&LEFT($BQ$1,2),IF({1,0},广告数据!$A$2:$A$7027&广告数据!$B$2:$B$7027&广告数据!$C$2:$C$7027,广告数据!$E$2:$E$7027),2,0),"0")} -> 0 | BS3: {=IFERROR(VLOOKUP(A3&B3&C3&LEFT($BQ$1,2),IF({1,0},广告数据!$A$2:$A$7027&广告数据!$B$2:$B$7027&广告数据!$C$2:$C$7027,广告数据!$I$2:$I$7027),2,0),"0")} -> 0 | BT3: =IFERROR(BR3/BQ3,"0") -> 0 | BU3: =IFERROR(BS3/BR3,"0") -> 0 | BV3: {=IFERROR(VLOOKUP(A3&B3&C3&LEFT($BQ$1,2),IF({1,0},广告数据!$A$2:$A$7027&广告数据!$B$2:$B$7027&广告数据!$C$2:$C$7027,广告数据!$G$2:$G$7027),2,0),"0")} -> 0 | BW3: {=IFERROR(VLOOKUP(A3&B3&C3&LEFT($BQ$1,2),IF({1,0},广告数据!$A$2:$A$7027&广告数据!$B$2:$B$7027&广告数据!$C$2:$C$7027,广告数据!$J$2:$J$7027),2,0),"0")} -> 0
A4: 44729 | B4: US | C4: 按压皂液器 | D4: B0B17717D3 | E4: =SUMIFS('Business report'!$D$2:$D$9442,'Business report'!$A$2:$A$9442,A4,'Business report'!$B$2:$B$9442,B4,'Business report'!$C$2:$C$9442,D4) -> 19 | F4: =SUMIFS('Business report'!$F$2:$F$9442,'Business report'!$A$2:$A$9442,A4,'Business report'!$B$2:$B$9442,B4,'Business report'!$C$2:$C$9442,D4) -> 28 | G4: =SUMIFS('Business report'!$I$2:$I$9442,'Business report'!$A$2:$A$9442,A4,'Business report'!$B$2:$B$9442,B4,'Business report'!$C$2:$C$9442,D4) -> 0 | H4: =SUMIFS('Business report'!$K$2:$K$9442,'Business report'!$A$2:$A$9442,A4,'Business report'!$B$2:$B$9442,B4,'Business report'!$C$2:$C$9442,D4) -> 0 | I4: 11.99 | J4: 0 | K4: 0 | AK4: {=IFERROR(VLOOKUP(A4&B4&C4&LEFT($AK$1,2),IF({1,0},广告数据!$A$2:$A$7027&广告数据!$B$2:$B$7027&广告数据!$C$2:$C$7027,广告数据!$D$2:$D$7027),2,0),"")} | AL4: {=IFERROR(VLOOKUP(A4&B4&C4&LEFT($AK$1,2),IF({1,0},广告数据!$A$2:$A$7027&广告数据!$B$2:$B$7027&广告数据!$C$2:$C$7027,广告数据!$E$2:$E$7027),2,0),"")} | AM4: =IFERROR(AL4/AK4,"0") -> 0 | AN4: {=IFERROR(VLOOKUP(A4&B4&C4&LEFT($AK$1,2),IF({1,0},广告数据!$A$2:$A$7027&广告数据!$B$2:$B$7027&广告数据!$C$2:$C$7027,广告数据!$I$2:$I$7027),2,0),"")} | AO4: =IFERROR(AN4/AL4,"0") -> 0 | AP4: {=IFERROR(VLOOKUP(A4&B4&C4&LEFT($AK$1,2),IF({1,0},广告数据!$A$2:$A$7027&广告数据!$B$2:$B$7027&广告数据!$C$2:$C$7027,广告数据!$G$2:$G$7027),2,0),"")} | AQ4: {=IFERROR(VLOOKUP(A4&B4&C4&LEFT($AK$1,2),IF({1,0},广告数据!$A$2:$A$7027&广告数据!$B$2:$B$7027&广告数据!$C$2:$C$7027,广告数据!$J$2:$J$7027),2,0),"")} | AR4: =IFERROR(AP4/AQ4,"0") -> 0 | AS4: {=IFERROR(VLOOKUP(A4&B4&C4&LEFT($AS$1,2),IF({1,0},广告数据!$A$2:$A$7027&广告数据!$B$2:$B$7027&广告数据!$C$2:$C$7027,广告数据!$D$2:$D$7027),2,0),"")} | AT4: {=IFERROR(VLOOKUP(A4&B4&C4&LEFT($AS$1,2),IF({1,0},广告数据!$A$2:$A$7027&广告数据!$B$2:$B$7027&广告数据!$C$2:$C$7027,广告数据!$E$2:$E$7027),2,0),"")} | AU4: {=IFERROR(VLOOKUP(A4&B4&C4&LEFT($AS$1,2),IF({1,0},广告数据!$A$2:$A$7027&广告数据!$B$2:$B$7027&广告数据!$C$2:$C$7027,广告数据!$I$2:$I$7027),2,0),"")} | AV4: =IFERROR(AT4/AS4,"0") -> 0 | AW4: =IFERROR(AU4/AT4,"0") -> 0 | AX4: {=IFERROR(VLOOKUP(A4&B4&C4&LEFT($AS$1,2),IF({1,0},广告数据!$A$2:$A$7027&广告数据!$B$2:$B$7027&广告数据!$C$2:$C$7027,广告数据!$G$2:$G$7027),2,0),"")} | AY4: {=IFERROR(VLOOKUP(A4&B4&C4&LEFT($AS$1,2),IF({1,0},广告数据!$A$2:$A$7027&广告数据!$B$2:$B$7027&广告数据!$C$2:$C$7027,广告数据!$J$2:$J$7027),2,0),"")} | AZ4: =IFERROR(AX4/AY4,"0") -> 0 | BA4: {=IFERROR(VLOOKUP(A4&B4&C4&LEFT($BA$1,2),IF({1,0},广告数据!$A$2:$A$7027&广告数据!$B$2:$B$7027&广告数据!$C$2:$C$7027,广告数据!$D$2:$D$7027),2,0),"")} -> 4832 | BB4: {=IFERROR(VLOOKUP(A4&B4&C4&LEFT($BA$1,2),IF({1,0},广告数据!$A$2:$A$7027&广告数据!$B$2:$B$7027&广告数据!$C$2:$C$7027,广告数据!$E$2:$E$7027),2,0),"")} -> 15 | BC4: {=IFERROR(VLOOKUP(A4&B4&C4&LEFT($BA$1,2),IF({1,0},广告数据!$A$2:$A$7027&广告数据!$B$2:$B$7027&广告数据!$C$2:$C$7027,广告数据!$I$2:$I$7027),2,0),"")} -> 0 | BD4: =IFERROR(BB4/BA4,"0") -> 0.0031043046 | BE4: =IFERROR(BC4/BB4,"0") -> 0 | BF4: {=IFERROR(VLOOKUP(A4&B4&C4&LEFT($BA$1,2),IF({1,0},广告数据!$A$2:$A$7027&广告数据!$B$2:$B$7027&广告数据!$C$2:$C$7027,广告数据!$G$2:$G$7027),2,0),"")} -> 20.75 | BG4: {=IFERROR(VLOOKUP(A4&B4&C4&LEFT($BA$1,2),IF({1,0},广告数据!$A$2:$A$7027&广告数据!$B$2:$B$7027&广告数据!$C$2:$C$7027,广告数据!$J$2:$J$7027),2,0),"")} -> 0 | BH4: =IFERROR(BF4/BG4,"0") -> 0 | BI4: {=IFERROR(VLOOKUP(A4&B4&C4&LEFT($BI$1,2),IF({1,0},广告数据!$A$2:$A$7027&广告数据!$B$2:$B$7027&广告数据!$C$2:$C$7027,广告数据!$D$2:$D$7027),2,0),"0")} -> 0 | BJ4: {=IFERROR(VLOOKUP(A4&B4&C4&LEFT($BI$1,2),IF({1,0},广告数据!$A$2:$A$7027&广告数据!$B$2:$B$7027&广告数据!$C$2:$C$7027,广告数据!$E$2:$E$7027),2,0),"0")} -> 0 | BK4: {=IFERROR(VLOOKUP(A4&B4&C4&LEFT($BI$1,2),IF({1,0},广告数据!$A$2:$A$7027&广告数据!$B$2:$B$7027&广告数据!$C$2:$C$7027,广告数据!$I$2:$I$7027),2,0),"0")} -> 0 | BL4: =IFERROR(BJ4/BI4,"0") -> 0 | BM4: =IFERROR(BK4/BJ4,"0") -> 0 | BN4: {=IFERROR(VLOOKUP(A4&B4&C4&LEFT($BI$1,2),IF({1,0},广告数据!$A$2:$A$7027&广告数据!$B$2:$B$7027&广告数据!$C$2:$C$7027,广告数据!$G$2:$G$7027),2,0),"0")} -> 0 | BO4: {=IFERROR(VLOOKUP(A4&B4&C4&LEFT($BI$1,2),IF({1,0},广告数据!$A$2:$A$7027&广告数据!$B$2:$B$7027&广告数据!$C$2:$C$7027,广告数据!$J$2:$J$7027),2,0),"0")} -> 0 | BP4: =IFERROR(BN4/BO4,"") | BQ4: {=IFERROR(VLOOKUP(A4&B4&C4&LEFT($BQ$1,2),IF({1,0},广告数据!$A$2:$A$7027&广告数据!$B$2:$B$7027&广告数据!$C$2:$C$7027,广告数据!$D$2:$D$7027),2,0),"0")} -> 0 | BR4: {=IFERROR(VLOOKUP(A4&B4&C4&LEFT($BQ$1,2),IF({1,0},广告数据!$A$2:$A$7027&广告数据!$B$2:$B$7027&广告数据!$C$2:$C$7027,广告数据!$E$2:$E$7027),2,0),"0")} -> 0 | BS4: {=IFERROR(VLOOKUP(A4&B4&C4&LEFT($BQ$1,2),IF({1,0},广告数据!$A$2:$A$7027&广告数据!$B$2:$B$7027&广告数据!$C$2:$C$7027,广告数据!$I$2:$I$7027),2,0),"0")} -> 0 | BT4: =IFERROR(BR4/BQ4,"0") -> 0 | BU4: =IFERROR(BS4/BR4,"0") -> 0 | BV4: {=IFERROR(VLOOKUP(A4&B4&C4&LEFT($BQ$1,2),IF({1,0},广告数据!$A$2:$A$7027&广告数据!$B$2:$B$7027&广告数据!$C$2:$C$7027,广告数据!$G$2:$G$7027),2,0),"0")} -> 0 | BW4: {=IFERROR(VLOOKUP(A4&B4&C4&LEFT($BQ$1,2),IF({1,0},广告数据!$A$2:$A$7027&广告数据!$B$2:$B$7027&广告数据!$C$2:$C$7027,广告数据!$J$2:$J$7027),2,0),"0")} -> 0
A5: 44729 | B5: UK | C5: 消毒盒 | D5: B08HD197ZZ | E5: =SUMIFS('Business report'!$D$2:$D$9442,'Business report'!$A$2:$A$9442,A5,'Business report'!$B$2:$B$9442,B5,'Business report'!$C$2:$C$9442,D5) -> 4 | F5: =SUMIFS('Business report'!$F$2:$F$9442,'Business report'!$A$2:$A$9442,A5,'Business report'!$B$2:$B$9442,B5,'Business report'!$C$2:$C$9442,D5) -> 12 | G5: =SUMIFS('Business report'!$D$2:$D$9442,'Business report'!$A$2:$A$9442,C5,'Business report'!$B$2:$B$9442,D5,'Business report'!$C$2:$C$9442,F5) -> 0 | H5: =SUMIFS('Business report'!$D$2:$D$9442,'Business report'!$A$2:$A$9442,D5,'Business report'!$B$2:$B$9442,E5,'Business report'!$C$2:$C$9442,G5) -> 0 | I5: 17.99 | J5: 4 | K5: 32 | BA5: {=IFERROR(VLOOKUP(A5&B5&C5&LEFT($BA$1,2),IF({1,0},广告数据!$A$2:$A$7027&广告数据!$B$2:$B$7027&广告数据!$C$2:$C$7027,广告数据!$D$2:$D$7027),2,0),"")} -> 2006 | BB5: {=IFERROR(VLOOKUP(A5&B5&C5&LEFT($BA$1,2),IF({1,0},广告数据!$A$2:$A$7027&广告数据!$B$2:$B$7027&广告数据!$C$2:$C$7027,广告数据!$E$2:$E$7027),2,0),"")} -> 4 | BC5: {=IFERROR(VLOOKUP(A5&B5&C5&LEFT($BA$1,2),IF({1,0},广告数据!$A$2:$A$7027&广告数据!$B$2:$B$7027&广告数据!$C$2:$C$7027,广告数据!$I$2:$I$7027),2,0),"")} -> 0 | BD5: =IFERROR(BB5/BA5,"0") -> 0.0019940179 | BE5: =IFERROR(BC5/BB5,"0") -> 0 | BF5: {=IFERROR(VLOOKUP(A5&B5&C5&LEFT($BA$1,2),IF({1,0},广告数据!$A$2:$A$7027&广告数据!$B$2:$B$7027&广告数据!$C$2:$C$7027,广告数据!$G$2:$G$7027),2,0),"")} -> 1.45 | BG5: {=IFERROR(VLOOKUP(A5&B5&C5&LEFT($BA$1,2),IF({1,0},广告数据!$A$2:$A$7027&广告数据!$B$2:$B$7027&广告数据!$C$2:$C$7027,广告数据!$J$2:$J$7027),2,0),"")} -> 0 | BH5: =IFERROR(BF5/BG5,"0") -> 0 | BI5: {=IFERROR(VLOOKUP(A5&B5&C5&LEFT($BI$1,2),IF({1,0},广告数据!$A$2:$A$7027&广告数据!$B$2:$B$7027&广告数据!$C$2:$C$7027,广告数据!$D$2:$D$7027),2,0),"0")} -> 0 | BJ5: {=IFERROR(VLOOKUP(A5&B5&C5&LEFT($BI$1,2),IF({1,0},广告数据!$A$2:$A$7027&广告数据!$B$2:$B$7027&广告数据!$C$2:$C$7027,广告数据!$E$2:$E$7027),2,0),"0")} -> 0 | BK5: {=IFERROR(VLOOKUP(A5&B5&C5&LEFT($BI$1,2),IF({1,0},广告数据!$A$2:$A$7027&广告数据!$B$2:$B$7027&广告数据!$C$2:$C$7027,广告数据!$I$2:$I$7027),2,0),"0")} -> 0 | BL5: =IFERROR(BJ5/BI5,"0") -> 0 | BM5: =IFERROR(BK5/BJ5,"0") -> 0 | BN5: {=IFERROR(VLOOKUP(A5&B5&C5&LEFT($BI$1,2),IF({1,0},广告数据!$A$2:$A$7027&广告数据!$B$2:$B$7027&广告数据!$C$2:$C$7027,广告数据!$G$2:$G$7027),2,0),"0")} -> 0 | BO5: {=IFERROR(VLOOKUP(A5&B5&C5&LEFT($BI$1,2),IF({1,0},广告数据!$A$2:$A$7027&广告数据!$B$2:$B$7027&广告数据!$C$2:$C$7027,广告数据!$J$2:$J$7027),2,0),"0")} -> 0 | BP5: =IFERROR(BN5/BO5,"") | BQ5: {=IFERROR(VLOOKUP(A5&B5&C5&LEFT($BQ$1,2),IF({1,0},广告数据!$A$2:$A$7027&广告数据!$B$2:$B$7027&广告数据!$C$2:$C$7027,广告数据!$D$2:$D$7027),2,0),"0")} -> 0 | BR5: {=IFERROR(VLOOKUP(A5&B5&C5&LEFT($BQ$1,2),IF({1,0},广告数据!$A$2:$A$7027&广告数据!$B$2:$B$7027&广告数据!$C$2:$C$7027,广告数据!$E$2:$E$7027),2,0),"0")} -> 0 | BS5: {=IFERROR(VLOOKUP(A5&B5&C5&LEFT($BQ$1,2),IF({1,0},广告数据!$A$2:$A$7027&广告数据!$B$2:$B$7027&广告数据!$C$2:$C$7027,广告数据!$I$2:$I$7027),2,0),"0")} -> 0 | BT5: =IFERROR(BR5/BQ5,"0") -> 0 | BU5: =IFERROR(BS5/BR5,"0") -> 0 | BV5: {=IFERROR(VLOOKUP(A5&B5&C5&LEFT($BQ$1,2),IF({1,0},广告数据!$A$2:$A$7027&广告数据!$B$2:$B$7027&广告数据!$C$2:$C$7027,广告数据!$G$2:$G$7027),2,0),"0")} -> 0 | BW5: {=IFERROR(VLOOKUP(A5&B5&C5&LEFT($BQ$1,2),IF({1,0},广告数据!$A$2:$A$7027&广告数据!$B$2:$B$7027&广告数据!$C$2:$C$7027,广告数据!$J$2:$J$7027),2,0),"0")} -> 0
A6: 44730 | B6: US | C6: 按压皂液器 | D6: B0B17717D3 | E6: =SUMIFS('Business report'!$D$2:$D$9442,'Business report'!$A$2:$A$9442,A6,'Business report'!$B$2:$B$9442,B6,'Business report'!$C$2:$C$9442,D6) -> 18 | F6: =SUMIFS('Business report'!$F$2:$F$9442,'Business report'!$A$2:$A$9442,A6,'Business report'!$B$2:$B$9442,B6,'Business report'!$C$2:$C$9442,D6) -> 26 | G6: =SUMIFS('Business report'!$I$2:$I$9442,'Business report'!$A$2:$A$9442,A6,'Business report'!$B$2:$B$9442,B6,'Business report'!$C$2:$C$9442,D6) -> 1 | H6: =SUMIFS('Business report'!$K$2:$K$9442,'Business report'!$A$2:$A$9442,A6,'Business report'!$B$2:$B$9442,B6,'Business report'!$C$2:$C$9442,D6) -> 11.99 | I6: 11.99 | J6: 0 | K6: 0 | AK6: =IFERROR(VLOOKUP(A6&B6&C6&LEFT($AK$1,2),IF({1,0},广告数据!$A$2:$A$7027&广告数据!$B$2:$B$7027&广告数据!$C$2:$C$7027,广告数据!$D$2:$D$7027),2,0),"") | AL6: {=IFERROR(VLOOKUP(A6&B6&C6&LEFT($AK$1,2),IF({1,0},广告数据!$A$2:$A$7027&广告数据!$B$2:$B$7027&广告数据!$C$2:$C$7027,广告数据!$E$2:$E$7027),2,0),"")} | AM6: =IFERROR(AL6/AK6,"0") -> 0 | AN6: {=IFERROR(VLOOKUP(A6&B6&C6&LEFT($AK$1,2),IF({1,0},广告数据!$A$2:$A$7027&广告数据!$B$2:$B$7027&广告数据!$C$2:$C$7027,广告数据!$I$2:$I$7027),2,0),"")} | AO6: =IFERROR(AN6/AL6,"0") -> 0 | AP6: {=IFERROR(VLOOKUP(A6&B6&C6&LEFT($AK$1,2),IF({1,0},广告数据!$A$2:$A$7027&广告数据!$B$2:$B$7027&广告数据!$C$2:$C$7027,广告数据!$G$2:$G$7027),2,0),"")} | AQ6: {=IFERROR(VLOOKUP(A6&B6&C6&LEFT($AK$1,2),IF({1,0},广告数据!$A$2:$A$7027&广告数据!$B$2:$B$7027&广告数据!$C$2:$C$7027,广告数据!$J$2:$J$7027),2,0),"")} | AR6: =IFERROR(AP6/AQ6,"0") -> 0 | AS6: {=IFERROR(VLOOKUP(A6&B6&C6&LEFT($AS$1,2),IF({1,0},广告数据!$A$2:$A$7027&广告数据!$B$2:$B$7027&广告数据!$C$2:$C$7027,广告数据!$D$2:$D$7027),2,0),"")} | AT6: {=IFERROR(VLOOKUP(A6&B6&C6&LEFT($AS$1,2),IF({1,0},广告数据!$A$2:$A$7027&广告数据!$B$2:$B$7027&广告数据!$C$2:$C$7027,广告数据!$E$2:$E$7027),2,0),"")} | AU6: {=IFERROR(VLOOKUP(A6&B6&C6&LEFT($AS$1,2),IF({1,0},广告数据!$A$2:$A$7027&广告数据!$B$2:$B$7027&广告数据!$C$2:$C$7027,广告数据!$I$2:$I$7027),2,0),"")} | AV6: =IFERROR(AT6/AS6,"0") -> 0 | AW6: =IFERROR(AU6/AT6,"0") -> 0 | AX6: {=IFERROR(VLOOKUP(A6&B6&C6&LEFT($AS$1,2),IF({1,0},广告数据!$A$2:$A$7027&广告数据!$B$2:$B$7027&广告数据!$C$2:$C$7027,广告数据!$G$2:$G$7027),2,0),"")} | AY6: {=IFERROR(VLOOKUP(A6&B6&C6&LEFT($AS$1,2),IF({1,0},广告数据!$A$2:$A$7027&广告数据!$B$2:$B$7027&广告数据!$C$2:$C$7027,广告数据!$J$2:$J$7027),2,0),"")} | AZ6: =IFERROR(AX6/AY6,"0") -> 0 | BA6: {=IFERROR(VLOOKUP(A6&B6&C6&LEFT($BA$1,2),IF({1,0},广告数据!$A$2:$A$7027&广告数据!$B$2:$B$7027&广告数据!$C$2:$C$7027,广告数据!$D$2:$D$7027),2,0),"")} -> 5520 | BB6: {=IFERROR(VLOOKUP(A6&B6&C6&LEFT($BA$1,2),IF({1,0},广告数据!$A$2:$A$7027&广告数据!$B$2:$B$7027&广告数据!$C$2:$C$7027,广告数据!$E$2:$E$7027),2,0),"")} -> 13 | BC6: {=IFERROR(VLOOKUP(A6&B6&C6&LEFT($BA$1,2),IF({1,0},广告数据!$A$2:$A$7027&广告数据!$B$2:$B$7027&广告数据!$C$2:$C$7027,广告数据!$I$2:$I$7027),2,0),"")} -> 1 | BD6: =IFERROR(BB6/BA6,"0") -> 0.0023550725 | BE6: =IFERROR(BC6/BB6,"0") -> 0.076923077 | BF6: {=IFERROR(VLOOKUP(A6&B6&C6&LEFT($BA$1,2),IF({1,0},广告数据!$A$2:$A$7027&广告数据!$B$2:$B$7027&广告数据!$C$2:$C$7027,广告数据!$G$2:$G$7027),2,0),"")} -> 20.39 | BG6: {=IFERROR(VLOOKUP(A6&B6&C6&LEFT($BA$1,2),IF({1,0},广告数据!$A$2:$A$7027&广告数据!$B$2:$B$7027&广告数据!$C$2:$C$7027,广告数据!$J$2:$J$7027),2,0),"")} -> 11.99 | BH6: =IFERROR(BF6/BG6,"0") -> 1.7005838 | BI6: {=IFERROR(VLOOKUP(A6&B6&C6&LEFT($BI$1,2),IF({1,0},广告数据!$A$2:$A$7027&广告数据!$B$2:$B$7027&广告数据!$C$2:$C$7027,广告数据!$D$2:$D$7027),2,0),"0")} -> 0 | BJ6: {=IFERROR(VLOOKUP(A6&B6&C6&LEFT($BI$1,2),IF({1,0},广告数据!$A$2:$A$7027&广告数据!$B$2:$B$7027&广告数据!$C$2:$C$7027,广告数据!$E$2:$E$7027),2,0),"0")} -> 0 | BK6: {=IFERROR(VLOOKUP(A6&B6&C6&LEFT($BI$1,2),IF({1,0},广告数据!$A$2:$A$7027&广告数据!$B$2:$B$7027&广告数据!$C$2:$C$7027,广告数据!$I$2:$I$7027),2,0),"0")} -> 0 | BL6: =IFERROR(BJ6/BI6,"0") -> 0 | BM6: =IFERROR(BK6/BJ6,"0") -> 0 | BN6: {=IFERROR(VLOOKUP(A6&B6&C6&LEFT($BI$1,2),IF({1,0},广告数据!$A$2:$A$7027&广告数据!$B$2:$B$7027&广告数据!$C$2:$C$7027,广告数据!$G$2:$G$7027),2,0),"0")} -> 0 | BO6: {=IFERROR(VLOOKUP(A6&B6&C6&LEFT($BI$1,2),IF({1,0},广告数据!$A$2:$A$7027&广告数据!$B$2:$B$7027&广告数据!$C$2:$C$7027,广告数据!$J$2:$J$7027),2,0),"0")} -> 0 | BP6: =IFERROR(BN6/BO6,"") | BQ6: {=IFERROR(VLOOKUP(A6&B6&C6&LEFT($BQ$1,2),IF({1,0},广告数据!$A$2:$A$7027&广告数据!$B$2:$B$7027&广告数据!$C$2:$C$7027,广告数据!$D$2:$D$7027),2,0),"0")} -> 0 | BR6: {=IFERROR(VLOOKUP(A6&B6&C6&LEFT($BQ$1,2),IF({1,0},广告数据!$A$2:$A$7027&广告数据!$B$2:$B$7027&广告数据!$C$2:$C$7027,广告数据!$E$2:$E$7027),2,0),"0")} -> 0 | BS6: {=IFERROR(VLOOKUP(A6&B6&C6&LEFT($BQ$1,2),IF({1,0},广告数据!$A$2:$A$7027&广告数据!$B$2:$B$7027&广告数据!$C$2:$C$7027,广告数据!$I$2:$I$7027),2,0),"0")} -> 0 | BT6: =IFERROR(BR6/BQ6,"0") -> 0 | BU6: =IFERROR(BS6/BR6,"0") -> 0 | BV6: {=IFERROR(VLOOKUP(A6&B6&C6&LEFT($BQ$1,2),IF({1,0},广告数据!$A$2:$A$7027&广告数据!$B$2:$B$7027&广告数据!$C$2:$C$7027,广告数据!$G$2:$G$7027),2,0),"0")} -> 0 | BW6: {=IFERROR(VLOOKUP(A6&B6&C6&LEFT($BQ$1,2),IF({1,0},广告数据!$A$2:$A$7027&广告数据!$B$2:$B$7027&广告数据!$C$2:$C$7027,广告数据!$J$2:$J$7027),2,0),"0")} -> 0
A7: 44730 | B7: UK | C7: 消毒盒 | D7: B08HD197ZZ | E7: =SUMIFS('Business report'!$D$2:$D$9442,'Business report'!$A$2:$A$9442,A7,'Business report'!$B$2:$B$9442,B7,'Business report'!$C$2:$C$9442,D7) -> 12 | F7: =SUMIFS('Business report'!$F$2:$F$9442,'Business report'!$A$2:$A$9442,A7,'Business report'!$B$2:$B$9442,B7,'Business report'!$C$2:$C$9442,D7) -> 23 | G7: =SUMIFS('Business report'!$D$2:$D$9442,'Business report'!$A$2:$A$9442,C7,'Business report'!$B$2:$B$9442,D7,'Business report'!$C$2:$C$9442,F7) -> 0 | H7: =SUMIFS('Business report'!$D$2:$D$9442,'Business report'!$A$2:$A$9442,D7,'Business report'!$B$2:$B$9442,E7,'Business report'!$C$2:$C$9442,G7) -> 0 | I7: 17.99 | J7: 4 | K7: 32 | BA7: {=IFERROR(VLOOKUP(A7&B7&C7&LEFT($BA$1,2),IF({1,0},广告数据!$A$2:$A$7027&广告数据!$B$2:$B$7027&广告数据!$C$2:$C$7027,广告数据!$D$2:$D$7027),2,0),"")} -> 3381 | BB7: {=IFERROR(VLOOKUP(A7&B7&C7&LEFT($BA$1,2),IF({1,0},广告数据!$A$2:$A$7027&广告数据!$B$2:$B$7027&广告数据!$C$2:$C$7027,广告数据!$E$2:$E$7027),2,0),"")} -> 11 | BC7: {=IFERROR(VLOOKUP(A7&B7&C7&LEFT($BA$1,2),IF({1,0},广告数据!$A$2:$A$7027&广告数据!$B$2:$B$7027&广告数据!$C$2:$C$7027,广告数据!$I$2:$I$7027),2,0),"")} -> 0 | BD7: =IFERROR(BB7/BA7,"0") -> 0.0032534753 | BE7: =IFERROR(BC7/BB7,"0") -> 0 | BF7: {=IFERROR(VLOOKUP(A7&B7&C7&LEFT($BA$1,2),IF({1,0},广告数据!$A$2:$A$7027&广告数据!$B$2:$B$7027&广告数据!$C$2:$C$7027,广告数据!$G$2:$G$7027),2,0),"")} -> 3.97 | BG7: {=IFERROR(VLOOKUP(A7&B7&C7&LEFT($BA$1,2),IF({1,0},广告数据!$A$2:$A$7027&广告数据!$B$2:$B$7027&广告数据!$C$2:$C$7027,广告数据!$J$2:$J$7027),2,0),"")} -> 0 | BH7: =IFERROR(BF7/BG7,"0") -> 0 | BI7: {=IFERROR(VLOOKUP(A7&B7&C7&LEFT($BI$1,2),IF({1,0},广告数据!$A$2:$A$7027&广告数据!$B$2:$B$7027&广告数据!$C$2:$C$7027,广告数据!$D$2:$D$7027),2,0),"0")} -> 0 | BJ7: {=IFERROR(VLOOKUP(A7&B7&C7&LEFT($BI$1,2),IF({1,0},广告数据!$A$2:$A$7027&广告数据!$B$2:$B$7027&广告数据!$C$2:$C$7027,广告数据!$E$2:$E$7027),2,0),"0")} -> 0 | BK7: {=IFERROR(VLOOKUP(A7&B7&C7&LEFT($BI$1,2),IF({1,0},广告数据!$A$2:$A$7027&广告数据!$B$2:$B$7027&广告数据!$C$2:$C$7027,广告数据!$I$2:$I$7027),2,0),"0")} -> 0 | BL7: =IFERROR(BJ7/BI7,"0") -> 0 | BM7: =IFERROR(BK7/BJ7,"0") -> 0 | BN7: {=IFERROR(VLOOKUP(A7&B7&C7&LEFT($BI$1,2),IF({1,0},广告数据!$A$2:$A$7027&广告数据!$B$2:$B$7027&广告数据!$C$2:$C$7027,广告数据!$G$2:$G$7027),2,0),"0")} -> 0 | BO7: {=IFERROR(VLOOKUP(A7&B7&C7&LEFT($BI$1,2),IF({1,0},广告数据!$A$2:$A$7027&广告数据!$B$2:$B$7027&广告数据!$C$2:$C$7027,广告数据!$J$2:$J$7027),2,0),"0")} -> 0 | BP7: =IFERROR(BN7/BO7,"") | BQ7: {=IFERROR(VLOOKUP(A7&B7&C7&LEFT($BQ$1,2),IF({1,0},广告数据!$A$2:$A$7027&广告数据!$B$2:$B$7027&广告数据!$C$2:$C$7027,广告数据!$D$2:$D$7027),2,0),"0")} -> 0 | BR7: {=IFERROR(VLOOKUP(A7&B7&C7&LEFT($BQ$1,2),IF({1,0},广告数据!$A$2:$A$7027&广告数据!$B$2:$B$7027&广告数据!$C$2:$C$7027,广告数据!$E$2:$E$7027),2,0),"0")} -> 0 | BS7: {=IFERROR(VLOOKUP(A7&B7&C7&LEFT($BQ$1,2),IF({1,0},广告数据!$A$2:$A$7027&广告数据!$B$2:$B$7027&广告数据!$C$2:$C$7027,广告数据!$I$2:$I$7027),2,0),"0")} -> 0 | BT7: =IFERROR(BR7/BQ7,"0") -> 0 | BU7: =IFERROR(BS7/BR7,"0") -> 0 | BV7: {=IFERROR(VLOOKUP(A7&B7&C7&LEFT($BQ$1,2),IF({1,0},广告数据!$A$2:$A$7027&广告数据!$B$2:$B$7027&广告数据!$C$2:$C$7027,广告数据!$G$2:$G$7027),2,0),"0")} -> 0 | BW7: {=IFERROR(VLOOKUP(A7&B7&C7&LEFT($BQ$1,2),IF({1,0},广告数据!$A$2:$A$7027&广告数据!$B$2:$B$7027&广告数据!$C$2:$C$7027,广告数据!$J$2:$J$7027),2,0),"0")} -> 0
A8: 44731 | B8: US | C8: 按压皂液器 | D8: B0B17717D3 | E8: =SUMIFS('Business report'!$D$2:$D$9442,'Business report'!$A$2:$A$9442,A8,'Business report'!$B$2:$B$9442,B8,'Business report'!$C$2:$C$9442,D8) -> 27 | F8: =SUMIFS('Business report'!$F$2:$F$9442,'Business report'!$A$2:$A$9442,A8,'Business report'!$B$2:$B$9442,B8,'Business report'!$C$2:$C$9442,D8) -> 31 | G8: =SUMIFS('Business report'!$I$2:$I$9442,'Business report'!$A$2:$A$9442,A8,'Business report'!$B$2:$B$9442,B8,'Business report'!$C$2:$C$9442,D8) -> 2 | H8: =SUMIFS('Business report'!$K$2:$K$9442,'Business report'!$A$2:$A$9442,A8,'Business report'!$B$2:$B$9442,B8,'Business report'!$C$2:$C$9442,D8) -> 23.98 | I8: 11.99 | J8: 0 | K8: 0 | L8: Home & Kitchen | M8: 426,619 | N8: Bathroom Countertop Soap Dispensers | O8: 817 | P8: soap pump and sponge holder | Q8: 第4页 第21位 | S8: soap dispenser and sponge holder | T8: 第7页 第10位 | U8: 第1页 第7位 | V8: soap dispenser with sponge holder | W8: 第7页 第18位 | X8: 第1页 第6位 | Y8: sponge holder and soap dispenser | Z8: 第6页 第48位 | AB8: dish soap dispenser with sponge holder | AC8: 前7页无排名 | AD8: 第1页 第34位 | AE8: soap dispenser kitchen sink | AF8: 前7页无排名 | AH8: sponge holder for kitchen sink | AI8: 前7页无排名 | AJ8: 第1页 第5位 | AK8: {=IFERROR(VLOOKUP(A8&B8&C8&LEFT($AK$1,2),IF({1,0},广告数据!$A$2:$A$7027&广告数据!$B$2:$B$7027&广告数据!$C$2:$C$7027,广告数据!$D$2:$D$7027),2,0),"")} | AL8: {=IFERROR(VLOOKUP(A8&B8&C8&LEFT($AK$1,2),IF({1,0},广告数据!$A$2:$A$7027&广告数据!$B$2:$B$7027&广告数据!$C$2:$C$7027,广告数据!$E$2:$E$7027),2,0),"")} | AM8: =IFERROR(AL8/AK8,"0") -> 0 | AN8: {=IFERROR(VLOOKUP(A8&B8&C8&LEFT($AK$1,2),IF({1,0},广告数据!$A$2:$A$7027&广告数据!$B$2:$B$7027&广告数据!$C$2:$C$7027,广告数据!$I$2:$I$7027),2,0),"")} | AO8: =IFERROR(AN8/AL8,"0") -> 0 | AP8: {=IFERROR(VLOOKUP(A8&B8&C8&LEFT($AK$1,2),IF({1,0},广告数据!$A$2:$A$7027&广告数据!$B$2:$B$7027&广告数据!$C$2:$C$7027,广告数据!$G$2:$G$7027),2,0),"")} | AQ8: {=IFERROR(VLOOKUP(A8&B8&C8&LEFT($AK$1,2),IF({1,0},广告数据!$A$2:$A$7027&广告数据!$B$2:$B$7027&广告数据!$C$2:$C$7027,广告数据!$J$2:$J$7027),2,0),"")} | AR8: =IFERROR(AP8/AQ8,"0") -> 0 | AS8: {=IFERROR(VLOOKUP(A8&B8&C8&LEFT($AS$1,2),IF({1,0},广告数据!$A$2:$A$7027&广告数据!$B$2:$B$7027&广告数据!$C$2:$C$7027,广告数据!$D$2:$D$7027),2,0),"")} | AT8: {=IFERROR(VLOOKUP(A8&B8&C8&LEFT($AS$1,2),IF({1,0},广告数据!$A$2:$A$7027&广告数据!$B$2:$B$7027&广告数据!$C$2:$C$7027,广告数据!$E$2:$E$7027),2,0),"")} | AU8: {=IFERROR(VLOOKUP(A8&B8&C8&LEFT($AS$1,2),IF({1,0},广告数据!$A$2:$A$7027&广告数据!$B$2:$B$7027&广告数据!$C$2:$C$7027,广告数据!$I$2:$I$7027),2,0),"")} | AV8: =IFERROR(AT8/AS8,"0") -> 0 | AW8: =IFERROR(AU8/AT8,"0") -> 0 | AX8: {=IFERROR(VLOOKUP(A8&B8&C8&LEFT($AS$1,2),IF({1,0},广告数据!$A$2:$A$7027&广告数据!$B$2:$B$7027&广告数据!$C$2:$C$7027,广告数据!$G$2:$G$7027),2,0),"")} | AY8: {=IFERROR(VLOOKUP(A8&B8&C8&LEFT($AS$1,2),IF({1,0},广告数据!$A$2:$A$7027&广告数据!$B$2:$B$7027&广告数据!$C$2:$C$7027,广告数据!$J$2:$J$7027),2,0),"")} | AZ8: =IFERROR(AX8/AY8,"0") -> 0 | BA8: {=IFERROR(VLOOKUP(A8&B8&C8&LEFT($BA$1,2),IF({1,0},广告数据!$A$2:$A$7027&广告数据!$B$2:$B$7027&广告数据!$C$2:$C$7027,广告数据!$D$2:$D$7027),2,0),"")} -> 6245 | BB8: {=IFERROR(VLOOKUP(A8&B8&C8&LEFT($BA$1,2),IF({1,0},广告数据!$A$2:$A$7027&广告数据!$B$2:$B$7027&广告数据!$C$2:$C$7027,广告数据!$E$2:$E$7027),2,0),"")} -> 18 | BC8: {=IFERROR(VLOOKUP(A8&B8&C8&LEFT($BA$1,2),IF({1,0},广告数据!$A$2:$A$7027&广告数据!$B$2:$B$7027&广告数据!$C$2:$C$7027,广告数据!$I$2:$I$7027),2,0),"")} -> 0 | BD8: =IFERROR(BB8/BA8,"0") -> 0.0028823058 | BE8: =IFERROR(BC8/BB8,"0") -> 0 | BF8: {=IFERROR(VLOOKUP(A8&B8&C8&LEFT($BA$1,2),IF({1,0},广告数据!$A$2:$A$7027&广告数据!$B$2:$B$7027&广告数据!$C$2:$C$7027,广告数据!$G$2:$G$7027),2,0),"")} -> 22.82 | BG8: {=IFERROR(VLOOKUP(A8&B8&C8&LEFT($BA$1,2),IF({1,0},广告数据!$A$2:$A$7027&广告数据!$B$2:$B$7027&广告数据!$C$2:$C$7027,广告数据!$J$2:$J$7027),2,0),"")} -> 0 | BH8: =IFERROR(BF8/BG8,"0") -> 0 | BI8: {=IFERROR(VLOOKUP(A8&B8&C8&LEFT($BI$1,2),IF({1,0},广告数据!$A$2:$A$7027&广告数据!$B$2:$B$7027&广告数据!$C$2:$C$7027,广告数据!$D$2:$D$7027),2,0),"0")} -> 0 | BJ8: {=IFERROR(VLOOKUP(A8&B8&C8&LEFT($BI$1,2),IF({1,0},广告数据!$A$2:$A$7027&广告数据!$B$2:$B$7027&广告数据!$C$2:$C$7027,广告数据!$E$2:$E$7027),2,0),"0")} -> 0 | BK8: {=IFERROR(VLOOKUP(A8&B8&C8&LEFT($BI$1,2),IF({1,0},广告数据!$A$2:$A$7027&广告数据!$B$2:$B$7027&广告数据!$C$2:$C$7027,广告数据!$I$2:$I$7027),2,0),"0")} -> 0 | BL8: =IFERROR(BJ8/BI8,"0") -> 0 | BM8: =IFERROR(BK8/BJ8,"0") -> 0 | BN8: {=IFERROR(VLOOKUP(A8&B8&C8&LEFT($BI$1,2),IF({1,0},广告数据!$A$2:$A$7027&广告数据!$B$2:$B$7027&广告数据!$C$2:$C$7027,广告数据!$G$2:$G$7027),2,0),"0")} -> 0 | BO8: {=IFERROR(VLOOKUP(A8&B8&C8&LEFT($BI$1,2),IF({1,0},广告数据!$A$2:$A$7027&广告数据!$B$2:$B$7027&广告数据!$C$2:$C$7027,广告数据!$J$2:$J$7027),2,0),"0")} -> 0 | BP8: =IFERROR(BN8/BO8,"") | BQ8: {=IFERROR(VLOOKUP(A8&B8&C8&LEFT($BQ$1,2),IF({1,0},广告数据!$A$2:$A$7027&广告数据!$B$2:$B$7027&广告数据!$C$2:$C$7027,广告数据!$D$2:$D$7027),2,0),"0")} -> 0 | BR8: {=IFERROR(VLOOKUP(A8&B8&C8&LEFT($BQ$1,2),IF({1,0},广告数据!$A$2:$A$7027&广告数据!$B$2:$B$7027&广告数据!$C$2:$C$7027,广告数据!$E$2:$E$7027),2,0),"0")} -> 0 | BS8: {=IFERROR(VLOOKUP(A8&B8&C8&LEFT($BQ$1,2),IF({1,0},广告数据!$A$2:$A$7027&广告数据!$B$2:$B$7027&广告数据!$C$2:$C$7027,广告数据!$I$2:$I$7027),2,0),"0")} -> 0 | BT8: =IFERROR(BR8/BQ8,"0") -> 0 | BU8: =IFERROR(BS8/BR8,"0") -> 0 | BV8: {=IFERROR(VLOOKUP(A8&B8&C8&LEFT($BQ$1,2),IF({1,0},广告数据!$A$2:$A$7027&广告数据!$B$2:$B$7027&广告数据!$C$2:$C$7027,广告数据!$G$2:$G$7027),2,0),"0")} -> 0 | BW8: {=IFERROR(VLOOKUP(A8&B8&C8&LEFT($BQ$1,2),IF({1,0},广告数据!$A$2:$A$7027&广告数据!$B$2:$B$7027&广告数据!$C$2:$C$7027,广告数据!$J$2:$J$7027),2,0),"0")} -> 0 | BY8: 广告部分关键词降竞价 | BZ8: 上了两个QA
A9: 44731 | B9: UK | C9: 消毒盒 | D9: B08HD197ZZ | E9: =SUMIFS('Business report'!$D$2:$D$9442,'Business report'!$A$2:$A$9442,A9,'Business report'!$B$2:$B$9442,B9,'Business report'!$C$2:$C$9442,D9) -> 10 | F9: =SUMIFS('Business report'!$F$2:$F$9442,'Business report'!$A$2:$A$9442,A9,'Business report'!$B$2:$B$9442,B9,'Business report'!$C$2:$C$9442,D9) -> 18 | G9: =SUMIFS('Business report'!$I$2:$I$9442,'Business report'!$A$2:$A$9442,A9,'Business report'!$B$2:$B$9442,B9,'Business report'!$C$2:$C$9442,D9) -> 1 | H9: =SUMIFS('Business report'!$K$2:$K$9442,'Business report'!$A$2:$A$9442,A9,'Business report'!$B$2:$B$9442,B9,'Business report'!$C$2:$C$9442,D9) -> 17.99 | I9: 17.99 | J9: 4 | K9: 32 | BA9: {=IFERROR(VLOOKUP(A9&B9&C9&LEFT($BA$1,2),IF({1,0},广告数据!$A$2:$A$7027&广告数据!$B$2:$B$7027&广告数据!$C$2:$C$7027,广告数据!$D$2:$D$7027),2,0),"")} -> 3737 | BB9: {=IFERROR(VLOOKUP(A9&B9&C9&LEFT($BA$1,2),IF({1,0},广告数据!$A$2:$A$7027&广告数据!$B$2:$B$7027&广告数据!$C$2:$C$7027,广告数据!$E$2:$E$7027),2,0),"")} -> 8 | BC9: {=IFERROR(VLOOKUP(A9&B9&C9&LEFT($BA$1,2),IF({1,0},广告数据!$A$2:$A$7027&广告数据!$B$2:$B$7027&广告数据!$C$2:$C$7027,广告数据!$I$2:$I$7027),2,0),"")} -> 1 | BD9: =IFERROR(BB9/BA9,"0") -> 0.0021407546 | BE9: =IFERROR(BC9/BB9,"0") -> 0.125 | BF9: {=IFERROR(VLOOKUP(A9&B9&C9&LEFT($BA$1,2),IF({1,0},广告数据!$A$2:$A$7027&广告数据!$B$2:$B$7027&广告数据!$C$2:$C$7027,广告数据!$G$2:$G$7027),2,0),"")} -> 3.05 | BG9: {=IFERROR(VLOOKUP(A9&B9&C9&LEFT($BA$1,2),IF({1,0},广告数据!$A$2:$A$7027&广告数据!$B$2:$B$7027&广告数据!$C$2:$C$7027,广告数据!$J$2:$J$7027),2,0),"")} -> 14.99 | BH9: =IFERROR(BF9/BG9,"0") -> 0.20346898 | BI9: {=IFERROR(VLOOKUP(A9&B9&C9&LEFT($BI$1,2),IF({1,0},广告数据!$A$2:$A$7027&广告数据!$B$2:$B$7027&广告数据!$C$2:$C$7027,广告数据!$D$2:$D$7027),2,0),"0")} -> 0 | BJ9: {=IFERROR(VLOOKUP(A9&B9&C9&LEFT($BI$1,2),IF({1,0},广告数据!$A$2:$A$7027&广告数据!$B$2:$B$7027&广告数据!$C$2:$C$7027,广告数据!$E$2:$E$7027),2,0),"0")} -> 0 | BK9: {=IFERROR(VLOOKUP(A9&B9&C9&LEFT($BI$1,2),IF({1,0},广告数据!$A$2:$A$7027&广告数据!$B$2:$B$7027&广告数据!$C$2:$C$7027,广告数据!$I$2:$I$7027),2,0),"0")} -> 0 | BL9: =IFERROR(BJ9/BI9,"0") -> 0 | BM9: =IFERROR(BK9/BJ9,"0") -> 0 | BN9: {=IFERROR(VLOOKUP(A9&B9&C9&LEFT($BI$1,2),IF({1,0},广告数据!$A$2:$A$7027&广告数据!$B$2:$B$7027&广告数据!$C$2:$C$7027,广告数据!$G$2:$G$7027),2,0),"0")} -> 0 | BO9: {=IFERROR(VLOOKUP(A9&B9&C9&LEFT($BI$1,2),IF({1,0},广告数据!$A$2:$A$7027&广告数据!$B$2:$B$7027&广告数据!$C$2:$C$7027,广告数据!$J$2:$J$7027),2,0),"0")} -> 0 | BP9: =IFERROR(BN9/BO9,"") | BQ9: {=IFERROR(VLOOKUP(A9&B9&C9&LEFT($BQ$1,2),IF({1,0},广告数据!$A$2:$A$7027&广告数据!$B$2:$B$7027&广告数据!$C$2:$C$7027,广告数据!$D$2:$D$7027),2,0),"0")} -> 0 | BR9: {=IFERROR(VLOOKUP(A9&B9&C9&LEFT($BQ$1,2),IF({1,0},广告数据!$A$2:$A$7027&广告数据!$B$2:$B$7027&广告数据!$C$2:$C$7027,广告数据!$E$2:$E$7027),2,0),"0")} -> 0 | BS9: {=IFERROR(VLOOKUP(A9&B9&C9&LEFT($BQ$1,2),IF({1,0},广告数据!$A$2:$A$7027&广告数据!$B$2:$B$7027&广告数据!$C$2:$C$7027,广告数据!$I$2:$I$7027),2,0),"0")} -> 0 | BT9: =IFERROR(BR9/BQ9,"0") -> 0 | BU9: =IFERROR(BS9/BR9,"0") -> 0 | BV9: {=IFERROR(VLOOKUP(A9&B9&C9&LEFT($BQ$1,2),IF({1,0},广告数据!$A$2:$A$7027&广告数据!$B$2:$B$7027&广告数据!$C$2:$C$7027,广告数据!$G$2:$G$7027),2,0),"0")} -> 0 | BW9: {=IFERROR(VLOOKUP(A9&B9&C9&LEFT($BQ$1,2),IF({1,0},广告数据!$A$2:$A$7027&广告数据!$B$2:$B$7027&广告数据!$C$2:$C$7027,广告数据!$J$2:$J$7027),2,0),"0")} -> 0
A10: 44732 | B10: US | C10: 按压皂液器 | D10: B0B17717D3 | E10: =SUMIFS('Business report'!$D$2:$D$9442,'Business report'!$A$2:$A$9442,A10,'Business report'!$B$2:$B$9442,B10,'Business report'!$C$2:$C$9442,D10) -> 38 | F10: =SUMIFS('Business report'!$F$2:$F$9442,'Business report'!$A$2:$A$9442,A10,'Business report'!$B$2:$B$9442,B10,'Business report'!$C$2:$C$9442,D10) -> 45 | G10: =SUMIFS('Business report'!$I$2:$I$9442,'Business report'!$A$2:$A$9442,A10,'Business report'!$B$2:$B$9442,B10,'Business report'!$C$2:$C$9442,D10) -> 1 | H10: =SUMIFS('Business report'!$K$2:$K$9442,'Business report'!$A$2:$A$9442,A10,'Business report'!$B$2:$B$9442,B10,'Business report'!$C$2:$C$9442,D10) -> 11.99 | I10: 11.99 | J10: 0 | K10: 0 | L10: Home & Kitchen | M10: 367567 | N10: Bathroom Countertop Soap Dispensers | O10: 773 | P10: sponge holder for kitchen sink | Q10: 前7页无排名 | S10: soap dispenser pump | T10: 第5页 第50位 | V10: dishwashing liquid dispenser for kitchen | W10: 第2页 第19位 | X10: 第1页 第5位 | Y10: dish soap pump | Z10: 第4页 第22位 | AB10: soap dispenser holder | AC10: 第3页 第9位 | AE10: dish sponge holder | AF10: 第6页 第62位 | AG10: 第2页 第4位 | AH10: soap pump | AI10: 第5页 第51位 | AK10: {=IFERROR(VLOOKUP(A10&B10&C10&LEFT($AK$1,2),IF({1,0},广告数据!$A$2:$A$7027&广告数据!$B$2:$B$7027&广告数据!$C$2:$C$7027,广告数据!$D$2:$D$7027),2,0),"")} | AL10: {=IFERROR(VLOOKUP(A10&B10&C10&LEFT($AK$1,2),IF({1,0},广告数据!$A$2:$A$7027&广告数据!$B$2:$B$7027&广告数据!$C$2:$C$7027,广告数据!$E$2:$E$7027),2,0),"")} | AM10: =IFERROR(AL10/AK10,"0") -> 0 | AN10: {=IFERROR(VLOOKUP(A10&B10&C10&LEFT($AK$1,2),IF({1,0},广告数据!$A$2:$A$7027&广告数据!$B$2:$B$7027&广告数据!$C$2:$C$7027,广告数据!$I$2:$I$7027),2,0),"")} | AO10: =IFERROR(AN10/AL10,"0") -> 0 | AP10: {=IFERROR(VLOOKUP(A10&B10&C10&LEFT($AK$1,2),IF({1,0},广告数据!$A$2:$A$7027&广告数据!$B$2:$B$7027&广告数据!$C$2:$C$7027,广告数据!$G$2:$G$7027),2,0),"")} | AQ10: {=IFERROR(VLOOKUP(A10&B10&C10&LEFT($AK$1,2),IF({1,0},广告数据!$A$2:$A$7027&广告数据!$B$2:$B$7027&广告数据!$C$2:$C$7027,广告数据!$J$2:$J$7027),2,0),"")} | AR10: =IFERROR(AP10/AQ10,"0") -> 0 | AS10: {=IFERROR(VLOOKUP(A10&B10&C10&LEFT($AS$1,2),IF({1,0},广告数据!$A$2:$A$7027&广告数据!$B$2:$B$7027&广告数据!$C$2:$C$7027,广告数据!$D$2:$D$7027),2,0),"")} | AT10: {=IFERROR(VLOOKUP(A10&B10&C10&LEFT($AS$1,2),IF({1,0},广告数据!$A$2:$A$7027&广告数据!$B$2:$B$7027&广告数据!$C$2:$C$7027,广告数据!$E$2:$E$7027),2,0),"")} | AU10: {=IFERROR(VLOOKUP(A10&B10&C10&LEFT($AS$1,2),IF({1,0},广告数据!$A$2:$A$7027&广告数据!$B$2:$B$7027&广告数据!$C$2:$C$7027,广告数据!$I$2:$I$7027),2,0),"")} | AV10: =IFERROR(AT10/AS10,"0") -> 0 | AW10: =IFERROR(AU10/AT10,"0") -> 0 | AX10: {=IFERROR(VLOOKUP(A10&B10&C10&LEFT($AS$1,2),IF({1,0},广告数据!$A$2:$A$7027&广告数据!$B$2:$B$7027&广告数据!$C$2:$C$7027,广告数据!$G$2:$G$7027),2,0),"")} | AY10: {=IFERROR(VLOOKUP(A10&B10&C10&LEFT($AS$1,2),IF({1,0},广告数据!$A$2:$A$7027&广告数据!$B$2:$B$7027&广告数据!$C$2:$C$7027,广告数据!$J$2:$J$7027),2,0),"")} | AZ10: =IFERROR(AX10/AY10,"0") -> 0 | BA10: {=IFERROR(VLOOKUP(A10&B10&C10&LEFT($BA$1,2),IF({1,0},广告数据!$A$2:$A$7027&广告数据!$B$2:$B$7027&广告数据!$C$2:$C$7027,广告数据!$D$2:$D$7027),2,0),"")} -> 5962 | BB10: {=IFERROR(VLOOKUP(A10&B10&C10&LEFT($BA$1,2),IF({1,0},广告数据!$A$2:$A$7027&广告数据!$B$2:$B$7027&广告数据!$C$2:$C$7027,广告数据!$E$2:$E$7027),2,0),"")} -> 22 | BC10: {=IFERROR(VLOOKUP(A10&B10&C10&LEFT($BA$1,2),IF({1,0},广告数据!$A$2:$A$7027&广告数据!$B$2:$B$7027&广告数据!$C$2:$C$7027,广告数据!$I$2:$I$7027),2,0),"")} -> 1 | BD10: =IFERROR(BB10/BA10,"0") -> 0.0036900369 | BE10: =IFERROR(BC10/BB10,"0") -> 0.045454545 | BF10: {=IFERROR(VLOOKUP(A10&B10&C10&LEFT($BA$1,2),IF({1,0},广告数据!$A$2:$A$7027&广告数据!$B$2:$B$7027&广告数据!$C$2:$C$7027,广告数据!$G$2:$G$7027),2,0),"")} -> 25.53 | BG10: {=IFERROR(VLOOKUP(A10&B10&C10&LEFT($BA$1,2),IF({1,0},广告数据!$A$2:$A$7027&广告数据!$B$2:$B$7027&广告数据!$C$2:$C$7027,广告数据!$J$2:$J$7027),2,0),"")} -> 11.99 | BH10: =IFERROR(BF10/BG10,"0") -> 2.1292744 | BI10: {=IFERROR(VLOOKUP(A10&B10&C10&LEFT($BI$1,2),IF({1,0},广告数据!$A$2:$A$7027&广告数据!$B$2:$B$7027&广告数据!$C$2:$C$7027,广告数据!$D$2:$D$7027),2,0),"0")} -> 0 | BJ10: {=IFERROR(VLOOKUP(A10&B10&C10&LEFT($BI$1,2),IF({1,0},广告数据!$A$2:$A$7027&广告数据!$B$2:$B$7027&广告数据!$C$2:$C$7027,广告数据!$E$2:$E$7027),2,0),"0")} -> 0 | BK10: {=IFERROR(VLOOKUP(A10&B10&C10&LEFT($BI$1,2),IF({1,0},广告数据!$A$2:$A$7027&广告数据!$B$2:$B$7027&广告数据!$C$2:$C$7027,广告数据!$I$2:$I$7027),2,0),"0")} -> 0 | BL10: =IFERROR(BJ10/BI10,"0") -> 0 | BM10: =IFERROR(BK10/BJ10,"0") -> 0 | BN10: {=IFERROR(VLOOKUP(A10&B10&C10&LEFT($BI$1,2),IF({1,0},广告数据!$A$2:$A$7027&广告数据!$B$2:$B$7027&广告数据!$C$2:$C$7027,广告数据!$G$2:$G$7027),2,0),"0")} -> 0 | BO10: {=IFERROR(VLOOKUP(A10&B10&C10&LEFT($BI$1,2),IF({1,0},广告数据!$A$2:$A$7027&广告数据!$B$2:$B$7027&广告数据!$C$2:$C$7027,广告数据!$J$2:$J$7027),2,0),"0")} -> 0 | BP10: =IFERROR(BN10/BO10,"") | BQ10: {=IFERROR(VLOOKUP(A10&B10&C10&LEFT($BQ$1,2),IF({1,0},广告数据!$A$2:$A$7027&广告数据!$B$2:$B$7027&广告数据!$C$2:$C$7027,广告数据!$D$2:$D$7027),2,0),"0")} -> 0 | BR10: {=IFERROR(VLOOKUP(A10&B10&C10&LEFT($BQ$1,2),IF({1,0},广告数据!$A$2:$A$7027&广告数据!$B$2:$B$7027&广告数据!$C$2:$C$7027,广告数据!$E$2:$E$7027),2,0),"0")} -> 0 | BS10: {=IFERROR(VLOOKUP(A10&B10&C10&LEFT($BQ$1,2),IF({1,0},广告数据!$A$2:$A$7027&广告数据!$B$2:$B$7027&广告数据!$C$2:$C$7027,广告数据!$I$2:$I$7027),2,0),"0")} -> 0 | BT10: =IFERROR(BR10/BQ10,"0") -> 0 | BU10: =IFERROR(BS10/BR10,"0") -> 0 | BV10: {=IFERROR(VLOOKUP(A10&B10&C10&LEFT($BQ$1,2),IF({1,0},广告数据!$A$2:$A$7027&广告数据!$B$2:$B$7027&广告数据!$C$2:$C$7027,广告数据!$G$2:$G$7027),2,0),"0")} -> 0 | BW10: {=IFERROR(VLOOKUP(A10&B10&C10&LEFT($BQ$1,2),IF({1,0},广告数据!$A$2:$A$7027&广告数据!$B$2:$B$7027&广告数据!$C$2:$C$7027,广告数据!$J$2:$J$7027),2,0),"0")} -> 0 | BY10: 关键词竞价调整
A11: 44732 | B11: UK | C11: 消毒盒 | D11: B08HD197ZZ | E11: =SUMIFS('Business report'!$D$2:$D$9442,'Business report'!$A$2:$A$9442,A11,'Business report'!$B$2:$B$9442,B11,'Business report'!$C$2:$C$9442,D11) -> 11 | F11: =SUMIFS('Business report'!$F$2:$F$9442,'Business report'!$A$2:$A$9442,A11,'Business report'!$B$2:$B$9442,B11,'Business report'!$C$2:$C$9442,D11) -> 17 | G11: =SUMIFS('Business report'!$I$2:$I$9442,'Business report'!$A$2:$A$9442,A11,'Business report'!$B$2:$B$9442,B11,'Business report'!$C$2:$C$9442,D11) -> 0 | H11: =SUMIFS('Business report'!$K$2:$K$9442,'Business report'!$A$2:$A$9442,A11,'Business report'!$B$2:$B$9442,B11,'Business report'!$C$2:$C$9442,D11) -> 0 | I11: 17.99 | J11: 4 | K11: 32 | BA11: {=IFERROR(VLOOKUP(A11&B11&C11&LEFT($BA$1,2),IF({1,0},广告数据!$A$2:$A$7027&广告数据!$B$2:$B$7027&广告数据!$C$2:$C$7027,广告数据!$D$2:$D$7027),2,0),"")} -> 3924 | BB11: {=IFERROR(VLOOKUP(A11&B11&C11&LEFT($BA$1,2),IF({1,0},广告数据!$A$2:$A$7027&广告数据!$B$2:$B$7027&广告数据!$C$2:$C$7027,广告数据!$E$2:$E$7027),2,0),"")} -> 10 | BC11: {=IFERROR(VLOOKUP(A11&B11&C11&LEFT($BA$1,2),IF({1,0},广告数据!$A$2:$A$7027&广告数据!$B$2:$B$7027&广告数据!$C$2:$C$7027,广告数据!$I$2:$I$7027),2,0),"")} -> 0 | BD11: =IFERROR(BB11/BA11,"0") -> 0.00254842 | BE11: =IFERROR(BC11/BB11,"0") -> 0 | BF11: {=IFERROR(VLOOKUP(A11&B11&C11&LEFT($BA$1,2),IF({1,0},广告数据!$A$2:$A$7027&广告数据!$B$2:$B$7027&广告数据!$C$2:$C$7027,广告数据!$G$2:$G$7027),2,0),"")} -> 1.96 | BG11: {=IFERROR(VLOOKUP(A11&B11&C11&LEFT($BA$1,2),IF({1,0},广告数据!$A$2:$A$7027&广告数据!$B$2:$B$7027&广告数据!$C$2:$C$7027,广告数据!$J$2:$J$7027),2,0),"")} -> 0 | BH11: =IFERROR(BF11/BG11,"0") -> 0 | BI11: {=IFERROR(VLOOKUP(A11&B11&C11&LEFT($BI$1,2),IF({1,0},广告数据!$A$2:$A$7027&广告数据!$B$2:$B$7027&广告数据!$C$2:$C$7027,广告数据!$D$2:$D$7027),2,0),"0")} -> 0 | BJ11: {=IFERROR(VLOOKUP(A11&B11&C11&LEFT($BI$1,2),IF({1,0},广告数据!$A$2:$A$7027&广告数据!$B$2:$B$7027&广告数据!$C$2:$C$7027,广告数据!$E$2:$E$7027),2,0),"0")} -> 0 | BK11: {=IFERROR(VLOOKUP(A11&B11&C11&LEFT($BI$1,2),IF({1,0},广告数据!$A$2:$A$7027&广告数据!$B$2:$B$7027&广告数据!$C$2:$C$7027,广告数据!$I$2:$I$7027),2,0),"0")} -> 0 | BL11: =IFERROR(BJ11/BI11,"0") -> 0 | BM11: =IFERROR(BK11/BJ11,"0") -> 0 | BN11: {=IFERROR(VLOOKUP(A11&B11&C11&LEFT($BI$1,2),IF({1,0},广告数据!$A$2:$A$7027&广告数据!$B$2:$B$7027&广告数据!$C$2:$C$7027,广告数据!$G$2:$G$7027),2,0),"0")} -> 0 | BO11: {=IFERROR(VLOOKUP(A11&B11&C11&LEFT($BI$1,2),IF({1,0},广告数据!$A$2:$A$7027&广告数据!$B$2:$B$7027&广告数据!$C$2:$C$7027,广告数据!$J$2:$J$7027),2,0),"0")} -> 0 | BP11: =IFERROR(BN11/BO11,"") | BQ11: {=IFERROR(VLOOKUP(A11&B11&C11&LEFT($BQ$1,2),IF({1,0},广告数据!$A$2:$A$7027&广告数据!$B$2:$B$7027&广告数据!$C$2:$C$7027,广告数据!$D$2:$D$7027),2,0),"0")} -> 0 | BR11: {=IFERROR(VLOOKUP(A11&B11&C11&LEFT($BQ$1,2),IF({1,0},广告数据!$A$2:$A$7027&广告数据!$B$2:$B$7027&广告数据!$C$2:$C$7027,广告数据!$E$2:$E$7027),2,0),"0")} -> 0 | BS11: {=IFERROR(VLOOKUP(A11&B11&C11&LEFT($BQ$1,2),IF({1,0},广告数据!$A$2:$A$7027&广告数据!$B$2:$B$7027&广告数据!$C$2:$C$7027,广告数据!$I$2:$I$7027),2,0),"0")} -> 0 | BT11: =IFERROR(BR11/BQ11,"0") -> 0 | BU11: =IFERROR(BS11/BR11,"0") -> 0 | BV11: {=IFERROR(VLOOKUP(A11&B11&C11&LEFT($BQ$1,2),IF({1,0},广告数据!$A$2:$A$7027&广告数据!$B$2:$B$7027&广告数据!$C$2:$C$7027,广告数据!$G$2:$G$7027),2,0),"0")} -> 0 | BW11: {=IFERROR(VLOOKUP(A11&B11&C11&LEFT($BQ$1,2),IF({1,0},广告数据!$A$2:$A$7027&广告数据!$B$2:$B$7027&广告数据!$C$2:$C$7027,广告数据!$J$2:$J$7027),2,0),"0")} -> 0
A12: 44733 | B12: US | C12: 按压皂液器 | D12: B0B17717D3 | E12: =SUMIFS('Business report'!$D$2:$D$9442,'Business report'!$A$2:$A$9442,A12,'Business report'!$B$2:$B$9442,B12,'Business report'!$C$2:$C$9442,D12) -> 37 | F12: =SUMIFS('Business report'!$F$2:$F$9442,'Business report'!$A$2:$A$9442,A12,'Business report'!$B$2:$B$9442,B12,'Business report'!$C$2:$C$9442,D12) -> 57 | G12: =SUMIFS('Business report'!$I$2:$I$9442,'Business report'!$A$2:$A$9442,A12,'Business report'!$B$2:$B$9442,B12,'Business report'!$C$2:$C$9442,D12) -> 1 | H12: =SUMIFS('Business report'!$K$2:$K$9442,'Business report'!$A$2:$A$9442,A12,'Business report'!$B$2:$B$9442,B12,'Business report'!$C$2:$C$9442,D12) -> 11.99 | I12: 11.99 | J12: 0 | K12: 0 | L12: Home & Kitchen | M12: 324,327 | N12: Bathroom Countertop Soap Dispensers | O12: 811 | P12: dishwashing liquid dispenser for kitchen | Q12: 第4页 第8位 | R12: 第1页 第4位 | S12: dish sponge holder | T12: 前7页无排名 | U12: 第1页 第7位 | V12: dish soap dispenser with sponge holder | W12: 第5页 第48位 | X12: 第6页 第38位 | Y12: sponge holder and soap dispenser | Z12: 第3页 第51位 | AB12: dish soap pump | AC12: 前7页无排名 | AD12: 第1页 第4位 | AE12: soap pump and sponge holder | AF12: 第3页 第10位 | AH12: soap dispenser and sponge holder | AI12: 第4页 第10位 | AJ12: 第1页 第4位 | AK12: {=IFERROR(VLOOKUP(A12&B12&C12&LEFT($AK$1,2),IF({1,0},广告数据!$A$2:$A$7027&广告数据!$B$2:$B$7027&广告数据!$C$2:$C$7027,广告数据!$D$2:$D$7027),2,0),"")} | AL12: {=IFERROR(VLOOKUP(A12&B12&C12&LEFT($AK$1,2),IF({1,0},广告数据!$A$2:$A$7027&广告数据!$B$2:$B$7027&广告数据!$C$2:$C$7027,广告数据!$E$2:$E$7027),2,0),"")} | AM12: =IFERROR(AL12/AK12,"0") -> 0 | AN12: {=IFERROR(VLOOKUP(A12&B12&C12&LEFT($AK$1,2),IF({1,0},广告数据!$A$2:$A$7027&广告数据!$B$2:$B$7027&广告数据!$C$2:$C$7027,广告数据!$I$2:$I$7027),2,0),"")} | AO12: =IFERROR(AN12/AL12,"0") -> 0 | AP12: {=IFERROR(VLOOKUP(A12&B12&C12&LEFT($AK$1,2),IF({1,0},广告数据!$A$2:$A$7027&广告数据!$B$2:$B$7027&广告数据!$C$2:$C$7027,广告数据!$G$2:$G$7027),2,0),"")} | AQ12: {=IFERROR(VLOOKUP(A12&B12&C12&LEFT($AK$1,2),IF({1,0},广告数据!$A$2:$A$7027&广告数据!$B$2:$B$7027&广告数据!$C$2:$C$7027,广告数据!$J$2:$J$7027),2,0),"")} | AR12: =IFERROR(AP12/AQ12,"0") -> 0 | AS12: {=IFERROR(VLOOKUP(A12&B12&C12&LEFT($AS$1,2),IF({1,0},广告数据!$A$2:$A$7027&广告数据!$B$2:$B$7027&广告数据!$C$2:$C$7027,广告数据!$D$2:$D$7027),2,0),"")} | AT12: {=IFERROR(VLOOKUP(A12&B12&C12&LEFT($AS$1,2),IF({1,0},广告数据!$A$2:$A$7027&广告数据!$B$2:$B$7027&广告数据!$C$2:$C$7027,广告数据!$E$2:$E$7027),2,0),"")} | AU12: {=IFERROR(VLOOKUP(A12&B12&C12&LEFT($AS$1,2),IF({1,0},广告数据!$A$2:$A$7027&广告数据!$B$2:$B$7027&广告数据!$C$2:$C$7027,广告数据!$I$2:$I$7027),2,0),"")} | AV12: =IFERROR(AT12/AS12,"0") -> 0 | AW12: =IFERROR(AU12/AT12,"0") -> 0 | AX12: {=IFERROR(VLOOKUP(A12&B12&C12&LEFT($AS$1,2),IF({1,0},广告数据!$A$2:$A$7027&广告数据!$B$2:$B$7027&广告数据!$C$2:$C$7027,广告数据!$G$2:$G$7027),2,0),"")} | AY12: {=IFERROR(VLOOKUP(A12&B12&C12&LEFT($AS$1,2),IF({1,0},广告数据!$A$2:$A$7027&广告数据!$B$2:$B$7027&广告数据!$C$2:$C$7027,广告数据!$J$2:$J$7027),2,0),"")} | AZ12: =IFERROR(AX12/AY12,"0") -> 0 | BA12: {=IFERROR(VLOOKUP(A12&B12&C12&LEFT($BA$1,2),IF({1,0},广告数据!$A$2:$A$7027&广告数据!$B$2:$B$7027&广告数据!$C$2:$C$7027,广告数据!$D$2:$D$7027),2,0),"")} -> 3972 | BB12: {=IFERROR(VLOOKUP(A12&B12&C12&LEFT($BA$1,2),IF({1,0},广告数据!$A$2:$A$7027&广告数据!$B$2:$B$7027&广告数据!$C$2:$C$7027,广告数据!$E$2:$E$7027),2,0),"")} -> 24 | BC12: {=IFERROR(VLOOKUP(A12&B12&C12&LEFT($BA$1,2),IF({1,0},广告数据!$A$2:$A$7027&广告数据!$B$2:$B$7027&广告数据!$C$2:$C$7027,广告数据!$I$2:$I$7027),2,0),"")} -> 1 | BD12: =IFERROR(BB12/BA12,"0") -> 0.0060422961 | BE12: =IFERROR(BC12/BB12,"0") -> 0.041666667 | BF12: {=IFERROR(VLOOKUP(A12&B12&C12&LEFT($BA$1,2),IF({1,0},广告数据!$A$2:$A$7027&广告数据!$B$2:$B$7027&广告数据!$C$2:$C$7027,广告数据!$G$2:$G$7027),2,0),"")} -> 22.45 | BG12: {=IFERROR(VLOOKUP(A12&B12&C12&LEFT($BA$1,2),IF({1,0},广告数据!$A$2:$A$7027&广告数据!$B$2:$B$7027&广告数据!$C$2:$C$7027,广告数据!$J$2:$J$7027),2,0),"")} -> 11.99 | BH12: =IFERROR(BF12/BG12,"0") -> 1.8723937 | BI12: {=IFERROR(VLOOKUP(A12&B12&C12&LEFT($BI$1,2),IF({1,0},广告数据!$A$2:$A$7027&广告数据!$B$2:$B$7027&广告数据!$C$2:$C$7027,广告数据!$D$2:$D$7027),2,0),"0")} -> 0 | BJ12: {=IFERROR(VLOOKUP(A12&B12&C12&LEFT($BI$1,2),IF({1,0},广告数据!$A$2:$A$7027&广告数据!$B$2:$B$7027&广告数据!$C$2:$C$7027,广告数据!$E$2:$E$7027),2,0),"0")} -> 0 | BK12: {=IFERROR(VLOOKUP(A12&B12&C12&LEFT($BI$1,2),IF({1,0},广告数据!$A$2:$A$7027&广告数据!$B$2:$B$7027&广告数据!$C$2:$C$7027,广告数据!$I$2:$I$7027),2,0),"0")} -> 0 | BL12: =IFERROR(BJ12/BI12,"0") -> 0 | BM12: =IFERROR(BK12/BJ12,"0") -> 0 | BN12: {=IFERROR(VLOOKUP(A12&B12&C12&LEFT($BI$1,2),IF({1,0},广告数据!$A$2:$A$7027&广告数据!$B$2:$B$7027&广告数据!$C$2:$C$7027,广告数据!$G$2:$G$7027),2,0),"0")} -> 0 | BO12: {=IFERROR(VLOOKUP(A12&B12&C12&LEFT($BI$1,2),IF({1,0},广告数据!$A$2:$A$7027&广告数据!$B$2:$B$7027&广告数据!$C$2:$C$7027,广告数据!$J$2:$J$7027),2,0),"0")} -> 0 | BP12: =IFERROR(BN12/BO12,"") | BQ12: {=IFERROR(VLOOKUP(A12&B12&C12&LEFT($BQ$1,2),IF({1,0},广告数据!$A$2:$A$7027&广告数据!$B$2:$B$7027&广告数据!$C$2:$C$7027,广告数据!$D$2:$D$7027),2,0),"0")} -> 0 | BR12: {=IFERROR(VLOOKUP(A12&B12&C12&LEFT($BQ$1,2),IF({1,0},广告数据!$A$2:$A$7027&广告数据!$B$2:$B$7027&广告数据!$C$2:$C$7027,广告数据!$E$2:$E$7027),2,0),"0")} -> 0 | BS12: {=IFERROR(VLOOKUP(A12&B12&C12&LEFT($BQ$1,2),IF({1,0},广告数据!$A$2:$A$7027&广告数据!$B$2:$B$7027&广告数据!$C$2:$C$7027,广告数据!$I$2:$I$7027),2,0),"0")} -> 0 | BT12: =IFERROR(BR12/BQ12,"0") -> 0 | BU12: =IFERROR(BS12/BR12,"0") -> 0 | BV12: {=IFERROR(VLOOKUP(A12&B12&C12&LEFT($BQ$1,2),IF({1,0},广告数据!$A$2:$A$7027&广告数据!$B$2:$B$7027&广告数据!$C$2:$C$7027,广告数据!$G$2:$G$7027),2,0),"0")} -> 0 | BW12: {=IFERROR(VLOOKUP(A12&B12&C12&LEFT($BQ$1,2),IF({1,0},广告数据!$A$2:$A$7027&广告数据!$B$2:$B$7027&广告数据!$C$2:$C$7027,广告数据!$J$2:$J$7027),2,0),"0")} -> 0 | BY12: 蓝色比粉色曝光多但点击持平，更换蓝色主图
A13: 44733 | B13: UK | C13: 消毒盒 | D13: B08HD197ZZ | E13: =SUMIFS('Business report'!$D$2:$D$9442,'Business report'!$A$2:$A$9442,A13,'Business report'!$B$2:$B$9442,B13,'Business report'!$C$2:$C$9442,D13) -> 8 | F13: =SUMIFS('Business report'!$F$2:$F$9442,'Business report'!$A$2:$A$9442,A13,'Business report'!$B$2:$B$9442,B13,'Business report'!$C$2:$C$9442,D13) -> 14 | G13: =SUMIFS('Business report'!$I$2:$I$9442,'Business report'!$A$2:$A$9442,A13,'Business report'!$B$2:$B$9442,B13,'Business report'!$C$2:$C$9442,D13) -> 0 | H13: =SUMIFS('Business report'!$K$2:$K$9442,'Business report'!$A$2:$A$9442,A13,'Business report'!$B$2:$B$9442,B13,'Business report'!$C$2:$C$9442,D13) -> 0 | I13: 17.99 | J13: 4 | K13: 32 | BA13: {=IFERROR(VLOOKUP(A13&B13&C13&LEFT($BA$1,2),IF({1,0},广告数据!$A$2:$A$7027&广告数据!$B$2:$B$7027&广告数据!$C$2:$C$7027,广告数据!$D$2:$D$7027),2,0),"")} -> 4208 | BB13: {=IFERROR(VLOOKUP(A13&B13&C13&LEFT($BA$1,2),IF({1,0},广告数据!$A$2:$A$7027&广告数据!$B$2:$B$7027&广告数据!$C$2:$C$7027,广告数据!$E$2:$E$7027),2,0),"")} -> 7 | BC13: {=IFERROR(VLOOKUP(A13&B13&C13&LEFT($BA$1,2),IF({1,0},广告数据!$A$2:$A$7027&广告数据!$B$2:$B$7027&广告数据!$C$2:$C$7027,广告数据!$I$2:$I$7027),2,0),"")} -> 0 | BD13: =IFERROR(BB13/BA13,"0") -> 0.0016634981 | BE13: =IFERROR(BC13/BB13,"0") -> 0 | BF13: {=IFERROR(VLOOKUP(A13&B13&C13&LEFT($BA$1,2),IF({1,0},广告数据!$A$2:$A$7027&广告数据!$B$2:$B$7027&广告数据!$C$2:$C$7027,广告数据!$G$2:$G$7027),2,0),"")} -> 2.62 | BG13: {=IFERROR(VLOOKUP(A13&B13&C13&LEFT($BA$1,2),IF({1,0},广告数据!$A$2:$A$7027&广告数据!$B$2:$B$7027&广告数据!$C$2:$C$7027,广告数据!$J$2:$J$7027),2,0),"")} -> 0 | BH13: =IFERROR(BF13/BG13,"0") -> 0 | BI13: {=IFERROR(VLOOKUP(A13&B13&C13&LEFT($BI$1,2),IF({1,0},广告数据!$A$2:$A$7027&广告数据!$B$2:$B$7027&广告数据!$C$2:$C$7027,广告数据!$D$2:$D$7027),2,0),"0")} -> 0 | BJ13: {=IFERROR(VLOOKUP(A13&B13&C13&LEFT($BI$1,2),IF({1,0},广告数据!$A$2:$A$7027&广告数据!$B$2:$B$7027&广告数据!$C$2:$C$7027,广告数据!$E$2:$E$7027),2,0),"0")} -> 0 | BK13: {=IFERROR(VLOOKUP(A13&B13&C13&LEFT($BI$1,2),IF({1,0},广告数据!$A$2:$A$7027&广告数据!$B$2:$B$7027&广告数据!$C$2:$C$7027,广告数据!$I$2:$I$7027),2,0),"0")} -> 0 | BL13: =IFERROR(BJ13/BI13,"0") -> 0 | BM13: =IFERROR(BK13/BJ13,"0") -> 0 | BN13: {=IFERROR(VLOOKUP(A13&B13&C13&LEFT($BI$1,2),IF({1,0},广告数据!$A$2:$A$7027&广告数据!$B$2:$B$7027&广告数据!$C$2:$C$7027,广告数据!$G$2:$G$7027),2,0),"0")} -> 0 | BO13: {=IFERROR(VLOOKUP(A13&B13&C13&LEFT($BI$1,2),IF({1,0},广告数据!$A$2:$A$7027&广告数据!$B$2:$B$7027&广告数据!$C$2:$C$7027,广告数据!$J$2:$J$7027),2,0),"0")} -> 0 | BP13: =IFERROR(BN13/BO13,"") | BQ13: {=IFERROR(VLOOKUP(A13&B13&C13&LEFT($BQ$1,2),IF({1,0},广告数据!$A$2:$A$7027&广告数据!$B$2:$B$7027&广告数据!$C$2:$C$7027,广告数据!$D$2:$D$7027),2,0),"0")} -> 0 | BR13: {=IFERROR(VLOOKUP(A13&B13&C13&LEFT($BQ$1,2),IF({1,0},广告数据!$A$2:$A$7027&广告数据!$B$2:$B$7027&广告数据!$C$2:$C$7027,广告数据!$E$2:$E$7027),2,0),"0")} -> 0 | BS13: {=IFERROR(VLOOKUP(A13&B13&C13&LEFT($BQ$1,2),IF({1,0},广告数据!$A$2:$A$7027&广告数据!$B$2:$B$7027&广告数据!$C$2:$C$7027,广告数据!$I$2:$I$7027),2,0),"0")} -> 0 | BT13: =IFERROR(BR13/BQ13,"0") -> 0 | BU13: =IFERROR(BS13/BR13,"0") -> 0 | BV13: {=IFERROR(VLOOKUP(A13&B13&C13&LEFT($BQ$1,2),IF({1,0},广告数据!$A$2:$A$7027&广告数据!$B$2:$B$7027&广告数据!$C$2:$C$7027,广告数据!$G$2:$G$7027),2,0),"0")} -> 0 | BW13: {=IFERROR(VLOOKUP(A13&B13&C13&LEFT($BQ$1,2),IF({1,0},广告数据!$A$2:$A$7027&广告数据!$B$2:$B$7027&广告数据!$C$2:$C$7027,广告数据!$J$2:$J$7027),2,0),"0")} -> 0
