Workbook

Sheet 汇总
A1: 日期 | B1: 产品 | C1: seller-sku | D1: ASIN | E1: 产品成本(¥) | F1: 运费(¥) | G1: 成本(¥) | H1: 价格(＄) | I1: 仓储费(＄) | J1: 30天销量 | K1: 30天销售额($) | L1: 配送费用($) | M1: 总配送费用($) | N1: 总成本(¥) | O1: 退货 | P1: 换货 | Q1: 退货金额($) | R1: 赔偿金($) | S1: 广告($) | T1: 回款($) | U1: 产品名称1 | W1: 产品名称2
A2: 2022年五月 | B2: 产品名称1 | C2: 产品SKU-1 | D2: 产品ASIN-1 | E2: 10 | F2: 10 | G2: =E2+F2 -> 20 | H2: =VLOOKUP(C2,库存报告!$A:$F,6,0) -> #N/A | I2: =SUMIF(仓储费!$A:$A,D2,仓储费!$T:$T) -> 0 | J2: =SUMIF(销量!$L:$L,C2,销量!$O:$O) -> 0 | K2: =SUMIF(销量!L:L,C2,销量!Q:Q)-SUMIF(销量!L:L,C2,销量!W:W) -> 0 | L2: =VLOOKUP(C2,FBA费用!A:S,19,0) -> #N/A | M2: =L2*J2 -> #N/A | N2: =G2*J2 -> 0 | O2: =SUMIF(退货!C:C,C2,退货!G:G) -> 0 | P2: =SUMIF(换货!B:B,C2,换货!F:F) -> 0 | Q2: =(-(H2*0.85-L2)+H2*0.12)*O2 -> #N/A | R2: =SUMIF(赔偿金!F:F,C2,赔偿金!M:M) -> 0 | S2: =SUMIF(广告!H:H,D2,广告!M:M) -> 0 | T2: =K2*0.85-M2-I2+Q2+R2-S2 -> #N/A | U2: 销量 | V2: =J2 -> 0 | W2: 销量 | X2: =J3 -> 0
B3: 产品名称2 | C3: 产品SKU-2 | D3: 产品ASIN-2 | E3: 10 | F3: 10 | G3: =E3+F3 -> 20 | H3: =VLOOKUP(C3,库存报告!$A:$F,6,0) -> #N/A | I3: =SUMIF(仓储费!$A:$A,D3,仓储费!$T:$T) -> 0 | J3: =SUMIF(销量!$L:$L,C3,销量!$O:$O) -> 0 | K3: =SUMIF(销量!L:L,C3,销量!Q:Q)-SUMIF(销量!L:L,C3,销量!W:W) -> 0 | L3: =VLOOKUP(C3,FBA费用!A:S,19,0) -> #N/A | M3: =L3*J3 -> #N/A | N3: =G3*J3 -> 0 | O3: =SUMIF(退货!C:C,C3,退货!G:G) -> 0 | P3: =SUMIF(换货!B:B,C3,换货!F:F) -> 0 | Q3: =(-(H3*0.85-L3)+H3*0.12)*O3 -> #N/A | R3: =SUMIF(赔偿金!F:F,C3,赔偿金!M:M) -> 0 | S3: =SUMIF(广告!H:H,D3,广告!M:M) -> 0 | T3: =K3*0.85-M3-I3+Q3+R3-S3 -> #N/A | U3: 销售额($) | V3: =SUM(K7) -> 0 | W3: 销售额($) | X3: =SUM(K5:K6) -> 0
U4: 客单价 | V4: =V3/V2 -> #DIV/0! | W4: 客单价 | X4: =X3/X2 -> #DIV/0!
U5: 配送费用($) | V5: =M2 -> #N/A | W5: 配送费用($) | X5: =M3 -> #N/A
U6: 费送费用比 | V6: =V5/V3 -> #N/A | W6: 费送费用比 | X6: =X5/X3 -> #N/A
U7: 仓储费($) | V7: =I2 -> 0 | W7: 仓储费($) | X7: =I3 -> 0
U8: 仓储费用比 | V8: =V7/V3 -> #DIV/0! | W8: 仓储费用比 | X8: =X7/X3 -> #DIV/0!
U9: 广告($) | V9: =S2 -> 0 | W9: 广告($) | X9: =S3 -> 0
U10: 品牌广告 | V10: 手动添加 | W10: 品牌广告 | X10: 手动添加
U11: 广告费用比 | V11: =V9/V3 -> #DIV/0! | W11: 广告费用比 | X11: =X9/X3 -> #DIV/0!
U12: 回款($) | V12: =T2 -> #N/A | W12: 回款($) | X12: =T3 -> #N/A
U13: 回款比 | V13: =V12/V3 -> #N/A | W13: 回款比 | X13: =X12/X3 -> #N/A
U14: 汇率 | V14: 6.688 | W14: 汇率 | X14: 6.688
U15: 成本(¥) | V15: =N2 -> 0 | W15: 成本(¥) | X15: =N3 -> 0
U16: 成本比 | V16: =V15/V14/V3 -> #DIV/0! | W16: 成本比 | X16: =X15/X14/X3 -> #DIV/0!
U17: 利润(¥) | V17: =V12*V14*0.997-V15 -> #N/A | W17: 利润(¥) | X17: =X12*X14*0.997-X15 -> #N/A
U18: 利润率 | V18: =V17/V14/V3 -> #N/A | W18: 利润率 | X18: =X17/X14/X3 -> #N/A
U19: 单个利润(¥) | V19: =V17/V2 -> #N/A | W19: 单个利润(¥) | X19: =X17/X2 -> #N/A
U20: 总利润 | V20: =V19*V2 -> #N/A | W20: 总利润 | X20: =X19*X2 -> #N/A | Y20: =V20+X20+#REF!+#REF! -> #N/A

Sheet 库存报告

Sheet 仓储费

Sheet 销量

Sheet 广告

Sheet FBA费用

Sheet 退货

Sheet 赔偿金

Sheet 换货

Sheet 报告说明
A39: 品牌广告报告比较复杂，所以我一般都是直接广告页面拉一整个月的，然后扣除掉自动广告和手动广告，其他剩下的费用手动加到品牌广告那一栏去
