Workbook

Sheet 表格说明
A1: 子表 | B1: 表格说明 | C1: 流程 | D1: 截图
A2: 年目标 | B2: 1. 2023年计划对比2022年实际完成的增长情况 2. 2023年计划完成销售额部分根据每月目标分解的每月销售额求和而来 3. 自己导入2022年的数据即可 其余部分均有公式 | C2: / | D2: /
A3: 2023年利润预测 | B3: 1. 旧品的FBA操作费 退款金额 平台费用等数据都是用2023年的目标销售额与2022年各个指标的比率相乘得来的预估数据 2. 广告花费部分则是根据船长2022年的CPC及转化率和预估的广告订单占比 得出的数据， 对于部分旧品可能存在2022年头程成本或者广告成本 促销成本较高的情况 可以根据产品当前的一个实际情况给予一个系数
A4: 市占率目标 | B4: 1. 表格包括对2023年整体的市场预估以及xxx的目标市占率 2. 整体的市场预估根据过去4年的市场容量复合增长情况得出 3. 表格无需任何预处理操作 直接有公式获取子表 - 市场概况里的数据 | C4: / | D4: /
A5: 单品目标年销量 | B5: 1. 旧品部分是根据xxx过去两年（2021-2022年)的销售数据得出的复合增长情况 作为2023年的销量目标增长，其中可能有部分新品是有出现暴增的情况 这种情况下 在销量目标占比那里除以一个系数即可 2. 新品规划部分批注上写了试产时间 各自按照站点情况 填写全年的目标销量 3. 其余系列部分均嵌入公式 除了第一点提到的情况 其余无需改动 | C5: /
A6: 每月目标分解 | B6: 1. 表格自动获取 子表 - 单品目标年销量里的年销售额 根据子表 - 2022年销售情况里每个月份占全年销售额的比例计算出每月的销售额 2. 对于部分新品 由于试产时间不一 有些上半年就可以卖 有些年中才试产 下半年销售 因此根据2022年的每月销售额占比计算会有缺失 因此均在11-12月份给出了一个增长系数(主要是销售额占比的增长系数) | C6: /
A7: 市场概况 | B7: 1. 表格包括了xxx自身总的及部分细分ASIN的销量及市占率走势 市场容量及市场份额的趋势 以及过去4年的市场容量复合增长和过去2年的市场份额复合增长情况 2. 其中有几个部分 需要手动改动 1）xxx主要ASIN销售情况(2022年) 这一部分需要修改自己ASIN所在类目市场容量及市场份额这部分的数据来源 2）各类目TOP5品牌集中度(近30天)这一部分也需要修改自己ASIN所在类目市场容量及市场份额这部分的数据来源 3. 过去四年市场销量复合增长情况这部分 需要通过sorftime插件获取2019年-2020年的销量数据 因为卖家精灵只能获取20年12月份到22年12月份的数据 | C7: /
A8: 2022年销售情况 | B8: 1. 内嵌公式 无需任何改动 2. 各站点可能有些ASIN是独立的 加入进去 下拉公式即可 | C8: / | D8: /
A9: 单品每月销售额占比 | B9: 1. 内嵌公式 无需任何改动 2. 各站点可能有些ASIN是独立的 加入进去 下拉公式即可 | C9: / | D9: /
A10: 船长每月数据(2021年) | B10: 1. 数据获取路径: 数据方舟 - 月度分析报表 - 筛选2021年的数据 | C10: /
A11: 船长每月数据(2022年) | B11: 1. 数据获取路径: 数据方舟 - 月度分析报表 - 筛选2022年的数据
A12: 每月市场趋势 | B12: 1. 数据下载路径: 卖家精灵 - 选市场 - 选择类目 - 筛选市场 - 下载市场分析报告为Excel格式 2. 文件下载下来后 复制 行业销售趋势的数据即可
A13: 类目品牌市占率 | B13: 1. 数据下载路径: 卖家精灵 - 选市场 - 选择类目 - 筛选市场 - 下载市场分析报告为Excel格式 2. 文件下载下来后 复制 品牌集中度的数据即可
A14: 2021&2022营销成本概况 | B14: 拉取2021年及2022年船长的数据得出的营销成本概况
A15: 2022年全年财务报表 | B15: 在全年的财务报表里做数据预处理 行一列只保留渠道SKU 然后复制过来即可

Sheet 年目标
A1: 2023年度目标计划 | H1: 各系列产品销量及销售额明细(年度)
A2: 月份 | B2: 2022年计划完成 | C2: 2022年实际完成 | D2: 2022年实际完成率 | E2: 2023年计划完成 | F2: 同比增长率 | H2: 大类 | I2: 系列 | J2: 2022年销量 | K2: 2022年销售额 | L2: 2023年计划销量 | M2: 2023年计划销售额 | N2: 销量同比 | O2: 销售额同比
A3: 1 | D3: =IFERROR(C3/B3,0) -> 0 | F3: =IFERROR((E3-C3)/C3,0) -> 0 | J3: =SUMIFS(单品目标年销量!I:I,单品目标年销量!B:B,I:I,单品目标年销量!A:A,H:H) -> 0 | K3: =SUMIFS(单品目标年销量!P:P,单品目标年销量!B:B,I:I,单品目标年销量!A:A,H:H) -> 0 | L3: =SUMIFS(单品目标年销量!U:U,单品目标年销量!B:B,I:I,单品目标年销量!A:A,H:H) -> 0 | M3: =SUMIFS(单品目标年销量!W:W,单品目标年销量!B:B,I:I,单品目标年销量!A:A,H:H) -> 0 | N3: =IFERROR((L3-J3)/J3,0) -> 0 | O3: =IFERROR((M3-K3)/K3,0) -> 0
A4: 2 | D4: =IFERROR(C4/B4,0) -> 0 | F4: =IFERROR((E4-C4)/C4,0) -> 0 | J4: =SUMIFS(单品目标年销量!I:I,单品目标年销量!B:B,I:I,单品目标年销量!A:A,H:H) -> 0 | K4: =SUMIFS(单品目标年销量!P:P,单品目标年销量!B:B,I:I,单品目标年销量!A:A,H:H) -> 0 | L4: =SUMIFS(单品目标年销量!U:U,单品目标年销量!B:B,I:I,单品目标年销量!A:A,H:H) -> 0 | M4: =SUMIFS(单品目标年销量!W:W,单品目标年销量!B:B,I:I,单品目标年销量!A:A,H:H) -> 0 | N4: =IFERROR((L4-J4)/J4,0) -> 0 | O4: =IFERROR((M4-K4)/K4,0) -> 0
A5: 3 | D5: =IFERROR(C5/B5,0) -> 0 | F5: =IFERROR((E5-C5)/C5,0) -> 0 | J5: =SUMIFS(单品目标年销量!I:I,单品目标年销量!B:B,I:I,单品目标年销量!A:A,H:H) -> 0 | K5: =SUMIFS(单品目标年销量!P:P,单品目标年销量!B:B,I:I,单品目标年销量!A:A,H:H) -> 0 | L5: =SUMIFS(单品目标年销量!U:U,单品目标年销量!B:B,I:I,单品目标年销量!A:A,H:H) -> 0 | M5: =SUMIFS(单品目标年销量!W:W,单品目标年销量!B:B,I:I,单品目标年销量!A:A,H:H) -> 0 | N5: =IFERROR((L5-J5)/J5,0) -> 0 | O5: =IFERROR((M5-K5)/K5,0) -> 0
A6: 4 | D6: =IFERROR(C6/B6,0) -> 0 | F6: =IFERROR((E6-C6)/C6,0) -> 0 | J6: =SUMIFS(单品目标年销量!I:I,单品目标年销量!B:B,I:I,单品目标年销量!A:A,H:H) -> 0 | K6: =SUMIFS(单品目标年销量!P:P,单品目标年销量!B:B,I:I,单品目标年销量!A:A,H:H) -> 0 | L6: =SUMIFS(单品目标年销量!U:U,单品目标年销量!B:B,I:I,单品目标年销量!A:A,H:H) -> 0 | M6: =SUMIFS(单品目标年销量!W:W,单品目标年销量!B:B,I:I,单品目标年销量!A:A,H:H) -> 0 | N6: =IFERROR((L6-J6)/J6,0) -> 0 | O6: =IFERROR((M6-K6)/K6,0) -> 0
A7: 5 | D7: =IFERROR(C7/B7,0) -> 0 | F7: =IFERROR((E7-C7)/C7,0) -> 0 | J7: =SUMIFS(单品目标年销量!I:I,单品目标年销量!B:B,I:I,单品目标年销量!A:A,H:H) -> 0 | K7: =SUMIFS(单品目标年销量!P:P,单品目标年销量!B:B,I:I,单品目标年销量!A:A,H:H) -> 0 | L7: =SUMIFS(单品目标年销量!U:U,单品目标年销量!B:B,I:I,单品目标年销量!A:A,H:H) -> 0 | M7: =SUMIFS(单品目标年销量!W:W,单品目标年销量!B:B,I:I,单品目标年销量!A:A,H:H) -> 0 | N7: =IFERROR((L7-J7)/J7,0) -> 0 | O7: =IFERROR((M7-K7)/K7,0) -> 0
A8: 6 | D8: =IFERROR(C8/B8,0) -> 0 | F8: =IFERROR((E8-C8)/C8,0) -> 0 | J8: =SUMIFS(单品目标年销量!I:I,单品目标年销量!B:B,I:I,单品目标年销量!A:A,H:H) -> 0 | K8: =SUMIFS(单品目标年销量!P:P,单品目标年销量!B:B,I:I,单品目标年销量!A:A,H:H) -> 0 | L8: =SUMIFS(单品目标年销量!U:U,单品目标年销量!B:B,I:I,单品目标年销量!A:A,H:H) -> 0 | M8: =SUMIFS(单品目标年销量!W:W,单品目标年销量!B:B,I:I,单品目标年销量!A:A,H:H) -> 0 | N8: =IFERROR((L8-J8)/J8,0) -> 0 | O8: =IFERROR((M8-K8)/K8,0) -> 0
A9: 7 | D9: =IFERROR(C9/B9,0) -> 0 | F9: =IFERROR((E9-C9)/C9,0) -> 0 | J9: =SUMIFS(单品目标年销量!I:I,单品目标年销量!B:B,I:I,单品目标年销量!A:A,H:H) -> 0 | K9: =SUMIFS(单品目标年销量!P:P,单品目标年销量!B:B,I:I,单品目标年销量!A:A,H:H) -> 0 | L9: =SUMIFS(单品目标年销量!U:U,单品目标年销量!B:B,I:I,单品目标年销量!A:A,H:H) -> 0 | M9: =SUMIFS(单品目标年销量!W:W,单品目标年销量!B:B,I:I,单品目标年销量!A:A,H:H) -> 0 | N9: =IFERROR((L9-J9)/J9,0) -> 0 | O9: =IFERROR((M9-K9)/K9,0) -> 0
A10: 8 | D10: =IFERROR(C10/B10,0) -> 0 | F10: =IFERROR((E10-C10)/C10,0) -> 0 | J10: =SUMIFS(单品目标年销量!I:I,单品目标年销量!B:B,I:I,单品目标年销量!A:A,H:H) -> 0 | K10: =SUMIFS(单品目标年销量!P:P,单品目标年销量!B:B,I:I,单品目标年销量!A:A,H:H) -> 0 | L10: =SUMIFS(单品目标年销量!U:U,单品目标年销量!B:B,I:I,单品目标年销量!A:A,H:H) -> 0 | M10: =SUMIFS(单品目标年销量!W:W,单品目标年销量!B:B,I:I,单品目标年销量!A:A,H:H) -> 0 | N10: =IFERROR((L10-J10)/J10,0) -> 0 | O10: =IFERROR((M10-K10)/K10,0) -> 0
A11: 9 | D11: =IFERROR(C11/B11,0) -> 0 | F11: =IFERROR((E11-C11)/C11,0) -> 0 | J11: =SUMIFS(单品目标年销量!I:I,单品目标年销量!B:B,I:I,单品目标年销量!A:A,H:H) -> 0 | K11: =SUMIFS(单品目标年销量!P:P,单品目标年销量!B:B,I:I,单品目标年销量!A:A,H:H) -> 0 | L11: =SUMIFS(单品目标年销量!U:U,单品目标年销量!B:B,I:I,单品目标年销量!A:A,H:H) -> 0 | M11: =SUMIFS(单品目标年销量!W:W,单品目标年销量!B:B,I:I,单品目标年销量!A:A,H:H) -> 0 | N11: =IFERROR((L11-J11)/J11,0) -> 0 | O11: =IFERROR((M11-K11)/K11,0) -> 0
A12: 10 | D12: =IFERROR(C12/B12,0) -> 0 | F12: =IFERROR((E12-C12)/C12,0) -> 0 | H12: 总计 | I12: / | J12: =SUM(J3:J11) -> 0 | K12: =SUM(K3:K11) -> 0 | L12: =SUM(L3:L11) -> 0 | M12: =SUM(M3:M11) -> 0 | N12: =IFERROR((L12-J12)/J12,0) -> 0 | O12: =IFERROR((M12-K12)/K12,0) -> 0
A13: 11 | D13: =IFERROR(C13/B13,0) -> 0 | F13: =IFERROR((E13-C13)/C13,0) -> 0
A14: 12 | D14: =IFERROR(C14/B14,0) -> 0 | F14: =IFERROR((E14-C14)/C14,0) -> 0
A15: 总计 | B15: =SUM(B3:B14) -> 0 | C15: =SUM(C3:C14) -> 0 | D15: =IFERROR(C15/B15,0) -> 0 | E15: =SUM(E3:E14) -> 0 | F15: =IFERROR((E15-C15)/C15,0) -> 0
A17: 币种 | B17: 汇率
A18: EUR | B18: 1.0682148
A19: GBP | B19: 1.2075472
A20: CNY | B20: 6.89
A21: SEK | B21: 0.0956459

Sheet 2023年利润预测
A1: 产品大类 | B1: 产品系列 | C1: 产品SKU | D1: 产品ASIN | E1: 型号系列 | F1: 产品中文名 | G1: 2023年利润预测
G2: 预估销售额 | H2: 预估销量 | I2: 预估广告订单量 | J2: 退款金额 | K2: FBA操作费 | L2: 平台费用 | M2: 头程费用 | N2: 产品成本 | O2: 税金 | P2: 预估广告花费 | Q2: 广告花费占比 | R2: 预估CPC | S2: 预估CPA | T2: 预估TCPA | U2: 预估促销花费 | V2: 促销花费占比 | W2: 预估转化率 | X2: 预估利润 | Y2: 预估利润率
G3: =SUMIF(每月目标分解!E:E,F:F,每月目标分解!R:R)*年目标!$B$18 -> 0 | H3: =IFERROR(SUMIF(F:F,每月目标分解!E:E,每月目标分解!R:R)/SUMIF(F:F,单品目标年销量!E:E,单品目标年销量!F:F),0) -> 0 | I3: =H3*0.4 -> 0 | J3: =IFERROR(G3*'2022年全年财务报表'!$E$154,0) -> 0 | K3: =G3*'2022年全年财务报表'!$G$154 -> 0 | L3: =G3*'2022年全年财务报表'!$I$154 -> 0 | M3: =G3*'2022年全年财务报表'!$O$154 -> 0 | N3: =G3*'2022年全年财务报表'!$Q$154 -> 0 | O3: =G3*'2022年全年财务报表'!$S$154 -> 0 | P3: =IFERROR(I3/W3*R3,0) -> 0 | Q3: =IFERROR(P3/G3,0) -> 0 | R3: =SUMIF('船长每月数据(2023年)'!C:C,"BBQ",'船长每月数据(2023年)'!AA:AA)/SUMIF('船长每月数据(2023年)'!C:C,"BBQ",'船长每月数据(2023年)'!AD:AD)*年目标!$B$18 -> #DIV/0! | S3: =IFERROR(P3/I3,0) -> 0 | T3: =IFERROR(P3/H3,0) -> 0 | U3: =G3*'2022年全年财务报表'!$K$154 -> 0 | V3: =IFERROR(U3/G3,0) -> 0 | W3: =SUMIF('船长每月数据(2023年)'!C:C,"BBQ",'船长每月数据(2023年)'!P:P)/SUMIF('船长每月数据(2023年)'!C:C,"BBQ",'船长每月数据(2023年)'!H:H) -> #DIV/0! | X3: =IFERROR(G3+J3+K3+L3+M3+N3+O3+P3+U3,0) -> 0 | Y3: =IFERROR(X3/G3,0) -> 0
G4: =SUMIF(每月目标分解!E:E,F:F,每月目标分解!R:R)*年目标!$B$18 -> 0 | H4: =IFERROR(SUMIF(F:F,每月目标分解!E:E,每月目标分解!R:R)/SUMIF(F:F,单品目标年销量!E:E,单品目标年销量!F:F),0) -> 0 | I4: =H4*0.4 -> 0 | J4: =IFERROR(G4*'2022年全年财务报表'!$E$154,0) -> 0 | K4: =G4*'2022年全年财务报表'!$G$154 -> 0 | L4: =G4*'2022年全年财务报表'!$I$154 -> 0 | M4: =G4*'2022年全年财务报表'!$O$154 -> 0 | N4: =G4*'2022年全年财务报表'!$Q$154 -> 0 | O4: =G4*'2022年全年财务报表'!$S$154 -> 0 | P4: =IFERROR(I4/W4*R4,0) -> 0 | Q4: =IFERROR(P4/G4,0) -> 0 | R4: =SUMIF('船长每月数据(2023年)'!C:C,"BBQ",'船长每月数据(2023年)'!AA:AA)/SUMIF('船长每月数据(2023年)'!C:C,"BBQ",'船长每月数据(2023年)'!AD:AD)*年目标!$B$18 -> #DIV/0! | S4: =IFERROR(P4/I4,0) -> 0 | T4: =IFERROR(P4/H4,0) -> 0 | U4: =G4*'2022年全年财务报表'!$K$154 -> 0 | V4: =IFERROR(U4/G4,0) -> 0 | W4: =SUMIF('船长每月数据(2023年)'!C:C,"BBQ",'船长每月数据(2023年)'!P:P)/SUMIF('船长每月数据(2023年)'!C:C,"BBQ",'船长每月数据(2023年)'!H:H) -> #DIV/0! | X4: =IFERROR(G4+J4+K4+L4+M4+N4+O4+P4+U4,0) -> 0 | Y4: =IFERROR(X4/G4,0) -> 0
G5: =SUMIF(每月目标分解!E:E,F:F,每月目标分解!R:R)*年目标!$B$18 -> 0 | H5: =IFERROR(SUMIF(F:F,每月目标分解!E:E,每月目标分解!R:R)/SUMIF(F:F,单品目标年销量!E:E,单品目标年销量!F:F),0) -> 0 | I5: =H5*0.4 -> 0 | J5: =IFERROR(G5*'2022年全年财务报表'!$E$154,0) -> 0 | K5: =G5*'2022年全年财务报表'!$G$154 -> 0 | L5: =G5*'2022年全年财务报表'!$I$154 -> 0 | M5: =G5*'2022年全年财务报表'!$O$154 -> 0 | N5: =G5*'2022年全年财务报表'!$Q$154 -> 0 | O5: =G5*'2022年全年财务报表'!$S$154 -> 0 | P5: =IFERROR(I5/W5*R5,0) -> 0 | Q5: =IFERROR(P5/G5,0) -> 0 | R5: =SUMIF('船长每月数据(2023年)'!C:C,"BBQ",'船长每月数据(2023年)'!AA:AA)/SUMIF('船长每月数据(2023年)'!C:C,"BBQ",'船长每月数据(2023年)'!AD:AD)*年目标!$B$18 -> #DIV/0! | S5: =IFERROR(P5/I5,0) -> 0 | T5: =IFERROR(P5/H5,0) -> 0 | U5: =G5*'2022年全年财务报表'!$K$154 -> 0 | V5: =IFERROR(U5/G5,0) -> 0 | W5: =SUMIF('船长每月数据(2023年)'!C:C,"BBQ",'船长每月数据(2023年)'!P:P)/SUMIF('船长每月数据(2023年)'!C:C,"BBQ",'船长每月数据(2023年)'!H:H) -> #DIV/0! | X5: =IFERROR(G5+J5+K5+L5+M5+N5+O5+P5+U5,0) -> 0 | Y5: =IFERROR(X5/G5,0) -> 0
G6: =SUMIF(每月目标分解!E:E,F:F,每月目标分解!R:R)*年目标!$B$18 -> 0 | H6: =IFERROR(SUMIF(F:F,每月目标分解!E:E,每月目标分解!R:R)/SUMIF(F:F,单品目标年销量!E:E,单品目标年销量!F:F),0) -> 0 | I6: =H6*0.4 -> 0 | J6: =IFERROR(G6*'2022年全年财务报表'!$E$154,0) -> 0 | K6: =G6*'2022年全年财务报表'!$G$154 -> 0 | L6: =G6*'2022年全年财务报表'!$I$154 -> 0 | M6: =G6*'2022年全年财务报表'!$O$154 -> 0 | N6: =G6*'2022年全年财务报表'!$Q$154 -> 0 | O6: =G6*'2022年全年财务报表'!$S$154 -> 0 | P6: =IFERROR(I6/W6*R6,0) -> 0 | Q6: =IFERROR(P6/G6,0) -> 0 | R6: =SUMIF('船长每月数据(2023年)'!C:C,"BBQ",'船长每月数据(2023年)'!AA:AA)/SUMIF('船长每月数据(2023年)'!C:C,"BBQ",'船长每月数据(2023年)'!AD:AD)*年目标!$B$18 -> #DIV/0! | S6: =IFERROR(P6/I6,0) -> 0 | T6: =IFERROR(P6/H6,0) -> 0 | U6: =G6*'2022年全年财务报表'!$K$154 -> 0 | V6: =IFERROR(U6/G6,0) -> 0 | W6: =SUMIF('船长每月数据(2023年)'!C:C,"BBQ",'船长每月数据(2023年)'!P:P)/SUMIF('船长每月数据(2023年)'!C:C,"BBQ",'船长每月数据(2023年)'!H:H) -> #DIV/0! | X6: =IFERROR(G6+J6+K6+L6+M6+N6+O6+P6+U6,0) -> 0 | Y6: =IFERROR(X6/G6,0) -> 0
G7: =SUMIF(每月目标分解!E:E,F:F,每月目标分解!R:R)*年目标!$B$18 -> 0 | H7: =IFERROR(SUMIF(F:F,每月目标分解!E:E,每月目标分解!R:R)/SUMIF(F:F,单品目标年销量!E:E,单品目标年销量!F:F),0) -> 0 | I7: =H7*0.4 -> 0 | J7: =IFERROR(G7*'2022年全年财务报表'!$E$154,0) -> 0 | K7: =G7*'2022年全年财务报表'!$G$154 -> 0 | L7: =G7*'2022年全年财务报表'!$I$154 -> 0 | M7: =G7*'2022年全年财务报表'!$O$154 -> 0 | N7: =G7*'2022年全年财务报表'!$Q$154 -> 0 | O7: =G7*'2022年全年财务报表'!$S$154 -> 0 | P7: =IFERROR(I7/W7*R7,0) -> 0 | Q7: =IFERROR(P7/G7,0) -> 0 | R7: =SUMIF('船长每月数据(2023年)'!C:C,"BBQ",'船长每月数据(2023年)'!AA:AA)/SUMIF('船长每月数据(2023年)'!C:C,"BBQ",'船长每月数据(2023年)'!AD:AD)*年目标!$B$18 -> #DIV/0! | S7: =IFERROR(P7/I7,0) -> 0 | T7: =IFERROR(P7/H7,0) -> 0 | U7: =G7*'2022年全年财务报表'!$K$154 -> 0 | V7: =IFERROR(U7/G7,0) -> 0 | W7: =SUMIF('船长每月数据(2023年)'!C:C,"BBQ",'船长每月数据(2023年)'!P:P)/SUMIF('船长每月数据(2023年)'!C:C,"BBQ",'船长每月数据(2023年)'!H:H) -> #DIV/0! | X7: =IFERROR(G7+J7+K7+L7+M7+N7+O7+P7+U7,0) -> 0 | Y7: =IFERROR(X7/G7,0) -> 0
G8: =SUMIF(每月目标分解!E:E,F:F,每月目标分解!R:R)*年目标!$B$18 -> 0 | H8: =IFERROR(SUMIF(F:F,每月目标分解!E:E,每月目标分解!R:R)/SUMIF(F:F,单品目标年销量!E:E,单品目标年销量!F:F),0) -> 0 | I8: =H8*0.4 -> 0 | J8: =IFERROR(G8*'2022年全年财务报表'!$E$154,0) -> 0 | K8: =G8*'2022年全年财务报表'!$G$154 -> 0 | L8: =G8*'2022年全年财务报表'!$I$154 -> 0 | M8: =G8*'2022年全年财务报表'!$O$154 -> 0 | N8: =G8*'2022年全年财务报表'!$Q$154 -> 0 | O8: =G8*'2022年全年财务报表'!$S$154 -> 0 | P8: =IFERROR(I8/W8*R8,0) -> 0 | Q8: =IFERROR(P8/G8,0) -> 0 | R8: =SUMIF('船长每月数据(2023年)'!C:C,"BBQ",'船长每月数据(2023年)'!AA:AA)/SUMIF('船长每月数据(2023年)'!C:C,"BBQ",'船长每月数据(2023年)'!AD:AD)*年目标!$B$18 -> #DIV/0! | S8: =IFERROR(P8/I8,0) -> 0 | T8: =IFERROR(P8/H8,0) -> 0 | U8: =G8*'2022年全年财务报表'!$K$154 -> 0 | V8: =IFERROR(U8/G8,0) -> 0 | W8: =SUMIF('船长每月数据(2023年)'!C:C,"BBQ",'船长每月数据(2023年)'!P:P)/SUMIF('船长每月数据(2023年)'!C:C,"BBQ",'船长每月数据(2023年)'!H:H) -> #DIV/0! | X8: =IFERROR(G8+J8+K8+L8+M8+N8+O8+P8+U8,0) -> 0 | Y8: =IFERROR(X8/G8,0) -> 0
G9: =SUMIF(每月目标分解!E:E,F:F,每月目标分解!R:R)*年目标!$B$18 -> 0 | H9: =IFERROR(SUMIF(F:F,每月目标分解!E:E,每月目标分解!R:R)/SUMIF(F:F,单品目标年销量!E:E,单品目标年销量!F:F),0) -> 0 | I9: =H9*0.4 -> 0 | J9: =IFERROR(G9*'2022年全年财务报表'!$E$154,0) -> 0 | K9: =G9*'2022年全年财务报表'!$G$154 -> 0 | L9: =G9*'2022年全年财务报表'!$I$154 -> 0 | M9: =G9*'2022年全年财务报表'!$O$154 -> 0 | N9: =G9*'2022年全年财务报表'!$Q$154 -> 0 | O9: =G9*'2022年全年财务报表'!$S$154 -> 0 | P9: =IFERROR(I9/W9*R9,0) -> 0 | Q9: =IFERROR(P9/G9,0) -> 0 | R9: =SUMIF('船长每月数据(2023年)'!C:C,"BBQ",'船长每月数据(2023年)'!AA:AA)/SUMIF('船长每月数据(2023年)'!C:C,"BBQ",'船长每月数据(2023年)'!AD:AD)*年目标!$B$18 -> #DIV/0! | S9: =IFERROR(P9/I9,0) -> 0 | T9: =IFERROR(P9/H9,0) -> 0 | U9: =G9*'2022年全年财务报表'!$K$154 -> 0 | V9: =IFERROR(U9/G9,0) -> 0 | W9: =SUMIF('船长每月数据(2023年)'!C:C,"BBQ",'船长每月数据(2023年)'!P:P)/SUMIF('船长每月数据(2023年)'!C:C,"BBQ",'船长每月数据(2023年)'!H:H) -> #DIV/0! | X9: =IFERROR(G9+J9+K9+L9+M9+N9+O9+P9+U9,0) -> 0 | Y9: =IFERROR(X9/G9,0) -> 0
G10: =SUMIF(每月目标分解!E:E,F:F,每月目标分解!R:R)*年目标!$B$18 -> 0 | H10: =IFERROR(SUMIF(F:F,每月目标分解!E:E,每月目标分解!R:R)/SUMIF(F:F,单品目标年销量!E:E,单品目标年销量!F:F),0) -> 0 | I10: =H10*0.4 -> 0 | J10: =IFERROR(G10*'2022年全年财务报表'!$E$154,0) -> 0 | K10: =G10*'2022年全年财务报表'!$G$154 -> 0 | L10: =G10*'2022年全年财务报表'!$I$154 -> 0 | M10: =G10*'2022年全年财务报表'!$O$154 -> 0 | N10: =G10*'2022年全年财务报表'!$Q$154 -> 0 | O10: =G10*'2022年全年财务报表'!$S$154 -> 0 | P10: =IFERROR(I10/W10*R10,0) -> 0 | Q10: =IFERROR(P10/G10,0) -> 0 | R10: =SUMIF('船长每月数据(2023年)'!C:C,"BBQ",'船长每月数据(2023年)'!AA:AA)/SUMIF('船长每月数据(2023年)'!C:C,"BBQ",'船长每月数据(2023年)'!AD:AD)*年目标!$B$18 -> #DIV/0! | S10: =IFERROR(P10/I10,0) -> 0 | T10: =IFERROR(P10/H10,0) -> 0 | U10: =G10*'2022年全年财务报表'!$K$154 -> 0 | V10: =IFERROR(U10/G10,0) -> 0 | W10: =SUMIF('船长每月数据(2023年)'!C:C,"BBQ",'船长每月数据(2023年)'!P:P)/SUMIF('船长每月数据(2023年)'!C:C,"BBQ",'船长每月数据(2023年)'!H:H) -> #DIV/0! | X10: =IFERROR(G10+J10+K10+L10+M10+N10+O10+P10+U10,0) -> 0 | Y10: =IFERROR(X10/G10,0) -> 0
G11: =SUMIF(每月目标分解!E:E,F:F,每月目标分解!R:R)*年目标!$B$18 -> 0 | H11: =IFERROR(SUMIF(F:F,每月目标分解!E:E,每月目标分解!R:R)/SUMIF(F:F,单品目标年销量!E:E,单品目标年销量!F:F),0) -> 0 | I11: =H11*0.4 -> 0 | J11: =IFERROR(G11*'2022年全年财务报表'!$E$154,0) -> 0 | K11: =G11*'2022年全年财务报表'!$G$154 -> 0 | L11: =G11*'2022年全年财务报表'!$I$154 -> 0 | M11: =G11*'2022年全年财务报表'!$O$154 -> 0 | N11: =G11*'2022年全年财务报表'!$Q$154 -> 0 | O11: =G11*'2022年全年财务报表'!$S$154 -> 0 | P11: =IFERROR(I11/W11*R11,0) -> 0 | Q11: =IFERROR(P11/G11,0) -> 0 | R11: =SUMIF('船长每月数据(2023年)'!C:C,"BBQ",'船长每月数据(2023年)'!AA:AA)/SUMIF('船长每月数据(2023年)'!C:C,"BBQ",'船长每月数据(2023年)'!AD:AD)*年目标!$B$18 -> #DIV/0! | S11: =IFERROR(P11/I11,0) -> 0 | T11: =IFERROR(P11/H11,0) -> 0 | U11: =G11*'2022年全年财务报表'!$K$154 -> 0 | V11: =IFERROR(U11/G11,0) -> 0 | W11: =SUMIF('船长每月数据(2023年)'!C:C,"BBQ",'船长每月数据(2023年)'!P:P)/SUMIF('船长每月数据(2023年)'!C:C,"BBQ",'船长每月数据(2023年)'!H:H) -> #DIV/0! | X11: =IFERROR(G11+J11+K11+L11+M11+N11+O11+P11+U11,0) -> 0 | Y11: =IFERROR(X11/G11,0) -> 0
G12: =SUMIF(每月目标分解!E:E,F:F,每月目标分解!R:R)*年目标!$B$18 -> 0 | H12: =IFERROR(SUMIF(F:F,每月目标分解!E:E,每月目标分解!R:R)/SUMIF(F:F,单品目标年销量!E:E,单品目标年销量!F:F),0) -> 0 | I12: =H12*0.4 -> 0 | J12: =IFERROR(G12*'2022年全年财务报表'!$E$154,0) -> 0 | K12: =G12*'2022年全年财务报表'!$G$154 -> 0 | L12: =G12*'2022年全年财务报表'!$I$154 -> 0 | M12: =G12*'2022年全年财务报表'!$O$154 -> 0 | N12: =G12*'2022年全年财务报表'!$Q$154 -> 0 | O12: =G12*'2022年全年财务报表'!$S$154 -> 0 | P12: =IFERROR(I12/W12*R12,0) -> 0 | Q12: =IFERROR(P12/G12,0) -> 0 | R12: =SUMIF('船长每月数据(2023年)'!C:C,"BBQ",'船长每月数据(2023年)'!AA:AA)/SUMIF('船长每月数据(2023年)'!C:C,"BBQ",'船长每月数据(2023年)'!AD:AD)*年目标!$B$18 -> #DIV/0! | S12: =IFERROR(P12/I12,0) -> 0 | T12: =IFERROR(P12/H12,0) -> 0 | U12: =G12*'2022年全年财务报表'!$K$154 -> 0 | V12: =IFERROR(U12/G12,0) -> 0 | W12: =SUMIF('船长每月数据(2023年)'!C:C,"BBQ",'船长每月数据(2023年)'!P:P)/SUMIF('船长每月数据(2023年)'!C:C,"BBQ",'船长每月数据(2023年)'!H:H) -> #DIV/0! | X12: =IFERROR(G12+J12+K12+L12+M12+N12+O12+P12+U12,0) -> 0 | Y12: =IFERROR(X12/G12,0) -> 0
G13: =SUMIF(每月目标分解!E:E,F:F,每月目标分解!R:R)*年目标!$B$18 -> 0 | H13: =IFERROR(SUMIF(F:F,每月目标分解!E:E,每月目标分解!R:R)/SUMIF(F:F,单品目标年销量!E:E,单品目标年销量!F:F),0) -> 0 | I13: =H13*0.4 -> 0 | J13: =IFERROR(G13*'2022年全年财务报表'!$E$154,0) -> 0 | K13: =G13*'2022年全年财务报表'!$G$154 -> 0 | L13: =G13*'2022年全年财务报表'!$I$154 -> 0 | M13: =G13*'2022年全年财务报表'!$O$154 -> 0 | N13: =G13*'2022年全年财务报表'!$Q$154 -> 0 | O13: =G13*'2022年全年财务报表'!$S$154 -> 0 | P13: =IFERROR(I13/W13*R13,0) -> 0 | Q13: =IFERROR(P13/G13,0) -> 0 | R13: =SUMIF('船长每月数据(2023年)'!C:C,"BBQ",'船长每月数据(2023年)'!AA:AA)/SUMIF('船长每月数据(2023年)'!C:C,"BBQ",'船长每月数据(2023年)'!AD:AD)*年目标!$B$18 -> #DIV/0! | S13: =IFERROR(P13/I13,0) -> 0 | T13: =IFERROR(P13/H13,0) -> 0 | U13: =G13*'2022年全年财务报表'!$K$154 -> 0 | V13: =IFERROR(U13/G13,0) -> 0 | W13: 0.1399 | X13: =IFERROR(G13+J13+K13+L13+M13+N13+O13+P13+U13,0) -> 0 | Y13: =IFERROR(X13/G13,0) -> 0
G14: =SUMIF(每月目标分解!E:E,F:F,每月目标分解!R:R)*年目标!$B$18 -> 0 | H14: =IFERROR(SUMIF(F:F,每月目标分解!E:E,每月目标分解!R:R)/SUMIF(F:F,单品目标年销量!E:E,单品目标年销量!F:F),0) -> 0 | I14: =IFERROR(SUMIF(D:D,D:D,H:H)*(SUMIF('船长每月数据(2023年)'!E:E,D:D,'船长每月数据(2023年)'!AI:AI)/SUMIF('船长每月数据(2023年)'!E:E,D:D,'船长每月数据(2023年)'!P:P)),0) -> 0 | J14: =SUMIF(D:D,D:D,G:G)*SUMIF('2022年全年财务报表'!A:A,C:C,'2022年全年财务报表'!E:E) -> 0 | K14: =SUMIF(D:D,D:D,G:G)*SUMIF('2022年全年财务报表'!A:A,C:C,'2022年全年财务报表'!G:G) -> 0 | L14: =SUMIF(D:D,D:D,G:G)*SUMIF('2022年全年财务报表'!A:A,C:C,'2022年全年财务报表'!I:I) -> 0 | M14: =SUMIF(D:D,D:D,G:G)*SUMIF('2022年全年财务报表'!A:A,C:C,'2022年全年财务报表'!O:O) -> 0 | N14: =SUMIF(D:D,D:D,G:G)*SUMIF('2022年全年财务报表'!A:A,C:C,'2022年全年财务报表'!Q:Q) -> 0 | O14: =SUMIF(D:D,D:D,G:G)*SUMIF('2022年全年财务报表'!A:A,C:C,'2022年全年财务报表'!S:S) -> 0 | P14: =IFERROR(I14/W14*R14,0)/1.5 -> 0 | Q14: =IFERROR(P14/G14,0) -> 0 | R14: =IFERROR(SUMIF('2021&2022营销成本概况'!C:C,D:D,'2021&2022营销成本概况'!S:S)+SUMIF('2021&2022营销成本概况'!C:C,D:D,'2021&2022营销成本概况'!S:S)*'2021&2022营销成本概况'!$T$37,0)*年目标!$B$18 -> 0 | S14: =IFERROR(P14/I14,0) -> 0 | T14: =IFERROR(P14/H14,0) -> 0 | U14: =SUMIF(D:D,D:D,G:G)*SUMIF('2022年全年财务报表'!A:A,C:C,'2022年全年财务报表'!K:K)/2 -> 0 | V14: =IFERROR(U14/G14,0) -> 0 | W14: =IFERROR(SUMIF('船长每月数据(2023年)'!E:E,D:D,'船长每月数据(2023年)'!P:P)/SUMIF('船长每月数据(2023年)'!E:E,D:D,'船长每月数据(2023年)'!H:H),0) -> 0 | X14: =IFERROR(G14+J14+K14+L14+M14+N14+O14+P14+U14,0) -> 0 | Y14: =IFERROR(X14/G14,0) -> 0
G15: =SUMIF(每月目标分解!E:E,F:F,每月目标分解!R:R)*年目标!$B$18 -> 0 | H15: =IFERROR(SUMIF(F:F,每月目标分解!E:E,每月目标分解!R:R)/SUMIF(F:F,单品目标年销量!E:E,单品目标年销量!F:F),0) -> 0 | I15: =IFERROR(SUMIF(D:D,D:D,H:H)*(SUMIF('船长每月数据(2023年)'!E:E,D:D,'船长每月数据(2023年)'!AI:AI)/SUMIF('船长每月数据(2023年)'!E:E,D:D,'船长每月数据(2023年)'!P:P)),0) -> 0 | J15: =SUMIF(D:D,D:D,G:G)*SUMIF('2022年全年财务报表'!A:A,C:C,'2022年全年财务报表'!E:E) -> 0 | K15: =SUMIF(D:D,D:D,G:G)*SUMIF('2022年全年财务报表'!A:A,C:C,'2022年全年财务报表'!G:G) -> 0 | L15: =SUMIF(D:D,D:D,G:G)*SUMIF('2022年全年财务报表'!A:A,C:C,'2022年全年财务报表'!I:I) -> 0 | M15: =SUMIF(D:D,D:D,G:G)*SUMIF('2022年全年财务报表'!A:A,C:C,'2022年全年财务报表'!O:O) -> 0 | N15: =SUMIF(D:D,D:D,G:G)*SUMIF('2022年全年财务报表'!A:A,C:C,'2022年全年财务报表'!Q:Q) -> 0 | O15: =SUMIF(D:D,D:D,G:G)*SUMIF('2022年全年财务报表'!A:A,C:C,'2022年全年财务报表'!S:S) -> 0 | P15: =IFERROR(I15/W15*R15,0) -> 0 | Q15: =IFERROR(P15/G15,0) -> 0 | R15: =IFERROR(SUMIF('2021&2022营销成本概况'!C:C,D:D,'2021&2022营销成本概况'!S:S)+SUMIF('2021&2022营销成本概况'!C:C,D:D,'2021&2022营销成本概况'!S:S)*'2021&2022营销成本概况'!$T$37,0)*年目标!$B$18 -> 0 | S15: =IFERROR(P15/I15,0) -> 0 | T15: =IFERROR(P15/H15,0) -> 0 | U15: =SUMIF(D:D,D:D,G:G)*SUMIF('2022年全年财务报表'!A:A,C:C,'2022年全年财务报表'!K:K) -> 0 | V15: =IFERROR(U15/G15,0) -> 0 | W15: =IFERROR(SUMIF('船长每月数据(2023年)'!E:E,D:D,'船长每月数据(2023年)'!P:P)/SUMIF('船长每月数据(2023年)'!E:E,D:D,'船长每月数据(2023年)'!H:H),0) -> 0 | X15: =IFERROR(G15+J15+K15+L15+M15+N15+O15+P15+U15,0) -> 0 | Y15: =IFERROR(X15/G15,0) -> 0
G16: =SUMIF(每月目标分解!E:E,F:F,每月目标分解!R:R)*年目标!$B$18 -> 0 | H16: =IFERROR(SUMIF(F:F,每月目标分解!E:E,每月目标分解!R:R)/SUMIF(F:F,单品目标年销量!E:E,单品目标年销量!F:F),0) -> 0 | I16: =IFERROR(SUMIF(D:D,D:D,H:H)*(SUMIF('船长每月数据(2023年)'!E:E,D:D,'船长每月数据(2023年)'!AI:AI)/SUMIF('船长每月数据(2023年)'!E:E,D:D,'船长每月数据(2023年)'!P:P)),0) -> 0 | J16: =SUMIF(D:D,D:D,G:G)*SUMIF('2022年全年财务报表'!A:A,C:C,'2022年全年财务报表'!E:E) -> 0 | K16: =SUMIF(D:D,D:D,G:G)*SUMIF('2022年全年财务报表'!A:A,C:C,'2022年全年财务报表'!G:G) -> 0 | L16: =SUMIF(D:D,D:D,G:G)*SUMIF('2022年全年财务报表'!A:A,C:C,'2022年全年财务报表'!I:I) -> 0 | M16: =SUMIF(D:D,D:D,G:G)*SUMIF('2022年全年财务报表'!A:A,C:C,'2022年全年财务报表'!O:O) -> 0 | N16: =SUMIF(D:D,D:D,G:G)*SUMIF('2022年全年财务报表'!A:A,C:C,'2022年全年财务报表'!Q:Q) -> 0 | O16: =SUMIF(D:D,D:D,G:G)*SUMIF('2022年全年财务报表'!A:A,C:C,'2022年全年财务报表'!S:S) -> 0 | P16: =IFERROR(I16/W16*R16,0)/1.2 -> 0 | Q16: =IFERROR(P16/G16,0) -> 0 | R16: =IFERROR(SUMIF('2021&2022营销成本概况'!C:C,D:D,'2021&2022营销成本概况'!S:S)+SUMIF('2021&2022营销成本概况'!C:C,D:D,'2021&2022营销成本概况'!S:S)*'2021&2022营销成本概况'!$T$37,0)*年目标!$B$18 -> 0 | S16: =IFERROR(P16/I16,0) -> 0 | T16: =IFERROR(P16/H16,0) -> 0 | U16: =SUMIF(D:D,D:D,G:G)*SUMIF('2022年全年财务报表'!A:A,C:C,'2022年全年财务报表'!K:K)/1.2 -> 0 | V16: =IFERROR(U16/G16,0) -> 0 | W16: =IFERROR(SUMIF('船长每月数据(2023年)'!E:E,D:D,'船长每月数据(2023年)'!P:P)/SUMIF('船长每月数据(2023年)'!E:E,D:D,'船长每月数据(2023年)'!H:H),0) -> 0 | X16: =IFERROR(G16+J16+K16+L16+M16+N16+O16+P16+U16,0) -> 0 | Y16: =IFERROR(X16/G16,0) -> 0
G17: =SUMIF(每月目标分解!E:E,F:F,每月目标分解!R:R)*年目标!$B$18 -> 0 | H17: =IFERROR(SUMIF(F:F,每月目标分解!E:E,每月目标分解!R:R)/SUMIF(F:F,单品目标年销量!E:E,单品目标年销量!F:F),0) -> 0 | I17: =IFERROR(SUMIF(D:D,D:D,H:H)*(SUMIF('船长每月数据(2023年)'!E:E,D:D,'船长每月数据(2023年)'!AI:AI)/SUMIF('船长每月数据(2023年)'!E:E,D:D,'船长每月数据(2023年)'!P:P)),0) -> 0 | J17: =SUMIF(D:D,D:D,G:G)*SUMIF('2022年全年财务报表'!A:A,C:C,'2022年全年财务报表'!E:E) -> 0 | K17: =SUMIF(D:D,D:D,G:G)*SUMIF('2022年全年财务报表'!A:A,C:C,'2022年全年财务报表'!G:G) -> 0 | L17: =SUMIF(D:D,D:D,G:G)*SUMIF('2022年全年财务报表'!A:A,C:C,'2022年全年财务报表'!I:I) -> 0 | M17: =SUMIF(D:D,D:D,G:G)*SUMIF('2022年全年财务报表'!A:A,C:C,'2022年全年财务报表'!O:O) -> 0 | N17: =SUMIF(D:D,D:D,G:G)*SUMIF('2022年全年财务报表'!A:A,C:C,'2022年全年财务报表'!Q:Q) -> 0 | O17: =SUMIF(D:D,D:D,G:G)*SUMIF('2022年全年财务报表'!A:A,C:C,'2022年全年财务报表'!S:S) -> 0 | P17: =IFERROR(I17/W17*R17,0) -> 0 | Q17: =IFERROR(P17/G17,0) -> 0 | R17: =IFERROR(SUMIF('2021&2022营销成本概况'!C:C,D:D,'2021&2022营销成本概况'!S:S)+SUMIF('2021&2022营销成本概况'!C:C,D:D,'2021&2022营销成本概况'!S:S)*'2021&2022营销成本概况'!$T$37,0)*年目标!$B$18 -> 0 | S17: =IFERROR(P17/I17,0) -> 0 | T17: =IFERROR(P17/H17,0) -> 0 | U17: =SUMIF(D:D,D:D,G:G)*SUMIF('2022年全年财务报表'!A:A,C:C,'2022年全年财务报表'!K:K) -> 0 | V17: =IFERROR(U17/G17,0) -> 0 | W17: =IFERROR(SUMIF('船长每月数据(2023年)'!E:E,D:D,'船长每月数据(2023年)'!P:P)/SUMIF('船长每月数据(2023年)'!E:E,D:D,'船长每月数据(2023年)'!H:H),0) -> 0 | X17: =IFERROR(G17+J17+K17+L17+M17+N17+O17+P17+U17,0) -> 0 | Y17: =IFERROR(X17/G17,0) -> 0
G18: =SUMIF(每月目标分解!E:E,F:F,每月目标分解!R:R)*年目标!$B$18 -> 0 | H18: =IFERROR(SUMIF(F:F,每月目标分解!E:E,每月目标分解!R:R)/SUMIF(F:F,单品目标年销量!E:E,单品目标年销量!F:F),0) -> 0 | I18: =IFERROR(SUMIF(D:D,D:D,H:H)*(SUMIF('船长每月数据(2023年)'!E:E,D:D,'船长每月数据(2023年)'!AI:AI)/SUMIF('船长每月数据(2023年)'!E:E,D:D,'船长每月数据(2023年)'!P:P)),0) -> 0 | J18: =SUMIF(D:D,D:D,G:G)*SUMIF('2022年全年财务报表'!A:A,C:C,'2022年全年财务报表'!E:E) -> 0 | K18: =SUMIF(D:D,D:D,G:G)*SUMIF('2022年全年财务报表'!A:A,C:C,'2022年全年财务报表'!G:G) -> 0 | L18: =SUMIF(D:D,D:D,G:G)*SUMIF('2022年全年财务报表'!A:A,C:C,'2022年全年财务报表'!I:I) -> 0 | M18: =SUMIF(D:D,D:D,G:G)*SUMIF('2022年全年财务报表'!A:A,C:C,'2022年全年财务报表'!O:O) -> 0 | N18: =SUMIF(D:D,D:D,G:G)*SUMIF('2022年全年财务报表'!A:A,C:C,'2022年全年财务报表'!Q:Q) -> 0 | O18: =SUMIF(D:D,D:D,G:G)*SUMIF('2022年全年财务报表'!A:A,C:C,'2022年全年财务报表'!S:S) -> 0 | P18: =IFERROR(I18/W18*R18,0) -> 0 | Q18: =IFERROR(P18/G18,0) -> 0 | R18: =IFERROR(SUMIF('2021&2022营销成本概况'!C:C,D:D,'2021&2022营销成本概况'!S:S)+SUMIF('2021&2022营销成本概况'!C:C,D:D,'2021&2022营销成本概况'!S:S)*'2021&2022营销成本概况'!$T$37,0)*年目标!$B$18 -> 0 | S18: =IFERROR(P18/I18,0) -> 0 | T18: =IFERROR(P18/H18,0) -> 0 | U18: =SUMIF(D:D,D:D,G:G)*SUMIF('2022年全年财务报表'!A:A,C:C,'2022年全年财务报表'!K:K) -> 0 | V18: =IFERROR(U18/G18,0) -> 0 | W18: =IFERROR(SUMIF('船长每月数据(2023年)'!E:E,D:D,'船长每月数据(2023年)'!P:P)/SUMIF('船长每月数据(2023年)'!E:E,D:D,'船长每月数据(2023年)'!H:H),0) -> 0 | X18: =IFERROR(G18+J18+K18+L18+M18+N18+O18+P18+U18,0) -> 0 | Y18: =IFERROR(X18/G18,0) -> 0
G19: =SUMIF(每月目标分解!E:E,F:F,每月目标分解!R:R)*年目标!$B$18 -> 0 | H19: =IFERROR(SUMIF(F:F,每月目标分解!E:E,每月目标分解!R:R)/SUMIF(F:F,单品目标年销量!E:E,单品目标年销量!F:F),0) -> 0 | I19: =IFERROR(SUMIF(D:D,D:D,H:H)*(SUMIF('船长每月数据(2023年)'!E:E,D:D,'船长每月数据(2023年)'!AI:AI)/SUMIF('船长每月数据(2023年)'!E:E,D:D,'船长每月数据(2023年)'!P:P)),0) -> 0 | J19: =SUMIF(D:D,D:D,G:G)*SUMIF('2022年全年财务报表'!A:A,C:C,'2022年全年财务报表'!E:E) -> 0 | K19: =SUMIF(D:D,D:D,G:G)*SUMIF('2022年全年财务报表'!A:A,C:C,'2022年全年财务报表'!G:G) -> 0 | L19: =SUMIF(D:D,D:D,G:G)*SUMIF('2022年全年财务报表'!A:A,C:C,'2022年全年财务报表'!I:I) -> 0 | M19: =SUMIF(D:D,D:D,G:G)*SUMIF('2022年全年财务报表'!A:A,C:C,'2022年全年财务报表'!O:O) -> 0 | N19: =SUMIF(D:D,D:D,G:G)*SUMIF('2022年全年财务报表'!A:A,C:C,'2022年全年财务报表'!Q:Q) -> 0 | O19: =SUMIF(D:D,D:D,G:G)*SUMIF('2022年全年财务报表'!A:A,C:C,'2022年全年财务报表'!S:S) -> 0 | P19: =IFERROR(I19/W19*R19,0)*0 -> 0 | Q19: =IFERROR(P19/G19,0) -> 0 | R19: =IFERROR(SUMIF('2021&2022营销成本概况'!C:C,D:D,'2021&2022营销成本概况'!S:S)+SUMIF('2021&2022营销成本概况'!C:C,D:D,'2021&2022营销成本概况'!S:S)*'2021&2022营销成本概况'!$T$37,0)*年目标!$B$18 -> 0 | S19: =IFERROR(P19/I19,0) -> 0 | T19: =IFERROR(P19/H19,0) -> 0 | U19: =SUMIF(D:D,D:D,G:G)*SUMIF('2022年全年财务报表'!A:A,C:C,'2022年全年财务报表'!K:K)/2 -> 0 | V19: =IFERROR(U19/G19,0) -> 0 | W19: =IFERROR(SUMIF('船长每月数据(2023年)'!E:E,D:D,'船长每月数据(2023年)'!P:P)/SUMIF('船长每月数据(2023年)'!E:E,D:D,'船长每月数据(2023年)'!H:H),0) -> 0 | X19: =IFERROR(G19+J19+K19+L19+M19+N19+O19+P19+U19,0) -> 0 | Y19: =IFERROR(X19/G19,0) -> 0
G20: =SUMIF(每月目标分解!E:E,F:F,每月目标分解!R:R)*年目标!$B$18 -> 0 | H20: =IFERROR(SUMIF(F:F,每月目标分解!E:E,每月目标分解!R:R)/SUMIF(F:F,单品目标年销量!E:E,单品目标年销量!F:F),0) -> 0 | I20: =IFERROR(SUMIF(D:D,D:D,H:H)*(SUMIF('船长每月数据(2023年)'!E:E,D:D,'船长每月数据(2023年)'!AI:AI)/SUMIF('船长每月数据(2023年)'!E:E,D:D,'船长每月数据(2023年)'!P:P)),0) -> 0 | J20: =SUMIF(D:D,D:D,G:G)*SUMIF('2022年全年财务报表'!A:A,C:C,'2022年全年财务报表'!E:E) -> 0 | K20: =SUMIF(D:D,D:D,G:G)*SUMIF('2022年全年财务报表'!A:A,C:C,'2022年全年财务报表'!G:G) -> 0 | L20: =SUMIF(D:D,D:D,G:G)*SUMIF('2022年全年财务报表'!A:A,C:C,'2022年全年财务报表'!I:I) -> 0 | M20: =SUMIF(D:D,D:D,G:G)*SUMIF('2022年全年财务报表'!A:A,C:C,'2022年全年财务报表'!O:O) -> 0 | N20: =SUMIF(D:D,D:D,G:G)*SUMIF('2022年全年财务报表'!A:A,C:C,'2022年全年财务报表'!Q:Q) -> 0 | O20: =SUMIF(D:D,D:D,G:G)*SUMIF('2022年全年财务报表'!A:A,C:C,'2022年全年财务报表'!S:S) -> 0 | P20: =IFERROR(I20/W20*R20,0) -> 0 | Q20: =IFERROR(P20/G20,0) -> 0 | R20: =IFERROR(SUMIF('2021&2022营销成本概况'!C:C,D:D,'2021&2022营销成本概况'!S:S)+SUMIF('2021&2022营销成本概况'!C:C,D:D,'2021&2022营销成本概况'!S:S)*'2021&2022营销成本概况'!$T$37,0)*年目标!$B$18 -> 0 | S20: =IFERROR(P20/I20,0) -> 0 | T20: =IFERROR(P20/H20,0) -> 0 | U20: =SUMIF(D:D,D:D,G:G)*SUMIF('2022年全年财务报表'!A:A,C:C,'2022年全年财务报表'!K:K) -> 0 | V20: =IFERROR(U20/G20,0) -> 0 | W20: =IFERROR(SUMIF('船长每月数据(2023年)'!E:E,D:D,'船长每月数据(2023年)'!P:P)/SUMIF('船长每月数据(2023年)'!E:E,D:D,'船长每月数据(2023年)'!H:H),0) -> 0 | X20: =IFERROR(G20+J20+K20+L20+M20+N20+O20+P20+U20,0) -> 0 | Y20: =IFERROR(X20/G20,0) -> 0
G21: =SUMIF(每月目标分解!E:E,F:F,每月目标分解!R:R)*年目标!$B$18 -> 0 | H21: =IFERROR(SUMIF(F:F,每月目标分解!E:E,每月目标分解!R:R)/SUMIF(F:F,单品目标年销量!E:E,单品目标年销量!F:F),0) -> 0 | I21: =IFERROR(SUMIF(D:D,D:D,H:H)*(SUMIF('船长每月数据(2023年)'!E:E,D:D,'船长每月数据(2023年)'!AI:AI)/SUMIF('船长每月数据(2023年)'!E:E,D:D,'船长每月数据(2023年)'!P:P)),0) -> 0 | J21: =SUMIF(D:D,D:D,G:G)*SUMIF('2022年全年财务报表'!A:A,C:C,'2022年全年财务报表'!E:E) -> 0 | K21: =SUMIF(D:D,D:D,G:G)*SUMIF('2022年全年财务报表'!A:A,C:C,'2022年全年财务报表'!G:G) -> 0 | L21: =SUMIF(D:D,D:D,G:G)*SUMIF('2022年全年财务报表'!A:A,C:C,'2022年全年财务报表'!I:I) -> 0 | M21: =SUMIF(D:D,D:D,G:G)*SUMIF('2022年全年财务报表'!A:A,C:C,'2022年全年财务报表'!O:O) -> 0 | N21: =SUMIF(D:D,D:D,G:G)*SUMIF('2022年全年财务报表'!A:A,C:C,'2022年全年财务报表'!Q:Q) -> 0 | O21: =SUMIF(D:D,D:D,G:G)*SUMIF('2022年全年财务报表'!A:A,C:C,'2022年全年财务报表'!S:S) -> 0 | P21: =IFERROR(I21/W21*R21,0) -> 0 | Q21: =IFERROR(P21/G21,0) -> 0 | R21: =IFERROR(SUMIF('2021&2022营销成本概况'!C:C,D:D,'2021&2022营销成本概况'!S:S)+SUMIF('2021&2022营销成本概况'!C:C,D:D,'2021&2022营销成本概况'!S:S)*'2021&2022营销成本概况'!$T$37,0)*年目标!$B$18 -> 0 | S21: =IFERROR(P21/I21,0) -> 0 | T21: =IFERROR(P21/H21,0) -> 0 | U21: =SUMIF(D:D,D:D,G:G)*SUMIF('2022年全年财务报表'!A:A,C:C,'2022年全年财务报表'!K:K) -> 0 | V21: =IFERROR(U21/G21,0) -> 0 | W21: =IFERROR(SUMIF('船长每月数据(2023年)'!E:E,D:D,'船长每月数据(2023年)'!P:P)/SUMIF('船长每月数据(2023年)'!E:E,D:D,'船长每月数据(2023年)'!H:H),0) -> 0 | X21: =IFERROR(G21+J21+K21+L21+M21+N21+O21+P21+U21,0) -> 0 | Y21: =IFERROR(X21/G21,0) -> 0
G22: =SUMIF(每月目标分解!E:E,F:F,每月目标分解!R:R)*年目标!$B$18 -> 0 | H22: =IFERROR(SUMIF(F:F,每月目标分解!E:E,每月目标分解!R:R)/SUMIF(F:F,单品目标年销量!E:E,单品目标年销量!F:F),0) -> 0 | I22: =IFERROR(SUMIF(D:D,D:D,H:H)*(SUMIF('船长每月数据(2023年)'!E:E,D:D,'船长每月数据(2023年)'!AI:AI)/SUMIF('船长每月数据(2023年)'!E:E,D:D,'船长每月数据(2023年)'!P:P)),0) -> 0 | J22: =SUMIF(D:D,D:D,G:G)*SUMIF('2022年全年财务报表'!A:A,C:C,'2022年全年财务报表'!E:E) -> 0 | K22: =SUMIF(D:D,D:D,G:G)*SUMIF('2022年全年财务报表'!A:A,C:C,'2022年全年财务报表'!G:G) -> 0 | L22: =SUMIF(D:D,D:D,G:G)*SUMIF('2022年全年财务报表'!A:A,C:C,'2022年全年财务报表'!I:I) -> 0 | M22: =SUMIF(D:D,D:D,G:G)*SUMIF('2022年全年财务报表'!A:A,C:C,'2022年全年财务报表'!O:O) -> 0 | N22: =SUMIF(D:D,D:D,G:G)*SUMIF('2022年全年财务报表'!A:A,C:C,'2022年全年财务报表'!Q:Q) -> 0 | O22: =SUMIF(D:D,D:D,G:G)*SUMIF('2022年全年财务报表'!A:A,C:C,'2022年全年财务报表'!S:S) -> 0 | P22: =IFERROR(I22/W22*R22,0)/2.5 -> 0 | Q22: =IFERROR(P22/G22,0) -> 0 | R22: =IFERROR(SUMIF('2021&2022营销成本概况'!C:C,D:D,'2021&2022营销成本概况'!S:S)+SUMIF('2021&2022营销成本概况'!C:C,D:D,'2021&2022营销成本概况'!S:S)*'2021&2022营销成本概况'!$T$37,0)*年目标!$B$18 -> 0 | S22: =IFERROR(P22/I22,0) -> 0 | T22: =IFERROR(P22/H22,0) -> 0 | U22: =SUMIF(D:D,D:D,G:G)*SUMIF('2022年全年财务报表'!A:A,C:C,'2022年全年财务报表'!K:K)/1.2 -> 0 | V22: =IFERROR(U22/G22,0) -> 0 | W22: =IFERROR(SUMIF('船长每月数据(2023年)'!E:E,D:D,'船长每月数据(2023年)'!P:P)/SUMIF('船长每月数据(2023年)'!E:E,D:D,'船长每月数据(2023年)'!H:H),0) -> 0 | X22: =IFERROR(G22+J22+K22+L22+M22+N22+O22+P22+U22,0) -> 0 | Y22: =IFERROR(X22/G22,0) -> 0
G23: =SUMIF(每月目标分解!E:E,F:F,每月目标分解!R:R)*年目标!$B$18 -> 0 | H23: =IFERROR(SUMIF(F:F,每月目标分解!E:E,每月目标分解!R:R)/SUMIF(F:F,单品目标年销量!E:E,单品目标年销量!F:F),0) -> 0 | I23: =IFERROR(SUMIF(D:D,D:D,H:H)*(SUMIF('船长每月数据(2023年)'!E:E,D:D,'船长每月数据(2023年)'!AI:AI)/SUMIF('船长每月数据(2023年)'!E:E,D:D,'船长每月数据(2023年)'!P:P)),0) -> 0 | J23: =SUMIF(D:D,D:D,G:G)*SUMIF('2022年全年财务报表'!A:A,C:C,'2022年全年财务报表'!E:E) -> 0 | K23: =SUMIF(D:D,D:D,G:G)*SUMIF('2022年全年财务报表'!A:A,C:C,'2022年全年财务报表'!G:G) -> 0 | L23: =SUMIF(D:D,D:D,G:G)*SUMIF('2022年全年财务报表'!A:A,C:C,'2022年全年财务报表'!I:I) -> 0 | M23: =SUMIF(D:D,D:D,G:G)*SUMIF('2022年全年财务报表'!A:A,C:C,'2022年全年财务报表'!O:O) -> 0 | N23: =SUMIF(D:D,D:D,G:G)*SUMIF('2022年全年财务报表'!A:A,C:C,'2022年全年财务报表'!Q:Q) -> 0 | O23: =SUMIF(D:D,D:D,G:G)*SUMIF('2022年全年财务报表'!A:A,C:C,'2022年全年财务报表'!S:S) -> 0 | P23: =IFERROR(I23/W23*R23,0)/2.5 -> 0 | Q23: =IFERROR(P23/G23,0) -> 0 | R23: =IFERROR(SUMIF('2021&2022营销成本概况'!C:C,D:D,'2021&2022营销成本概况'!S:S)+SUMIF('2021&2022营销成本概况'!C:C,D:D,'2021&2022营销成本概况'!S:S)*'2021&2022营销成本概况'!$T$37,0)*年目标!$B$18 -> 0 | S23: =IFERROR(P23/I23,0) -> 0 | T23: =IFERROR(P23/H23,0) -> 0 | U23: =SUMIF(D:D,D:D,G:G)*SUMIF('2022年全年财务报表'!A:A,C:C,'2022年全年财务报表'!K:K)/1.2 -> 0 | V23: =IFERROR(U23/G23,0) -> 0 | W23: =IFERROR(SUMIF('船长每月数据(2023年)'!E:E,D:D,'船长每月数据(2023年)'!P:P)/SUMIF('船长每月数据(2023年)'!E:E,D:D,'船长每月数据(2023年)'!H:H),0) -> 0 | X23: =IFERROR(G23+J23+K23+L23+M23+N23+O23+P23+U23,0) -> 0 | Y23: =IFERROR(X23/G23,0) -> 0
G24: =SUMIF(每月目标分解!E:E,F:F,每月目标分解!R:R)*年目标!$B$18 -> 0 | H24: =IFERROR(SUMIF(F:F,每月目标分解!E:E,每月目标分解!R:R)/SUMIF(F:F,单品目标年销量!E:E,单品目标年销量!F:F),0) -> 0 | I24: =IFERROR(SUMIF(D:D,D:D,H:H)*(SUMIF('船长每月数据(2023年)'!E:E,D:D,'船长每月数据(2023年)'!AI:AI)/SUMIF('船长每月数据(2023年)'!E:E,D:D,'船长每月数据(2023年)'!P:P)),0) -> 0 | J24: =SUMIF(D:D,D:D,G:G)*SUMIF('2022年全年财务报表'!A:A,C:C,'2022年全年财务报表'!E:E) -> 0 | K24: =SUMIF(D:D,D:D,G:G)*SUMIF('2022年全年财务报表'!A:A,C:C,'2022年全年财务报表'!G:G) -> 0 | L24: =SUMIF(D:D,D:D,G:G)*SUMIF('2022年全年财务报表'!A:A,C:C,'2022年全年财务报表'!I:I) -> 0 | M24: =SUMIF(D:D,D:D,G:G)*SUMIF('2022年全年财务报表'!A:A,C:C,'2022年全年财务报表'!O:O) -> 0 | N24: =SUMIF(D:D,D:D,G:G)*SUMIF('2022年全年财务报表'!A:A,C:C,'2022年全年财务报表'!Q:Q) -> 0 | O24: =SUMIF(D:D,D:D,G:G)*SUMIF('2022年全年财务报表'!A:A,C:C,'2022年全年财务报表'!S:S) -> 0 | P24: =IFERROR(I24/W24*R24,0)/1.2 -> 0 | Q24: =IFERROR(P24/G24,0) -> 0 | R24: =IFERROR(SUMIF('2021&2022营销成本概况'!C:C,D:D,'2021&2022营销成本概况'!S:S)+SUMIF('2021&2022营销成本概况'!C:C,D:D,'2021&2022营销成本概况'!S:S)*'2021&2022营销成本概况'!$T$37,0)*年目标!$B$18 -> 0 | S24: =IFERROR(P24/I24,0) -> 0 | T24: =IFERROR(P24/H24,0) -> 0 | U24: =SUMIF(D:D,D:D,G:G)*SUMIF('2022年全年财务报表'!A:A,C:C,'2022年全年财务报表'!K:K) -> 0 | V24: =IFERROR(U24/G24,0) -> 0 | W24: =IFERROR(SUMIF('船长每月数据(2023年)'!E:E,D:D,'船长每月数据(2023年)'!P:P)/SUMIF('船长每月数据(2023年)'!E:E,D:D,'船长每月数据(2023年)'!H:H),0) -> 0 | X24: =IFERROR(G24+J24+K24+L24+M24+N24+O24+P24+U24,0) -> 0 | Y24: =IFERROR(X24/G24,0) -> 0
G25: =SUMIF(每月目标分解!E:E,F:F,每月目标分解!R:R)*年目标!$B$18 -> 0 | H25: =IFERROR(SUMIF(F:F,每月目标分解!E:E,每月目标分解!R:R)/SUMIF(F:F,单品目标年销量!E:E,单品目标年销量!F:F),0) -> 0 | I25: =IFERROR(SUMIF(D:D,D:D,H:H)*(SUMIF('船长每月数据(2023年)'!E:E,D:D,'船长每月数据(2023年)'!AI:AI)/SUMIF('船长每月数据(2023年)'!E:E,D:D,'船长每月数据(2023年)'!P:P)),0) -> 0 | J25: =SUMIF(D:D,D:D,G:G)*SUMIF('2022年全年财务报表'!A:A,C:C,'2022年全年财务报表'!E:E) -> 0 | K25: =SUMIF(D:D,D:D,G:G)*SUMIF('2022年全年财务报表'!A:A,C:C,'2022年全年财务报表'!G:G) -> 0 | L25: =SUMIF(D:D,D:D,G:G)*SUMIF('2022年全年财务报表'!A:A,C:C,'2022年全年财务报表'!I:I) -> 0 | M25: =SUMIF(D:D,D:D,G:G)*SUMIF('2022年全年财务报表'!A:A,C:C,'2022年全年财务报表'!O:O) -> 0 | N25: =SUMIF(D:D,D:D,G:G)*SUMIF('2022年全年财务报表'!A:A,C:C,'2022年全年财务报表'!Q:Q) -> 0 | O25: =SUMIF(D:D,D:D,G:G)*SUMIF('2022年全年财务报表'!A:A,C:C,'2022年全年财务报表'!S:S) -> 0 | P25: =IFERROR(I25/W25*R25,0) -> 0 | Q25: =IFERROR(P25/G25,0) -> 0 | R25: =IFERROR(SUMIF('2021&2022营销成本概况'!C:C,D:D,'2021&2022营销成本概况'!S:S)+SUMIF('2021&2022营销成本概况'!C:C,D:D,'2021&2022营销成本概况'!S:S)*'2021&2022营销成本概况'!$T$37,0)*年目标!$B$18 -> 0 | S25: =IFERROR(P25/I25,0) -> 0 | T25: =IFERROR(P25/H25,0) -> 0 | U25: =SUMIF(D:D,D:D,G:G)*SUMIF('2022年全年财务报表'!A:A,C:C,'2022年全年财务报表'!K:K) -> 0 | V25: =IFERROR(U25/G25,0) -> 0 | W25: =IFERROR(SUMIF('船长每月数据(2023年)'!E:E,D:D,'船长每月数据(2023年)'!P:P)/SUMIF('船长每月数据(2023年)'!E:E,D:D,'船长每月数据(2023年)'!H:H),0) -> 0 | X25: =IFERROR(G25+J25+K25+L25+M25+N25+O25+P25+U25,0) -> 0 | Y25: =IFERROR(X25/G25,0) -> 0
G26: =SUMIF(每月目标分解!E:E,F:F,每月目标分解!R:R)*年目标!$B$18 -> 0 | H26: =IFERROR(SUMIF(F:F,每月目标分解!E:E,每月目标分解!R:R)/SUMIF(F:F,单品目标年销量!E:E,单品目标年销量!F:F),0) -> 0 | I26: =IFERROR(SUMIF(D:D,D:D,H:H)*(SUMIF('船长每月数据(2023年)'!E:E,D:D,'船长每月数据(2023年)'!AI:AI)/SUMIF('船长每月数据(2023年)'!E:E,D:D,'船长每月数据(2023年)'!P:P)),0) -> 0 | J26: =SUMIF(D:D,D:D,G:G)*SUMIF('2022年全年财务报表'!A:A,C:C,'2022年全年财务报表'!E:E) -> 0 | K26: =SUMIF(D:D,D:D,G:G)*SUMIF('2022年全年财务报表'!A:A,C:C,'2022年全年财务报表'!G:G) -> 0 | L26: =SUMIF(D:D,D:D,G:G)*SUMIF('2022年全年财务报表'!A:A,C:C,'2022年全年财务报表'!I:I) -> 0 | M26: =SUMIF(D:D,D:D,G:G)*SUMIF('2022年全年财务报表'!A:A,C:C,'2022年全年财务报表'!O:O) -> 0 | N26: =SUMIF(D:D,D:D,G:G)*SUMIF('2022年全年财务报表'!A:A,C:C,'2022年全年财务报表'!Q:Q) -> 0 | O26: =SUMIF(D:D,D:D,G:G)*SUMIF('2022年全年财务报表'!A:A,C:C,'2022年全年财务报表'!S:S) -> 0 | P26: =IFERROR(I26/W26*R26,0) -> 0 | Q26: =IFERROR(P26/G26,0) -> 0 | R26: =IFERROR(SUMIF('2021&2022营销成本概况'!C:C,D:D,'2021&2022营销成本概况'!S:S)+SUMIF('2021&2022营销成本概况'!C:C,D:D,'2021&2022营销成本概况'!S:S)*'2021&2022营销成本概况'!$T$37,0)*年目标!$B$18 -> 0 | S26: =IFERROR(P26/I26,0) -> 0 | T26: =IFERROR(P26/H26,0) -> 0 | U26: =SUMIF(D:D,D:D,G:G)*SUMIF('2022年全年财务报表'!A:A,C:C,'2022年全年财务报表'!K:K) -> 0 | V26: =IFERROR(U26/G26,0) -> 0 | W26: =IFERROR(SUMIF('船长每月数据(2023年)'!E:E,D:D,'船长每月数据(2023年)'!P:P)/SUMIF('船长每月数据(2023年)'!E:E,D:D,'船长每月数据(2023年)'!H:H),0) -> 0 | X26: =IFERROR(G26+J26+K26+L26+M26+N26+O26+P26+U26,0) -> 0 | Y26: =IFERROR(X26/G26,0) -> 0
G27: =SUMIF(每月目标分解!E:E,F:F,每月目标分解!R:R)*年目标!$B$18 -> 0 | H27: =IFERROR(SUMIF(F:F,每月目标分解!E:E,每月目标分解!R:R)/SUMIF(F:F,单品目标年销量!E:E,单品目标年销量!F:F),0) -> 0 | I27: =IFERROR(SUMIF(D:D,D:D,H:H)*(SUMIF('船长每月数据(2023年)'!E:E,D:D,'船长每月数据(2023年)'!AI:AI)/SUMIF('船长每月数据(2023年)'!E:E,D:D,'船长每月数据(2023年)'!P:P)),0) -> 0 | J27: =SUMIF(D:D,D:D,G:G)*SUMIF('2022年全年财务报表'!A:A,C:C,'2022年全年财务报表'!E:E) -> 0 | K27: =SUMIF(D:D,D:D,G:G)*SUMIF('2022年全年财务报表'!A:A,C:C,'2022年全年财务报表'!G:G) -> 0 | L27: =SUMIF(D:D,D:D,G:G)*SUMIF('2022年全年财务报表'!A:A,C:C,'2022年全年财务报表'!I:I) -> 0 | M27: =SUMIF(D:D,D:D,G:G)*SUMIF('2022年全年财务报表'!A:A,C:C,'2022年全年财务报表'!O:O) -> 0 | N27: =SUMIF(D:D,D:D,G:G)*SUMIF('2022年全年财务报表'!A:A,C:C,'2022年全年财务报表'!Q:Q) -> 0 | O27: =SUMIF(D:D,D:D,G:G)*SUMIF('2022年全年财务报表'!A:A,C:C,'2022年全年财务报表'!S:S) -> 0 | P27: =IFERROR(I27/W27*R27,0)/3.5 -> 0 | Q27: =IFERROR(P27/G27,0) -> 0 | R27: =IFERROR(SUMIF('2021&2022营销成本概况'!C:C,D:D,'2021&2022营销成本概况'!S:S)+SUMIF('2021&2022营销成本概况'!C:C,D:D,'2021&2022营销成本概况'!S:S)*'2021&2022营销成本概况'!$T$37,0)*年目标!$B$18 -> 0 | S27: =IFERROR(P27/I27,0) -> 0 | T27: =IFERROR(P27/H27,0) -> 0 | U27: =SUMIF(D:D,D:D,G:G)*SUMIF('2022年全年财务报表'!A:A,C:C,'2022年全年财务报表'!K:K)/4 -> 0 | V27: =IFERROR(U27/G27,0) -> 0 | W27: =IFERROR(SUMIF('船长每月数据(2023年)'!E:E,D:D,'船长每月数据(2023年)'!P:P)/SUMIF('船长每月数据(2023年)'!E:E,D:D,'船长每月数据(2023年)'!H:H),0) -> 0 | X27: =IFERROR(G27+J27+K27+L27+M27+N27+O27+P27+U27,0) -> 0 | Y27: =IFERROR(X27/G27,0) -> 0
G28: =SUMIF(每月目标分解!E:E,F:F,每月目标分解!R:R)*年目标!$B$18 -> 0 | H28: =IFERROR(SUMIF(F:F,每月目标分解!E:E,每月目标分解!R:R)/SUMIF(F:F,单品目标年销量!E:E,单品目标年销量!F:F),0) -> 0 | I28: =IFERROR(SUMIF(D:D,D:D,H:H)*(SUMIF('船长每月数据(2023年)'!E:E,D:D,'船长每月数据(2023年)'!AI:AI)/SUMIF('船长每月数据(2023年)'!E:E,D:D,'船长每月数据(2023年)'!P:P)),0) -> 0 | J28: =SUMIF(D:D,D:D,G:G)*SUMIF('2022年全年财务报表'!A:A,C:C,'2022年全年财务报表'!E:E) -> 0 | K28: =SUMIF(D:D,D:D,G:G)*SUMIF('2022年全年财务报表'!A:A,C:C,'2022年全年财务报表'!G:G) -> 0 | L28: =SUMIF(D:D,D:D,G:G)*SUMIF('2022年全年财务报表'!A:A,C:C,'2022年全年财务报表'!I:I) -> 0 | M28: =SUMIF(D:D,D:D,G:G)*SUMIF('2022年全年财务报表'!A:A,C:C,'2022年全年财务报表'!O:O) -> 0 | N28: =SUMIF(D:D,D:D,G:G)*SUMIF('2022年全年财务报表'!A:A,C:C,'2022年全年财务报表'!Q:Q) -> 0 | O28: =SUMIF(D:D,D:D,G:G)*SUMIF('2022年全年财务报表'!A:A,C:C,'2022年全年财务报表'!S:S) -> 0 | P28: =IFERROR(I28/W28*R28,0)/3 -> 0 | Q28: =IFERROR(P28/G28,0) -> 0 | R28: =IFERROR(SUMIF('2021&2022营销成本概况'!C:C,D:D,'2021&2022营销成本概况'!S:S)+SUMIF('2021&2022营销成本概况'!C:C,D:D,'2021&2022营销成本概况'!S:S)*'2021&2022营销成本概况'!$T$37,0)*年目标!$B$18 -> 0 | S28: =IFERROR(P28/I28,0) -> 0 | T28: =IFERROR(P28/H28,0) -> 0 | U28: =SUMIF(D:D,D:D,G:G)*SUMIF('2022年全年财务报表'!A:A,C:C,'2022年全年财务报表'!K:K)/3 -> 0 | V28: =IFERROR(U28/G28,0) -> 0 | W28: =IFERROR(SUMIF('船长每月数据(2023年)'!E:E,D:D,'船长每月数据(2023年)'!P:P)/SUMIF('船长每月数据(2023年)'!E:E,D:D,'船长每月数据(2023年)'!H:H),0) -> 0 | X28: =IFERROR(G28+J28+K28+L28+M28+N28+O28+P28+U28,0) -> 0 | Y28: =IFERROR(X28/G28,0) -> 0
G29: =SUMIF(每月目标分解!E:E,F:F,每月目标分解!R:R)*年目标!$B$18 -> 0 | H29: =IFERROR(SUMIF(F:F,每月目标分解!E:E,每月目标分解!R:R)/SUMIF(F:F,单品目标年销量!E:E,单品目标年销量!F:F),0) -> 0 | I29: =IFERROR(SUMIF(D:D,D:D,H:H)*(SUMIF('船长每月数据(2023年)'!E:E,D:D,'船长每月数据(2023年)'!AI:AI)/SUMIF('船长每月数据(2023年)'!E:E,D:D,'船长每月数据(2023年)'!P:P)),0) -> 0 | J29: =SUMIF(D:D,D:D,G:G)*SUMIF('2022年全年财务报表'!A:A,C:C,'2022年全年财务报表'!E:E) -> 0 | K29: =SUMIF(D:D,D:D,G:G)*SUMIF('2022年全年财务报表'!A:A,C:C,'2022年全年财务报表'!G:G) -> 0 | L29: =SUMIF(D:D,D:D,G:G)*SUMIF('2022年全年财务报表'!A:A,C:C,'2022年全年财务报表'!I:I) -> 0 | M29: =SUMIF(D:D,D:D,G:G)*SUMIF('2022年全年财务报表'!A:A,C:C,'2022年全年财务报表'!O:O) -> 0 | N29: =SUMIF(D:D,D:D,G:G)*SUMIF('2022年全年财务报表'!A:A,C:C,'2022年全年财务报表'!Q:Q) -> 0 | O29: =SUMIF(D:D,D:D,G:G)*SUMIF('2022年全年财务报表'!A:A,C:C,'2022年全年财务报表'!S:S) -> 0 | P29: =IFERROR(I29/W29*R29,0)/2 -> 0 | Q29: =IFERROR(P29/G29,0) -> 0 | R29: =IFERROR(SUMIF('2021&2022营销成本概况'!C:C,D:D,'2021&2022营销成本概况'!S:S)+SUMIF('2021&2022营销成本概况'!C:C,D:D,'2021&2022营销成本概况'!S:S)*'2021&2022营销成本概况'!$T$37,0)*年目标!$B$18 -> 0 | S29: =IFERROR(P29/I29,0) -> 0 | T29: =IFERROR(P29/H29,0) -> 0 | U29: =SUMIF(D:D,D:D,G:G)*SUMIF('2022年全年财务报表'!A:A,C:C,'2022年全年财务报表'!K:K)/2 -> 0 | V29: =IFERROR(U29/G29,0) -> 0 | W29: =IFERROR(SUMIF('船长每月数据(2023年)'!E:E,D:D,'船长每月数据(2023年)'!P:P)/SUMIF('船长每月数据(2023年)'!E:E,D:D,'船长每月数据(2023年)'!H:H),0) -> 0 | X29: =IFERROR(G29+J29+K29+L29+M29+N29+O29+P29+U29,0) -> 0 | Y29: =IFERROR(X29/G29,0) -> 0
G30: =SUMIF(每月目标分解!E:E,F:F,每月目标分解!R:R)*年目标!$B$18 -> 0 | H30: =IFERROR(SUMIF(F:F,每月目标分解!E:E,每月目标分解!R:R)/SUMIF(F:F,单品目标年销量!E:E,单品目标年销量!F:F),0) -> 0 | I30: =IFERROR(SUMIF(D:D,D:D,H:H)*(SUMIF('船长每月数据(2023年)'!E:E,D:D,'船长每月数据(2023年)'!AI:AI)/SUMIF('船长每月数据(2023年)'!E:E,D:D,'船长每月数据(2023年)'!P:P)),0) -> 0 | J30: =SUMIF(D:D,D:D,G:G)*SUMIF('2022年全年财务报表'!A:A,C:C,'2022年全年财务报表'!E:E) -> 0 | K30: =SUMIF(D:D,D:D,G:G)*SUMIF('2022年全年财务报表'!A:A,C:C,'2022年全年财务报表'!G:G) -> 0 | L30: =SUMIF(D:D,D:D,G:G)*SUMIF('2022年全年财务报表'!A:A,C:C,'2022年全年财务报表'!I:I) -> 0 | M30: =SUMIF(D:D,D:D,G:G)*SUMIF('2022年全年财务报表'!A:A,C:C,'2022年全年财务报表'!O:O) -> 0 | N30: =SUMIF(D:D,D:D,G:G)*SUMIF('2022年全年财务报表'!A:A,C:C,'2022年全年财务报表'!Q:Q) -> 0 | O30: =SUMIF(D:D,D:D,G:G)*SUMIF('2022年全年财务报表'!A:A,C:C,'2022年全年财务报表'!S:S) -> 0 | P30: =IFERROR(I30/W30*R30,0)/5 -> 0 | Q30: =IFERROR(P30/G30,0) -> 0 | R30: =IFERROR(SUMIF('2021&2022营销成本概况'!C:C,D:D,'2021&2022营销成本概况'!S:S)+SUMIF('2021&2022营销成本概况'!C:C,D:D,'2021&2022营销成本概况'!S:S)*'2021&2022营销成本概况'!$T$37,0)*年目标!$B$18 -> 0 | S30: =IFERROR(P30/I30,0) -> 0 | T30: =IFERROR(P30/H30,0) -> 0 | U30: =SUMIF(D:D,D:D,G:G)*SUMIF('2022年全年财务报表'!A:A,C:C,'2022年全年财务报表'!K:K) -> 0 | V30: =IFERROR(U30/G30,0) -> 0 | W30: =IFERROR(SUMIF('船长每月数据(2023年)'!E:E,D:D,'船长每月数据(2023年)'!P:P)/SUMIF('船长每月数据(2023年)'!E:E,D:D,'船长每月数据(2023年)'!H:H),0) -> 0 | X30: =IFERROR(G30+J30+K30+L30+M30+N30+O30+P30+U30,0) -> 0 | Y30: =IFERROR(X30/G30,0) -> 0
G31: =SUMIF(每月目标分解!E:E,F:F,每月目标分解!R:R)*年目标!$B$18 -> 0 | H31: =IFERROR(SUMIF(F:F,每月目标分解!E:E,每月目标分解!R:R)/SUMIF(F:F,单品目标年销量!E:E,单品目标年销量!F:F),0) -> 0 | I31: =IFERROR(SUMIF(D:D,D:D,H:H)*(SUMIF('船长每月数据(2023年)'!E:E,D:D,'船长每月数据(2023年)'!AI:AI)/SUMIF('船长每月数据(2023年)'!E:E,D:D,'船长每月数据(2023年)'!P:P)),0) -> 0 | J31: =SUMIF(D:D,D:D,G:G)*SUMIF('2022年全年财务报表'!A:A,C:C,'2022年全年财务报表'!E:E) -> 0 | K31: =SUMIF(D:D,D:D,G:G)*SUMIF('2022年全年财务报表'!A:A,C:C,'2022年全年财务报表'!G:G) -> 0 | L31: =SUMIF(D:D,D:D,G:G)*SUMIF('2022年全年财务报表'!A:A,C:C,'2022年全年财务报表'!I:I) -> 0 | M31: =SUMIF(D:D,D:D,G:G)*SUMIF('2022年全年财务报表'!A:A,C:C,'2022年全年财务报表'!O:O)/3 -> 0 | N31: =SUMIF(D:D,D:D,G:G)*SUMIF('2022年全年财务报表'!A:A,C:C,'2022年全年财务报表'!Q:Q) -> 0 | O31: =SUMIF(D:D,D:D,G:G)*SUMIF('2022年全年财务报表'!A:A,C:C,'2022年全年财务报表'!S:S) -> 0 | P31: =IFERROR(I31/W31*R31,0)/2 -> 0 | Q31: =IFERROR(P31/G31,0) -> 0 | R31: =IFERROR(SUMIF('2021&2022营销成本概况'!C:C,D:D,'2021&2022营销成本概况'!S:S)+SUMIF('2021&2022营销成本概况'!C:C,D:D,'2021&2022营销成本概况'!S:S)*'2021&2022营销成本概况'!$T$37,0)*年目标!$B$18 -> 0 | S31: =IFERROR(P31/I31,0) -> 0 | T31: =IFERROR(P31/H31,0) -> 0 | U31: =SUMIF(D:D,D:D,G:G)*SUMIF('2022年全年财务报表'!A:A,C:C,'2022年全年财务报表'!K:K) -> 0 | V31: =IFERROR(U31/G31,0) -> 0 | W31: =IFERROR(SUMIF('船长每月数据(2023年)'!E:E,D:D,'船长每月数据(2023年)'!P:P)/SUMIF('船长每月数据(2023年)'!E:E,D:D,'船长每月数据(2023年)'!H:H),0) -> 0 | X31: =IFERROR(G31+J31+K31+L31+M31+N31+O31+P31+U31,0) -> 0 | Y31: =IFERROR(X31/G31,0) -> 0
G32: =SUMIF(每月目标分解!E:E,F:F,每月目标分解!R:R)*年目标!$B$18 -> 0 | H32: =IFERROR(SUMIF(F:F,每月目标分解!E:E,每月目标分解!R:R)/SUMIF(F:F,单品目标年销量!E:E,单品目标年销量!F:F),0) -> 0 | I32: =IFERROR(SUMIF(D:D,D:D,H:H)*(SUMIF('船长每月数据(2023年)'!E:E,D:D,'船长每月数据(2023年)'!AI:AI)/SUMIF('船长每月数据(2023年)'!E:E,D:D,'船长每月数据(2023年)'!P:P)),0) -> 0 | J32: =SUMIF(D:D,D:D,G:G)*SUMIF('2022年全年财务报表'!A:A,C:C,'2022年全年财务报表'!E:E) -> 0 | K32: =SUMIF(D:D,D:D,G:G)*SUMIF('2022年全年财务报表'!A:A,C:C,'2022年全年财务报表'!G:G) -> 0 | L32: =SUMIF(D:D,D:D,G:G)*SUMIF('2022年全年财务报表'!A:A,C:C,'2022年全年财务报表'!I:I) -> 0 | M32: =SUMIF(D:D,D:D,G:G)*SUMIF('2022年全年财务报表'!A:A,C:C,'2022年全年财务报表'!O:O) -> 0 | N32: =SUMIF(D:D,D:D,G:G)*SUMIF('2022年全年财务报表'!A:A,C:C,'2022年全年财务报表'!Q:Q) -> 0 | O32: =SUMIF(D:D,D:D,G:G)*SUMIF('2022年全年财务报表'!A:A,C:C,'2022年全年财务报表'!S:S) -> 0 | P32: =IFERROR(I32/W32*R32,0)/3 -> 0 | Q32: =IFERROR(P32/G32,0) -> 0 | R32: =IFERROR(SUMIF('2021&2022营销成本概况'!C:C,D:D,'2021&2022营销成本概况'!S:S)+SUMIF('2021&2022营销成本概况'!C:C,D:D,'2021&2022营销成本概况'!S:S)*'2021&2022营销成本概况'!$T$37,0)*年目标!$B$18 -> 0 | S32: =IFERROR(P32/I32,0) -> 0 | T32: =IFERROR(P32/H32,0) -> 0 | U32: =SUMIF(D:D,D:D,G:G)*SUMIF('2022年全年财务报表'!A:A,C:C,'2022年全年财务报表'!K:K) -> 0 | V32: =IFERROR(U32/G32,0) -> 0 | W32: =IFERROR(SUMIF('船长每月数据(2023年)'!E:E,D:D,'船长每月数据(2023年)'!P:P)/SUMIF('船长每月数据(2023年)'!E:E,D:D,'船长每月数据(2023年)'!H:H),0) -> 0 | X32: =IFERROR(G32+J32+K32+L32+M32+N32+O32+P32+U32,0) -> 0 | Y32: =IFERROR(X32/G32,0) -> 0
G33: =SUMIF(每月目标分解!E:E,F:F,每月目标分解!R:R)*年目标!$B$18 -> 0 | H33: =IFERROR(SUMIF(F:F,每月目标分解!E:E,每月目标分解!R:R)/SUMIF(F:F,单品目标年销量!E:E,单品目标年销量!F:F),0) -> 0 | I33: =IFERROR(SUMIF(D:D,D:D,H:H)*(SUMIF('船长每月数据(2023年)'!E:E,D:D,'船长每月数据(2023年)'!AI:AI)/SUMIF('船长每月数据(2023年)'!E:E,D:D,'船长每月数据(2023年)'!P:P)),0) -> 0 | J33: =SUMIF(D:D,D:D,G:G)*SUMIF('2022年全年财务报表'!A:A,C:C,'2022年全年财务报表'!E:E) -> 0 | K33: =SUMIF(D:D,D:D,G:G)*SUMIF('2022年全年财务报表'!A:A,C:C,'2022年全年财务报表'!G:G) -> 0 | L33: =SUMIF(D:D,D:D,G:G)*SUMIF('2022年全年财务报表'!A:A,C:C,'2022年全年财务报表'!I:I) -> 0 | M33: =SUMIF(D:D,D:D,G:G)*SUMIF('2022年全年财务报表'!A:A,C:C,'2022年全年财务报表'!O:O) -> 0 | N33: =SUMIF(D:D,D:D,G:G)*SUMIF('2022年全年财务报表'!A:A,C:C,'2022年全年财务报表'!Q:Q) -> 0 | O33: =SUMIF(D:D,D:D,G:G)*SUMIF('2022年全年财务报表'!A:A,C:C,'2022年全年财务报表'!S:S) -> 0 | P33: =IFERROR(I33/W33*R33,0)/4 -> 0 | Q33: =IFERROR(P33/G33,0) -> 0 | R33: =IFERROR(SUMIF('2021&2022营销成本概况'!C:C,D:D,'2021&2022营销成本概况'!S:S)+SUMIF('2021&2022营销成本概况'!C:C,D:D,'2021&2022营销成本概况'!S:S)*'2021&2022营销成本概况'!$T$37,0)*年目标!$B$18 -> 0 | S33: =IFERROR(P33/I33,0) -> 0 | T33: =IFERROR(P33/H33,0) -> 0 | U33: =SUMIF(D:D,D:D,G:G)*SUMIF('2022年全年财务报表'!A:A,C:C,'2022年全年财务报表'!K:K) -> 0 | V33: =IFERROR(U33/G33,0) -> 0 | W33: =IFERROR(SUMIF('船长每月数据(2023年)'!E:E,D:D,'船长每月数据(2023年)'!P:P)/SUMIF('船长每月数据(2023年)'!E:E,D:D,'船长每月数据(2023年)'!H:H),0) -> 0 | X33: =IFERROR(G33+J33+K33+L33+M33+N33+O33+P33+U33,0) -> 0 | Y33: =IFERROR(X33/G33,0) -> 0
G34: =SUMIF(每月目标分解!E:E,F:F,每月目标分解!R:R)*年目标!$B$18 -> 0 | H34: =IFERROR(SUMIF(F:F,每月目标分解!E:E,每月目标分解!R:R)/SUMIF(F:F,单品目标年销量!E:E,单品目标年销量!F:F),0) -> 0 | I34: =IFERROR(SUMIF(D:D,D:D,H:H)*(SUMIF('船长每月数据(2023年)'!E:E,D:D,'船长每月数据(2023年)'!AI:AI)/SUMIF('船长每月数据(2023年)'!E:E,D:D,'船长每月数据(2023年)'!P:P)),0) -> 0 | J34: =SUMIF(D:D,D:D,G:G)*SUMIF('2022年全年财务报表'!A:A,C:C,'2022年全年财务报表'!E:E) -> 0 | K34: =SUMIF(D:D,D:D,G:G)*SUMIF('2022年全年财务报表'!A:A,C:C,'2022年全年财务报表'!G:G) -> 0 | L34: =SUMIF(D:D,D:D,G:G)*SUMIF('2022年全年财务报表'!A:A,C:C,'2022年全年财务报表'!I:I) -> 0 | M34: =SUMIF(D:D,D:D,G:G)*SUMIF('2022年全年财务报表'!A:A,C:C,'2022年全年财务报表'!O:O) -> 0 | N34: =SUMIF(D:D,D:D,G:G)*SUMIF('2022年全年财务报表'!A:A,C:C,'2022年全年财务报表'!Q:Q) -> 0 | O34: =SUMIF(D:D,D:D,G:G)*SUMIF('2022年全年财务报表'!A:A,C:C,'2022年全年财务报表'!S:S) -> 0 | P34: =IFERROR(I34/W34*R34,0)/3 -> 0 | Q34: =IFERROR(P34/G34,0) -> 0 | R34: =IFERROR(SUMIF('2021&2022营销成本概况'!C:C,D:D,'2021&2022营销成本概况'!S:S)+SUMIF('2021&2022营销成本概况'!C:C,D:D,'2021&2022营销成本概况'!S:S)*'2021&2022营销成本概况'!$T$37,0)*年目标!$B$18 -> 0 | S34: =IFERROR(P34/I34,0) -> 0 | T34: =IFERROR(P34/H34,0) -> 0 | U34: =SUMIF(D:D,D:D,G:G)*SUMIF('2022年全年财务报表'!A:A,C:C,'2022年全年财务报表'!K:K) -> 0 | V34: =IFERROR(U34/G34,0) -> 0 | W34: =IFERROR(SUMIF('船长每月数据(2023年)'!E:E,D:D,'船长每月数据(2023年)'!P:P)/SUMIF('船长每月数据(2023年)'!E:E,D:D,'船长每月数据(2023年)'!H:H),0) -> 0 | X34: =IFERROR(G34+J34+K34+L34+M34+N34+O34+P34+U34,0) -> 0 | Y34: =IFERROR(X34/G34,0) -> 0
G35: =SUMIF(每月目标分解!E:E,F:F,每月目标分解!R:R)*年目标!$B$18 -> 0 | H35: =IFERROR(SUMIF(F:F,每月目标分解!E:E,每月目标分解!R:R)/SUMIF(F:F,单品目标年销量!E:E,单品目标年销量!F:F),0) -> 0 | I35: =IFERROR(SUMIF(D:D,D:D,H:H)*(SUMIF('船长每月数据(2023年)'!E:E,D:D,'船长每月数据(2023年)'!AI:AI)/SUMIF('船长每月数据(2023年)'!E:E,D:D,'船长每月数据(2023年)'!P:P)),0) -> 0 | J35: =SUMIF(D:D,D:D,G:G)*SUMIF('2022年全年财务报表'!A:A,C:C,'2022年全年财务报表'!E:E)/1.2 -> 0 | K35: =SUMIF(D:D,D:D,G:G)*SUMIF('2022年全年财务报表'!A:A,C:C,'2022年全年财务报表'!G:G) -> 0 | L35: =SUMIF(D:D,D:D,G:G)*SUMIF('2022年全年财务报表'!A:A,C:C,'2022年全年财务报表'!I:I) -> 0 | M35: =SUMIF(D:D,D:D,G:G)*SUMIF('2022年全年财务报表'!A:A,C:C,'2022年全年财务报表'!O:O)/2 -> 0 | N35: =SUMIF(D:D,D:D,G:G)*SUMIF('2022年全年财务报表'!A:A,C:C,'2022年全年财务报表'!Q:Q) -> 0 | O35: =SUMIF(D:D,D:D,G:G)*SUMIF('2022年全年财务报表'!A:A,C:C,'2022年全年财务报表'!S:S) -> 0 | P35: =IFERROR(I35/W35*R35,0)/5 -> 0 | Q35: =IFERROR(P35/G35,0) -> 0 | R35: =IFERROR(SUMIF('2021&2022营销成本概况'!C:C,D:D,'2021&2022营销成本概况'!S:S)+SUMIF('2021&2022营销成本概况'!C:C,D:D,'2021&2022营销成本概况'!S:S)*'2021&2022营销成本概况'!$T$37,0)*年目标!$B$18 -> 0 | S35: =IFERROR(P35/I35,0) -> 0 | T35: =IFERROR(P35/H35,0) -> 0 | U35: =SUMIF(D:D,D:D,G:G)*SUMIF('2022年全年财务报表'!A:A,C:C,'2022年全年财务报表'!K:K)/5 -> 0 | V35: =IFERROR(U35/G35,0) -> 0 | W35: =IFERROR(SUMIF('船长每月数据(2023年)'!E:E,D:D,'船长每月数据(2023年)'!P:P)/SUMIF('船长每月数据(2023年)'!E:E,D:D,'船长每月数据(2023年)'!H:H),0) -> 0 | X35: =IFERROR(G35+J35+K35+L35+M35+N35+O35+P35+U35,0) -> 0 | Y35: =IFERROR(X35/G35,0) -> 0
G36: =SUMIF(每月目标分解!E:E,F:F,每月目标分解!R:R)*年目标!$B$18 -> 0 | H36: =IFERROR(SUMIF(F:F,每月目标分解!E:E,每月目标分解!R:R)/SUMIF(F:F,单品目标年销量!E:E,单品目标年销量!F:F),0) -> 0 | I36: =IFERROR(SUMIF(D:D,D:D,H:H)*(SUMIF('船长每月数据(2023年)'!E:E,D:D,'船长每月数据(2023年)'!AI:AI)/SUMIF('船长每月数据(2023年)'!E:E,D:D,'船长每月数据(2023年)'!P:P)),0) -> 0 | J36: =SUMIF(D:D,D:D,G:G)*SUMIF('2022年全年财务报表'!A:A,C:C,'2022年全年财务报表'!E:E) -> 0 | K36: =SUMIF(D:D,D:D,G:G)*SUMIF('2022年全年财务报表'!A:A,C:C,'2022年全年财务报表'!G:G) -> 0 | L36: =SUMIF(D:D,D:D,G:G)*SUMIF('2022年全年财务报表'!A:A,C:C,'2022年全年财务报表'!I:I) -> 0 | M36: =SUMIF(D:D,D:D,G:G)*SUMIF('2022年全年财务报表'!A:A,C:C,'2022年全年财务报表'!O:O)/2 -> 0 | N36: =SUMIF(D:D,D:D,G:G)*SUMIF('2022年全年财务报表'!A:A,C:C,'2022年全年财务报表'!Q:Q) -> 0 | O36: =SUMIF(D:D,D:D,G:G)*SUMIF('2022年全年财务报表'!A:A,C:C,'2022年全年财务报表'!S:S) -> 0 | P36: =IFERROR(I36/W36*R36,0)/8 -> 0 | Q36: =IFERROR(P36/G36,0) -> 0 | R36: =IFERROR(SUMIF('2021&2022营销成本概况'!C:C,D:D,'2021&2022营销成本概况'!S:S)+SUMIF('2021&2022营销成本概况'!C:C,D:D,'2021&2022营销成本概况'!S:S)*'2021&2022营销成本概况'!$T$37,0)*年目标!$B$18 -> 0 | S36: =IFERROR(P36/I36,0) -> 0 | T36: =IFERROR(P36/H36,0) -> 0 | U36: =SUMIF(D:D,D:D,G:G)*SUMIF('2022年全年财务报表'!A:A,C:C,'2022年全年财务报表'!K:K)/5 -> 0 | V36: =IFERROR(U36/G36,0) -> 0 | W36: =IFERROR(SUMIF('船长每月数据(2023年)'!E:E,D:D,'船长每月数据(2023年)'!P:P)/SUMIF('船长每月数据(2023年)'!E:E,D:D,'船长每月数据(2023年)'!H:H),0) -> 0 | X36: =IFERROR(G36+J36+K36+L36+M36+N36+O36+P36+U36,0) -> 0 | Y36: =IFERROR(X36/G36,0) -> 0
A37: 总计 | G37: =SUM(G3:G36) -> 0 | H37: =SUM(H3:H36) -> 0 | I37: =SUM(I3:I36) -> 0 | J37: =SUM(J3:J36) -> 0 | K37: =SUM(K3:K36) -> 0 | L37: =SUM(L3:L36) -> 0 | M37: =SUM(M3:M36) -> 0 | N37: =SUM(N3:N36) -> 0 | ... P37: =SUM(P3:P36) -> 0 | Q37: =IFERROR(P37/G37,0) -> 0 | R37: =IFERROR(SUMIF('2021&2022营销成本概况'!C:C,D:D,'2021&2022营销成本概况'!S:S)+SUMIF('2021&2022营销成本概况'!C:C,D:D,'2021&2022营销成本概况'!S:S)*'2021&2022营销成本概况'!$T$37,0) -> 0 | S37: =IFERROR(P37/I37,0) -> 0 | T37: =IFERROR(P37/H37,0) -> 0 | U37: =SUM(U3:U36) -> 0 | V37: =IFERROR(U37/G37,0) -> 0 | W37: =AVERAGE(W3:W36) -> #DIV/0! | X37: =SUM(X3:X36) -> 0 | Y37: =IFERROR(X37/G37,0) -> 0

Sheet 市场概况
A1: 本品牌市场概况(2021-2022)
A2: 年份 | B2: 品类 | C2: 市场容量 | D2: 市场容量同比 | E2: xxx销量 | F2: xxx市占率 | G2: 市占率同比 | H2: 市场份额 | I2: 市场份额同比 | J2: xxx销售额 | K2: xxx市场份额占比 | L2: 市场份额同比
A3: 2021年 | C3: =SUM(C9:C20) -> 0 | D3: / | E3: =SUM(C36:C47) -> 0 | F3: =IFERROR(E3/C3,0) -> 0 | G3: / | H3: =SUM(F8:F20) -> 0 | I3: / | J3: =SUM(G36:G47) -> 0 | K3: =IFERROR(J3/H3,0) -> 0 | L3: /
A4: 2022年 | C4: =SUM(C21:C32) -> 0 | D4: =IFERROR((C4-C3)/C3,0) -> 0 | E4: =SUM(C48:C59) -> 0 | F4: =IFERROR(E4/C4,0) -> 0 | G4: =IFERROR((F4-F3)/F3,0) -> 0 | H4: =SUM(F21:F32) -> 0 | I4: =IFERROR((H4-H3)/H3,0) -> 0 | J4: =SUM(G48:G59) -> 0 | K4: =IFERROR(J4/H4,0) -> 0 | L4: =IFERROR((K4-K3)/K3,0) -> 0
A6: 每月市场趋势变化(2021-2022)
A7: 年份 | B7: 月份 | C7: 市场容量 | D7: 环比 | E7: 同比 | F7: 市场份额 | G7: 环比 | H7: 同比 | I7: 平均客单价 | J7: 环比 | K7: 同比
A8: 2020 | B8: 12 | C8: =每月市场趋势!B26+每月市场趋势!G26+每月市场趋势!L26+每月市场趋势!Q26 -> 0 | D8: / | E8: / | F8: =每月市场趋势!C26+每月市场趋势!H26+每月市场趋势!M26+每月市场趋势!R26 -> 0 | G8: / | H8: / | I8: =IFERROR(F8/C8,0) -> 0 | J8: / | K8: /
A9: 2021 | B9: 1 | C9: =每月市场趋势!B27+每月市场趋势!G27+每月市场趋势!L27+每月市场趋势!Q27 -> 0 | D9: =IFERROR((C9-C8)/C8,0) -> 0 | E9: / | F9: =每月市场趋势!C27+每月市场趋势!H27+每月市场趋势!M27+每月市场趋势!R27 -> 0 | G9: =IFERROR((F9-F8)/F8,0) -> 0 | H9: / | I9: =IFERROR(F9/C9,0) -> 0 | J9: =IFERROR((I9-I8)/I8,0) -> 0 | K9: /
A10: 2021 | B10: 2 | C10: =每月市场趋势!B28+每月市场趋势!G28+每月市场趋势!L28+每月市场趋势!Q28 -> 0 | D10: =IFERROR((C10-C9)/C9,0) -> 0 | E10: / | F10: =每月市场趋势!C28+每月市场趋势!H28+每月市场趋势!M28+每月市场趋势!R28 -> 0 | G10: =IFERROR((F10-F9)/F9,0) -> 0 | H10: / | I10: =IFERROR(F10/C10,0) -> 0 | J10: =IFERROR((I10-I9)/I9,0) -> 0 | K10: /
A11: 2021 | B11: 3 | C11: =每月市场趋势!B29+每月市场趋势!G29+每月市场趋势!L29+每月市场趋势!Q29 -> 0 | D11: =IFERROR((C11-C10)/C10,0) -> 0 | E11: / | F11: =每月市场趋势!C29+每月市场趋势!H29+每月市场趋势!M29+每月市场趋势!R29 -> 0 | G11: =IFERROR((F11-F10)/F10,0) -> 0 | H11: / | I11: =IFERROR(F11/C11,0) -> 0 | J11: =IFERROR((I11-I10)/I10,0) -> 0 | K11: /
A12: 2021 | B12: 4 | C12: =每月市场趋势!B30+每月市场趋势!G30+每月市场趋势!L30+每月市场趋势!Q30 -> 0 | D12: =IFERROR((C12-C11)/C11,0) -> 0 | E12: / | F12: =每月市场趋势!C30+每月市场趋势!H30+每月市场趋势!M30+每月市场趋势!R30 -> 0 | G12: =IFERROR((F12-F11)/F11,0) -> 0 | H12: / | I12: =IFERROR(F12/C12,0) -> 0 | J12: =IFERROR((I12-I11)/I11,0) -> 0 | K12: /
A13: 2021 | B13: 5 | C13: =每月市场趋势!B31+每月市场趋势!G31+每月市场趋势!L31+每月市场趋势!Q31 -> 0 | D13: =IFERROR((C13-C12)/C12,0) -> 0 | E13: / | F13: =每月市场趋势!C31+每月市场趋势!H31+每月市场趋势!M31+每月市场趋势!R31 -> 0 | G13: =IFERROR((F13-F12)/F12,0) -> 0 | H13: / | I13: =IFERROR(F13/C13,0) -> 0 | J13: =IFERROR((I13-I12)/I12,0) -> 0 | K13: /
A14: 2021 | B14: 6 | C14: =每月市场趋势!B32+每月市场趋势!G32+每月市场趋势!L32+每月市场趋势!Q32 -> 0 | D14: =IFERROR((C14-C13)/C13,0) -> 0 | E14: / | F14: =每月市场趋势!C32+每月市场趋势!H32+每月市场趋势!M32+每月市场趋势!R32 -> 0 | G14: =IFERROR((F14-F13)/F13,0) -> 0 | H14: / | I14: =IFERROR(F14/C14,0) -> 0 | J14: =IFERROR((I14-I13)/I13,0) -> 0 | K14: /
A15: 2021 | B15: 7 | C15: =每月市场趋势!B33+每月市场趋势!G33+每月市场趋势!L33+每月市场趋势!Q33 -> 0 | D15: =IFERROR((C15-C14)/C14,0) -> 0 | E15: / | F15: =每月市场趋势!C33+每月市场趋势!H33+每月市场趋势!M33+每月市场趋势!R33 -> 0 | G15: =IFERROR((F15-F14)/F14,0) -> 0 | H15: / | I15: =IFERROR(F15/C15,0) -> 0 | J15: =IFERROR((I15-I14)/I14,0) -> 0 | K15: /
A16: 2021 | B16: 8 | C16: =每月市场趋势!B34+每月市场趋势!G34+每月市场趋势!L34+每月市场趋势!Q34 -> 0 | D16: =IFERROR((C16-C15)/C15,0) -> 0 | E16: / | F16: =每月市场趋势!C34+每月市场趋势!H34+每月市场趋势!M34+每月市场趋势!R34 -> 0 | G16: =IFERROR((F16-F15)/F15,0) -> 0 | H16: / | I16: =IFERROR(F16/C16,0) -> 0 | J16: =IFERROR((I16-I15)/I15,0) -> 0 | K16: /
A17: 2021 | B17: 9 | C17: =每月市场趋势!B35+每月市场趋势!G35+每月市场趋势!L35+每月市场趋势!Q35 -> 0 | D17: =IFERROR((C17-C16)/C16,0) -> 0 | E17: / | F17: =每月市场趋势!C35+每月市场趋势!H35+每月市场趋势!M35+每月市场趋势!R35 -> 0 | G17: =IFERROR((F17-F16)/F16,0) -> 0 | H17: / | I17: =IFERROR(F17/C17,0) -> 0 | J17: =IFERROR((I17-I16)/I16,0) -> 0 | K17: /
A18: 2021 | B18: 10 | C18: =每月市场趋势!B36+每月市场趋势!G36+每月市场趋势!L36+每月市场趋势!Q36 -> 0 | D18: =IFERROR((C18-C17)/C17,0) -> 0 | E18: / | F18: =每月市场趋势!C36+每月市场趋势!H36+每月市场趋势!M36+每月市场趋势!R36 -> 0 | G18: =IFERROR((F18-F17)/F17,0) -> 0 | H18: / | I18: =IFERROR(F18/C18,0) -> 0 | J18: =IFERROR((I18-I17)/I17,0) -> 0 | K18: /
A19: 2021 | B19: 11 | C19: =每月市场趋势!B37+每月市场趋势!G37+每月市场趋势!L37+每月市场趋势!Q37 -> 0 | D19: =IFERROR((C19-C18)/C18,0) -> 0 | E19: / | F19: =每月市场趋势!C37+每月市场趋势!H37+每月市场趋势!M37+每月市场趋势!R37 -> 0 | G19: =IFERROR((F19-F18)/F18,0) -> 0 | H19: / | I19: =IFERROR(F19/C19,0) -> 0 | J19: =IFERROR((I19-I18)/I18,0) -> 0 | K19: /
A20: 2021 | B20: 12 | C20: =每月市场趋势!B38+每月市场趋势!G38+每月市场趋势!L38+每月市场趋势!Q38 -> 0 | D20: =IFERROR((C20-C19)/C19,0) -> 0 | E20: / | F20: =每月市场趋势!C38+每月市场趋势!H38+每月市场趋势!M38+每月市场趋势!R38 -> 0 | G20: =IFERROR((F20-F19)/F19,0) -> 0 | H20: / | I20: =IFERROR(F20/C20,0) -> 0 | J20: =IFERROR((I20-I19)/I19,0) -> 0 | K20: /
A21: 2022 | B21: 1 | C21: =每月市场趋势!B39+每月市场趋势!G39+每月市场趋势!L39+每月市场趋势!Q39 -> 0 | D21: =IFERROR((C21-C20)/C20,0) -> 0 | E21: =IFERROR((C21-C9)/C9,0) -> 0 | F21: =每月市场趋势!C39+每月市场趋势!H39+每月市场趋势!M39+每月市场趋势!R39 -> 0 | G21: =IFERROR((F21-F20)/F20,0) -> 0 | H21: =IFERROR((F21-F9)/F9,0) -> 0 | I21: =IFERROR(F21/C21,0) -> 0 | J21: =IFERROR((I21-I20)/I20,0) -> 0 | K21: =IFERROR((I21-I8)/I8,0) -> 0
A22: 2022 | B22: 2 | C22: =每月市场趋势!B40+每月市场趋势!G40+每月市场趋势!L40+每月市场趋势!Q40 -> 0 | D22: =IFERROR((C22-C21)/C21,0) -> 0 | E22: =IFERROR((C22-C10)/C10,0) -> 0 | F22: =每月市场趋势!C40+每月市场趋势!H40+每月市场趋势!M40+每月市场趋势!R40 -> 0 | G22: =IFERROR((F22-F21)/F21,0) -> 0 | H22: =IFERROR((F22-F10)/F10,0) -> 0 | I22: =IFERROR(F22/C22,0) -> 0 | J22: =IFERROR((I22-I21)/I21,0) -> 0 | K22: =IFERROR((I22-I9)/I9,0) -> 0
A23: 2022 | B23: 3 | C23: =每月市场趋势!B41+每月市场趋势!G41+每月市场趋势!L41+每月市场趋势!Q41 -> 0 | D23: =IFERROR((C23-C22)/C22,0) -> 0 | E23: =IFERROR((C23-C11)/C11,0) -> 0 | F23: =每月市场趋势!C41+每月市场趋势!H41+每月市场趋势!M41+每月市场趋势!R41 -> 0 | G23: =IFERROR((F23-F22)/F22,0) -> 0 | H23: =IFERROR((F23-F11)/F11,0) -> 0 | I23: =IFERROR(F23/C23,0) -> 0 | J23: =IFERROR((I23-I22)/I22,0) -> 0 | K23: =IFERROR((I23-I10)/I10,0) -> 0
A24: 2022 | B24: 4 | C24: =每月市场趋势!B42+每月市场趋势!G42+每月市场趋势!L42+每月市场趋势!Q42 -> 0 | D24: =IFERROR((C24-C23)/C23,0) -> 0 | E24: =IFERROR((C24-C12)/C12,0) -> 0 | F24: =每月市场趋势!C42+每月市场趋势!H42+每月市场趋势!M42+每月市场趋势!R42 -> 0 | G24: =IFERROR((F24-F23)/F23,0) -> 0 | H24: =IFERROR((F24-F12)/F12,0) -> 0 | I24: =IFERROR(F24/C24,0) -> 0 | J24: =IFERROR((I24-I23)/I23,0) -> 0 | K24: =IFERROR((I24-I11)/I11,0) -> 0
A25: 2022 | B25: 5 | C25: =每月市场趋势!B43+每月市场趋势!G43+每月市场趋势!L43+每月市场趋势!Q43 -> 0 | D25: =IFERROR((C25-C24)/C24,0) -> 0 | E25: =IFERROR((C25-C13)/C13,0) -> 0 | F25: =每月市场趋势!C43+每月市场趋势!H43+每月市场趋势!M43+每月市场趋势!R43 -> 0 | G25: =IFERROR((F25-F24)/F24,0) -> 0 | H25: =IFERROR((F25-F13)/F13,0) -> 0 | I25: =IFERROR(F25/C25,0) -> 0 | J25: =IFERROR((I25-I24)/I24,0) -> 0 | K25: =IFERROR((I25-I12)/I12,0) -> 0
A26: 2022 | B26: 6 | C26: =每月市场趋势!B44+每月市场趋势!G44+每月市场趋势!L44+每月市场趋势!Q44 -> 0 | D26: =IFERROR((C26-C25)/C25,0) -> 0 | E26: =IFERROR((C26-C14)/C14,0) -> 0 | F26: =每月市场趋势!C44+每月市场趋势!H44+每月市场趋势!M44+每月市场趋势!R44 -> 0 | G26: =IFERROR((F26-F25)/F25,0) -> 0 | H26: =IFERROR((F26-F14)/F14,0) -> 0 | I26: =IFERROR(F26/C26,0) -> 0 | J26: =IFERROR((I26-I25)/I25,0) -> 0 | K26: =IFERROR((I26-I13)/I13,0) -> 0
A27: 2022 | B27: 7 | C27: =每月市场趋势!B45+每月市场趋势!G45+每月市场趋势!L45+每月市场趋势!Q45 -> 0 | D27: =IFERROR((C27-C26)/C26,0) -> 0 | E27: =IFERROR((C27-C15)/C15,0) -> 0 | F27: =每月市场趋势!C45+每月市场趋势!H45+每月市场趋势!M45+每月市场趋势!R45 -> 0 | G27: =IFERROR((F27-F26)/F26,0) -> 0 | H27: =IFERROR((F27-F15)/F15,0) -> 0 | I27: =IFERROR(F27/C27,0) -> 0 | J27: =IFERROR((I27-I26)/I26,0) -> 0 | K27: =IFERROR((I27-I14)/I14,0) -> 0
A28: 2022 | B28: 8 | C28: =每月市场趋势!B46+每月市场趋势!G46+每月市场趋势!L46+每月市场趋势!Q46 -> 0 | D28: =IFERROR((C28-C27)/C27,0) -> 0 | E28: =IFERROR((C28-C16)/C16,0) -> 0 | F28: =每月市场趋势!C46+每月市场趋势!H46+每月市场趋势!M46+每月市场趋势!R46 -> 0 | G28: =IFERROR((F28-F27)/F27,0) -> 0 | H28: =IFERROR((F28-F16)/F16,0) -> 0 | I28: =IFERROR(F28/C28,0) -> 0 | J28: =IFERROR((I28-I27)/I27,0) -> 0 | K28: =IFERROR((I28-I15)/I15,0) -> 0
A29: 2022 | B29: 9 | C29: =每月市场趋势!B47+每月市场趋势!G47+每月市场趋势!L47+每月市场趋势!Q47 -> 0 | D29: =IFERROR((C29-C28)/C28,0) -> 0 | E29: =IFERROR((C29-C17)/C17,0) -> 0 | F29: =每月市场趋势!C47+每月市场趋势!H47+每月市场趋势!M47+每月市场趋势!R47 -> 0 | G29: =IFERROR((F29-F28)/F28,0) -> 0 | H29: =IFERROR((F29-F17)/F17,0) -> 0 | I29: =IFERROR(F29/C29,0) -> 0 | J29: =IFERROR((I29-I28)/I28,0) -> 0 | K29: =IFERROR((I29-I16)/I16,0) -> 0
A30: 2022 | B30: 10 | C30: =每月市场趋势!B48+每月市场趋势!G48+每月市场趋势!L48+每月市场趋势!Q48 -> 0 | D30: =IFERROR((C30-C29)/C29,0) -> 0 | E30: =IFERROR((C30-C18)/C18,0) -> 0 | F30: =每月市场趋势!C48+每月市场趋势!H48+每月市场趋势!M48+每月市场趋势!R48 -> 0 | G30: =IFERROR((F30-F29)/F29,0) -> 0 | H30: =IFERROR((F30-F18)/F18,0) -> 0 | I30: =IFERROR(F30/C30,0) -> 0 | J30: =IFERROR((I30-I29)/I29,0) -> 0 | K30: =IFERROR((I30-I17)/I17,0) -> 0
A31: 2022 | B31: 11 | C31: =每月市场趋势!B49+每月市场趋势!G49+每月市场趋势!L49+每月市场趋势!Q49 -> 0 | D31: =IFERROR((C31-C30)/C30,0) -> 0 | E31: =IFERROR((C31-C19)/C19,0) -> 0 | F31: =每月市场趋势!C49+每月市场趋势!H49+每月市场趋势!M49+每月市场趋势!R49 -> 0 | G31: =IFERROR((F31-F30)/F30,0) -> 0 | H31: =IFERROR((F31-F19)/F19,0) -> 0 | I31: =IFERROR(F31/C31,0) -> 0 | J31: =IFERROR((I31-I30)/I30,0) -> 0 | K31: =IFERROR((I31-I18)/I18,0) -> 0
A32: 2022 | B32: 12 | C32: =每月市场趋势!B50+每月市场趋势!G50+每月市场趋势!L50+每月市场趋势!Q50 -> 0 | D32: =IFERROR((C32-C31)/C31,0) -> 0 | E32: =IFERROR((C32-C20)/C20,0) -> 0 | F32: =每月市场趋势!C50+每月市场趋势!H50+每月市场趋势!M50+每月市场趋势!R50 -> 0 | G32: =IFERROR((F32-F31)/F31,0) -> 0 | H32: =IFERROR((F32-F20)/F20,0) -> 0 | I32: =IFERROR(F32/C32,0) -> 0 | J32: =IFERROR((I32-I31)/I31,0) -> 0 | K32: =IFERROR((I32-I19)/I19,0) -> 0
A34: xxx每月市占率趋势(2022年)
A35: 年份 | B35: 月份 | C35: 销量 | D35: 市占率 | E35: 市占率环比 | F35: 市占率同比 | G35: 销售额 | H35: 市场份额占比 | I35: 市场份额环比 | J35: 市场份额同比
A36: 2021 | B36: 44197 | C36: =SUMIFS('船长每月数据(2022年)'!P:P,'船长每月数据(2022年)'!C:C,"BBQ",'船长每月数据(2022年)'!F:F,B36) -> 0 | D36: =IFERROR(C36/C9,0) -> 0 | E36: / | F36: / | G36: =SUMIFS('船长每月数据(2022年)'!R:R,'船长每月数据(2022年)'!C:C,"BBQ",'船长每月数据(2022年)'!F:F,B36) -> 0 | H36: =IFERROR(G36/F8,0) -> 0 | I36: / | J36: /
A37: 2021 | B37: 44228 | C37: =SUMIFS('船长每月数据(2022年)'!P:P,'船长每月数据(2022年)'!C:C,"BBQ",'船长每月数据(2022年)'!F:F,B37) -> 0 | D37: =IFERROR(C37/C10,0) -> 0 | E37: =IFERROR((D37-D36)/D36,0) -> 0 | F37: / | G37: =SUMIFS('船长每月数据(2022年)'!R:R,'船长每月数据(2022年)'!C:C,"BBQ",'船长每月数据(2022年)'!F:F,B37) -> 0 | H37: =IFERROR(G37/F9,0) -> 0 | I37: =IFERROR((H37-H36)/H36,0) -> 0 | J37: /
A38: 2021 | B38: 44256 | C38: =SUMIFS('船长每月数据(2022年)'!P:P,'船长每月数据(2022年)'!C:C,"BBQ",'船长每月数据(2022年)'!F:F,B38) -> 0 | D38: =IFERROR(C38/C11,0) -> 0 | E38: =IFERROR((D38-D37)/D37,0) -> 0 | F38: / | G38: =SUMIFS('船长每月数据(2022年)'!R:R,'船长每月数据(2022年)'!C:C,"BBQ",'船长每月数据(2022年)'!F:F,B38) -> 0 | H38: =IFERROR(G38/F10,0) -> 0 | I38: =IFERROR((H38-H37)/H37,0) -> 0 | J38: /
A39: 2021 | B39: 44287 | C39: =SUMIFS('船长每月数据(2022年)'!P:P,'船长每月数据(2022年)'!C:C,"BBQ",'船长每月数据(2022年)'!F:F,B39) -> 0 | D39: =IFERROR(C39/C12,0) -> 0 | E39: =IFERROR((D39-D38)/D38,0) -> 0 | F39: / | G39: =SUMIFS('船长每月数据(2022年)'!R:R,'船长每月数据(2022年)'!C:C,"BBQ",'船长每月数据(2022年)'!F:F,B39) -> 0 | H39: =IFERROR(G39/F11,0) -> 0 | I39: =IFERROR((H39-H38)/H38,0) -> 0 | J39: /
A40: 2021 | B40: 44317 | C40: =SUMIFS('船长每月数据(2022年)'!P:P,'船长每月数据(2022年)'!C:C,"BBQ",'船长每月数据(2022年)'!F:F,B40) -> 0 | D40: =IFERROR(C40/C13,0) -> 0 | E40: =IFERROR((D40-D39)/D39,0) -> 0 | F40: / | G40: =SUMIFS('船长每月数据(2022年)'!R:R,'船长每月数据(2022年)'!C:C,"BBQ",'船长每月数据(2022年)'!F:F,B40) -> 0 | H40: =IFERROR(G40/F12,0) -> 0 | I40: =IFERROR((H40-H39)/H39,0) -> 0 | J40: /
A41: 2021 | B41: 44348 | C41: =SUMIFS('船长每月数据(2022年)'!P:P,'船长每月数据(2022年)'!C:C,"BBQ",'船长每月数据(2022年)'!F:F,B41) -> 0 | D41: =IFERROR(C41/C14,0) -> 0 | E41: =IFERROR((D41-D40)/D40,0) -> 0 | F41: / | G41: =SUMIFS('船长每月数据(2022年)'!R:R,'船长每月数据(2022年)'!C:C,"BBQ",'船长每月数据(2022年)'!F:F,B41) -> 0 | H41: =IFERROR(G41/F13,0) -> 0 | I41: =IFERROR((H41-H40)/H40,0) -> 0 | J41: /
A42: 2021 | B42: 44378 | C42: =SUMIFS('船长每月数据(2022年)'!P:P,'船长每月数据(2022年)'!C:C,"BBQ",'船长每月数据(2022年)'!F:F,B42) -> 0 | D42: =IFERROR(C42/C15,0) -> 0 | E42: =IFERROR((D42-D41)/D41,0) -> 0 | F42: / | G42: =SUMIFS('船长每月数据(2022年)'!R:R,'船长每月数据(2022年)'!C:C,"BBQ",'船长每月数据(2022年)'!F:F,B42) -> 0 | H42: =IFERROR(G42/F14,0) -> 0 | I42: =IFERROR((H42-H41)/H41,0) -> 0 | J42: /
A43: 2021 | B43: 44409 | C43: =SUMIFS('船长每月数据(2022年)'!P:P,'船长每月数据(2022年)'!C:C,"BBQ",'船长每月数据(2022年)'!F:F,B43) -> 0 | D43: =IFERROR(C43/C16,0) -> 0 | E43: =IFERROR((D43-D42)/D42,0) -> 0 | F43: / | G43: =SUMIFS('船长每月数据(2022年)'!R:R,'船长每月数据(2022年)'!C:C,"BBQ",'船长每月数据(2022年)'!F:F,B43) -> 0 | H43: =IFERROR(G43/F15,0) -> 0 | I43: =IFERROR((H43-H42)/H42,0) -> 0 | J43: /
A44: 2021 | B44: 44440 | C44: =SUMIFS('船长每月数据(2022年)'!P:P,'船长每月数据(2022年)'!C:C,"BBQ",'船长每月数据(2022年)'!F:F,B44) -> 0 | D44: =IFERROR(C44/C17,0) -> 0 | E44: =IFERROR((D44-D43)/D43,0) -> 0 | F44: / | G44: =SUMIFS('船长每月数据(2022年)'!R:R,'船长每月数据(2022年)'!C:C,"BBQ",'船长每月数据(2022年)'!F:F,B44) -> 0 | H44: =IFERROR(G44/F16,0) -> 0 | I44: =IFERROR((H44-H43)/H43,0) -> 0 | J44: /
A45: 2021 | B45: 44470 | C45: =SUMIFS('船长每月数据(2022年)'!P:P,'船长每月数据(2022年)'!C:C,"BBQ",'船长每月数据(2022年)'!F:F,B45) -> 0 | D45: =IFERROR(C45/C18,0) -> 0 | E45: =IFERROR((D45-D44)/D44,0) -> 0 | F45: / | G45: =SUMIFS('船长每月数据(2022年)'!R:R,'船长每月数据(2022年)'!C:C,"BBQ",'船长每月数据(2022年)'!F:F,B45) -> 0 | H45: =IFERROR(G45/F17,0) -> 0 | I45: =IFERROR((H45-H44)/H44,0) -> 0 | J45: /
A46: 2021 | B46: 44501 | C46: =SUMIFS('船长每月数据(2022年)'!P:P,'船长每月数据(2022年)'!C:C,"BBQ",'船长每月数据(2022年)'!F:F,B46) -> 0 | D46: =IFERROR(C46/C19,0) -> 0 | E46: =IFERROR((D46-D45)/D45,0) -> 0 | F46: / | G46: =SUMIFS('船长每月数据(2022年)'!R:R,'船长每月数据(2022年)'!C:C,"BBQ",'船长每月数据(2022年)'!F:F,B46) -> 0 | H46: =IFERROR(G46/F18,0) -> 0 | I46: =IFERROR((H46-H45)/H45,0) -> 0 | J46: /
A47: 2021 | B47: 44531 | C47: =SUMIFS('船长每月数据(2022年)'!P:P,'船长每月数据(2022年)'!C:C,"BBQ",'船长每月数据(2022年)'!F:F,B47) -> 0 | D47: =IFERROR(C47/C20,0) -> 0 | E47: =IFERROR((D47-D46)/D46,0) -> 0 | F47: / | G47: =SUMIFS('船长每月数据(2022年)'!R:R,'船长每月数据(2022年)'!C:C,"BBQ",'船长每月数据(2022年)'!F:F,B47) -> 0 | H47: =IFERROR(G47/F19,0) -> 0 | I47: =IFERROR((H47-H46)/H46,0) -> 0 | J47: /
A48: 2022 | B48: 44562 | C48: =SUMIFS('船长每月数据(2023年)'!P:P,'船长每月数据(2023年)'!C:C,"BBQ",'船长每月数据(2023年)'!F:F,B48) -> 0 | D48: =IFERROR(C48/C21,0) -> 0 | E48: =IFERROR((D48-D47)/D47,0) -> 0 | F48: =IFERROR((D48-D36)/D36,0) -> 0 | G48: =SUMIFS('船长每月数据(2023年)'!R:R,'船长每月数据(2023年)'!C:C,"BBQ",'船长每月数据(2023年)'!F:F,B48) -> 0 | H48: =IFERROR(G48/F20,0) -> 0 | I48: =IFERROR((H48-H47)/H47,0) -> 0 | J48: =IFERROR((H48-H36)/H36,0) -> 0
A49: 2022 | B49: 44593 | C49: =SUMIFS('船长每月数据(2023年)'!P:P,'船长每月数据(2023年)'!C:C,"BBQ",'船长每月数据(2023年)'!F:F,B49) -> 0 | D49: =IFERROR(C49/C22,0) -> 0 | E49: =IFERROR((D49-D48)/D48,0) -> 0 | F49: =IFERROR((D49-D37)/D37,0) -> 0 | G49: =SUMIFS('船长每月数据(2023年)'!R:R,'船长每月数据(2023年)'!C:C,"BBQ",'船长每月数据(2023年)'!F:F,B49) -> 0 | H49: =IFERROR(G49/F21,0) -> 0 | I49: =IFERROR((H49-H48)/H48,0) -> 0 | J49: =IFERROR((H49-H37)/H37,0) -> 0
A50: 2022 | B50: 44621 | C50: =SUMIFS('船长每月数据(2023年)'!P:P,'船长每月数据(2023年)'!C:C,"BBQ",'船长每月数据(2023年)'!F:F,B50) -> 0 | D50: =IFERROR(C50/C23,0) -> 0 | E50: =IFERROR((D50-D49)/D49,0) -> 0 | F50: =IFERROR((D50-D38)/D38,0) -> 0 | G50: =SUMIFS('船长每月数据(2023年)'!R:R,'船长每月数据(2023年)'!C:C,"BBQ",'船长每月数据(2023年)'!F:F,B50) -> 0 | H50: =IFERROR(G50/F22,0) -> 0 | I50: =IFERROR((H50-H49)/H49,0) -> 0 | J50: =IFERROR((H50-H38)/H38,0) -> 0
A51: 2022 | B51: 44652 | C51: =SUMIFS('船长每月数据(2023年)'!P:P,'船长每月数据(2023年)'!C:C,"BBQ",'船长每月数据(2023年)'!F:F,B51) -> 0 | D51: =IFERROR(C51/C24,0) -> 0 | E51: =IFERROR((D51-D50)/D50,0) -> 0 | F51: =IFERROR((D51-D39)/D39,0) -> 0 | G51: =SUMIFS('船长每月数据(2023年)'!R:R,'船长每月数据(2023年)'!C:C,"BBQ",'船长每月数据(2023年)'!F:F,B51) -> 0 | H51: =IFERROR(G51/F23,0) -> 0 | I51: =IFERROR((H51-H50)/H50,0) -> 0 | J51: =IFERROR((H51-H39)/H39,0) -> 0
A52: 2022 | B52: 44682 | C52: =SUMIFS('船长每月数据(2023年)'!P:P,'船长每月数据(2023年)'!C:C,"BBQ",'船长每月数据(2023年)'!F:F,B52) -> 0 | D52: =IFERROR(C52/C25,0) -> 0 | E52: =IFERROR((D52-D51)/D51,0) -> 0 | F52: =IFERROR((D52-D40)/D40,0) -> 0 | G52: =SUMIFS('船长每月数据(2023年)'!R:R,'船长每月数据(2023年)'!C:C,"BBQ",'船长每月数据(2023年)'!F:F,B52) -> 0 | H52: =IFERROR(G52/F24,0) -> 0 | I52: =IFERROR((H52-H51)/H51,0) -> 0 | J52: =IFERROR((H52-H40)/H40,0) -> 0
A53: 2022 | B53: 44713 | C53: =SUMIFS('船长每月数据(2023年)'!P:P,'船长每月数据(2023年)'!C:C,"BBQ",'船长每月数据(2023年)'!F:F,B53) -> 0 | D53: =IFERROR(C53/C26,0) -> 0 | E53: =IFERROR((D53-D52)/D52,0) -> 0 | F53: =IFERROR((D53-D41)/D41,0) -> 0 | G53: =SUMIFS('船长每月数据(2023年)'!R:R,'船长每月数据(2023年)'!C:C,"BBQ",'船长每月数据(2023年)'!F:F,B53) -> 0 | H53: =IFERROR(G53/F25,0) -> 0 | I53: =IFERROR((H53-H52)/H52,0) -> 0 | J53: =IFERROR((H53-H41)/H41,0) -> 0
A54: 2022 | B54: 44743 | C54: =SUMIFS('船长每月数据(2023年)'!P:P,'船长每月数据(2023年)'!C:C,"BBQ",'船长每月数据(2023年)'!F:F,B54) -> 0 | D54: =IFERROR(C54/C27,0) -> 0 | E54: =IFERROR((D54-D53)/D53,0) -> 0 | F54: =IFERROR((D54-D42)/D42,0) -> 0 | G54: =SUMIFS('船长每月数据(2023年)'!R:R,'船长每月数据(2023年)'!C:C,"BBQ",'船长每月数据(2023年)'!F:F,B54) -> 0 | H54: =IFERROR(G54/F26,0) -> 0 | I54: =IFERROR((H54-H53)/H53,0) -> 0 | J54: =IFERROR((H54-H42)/H42,0) -> 0
A55: 2022 | B55: 44774 | C55: =SUMIFS('船长每月数据(2023年)'!P:P,'船长每月数据(2023年)'!C:C,"BBQ",'船长每月数据(2023年)'!F:F,B55) -> 0 | D55: =IFERROR(C55/C28,0) -> 0 | E55: =IFERROR((D55-D54)/D54,0) -> 0 | F55: =IFERROR((D55-D43)/D43,0) -> 0 | G55: =SUMIFS('船长每月数据(2023年)'!R:R,'船长每月数据(2023年)'!C:C,"BBQ",'船长每月数据(2023年)'!F:F,B55) -> 0 | H55: =IFERROR(G55/F27,0) -> 0 | I55: =IFERROR((H55-H54)/H54,0) -> 0 | J55: =IFERROR((H55-H43)/H43,0) -> 0
A56: 2022 | B56: 44805 | C56: =SUMIFS('船长每月数据(2023年)'!P:P,'船长每月数据(2023年)'!C:C,"BBQ",'船长每月数据(2023年)'!F:F,B56) -> 0 | D56: =IFERROR(C56/C29,0) -> 0 | E56: =IFERROR((D56-D55)/D55,0) -> 0 | F56: =IFERROR((D56-D44)/D44,0) -> 0 | G56: =SUMIFS('船长每月数据(2023年)'!R:R,'船长每月数据(2023年)'!C:C,"BBQ",'船长每月数据(2023年)'!F:F,B56) -> 0 | H56: =IFERROR(G56/F28,0) -> 0 | I56: =IFERROR((H56-H55)/H55,0) -> 0 | J56: =IFERROR((H56-H44)/H44,0) -> 0
A57: 2022 | B57: 44835 | C57: =SUMIFS('船长每月数据(2023年)'!P:P,'船长每月数据(2023年)'!C:C,"BBQ",'船长每月数据(2023年)'!F:F,B57) -> 0 | D57: =IFERROR(C57/C30,0) -> 0 | E57: =IFERROR((D57-D56)/D56,0) -> 0 | F57: =IFERROR((D57-D45)/D45,0) -> 0 | G57: =SUMIFS('船长每月数据(2023年)'!R:R,'船长每月数据(2023年)'!C:C,"BBQ",'船长每月数据(2023年)'!F:F,B57) -> 0 | H57: =IFERROR(G57/F29,0) -> 0 | I57: =IFERROR((H57-H56)/H56,0) -> 0 | J57: =IFERROR((H57-H45)/H45,0) -> 0
A58: 2022 | B58: 44866 | C58: =SUMIFS('船长每月数据(2023年)'!P:P,'船长每月数据(2023年)'!C:C,"BBQ",'船长每月数据(2023年)'!F:F,B58) -> 0 | D58: =IFERROR(C58/C31,0) -> 0 | E58: =IFERROR((D58-D57)/D57,0) -> 0 | F58: =IFERROR((D58-D46)/D46,0) -> 0 | G58: =SUMIFS('船长每月数据(2023年)'!R:R,'船长每月数据(2023年)'!C:C,"BBQ",'船长每月数据(2023年)'!F:F,B58) -> 0 | H58: =IFERROR(G58/F30,0) -> 0 | I58: =IFERROR((H58-H57)/H57,0) -> 0 | J58: =IFERROR((H58-H46)/H46,0) -> 0
A59: 2022 | B59: 44896 | C59: =SUMIFS('船长每月数据(2023年)'!P:P,'船长每月数据(2023年)'!C:C,"BBQ",'船长每月数据(2023年)'!F:F,B59) -> 0 | D59: =IFERROR(C59/C32,0) -> 0 | E59: =IFERROR((D59-D58)/D58,0) -> 0 | F59: =IFERROR((D59-D47)/D47,0) -> 0 | G59: =SUMIFS('船长每月数据(2023年)'!R:R,'船长每月数据(2023年)'!C:C,"BBQ",'船长每月数据(2023年)'!F:F,B59) -> 0 | H59: =IFERROR(G59/F31,0) -> 0 | I59: =IFERROR((H59-H58)/H58,0) -> 0 | J59: =IFERROR((H59-H47)/H47,0) -> 0
A61: xxx主要ASIN销售情况(2022年)
A62: ASIN | B62: 所在类目 | C62: 平均市场容量 | D62: 年销量 | E62: xxx市占率 | F62: 市场份额 | G62: 年销售额 | H62: xxx市场份额占比
C63: =SUM(每月市场趋势!$G$39:$G$50) -> 0 | D63: =SUMIF('船长每月数据(2023年)'!E:E,A:A,'船长每月数据(2023年)'!P:P) -> 0 | E63: =IFERROR(D63/C63,0) -> 0 | F63: =SUM(每月市场趋势!$H$39:$H$50) -> 0 | G63: =SUMIF('船长每月数据(2023年)'!E:E,A:A,'船长每月数据(2023年)'!R:R) -> 0 | H63: =IFERROR(G63/F63,0) -> 0
C64: =SUM(每月市场趋势!$G$39:$G$50) -> 0 | D64: =SUMIF('船长每月数据(2023年)'!E:E,A:A,'船长每月数据(2023年)'!P:P) -> 0 | E64: =IFERROR(D64/C64,0) -> 0 | F64: =SUM(每月市场趋势!$H$39:$H$50) -> 0 | G64: =SUMIF('船长每月数据(2023年)'!E:E,A:A,'船长每月数据(2023年)'!R:R) -> 0 | H64: =IFERROR(G64/F64,0) -> 0
C65: =SUM(每月市场趋势!$G$39:$G$50) -> 0 | D65: =SUMIF('船长每月数据(2023年)'!E:E,A:A,'船长每月数据(2023年)'!P:P) -> 0 | E65: =IFERROR(D65/C65,0) -> 0 | F65: =SUM(每月市场趋势!$H$39:$H$50) -> 0 | G65: =SUMIF('船长每月数据(2023年)'!E:E,A:A,'船长每月数据(2023年)'!R:R) -> 0 | H65: =IFERROR(G65/F65,0) -> 0
C66: =SUM(每月市场趋势!$G$39:$G$50) -> 0 | D66: =SUMIF('船长每月数据(2023年)'!E:E,A:A,'船长每月数据(2023年)'!P:P) -> 0 | E66: =IFERROR(D66/C66,0) -> 0 | F66: =SUM(每月市场趋势!$H$39:$H$50) -> 0 | G66: =SUMIF('船长每月数据(2023年)'!E:E,A:A,'船长每月数据(2023年)'!R:R) -> 0 | H66: =IFERROR(G66/F66,0) -> 0
C67: =SUM(每月市场趋势!$B$39:$B$50) -> 0 | D67: =SUMIF('船长每月数据(2023年)'!E:E,A:A,'船长每月数据(2023年)'!P:P) -> 0 | E67: =IFERROR(D67/C67,0) -> 0 | F67: =SUM(每月市场趋势!$C$39:$C$50) -> 0 | G67: =SUMIF('船长每月数据(2023年)'!E:E,A:A,'船长每月数据(2023年)'!R:R) -> 0 | H67: =IFERROR(G67/F67,0) -> 0
C68: =SUM(每月市场趋势!$B$39:$B$50) -> 0 | D68: =SUMIF('船长每月数据(2023年)'!E:E,A:A,'船长每月数据(2023年)'!P:P) -> 0 | E68: =IFERROR(D68/C68,0) -> 0 | F68: =SUM(每月市场趋势!$C$39:$C$50) -> 0 | G68: =SUMIF('船长每月数据(2023年)'!E:E,A:A,'船长每月数据(2023年)'!R:R) -> 0 | H68: =IFERROR(G68/F68,0) -> 0
C69: =SUM(每月市场趋势!Q39:Q50) -> 0 | D69: =SUMIF('船长每月数据(2023年)'!E:E,A:A,'船长每月数据(2023年)'!P:P) -> 0 | E69: =IFERROR(D69/C69,0) -> 0 | F69: =SUM(每月市场趋势!$R$39:$R$50) -> 0 | G69: =SUMIF('船长每月数据(2023年)'!E:E,A:A,'船长每月数据(2023年)'!R:R) -> 0 | H69: =IFERROR(G69/F69,0) -> 0
C70: =SUM(每月市场趋势!$B$39:$B$50) -> 0 | D70: =SUMIF('船长每月数据(2023年)'!E:E,A:A,'船长每月数据(2023年)'!P:P) -> 0 | E70: =IFERROR(D70/C70,0) -> 0 | F70: =SUM(每月市场趋势!$C$39:$C$50) -> 0 | G70: =SUMIF('船长每月数据(2023年)'!E:E,A:A,'船长每月数据(2023年)'!R:R) -> 0 | H70: =IFERROR(G70/F70,0) -> 0
C71: =SUM(每月市场趋势!$G$39:$G$50) -> 0 | D71: =SUMIF('船长每月数据(2023年)'!E:E,A:A,'船长每月数据(2023年)'!P:P) -> 0 | E71: =IFERROR(D71/C71,0) -> 0 | F71: =SUM(每月市场趋势!$H$39:$H$50) -> 0 | G71: =SUMIF('船长每月数据(2023年)'!E:E,A:A,'船长每月数据(2023年)'!R:R) -> 0 | H71: =IFERROR(G71/F71,0) -> 0
C72: =SUM(每月市场趋势!$B$39:$B$50) -> 0 | D72: =SUMIF('船长每月数据(2023年)'!E:E,A:A,'船长每月数据(2023年)'!P:P) -> 0 | E72: =IFERROR(D72/C72,0) -> 0 | F72: =SUM(每月市场趋势!$C$39:$C$50) -> 0 | G72: =SUMIF('船长每月数据(2023年)'!E:E,A:A,'船长每月数据(2023年)'!R:R) -> 0 | H72: =IFERROR(G72/F72,0) -> 0
A74: 各类目TOP5品牌集中度(近30天)
A75: 类目 | B75: 类目容量 | C75: 类目份额 | D75: 品牌 | E75: 品牌销量 | F75: 品牌销量占比 | G75: 品牌销售额 | H75: 品牌销售额占比
B76: =SUM(类目品牌市占率!AE3:AE61) -> 0 | C76: =SUM(类目品牌市占率!AI3:AI61) -> 0 | E76: =SUMIF(类目品牌市占率!AB:AB,D:D,类目品牌市占率!AE:AE) -> 0 | F76: =IFERROR(E76/$B$76,0) -> 0 | G76: =SUMIF(类目品牌市占率!AB:AB,D:D,类目品牌市占率!AI:AI) -> 0 | H76: =IFERROR(G76/$C$76,0) -> 0
E77: =SUMIF(类目品牌市占率!AB:AB,D:D,类目品牌市占率!AE:AE) -> 0 | F77: =IFERROR(E77/$B$76,0) -> 0 | G77: =SUMIF(类目品牌市占率!AB:AB,D:D,类目品牌市占率!AI:AI) -> 0 | H77: =IFERROR(G77/$C$76,0) -> 0
E78: =SUMIF(类目品牌市占率!AB:AB,D:D,类目品牌市占率!AE:AE) -> 0 | F78: =IFERROR(E78/$B$76,0) -> 0 | G78: =SUMIF(类目品牌市占率!AB:AB,D:D,类目品牌市占率!AI:AI) -> 0 | H78: =IFERROR(G78/$C$76,0) -> 0
E79: =SUMIF(类目品牌市占率!AB:AB,D:D,类目品牌市占率!AE:AE) -> 0 | F79: =IFERROR(E79/$B$76,0) -> 0 | G79: =SUMIF(类目品牌市占率!AB:AB,D:D,类目品牌市占率!AI:AI) -> 0 | H79: =IFERROR(G79/$C$76,0) -> 0
E80: =SUMIF(类目品牌市占率!AB:AB,D:D,类目品牌市占率!AE:AE) -> 0 | F80: =IFERROR(E80/$B$76,0) -> 0 | G80: =SUMIF(类目品牌市占率!AB:AB,D:D,类目品牌市占率!AI:AI) -> 0 | H80: =IFERROR(G80/$C$76,0) -> 0
A81: 总计 | B81: / | C81: / | D81: / | E81: =SUM(E76:E80) -> 0 | F81: =IFERROR(E81/B76,0) -> 0 | G81: =SUM(G76:G80) -> 0 | H81: =IFERROR(G81/$C$76,0) -> 0
B82: =SUM(类目品牌市占率!E3:E73) -> 0 | C82: =SUM(类目品牌市占率!I3:I73) -> 0 | E82: =SUMIF(类目品牌市占率!B:B,D:D,类目品牌市占率!E:E) -> 0 | F82: =IFERROR(E82/$B$82,0) -> 0 | G82: =SUMIF(类目品牌市占率!B:B,D:D,类目品牌市占率!I:I) -> 0 | H82: =IFERROR(G82/$C$82,0) -> 0
E83: =SUMIF(类目品牌市占率!B:B,D:D,类目品牌市占率!E:E) -> 0 | F83: =IFERROR(E83/$B$82,0) -> 0 | G83: =SUMIF(类目品牌市占率!B:B,D:D,类目品牌市占率!I:I) -> 0 | H83: =IFERROR(G83/$C$82,0) -> 0
E84: =SUMIF(类目品牌市占率!B:B,D:D,类目品牌市占率!E:E) -> 0 | F84: =IFERROR(E84/$B$82,0) -> 0 | G84: =SUMIF(类目品牌市占率!B:B,D:D,类目品牌市占率!I:I) -> 0 | H84: =IFERROR(G84/$C$82,0) -> 0
E85: =SUMIF(类目品牌市占率!B:B,D:D,类目品牌市占率!E:E) -> 0 | F85: =IFERROR(E85/$B$82,0) -> 0 | G85: =SUMIF(类目品牌市占率!B:B,D:D,类目品牌市占率!I:I) -> 0 | H85: =IFERROR(G85/$C$82,0) -> 0
E86: =SUMIF(类目品牌市占率!B:B,D:D,类目品牌市占率!E:E) -> 0 | F86: =IFERROR(E86/$B$82,0) -> 0 | G86: =SUMIF(类目品牌市占率!B:B,D:D,类目品牌市占率!I:I) -> 0 | H86: =IFERROR(G86/$C$82,0) -> 0
E87: =SUMIF(类目品牌市占率!B:B,D:D,类目品牌市占率!E:E) -> 0 | F87: =IFERROR(E87/$B$82,0) -> 0 | G87: =SUMIF(类目品牌市占率!B:B,D:D,类目品牌市占率!I:I) -> 0 | H87: =IFERROR(G87/$C$82,0) -> 0
A88: 总计 | B88: / | C88: / | D88: / | E88: =SUM(E82:E86) -> 0 | F88: =IFERROR(E88/B82,0) -> 0 | G88: =SUM(G82:G86) -> 0 | H88: =IFERROR(G88/C82,0) -> 0
B89: =SUM(类目品牌市占率!R3:R30) -> 0 | C89: =SUM(类目品牌市占率!V3:V30) -> 0 | E89: =SUMIF(类目品牌市占率!O:O,D:D,类目品牌市占率!R:R) -> 0 | F89: =IFERROR(E89/$B$89,0) -> 0 | G89: =SUMIF(类目品牌市占率!O:O,D:D,类目品牌市占率!V:V) -> 0 | H89: =IFERROR(G89/$C$89,0) -> 0
E90: =SUMIF(类目品牌市占率!O:O,D:D,类目品牌市占率!R:R) -> 0 | F90: =IFERROR(E90/$B$89,0) -> 0 | G90: =SUMIF(类目品牌市占率!O:O,D:D,类目品牌市占率!V:V) -> 0 | H90: =IFERROR(G90/$C$89,0) -> 0
E91: =SUMIF(类目品牌市占率!O:O,D:D,类目品牌市占率!R:R) -> 0 | F91: =IFERROR(E91/$B$89,0) -> 0 | G91: =SUMIF(类目品牌市占率!O:O,D:D,类目品牌市占率!V:V) -> 0 | H91: =IFERROR(G91/$C$89,0) -> 0
E92: =SUMIF(类目品牌市占率!O:O,D:D,类目品牌市占率!R:R) -> 0 | F92: =IFERROR(E92/$B$89,0) -> 0 | G92: =SUMIF(类目品牌市占率!O:O,D:D,类目品牌市占率!V:V) -> 0 | H92: =IFERROR(G92/$C$89,0) -> 0
E93: =SUMIF(类目品牌市占率!O:O,D:D,类目品牌市占率!R:R) -> 0 | F93: =IFERROR(E93/$B$89,0) -> 0 | G93: =SUMIF(类目品牌市占率!O:O,D:D,类目品牌市占率!V:V) -> 0 | H93: =IFERROR(G93/$C$89,0) -> 0
A94: 总计 | B94: / | C94: / | D94: / | E94: =SUM(E89:E93) -> 0 | F94: =IFERROR(E94/$B$89,0) -> 0 | G94: =SUM(G89:G93) -> 0 | H94: =IFERROR(G94/C89,0) -> 0
B95: =SUM(类目品牌市占率!AR3:AR62) -> 0 | C95: =SUM(类目品牌市占率!AV3:AV62) -> 0 | E95: =SUMIF(类目品牌市占率!AO:AO,D:D,类目品牌市占率!AR:AR) -> 0 | F95: =IFERROR(E95/$B$95,0) -> 0 | G95: =SUMIF(类目品牌市占率!AO:AO,D:D,类目品牌市占率!AV:AV) -> 0 | H95: =IFERROR(G95/$C$95,0) -> 0
E96: =SUMIF(类目品牌市占率!AO:AO,D:D,类目品牌市占率!AR:AR) -> 0 | F96: =IFERROR(E96/$B$95,0) -> 0 | G96: =SUMIF(类目品牌市占率!AO:AO,D:D,类目品牌市占率!AV:AV) -> 0 | H96: =IFERROR(G96/$C$95,0) -> 0
E97: =SUMIF(类目品牌市占率!AO:AO,D:D,类目品牌市占率!AR:AR) -> 0 | F97: =IFERROR(E97/$B$95,0) -> 0 | G97: =SUMIF(类目品牌市占率!AO:AO,D:D,类目品牌市占率!AV:AV) -> 0 | H97: =IFERROR(G97/$C$95,0) -> 0
E98: =SUMIF(类目品牌市占率!AO:AO,D:D,类目品牌市占率!AR:AR) -> 0 | F98: =IFERROR(E98/$B$95,0) -> 0 | G98: =SUMIF(类目品牌市占率!AO:AO,D:D,类目品牌市占率!AV:AV) -> 0 | H98: =IFERROR(G98/$C$95,0) -> 0
E99: =SUMIF(类目品牌市占率!AO:AO,D:D,类目品牌市占率!AR:AR) -> 0 | F99: =IFERROR(E99/$B$95,0) -> 0 | G99: =SUMIF(类目品牌市占率!AO:AO,D:D,类目品牌市占率!AV:AV) -> 0 | H99: =IFERROR(G99/$C$95,0) -> 0
A100: 总计 | B100: / | C100: / | D100: / | E100: =SUM(E95:E99) -> 0 | F100: =IFERROR(E100/B95,0) -> 0 | G100: =SUM(G95:G99) -> 0 | H100: =IFERROR(G100/C95,0) -> 0
A102: 过去四年市场销量复合增长情况 | H102: 过去两年市场销售额复合增长情况
A103: 月份 | B103: 过去4年销量明细 | F103: 年复合增长率 | G103: 年均复合增长率 | H103: 过去2年销售额明细 | J103: 年复合增长率 | K103: 年均复合增长率
B104: 2019年 | C104: 2020年 | D104: 2021年 | E104: 2022年 | H104: 2021年 | I104: 2022年
A105: 1 | B105: =IFERROR(每月市场趋势!B3+每月市场趋势!G3+每月市场趋势!L3+每月市场趋势!Q3,0) -> 0 | C105: =IFERROR(每月市场趋势!B15+每月市场趋势!G15+每月市场趋势!L15+每月市场趋势!Q15,0) -> 0 | D105: =IFERROR(每月市场趋势!B27+每月市场趋势!G27+每月市场趋势!L27+每月市场趋势!Q27,0) -> 0 | E105: =IFERROR(每月市场趋势!B39+每月市场趋势!G39+每月市场趋势!L39+每月市场趋势!Q39,0) -> 0 | F105: =EXP(LN(E105/B105/4)-1) -> #DIV/0! | G105: =POWER(E105/B105,1/4)-1 -> #DIV/0! | H105: =IFERROR(每月市场趋势!C27+每月市场趋势!H27+每月市场趋势!M27+每月市场趋势!R27,0) -> 0 | I105: =IFERROR(每月市场趋势!C39+每月市场趋势!H39+每月市场趋势!M39+每月市场趋势!R39,0) -> 0 | J105: =EXP(LN(I105/H105/2)-1) -> #DIV/0! | K105: =POWER(I105/H105,1/2)-1 -> #DIV/0!
...

Sheet 市场预估
A1: 2023年XXX市场概况预测及XXX目标
A2: 整体市场预估 | H2: XXX市占率&市场份额目标
A3: 月份 | B3: 2022年市场容量 | C3: 过去4年平均复合增长 | D3: 2023年预测市场容量 | E3: 2022年市场份额 | F3: 过去两年复合增长 | G3: 2023年预测市场份额 | H3: 2022年销量 | I3: 2022年市占率 | J3: 市占率增长目标 | K3: 目标市占率 | L3: 2023年销量 | M3: 销量同比 | N3: 2022年销售额 | O3: 2022年市场份额 | P3: 市占份额增长目标 | Q3: 目标市场份额占比 | R3: 2023年销售额 | S3: 销售额同比
A4: 1 | B4: =SUMIFS(市场概况!C:C,市场概况!A:A,"2022",市场概况!B:B,A:A) -> 0 | C4: 0.17695553 | D4: =IFERROR(B4+B4*C4,0) -> 0 | E4: =SUMIFS(市场概况!F:F,市场概况!A:A,"2022",市场概况!B:B,A:A) -> 0 | F4: 0.29045724 | G4: =IFERROR(E4+E4*F4,0) -> 0 | H4: =市场概况!C48 -> 0 | I4: =市场概况!D48 -> 0 | J4: =IFERROR((K4-I4)/I4,0) -> 0 | K4: =IFERROR(L4/D4,0) -> 0 | L4: =IFERROR(H4+H4*市场概况!E121,0) -> 0 | M4: =IFERROR((L4-H4)/H4,0) -> 0 | N4: =市场概况!G48 -> 0 | O4: =市场概况!H48 -> 0 | P4: =IFERROR((Q4-O4)/O4,0) -> 0 | Q4: =IFERROR(R4/G4,0) -> 0 | R4: =IFERROR(N4*(1+市场概况!L121),0) -> 0 | S4: =IFERROR((R4-N4)/N4,0) -> 0
A5: 2 | B5: =SUMIFS(市场概况!C:C,市场概况!A:A,"2022",市场概况!B:B,A:A) -> 0 | C5: 0.1410231 | D5: =IFERROR(B5+B5*C5,0) -> 0 | E5: =SUMIFS(市场概况!F:F,市场概况!A:A,"2022",市场概况!B:B,A:A) -> 0 | F5: 0.14026569 | G5: =IFERROR(E5+E5*F5,0) -> 0 | H5: =市场概况!C49 -> 0 | I5: =市场概况!D49 -> 0 | J5: =IFERROR((K5-I5)/I5,0) -> 0 | K5: =IFERROR(L5/D5,0) -> 0 | L5: =IFERROR(H5+H5*市场概况!E122,0) -> 0 | M5: =IFERROR((L5-H5)/H5,0) -> 0 | N5: =市场概况!G49 -> 0 | O5: =市场概况!H49 -> 0 | P5: =IFERROR((Q5-O5)/O5,0) -> 0 | Q5: =IFERROR(R5/G5,0) -> 0 | R5: =IFERROR(N5*(1+市场概况!L122),0) -> 0 | S5: =IFERROR((R5-N5)/N5,0) -> 0
A6: 3 | B6: =SUMIFS(市场概况!C:C,市场概况!A:A,"2022",市场概况!B:B,A:A) -> 0 | C6: 0.061641991 | D6: =IFERROR(B6+B6*C6,0) -> 0 | E6: =SUMIFS(市场概况!F:F,市场概况!A:A,"2022",市场概况!B:B,A:A) -> 0 | F6: 0.50149636 | G6: =IFERROR(E6+E6*F6,0) -> 0 | H6: =市场概况!C50 -> 0 | I6: =市场概况!D50 -> 0 | J6: =IFERROR((K6-I6)/I6,0) -> 0 | K6: =IFERROR(L6/D6,0) -> 0 | L6: =IFERROR(H6+H6*市场概况!E123,0) -> 0 | M6: =IFERROR((L6-H6)/H6,0) -> 0 | N6: =市场概况!G50 -> 0 | O6: =市场概况!H50 -> 0 | P6: =IFERROR((Q6-O6)/O6,0) -> 0 | Q6: =IFERROR(R6/G6,0) -> 0 | R6: =IFERROR(N6*(1+市场概况!L123),0) -> 0 | S6: =IFERROR((R6-N6)/N6,0) -> 0
A7: 4 | B7: =SUMIFS(市场概况!C:C,市场概况!A:A,"2022",市场概况!B:B,A:A) -> 0 | C7: 0.058809533 | D7: =IFERROR(B7+B7*C7,0) -> 0 | E7: =SUMIFS(市场概况!F:F,市场概况!A:A,"2022",市场概况!B:B,A:A) -> 0 | F7: 0.26601202 | G7: =IFERROR(E7+E7*F7,0) -> 0 | H7: =市场概况!C51 -> 0 | I7: =市场概况!D51 -> 0 | J7: =IFERROR((K7-I7)/I7,0) -> 0 | K7: =IFERROR(L7/D7,0) -> 0 | L7: =IFERROR(H7+H7*市场概况!E124,0) -> 0 | M7: =IFERROR((L7-H7)/H7,0) -> 0 | N7: =市场概况!G51 -> 0 | O7: =市场概况!H51 -> 0 | P7: =IFERROR((Q7-O7)/O7,0) -> 0 | Q7: =IFERROR(R7/G7,0) -> 0 | R7: =IFERROR(N7*(1+市场概况!L124),0) -> 0 | S7: =IFERROR((R7-N7)/N7,0) -> 0
A8: 5 | B8: =SUMIFS(市场概况!C:C,市场概况!A:A,"2022",市场概况!B:B,A:A) -> 0 | C8: 0.15930865 | D8: =IFERROR(B8+B8*C8,0) -> 0 | E8: =SUMIFS(市场概况!F:F,市场概况!A:A,"2022",市场概况!B:B,A:A) -> 0 | F8: 0.44930666 | G8: =IFERROR(E8+E8*F8,0) -> 0 | H8: =市场概况!C52 -> 0 | I8: =市场概况!D52 -> 0 | J8: =IFERROR((K8-I8)/I8,0) -> 0 | K8: =IFERROR(L8/D8,0) -> 0 | L8: =IFERROR(H8+H8*市场概况!E125,0) -> 0 | M8: =IFERROR((L8-H8)/H8,0) -> 0 | N8: =市场概况!G52 -> 0 | O8: =市场概况!H52 -> 0 | P8: =IFERROR((Q8-O8)/O8,0) -> 0 | Q8: =IFERROR(R8/G8,0) -> 0 | R8: =IFERROR(N8*(1+市场概况!L125),0) -> 0 | S8: =IFERROR((R8-N8)/N8,0) -> 0
A9: 6 | B9: =SUMIFS(市场概况!C:C,市场概况!A:A,"2022",市场概况!B:B,A:A) -> 0 | C9: 0.10132656 | D9: =IFERROR(B9+B9*C9,0) -> 0 | E9: =SUMIFS(市场概况!F:F,市场概况!A:A,"2022",市场概况!B:B,A:A) -> 0 | F9: 0.054028608 | G9: =IFERROR(E9+E9*F9,0) -> 0 | H9: =市场概况!C53 -> 0 | I9: =市场概况!D53 -> 0 | J9: =IFERROR((K9-I9)/I9,0) -> 0 | K9: =IFERROR(L9/D9,0) -> 0 | L9: =IFERROR(H9+H9*市场概况!E126,0) -> 0 | M9: =IFERROR((L9-H9)/H9,0) -> 0 | N9: =市场概况!G53 -> 0 | O9: =市场概况!H53 -> 0 | P9: =IFERROR((Q9-O9)/O9,0) -> 0 | Q9: =IFERROR(R9/G9,0) -> 0 | R9: =IFERROR(N9*(1+市场概况!L126),0) -> 0 | S9: =IFERROR((R9-N9)/N9,0) -> 0
A10: 7 | B10: =SUMIFS(市场概况!C:C,市场概况!A:A,"2022",市场概况!B:B,A:A) -> 0 | C10: 0.14267549 | D10: =IFERROR(B10+B10*C10,0) -> 0 | E10: =SUMIFS(市场概况!F:F,市场概况!A:A,"2022",市场概况!B:B,A:A) -> 0 | F10: 0.35248223 | G10: =IFERROR(E10+E10*F10,0) -> 0 | H10: =市场概况!C54 -> 0 | I10: =市场概况!D54 -> 0 | J10: =IFERROR((K10-I10)/I10,0) -> 0 | K10: =IFERROR(L10/D10,0) -> 0 | L10: =IFERROR(H10+H10*市场概况!E127,0) -> 0 | M10: =IFERROR((L10-H10)/H10,0) -> 0 | N10: =市场概况!G54 -> 0 | O10: =市场概况!H54 -> 0 | P10: =IFERROR((Q10-O10)/O10,0) -> 0 | Q10: =IFERROR(R10/G10,0) -> 0 | R10: =IFERROR(N10*(1+市场概况!L127),0) -> 0 | S10: =IFERROR((R10-N10)/N10,0) -> 0
A11: 8 | B11: =SUMIFS(市场概况!C:C,市场概况!A:A,"2022",市场概况!B:B,A:A) -> 0 | C11: 0.090078803 | D11: =IFERROR(B11+B11*C11,0) -> 0 | E11: =SUMIFS(市场概况!F:F,市场概况!A:A,"2022",市场概况!B:B,A:A) -> 0 | F11: 0.23679859 | G11: =IFERROR(E11+E11*F11,0) -> 0 | H11: =市场概况!C55 -> 0 | I11: =市场概况!D55 -> 0 | J11: =IFERROR((K11-I11)/I11,0) -> 0 | K11: =IFERROR(L11/D11,0) -> 0 | L11: =IFERROR(H11+H11*市场概况!E128,0) -> 0 | M11: =IFERROR((L11-H11)/H11,0) -> 0 | N11: =市场概况!G55 -> 0 | O11: =市场概况!H55 -> 0 | P11: =IFERROR((Q11-O11)/O11,0) -> 0 | Q11: =IFERROR(R11/G11,0) -> 0 | R11: =IFERROR(N11*(1+市场概况!L128),0) -> 0 | S11: =IFERROR((R11-N11)/N11,0) -> 0
A12: 9 | B12: =SUMIFS(市场概况!C:C,市场概况!A:A,"2022",市场概况!B:B,A:A) -> 0 | C12: 0.043828982 | D12: =IFERROR(B12+B12*C12,0) -> 0 | E12: =SUMIFS(市场概况!F:F,市场概况!A:A,"2022",市场概况!B:B,A:A) -> 0 | F12: 0.40688876 | G12: =IFERROR(E12+E12*F12,0) -> 0 | H12: =市场概况!C56 -> 0 | I12: =市场概况!D56 -> 0 | J12: =IFERROR((K12-I12)/I12,0) -> 0 | K12: =IFERROR(L12/D12,0) -> 0 | L12: =IFERROR(H12+H12*市场概况!E129,0) -> 0 | M12: =IFERROR((L12-H12)/H12,0) -> 0 | N12: =市场概况!G56 -> 0 | O12: =市场概况!H56 -> 0 | P12: =IFERROR((Q12-O12)/O12,0) -> 0 | Q12: =IFERROR(R12/G12,0) -> 0 | R12: =IFERROR(N12*(1+市场概况!L129),0) -> 0 | S12: =IFERROR((R12-N12)/N12,0) -> 0
A13: 10 | B13: =SUMIFS(市场概况!C:C,市场概况!A:A,"2022",市场概况!B:B,A:A) -> 0 | C13: 0.05177335 | D13: =IFERROR(B13+B13*C13,0) -> 0 | E13: =SUMIFS(市场概况!F:F,市场概况!A:A,"2022",市场概况!B:B,A:A) -> 0 | F13: 0.69580486 | G13: =IFERROR(E13+E13*F13,0) -> 0 | H13: =市场概况!C57 -> 0 | I13: =市场概况!D57 -> 0 | J13: =IFERROR((K13-I13)/I13,0) -> 0 | K13: =IFERROR(L13/D13,0) -> 0 | L13: =IFERROR(H13+H13*市场概况!E130,0) -> 0 | M13: =IFERROR((L13-H13)/H13,0) -> 0 | N13: =市场概况!G57 -> 0 | O13: =市场概况!H57 -> 0 | P13: =IFERROR((Q13-O13)/O13,0) -> 0 | Q13: =IFERROR(R13/G13,0) -> 0 | R13: =IFERROR(N13*(1+市场概况!L130),0) -> 0 | S13: =IFERROR((R13-N13)/N13,0) -> 0
A14: 11 | B14: =SUMIFS(市场概况!C:C,市场概况!A:A,"2022",市场概况!B:B,A:A) -> 0 | C14: 0.063787089 | D14: =IFERROR(B14+B14*C14,0) -> 0 | E14: =SUMIFS(市场概况!F:F,市场概况!A:A,"2022",市场概况!B:B,A:A) -> 0 | F14: 0.4783983 | G14: =IFERROR(E14+E14*F14,0) -> 0 | H14: =市场概况!C58 -> 0 | I14: =市场概况!D58 -> 0 | J14: =IFERROR((K14-I14)/I14,0) -> 0 | K14: =IFERROR(L14/D14,0) -> 0 | L14: =IFERROR(H14+H14*市场概况!E131,0) -> 0 | M14: =IFERROR((L14-H14)/H14,0) -> 0 | N14: =市场概况!G58 -> 0 | O14: =市场概况!H58 -> 0 | P14: =IFERROR((Q14-O14)/O14,0) -> 0 | Q14: =IFERROR(R14/G14,0) -> 0 | R14: =IFERROR(N14*(1+市场概况!L131),0) -> 0 | S14: =IFERROR((R14-N14)/N14,0) -> 0
A15: 12 | B15: =SUMIFS(市场概况!C:C,市场概况!A:A,"2022",市场概况!B:B,A:A) -> 0 | C15: 0.10788764 | D15: =IFERROR(B15+B15*C15,0) -> 0 | E15: =SUMIFS(市场概况!F:F,市场概况!A:A,"2022",市场概况!B:B,A:A) -> 0 | F15: 0.32759829 | G15: =IFERROR(E15+E15*F15,0) -> 0 | H15: =市场概况!C59 -> 0 | I15: =市场概况!D59 -> 0 | J15: =IFERROR((K15-I15)/I15,0) -> 0 | K15: =IFERROR(L15/D15,0) -> 0 | L15: =IFERROR(H15+H15*市场概况!E132,0) -> 0 | M15: =IFERROR((L15-H15)/H15,0) -> 0 | N15: =市场概况!G59 -> 0 | O15: =市场概况!H59 -> 0 | P15: =IFERROR((Q15-O15)/O15,0) -> 0 | Q15: =IFERROR(R15/G15,0) -> 0 | R15: =IFERROR(N15*(1+市场概况!L132),0) -> 0 | S15: =IFERROR((R15-N15)/N15,0) -> 0
A16: 总计 | B16: =SUM(B4:B15) -> 0 | C16: =IFERROR(POWER(SUM(市场概况!E105:E116)/SUM(市场概况!B105:B116),1/4)-1,0) -> 0 | D16: =SUM(D4:D15) -> 0 | E16: =SUM(E4:E15) -> 0 | F16: =IFERROR(POWER(SUM(市场概况!I105:I116)/SUM(市场概况!H105:H116),1/2)-1,0) -> 0 | G16: =SUM(G4:G15) -> 0 | H16: =SUM(H4:H15) -> 0 | I16: =IFERROR(H16/B16,0) -> 0 | J16: =IFERROR((K16-I16)/I16,0) -> 0 | K16: =IFERROR(L16/D16,0) -> 0 | L16: =SUM(L4:L15) -> 0 | M16: =IFERROR((L16-H16)/H16,0) -> 0 | N16: =SUM(N4:N15) -> 0 | O16: =AVERAGE(O4:O15) -> 0 | P16: =IFERROR((Q16-O16)/O16,0) -> 0 | Q16: =IFERROR(R16/G16,0) -> 0 | R16: =SUM(R4:R15) -> 0 | S16: =IFERROR((R16-N16)/N16,0) -> 0

Sheet 单品目标年销量
A1: 2023年 - XXX - 细分ASIN销售额
A2: 产品大类 | B2: 产品系列 | C2: 产品ASIN | D2: 型号系列 | E2: 产品中文名 | F2: 客单价 | G2: 2021年销量 | H2: 2021年销量占比 | I2: 2022年销量 | J2: 2022年销量占比 | K2: 销量同比 | L2: 销量比例同比 | M2: 销量占比复合增长 | N2: 2021年销售额 | O2: 2021年销售额占比 | P2: 2022年销售额 | Q2: 2022年销售额占比 | R2: 销售额同比 | S2: 销售额比例同比 | T2: 销售额占比复合增长 | U2: 2023年目标销量 | V2: 目标销量占比 | W2: 2023年目标销售额 | X2: 2023年目标销售额占比
G3: =SUMIF('船长每月数据(2022年)'!E:E,C:C,'船长每月数据(2022年)'!P:P) -> 0 | H3: =IFERROR(G3/SUM('船长每月数据(2022年)'!P2:P1077),0) -> 0 | I3: =SUMIF('船长每月数据(2023年)'!E:E,C:C,'船长每月数据(2023年)'!P:P) -> 0 | J3: =IFERROR(I3/SUM('船长每月数据(2023年)'!P2:P1002),0) -> 0 | K3: =IFERROR((I3-G3)/G3,0) -> 0 | L3: =IFERROR((J3-H3)/H3,0) -> 0 | M3: =IFERROR(EXP(LN(J3/H3/2)-1),0) -> 0 | N3: =SUMIF('船长每月数据(2022年)'!E:E,C:C,'船长每月数据(2022年)'!R:R) -> 0 | O3: =IFERROR(N3/SUM('船长每月数据(2022年)'!R2:R1077),0) -> 0 | P3: =SUMIF('船长每月数据(2023年)'!E:E,C:C,'船长每月数据(2023年)'!R:R) -> 0 | Q3: =IFERROR(P3/SUM('船长每月数据(2023年)'!R2:R1002),0) -> 0 | R3: =IFERROR((P3-N3)/N3,0) -> 0 | S3: =IFERROR((Q3-O3)/O3,0) -> 0 | T3: =IFERROR(EXP(LN(Q3/O3/2)-1),0) -> 0 | U3: =IFERROR(市场预估!$L$16*(J3+J3*M3)/1.2,0) -> 0 | V3: =IFERROR(U3/市场预估!$L$16,0) -> 0 | W3: =IFERROR(U3*F3,0) -> 0 | X3: =IFERROR(W3/年目标!$E$15,0) -> 0
G4: =SUMIF('船长每月数据(2022年)'!E:E,C:C,'船长每月数据(2022年)'!P:P) -> 0 | H4: =IFERROR(G4/SUM('船长每月数据(2022年)'!P3:P1078),0) -> 0 | I4: =SUMIF('船长每月数据(2023年)'!E:E,C:C,'船长每月数据(2023年)'!P:P) -> 0 | J4: =IFERROR(I4/SUM('船长每月数据(2023年)'!P3:P1003),0) -> 0 | K4: =IFERROR((I4-G4)/G4,0) -> 0 | L4: =IFERROR((J4-H4)/H4,0) -> 0 | M4: =IFERROR(EXP(LN(J4/H4/2)-1),0) -> 0 | N4: =SUMIF('船长每月数据(2022年)'!E:E,C:C,'船长每月数据(2022年)'!R:R) -> 0 | O4: =IFERROR(N4/SUM('船长每月数据(2022年)'!R3:R1078),0) -> 0 | P4: =SUMIF('船长每月数据(2023年)'!E:E,C:C,'船长每月数据(2023年)'!R:R) -> 0 | Q4: =IFERROR(P4/SUM('船长每月数据(2023年)'!R3:R1003),0) -> 0 | R4: =IFERROR((P4-N4)/N4,0) -> 0 | S4: =IFERROR((Q4-O4)/O4,0) -> 0 | T4: =IFERROR(EXP(LN(Q4/O4/2)-1),0) -> 0 | U4: =IFERROR(市场预估!$L$16*(J4+J4*M4)/1.2,0) -> 0 | V4: =IFERROR(U4/市场预估!$L$16,0) -> 0 | W4: =IFERROR(U4*F4,0) -> 0 | X4: =IFERROR(W4/年目标!$E$15,0) -> 0
G5: =SUMIF('船长每月数据(2022年)'!E:E,C:C,'船长每月数据(2022年)'!P:P) -> 0 | H5: =IFERROR(G5/SUM('船长每月数据(2022年)'!P4:P1079),0) -> 0 | I5: =SUMIF('船长每月数据(2023年)'!E:E,C:C,'船长每月数据(2023年)'!P:P) -> 0 | J5: =IFERROR(I5/SUM('船长每月数据(2023年)'!P4:P1004),0) -> 0 | K5: =IFERROR((I5-G5)/G5,0) -> 0 | L5: =IFERROR((J5-H5)/H5,0) -> 0 | M5: =IFERROR(EXP(LN(J5/H5/2)-1),0) -> 0 | N5: =SUMIF('船长每月数据(2022年)'!E:E,C:C,'船长每月数据(2022年)'!R:R) -> 0 | O5: =IFERROR(N5/SUM('船长每月数据(2022年)'!R4:R1079),0) -> 0 | P5: =SUMIF('船长每月数据(2023年)'!E:E,C:C,'船长每月数据(2023年)'!R:R) -> 0 | Q5: =IFERROR(P5/SUM('船长每月数据(2023年)'!R4:R1004),0) -> 0 | R5: =IFERROR((P5-N5)/N5,0) -> 0 | S5: =IFERROR((Q5-O5)/O5,0) -> 0 | T5: =IFERROR(EXP(LN(Q5/O5/2)-1),0) -> 0 | U5: =IFERROR(市场预估!$L$16*(J5+J5*M5)/1.2,0) -> 0 | V5: =IFERROR(U5/市场预估!$L$16,0) -> 0 | W5: =IFERROR(U5*F5,0) -> 0 | X5: =IFERROR(W5/年目标!$E$15,0) -> 0
G6: =SUMIF('船长每月数据(2022年)'!E:E,C:C,'船长每月数据(2022年)'!P:P) -> 0 | H6: =IFERROR(G6/SUM('船长每月数据(2022年)'!P5:P1080),0) -> 0 | I6: =SUMIF('船长每月数据(2023年)'!E:E,C:C,'船长每月数据(2023年)'!P:P) -> 0 | J6: =IFERROR(I6/SUM('船长每月数据(2023年)'!P5:P1005),0) -> 0 | K6: =IFERROR((I6-G6)/G6,0) -> 0 | L6: =IFERROR((J6-H6)/H6,0) -> 0 | M6: =IFERROR(EXP(LN(J6/H6/2)-1),0) -> 0 | N6: =SUMIF('船长每月数据(2022年)'!E:E,C:C,'船长每月数据(2022年)'!R:R) -> 0 | O6: =IFERROR(N6/SUM('船长每月数据(2022年)'!R5:R1080),0) -> 0 | P6: =SUMIF('船长每月数据(2023年)'!E:E,C:C,'船长每月数据(2023年)'!R:R) -> 0 | Q6: =IFERROR(P6/SUM('船长每月数据(2023年)'!R5:R1005),0) -> 0 | R6: =IFERROR((P6-N6)/N6,0) -> 0 | S6: =IFERROR((Q6-O6)/O6,0) -> 0 | T6: =IFERROR(EXP(LN(Q6/O6/2)-1),0) -> 0 | U6: =IFERROR(市场预估!$L$16*(J6+J6*M6)/1.2,0) -> 0 | V6: =IFERROR(U6/市场预估!$L$16,0) -> 0 | W6: =IFERROR(U6*F6,0) -> 0 | X6: =IFERROR(W6/年目标!$E$15,0) -> 0
G7: =SUMIF('船长每月数据(2022年)'!E:E,C:C,'船长每月数据(2022年)'!P:P) -> 0 | H7: =IFERROR(G7/SUM('船长每月数据(2022年)'!P6:P1081),0) -> 0 | I7: =SUMIF('船长每月数据(2023年)'!E:E,C:C,'船长每月数据(2023年)'!P:P) -> 0 | J7: =IFERROR(I7/SUM('船长每月数据(2023年)'!P6:P1006),0) -> 0 | K7: =IFERROR((I7-G7)/G7,0) -> 0 | L7: =IFERROR((J7-H7)/H7,0) -> 0 | M7: =IFERROR(EXP(LN(J7/H7/2)-1),0) -> 0 | N7: =SUMIF('船长每月数据(2022年)'!E:E,C:C,'船长每月数据(2022年)'!R:R) -> 0 | O7: =IFERROR(N7/SUM('船长每月数据(2022年)'!R6:R1081),0) -> 0 | P7: =SUMIF('船长每月数据(2023年)'!E:E,C:C,'船长每月数据(2023年)'!R:R) -> 0 | Q7: =IFERROR(P7/SUM('船长每月数据(2023年)'!R6:R1006),0) -> 0 | R7: =IFERROR((P7-N7)/N7,0) -> 0 | S7: =IFERROR((Q7-O7)/O7,0) -> 0 | T7: =IFERROR(EXP(LN(Q7/O7/2)-1),0) -> 0 | U7: =IFERROR(市场预估!$L$16*(J7+J7*M7)/1.2,0) -> 0 | V7: =IFERROR(U7/市场预估!$L$16,0) -> 0 | W7: =IFERROR(U7*F7,0) -> 0 | X7: =IFERROR(W7/年目标!$E$15,0) -> 0
G8: =SUMIF('船长每月数据(2022年)'!E:E,C:C,'船长每月数据(2022年)'!P:P) -> 0 | H8: =IFERROR(G8/SUM('船长每月数据(2022年)'!P7:P1082),0) -> 0 | I8: =SUMIF('船长每月数据(2023年)'!E:E,C:C,'船长每月数据(2023年)'!P:P) -> 0 | J8: =IFERROR(I8/SUM('船长每月数据(2023年)'!P7:P1007),0) -> 0 | K8: =IFERROR((I8-G8)/G8,0) -> 0 | L8: =IFERROR((J8-H8)/H8,0) -> 0 | M8: =IFERROR(EXP(LN(J8/H8/2)-1),0) -> 0 | N8: =SUMIF('船长每月数据(2022年)'!E:E,C:C,'船长每月数据(2022年)'!R:R) -> 0 | O8: =IFERROR(N8/SUM('船长每月数据(2022年)'!R7:R1082),0) -> 0 | P8: =SUMIF('船长每月数据(2023年)'!E:E,C:C,'船长每月数据(2023年)'!R:R) -> 0 | Q8: =IFERROR(P8/SUM('船长每月数据(2023年)'!R7:R1007),0) -> 0 | R8: =IFERROR((P8-N8)/N8,0) -> 0 | S8: =IFERROR((Q8-O8)/O8,0) -> 0 | T8: =IFERROR(EXP(LN(Q8/O8/2)-1),0) -> 0 | U8: =IFERROR(市场预估!$L$16*(J8+J8*M8)/1.2,0) -> 0 | V8: =IFERROR(U8/市场预估!$L$16,0) -> 0 | W8: =IFERROR(U8*F8,0) -> 0 | X8: =IFERROR(W8/年目标!$E$15,0) -> 0
G9: =SUMIF('船长每月数据(2022年)'!E:E,C:C,'船长每月数据(2022年)'!P:P) -> 0 | H9: =IFERROR(G9/SUM('船长每月数据(2022年)'!P8:P1083),0) -> 0 | I9: =SUMIF('船长每月数据(2023年)'!E:E,C:C,'船长每月数据(2023年)'!P:P) -> 0 | J9: =IFERROR(I9/SUM('船长每月数据(2023年)'!P8:P1008),0) -> 0 | K9: =IFERROR((I9-G9)/G9,0) -> 0 | L9: =IFERROR((J9-H9)/H9,0) -> 0 | M9: =IFERROR(EXP(LN(J9/H9/2)-1),0) -> 0 | N9: =SUMIF('船长每月数据(2022年)'!E:E,C:C,'船长每月数据(2022年)'!R:R) -> 0 | O9: =IFERROR(N9/SUM('船长每月数据(2022年)'!R8:R1083),0) -> 0 | P9: =SUMIF('船长每月数据(2023年)'!E:E,C:C,'船长每月数据(2023年)'!R:R) -> 0 | Q9: =IFERROR(P9/SUM('船长每月数据(2023年)'!R8:R1008),0) -> 0 | R9: =IFERROR((P9-N9)/N9,0) -> 0 | S9: =IFERROR((Q9-O9)/O9,0) -> 0 | T9: =IFERROR(EXP(LN(Q9/O9/2)-1),0) -> 0 | U9: =IFERROR(市场预估!$L$16*(J9+J9*M9)/1.2,0) -> 0 | V9: =IFERROR(U9/市场预估!$L$16,0) -> 0 | W9: =IFERROR(U9*F9,0) -> 0 | X9: =IFERROR(W9/年目标!$E$15,0) -> 0
G10: =SUMIF('船长每月数据(2022年)'!E:E,C:C,'船长每月数据(2022年)'!P:P) -> 0 | H10: =IFERROR(G10/SUM('船长每月数据(2022年)'!P9:P1084),0) -> 0 | I10: =SUMIF('船长每月数据(2023年)'!E:E,C:C,'船长每月数据(2023年)'!P:P) -> 0 | J10: =IFERROR(I10/SUM('船长每月数据(2023年)'!P9:P1009),0) -> 0 | K10: =IFERROR((I10-G10)/G10,0) -> 0 | L10: =IFERROR((J10-H10)/H10,0) -> 0 | M10: =IFERROR(EXP(LN(J10/H10/2)-1),0) -> 0 | N10: =SUMIF('船长每月数据(2022年)'!E:E,C:C,'船长每月数据(2022年)'!R:R) -> 0 | O10: =IFERROR(N10/SUM('船长每月数据(2022年)'!R9:R1084),0) -> 0 | P10: =SUMIF('船长每月数据(2023年)'!E:E,C:C,'船长每月数据(2023年)'!R:R) -> 0 | Q10: =IFERROR(P10/SUM('船长每月数据(2023年)'!R9:R1009),0) -> 0 | R10: =IFERROR((P10-N10)/N10,0) -> 0 | S10: =IFERROR((Q10-O10)/O10,0) -> 0 | T10: =IFERROR(EXP(LN(Q10/O10/2)-1),0) -> 0 | U10: =IFERROR(市场预估!$L$16*(J10+J10*M10)/1.2,0) -> 0 | V10: =IFERROR(U10/市场预估!$L$16,0) -> 0 | W10: =IFERROR(U10*F10,0) -> 0 | X10: =IFERROR(W10/年目标!$E$15,0) -> 0
G11: =SUMIF('船长每月数据(2022年)'!E:E,C:C,'船长每月数据(2022年)'!P:P) -> 0 | H11: =IFERROR(G11/SUM('船长每月数据(2022年)'!P10:P1085),0) -> 0 | I11: =SUMIF('船长每月数据(2023年)'!E:E,C:C,'船长每月数据(2023年)'!P:P) -> 0 | J11: =IFERROR(I11/SUM('船长每月数据(2023年)'!P10:P1010),0) -> 0 | K11: =IFERROR((I11-G11)/G11,0) -> 0 | L11: =IFERROR((J11-H11)/H11,0) -> 0 | M11: =IFERROR(EXP(LN(J11/H11/2)-1),0) -> 0 | N11: =SUMIF('船长每月数据(2022年)'!E:E,C:C,'船长每月数据(2022年)'!R:R) -> 0 | O11: =IFERROR(N11/SUM('船长每月数据(2022年)'!R10:R1085),0) -> 0 | P11: =SUMIF('船长每月数据(2023年)'!E:E,C:C,'船长每月数据(2023年)'!R:R) -> 0 | Q11: =IFERROR(P11/SUM('船长每月数据(2023年)'!R10:R1010),0) -> 0 | R11: =IFERROR((P11-N11)/N11,0) -> 0 | S11: =IFERROR((Q11-O11)/O11,0) -> 0 | T11: =IFERROR(EXP(LN(Q11/O11/2)-1),0) -> 0 | U11: =IFERROR(市场预估!$L$16*(J11+J11*M11)/1.2,0) -> 0 | V11: =IFERROR(U11/市场预估!$L$16,0) -> 0 | W11: =IFERROR(U11*F11,0) -> 0 | X11: =IFERROR(W11/年目标!$E$15,0) -> 0
G12: =SUMIF('船长每月数据(2022年)'!E:E,C:C,'船长每月数据(2022年)'!P:P) -> 0 | H12: =IFERROR(G12/SUM('船长每月数据(2022年)'!P11:P1086),0) -> 0 | I12: =SUMIF('船长每月数据(2023年)'!E:E,C:C,'船长每月数据(2023年)'!P:P) -> 0 | J12: =IFERROR(I12/SUM('船长每月数据(2023年)'!P11:P1011),0) -> 0 | K12: =IFERROR((I12-G12)/G12,0) -> 0 | L12: =IFERROR((J12-H12)/H12,0) -> 0 | M12: =IFERROR(EXP(LN(J12/H12/2)-1),0) -> 0 | N12: =SUMIF('船长每月数据(2022年)'!E:E,C:C,'船长每月数据(2022年)'!R:R) -> 0 | O12: =IFERROR(N12/SUM('船长每月数据(2022年)'!R11:R1086),0) -> 0 | P12: =SUMIF('船长每月数据(2023年)'!E:E,C:C,'船长每月数据(2023年)'!R:R) -> 0 | Q12: =IFERROR(P12/SUM('船长每月数据(2023年)'!R11:R1011),0) -> 0 | R12: =IFERROR((P12-N12)/N12,0) -> 0 | S12: =IFERROR((Q12-O12)/O12,0) -> 0 | T12: =IFERROR(EXP(LN(Q12/O12/2)-1),0) -> 0 | U12: =IFERROR(市场预估!$L$16*(J12+J12*M12)/1.2,0) -> 0 | V12: =IFERROR(U12/市场预估!$L$16,0) -> 0 | W12: =IFERROR(U12*F12,0) -> 0 | X12: =IFERROR(W12/年目标!$E$15,0) -> 0
G13: =SUMIF('船长每月数据(2022年)'!E:E,C:C,'船长每月数据(2022年)'!P:P) -> 0 | H13: =IFERROR(G13/SUM('船长每月数据(2022年)'!P12:P1087),0) -> 0 | I13: =SUMIF('船长每月数据(2023年)'!E:E,C:C,'船长每月数据(2023年)'!P:P) -> 0 | J13: =IFERROR(I13/SUM('船长每月数据(2023年)'!P12:P1012),0) -> 0 | K13: =IFERROR((I13-G13)/G13,0) -> 0 | L13: =IFERROR((J13-H13)/H13,0) -> 0 | M13: =IFERROR(EXP(LN(J13/H13/2)-1),0) -> 0 | N13: =SUMIF('船长每月数据(2022年)'!E:E,C:C,'船长每月数据(2022年)'!R:R) -> 0 | O13: =IFERROR(N13/SUM('船长每月数据(2022年)'!R12:R1087),0) -> 0 | P13: =SUMIF('船长每月数据(2023年)'!E:E,C:C,'船长每月数据(2023年)'!R:R) -> 0 | Q13: =IFERROR(P13/SUM('船长每月数据(2023年)'!R12:R1012),0) -> 0 | R13: =IFERROR((P13-N13)/N13,0) -> 0 | S13: =IFERROR((Q13-O13)/O13,0) -> 0 | T13: =IFERROR(EXP(LN(Q13/O13/2)-1),0) -> 0 | U13: =IFERROR(市场预估!$L$16*(J13+J13*M13)/1.2,0) -> 0 | V13: =IFERROR(U13/市场预估!$L$16,0) -> 0 | W13: =IFERROR(U13*F13,0) -> 0 | X13: =IFERROR(W13/年目标!$E$15,0) -> 0
G14: =SUMIF('船长每月数据(2022年)'!E:E,C:C,'船长每月数据(2022年)'!P:P) -> 0 | H14: =IFERROR(G14/SUM('船长每月数据(2022年)'!P13:P1088),0) -> 0 | I14: =SUMIF('船长每月数据(2023年)'!E:E,C:C,'船长每月数据(2023年)'!P:P) -> 0 | J14: =IFERROR(I14/SUM('船长每月数据(2023年)'!P13:P1013),0) -> 0 | K14: =IFERROR((I14-G14)/G14,0) -> 0 | L14: =IFERROR((J14-H14)/H14,0) -> 0 | M14: =IFERROR(EXP(LN(J14/H14/2)-1),0) -> 0 | N14: =SUMIF('船长每月数据(2022年)'!E:E,C:C,'船长每月数据(2022年)'!R:R) -> 0 | O14: =IFERROR(N14/SUM('船长每月数据(2022年)'!R13:R1088),0) -> 0 | P14: =SUMIF('船长每月数据(2023年)'!E:E,C:C,'船长每月数据(2023年)'!R:R) -> 0 | Q14: =IFERROR(P14/SUM('船长每月数据(2023年)'!R13:R1013),0) -> 0 | R14: =IFERROR((P14-N14)/N14,0) -> 0 | S14: =IFERROR((Q14-O14)/O14,0) -> 0 | T14: =IFERROR(EXP(LN(Q14/O14/2)-1),0) -> 0 | U14: =IFERROR(市场预估!$L$16*(J14+J14*M14)/1.2,0) -> 0 | V14: =IFERROR(J14*(1+M14),0) -> 0 | W14: =IFERROR(U14*F14,0) -> 0 | X14: =IFERROR(W14/年目标!$E$15,0) -> 0
G15: =SUMIF('船长每月数据(2022年)'!E:E,C:C,'船长每月数据(2022年)'!P:P) -> 0 | H15: =IFERROR(G15/SUM('船长每月数据(2022年)'!P14:P1089),0) -> 0 | I15: =SUMIF('船长每月数据(2023年)'!E:E,C:C,'船长每月数据(2023年)'!P:P) -> 0 | J15: =IFERROR(I15/SUM('船长每月数据(2023年)'!P14:P1014),0) -> 0 | K15: =IFERROR((I15-G15)/G15,0) -> 0 | L15: =IFERROR((J15-H15)/H15,0) -> 0 | M15: =IFERROR(EXP(LN(J15/H15/2)-1),0) -> 0 | N15: =SUMIF('船长每月数据(2022年)'!E:E,C:C,'船长每月数据(2022年)'!R:R) -> 0 | O15: =IFERROR(N15/SUM('船长每月数据(2022年)'!R14:R1089),0) -> 0 | P15: =SUMIF('船长每月数据(2023年)'!E:E,C:C,'船长每月数据(2023年)'!R:R) -> 0 | Q15: =IFERROR(P15/SUM('船长每月数据(2023年)'!R14:R1014),0) -> 0 | R15: =IFERROR((P15-N15)/N15,0) -> 0 | S15: =IFERROR((Q15-O15)/O15,0) -> 0 | T15: =IFERROR(EXP(LN(Q15/O15/2)-1),0) -> 0 | U15: =IFERROR(市场预估!$L$16*(J15+J15*M15),0) -> 0 | V15: =IFERROR(J15*(1+M15),0) -> 0 | W15: =IFERROR(U15*F15,0) -> 0 | X15: =IFERROR(W15/年目标!$E$15,0) -> 0
G16: =SUMIF('船长每月数据(2022年)'!E:E,C:C,'船长每月数据(2022年)'!P:P) -> 0 | H16: =IFERROR(G16/SUM('船长每月数据(2022年)'!P17:P1092),0) -> 0 | I16: =SUMIF('船长每月数据(2023年)'!E:E,C:C,'船长每月数据(2023年)'!P:P) -> 0 | J16: =IFERROR(I16/SUM('船长每月数据(2023年)'!P17:P1017),0) -> 0 | K16: =IFERROR((I16-G16)/G16,0) -> 0 | L16: =IFERROR((J16-H16)/H16,0) -> 0 | M16: =IFERROR(EXP(LN(J16/H16/2)-1),0) -> 0 | N16: =SUMIF('船长每月数据(2022年)'!E:E,C:C,'船长每月数据(2022年)'!R:R) -> 0 | O16: =IFERROR(N16/SUM('船长每月数据(2022年)'!R17:R1092),0) -> 0 | P16: =SUMIF('船长每月数据(2023年)'!E:E,C:C,'船长每月数据(2023年)'!R:R) -> 0 | Q16: =IFERROR(P16/SUM('船长每月数据(2023年)'!R17:R1017),0) -> 0 | R16: =IFERROR((P16-N16)/N16,0) -> 0 | S16: =IFERROR((Q16-O16)/O16,0) -> 0 | T16: =IFERROR(EXP(LN(Q16/O16/2)-1),0) -> 0 | U16: =IFERROR(市场预估!$L$16*(J16+J16*M16),0)/1.2 -> 0 | V16: =IFERROR(J16*(1+M16),0) -> 0 | W16: =IFERROR(U16*F16,0) -> 0 | X16: =IFERROR(W16/年目标!$E$15,0) -> 0
G17: =SUMIF('船长每月数据(2022年)'!E:E,C:C,'船长每月数据(2022年)'!P:P) -> 0 | H17: =IFERROR(G17/SUM('船长每月数据(2022年)'!P22:P1097),0) -> 0 | I17: =SUMIF('船长每月数据(2023年)'!E:E,C:C,'船长每月数据(2023年)'!P:P) -> 0 | J17: =IFERROR(I17/SUM('船长每月数据(2023年)'!P22:P1022),0) -> 0 | K17: =IFERROR((I17-G17)/G17,0) -> 0 | L17: =IFERROR((J17-H17)/H17,0) -> 0 | M17: =IFERROR(EXP(LN(J17/H17/2)-1),0) -> 0 | N17: =SUMIF('船长每月数据(2022年)'!E:E,C:C,'船长每月数据(2022年)'!R:R) -> 0 | O17: =IFERROR(N17/SUM('船长每月数据(2022年)'!R22:R1097),0) -> 0 | P17: =SUMIF('船长每月数据(2023年)'!E:E,C:C,'船长每月数据(2023年)'!R:R) -> 0 | Q17: =IFERROR(P17/SUM('船长每月数据(2023年)'!R22:R1022),0) -> 0 | R17: =IFERROR((P17-N17)/N17,0) -> 0 | S17: =IFERROR((Q17-O17)/O17,0) -> 0 | T17: =IFERROR(EXP(LN(Q17/O17/2)-1),0) -> 0 | U17: =IFERROR(市场预估!$L$16*(J17+J17*M17),0)/1.2 -> 0 | V17: =IFERROR(J17*(1+M17),0) -> 0 | W17: =IFERROR(U17*F17,0) -> 0 | X17: =IFERROR(W17/年目标!$E$15,0) -> 0
G18: =SUMIF('船长每月数据(2022年)'!E:E,C:C,'船长每月数据(2022年)'!P:P) -> 0 | H18: =IFERROR(G18/SUM('船长每月数据(2022年)'!P23:P1098),0) -> 0 | I18: =SUMIF('船长每月数据(2023年)'!E:E,C:C,'船长每月数据(2023年)'!P:P) -> 0 | J18: =IFERROR(I18/SUM('船长每月数据(2023年)'!P23:P1023),0) -> 0 | K18: =IFERROR((I18-G18)/G18,0) -> 0 | L18: =IFERROR((J18-H18)/H18,0) -> 0 | M18: =IFERROR(EXP(LN(J18/H18/2)-1),0) -> 0 | N18: =SUMIF('船长每月数据(2022年)'!E:E,C:C,'船长每月数据(2022年)'!R:R) -> 0 | O18: =IFERROR(N18/SUM('船长每月数据(2022年)'!R23:R1098),0) -> 0 | P18: =SUMIF('船长每月数据(2023年)'!E:E,C:C,'船长每月数据(2023年)'!R:R) -> 0 | Q18: =IFERROR(P18/SUM('船长每月数据(2023年)'!R23:R1023),0) -> 0 | R18: =IFERROR((P18-N18)/N18,0) -> 0 | S18: =IFERROR((Q18-O18)/O18,0) -> 0 | T18: =IFERROR(EXP(LN(Q18/O18/2)-1),0) -> 0 | U18: =IFERROR(市场预估!$L$16*(J18+J18*M18),0) -> 0 | V18: =IFERROR(J18*(1+M18),0) -> 0 | W18: =IFERROR(U18*F18,0) -> 0 | X18: =IFERROR(W18/年目标!$E$15,0) -> 0
G19: =SUMIF('船长每月数据(2022年)'!E:E,C:C,'船长每月数据(2022年)'!P:P) -> 0 | H19: =IFERROR(G19/SUM('船长每月数据(2022年)'!P24:P1099),0) -> 0 | I19: =SUMIF('船长每月数据(2023年)'!E:E,C:C,'船长每月数据(2023年)'!P:P) -> 0 | J19: =IFERROR(I19/SUM('船长每月数据(2023年)'!P24:P1024),0) -> 0 | K19: =IFERROR((I19-G19)/G19,0) -> 0 | L19: =IFERROR((J19-H19)/H19,0) -> 0 | M19: =IFERROR(EXP(LN(J19/H19/2)-1),0) -> 0 | N19: =SUMIF('船长每月数据(2022年)'!E:E,C:C,'船长每月数据(2022年)'!R:R) -> 0 | O19: =IFERROR(N19/SUM('船长每月数据(2022年)'!R24:R1099),0) -> 0 | P19: =SUMIF('船长每月数据(2023年)'!E:E,C:C,'船长每月数据(2023年)'!R:R) -> 0 | Q19: =IFERROR(P19/SUM('船长每月数据(2023年)'!R24:R1024),0) -> 0 | R19: =IFERROR((P19-N19)/N19,0) -> 0 | S19: =IFERROR((Q19-O19)/O19,0) -> 0 | T19: =IFERROR(EXP(LN(Q19/O19/2)-1),0) -> 0 | U19: =IFERROR(市场预估!$L$16*(J19+J19*M19),0) -> 0 | V19: =IFERROR(J19*(1+M19),0) -> 0 | W19: =IFERROR(U19*F19,0) -> 0 | X19: =IFERROR(W19/年目标!$E$15,0) -> 0
G20: =SUMIF('船长每月数据(2022年)'!E:E,C:C,'船长每月数据(2022年)'!P:P) -> 0 | H20: =IFERROR(G20/SUM('船长每月数据(2022年)'!P25:P1100),0) -> 0 | I20: =SUMIF('船长每月数据(2023年)'!E:E,C:C,'船长每月数据(2023年)'!P:P) -> 0 | J20: =IFERROR(I20/SUM('船长每月数据(2023年)'!P25:P1025),0) -> 0 | K20: =IFERROR((I20-G20)/G20,0) -> 0 | L20: =IFERROR((J20-H20)/H20,0) -> 0 | M20: =IFERROR(EXP(LN(J20/H20/2)-1),0) -> 0 | N20: =SUMIF('船长每月数据(2022年)'!E:E,C:C,'船长每月数据(2022年)'!R:R) -> 0 | O20: =IFERROR(N20/SUM('船长每月数据(2022年)'!R25:R1100),0) -> 0 | P20: =SUMIF('船长每月数据(2023年)'!E:E,C:C,'船长每月数据(2023年)'!R:R) -> 0 | Q20: =IFERROR(P20/SUM('船长每月数据(2023年)'!R25:R1025),0) -> 0 | R20: =IFERROR((P20-N20)/N20,0) -> 0 | S20: =IFERROR((Q20-O20)/O20,0) -> 0 | T20: =IFERROR(EXP(LN(Q20/O20/2)-1),0) -> 0 | U20: =IFERROR(市场预估!$L$16*(J20+J20*M20),0) -> 0 | V20: =IFERROR(J20*(1+M20),0) -> 0 | W20: =IFERROR(U20*F20,0) -> 0 | X20: =IFERROR(W20/年目标!$E$15,0) -> 0
G21: =SUMIF('船长每月数据(2022年)'!E:E,C:C,'船长每月数据(2022年)'!P:P) -> 0 | H21: =IFERROR(G21/SUM('船长每月数据(2022年)'!P26:P1101),0) -> 0 | I21: =SUMIF('船长每月数据(2023年)'!E:E,C:C,'船长每月数据(2023年)'!P:P) -> 0 | J21: =IFERROR(I21/SUM('船长每月数据(2023年)'!P26:P1026),0) -> 0 | K21: =IFERROR((I21-G21)/G21,0) -> 0 | L21: =IFERROR((J21-H21)/H21,0) -> 0 | M21: =IFERROR(EXP(LN(J21/H21/2)-1),0) -> 0 | N21: =SUMIF('船长每月数据(2022年)'!E:E,C:C,'船长每月数据(2022年)'!R:R) -> 0 | O21: =IFERROR(N21/SUM('船长每月数据(2022年)'!R26:R1101),0) -> 0 | P21: =SUMIF('船长每月数据(2023年)'!E:E,C:C,'船长每月数据(2023年)'!R:R) -> 0 | Q21: =IFERROR(P21/SUM('船长每月数据(2023年)'!R26:R1026),0) -> 0 | R21: =IFERROR((P21-N21)/N21,0) -> 0 | S21: =IFERROR((Q21-O21)/O21,0) -> 0 | T21: =IFERROR(EXP(LN(Q21/O21/2)-1),0) -> 0 | U21: =IFERROR(市场预估!$L$16*(J21+J21*M21),0) -> 0 | V21: =IFERROR(J21*(1+M21),0) -> 0 | W21: =IFERROR(U21*F21,0) -> 0 | X21: =IFERROR(W21/年目标!$E$15,0) -> 0
G22: =SUMIF('船长每月数据(2022年)'!E:E,C:C,'船长每月数据(2022年)'!P:P) -> 0 | H22: =IFERROR(G22/SUM('船长每月数据(2022年)'!P29:P1104),0) -> 0 | I22: =SUMIF('船长每月数据(2023年)'!E:E,C:C,'船长每月数据(2023年)'!P:P) -> 0 | J22: =IFERROR(I22/SUM('船长每月数据(2023年)'!P29:P1029),0) -> 0 | K22: =IFERROR((I22-G22)/G22,0) -> 0 | L22: =IFERROR((J22-H22)/H22,0) -> 0 | M22: =IFERROR(EXP(LN(J22/H22/2)-1),0) -> 0 | N22: =SUMIF('船长每月数据(2022年)'!E:E,C:C,'船长每月数据(2022年)'!R:R) -> 0 | O22: =IFERROR(N22/SUM('船长每月数据(2022年)'!R29:R1104),0) -> 0 | P22: =SUMIF('船长每月数据(2023年)'!E:E,C:C,'船长每月数据(2023年)'!R:R) -> 0 | Q22: =IFERROR(P22/SUM('船长每月数据(2023年)'!R29:R1029),0) -> 0 | R22: =IFERROR((P22-N22)/N22,0) -> 0 | S22: =IFERROR((Q22-O22)/O22,0) -> 0 | T22: =IFERROR(EXP(LN(Q22/O22/2)-1),0) -> 0 | U22: =IFERROR(市场预估!$L$16*(J22+J22*M22)/2,0) -> 0 | V22: =IFERROR(J22*(1+M22),0) -> 0 | W22: =IFERROR(U22*F22,0) -> 0 | X22: =IFERROR(W22/年目标!$E$15,0) -> 0
G23: =SUMIF('船长每月数据(2022年)'!E:E,C:C,'船长每月数据(2022年)'!P:P) -> 0 | H23: =IFERROR(G23/SUM('船长每月数据(2022年)'!P30:P1105),0) -> 0 | I23: =SUMIF('船长每月数据(2023年)'!E:E,C:C,'船长每月数据(2023年)'!P:P) -> 0 | J23: =IFERROR(I23/SUM('船长每月数据(2023年)'!P30:P1030),0) -> 0 | K23: =IFERROR((I23-G23)/G23,0) -> 0 | L23: =IFERROR((J23-H23)/H23,0) -> 0 | M23: =IFERROR(EXP(LN(J23/H23/2)-1),0) -> 0 | N23: =SUMIF('船长每月数据(2022年)'!E:E,C:C,'船长每月数据(2022年)'!R:R) -> 0 | O23: =IFERROR(N23/SUM('船长每月数据(2022年)'!R30:R1105),0) -> 0 | P23: =SUMIF('船长每月数据(2023年)'!E:E,C:C,'船长每月数据(2023年)'!R:R) -> 0 | Q23: =IFERROR(P23/SUM('船长每月数据(2023年)'!R30:R1030),0) -> 0 | R23: =IFERROR((P23-N23)/N23,0) -> 0 | S23: =IFERROR((Q23-O23)/O23,0) -> 0 | T23: =IFERROR(EXP(LN(Q23/O23/2)-1),0) -> 0 | U23: =IFERROR(市场预估!$L$16*(J23+J23*M23)/2,0) -> 0 | V23: =IFERROR(J23*(1+M23),0) -> 0 | W23: =IFERROR(U23*F23,0) -> 0 | X23: =IFERROR(W23/年目标!$E$15,0) -> 0
G24: =SUMIF('船长每月数据(2022年)'!E:E,C:C,'船长每月数据(2022年)'!P:P) -> 0 | H24: =IFERROR(G24/SUM('船长每月数据(2022年)'!P32:P1107),0) -> 0 | I24: =SUMIF('船长每月数据(2023年)'!E:E,C:C,'船长每月数据(2023年)'!P:P) -> 0 | J24: =IFERROR(I24/SUM('船长每月数据(2023年)'!P32:P1032),0) -> 0 | K24: =IFERROR((I24-G24)/G24,0) -> 0 | L24: =IFERROR((J24-H24)/H24,0) -> 0 | M24: =IFERROR(EXP(LN(J24/H24/2)-1),0) -> 0 | N24: =SUMIF('船长每月数据(2022年)'!E:E,C:C,'船长每月数据(2022年)'!R:R) -> 0 | O24: =IFERROR(N24/SUM('船长每月数据(2022年)'!R32:R1107),0) -> 0 | P24: =SUMIF('船长每月数据(2023年)'!E:E,C:C,'船长每月数据(2023年)'!R:R) -> 0 | Q24: =IFERROR(P24/SUM('船长每月数据(2023年)'!R32:R1032),0) -> 0 | R24: =IFERROR((P24-N24)/N24,0) -> 0 | S24: =IFERROR((Q24-O24)/O24,0) -> 0 | T24: =IFERROR(EXP(LN(Q24/O24/2)-1),0) -> 0 | U24: =IFERROR(市场预估!$L$16*(J24+J24*M24)/1.5,0) -> 0 | V24: =IFERROR(J24*(1+M24),0) -> 0 | W24: =IFERROR(U24*F24,0) -> 0 | X24: =IFERROR(W24/年目标!$E$15,0) -> 0
G25: =SUMIF('船长每月数据(2022年)'!E:E,C:C,'船长每月数据(2022年)'!P:P) -> 0 | H25: =IFERROR(G25/SUM('船长每月数据(2022年)'!P33:P1108),0) -> 0 | I25: =SUMIF('船长每月数据(2023年)'!E:E,C:C,'船长每月数据(2023年)'!P:P) -> 0 | J25: =IFERROR(I25/SUM('船长每月数据(2023年)'!P33:P1033),0) -> 0 | K25: =IFERROR((I25-G25)/G25,0) -> 0 | L25: =IFERROR((J25-H25)/H25,0) -> 0 | M25: =IFERROR(EXP(LN(J25/H25/2)-1),0) -> 0 | N25: =SUMIF('船长每月数据(2022年)'!E:E,C:C,'船长每月数据(2022年)'!R:R) -> 0 | O25: =IFERROR(N25/SUM('船长每月数据(2022年)'!R33:R1108),0) -> 0 | P25: =SUMIF('船长每月数据(2023年)'!E:E,C:C,'船长每月数据(2023年)'!R:R) -> 0 | Q25: =IFERROR(P25/SUM('船长每月数据(2023年)'!R33:R1033),0) -> 0 | R25: =IFERROR((P25-N25)/N25,0) -> 0 | S25: =IFERROR((Q25-O25)/O25,0) -> 0 | T25: =IFERROR(EXP(LN(Q25/O25/2)-1),0) -> 0 | U25: =IFERROR(市场预估!$L$16*(J25+J25*M25),0) -> 0 | V25: =IFERROR(J25*(1+M25),0) -> 0 | W25: =IFERROR(U25*F25,0) -> 0 | X25: =IFERROR(W25/年目标!$E$15,0) -> 0
G26: =SUMIF('船长每月数据(2022年)'!E:E,C:C,'船长每月数据(2022年)'!P:P) -> 0 | H26: =IFERROR(G26/SUM('船长每月数据(2022年)'!P34:P1109),0) -> 0 | I26: =SUMIF('船长每月数据(2023年)'!E:E,C:C,'船长每月数据(2023年)'!P:P) -> 0 | J26: =IFERROR(I26/SUM('船长每月数据(2023年)'!P34:P1034),0) -> 0 | K26: =IFERROR((I26-G26)/G26,0) -> 0 | L26: =IFERROR((J26-H26)/H26,0) -> 0 | M26: =IFERROR(EXP(LN(J26/H26/2)-1),0) -> 0 | N26: =SUMIF('船长每月数据(2022年)'!E:E,C:C,'船长每月数据(2022年)'!R:R) -> 0 | O26: =IFERROR(N26/SUM('船长每月数据(2022年)'!R34:R1109),0) -> 0 | P26: =SUMIF('船长每月数据(2023年)'!E:E,C:C,'船长每月数据(2023年)'!R:R) -> 0 | Q26: =IFERROR(P26/SUM('船长每月数据(2023年)'!R34:R1034),0) -> 0 | R26: =IFERROR((P26-N26)/N26,0) -> 0 | S26: =IFERROR((Q26-O26)/O26,0) -> 0 | T26: =IFERROR(EXP(LN(Q26/O26/2)-1),0) -> 0 | U26: =IFERROR(市场预估!$L$16*(J26+J26*M26),0) -> 0 | V26: =IFERROR(J26*(1+M26),0) -> 0 | W26: =IFERROR(U26*F26,0) -> 0 | X26: =IFERROR(W26/年目标!$E$15,0) -> 0
G27: =SUMIF('船长每月数据(2022年)'!E:E,C:C,'船长每月数据(2022年)'!P:P) -> 0 | H27: =IFERROR(G27/SUM('船长每月数据(2022年)'!P35:P1110),0) -> 0 | I27: =SUMIF('船长每月数据(2023年)'!E:E,C:C,'船长每月数据(2023年)'!P:P) -> 0 | J27: =IFERROR(I27/SUM('船长每月数据(2023年)'!P35:P1035),0) -> 0 | K27: =IFERROR((I27-G27)/G27,0) -> 0 | L27: =IFERROR((J27-H27)/H27,0) -> 0 | M27: =IFERROR(EXP(LN(J27/H27/2)-1),0) -> 0 | N27: =SUMIF('船长每月数据(2022年)'!E:E,C:C,'船长每月数据(2022年)'!R:R) -> 0 | O27: =IFERROR(N27/SUM('船长每月数据(2022年)'!R35:R1110),0) -> 0 | P27: =SUMIF('船长每月数据(2023年)'!E:E,C:C,'船长每月数据(2023年)'!R:R) -> 0 | Q27: =IFERROR(P27/SUM('船长每月数据(2023年)'!R35:R1035),0) -> 0 | R27: =IFERROR((P27-N27)/N27,0) -> 0 | S27: =IFERROR((Q27-O27)/O27,0) -> 0 | T27: =IFERROR(EXP(LN(Q27/O27/2)-1),0) -> 0 | U27: =IFERROR(市场预估!$L$16*(J27+J27*M27)/7,0) -> 0 | V27: =IFERROR(J27*(1+M27),0) -> 0 | W27: =IFERROR(U27*F27,0) -> 0 | X27: =IFERROR(W27/年目标!$E$15,0) -> 0
G28: =SUMIF('船长每月数据(2022年)'!E:E,C:C,'船长每月数据(2022年)'!P:P) -> 0 | H28: =IFERROR(G28/SUM('船长每月数据(2022年)'!P36:P1111),0) -> 0 | I28: =SUMIF('船长每月数据(2023年)'!E:E,C:C,'船长每月数据(2023年)'!P:P) -> 0 | J28: =IFERROR(I28/SUM('船长每月数据(2023年)'!P36:P1036),0) -> 0 | K28: =IFERROR((I28-G28)/G28,0) -> 0 | L28: =IFERROR((J28-H28)/H28,0) -> 0 | M28: =IFERROR(EXP(LN(J28/H28/2)-1),0) -> 0 | N28: =SUMIF('船长每月数据(2022年)'!E:E,C:C,'船长每月数据(2022年)'!R:R) -> 0 | O28: =IFERROR(N28/SUM('船长每月数据(2022年)'!R36:R1111),0) -> 0 | P28: =SUMIF('船长每月数据(2023年)'!E:E,C:C,'船长每月数据(2023年)'!R:R) -> 0 | Q28: =IFERROR(P28/SUM('船长每月数据(2023年)'!R36:R1036),0) -> 0 | R28: =IFERROR((P28-N28)/N28,0) -> 0 | S28: =IFERROR((Q28-O28)/O28,0) -> 0 | T28: =IFERROR(EXP(LN(Q28/O28/2)-1),0) -> 0 | U28: =IFERROR(市场预估!$L$16*(J28+J28*M28),0) -> 0 | V28: =IFERROR(J28*(1+M28),0) -> 0 | W28: =IFERROR(U28*F28,0) -> 0 | X28: =IFERROR(W28/年目标!$E$15,0) -> 0
G29: =SUMIF('船长每月数据(2022年)'!E:E,C:C,'船长每月数据(2022年)'!P:P) -> 0 | H29: =IFERROR(G29/SUM('船长每月数据(2022年)'!P40:P1115),0) -> 0 | I29: =SUMIF('船长每月数据(2023年)'!E:E,C:C,'船长每月数据(2023年)'!P:P) -> 0 | J29: =IFERROR(I29/SUM('船长每月数据(2023年)'!P40:P1040),0) -> 0 | K29: =IFERROR((I29-G29)/G29,0) -> 0 | L29: =IFERROR((J29-H29)/H29,0) -> 0 | M29: =IFERROR(EXP(LN(J29/H29/2)-1),0) -> 0 | N29: =SUMIF('船长每月数据(2022年)'!E:E,C:C,'船长每月数据(2022年)'!R:R) -> 0 | O29: =IFERROR(N29/SUM('船长每月数据(2022年)'!R40:R1115),0) -> 0 | P29: =SUMIF('船长每月数据(2023年)'!E:E,C:C,'船长每月数据(2023年)'!R:R) -> 0 | Q29: =IFERROR(P29/SUM('船长每月数据(2023年)'!R40:R1040),0) -> 0 | R29: =IFERROR((P29-N29)/N29,0) -> 0 | S29: =IFERROR((Q29-O29)/O29,0) -> 0 | T29: =IFERROR(EXP(LN(Q29/O29/2)-1),0) -> 0 | U29: =IFERROR(市场预估!$L$16*(J29+J29*M29),0) -> 0 | V29: =IFERROR(J29*(1+M29),0) -> 0 | W29: =IFERROR(U29*F29,0) -> 0 | X29: =IFERROR(W29/年目标!$E$15,0) -> 0
G30: =SUMIF('船长每月数据(2022年)'!E:E,C:C,'船长每月数据(2022年)'!P:P) -> 0 | H30: =IFERROR(G30/SUM('船长每月数据(2022年)'!P42:P1117),0) -> 0 | I30: =SUMIF('船长每月数据(2023年)'!E:E,C:C,'船长每月数据(2023年)'!P:P) -> 0 | J30: =IFERROR(I30/SUM('船长每月数据(2023年)'!P42:P1042),0) -> 0 | K30: =IFERROR((I30-G30)/G30,0) -> 0 | L30: =IFERROR((J30-H30)/H30,0) -> 0 | M30: =IFERROR(EXP(LN(J30/H30/2)-1),0) -> 0 | N30: =SUMIF('船长每月数据(2022年)'!E:E,C:C,'船长每月数据(2022年)'!R:R) -> 0 | O30: =IFERROR(N30/SUM('船长每月数据(2022年)'!R42:R1117),0) -> 0 | P30: =SUMIF('船长每月数据(2023年)'!E:E,C:C,'船长每月数据(2023年)'!R:R) -> 0 | Q30: =IFERROR(P30/SUM('船长每月数据(2023年)'!R42:R1042),0) -> 0 | R30: =IFERROR((P30-N30)/N30,0) -> 0 | S30: =IFERROR((Q30-O30)/O30,0) -> 0 | T30: =IFERROR(EXP(LN(Q30/O30/2)-1),0) -> 0 | U30: =IFERROR(市场预估!$L$16*(J30+J30*M30),0) -> 0 | V30: =IFERROR(J30*(1+M30),0) -> 0 | W30: =IFERROR(U30*F30,0) -> 0 | X30: =IFERROR(W30/年目标!$E$15,0) -> 0
G31: =SUMIF('船长每月数据(2022年)'!E:E,C:C,'船长每月数据(2022年)'!P:P) -> 0 | H31: =IFERROR(G31/SUM('船长每月数据(2022年)'!P43:P1118),0) -> 0 | I31: =SUMIF('船长每月数据(2023年)'!E:E,C:C,'船长每月数据(2023年)'!P:P) -> 0 | J31: =IFERROR(I31/SUM('船长每月数据(2023年)'!P43:P1043),0) -> 0 | K31: =IFERROR((I31-G31)/G31,0) -> 0 | L31: =IFERROR((J31-H31)/H31,0) -> 0 | M31: =IFERROR(EXP(LN(J31/H31/2)-1),0) -> 0 | N31: =SUMIF('船长每月数据(2022年)'!E:E,C:C,'船长每月数据(2022年)'!R:R) -> 0 | O31: =IFERROR(N31/SUM('船长每月数据(2022年)'!R43:R1118),0) -> 0 | P31: =SUMIF('船长每月数据(2023年)'!E:E,C:C,'船长每月数据(2023年)'!R:R) -> 0 | Q31: =IFERROR(P31/SUM('船长每月数据(2023年)'!R43:R1043),0) -> 0 | R31: =IFERROR((P31-N31)/N31,0) -> 0 | S31: =IFERROR((Q31-O31)/O31,0) -> 0 | T31: =IFERROR(EXP(LN(Q31/O31/2)-1),0) -> 0 | U31: =IFERROR(市场预估!$L$16*(J31+J31*M31),0) -> 0 | V31: =IFERROR(J31*(1+M31),0) -> 0 | W31: =IFERROR(U31*F31,0) -> 0 | X31: =IFERROR(W31/年目标!$E$15,0) -> 0
G32: =SUMIF('船长每月数据(2022年)'!E:E,C:C,'船长每月数据(2022年)'!P:P) -> 0 | H32: =IFERROR(G32/SUM('船长每月数据(2022年)'!P44:P1119),0) -> 0 | I32: =SUMIF('船长每月数据(2023年)'!E:E,C:C,'船长每月数据(2023年)'!P:P) -> 0 | J32: =IFERROR(I32/SUM('船长每月数据(2023年)'!P44:P1044),0) -> 0 | K32: =IFERROR((I32-G32)/G32,0) -> 0 | L32: =IFERROR((J32-H32)/H32,0) -> 0 | M32: =IFERROR(EXP(LN(J32/H32/2)-1),0) -> 0 | N32: =SUMIF('船长每月数据(2022年)'!E:E,C:C,'船长每月数据(2022年)'!R:R) -> 0 | O32: =IFERROR(N32/SUM('船长每月数据(2022年)'!R44:R1119),0) -> 0 | P32: =SUMIF('船长每月数据(2023年)'!E:E,C:C,'船长每月数据(2023年)'!R:R) -> 0 | Q32: =IFERROR(P32/SUM('船长每月数据(2023年)'!R44:R1044),0) -> 0 | R32: =IFERROR((P32-N32)/N32,0) -> 0 | S32: =IFERROR((Q32-O32)/O32,0) -> 0 | T32: =IFERROR(EXP(LN(Q32/O32/2)-1),0) -> 0 | U32: =IFERROR(市场预估!$L$16*(J32+J32*M32),0) -> 0 | V32: =IFERROR(J32*(1+M32),0) -> 0 | W32: =IFERROR(U32*F32,0) -> 0 | X32: =IFERROR(W32/年目标!$E$15,0) -> 0
G33: =SUMIF('船长每月数据(2022年)'!E:E,C:C,'船长每月数据(2022年)'!P:P) -> 0 | H33: =IFERROR(G33/SUM('船长每月数据(2022年)'!P45:P1120),0) -> 0 | I33: =SUMIF('船长每月数据(2023年)'!E:E,C:C,'船长每月数据(2023年)'!P:P) -> 0 | J33: =IFERROR(I33/SUM('船长每月数据(2023年)'!P45:P1045),0) -> 0 | K33: =IFERROR((I33-G33)/G33,0) -> 0 | L33: =IFERROR((J33-H33)/H33,0) -> 0 | M33: =IFERROR(EXP(LN(J33/H33/2)-1),0) -> 0 | N33: =SUMIF('船长每月数据(2022年)'!E:E,C:C,'船长每月数据(2022年)'!R:R) -> 0 | O33: =IFERROR(N33/SUM('船长每月数据(2022年)'!R45:R1120),0) -> 0 | P33: =SUMIF('船长每月数据(2023年)'!E:E,C:C,'船长每月数据(2023年)'!R:R) -> 0 | Q33: =IFERROR(P33/SUM('船长每月数据(2023年)'!R45:R1045),0) -> 0 | R33: =IFERROR((P33-N33)/N33,0) -> 0 | S33: =IFERROR((Q33-O33)/O33,0) -> 0 | T33: =IFERROR(EXP(LN(Q33/O33/2)-1),0) -> 0 | U33: =IFERROR(市场预估!$L$16*(J33+J33*M33),0) -> 0 | V33: =IFERROR(J33*(1+M33),0) -> 0 | W33: =IFERROR(U33*F33,0) -> 0 | X33: =IFERROR(W33/年目标!$E$15,0) -> 0
G34: =SUMIF('船长每月数据(2022年)'!E:E,C:C,'船长每月数据(2022年)'!P:P) -> 0 | H34: =IFERROR(G34/SUM('船长每月数据(2022年)'!P46:P1121),0) -> 0 | I34: =SUMIF('船长每月数据(2023年)'!E:E,C:C,'船长每月数据(2023年)'!P:P) -> 0 | J34: =IFERROR(I34/SUM('船长每月数据(2023年)'!P46:P1046),0) -> 0 | K34: =IFERROR((I34-G34)/G34,0) -> 0 | L34: =IFERROR((J34-H34)/H34,0) -> 0 | M34: =IFERROR(EXP(LN(J34/H34/2)-1),0) -> 0 | N34: =SUMIF('船长每月数据(2022年)'!E:E,C:C,'船长每月数据(2022年)'!R:R) -> 0 | O34: =IFERROR(N34/SUM('船长每月数据(2022年)'!R46:R1121),0) -> 0 | P34: =SUMIF('船长每月数据(2023年)'!E:E,C:C,'船长每月数据(2023年)'!R:R) -> 0 | Q34: =IFERROR(P34/SUM('船长每月数据(2023年)'!R46:R1046),0) -> 0 | R34: =IFERROR((P34-N34)/N34,0) -> 0 | S34: =IFERROR((Q34-O34)/O34,0) -> 0 | T34: =IFERROR(EXP(LN(Q34/O34/2)-1),0) -> 0 | U34: =IFERROR(市场预估!$L$16*(J34+J34*M34)/3,0) -> 0 | V34: =IFERROR(J34*(1+M34),0)/3 -> 0 | W34: =IFERROR(U34*F34,0) -> 0 | X34: =IFERROR(W34/年目标!$E$15,0) -> 0
G35: =SUMIF('船长每月数据(2022年)'!E:E,C:C,'船长每月数据(2022年)'!P:P) -> 0 | H35: =IFERROR(G35/SUM('船长每月数据(2022年)'!P47:P1122),0) -> 0 | I35: =SUMIF('船长每月数据(2023年)'!E:E,C:C,'船长每月数据(2023年)'!P:P) -> 0 | J35: =IFERROR(I35/SUM('船长每月数据(2023年)'!P47:P1047),0) -> 0 | K35: =IFERROR((I35-G35)/G35,0) -> 0 | L35: =IFERROR((J35-H35)/H35,0) -> 0 | M35: =IFERROR(EXP(LN(J35/H35/2)-1),0) -> 0 | N35: =SUMIF('船长每月数据(2022年)'!E:E,C:C,'船长每月数据(2022年)'!R:R) -> 0 | O35: =IFERROR(N35/SUM('船长每月数据(2022年)'!R47:R1122),0) -> 0 | P35: =SUMIF('船长每月数据(2023年)'!E:E,C:C,'船长每月数据(2023年)'!R:R) -> 0 | Q35: =IFERROR(P35/SUM('船长每月数据(2023年)'!R47:R1047),0) -> 0 | R35: =IFERROR((P35-N35)/N35,0) -> 0 | S35: =IFERROR((Q35-O35)/O35,0) -> 0 | T35: =IFERROR(EXP(LN(Q35/O35/2)-1),0) -> 0 | U35: =IFERROR(市场预估!$L$16*(J35+J35*M35),0) -> 0 | V35: =IFERROR(J35*(1+M35)*10,0) -> 0 | W35: =IFERROR(U35*F35,0) -> 0 | X35: =IFERROR(W35/年目标!$E$15,0) -> 0
G36: =SUMIF('船长每月数据(2022年)'!E:E,C:C,'船长每月数据(2022年)'!P:P) -> 0 | H36: =IFERROR(G36/SUM('船长每月数据(2022年)'!P48:P1123),0) -> 0 | I36: =SUMIF('船长每月数据(2023年)'!E:E,C:C,'船长每月数据(2023年)'!P:P) -> 0 | J36: =IFERROR(I36/SUM('船长每月数据(2023年)'!P48:P1048),0) -> 0 | K36: =IFERROR((I36-G36)/G36,0) -> 0 | L36: =IFERROR((J36-H36)/H36,0) -> 0 | M36: =IFERROR(EXP(LN(J36/H36/2)-1),0) -> 0 | N36: =SUMIF('船长每月数据(2022年)'!E:E,C:C,'船长每月数据(2022年)'!R:R) -> 0 | O36: =IFERROR(N36/SUM('船长每月数据(2022年)'!R48:R1123),0) -> 0 | P36: =SUMIF('船长每月数据(2023年)'!E:E,C:C,'船长每月数据(2023年)'!R:R) -> 0 | Q36: =IFERROR(P36/SUM('船长每月数据(2023年)'!R48:R1048),0) -> 0 | R36: =IFERROR((P36-N36)/N36,0) -> 0 | S36: =IFERROR((Q36-O36)/O36,0) -> 0 | T36: =IFERROR(EXP(LN(Q36/O36/2)-1),0) -> 0 | U36: =IFERROR(市场预估!$L$16*(J36+J36*M36)*5,0) -> 0 | V36: =IFERROR(J36*(1+M36)*5,0) -> 0 | W36: =IFERROR(U36*F36,0) -> 0 | X36: =IFERROR(W36/年目标!$E$15,0) -> 0

Sheet 每月目标分解
A1: 2023年每月目标分解
A2: 产品大类 | B2: 产品系列 | C2: 产品ASIN | D2: 型号系列 | E2: 产品中文名 | F2: 1月 | G2: 2月 | H2: 3月 | I2: 4月 | J2: 5月 | K2: 6月 | L2: 7月 | M2: 8月 | N2: 9月 | O2: 10月 | P2: 11月 | Q2: 12月 | R2: 总计 | S2: 销售额占比
F3: 0 | G3: 0 | H3: 0 | I3: =IFERROR(SUMIF(单品目标年销量!$E:$E,$E:$E,单品目标年销量!$W:$W)*'2024年销售情况'!$AR$75,0) -> 0 | J3: =IFERROR(SUMIF(单品目标年销量!$E:$E,$E:$E,单品目标年销量!$W:$W)*'2024年销售情况'!$AV$75,0) -> 0 | K3: =IFERROR(SUMIF(单品目标年销量!$E:$E,$E:$E,单品目标年销量!$W:$W)*'2024年销售情况'!$AZ$75,0) -> 0 | L3: =IFERROR(SUMIF(单品目标年销量!$E:$E,$E:$E,单品目标年销量!$W:$W)*'2024年销售情况'!$BD$75,0) -> 0 | M3: =IFERROR(SUMIF(单品目标年销量!$E:$E,$E:$E,单品目标年销量!$W:$W)*'2024年销售情况'!$BH$75,0) -> 0 | N3: =IFERROR(SUMIF(单品目标年销量!$E:$E,$E:$E,单品目标年销量!$W:$W)*'2024年销售情况'!$BL$75,0) -> 0 | O3: =IFERROR(SUMIF(单品目标年销量!$E:$E,$E:$E,单品目标年销量!$W:$W)*'2024年销售情况'!$BP$75,0) -> 0 | P3: =IFERROR(SUMIF(单品目标年销量!$E:$E,$E:$E,单品目标年销量!$W:$W)*'2024年销售情况'!$BT$75,0)*2 -> 0 | Q3: =IFERROR(SUMIF(单品目标年销量!$E:$E,$E:$E,单品目标年销量!$W:$W)*'2024年销售情况'!$BX$75,0)*2 -> 0 | R3: =SUM(F3:Q3) -> 0 | S3: =IFERROR(R3/年目标!$E$15,0) -> 0
F4: 0 | G4: 0 | H4: 0 | I4: 0 | J4: 0 | K4: =IFERROR(SUMIF(单品目标年销量!$E:$E,$E:$E,单品目标年销量!$W:$W)*'2024年销售情况'!$AZ$75,0) -> 0 | L4: =IFERROR(SUMIF(单品目标年销量!$E:$E,$E:$E,单品目标年销量!$W:$W)*'2024年销售情况'!$BD$75,0) -> 0 | M4: =IFERROR(SUMIF(单品目标年销量!$E:$E,$E:$E,单品目标年销量!$W:$W)*'2024年销售情况'!$BH$75,0) -> 0 | N4: =IFERROR(SUMIF(单品目标年销量!$E:$E,$E:$E,单品目标年销量!$W:$W)*'2024年销售情况'!$BL$75,0)*2 -> 0 | O4: =IFERROR(SUMIF(单品目标年销量!$E:$E,$E:$E,单品目标年销量!$W:$W)*'2024年销售情况'!$BP$75,0) -> 0 | P4: =IFERROR(SUMIF(单品目标年销量!$E:$E,$E:$E,单品目标年销量!$W:$W)*'2024年销售情况'!$BT$75,0)*3 -> 0 | Q4: =IFERROR(SUMIF(单品目标年销量!$E:$E,$E:$E,单品目标年销量!$W:$W)*'2024年销售情况'!$BX$75,0)*2 -> 0 | R4: =SUM(F4:Q4) -> 0 | S4: =IFERROR(R4/年目标!$E$15,0) -> 0
F5: 0 | G5: 0 | H5: 0 | I5: 0 | J5: 0 | K5: 0 | L5: =IFERROR(SUMIF(单品目标年销量!$E:$E,$E:$E,单品目标年销量!$W:$W)*'2024年销售情况'!$BD$75,0) -> 0 | M5: =IFERROR(SUMIF(单品目标年销量!$E:$E,$E:$E,单品目标年销量!$W:$W)*'2024年销售情况'!$BH$75,0) -> 0 | N5: =IFERROR(SUMIF(单品目标年销量!$E:$E,$E:$E,单品目标年销量!$W:$W)*'2024年销售情况'!$BL$75,0) -> 0 | O5: =IFERROR(SUMIF(单品目标年销量!$E:$E,$E:$E,单品目标年销量!$W:$W)*'2024年销售情况'!$BP$75,0) -> 0 | P5: =IFERROR(SUMIF(单品目标年销量!$E:$E,$E:$E,单品目标年销量!$W:$W)*'2024年销售情况'!$BT$75,0)*3 -> 0 | Q5: =IFERROR(SUMIF(单品目标年销量!$E:$E,$E:$E,单品目标年销量!$W:$W)*'2024年销售情况'!$BX$75,0)*3 -> 0 | R5: =SUM(F5:Q5) -> 0 | S5: =IFERROR(R5/年目标!$E$15,0) -> 0
F6: 0 | G6: 0 | H6: 0 | I6: 0 | J6: 0 | K6: 0 | L6: 0 | M6: 0 | N6: =IFERROR(SUMIF(单品目标年销量!$E:$E,$E:$E,单品目标年销量!$W:$W)*'2024年销售情况'!$BL$75,0)*3 -> 0 | O6: =IFERROR(SUMIF(单品目标年销量!$E:$E,$E:$E,单品目标年销量!$W:$W)*'2024年销售情况'!$BP$75,0)*3 -> 0 | P6: =IFERROR(SUMIF(单品目标年销量!$E:$E,$E:$E,单品目标年销量!$W:$W)*'2024年销售情况'!$BT$75,0)*4 -> 0 | Q6: =IFERROR(SUMIF(单品目标年销量!$E:$E,$E:$E,单品目标年销量!$W:$W)*'2024年销售情况'!$BX$75,0)*3 -> 0 | R6: =SUM(F6:Q6) -> 0 | S6: =IFERROR(R6/年目标!$E$15,0) -> 0
F7: 0 | G7: 0 | H7: 0 | I7: 0 | J7: 0 | K7: =IFERROR(SUMIF(单品目标年销量!$E:$E,$E:$E,单品目标年销量!$W:$W)*'2024年销售情况'!$AZ$75,0) -> 0 | L7: =IFERROR(SUMIF(单品目标年销量!$E:$E,$E:$E,单品目标年销量!$W:$W)*'2024年销售情况'!$BD$75,0) -> 0 | M7: =IFERROR(SUMIF(单品目标年销量!$E:$E,$E:$E,单品目标年销量!$W:$W)*'2024年销售情况'!$BH$75,0) -> 0 | N7: =IFERROR(SUMIF(单品目标年销量!$E:$E,$E:$E,单品目标年销量!$W:$W)*'2024年销售情况'!$BL$75,0) -> 0 | O7: =IFERROR(SUMIF(单品目标年销量!$E:$E,$E:$E,单品目标年销量!$W:$W)*'2024年销售情况'!$BP$75,0) -> 0 | P7: =IFERROR(SUMIF(单品目标年销量!$E:$E,$E:$E,单品目标年销量!$W:$W)*'2024年销售情况'!$BT$75,0)*3 -> 0 | Q7: =IFERROR(SUMIF(单品目标年销量!$E:$E,$E:$E,单品目标年销量!$W:$W)*'2024年销售情况'!$BX$75,0)*2 -> 0 | R7: =SUM(F7:Q7) -> 0 | S7: =IFERROR(R7/年目标!$E$15,0) -> 0
F8: 0 | G8: 0 | H8: 0 | I8: 0 | J8: 0 | K8: =IFERROR(SUMIF(单品目标年销量!$E:$E,$E:$E,单品目标年销量!$W:$W)*'2024年销售情况'!$AZ$75,0) -> 0 | L8: =IFERROR(SUMIF(单品目标年销量!$E:$E,$E:$E,单品目标年销量!$W:$W)*'2024年销售情况'!$BD$75,0) -> 0 | M8: =IFERROR(SUMIF(单品目标年销量!$E:$E,$E:$E,单品目标年销量!$W:$W)*'2024年销售情况'!$BH$75,0) -> 0 | N8: =IFERROR(SUMIF(单品目标年销量!$E:$E,$E:$E,单品目标年销量!$W:$W)*'2024年销售情况'!$BL$75,0)*3 -> 0 | O8: =IFERROR(SUMIF(单品目标年销量!$E:$E,$E:$E,单品目标年销量!$W:$W)*'2024年销售情况'!$BP$75,0)*3 -> 0 | P8: =IFERROR(SUMIF(单品目标年销量!$E:$E,$E:$E,单品目标年销量!$W:$W)*'2024年销售情况'!$BT$75,0)*3 -> 0 | Q8: =IFERROR(SUMIF(单品目标年销量!$E:$E,$E:$E,单品目标年销量!$W:$W)*'2024年销售情况'!$BX$75,0)*2 -> 0 | R8: =SUM(F8:Q8) -> 0 | S8: =IFERROR(R8/年目标!$E$15,0) -> 0
F9: 0 | G9: 0 | H9: 0 | I9: =IFERROR(SUMIF(单品目标年销量!$E:$E,$E:$E,单品目标年销量!$W:$W)*'2024年销售情况'!$AR$75,0) -> 0 | J9: =IFERROR(SUMIF(单品目标年销量!$E:$E,$E:$E,单品目标年销量!$W:$W)*'2024年销售情况'!$AV$75,0) -> 0 | K9: =IFERROR(SUMIF(单品目标年销量!$E:$E,$E:$E,单品目标年销量!$W:$W)*'2024年销售情况'!$AZ$75,0) -> 0 | L9: =IFERROR(SUMIF(单品目标年销量!$E:$E,$E:$E,单品目标年销量!$W:$W)*'2024年销售情况'!$BD$75,0) -> 0 | M9: =IFERROR(SUMIF(单品目标年销量!$E:$E,$E:$E,单品目标年销量!$W:$W)*'2024年销售情况'!$BH$75,0) -> 0 | N9: =IFERROR(SUMIF(单品目标年销量!$E:$E,$E:$E,单品目标年销量!$W:$W)*'2024年销售情况'!$BL$75,0) -> 0 | O9: =IFERROR(SUMIF(单品目标年销量!$E:$E,$E:$E,单品目标年销量!$W:$W)*'2024年销售情况'!$BP$75,0) -> 0 | P9: =IFERROR(SUMIF(单品目标年销量!$E:$E,$E:$E,单品目标年销量!$W:$W)*'2024年销售情况'!$BT$75,0)*2 -> 0 | Q9: =IFERROR(SUMIF(单品目标年销量!$E:$E,$E:$E,单品目标年销量!$W:$W)*'2024年销售情况'!$BX$75,0)*2 -> 0 | R9: =SUM(F9:Q9) -> 0 | S9: =IFERROR(R9/年目标!$E$15,0) -> 0
F10: 0 | G10: 0 | H10: 0 | I10: =IFERROR(SUMIF(单品目标年销量!$E:$E,$E:$E,单品目标年销量!$W:$W)*'2024年销售情况'!$AR$75,0) -> 0 | J10: =IFERROR(SUMIF(单品目标年销量!$E:$E,$E:$E,单品目标年销量!$W:$W)*'2024年销售情况'!$AV$75,0) -> 0 | K10: =IFERROR(SUMIF(单品目标年销量!$E:$E,$E:$E,单品目标年销量!$W:$W)*'2024年销售情况'!$AZ$75,0) -> 0 | L10: =IFERROR(SUMIF(单品目标年销量!$E:$E,$E:$E,单品目标年销量!$W:$W)*'2024年销售情况'!$BD$75,0) -> 0 | M10: =IFERROR(SUMIF(单品目标年销量!$E:$E,$E:$E,单品目标年销量!$W:$W)*'2024年销售情况'!$BH$75,0) -> 0 | N10: =IFERROR(SUMIF(单品目标年销量!$E:$E,$E:$E,单品目标年销量!$W:$W)*'2024年销售情况'!$BL$75,0) -> 0 | O10: =IFERROR(SUMIF(单品目标年销量!$E:$E,$E:$E,单品目标年销量!$W:$W)*'2024年销售情况'!$BP$75,0) -> 0 | P10: =IFERROR(SUMIF(单品目标年销量!$E:$E,$E:$E,单品目标年销量!$W:$W)*'2024年销售情况'!$BT$75,0)*2 -> 0 | Q10: =IFERROR(SUMIF(单品目标年销量!$E:$E,$E:$E,单品目标年销量!$W:$W)*'2024年销售情况'!$BX$75,0)*2 -> 0 | R10: =SUM(F10:Q10) -> 0 | S10: =IFERROR(R10/年目标!$E$15,0) -> 0
F11: 0 | G11: 0 | H11: 0 | I11: 0 | J11: 0 | K11: =IFERROR(SUMIF(单品目标年销量!$E:$E,$E:$E,单品目标年销量!$W:$W)*'2024年销售情况'!$AZ$75,0) -> 0 | L11: =IFERROR(SUMIF(单品目标年销量!$E:$E,$E:$E,单品目标年销量!$W:$W)*'2024年销售情况'!$BD$75,0) -> 0 | M11: =IFERROR(SUMIF(单品目标年销量!$E:$E,$E:$E,单品目标年销量!$W:$W)*'2024年销售情况'!$BH$75,0) -> 0 | N11: =IFERROR(SUMIF(单品目标年销量!$E:$E,$E:$E,单品目标年销量!$W:$W)*'2024年销售情况'!$BL$75,0) -> 0 | O11: =IFERROR(SUMIF(单品目标年销量!$E:$E,$E:$E,单品目标年销量!$W:$W)*'2024年销售情况'!$BP$75,0)*3 -> 0 | P11: =IFERROR(SUMIF(单品目标年销量!$E:$E,$E:$E,单品目标年销量!$W:$W)*'2024年销售情况'!$BT$75,0)*3 -> 0 | Q11: =IFERROR(SUMIF(单品目标年销量!$E:$E,$E:$E,单品目标年销量!$W:$W)*'2024年销售情况'!$BX$75,0)*2 -> 0 | R11: =SUM(F11:Q11) -> 0 | S11: =IFERROR(R11/年目标!$E$15,0) -> 0
F12: 0 | G12: 0 | H12: 0 | I12: =IFERROR(SUMIF(单品目标年销量!$E:$E,$E:$E,单品目标年销量!$W:$W)*'2024年销售情况'!$AR$75,0) -> 0 | J12: =IFERROR(SUMIF(单品目标年销量!$E:$E,$E:$E,单品目标年销量!$W:$W)*'2024年销售情况'!$AV$75,0) -> 0 | K12: =IFERROR(SUMIF(单品目标年销量!$E:$E,$E:$E,单品目标年销量!$W:$W)*'2024年销售情况'!$AZ$75,0) -> 0 | L12: =IFERROR(SUMIF(单品目标年销量!$E:$E,$E:$E,单品目标年销量!$W:$W)*'2024年销售情况'!$BD$75,0) -> 0 | M12: =IFERROR(SUMIF(单品目标年销量!$E:$E,$E:$E,单品目标年销量!$W:$W)*'2024年销售情况'!$BH$75,0) -> 0 | N12: =IFERROR(SUMIF(单品目标年销量!$E:$E,$E:$E,单品目标年销量!$W:$W)*'2024年销售情况'!$BL$75,0) -> 0 | O12: =IFERROR(SUMIF(单品目标年销量!$E:$E,$E:$E,单品目标年销量!$W:$W)*'2024年销售情况'!$BP$75,0) -> 0 | P12: =IFERROR(SUMIF(单品目标年销量!$E:$E,$E:$E,单品目标年销量!$W:$W)*'2024年销售情况'!$BT$75,0)*2 -> 0 | Q12: =IFERROR(SUMIF(单品目标年销量!$E:$E,$E:$E,单品目标年销量!$W:$W)*'2024年销售情况'!$BX$75,0)*2 -> 0 | R12: =SUM(F12:Q12) -> 0 | S12: =IFERROR(R12/年目标!$E$15,0) -> 0
F13: 0 | G13: 0 | H13: 0 | I13: =IFERROR(SUMIF(单品目标年销量!$E:$E,$E:$E,单品目标年销量!$W:$W)*'2024年销售情况'!$AR$75,0) -> 0 | J13: =IFERROR(SUMIF(单品目标年销量!$E:$E,$E:$E,单品目标年销量!$W:$W)*'2024年销售情况'!$AV$75,0) -> 0 | K13: =IFERROR(SUMIF(单品目标年销量!$E:$E,$E:$E,单品目标年销量!$W:$W)*'2024年销售情况'!$AZ$75,0) -> 0 | L13: =IFERROR(SUMIF(单品目标年销量!$E:$E,$E:$E,单品目标年销量!$W:$W)*'2024年销售情况'!$BD$75,0) -> 0 | M13: =IFERROR(SUMIF(单品目标年销量!$E:$E,$E:$E,单品目标年销量!$W:$W)*'2024年销售情况'!$BH$75,0) -> 0 | N13: =IFERROR(SUMIF(单品目标年销量!$E:$E,$E:$E,单品目标年销量!$W:$W)*'2024年销售情况'!$BL$75,0) -> 0 | O13: =IFERROR(SUMIF(单品目标年销量!$E:$E,$E:$E,单品目标年销量!$W:$W)*'2024年销售情况'!$BP$75,0) -> 0 | P13: =IFERROR(SUMIF(单品目标年销量!$E:$E,$E:$E,单品目标年销量!$W:$W)*'2024年销售情况'!$BT$75,0)*2 -> 0 | Q13: =IFERROR(SUMIF(单品目标年销量!$E:$E,$E:$E,单品目标年销量!$W:$W)*'2024年销售情况'!$BX$75,0)*2 -> 0 | R13: =SUM(F13:Q13) -> 0 | S13: =IFERROR(R13/年目标!$E$15,0) -> 0
F14: =SUMIF(单品目标年销量!C:C,C:C,单品目标年销量!W:W)*SUMIF('2024年销售情况'!C:C,C:C,'2024年销售情况'!AF:AF) -> 0 | G14: =SUMIF(单品目标年销量!$C:$C,$C:$C,单品目标年销量!$W:$W)*SUMIF('2024年销售情况'!$C:$C,$C:$C,'2024年销售情况'!AJ:AJ) -> 0 | H14: =SUMIF(单品目标年销量!$C:$C,$C:$C,单品目标年销量!$W:$W)*SUMIF('2024年销售情况'!$C:$C,$C:$C,'2024年销售情况'!AN:AN) -> 0 | I14: =SUMIF(单品目标年销量!$C:$C,$C:$C,单品目标年销量!$W:$W)*SUMIF('2024年销售情况'!$C:$C,$C:$C,'2024年销售情况'!AR:AR) -> 0 | J14: =SUMIF(单品目标年销量!$C:$C,$C:$C,单品目标年销量!$W:$W)*SUMIF('2024年销售情况'!$C:$C,$C:$C,'2024年销售情况'!AV:AV) -> 0 | K14: =SUMIF(单品目标年销量!$C:$C,$C:$C,单品目标年销量!$W:$W)*SUMIF('2024年销售情况'!$C:$C,$C:$C,'2024年销售情况'!AZ:AZ) -> 0 | L14: =SUMIF(单品目标年销量!$C:$C,$C:$C,单品目标年销量!$W:$W)*SUMIF('2024年销售情况'!$C:$C,$C:$C,'2024年销售情况'!BD:BD) -> 0 | M14: =SUMIF(单品目标年销量!$C:$C,$C:$C,单品目标年销量!$W:$W)*SUMIF('2024年销售情况'!$C:$C,$C:$C,'2024年销售情况'!BH:BH) -> 0 | N14: =SUMIF(单品目标年销量!$C:$C,$C:$C,单品目标年销量!$W:$W)*SUMIF('2024年销售情况'!$C:$C,$C:$C,'2024年销售情况'!BL:BL) -> 0 | O14: =SUMIF(单品目标年销量!$C:$C,$C:$C,单品目标年销量!$W:$W)*SUMIF('2024年销售情况'!$C:$C,$C:$C,'2024年销售情况'!BP:BP) -> 0 | P14: =SUMIF(单品目标年销量!$C:$C,$C:$C,单品目标年销量!$W:$W)*SUMIF('2024年销售情况'!$C:$C,$C:$C,'2024年销售情况'!BT:BT) -> 0 | Q14: =SUMIF(单品目标年销量!$C:$C,$C:$C,单品目标年销量!$W:$W)*SUMIF('2024年销售情况'!$C:$C,$C:$C,'2024年销售情况'!BX:BX) -> 0 | R14: =SUM(F14:Q14) -> 0 | S14: =IFERROR(R14/年目标!$E$15,0) -> 0 | T14: =SUMIF('船长每月数据(2023年)'!E:E,C:C,'船长每月数据(2023年)'!R:R) -> 0
F15: =SUMIF(单品目标年销量!C:C,C:C,单品目标年销量!W:W)*SUMIF('2024年销售情况'!C:C,单品目标年销量!C:C,'2024年销售情况'!AF:AF) -> 0 | G15: =SUMIF(单品目标年销量!$C:$C,$C:$C,单品目标年销量!$W:$W)*SUMIF('2024年销售情况'!$C:$C,$C:$C,'2024年销售情况'!AJ:AJ) -> 0 | H15: =SUMIF(单品目标年销量!$C:$C,$C:$C,单品目标年销量!$W:$W)*SUMIF('2024年销售情况'!$C:$C,$C:$C,'2024年销售情况'!AN:AN) -> 0 | I15: =SUMIF(单品目标年销量!$C:$C,$C:$C,单品目标年销量!$W:$W)*SUMIF('2024年销售情况'!$C:$C,$C:$C,'2024年销售情况'!AR:AR) -> 0 | J15: =SUMIF(单品目标年销量!$C:$C,$C:$C,单品目标年销量!$W:$W)*SUMIF('2024年销售情况'!$C:$C,$C:$C,'2024年销售情况'!AV:AV) -> 0 | K15: =SUMIF(单品目标年销量!$C:$C,$C:$C,单品目标年销量!$W:$W)*SUMIF('2024年销售情况'!$C:$C,$C:$C,'2024年销售情况'!AZ:AZ) -> 0 | L15: =SUMIF(单品目标年销量!$C:$C,$C:$C,单品目标年销量!$W:$W)*SUMIF('2024年销售情况'!$C:$C,$C:$C,'2024年销售情况'!BD:BD) -> 0 | M15: =SUMIF(单品目标年销量!$C:$C,$C:$C,单品目标年销量!$W:$W)*SUMIF('2024年销售情况'!$C:$C,$C:$C,'2024年销售情况'!BH:BH) -> 0 | N15: =SUMIF(单品目标年销量!$C:$C,$C:$C,单品目标年销量!$W:$W)*SUMIF('2024年销售情况'!$C:$C,$C:$C,'2024年销售情况'!BL:BL) -> 0 | O15: =SUMIF(单品目标年销量!$C:$C,$C:$C,单品目标年销量!$W:$W)*SUMIF('2024年销售情况'!$C:$C,$C:$C,'2024年销售情况'!BP:BP) -> 0 | P15: =SUMIF(单品目标年销量!$C:$C,$C:$C,单品目标年销量!$W:$W)*SUMIF('2024年销售情况'!$C:$C,$C:$C,'2024年销售情况'!BT:BT) -> 0 | Q15: =SUMIF(单品目标年销量!$C:$C,$C:$C,单品目标年销量!$W:$W)*SUMIF('2024年销售情况'!$C:$C,$C:$C,'2024年销售情况'!BX:BX) -> 0 | R15: =SUM(F15:Q15) -> 0 | S15: =IFERROR(R15/年目标!$E$15,0) -> 0 | T15: =SUMIF('船长每月数据(2023年)'!E:E,C:C,'船长每月数据(2023年)'!R:R) -> 0
F16: =SUMIF(单品目标年销量!C:C,C:C,单品目标年销量!W:W)*SUMIF('2024年销售情况'!C:C,单品目标年销量!C:C,'2024年销售情况'!AF:AF) -> 0 | G16: =SUMIF(单品目标年销量!$C:$C,$C:$C,单品目标年销量!$W:$W)*SUMIF('2024年销售情况'!$C:$C,$C:$C,'2024年销售情况'!AJ:AJ) -> 0 | H16: =SUMIF(单品目标年销量!$C:$C,$C:$C,单品目标年销量!$W:$W)*SUMIF('2024年销售情况'!$C:$C,$C:$C,'2024年销售情况'!AN:AN) -> 0 | I16: =SUMIF(单品目标年销量!$C:$C,$C:$C,单品目标年销量!$W:$W)*SUMIF('2024年销售情况'!$C:$C,$C:$C,'2024年销售情况'!AR:AR) -> 0 | J16: =SUMIF(单品目标年销量!$C:$C,$C:$C,单品目标年销量!$W:$W)*SUMIF('2024年销售情况'!$C:$C,$C:$C,'2024年销售情况'!AV:AV) -> 0 | K16: =SUMIF(单品目标年销量!$C:$C,$C:$C,单品目标年销量!$W:$W)*SUMIF('2024年销售情况'!$C:$C,$C:$C,'2024年销售情况'!AZ:AZ) -> 0 | L16: =SUMIF(单品目标年销量!$C:$C,$C:$C,单品目标年销量!$W:$W)*SUMIF('2024年销售情况'!$C:$C,$C:$C,'2024年销售情况'!BD:BD) -> 0 | M16: =SUMIF(单品目标年销量!$C:$C,$C:$C,单品目标年销量!$W:$W)*SUMIF('2024年销售情况'!$C:$C,$C:$C,'2024年销售情况'!BH:BH) -> 0 | N16: =SUMIF(单品目标年销量!$C:$C,$C:$C,单品目标年销量!$W:$W)*SUMIF('2024年销售情况'!$C:$C,$C:$C,'2024年销售情况'!BL:BL) -> 0 | O16: =SUMIF(单品目标年销量!$C:$C,$C:$C,单品目标年销量!$W:$W)*SUMIF('2024年销售情况'!$C:$C,$C:$C,'2024年销售情况'!BP:BP) -> 0 | P16: =SUMIF(单品目标年销量!$C:$C,$C:$C,单品目标年销量!$W:$W)*SUMIF('2024年销售情况'!$C:$C,$C:$C,'2024年销售情况'!BT:BT) -> 0 | Q16: =SUMIF(单品目标年销量!$C:$C,$C:$C,单品目标年销量!$W:$W)*SUMIF('2024年销售情况'!$C:$C,$C:$C,'2024年销售情况'!BX:BX) -> 0 | R16: =SUM(F16:Q16) -> 0 | S16: =IFERROR(R16/年目标!$E$15,0) -> 0 | T16: =SUMIF('船长每月数据(2023年)'!E:E,C:C,'船长每月数据(2023年)'!R:R) -> 0
F17: =SUMIF(单品目标年销量!C:C,C:C,单品目标年销量!W:W)*SUMIF('2024年销售情况'!C:C,单品目标年销量!C:C,'2024年销售情况'!AF:AF) -> 0 | G17: =SUMIF(单品目标年销量!$C:$C,$C:$C,单品目标年销量!$W:$W)*SUMIF('2024年销售情况'!$C:$C,$C:$C,'2024年销售情况'!AJ:AJ) -> 0 | H17: =SUMIF(单品目标年销量!$C:$C,$C:$C,单品目标年销量!$W:$W)*SUMIF('2024年销售情况'!$C:$C,$C:$C,'2024年销售情况'!AN:AN) -> 0 | I17: =SUMIF(单品目标年销量!$C:$C,$C:$C,单品目标年销量!$W:$W)*SUMIF('2024年销售情况'!$C:$C,$C:$C,'2024年销售情况'!AR:AR) -> 0 | J17: =SUMIF(单品目标年销量!$C:$C,$C:$C,单品目标年销量!$W:$W)*SUMIF('2024年销售情况'!$C:$C,$C:$C,'2024年销售情况'!AV:AV) -> 0 | K17: =SUMIF(单品目标年销量!$C:$C,$C:$C,单品目标年销量!$W:$W)*SUMIF('2024年销售情况'!$C:$C,$C:$C,'2024年销售情况'!AZ:AZ) -> 0 | L17: =SUMIF(单品目标年销量!$C:$C,$C:$C,单品目标年销量!$W:$W)*SUMIF('2024年销售情况'!$C:$C,$C:$C,'2024年销售情况'!BD:BD) -> 0 | M17: =SUMIF(单品目标年销量!$C:$C,$C:$C,单品目标年销量!$W:$W)*SUMIF('2024年销售情况'!$C:$C,$C:$C,'2024年销售情况'!BH:BH) -> 0 | N17: =SUMIF(单品目标年销量!$C:$C,$C:$C,单品目标年销量!$W:$W)*SUMIF('2024年销售情况'!$C:$C,$C:$C,'2024年销售情况'!BL:BL) -> 0 | O17: =SUMIF(单品目标年销量!$C:$C,$C:$C,单品目标年销量!$W:$W)*SUMIF('2024年销售情况'!$C:$C,$C:$C,'2024年销售情况'!BP:BP) -> 0 | P17: =SUMIF(单品目标年销量!$C:$C,$C:$C,单品目标年销量!$W:$W)*SUMIF('2024年销售情况'!$C:$C,$C:$C,'2024年销售情况'!BT:BT) -> 0 | Q17: =SUMIF(单品目标年销量!$C:$C,$C:$C,单品目标年销量!$W:$W)*SUMIF('2024年销售情况'!$C:$C,$C:$C,'2024年销售情况'!BX:BX) -> 0 | R17: =SUM(F17:Q17) -> 0 | S17: =IFERROR(R17/年目标!$E$15,0) -> 0 | T17: =SUMIF('船长每月数据(2023年)'!E:E,C:C,'船长每月数据(2023年)'!R:R) -> 0
F18: =SUMIF(单品目标年销量!C:C,C:C,单品目标年销量!W:W)*SUMIF('2024年销售情况'!C:C,单品目标年销量!C:C,'2024年销售情况'!AF:AF) -> 0 | G18: =SUMIF(单品目标年销量!$C:$C,$C:$C,单品目标年销量!$W:$W)*SUMIF('2024年销售情况'!$C:$C,$C:$C,'2024年销售情况'!AJ:AJ) -> 0 | H18: =SUMIF(单品目标年销量!$C:$C,$C:$C,单品目标年销量!$W:$W)*SUMIF('2024年销售情况'!$C:$C,$C:$C,'2024年销售情况'!AN:AN) -> 0 | I18: =SUMIF(单品目标年销量!$C:$C,$C:$C,单品目标年销量!$W:$W)*SUMIF('2024年销售情况'!$C:$C,$C:$C,'2024年销售情况'!AR:AR) -> 0 | J18: =SUMIF(单品目标年销量!$C:$C,$C:$C,单品目标年销量!$W:$W)*SUMIF('2024年销售情况'!$C:$C,$C:$C,'2024年销售情况'!AV:AV) -> 0 | K18: =SUMIF(单品目标年销量!$C:$C,$C:$C,单品目标年销量!$W:$W)*SUMIF('2024年销售情况'!$C:$C,$C:$C,'2024年销售情况'!AZ:AZ) -> 0 | L18: =SUMIF(单品目标年销量!$C:$C,$C:$C,单品目标年销量!$W:$W)*SUMIF('2024年销售情况'!$C:$C,$C:$C,'2024年销售情况'!BD:BD) -> 0 | M18: =SUMIF(单品目标年销量!$C:$C,$C:$C,单品目标年销量!$W:$W)*SUMIF('2024年销售情况'!$C:$C,$C:$C,'2024年销售情况'!BH:BH) -> 0 | N18: =SUMIF(单品目标年销量!$C:$C,$C:$C,单品目标年销量!$W:$W)*SUMIF('2024年销售情况'!$C:$C,$C:$C,'2024年销售情况'!BL:BL) -> 0 | O18: =SUMIF(单品目标年销量!$C:$C,$C:$C,单品目标年销量!$W:$W)*SUMIF('2024年销售情况'!$C:$C,$C:$C,'2024年销售情况'!BP:BP) -> 0 | P18: =SUMIF(单品目标年销量!$C:$C,$C:$C,单品目标年销量!$W:$W)*SUMIF('2024年销售情况'!$C:$C,$C:$C,'2024年销售情况'!BT:BT) -> 0 | Q18: =SUMIF(单品目标年销量!$C:$C,$C:$C,单品目标年销量!$W:$W)*SUMIF('2024年销售情况'!$C:$C,$C:$C,'2024年销售情况'!BX:BX) -> 0 | R18: =SUM(F18:Q18) -> 0 | S18: =IFERROR(R18/年目标!$E$15,0) -> 0 | T18: =SUMIF('船长每月数据(2023年)'!E:E,C:C,'船长每月数据(2023年)'!R:R) -> 0
F19: =SUMIF(单品目标年销量!C:C,C:C,单品目标年销量!W:W)*SUMIF('2024年销售情况'!C:C,单品目标年销量!C:C,'2024年销售情况'!AF:AF) -> 0 | G19: =SUMIF(单品目标年销量!$C:$C,$C:$C,单品目标年销量!$W:$W)*SUMIF('2024年销售情况'!$C:$C,$C:$C,'2024年销售情况'!AJ:AJ) -> 0 | H19: =SUMIF(单品目标年销量!$C:$C,$C:$C,单品目标年销量!$W:$W)*SUMIF('2024年销售情况'!$C:$C,$C:$C,'2024年销售情况'!AN:AN) -> 0 | I19: =SUMIF(单品目标年销量!$C:$C,$C:$C,单品目标年销量!$W:$W)*SUMIF('2024年销售情况'!$C:$C,$C:$C,'2024年销售情况'!AR:AR) -> 0 | J19: =SUMIF(单品目标年销量!$C:$C,$C:$C,单品目标年销量!$W:$W)*SUMIF('2024年销售情况'!$C:$C,$C:$C,'2024年销售情况'!AV:AV) -> 0 | K19: =SUMIF(单品目标年销量!$C:$C,$C:$C,单品目标年销量!$W:$W)*SUMIF('2024年销售情况'!$C:$C,$C:$C,'2024年销售情况'!AZ:AZ) -> 0 | L19: =SUMIF(单品目标年销量!$C:$C,$C:$C,单品目标年销量!$W:$W)*SUMIF('2024年销售情况'!$C:$C,$C:$C,'2024年销售情况'!BD:BD) -> 0 | M19: =SUMIF(单品目标年销量!$C:$C,$C:$C,单品目标年销量!$W:$W)*SUMIF('2024年销售情况'!$C:$C,$C:$C,'2024年销售情况'!BH:BH) -> 0 | N19: =SUMIF(单品目标年销量!$C:$C,$C:$C,单品目标年销量!$W:$W)*SUMIF('2024年销售情况'!$C:$C,$C:$C,'2024年销售情况'!BL:BL) -> 0 | O19: =SUMIF(单品目标年销量!$C:$C,$C:$C,单品目标年销量!$W:$W)*SUMIF('2024年销售情况'!$C:$C,$C:$C,'2024年销售情况'!BP:BP) -> 0 | P19: =SUMIF(单品目标年销量!$C:$C,$C:$C,单品目标年销量!$W:$W)*SUMIF('2024年销售情况'!$C:$C,$C:$C,'2024年销售情况'!BT:BT) -> 0 | Q19: =SUMIF(单品目标年销量!$C:$C,$C:$C,单品目标年销量!$W:$W)*SUMIF('2024年销售情况'!$C:$C,$C:$C,'2024年销售情况'!BX:BX) -> 0 | R19: =SUM(F19:Q19) -> 0 | S19: =IFERROR(R19/年目标!$E$15,0) -> 0 | T19: =SUMIF('船长每月数据(2023年)'!E:E,C:C,'船长每月数据(2023年)'!R:R) -> 0
F20: =SUMIF(单品目标年销量!C:C,C:C,单品目标年销量!W:W)*SUMIF('2024年销售情况'!C:C,单品目标年销量!C:C,'2024年销售情况'!AF:AF) -> 0 | G20: =SUMIF(单品目标年销量!$C:$C,$C:$C,单品目标年销量!$W:$W)*SUMIF('2024年销售情况'!$C:$C,$C:$C,'2024年销售情况'!AJ:AJ) -> 0 | H20: =SUMIF(单品目标年销量!$C:$C,$C:$C,单品目标年销量!$W:$W)*SUMIF('2024年销售情况'!$C:$C,$C:$C,'2024年销售情况'!AN:AN) -> 0 | I20: =SUMIF(单品目标年销量!$C:$C,$C:$C,单品目标年销量!$W:$W)*SUMIF('2024年销售情况'!$C:$C,$C:$C,'2024年销售情况'!AR:AR) -> 0 | J20: =SUMIF(单品目标年销量!$C:$C,$C:$C,单品目标年销量!$W:$W)*SUMIF('2024年销售情况'!$C:$C,$C:$C,'2024年销售情况'!AV:AV) -> 0 | K20: =SUMIF(单品目标年销量!$C:$C,$C:$C,单品目标年销量!$W:$W)*SUMIF('2024年销售情况'!$C:$C,$C:$C,'2024年销售情况'!AZ:AZ) -> 0 | L20: =SUMIF(单品目标年销量!$C:$C,$C:$C,单品目标年销量!$W:$W)*SUMIF('2024年销售情况'!$C:$C,$C:$C,'2024年销售情况'!BD:BD) -> 0 | M20: =SUMIF(单品目标年销量!$C:$C,$C:$C,单品目标年销量!$W:$W)*SUMIF('2024年销售情况'!$C:$C,$C:$C,'2024年销售情况'!BH:BH) -> 0 | N20: =SUMIF(单品目标年销量!$C:$C,$C:$C,单品目标年销量!$W:$W)*SUMIF('2024年销售情况'!$C:$C,$C:$C,'2024年销售情况'!BL:BL) -> 0 | O20: =SUMIF(单品目标年销量!$C:$C,$C:$C,单品目标年销量!$W:$W)*SUMIF('2024年销售情况'!$C:$C,$C:$C,'2024年销售情况'!BP:BP) -> 0 | P20: =SUMIF(单品目标年销量!$C:$C,$C:$C,单品目标年销量!$W:$W)*SUMIF('2024年销售情况'!$C:$C,$C:$C,'2024年销售情况'!BT:BT) -> 0 | Q20: =SUMIF(单品目标年销量!$C:$C,$C:$C,单品目标年销量!$W:$W)*SUMIF('2024年销售情况'!$C:$C,$C:$C,'2024年销售情况'!BX:BX) -> 0 | R20: =SUM(F20:Q20) -> 0 | S20: =IFERROR(R20/年目标!$E$15,0) -> 0 | T20: =SUMIF('船长每月数据(2023年)'!E:E,C:C,'船长每月数据(2023年)'!R:R) -> 0
F21: =SUMIF(单品目标年销量!C:C,C:C,单品目标年销量!W:W)*SUMIF('2024年销售情况'!C:C,单品目标年销量!C:C,'2024年销售情况'!AF:AF) -> 0 | G21: =SUMIF(单品目标年销量!$C:$C,$C:$C,单品目标年销量!$W:$W)*SUMIF('2024年销售情况'!$C:$C,$C:$C,'2024年销售情况'!AJ:AJ) -> 0 | H21: =SUMIF(单品目标年销量!$C:$C,$C:$C,单品目标年销量!$W:$W)*SUMIF('2024年销售情况'!$C:$C,$C:$C,'2024年销售情况'!AN:AN) -> 0 | I21: =SUMIF(单品目标年销量!$C:$C,$C:$C,单品目标年销量!$W:$W)*SUMIF('2024年销售情况'!$C:$C,$C:$C,'2024年销售情况'!AR:AR) -> 0 | J21: =SUMIF(单品目标年销量!$C:$C,$C:$C,单品目标年销量!$W:$W)*SUMIF('2024年销售情况'!$C:$C,$C:$C,'2024年销售情况'!AV:AV) -> 0 | K21: =SUMIF(单品目标年销量!$C:$C,$C:$C,单品目标年销量!$W:$W)*SUMIF('2024年销售情况'!$C:$C,$C:$C,'2024年销售情况'!AZ:AZ) -> 0 | L21: =SUMIF(单品目标年销量!$C:$C,$C:$C,单品目标年销量!$W:$W)*SUMIF('2024年销售情况'!$C:$C,$C:$C,'2024年销售情况'!BD:BD) -> 0 | M21: =SUMIF(单品目标年销量!$C:$C,$C:$C,单品目标年销量!$W:$W)*SUMIF('2024年销售情况'!$C:$C,$C:$C,'2024年销售情况'!BH:BH) -> 0 | N21: =SUMIF(单品目标年销量!$C:$C,$C:$C,单品目标年销量!$W:$W)*SUMIF('2024年销售情况'!$C:$C,$C:$C,'2024年销售情况'!BL:BL) -> 0 | O21: =SUMIF(单品目标年销量!$C:$C,$C:$C,单品目标年销量!$W:$W)*SUMIF('2024年销售情况'!$C:$C,$C:$C,'2024年销售情况'!BP:BP) -> 0 | P21: =SUMIF(单品目标年销量!$C:$C,$C:$C,单品目标年销量!$W:$W)*SUMIF('2024年销售情况'!$C:$C,$C:$C,'2024年销售情况'!BT:BT) -> 0 | Q21: =SUMIF(单品目标年销量!$C:$C,$C:$C,单品目标年销量!$W:$W)*SUMIF('2024年销售情况'!$C:$C,$C:$C,'2024年销售情况'!BX:BX) -> 0 | R21: =SUM(F21:Q21) -> 0 | S21: =IFERROR(R21/年目标!$E$15,0) -> 0 | T21: =SUMIF('船长每月数据(2023年)'!E:E,C:C,'船长每月数据(2023年)'!R:R) -> 0
F22: =SUMIF(单品目标年销量!C:C,C:C,单品目标年销量!W:W)*SUMIF('2024年销售情况'!C:C,单品目标年销量!C:C,'2024年销售情况'!AF:AF) -> 0 | G22: =SUMIF(单品目标年销量!$C:$C,$C:$C,单品目标年销量!$W:$W)*SUMIF('2024年销售情况'!$C:$C,$C:$C,'2024年销售情况'!AJ:AJ) -> 0 | H22: =SUMIF(单品目标年销量!$C:$C,$C:$C,单品目标年销量!$W:$W)*SUMIF('2024年销售情况'!$C:$C,$C:$C,'2024年销售情况'!AN:AN) -> 0 | I22: =SUMIF(单品目标年销量!$C:$C,$C:$C,单品目标年销量!$W:$W)*SUMIF('2024年销售情况'!$C:$C,$C:$C,'2024年销售情况'!AR:AR) -> 0 | J22: =SUMIF(单品目标年销量!$C:$C,$C:$C,单品目标年销量!$W:$W)*SUMIF('2024年销售情况'!$C:$C,$C:$C,'2024年销售情况'!AV:AV) -> 0 | K22: =SUMIF(单品目标年销量!$C:$C,$C:$C,单品目标年销量!$W:$W)*SUMIF('2024年销售情况'!$C:$C,$C:$C,'2024年销售情况'!AZ:AZ) -> 0 | L22: =SUMIF(单品目标年销量!$C:$C,$C:$C,单品目标年销量!$W:$W)*SUMIF('2024年销售情况'!$C:$C,$C:$C,'2024年销售情况'!BD:BD) -> 0 | M22: =SUMIF(单品目标年销量!$C:$C,$C:$C,单品目标年销量!$W:$W)*SUMIF('2024年销售情况'!$C:$C,$C:$C,'2024年销售情况'!BH:BH) -> 0 | N22: =SUMIF(单品目标年销量!$C:$C,$C:$C,单品目标年销量!$W:$W)*SUMIF('2024年销售情况'!$C:$C,$C:$C,'2024年销售情况'!BL:BL) -> 0 | O22: =SUMIF(单品目标年销量!$C:$C,$C:$C,单品目标年销量!$W:$W)*SUMIF('2024年销售情况'!$C:$C,$C:$C,'2024年销售情况'!BP:BP) -> 0 | P22: =SUMIF(单品目标年销量!$C:$C,$C:$C,单品目标年销量!$W:$W)*SUMIF('2024年销售情况'!$C:$C,$C:$C,'2024年销售情况'!BT:BT) -> 0 | Q22: =SUMIF(单品目标年销量!$C:$C,$C:$C,单品目标年销量!$W:$W)*SUMIF('2024年销售情况'!$C:$C,$C:$C,'2024年销售情况'!BX:BX) -> 0 | R22: =SUM(F22:Q22) -> 0 | S22: =IFERROR(R22/年目标!$E$15,0) -> 0 | T22: =SUMIF('船长每月数据(2023年)'!E:E,C:C,'船长每月数据(2023年)'!R:R) -> 0
F23: =SUMIF(单品目标年销量!C:C,C:C,单品目标年销量!W:W)*SUMIF('2024年销售情况'!C:C,单品目标年销量!C:C,'2024年销售情况'!AF:AF) -> 0 | G23: =SUMIF(单品目标年销量!$C:$C,$C:$C,单品目标年销量!$W:$W)*SUMIF('2024年销售情况'!$C:$C,$C:$C,'2024年销售情况'!AJ:AJ) -> 0 | H23: =SUMIF(单品目标年销量!$C:$C,$C:$C,单品目标年销量!$W:$W)*SUMIF('2024年销售情况'!$C:$C,$C:$C,'2024年销售情况'!AN:AN) -> 0 | I23: =SUMIF(单品目标年销量!$C:$C,$C:$C,单品目标年销量!$W:$W)*SUMIF('2024年销售情况'!$C:$C,$C:$C,'2024年销售情况'!AR:AR) -> 0 | J23: =SUMIF(单品目标年销量!$C:$C,$C:$C,单品目标年销量!$W:$W)*SUMIF('2024年销售情况'!$C:$C,$C:$C,'2024年销售情况'!AV:AV) -> 0 | K23: =SUMIF(单品目标年销量!$C:$C,$C:$C,单品目标年销量!$W:$W)*SUMIF('2024年销售情况'!$C:$C,$C:$C,'2024年销售情况'!AZ:AZ) -> 0 | L23: =SUMIF(单品目标年销量!$C:$C,$C:$C,单品目标年销量!$W:$W)*SUMIF('2024年销售情况'!$C:$C,$C:$C,'2024年销售情况'!BD:BD) -> 0 | M23: =SUMIF(单品目标年销量!$C:$C,$C:$C,单品目标年销量!$W:$W)*SUMIF('2024年销售情况'!$C:$C,$C:$C,'2024年销售情况'!BH:BH) -> 0 | N23: =SUMIF(单品目标年销量!$C:$C,$C:$C,单品目标年销量!$W:$W)*SUMIF('2024年销售情况'!$C:$C,$C:$C,'2024年销售情况'!BL:BL) -> 0 | O23: =SUMIF(单品目标年销量!$C:$C,$C:$C,单品目标年销量!$W:$W)*SUMIF('2024年销售情况'!$C:$C,$C:$C,'2024年销售情况'!BP:BP) -> 0 | P23: =SUMIF(单品目标年销量!$C:$C,$C:$C,单品目标年销量!$W:$W)*SUMIF('2024年销售情况'!$C:$C,$C:$C,'2024年销售情况'!BT:BT) -> 0 | Q23: =SUMIF(单品目标年销量!$C:$C,$C:$C,单品目标年销量!$W:$W)*SUMIF('2024年销售情况'!$C:$C,$C:$C,'2024年销售情况'!BX:BX) -> 0 | R23: =SUM(F23:Q23) -> 0 | S23: =IFERROR(R23/年目标!$E$15,0) -> 0 | T23: =SUMIF('船长每月数据(2023年)'!E:E,C:C,'船长每月数据(2023年)'!R:R) -> 0
F24: =SUMIF(单品目标年销量!C:C,C:C,单品目标年销量!W:W)*SUMIF('2024年销售情况'!C:C,单品目标年销量!C:C,'2024年销售情况'!AF:AF) -> 0 | G24: =SUMIF(单品目标年销量!$C:$C,$C:$C,单品目标年销量!$W:$W)*SUMIF('2024年销售情况'!$C:$C,$C:$C,'2024年销售情况'!AJ:AJ) -> 0 | H24: =SUMIF(单品目标年销量!$C:$C,$C:$C,单品目标年销量!$W:$W)*SUMIF('2024年销售情况'!$C:$C,$C:$C,'2024年销售情况'!AN:AN) -> 0 | I24: =SUMIF(单品目标年销量!$C:$C,$C:$C,单品目标年销量!$W:$W)*SUMIF('2024年销售情况'!$C:$C,$C:$C,'2024年销售情况'!AR:AR) -> 0 | J24: =SUMIF(单品目标年销量!$C:$C,$C:$C,单品目标年销量!$W:$W)*SUMIF('2024年销售情况'!$C:$C,$C:$C,'2024年销售情况'!AV:AV) -> 0 | K24: =SUMIF(单品目标年销量!$C:$C,$C:$C,单品目标年销量!$W:$W)*SUMIF('2024年销售情况'!$C:$C,$C:$C,'2024年销售情况'!AZ:AZ) -> 0 | L24: =SUMIF(单品目标年销量!$C:$C,$C:$C,单品目标年销量!$W:$W)*SUMIF('2024年销售情况'!$C:$C,$C:$C,'2024年销售情况'!BD:BD) -> 0 | M24: =SUMIF(单品目标年销量!$C:$C,$C:$C,单品目标年销量!$W:$W)*SUMIF('2024年销售情况'!$C:$C,$C:$C,'2024年销售情况'!BH:BH) -> 0 | N24: =SUMIF(单品目标年销量!$C:$C,$C:$C,单品目标年销量!$W:$W)*SUMIF('2024年销售情况'!$C:$C,$C:$C,'2024年销售情况'!BL:BL) -> 0 | O24: =SUMIF(单品目标年销量!$C:$C,$C:$C,单品目标年销量!$W:$W)*SUMIF('2024年销售情况'!$C:$C,$C:$C,'2024年销售情况'!BP:BP) -> 0 | P24: =SUMIF(单品目标年销量!$C:$C,$C:$C,单品目标年销量!$W:$W)*SUMIF('2024年销售情况'!$C:$C,$C:$C,'2024年销售情况'!BT:BT) -> 0 | Q24: =SUMIF(单品目标年销量!$C:$C,$C:$C,单品目标年销量!$W:$W)*SUMIF('2024年销售情况'!$C:$C,$C:$C,'2024年销售情况'!BX:BX) -> 0 | R24: =SUM(F24:Q24) -> 0 | S24: =IFERROR(R24/年目标!$E$15,0) -> 0 | T24: =SUMIF('船长每月数据(2023年)'!E:E,C:C,'船长每月数据(2023年)'!R:R) -> 0
F25: =SUMIF(单品目标年销量!C:C,C:C,单品目标年销量!W:W)*SUMIF('2024年销售情况'!C:C,C:C,'2024年销售情况'!AF:AF) -> 0 | G25: =SUMIF(单品目标年销量!$C:$C,$C:$C,单品目标年销量!$W:$W)*SUMIF('2024年销售情况'!$C:$C,$C:$C,'2024年销售情况'!AJ:AJ) -> 0 | H25: =SUMIF(单品目标年销量!$C:$C,$C:$C,单品目标年销量!$W:$W)*SUMIF('2024年销售情况'!$C:$C,$C:$C,'2024年销售情况'!AN:AN) -> 0 | I25: =SUMIF(单品目标年销量!$C:$C,$C:$C,单品目标年销量!$W:$W)*SUMIF('2024年销售情况'!$C:$C,$C:$C,'2024年销售情况'!AR:AR) -> 0 | J25: =SUMIF(单品目标年销量!$C:$C,$C:$C,单品目标年销量!$W:$W)*SUMIF('2024年销售情况'!$C:$C,$C:$C,'2024年销售情况'!AV:AV) -> 0 | K25: =SUMIF(单品目标年销量!$C:$C,$C:$C,单品目标年销量!$W:$W)*SUMIF('2024年销售情况'!$C:$C,$C:$C,'2024年销售情况'!AZ:AZ) -> 0 | L25: =SUMIF(单品目标年销量!$C:$C,$C:$C,单品目标年销量!$W:$W)*SUMIF('2024年销售情况'!$C:$C,$C:$C,'2024年销售情况'!BD:BD) -> 0 | M25: =SUMIF(单品目标年销量!$C:$C,$C:$C,单品目标年销量!$W:$W)*SUMIF('2024年销售情况'!$C:$C,$C:$C,'2024年销售情况'!BH:BH) -> 0 | N25: =SUMIF(单品目标年销量!$C:$C,$C:$C,单品目标年销量!$W:$W)*SUMIF('2024年销售情况'!$C:$C,$C:$C,'2024年销售情况'!BL:BL) -> 0 | O25: =SUMIF(单品目标年销量!$C:$C,$C:$C,单品目标年销量!$W:$W)*SUMIF('2024年销售情况'!$C:$C,$C:$C,'2024年销售情况'!BP:BP) -> 0 | P25: =SUMIF(单品目标年销量!$C:$C,$C:$C,单品目标年销量!$W:$W)*SUMIF('2024年销售情况'!$C:$C,$C:$C,'2024年销售情况'!BT:BT) -> 0 | Q25: =SUMIF(单品目标年销量!$C:$C,$C:$C,单品目标年销量!$W:$W)*SUMIF('2024年销售情况'!$C:$C,$C:$C,'2024年销售情况'!BX:BX) -> 0 | R25: =SUM(F25:Q25) -> 0 | S25: =IFERROR(R25/年目标!$E$15,0) -> 0 | T25: =SUMIF('船长每月数据(2023年)'!E:E,C:C,'船长每月数据(2023年)'!R:R) -> 0
F26: =SUMIF(单品目标年销量!C:C,C:C,单品目标年销量!W:W)*SUMIF('2024年销售情况'!C:C,C:C,'2024年销售情况'!AF:AF) -> 0 | G26: =SUMIF(单品目标年销量!$C:$C,$C:$C,单品目标年销量!$W:$W)*SUMIF('2024年销售情况'!$C:$C,$C:$C,'2024年销售情况'!AJ:AJ) -> 0 | H26: =SUMIF(单品目标年销量!$C:$C,$C:$C,单品目标年销量!$W:$W)*SUMIF('2024年销售情况'!$C:$C,$C:$C,'2024年销售情况'!AN:AN) -> 0 | I26: =SUMIF(单品目标年销量!$C:$C,$C:$C,单品目标年销量!$W:$W)*SUMIF('2024年销售情况'!$C:$C,$C:$C,'2024年销售情况'!AR:AR) -> 0 | J26: =SUMIF(单品目标年销量!$C:$C,$C:$C,单品目标年销量!$W:$W)*SUMIF('2024年销售情况'!$C:$C,$C:$C,'2024年销售情况'!AV:AV) -> 0 | K26: =SUMIF(单品目标年销量!$C:$C,$C:$C,单品目标年销量!$W:$W)*SUMIF('2024年销售情况'!$C:$C,$C:$C,'2024年销售情况'!AZ:AZ) -> 0 | L26: =SUMIF(单品目标年销量!$C:$C,$C:$C,单品目标年销量!$W:$W)*SUMIF('2024年销售情况'!$C:$C,$C:$C,'2024年销售情况'!BD:BD) -> 0 | M26: =SUMIF(单品目标年销量!$C:$C,$C:$C,单品目标年销量!$W:$W)*SUMIF('2024年销售情况'!$C:$C,$C:$C,'2024年销售情况'!BH:BH) -> 0 | N26: =SUMIF(单品目标年销量!$C:$C,$C:$C,单品目标年销量!$W:$W)*SUMIF('2024年销售情况'!$C:$C,$C:$C,'2024年销售情况'!BL:BL) -> 0 | O26: =SUMIF(单品目标年销量!$C:$C,$C:$C,单品目标年销量!$W:$W)*SUMIF('2024年销售情况'!$C:$C,$C:$C,'2024年销售情况'!BP:BP) -> 0 | P26: =SUMIF(单品目标年销量!$C:$C,$C:$C,单品目标年销量!$W:$W)*SUMIF('2024年销售情况'!$C:$C,$C:$C,'2024年销售情况'!BT:BT) -> 0 | Q26: =SUMIF(单品目标年销量!$C:$C,$C:$C,单品目标年销量!$W:$W)*SUMIF('2024年销售情况'!$C:$C,$C:$C,'2024年销售情况'!BX:BX) -> 0 | R26: =SUM(F26:Q26) -> 0 | S26: =IFERROR(R26/年目标!$E$15,0) -> 0 | T26: =SUMIF('船长每月数据(2023年)'!E:E,C:C,'船长每月数据(2023年)'!R:R) -> 0
F27: =SUMIF(单品目标年销量!C:C,C:C,单品目标年销量!W:W)*SUMIF('2024年销售情况'!C:C,C:C,'2024年销售情况'!AF:AF) -> 0 | G27: =SUMIF(单品目标年销量!$C:$C,$C:$C,单品目标年销量!$W:$W)*SUMIF('2024年销售情况'!$C:$C,$C:$C,'2024年销售情况'!AJ:AJ) -> 0 | H27: =SUMIF(单品目标年销量!$C:$C,$C:$C,单品目标年销量!$W:$W)*SUMIF('2024年销售情况'!$C:$C,$C:$C,'2024年销售情况'!AN:AN) -> 0 | I27: =SUMIF(单品目标年销量!$C:$C,$C:$C,单品目标年销量!$W:$W)*SUMIF('2024年销售情况'!$C:$C,$C:$C,'2024年销售情况'!AR:AR) -> 0 | J27: =SUMIF(单品目标年销量!$C:$C,$C:$C,单品目标年销量!$W:$W)*SUMIF('2024年销售情况'!$C:$C,$C:$C,'2024年销售情况'!AV:AV) -> 0 | K27: =SUMIF(单品目标年销量!$C:$C,$C:$C,单品目标年销量!$W:$W)*SUMIF('2024年销售情况'!$C:$C,$C:$C,'2024年销售情况'!AZ:AZ) -> 0 | L27: =SUMIF(单品目标年销量!$C:$C,$C:$C,单品目标年销量!$W:$W)*SUMIF('2024年销售情况'!$C:$C,$C:$C,'2024年销售情况'!BD:BD) -> 0 | M27: =SUMIF(单品目标年销量!$C:$C,$C:$C,单品目标年销量!$W:$W)*SUMIF('2024年销售情况'!$C:$C,$C:$C,'2024年销售情况'!BH:BH) -> 0 | N27: =SUMIF(单品目标年销量!$C:$C,$C:$C,单品目标年销量!$W:$W)*SUMIF('2024年销售情况'!$C:$C,$C:$C,'2024年销售情况'!BL:BL) -> 0 | O27: =SUMIF(单品目标年销量!$C:$C,$C:$C,单品目标年销量!$W:$W)*SUMIF('2024年销售情况'!$C:$C,$C:$C,'2024年销售情况'!BP:BP) -> 0 | P27: =SUMIF(单品目标年销量!$C:$C,$C:$C,单品目标年销量!$W:$W)*SUMIF('2024年销售情况'!$C:$C,$C:$C,'2024年销售情况'!BT:BT) -> 0 | Q27: =SUMIF(单品目标年销量!$C:$C,$C:$C,单品目标年销量!$W:$W)*SUMIF('2024年销售情况'!$C:$C,$C:$C,'2024年销售情况'!BX:BX) -> 0 | R27: =SUM(F27:Q27) -> 0 | S27: =IFERROR(R27/年目标!$E$15,0) -> 0 | T27: =SUMIF('船长每月数据(2023年)'!E:E,C:C,'船长每月数据(2023年)'!R:R) -> 0
F28: =SUMIF(单品目标年销量!C:C,C:C,单品目标年销量!W:W)*SUMIF('2024年销售情况'!C:C,C:C,'2024年销售情况'!AF:AF) -> 0 | G28: =SUMIF(单品目标年销量!$C:$C,$C:$C,单品目标年销量!$W:$W)*SUMIF('2024年销售情况'!$C:$C,$C:$C,'2024年销售情况'!AJ:AJ) -> 0 | H28: =SUMIF(单品目标年销量!$C:$C,$C:$C,单品目标年销量!$W:$W)*SUMIF('2024年销售情况'!$C:$C,$C:$C,'2024年销售情况'!AN:AN) -> 0 | I28: =SUMIF(单品目标年销量!$C:$C,$C:$C,单品目标年销量!$W:$W)*SUMIF('2024年销售情况'!$C:$C,$C:$C,'2024年销售情况'!AR:AR) -> 0 | J28: =SUMIF(单品目标年销量!$C:$C,$C:$C,单品目标年销量!$W:$W)*SUMIF('2024年销售情况'!$C:$C,$C:$C,'2024年销售情况'!AV:AV) -> 0 | K28: =SUMIF(单品目标年销量!$C:$C,$C:$C,单品目标年销量!$W:$W)*SUMIF('2024年销售情况'!$C:$C,$C:$C,'2024年销售情况'!AZ:AZ) -> 0 | L28: =SUMIF(单品目标年销量!$C:$C,$C:$C,单品目标年销量!$W:$W)*SUMIF('2024年销售情况'!$C:$C,$C:$C,'2024年销售情况'!BD:BD) -> 0 | M28: =SUMIF(单品目标年销量!$C:$C,$C:$C,单品目标年销量!$W:$W)*SUMIF('2024年销售情况'!$C:$C,$C:$C,'2024年销售情况'!BH:BH) -> 0 | N28: =SUMIF(单品目标年销量!$C:$C,$C:$C,单品目标年销量!$W:$W)*SUMIF('2024年销售情况'!$C:$C,$C:$C,'2024年销售情况'!BL:BL) -> 0 | O28: =SUMIF(单品目标年销量!$C:$C,$C:$C,单品目标年销量!$W:$W)*SUMIF('2024年销售情况'!$C:$C,$C:$C,'2024年销售情况'!BP:BP) -> 0 | P28: =SUMIF(单品目标年销量!$C:$C,$C:$C,单品目标年销量!$W:$W)*SUMIF('2024年销售情况'!$C:$C,$C:$C,'2024年销售情况'!BT:BT) -> 0 | Q28: =SUMIF(单品目标年销量!$C:$C,$C:$C,单品目标年销量!$W:$W)*SUMIF('2024年销售情况'!$C:$C,$C:$C,'2024年销售情况'!BX:BX) -> 0 | R28: =SUM(F28:Q28) -> 0 | S28: =IFERROR(R28/年目标!$E$15,0) -> 0 | T28: =SUMIF('船长每月数据(2023年)'!E:E,C:C,'船长每月数据(2023年)'!R:R) -> 0
F29: =SUMIF(单品目标年销量!C:C,C:C,单品目标年销量!W:W)*SUMIF('2024年销售情况'!C:C,C:C,'2024年销售情况'!AF:AF) -> 0 | G29: =SUMIF(单品目标年销量!$C:$C,$C:$C,单品目标年销量!$W:$W)*SUMIF('2024年销售情况'!$C:$C,$C:$C,'2024年销售情况'!AJ:AJ) -> 0 | H29: =SUMIF(单品目标年销量!$C:$C,$C:$C,单品目标年销量!$W:$W)*SUMIF('2024年销售情况'!$C:$C,$C:$C,'2024年销售情况'!AN:AN) -> 0 | I29: =SUMIF(单品目标年销量!$C:$C,$C:$C,单品目标年销量!$W:$W)*SUMIF('2024年销售情况'!$C:$C,$C:$C,'2024年销售情况'!AR:AR) -> 0 | J29: =SUMIF(单品目标年销量!$C:$C,$C:$C,单品目标年销量!$W:$W)*SUMIF('2024年销售情况'!$C:$C,$C:$C,'2024年销售情况'!AV:AV) -> 0 | K29: =SUMIF(单品目标年销量!$C:$C,$C:$C,单品目标年销量!$W:$W)*SUMIF('2024年销售情况'!$C:$C,$C:$C,'2024年销售情况'!AZ:AZ) -> 0 | L29: =SUMIF(单品目标年销量!$C:$C,$C:$C,单品目标年销量!$W:$W)*SUMIF('2024年销售情况'!$C:$C,$C:$C,'2024年销售情况'!BD:BD) -> 0 | M29: =SUMIF(单品目标年销量!$C:$C,$C:$C,单品目标年销量!$W:$W)*SUMIF('2024年销售情况'!$C:$C,$C:$C,'2024年销售情况'!BH:BH) -> 0 | N29: =SUMIF(单品目标年销量!$C:$C,$C:$C,单品目标年销量!$W:$W)*SUMIF('2024年销售情况'!$C:$C,$C:$C,'2024年销售情况'!BL:BL) -> 0 | O29: =SUMIF(单品目标年销量!$C:$C,$C:$C,单品目标年销量!$W:$W)*SUMIF('2024年销售情况'!$C:$C,$C:$C,'2024年销售情况'!BP:BP) -> 0 | P29: =SUMIF(单品目标年销量!$C:$C,$C:$C,单品目标年销量!$W:$W)*SUMIF('2024年销售情况'!$C:$C,$C:$C,'2024年销售情况'!BT:BT) -> 0 | Q29: =SUMIF(单品目标年销量!$C:$C,$C:$C,单品目标年销量!$W:$W)*SUMIF('2024年销售情况'!$C:$C,$C:$C,'2024年销售情况'!BX:BX) -> 0 | R29: =SUM(F29:Q29) -> 0 | S29: =IFERROR(R29/年目标!$E$15,0) -> 0 | T29: =SUMIF('船长每月数据(2023年)'!E:E,C:C,'船长每月数据(2023年)'!R:R) -> 0
F30: =SUMIF(单品目标年销量!C:C,C:C,单品目标年销量!W:W)*SUMIF('2024年销售情况'!C:C,C:C,'2024年销售情况'!AF:AF) -> 0 | G30: =SUMIF(单品目标年销量!$C:$C,$C:$C,单品目标年销量!$W:$W)*SUMIF('2024年销售情况'!$C:$C,$C:$C,'2024年销售情况'!AJ:AJ) -> 0 | H30: =SUMIF(单品目标年销量!$C:$C,$C:$C,单品目标年销量!$W:$W)*SUMIF('2024年销售情况'!$C:$C,$C:$C,'2024年销售情况'!AN:AN) -> 0 | I30: =SUMIF(单品目标年销量!$C:$C,$C:$C,单品目标年销量!$W:$W)*SUMIF('2024年销售情况'!$C:$C,$C:$C,'2024年销售情况'!AR:AR) -> 0 | J30: =SUMIF(单品目标年销量!$C:$C,$C:$C,单品目标年销量!$W:$W)*SUMIF('2024年销售情况'!$C:$C,$C:$C,'2024年销售情况'!AV:AV) -> 0 | K30: =SUMIF(单品目标年销量!$C:$C,$C:$C,单品目标年销量!$W:$W)*SUMIF('2024年销售情况'!$C:$C,$C:$C,'2024年销售情况'!AZ:AZ) -> 0 | L30: =SUMIF(单品目标年销量!$C:$C,$C:$C,单品目标年销量!$W:$W)*SUMIF('2024年销售情况'!$C:$C,$C:$C,'2024年销售情况'!BD:BD) -> 0 | M30: =SUMIF(单品目标年销量!$C:$C,$C:$C,单品目标年销量!$W:$W)*SUMIF('2024年销售情况'!$C:$C,$C:$C,'2024年销售情况'!BH:BH) -> 0 | N30: =SUMIF(单品目标年销量!$C:$C,$C:$C,单品目标年销量!$W:$W)*SUMIF('2024年销售情况'!$C:$C,$C:$C,'2024年销售情况'!BL:BL) -> 0 | O30: =SUMIF(单品目标年销量!$C:$C,$C:$C,单品目标年销量!$W:$W)*SUMIF('2024年销售情况'!$C:$C,$C:$C,'2024年销售情况'!BP:BP) -> 0 | P30: =SUMIF(单品目标年销量!$C:$C,$C:$C,单品目标年销量!$W:$W)*SUMIF('2024年销售情况'!$C:$C,$C:$C,'2024年销售情况'!BT:BT) -> 0 | Q30: =SUMIF(单品目标年销量!$C:$C,$C:$C,单品目标年销量!$W:$W)*SUMIF('2024年销售情况'!$C:$C,$C:$C,'2024年销售情况'!BX:BX) -> 0 | R30: =SUM(F30:Q30) -> 0 | S30: =IFERROR(R30/年目标!$E$15,0) -> 0 | T30: =SUMIF('船长每月数据(2023年)'!E:E,C:C,'船长每月数据(2023年)'!R:R) -> 0
F31: =SUMIF(单品目标年销量!C:C,C:C,单品目标年销量!W:W)*SUMIF('2024年销售情况'!C:C,C:C,'2024年销售情况'!AF:AF) -> 0 | G31: =SUMIF(单品目标年销量!$C:$C,$C:$C,单品目标年销量!$W:$W)*SUMIF('2024年销售情况'!$C:$C,$C:$C,'2024年销售情况'!AJ:AJ) -> 0 | H31: =SUMIF(单品目标年销量!$C:$C,$C:$C,单品目标年销量!$W:$W)*SUMIF('2024年销售情况'!$C:$C,$C:$C,'2024年销售情况'!AN:AN) -> 0 | I31: =SUMIF(单品目标年销量!$C:$C,$C:$C,单品目标年销量!$W:$W)*SUMIF('2024年销售情况'!$C:$C,$C:$C,'2024年销售情况'!AR:AR) -> 0 | J31: =SUMIF(单品目标年销量!$C:$C,$C:$C,单品目标年销量!$W:$W)*SUMIF('2024年销售情况'!$C:$C,$C:$C,'2024年销售情况'!AV:AV) -> 0 | K31: =SUMIF(单品目标年销量!$C:$C,$C:$C,单品目标年销量!$W:$W)*SUMIF('2024年销售情况'!$C:$C,$C:$C,'2024年销售情况'!AZ:AZ) -> 0 | L31: =SUMIF(单品目标年销量!$C:$C,$C:$C,单品目标年销量!$W:$W)*SUMIF('2024年销售情况'!$C:$C,$C:$C,'2024年销售情况'!BD:BD) -> 0 | M31: =SUMIF(单品目标年销量!$C:$C,$C:$C,单品目标年销量!$W:$W)*SUMIF('2024年销售情况'!$C:$C,$C:$C,'2024年销售情况'!BH:BH) -> 0 | N31: =SUMIF(单品目标年销量!$C:$C,$C:$C,单品目标年销量!$W:$W)*SUMIF('2024年销售情况'!$C:$C,$C:$C,'2024年销售情况'!BL:BL) -> 0 | O31: =SUMIF(单品目标年销量!$C:$C,$C:$C,单品目标年销量!$W:$W)*SUMIF('2024年销售情况'!$C:$C,$C:$C,'2024年销售情况'!BP:BP) -> 0 | P31: =SUMIF(单品目标年销量!$C:$C,$C:$C,单品目标年销量!$W:$W)*SUMIF('2024年销售情况'!$C:$C,$C:$C,'2024年销售情况'!BT:BT) -> 0 | Q31: =SUMIF(单品目标年销量!$C:$C,$C:$C,单品目标年销量!$W:$W)*SUMIF('2024年销售情况'!$C:$C,$C:$C,'2024年销售情况'!BX:BX) -> 0 | R31: =SUM(F31:Q31) -> 0 | S31: =IFERROR(R31/年目标!$E$15,0) -> 0 | T31: =SUMIF('船长每月数据(2023年)'!E:E,C:C,'船长每月数据(2023年)'!R:R) -> 0
F32: =SUMIF(单品目标年销量!C:C,C:C,单品目标年销量!W:W)*SUMIF('2024年销售情况'!C:C,C:C,'2024年销售情况'!AF:AF) -> 0 | G32: =SUMIF(单品目标年销量!$C:$C,$C:$C,单品目标年销量!$W:$W)*SUMIF('2024年销售情况'!$C:$C,$C:$C,'2024年销售情况'!AJ:AJ) -> 0 | H32: =SUMIF(单品目标年销量!$C:$C,$C:$C,单品目标年销量!$W:$W)*SUMIF('2024年销售情况'!$C:$C,$C:$C,'2024年销售情况'!AN:AN) -> 0 | I32: =SUMIF(单品目标年销量!$C:$C,$C:$C,单品目标年销量!$W:$W)*SUMIF('2024年销售情况'!$C:$C,$C:$C,'2024年销售情况'!AR:AR) -> 0 | J32: =SUMIF(单品目标年销量!$C:$C,$C:$C,单品目标年销量!$W:$W)*SUMIF('2024年销售情况'!$C:$C,$C:$C,'2024年销售情况'!AV:AV) -> 0 | K32: =SUMIF(单品目标年销量!$C:$C,$C:$C,单品目标年销量!$W:$W)*SUMIF('2024年销售情况'!$C:$C,$C:$C,'2024年销售情况'!AZ:AZ) -> 0 | L32: =SUMIF(单品目标年销量!$C:$C,$C:$C,单品目标年销量!$W:$W)*SUMIF('2024年销售情况'!$C:$C,$C:$C,'2024年销售情况'!BD:BD) -> 0 | M32: =SUMIF(单品目标年销量!$C:$C,$C:$C,单品目标年销量!$W:$W)*SUMIF('2024年销售情况'!$C:$C,$C:$C,'2024年销售情况'!BH:BH) -> 0 | N32: =SUMIF(单品目标年销量!$C:$C,$C:$C,单品目标年销量!$W:$W)*SUMIF('2024年销售情况'!$C:$C,$C:$C,'2024年销售情况'!BL:BL) -> 0 | O32: =SUMIF(单品目标年销量!$C:$C,$C:$C,单品目标年销量!$W:$W)*SUMIF('2024年销售情况'!$C:$C,$C:$C,'2024年销售情况'!BP:BP) -> 0 | P32: =SUMIF(单品目标年销量!$C:$C,$C:$C,单品目标年销量!$W:$W)*SUMIF('2024年销售情况'!$C:$C,$C:$C,'2024年销售情况'!BT:BT) -> 0 | Q32: =SUMIF(单品目标年销量!$C:$C,$C:$C,单品目标年销量!$W:$W)*SUMIF('2024年销售情况'!$C:$C,$C:$C,'2024年销售情况'!BX:BX) -> 0 | R32: =SUM(F32:Q32) -> 0 | S32: =IFERROR(R32/年目标!$E$15,0) -> 0 | T32: =SUMIF('船长每月数据(2023年)'!E:E,C:C,'船长每月数据(2023年)'!R:R) -> 0
F33: =SUMIF(单品目标年销量!C:C,C:C,单品目标年销量!W:W)*SUMIF('2024年销售情况'!C:C,C:C,'2024年销售情况'!AF:AF) -> 0 | G33: =SUMIF(单品目标年销量!$C:$C,$C:$C,单品目标年销量!$W:$W)*SUMIF('2024年销售情况'!$C:$C,$C:$C,'2024年销售情况'!AJ:AJ) -> 0 | H33: =SUMIF(单品目标年销量!$C:$C,$C:$C,单品目标年销量!$W:$W)*SUMIF('2024年销售情况'!$C:$C,$C:$C,'2024年销售情况'!AN:AN) -> 0 | I33: =SUMIF(单品目标年销量!$C:$C,$C:$C,单品目标年销量!$W:$W)*SUMIF('2024年销售情况'!$C:$C,$C:$C,'2024年销售情况'!AR:AR) -> 0 | J33: =SUMIF(单品目标年销量!$C:$C,$C:$C,单品目标年销量!$W:$W)*SUMIF('2024年销售情况'!$C:$C,$C:$C,'2024年销售情况'!AV:AV) -> 0 | K33: =SUMIF(单品目标年销量!$C:$C,$C:$C,单品目标年销量!$W:$W)*SUMIF('2024年销售情况'!$C:$C,$C:$C,'2024年销售情况'!AZ:AZ) -> 0 | L33: =SUMIF(单品目标年销量!$C:$C,$C:$C,单品目标年销量!$W:$W)*SUMIF('2024年销售情况'!$C:$C,$C:$C,'2024年销售情况'!BD:BD) -> 0 | M33: =SUMIF(单品目标年销量!$C:$C,$C:$C,单品目标年销量!$W:$W)*SUMIF('2024年销售情况'!$C:$C,$C:$C,'2024年销售情况'!BH:BH) -> 0 | N33: =SUMIF(单品目标年销量!$C:$C,$C:$C,单品目标年销量!$W:$W)*SUMIF('2024年销售情况'!$C:$C,$C:$C,'2024年销售情况'!BL:BL) -> 0 | O33: =SUMIF(单品目标年销量!$C:$C,$C:$C,单品目标年销量!$W:$W)*SUMIF('2024年销售情况'!$C:$C,$C:$C,'2024年销售情况'!BP:BP) -> 0 | P33: =SUMIF(单品目标年销量!$C:$C,$C:$C,单品目标年销量!$W:$W)*SUMIF('2024年销售情况'!$C:$C,$C:$C,'2024年销售情况'!BT:BT) -> 0 | Q33: =SUMIF(单品目标年销量!$C:$C,$C:$C,单品目标年销量!$W:$W)*SUMIF('2024年销售情况'!$C:$C,$C:$C,'2024年销售情况'!BX:BX) -> 0 | R33: =SUM(F33:Q33) -> 0 | S33: =IFERROR(R33/年目标!$E$15,0) -> 0 | T33: =SUMIF('船长每月数据(2023年)'!E:E,C:C,'船长每月数据(2023年)'!R:R) -> 0
F34: =SUMIF(单品目标年销量!C:C,C:C,单品目标年销量!W:W)*SUMIF('2024年销售情况'!C:C,C:C,'2024年销售情况'!AF:AF) -> 0 | G34: =SUMIF(单品目标年销量!$C:$C,$C:$C,单品目标年销量!$W:$W)*SUMIF('2024年销售情况'!$C:$C,$C:$C,'2024年销售情况'!AJ:AJ) -> 0 | H34: =SUMIF(单品目标年销量!$C:$C,$C:$C,单品目标年销量!$W:$W)*SUMIF('2024年销售情况'!$C:$C,$C:$C,'2024年销售情况'!AN:AN) -> 0 | I34: =SUMIF(单品目标年销量!$C:$C,$C:$C,单品目标年销量!$W:$W)*SUMIF('2024年销售情况'!$C:$C,$C:$C,'2024年销售情况'!AR:AR) -> 0 | J34: =SUMIF(单品目标年销量!$C:$C,$C:$C,单品目标年销量!$W:$W)*SUMIF('2024年销售情况'!$C:$C,$C:$C,'2024年销售情况'!AV:AV) -> 0 | K34: =SUMIF(单品目标年销量!$C:$C,$C:$C,单品目标年销量!$W:$W)*SUMIF('2024年销售情况'!$C:$C,$C:$C,'2024年销售情况'!AZ:AZ) -> 0 | L34: =SUMIF(单品目标年销量!$C:$C,$C:$C,单品目标年销量!$W:$W)*SUMIF('2024年销售情况'!$C:$C,$C:$C,'2024年销售情况'!BD:BD) -> 0 | M34: =SUMIF(单品目标年销量!$C:$C,$C:$C,单品目标年销量!$W:$W)*SUMIF('2024年销售情况'!$C:$C,$C:$C,'2024年销售情况'!BH:BH) -> 0 | N34: =SUMIF(单品目标年销量!$C:$C,$C:$C,单品目标年销量!$W:$W)*SUMIF('2024年销售情况'!$C:$C,$C:$C,'2024年销售情况'!BL:BL) -> 0 | O34: =SUMIF(单品目标年销量!$C:$C,$C:$C,单品目标年销量!$W:$W)*SUMIF('2024年销售情况'!$C:$C,$C:$C,'2024年销售情况'!BP:BP) -> 0 | P34: =SUMIF(单品目标年销量!$C:$C,$C:$C,单品目标年销量!$W:$W)*SUMIF('2024年销售情况'!$C:$C,$C:$C,'2024年销售情况'!BT:BT) -> 0 | Q34: =SUMIF(单品目标年销量!$C:$C,$C:$C,单品目标年销量!$W:$W)*SUMIF('2024年销售情况'!$C:$C,$C:$C,'2024年销售情况'!BX:BX) -> 0 | R34: =SUM(F34:Q34) -> 0 | S34: =IFERROR(R34/年目标!$E$15,0) -> 0 | T34: =SUMIF('船长每月数据(2023年)'!E:E,C:C,'船长每月数据(2023年)'!R:R) -> 0
F35: =SUMIF(单品目标年销量!C:C,C:C,单品目标年销量!W:W)*SUMIF('2024年销售情况'!C:C,C:C,'2024年销售情况'!AF:AF) -> 0 | G35: =SUMIF(单品目标年销量!$C:$C,$C:$C,单品目标年销量!$W:$W)*SUMIF('2024年销售情况'!$C:$C,$C:$C,'2024年销售情况'!AJ:AJ) -> 0 | H35: =SUMIF(单品目标年销量!$C:$C,$C:$C,单品目标年销量!$W:$W)*SUMIF('2024年销售情况'!$C:$C,$C:$C,'2024年销售情况'!AN:AN) -> 0 | I35: =SUMIF(单品目标年销量!$C:$C,$C:$C,单品目标年销量!$W:$W)*SUMIF('2024年销售情况'!$C:$C,$C:$C,'2024年销售情况'!AR:AR) -> 0 | J35: =SUMIF(单品目标年销量!$C:$C,$C:$C,单品目标年销量!$W:$W)*SUMIF('2024年销售情况'!$C:$C,$C:$C,'2024年销售情况'!AV:AV) -> 0 | K35: =SUMIF(单品目标年销量!$C:$C,$C:$C,单品目标年销量!$W:$W)*SUMIF('2024年销售情况'!$C:$C,$C:$C,'2024年销售情况'!AZ:AZ) -> 0 | L35: =SUMIF(单品目标年销量!$C:$C,$C:$C,单品目标年销量!$W:$W)*SUMIF('2024年销售情况'!$C:$C,$C:$C,'2024年销售情况'!BD:BD) -> 0 | M35: =SUMIF(单品目标年销量!$C:$C,$C:$C,单品目标年销量!$W:$W)*SUMIF('2024年销售情况'!$C:$C,$C:$C,'2024年销售情况'!BH:BH) -> 0 | N35: =SUMIF(单品目标年销量!$C:$C,$C:$C,单品目标年销量!$W:$W)*SUMIF('2024年销售情况'!$C:$C,$C:$C,'2024年销售情况'!BL:BL) -> 0 | O35: =SUMIF(单品目标年销量!$C:$C,$C:$C,单品目标年销量!$W:$W)*SUMIF('2024年销售情况'!$C:$C,$C:$C,'2024年销售情况'!BP:BP) -> 0 | P35: =SUMIF(单品目标年销量!$C:$C,$C:$C,单品目标年销量!$W:$W)*SUMIF('2024年销售情况'!$C:$C,$C:$C,'2024年销售情况'!BT:BT) -> 0 | Q35: =SUMIF(单品目标年销量!$C:$C,$C:$C,单品目标年销量!$W:$W)*SUMIF('2024年销售情况'!$C:$C,$C:$C,'2024年销售情况'!BX:BX) -> 0 | R35: =SUM(F35:Q35) -> 0 | S35: =IFERROR(R35/年目标!$E$15,0) -> 0 | T35: =SUMIF('船长每月数据(2023年)'!E:E,C:C,'船长每月数据(2023年)'!R:R) -> 0
F36: =SUMIF(单品目标年销量!C:C,C:C,单品目标年销量!W:W)*SUMIF('2024年销售情况'!C:C,C:C,'2024年销售情况'!AF:AF) -> 0 | G36: =SUMIF(单品目标年销量!$C:$C,$C:$C,单品目标年销量!$W:$W)*SUMIF('2024年销售情况'!$C:$C,$C:$C,'2024年销售情况'!AJ:AJ) -> 0 | H36: =SUMIF(单品目标年销量!$C:$C,$C:$C,单品目标年销量!$W:$W)*SUMIF('2024年销售情况'!$C:$C,$C:$C,'2024年销售情况'!AN:AN) -> 0 | I36: =SUMIF(单品目标年销量!$C:$C,$C:$C,单品目标年销量!$W:$W)*SUMIF('2024年销售情况'!$C:$C,$C:$C,'2024年销售情况'!AR:AR) -> 0 | J36: =SUMIF(单品目标年销量!$C:$C,$C:$C,单品目标年销量!$W:$W)*SUMIF('2024年销售情况'!$C:$C,$C:$C,'2024年销售情况'!AV:AV) -> 0 | K36: =SUMIF(单品目标年销量!$C:$C,$C:$C,单品目标年销量!$W:$W)*SUMIF('2024年销售情况'!$C:$C,$C:$C,'2024年销售情况'!AZ:AZ) -> 0 | L36: =SUMIF(单品目标年销量!$C:$C,$C:$C,单品目标年销量!$W:$W)*SUMIF('2024年销售情况'!$C:$C,$C:$C,'2024年销售情况'!BD:BD) -> 0 | M36: =SUMIF(单品目标年销量!$C:$C,$C:$C,单品目标年销量!$W:$W)*SUMIF('2024年销售情况'!$C:$C,$C:$C,'2024年销售情况'!BH:BH) -> 0 | N36: =SUMIF(单品目标年销量!$C:$C,$C:$C,单品目标年销量!$W:$W)*SUMIF('2024年销售情况'!$C:$C,$C:$C,'2024年销售情况'!BL:BL) -> 0 | O36: =SUMIF(单品目标年销量!$C:$C,$C:$C,单品目标年销量!$W:$W)*SUMIF('2024年销售情况'!$C:$C,$C:$C,'2024年销售情况'!BP:BP) -> 0 | P36: =SUMIF(单品目标年销量!$C:$C,$C:$C,单品目标年销量!$W:$W)*SUMIF('2024年销售情况'!$C:$C,$C:$C,'2024年销售情况'!BT:BT) -> 0 | Q36: =SUMIF(单品目标年销量!$C:$C,$C:$C,单品目标年销量!$W:$W)*SUMIF('2024年销售情况'!$C:$C,$C:$C,'2024年销售情况'!BX:BX) -> 0 | R36: =SUM(F36:Q36) -> 0 | S36: =IFERROR(R36/年目标!$E$15,0) -> 0 | T36: =SUMIF('船长每月数据(2023年)'!E:E,C:C,'船长每月数据(2023年)'!R:R) -> 0

Sheet 2024年销售情况
A1: XXX - 2021-2022年销售情况
A2: 产品大类 | B2: 产品系列 | C2: ASIN | D2: 产品中文名 | E2: 44197 | F2: 44197 | G2: 44228 | H2: 44228 | I2: 44256 | J2: 44256 | K2: 44287 | L2: 44287 | M2: 44317 | N2: 44317 | O2: 44348 | P2: 44348 | Q2: 44378 | R2: 44378 | S2: 44409 | T2: 44409 | U2: 44440 | V2: 44440 | W2: 44470 | X2: 44470 | Y2: 44501 | Z2: 44501 | AA2: 44531 | AB2: 44531 | AC2: 44562 | AD2: 销量占比 | AE2: 44562 | AF2: 销售额占比 | AG2: 44593 | AH2: 销量占比 | AI2: 44593 | AJ2: 销售额占比 | AK2: 44621 | AL2: 销量占比 | AM2: 44621 | AN2: 销售额占比 | AO2: 44652 | AP2: 销量占比 | AQ2: 44652 | AR2: 销售额占比 | AS2: 44682 | AT2: 销量占比 | AU2: 44682 | AV2: 销售额占比 | AW2: 44713 | AX2: 销量占比 | AY2: 44713 | AZ2: 销售额占比 | BA2: 44743 | BB2: 销量占比 | BC2: 44743 | BD2: 销售额占比 | BE2: 44774 | BF2: 销量占比 | BG2: 44774 | BH2: 销售额占比 | BI2: 44805 | BJ2: 销量占比 | BK2: 44805 | BL2: 销售额占比 | BM2: 44835 | BN2: 销量占比 | BO2: 44835 | BP2: 销售额占比 | BQ2: 44866 | BR2: 销量占比 | BS2: 44866 | BT2: 销售额占比 | BU2: 44896 | BV2: 销量占比 | BW2: 44896 | BX2: 销售额占比
E3: =SUMIFS('船长每月数据(2022年)'!$P:$P,'船长每月数据(2022年)'!$F:$F,$E$2,'船长每月数据(2022年)'!$E:$E,$C:$C) -> 0 | F3: =SUMIFS('船长每月数据(2022年)'!$R:$R,'船长每月数据(2022年)'!$F:$F,$F$2,'船长每月数据(2022年)'!$E:$E,$C:$C) -> 0 | G3: =SUMIFS('船长每月数据(2022年)'!$P:$P,'船长每月数据(2022年)'!$F:$F,$G$2,'船长每月数据(2022年)'!$E:$E,$C:$C) -> 0 | H3: =SUMIFS('船长每月数据(2022年)'!$R:$R,'船长每月数据(2022年)'!$F:$F,$H$2,'船长每月数据(2022年)'!$E:$E,$C:$C) -> 0 | I3: =SUMIFS('船长每月数据(2022年)'!$P:$P,'船长每月数据(2022年)'!$F:$F,$I$2,'船长每月数据(2022年)'!$E:$E,$C:$C) -> 0 | J3: =SUMIFS('船长每月数据(2022年)'!$R:$R,'船长每月数据(2022年)'!$F:$F,$J$2,'船长每月数据(2022年)'!$E:$E,$C:$C) -> 0 | K3: =SUMIFS('船长每月数据(2022年)'!$P:$P,'船长每月数据(2022年)'!$F:$F,$K$2,'船长每月数据(2022年)'!$E:$E,$C:$C) -> 0 | L3: =SUMIFS('船长每月数据(2022年)'!$R:$R,'船长每月数据(2022年)'!$F:$F,$L$2,'船长每月数据(2022年)'!$E:$E,$C:$C) -> 0 | M3: =SUMIFS('船长每月数据(2022年)'!$P:$P,'船长每月数据(2022年)'!$F:$F,$M$2,'船长每月数据(2022年)'!$E:$E,$C:$C) -> 0 | N3: =SUMIFS('船长每月数据(2022年)'!$R:$R,'船长每月数据(2022年)'!$F:$F,$N$2,'船长每月数据(2022年)'!$E:$E,$C:$C) -> 0 | O3: =SUMIFS('船长每月数据(2022年)'!$P:$P,'船长每月数据(2022年)'!$F:$F,$O$2,'船长每月数据(2022年)'!$E:$E,$C:$C) -> 0 | P3: =SUMIFS('船长每月数据(2022年)'!$R:$R,'船长每月数据(2022年)'!$F:$F,$P$2,'船长每月数据(2022年)'!$E:$E,$C:$C) -> 0 | Q3: =SUMIFS('船长每月数据(2022年)'!$P:$P,'船长每月数据(2022年)'!$F:$F,$Q$2,'船长每月数据(2022年)'!$E:$E,$C:$C) -> 0 | R3: =SUMIFS('船长每月数据(2022年)'!$R:$R,'船长每月数据(2022年)'!$F:$F,$R$2,'船长每月数据(2022年)'!$E:$E,$C:$C) -> 0 | S3: =SUMIFS('船长每月数据(2022年)'!$P:$P,'船长每月数据(2022年)'!$F:$F,$S$2,'船长每月数据(2022年)'!$E:$E,$C:$C) -> 0 | T3: =SUMIFS('船长每月数据(2022年)'!$R:$R,'船长每月数据(2022年)'!$F:$F,$T$2,'船长每月数据(2022年)'!$E:$E,$C:$C) -> 0 | U3: =SUMIFS('船长每月数据(2022年)'!$P:$P,'船长每月数据(2022年)'!$F:$F,$U$2,'船长每月数据(2022年)'!$E:$E,$C:$C) -> 0 | V3: =SUMIFS('船长每月数据(2022年)'!$R:$R,'船长每月数据(2022年)'!$F:$F,$V$2,'船长每月数据(2022年)'!$E:$E,$C:$C) -> 0 | W3: =SUMIFS('船长每月数据(2022年)'!$P:$P,'船长每月数据(2022年)'!$F:$F,$W$2,'船长每月数据(2022年)'!$E:$E,$C:$C) -> 0 | X3: =SUMIFS('船长每月数据(2022年)'!$R:$R,'船长每月数据(2022年)'!$F:$F,$X$2,'船长每月数据(2022年)'!$E:$E,$C:$C) -> 0 | Y3: =SUMIFS('船长每月数据(2022年)'!$P:$P,'船长每月数据(2022年)'!$F:$F,$Y$2,'船长每月数据(2022年)'!$E:$E,$C:$C) -> 0 | Z3: =SUMIFS('船长每月数据(2022年)'!$R:$R,'船长每月数据(2022年)'!$F:$F,$Z$2,'船长每月数据(2022年)'!$E:$E,$C:$C) -> 0 | AA3: =SUMIFS('船长每月数据(2022年)'!$P:$P,'船长每月数据(2022年)'!$F:$F,$AA$2,'船长每月数据(2022年)'!$E:$E,$C:$C) -> 0 | AB3: =SUMIFS('船长每月数据(2022年)'!$R:$R,'船长每月数据(2022年)'!$F:$F,$AB$2,'船长每月数据(2022年)'!$E:$E,$C:$C) -> 0 | AC3: =SUMIFS('船长每月数据(2023年)'!P:P,'船长每月数据(2023年)'!F:F,$AC$2,'船长每月数据(2023年)'!E:E,C:C) -> 0 | AD3: =IFERROR(AC3/SUMIF('船长每月数据(2023年)'!$E:$E,$C:$C,'船长每月数据(2023年)'!$P:$P),0) -> 0 | AE3: =SUMIFS('船长每月数据(2023年)'!$R:$R,'船长每月数据(2023年)'!$F:$F,$AE$2,'船长每月数据(2023年)'!$E:$E,$C:$C) -> 0 | AF3: =IFERROR(AE3/SUMIF('船长每月数据(2023年)'!$E:$E,$C:$C,'船长每月数据(2023年)'!$R:$R),0) -> 0 | AG3: =SUMIFS('船长每月数据(2023年)'!P:P,'船长每月数据(2023年)'!F:F,$AG$2,'船长每月数据(2023年)'!E:E,C:C) -> 0 | AH3: =IFERROR(AG3/SUMIF('船长每月数据(2023年)'!$E:$E,$C:$C,'船长每月数据(2023年)'!$P:$P),0) -> 0 | AI3: =SUMIFS('船长每月数据(2023年)'!$R:$R,'船长每月数据(2023年)'!$F:$F,$AI$2,'船长每月数据(2023年)'!$E:$E,$C:$C) -> 0 | AJ3: =IFERROR(AI3/SUMIF('船长每月数据(2023年)'!$E:$E,$C:$C,'船长每月数据(2023年)'!$R:$R),0) -> 0 | AK3: =SUMIFS('船长每月数据(2023年)'!P:P,'船长每月数据(2023年)'!F:F,$AK$2,'船长每月数据(2023年)'!E:E,C:C) -> 0 | AL3: =IFERROR(AK3/SUMIF('船长每月数据(2023年)'!$E:$E,$C:$C,'船长每月数据(2023年)'!$P:$P),0) -> 0 | AM3: =SUMIFS('船长每月数据(2023年)'!$R:$R,'船长每月数据(2023年)'!$F:$F,$AM$2,'船长每月数据(2023年)'!$E:$E,$C:$C) -> 0 | AN3: =IFERROR(AM3/SUMIF('船长每月数据(2023年)'!$E:$E,$C:$C,'船长每月数据(2023年)'!$R:$R),0) -> 0 | AO3: =SUMIFS('船长每月数据(2023年)'!$P:$P,'船长每月数据(2023年)'!$F:$F,$AO$2,'船长每月数据(2023年)'!$E:$E,$C:$C) -> 0 | AP3: =IFERROR(AO3/SUMIF('船长每月数据(2023年)'!$E:$E,$C:$C,'船长每月数据(2023年)'!$P:$P),0) -> 0 | AQ3: =SUMIFS('船长每月数据(2023年)'!$R:$R,'船长每月数据(2023年)'!$F:$F,$AQ$2,'船长每月数据(2023年)'!$E:$E,$C:$C) -> 0 | AR3: =IFERROR(AQ3/SUMIF('船长每月数据(2023年)'!$E:$E,$C:$C,'船长每月数据(2023年)'!$R:$R),0) -> 0 | AS3: =SUMIFS('船长每月数据(2023年)'!$P:$P,'船长每月数据(2023年)'!$F:$F,$AS$2,'船长每月数据(2023年)'!$E:$E,$C:$C) -> 0 | AT3: =IFERROR(AS3/SUMIF('船长每月数据(2023年)'!$E:$E,$C:$C,'船长每月数据(2023年)'!$P:$P),0) -> 0 | AU3: =SUMIFS('船长每月数据(2023年)'!$R:$R,'船长每月数据(2023年)'!$F:$F,$AU$2,'船长每月数据(2023年)'!$E:$E,$C:$C) -> 0 | AV3: =IFERROR(AU3/SUMIF('船长每月数据(2023年)'!$E:$E,$C:$C,'船长每月数据(2023年)'!$R:$R),0) -> 0 | AW3: =SUMIFS('船长每月数据(2023年)'!$P:$P,'船长每月数据(2023年)'!$F:$F,$AW$2,'船长每月数据(2023年)'!$E:$E,$C:$C) -> 0 | AX3: =IFERROR(AW3/SUMIF('船长每月数据(2023年)'!$E:$E,$C:$C,'船长每月数据(2023年)'!$P:$P),0) -> 0 | AY3: =SUMIFS('船长每月数据(2023年)'!$R:$R,'船长每月数据(2023年)'!$F:$F,$AY$2,'船长每月数据(2023年)'!$E:$E,$C:$C) -> 0 | AZ3: =IFERROR(AY3/SUMIF('船长每月数据(2023年)'!$E:$E,$C:$C,'船长每月数据(2023年)'!$R:$R),0) -> 0 | BA3: =SUMIFS('船长每月数据(2023年)'!$P:$P,'船长每月数据(2023年)'!$F:$F,$BA$2,'船长每月数据(2023年)'!$E:$E,$C:$C) -> 0 | BB3: =IFERROR(BA3/SUMIF('船长每月数据(2023年)'!$E:$E,$C:$C,'船长每月数据(2023年)'!$P:$P),0) -> 0 | BC3: =SUMIFS('船长每月数据(2023年)'!$R:$R,'船长每月数据(2023年)'!$F:$F,$BC$2,'船长每月数据(2023年)'!$E:$E,$C:$C) -> 0 | BD3: =IFERROR(BC3/SUMIF('船长每月数据(2023年)'!$E:$E,$C:$C,'船长每月数据(2023年)'!$R:$R),0) -> 0 | BE3: =SUMIFS('船长每月数据(2023年)'!$P:$P,'船长每月数据(2023年)'!$F:$F,$BE$2,'船长每月数据(2023年)'!$E:$E,$C:$C) -> 0 | BF3: =IFERROR(BE3/SUMIF('船长每月数据(2023年)'!$E:$E,$C:$C,'船长每月数据(2023年)'!$P:$P),0) -> 0 | BG3: =SUMIFS('船长每月数据(2023年)'!$R:$R,'船长每月数据(2023年)'!$F:$F,$BG$2,'船长每月数据(2023年)'!$E:$E,$C:$C) -> 0 | BH3: =IFERROR(BG3/SUMIF('船长每月数据(2023年)'!$E:$E,$C:$C,'船长每月数据(2023年)'!$R:$R),0) -> 0 | BI3: =SUMIFS('船长每月数据(2023年)'!$P:$P,'船长每月数据(2023年)'!$F:$F,$BI$2,'船长每月数据(2023年)'!$E:$E,$C:$C) -> 0 | BJ3: =IFERROR(BI3/SUMIF('船长每月数据(2023年)'!$E:$E,$C:$C,'船长每月数据(2023年)'!$P:$P),0) -> 0 | BK3: =SUMIFS('船长每月数据(2023年)'!$R:$R,'船长每月数据(2023年)'!$F:$F,$BK$2,'船长每月数据(2023年)'!$E:$E,$C:$C) -> 0 | BL3: =IFERROR(BK3/SUMIF('船长每月数据(2023年)'!$E:$E,$C:$C,'船长每月数据(2023年)'!$R:$R),0) -> 0 | BM3: =SUMIFS('船长每月数据(2023年)'!$P:$P,'船长每月数据(2023年)'!$F:$F,$BM$2,'船长每月数据(2023年)'!$E:$E,$C:$C) -> 0 | BN3: =IFERROR(BM3/SUMIF('船长每月数据(2023年)'!$E:$E,$C:$C,'船长每月数据(2023年)'!$P:$P),0) -> 0 | BO3: =SUMIFS('船长每月数据(2023年)'!$R:$R,'船长每月数据(2023年)'!$F:$F,$BO$2,'船长每月数据(2023年)'!$E:$E,$C:$C) -> 0 | BP3: =IFERROR(BO3/SUMIF('船长每月数据(2023年)'!$E:$E,$C:$C,'船长每月数据(2023年)'!$R:$R),0) -> 0 | BQ3: =SUMIFS('船长每月数据(2023年)'!$P:$P,'船长每月数据(2023年)'!$F:$F,$BQ$2,'船长每月数据(2023年)'!$E:$E,$C:$C) -> 0 | BR3: =IFERROR(BQ3/SUMIF('船长每月数据(2023年)'!$E:$E,$C:$C,'船长每月数据(2023年)'!$P:$P),0) -> 0 | BS3: =SUMIFS('船长每月数据(2023年)'!$R:$R,'船长每月数据(2023年)'!$F:$F,$BS$2,'船长每月数据(2023年)'!$E:$E,$C:$C) -> 0 | BT3: =IFERROR(BS3/SUMIF('船长每月数据(2023年)'!$E:$E,$C:$C,'船长每月数据(2023年)'!$R:$R),0) -> 0 | BU3: =SUMIFS('船长每月数据(2023年)'!$P:$P,'船长每月数据(2023年)'!$F:$F,$BU$2,'船长每月数据(2023年)'!$E:$E,$C:$C) -> 0 | BV3: =IFERROR(BU3/SUMIF('船长每月数据(2023年)'!$E:$E,$C:$C,'船长每月数据(2023年)'!$P:$P),0) -> 0 | BW3: =SUMIFS('船长每月数据(2023年)'!$R:$R,'船长每月数据(2023年)'!$F:$F,$BW$2,'船长每月数据(2023年)'!$E:$E,$C:$C) -> 0 | BX3: =IFERROR(BW3/SUMIF('船长每月数据(2023年)'!$E:$E,$C:$C,'船长每月数据(2023年)'!$R:$R),0) -> 0
E4: =SUMIFS('船长每月数据(2022年)'!$P:$P,'船长每月数据(2022年)'!$F:$F,$E$2,'船长每月数据(2022年)'!E:E,C:C) -> 0 | F4: =SUMIFS('船长每月数据(2022年)'!$R:$R,'船长每月数据(2022年)'!$F:$F,$F$2,'船长每月数据(2022年)'!E:E,C:C) -> 0 | G4: =SUMIFS('船长每月数据(2022年)'!$P:$P,'船长每月数据(2022年)'!$F:$F,$G$2,'船长每月数据(2022年)'!$E:$E,$C:$C) -> 0 | H4: =SUMIFS('船长每月数据(2022年)'!$R:$R,'船长每月数据(2022年)'!$F:$F,$H$2,'船长每月数据(2022年)'!$E:$E,$C:$C) -> 0 | I4: =SUMIFS('船长每月数据(2022年)'!$P:$P,'船长每月数据(2022年)'!$F:$F,$I$2,'船长每月数据(2022年)'!$E:$E,$C:$C) -> 0 | J4: =SUMIFS('船长每月数据(2022年)'!$R:$R,'船长每月数据(2022年)'!$F:$F,$J$2,'船长每月数据(2022年)'!$E:$E,$C:$C) -> 0 | K4: =SUMIFS('船长每月数据(2022年)'!$P:$P,'船长每月数据(2022年)'!$F:$F,$K$2,'船长每月数据(2022年)'!$E:$E,$C:$C) -> 0 | L4: =SUMIFS('船长每月数据(2022年)'!$R:$R,'船长每月数据(2022年)'!$F:$F,$L$2,'船长每月数据(2022年)'!$E:$E,$C:$C) -> 0 | M4: =SUMIFS('船长每月数据(2022年)'!$P:$P,'船长每月数据(2022年)'!$F:$F,$M$2,'船长每月数据(2022年)'!$E:$E,$C:$C) -> 0 | N4: =SUMIFS('船长每月数据(2022年)'!$R:$R,'船长每月数据(2022年)'!$F:$F,$N$2,'船长每月数据(2022年)'!$E:$E,$C:$C) -> 0 | O4: =SUMIFS('船长每月数据(2022年)'!$P:$P,'船长每月数据(2022年)'!$F:$F,$O$2,'船长每月数据(2022年)'!$E:$E,$C:$C) -> 0 | P4: =SUMIFS('船长每月数据(2022年)'!$R:$R,'船长每月数据(2022年)'!$F:$F,$P$2,'船长每月数据(2022年)'!$E:$E,$C:$C) -> 0 | Q4: =SUMIFS('船长每月数据(2022年)'!$P:$P,'船长每月数据(2022年)'!$F:$F,$Q$2,'船长每月数据(2022年)'!$E:$E,$C:$C) -> 0 | R4: =SUMIFS('船长每月数据(2022年)'!$R:$R,'船长每月数据(2022年)'!$F:$F,$R$2,'船长每月数据(2022年)'!$E:$E,$C:$C) -> 0 | S4: =SUMIFS('船长每月数据(2022年)'!$P:$P,'船长每月数据(2022年)'!$F:$F,$S$2,'船长每月数据(2022年)'!$E:$E,$C:$C) -> 0 | T4: =SUMIFS('船长每月数据(2022年)'!$R:$R,'船长每月数据(2022年)'!$F:$F,$T$2,'船长每月数据(2022年)'!$E:$E,$C:$C) -> 0 | U4: =SUMIFS('船长每月数据(2022年)'!$P:$P,'船长每月数据(2022年)'!$F:$F,$U$2,'船长每月数据(2022年)'!$E:$E,$C:$C) -> 0 | V4: =SUMIFS('船长每月数据(2022年)'!$R:$R,'船长每月数据(2022年)'!$F:$F,$V$2,'船长每月数据(2022年)'!$E:$E,$C:$C) -> 0 | W4: =SUMIFS('船长每月数据(2022年)'!$P:$P,'船长每月数据(2022年)'!$F:$F,$W$2,'船长每月数据(2022年)'!$E:$E,$C:$C) -> 0 | X4: =SUMIFS('船长每月数据(2022年)'!$R:$R,'船长每月数据(2022年)'!$F:$F,$X$2,'船长每月数据(2022年)'!$E:$E,$C:$C) -> 0 | Y4: =SUMIFS('船长每月数据(2022年)'!$P:$P,'船长每月数据(2022年)'!$F:$F,$Y$2,'船长每月数据(2022年)'!$E:$E,$C:$C) -> 0 | Z4: =SUMIFS('船长每月数据(2022年)'!$R:$R,'船长每月数据(2022年)'!$F:$F,$Z$2,'船长每月数据(2022年)'!$E:$E,$C:$C) -> 0 | AA4: =SUMIFS('船长每月数据(2022年)'!$P:$P,'船长每月数据(2022年)'!$F:$F,$AA$2,'船长每月数据(2022年)'!$E:$E,$C:$C) -> 0 | AB4: =SUMIFS('船长每月数据(2022年)'!$R:$R,'船长每月数据(2022年)'!$F:$F,$AB$2,'船长每月数据(2022年)'!$E:$E,$C:$C) -> 0 | AC4: =SUMIFS('船长每月数据(2023年)'!P:P,'船长每月数据(2023年)'!F:F,$AC$2,'船长每月数据(2023年)'!E:E,C:C) -> 0 | AD4: =IFERROR(AC4/SUMIF('船长每月数据(2023年)'!$E:$E,C:C,'船长每月数据(2023年)'!P:P),0) -> 0 | AE4: =SUMIFS('船长每月数据(2023年)'!$R:$R,'船长每月数据(2023年)'!$F:$F,$AE$2,'船长每月数据(2023年)'!$E:$E,$C:$C) -> 0 | AF4: =IFERROR(AE4/SUMIF('船长每月数据(2023年)'!E:E,C:C,'船长每月数据(2023年)'!R:R),0) -> 0 | AG4: =SUMIFS('船长每月数据(2023年)'!P:P,'船长每月数据(2023年)'!F:F,$AG$2,'船长每月数据(2023年)'!E:E,C:C) -> 0 | AH4: =IFERROR(AG4/SUMIF('船长每月数据(2023年)'!$E:$E,$C:$C,'船长每月数据(2023年)'!$P:$P),0) -> 0 | AI4: =SUMIFS('船长每月数据(2023年)'!$R:$R,'船长每月数据(2023年)'!$F:$F,$AI$2,'船长每月数据(2023年)'!$E:$E,$C:$C) -> 0 | AJ4: =IFERROR(AI4/SUMIF('船长每月数据(2023年)'!$E:$E,$C:$C,'船长每月数据(2023年)'!$R:$R),0) -> 0 | AK4: =SUMIFS('船长每月数据(2023年)'!P:P,'船长每月数据(2023年)'!F:F,$AK$2,'船长每月数据(2023年)'!E:E,C:C) -> 0 | AL4: =IFERROR(AK4/SUMIF('船长每月数据(2023年)'!$E:$E,$C:$C,'船长每月数据(2023年)'!$P:$P),0) -> 0 | AM4: =SUMIFS('船长每月数据(2023年)'!$R:$R,'船长每月数据(2023年)'!$F:$F,$AM$2,'船长每月数据(2023年)'!$E:$E,$C:$C) -> 0 | AN4: =IFERROR(AM4/SUMIF('船长每月数据(2023年)'!$E:$E,$C:$C,'船长每月数据(2023年)'!$R:$R),0) -> 0 | AO4: =SUMIFS('船长每月数据(2023年)'!P:P,'船长每月数据(2023年)'!F:F,$AO$2,'船长每月数据(2023年)'!E:E,C:C) -> 0 | AP4: =IFERROR(AO4/SUMIF('船长每月数据(2023年)'!$E:$E,$C:$C,'船长每月数据(2023年)'!$P:$P),0) -> 0 | AQ4: =SUMIFS('船长每月数据(2023年)'!$R:$R,'船长每月数据(2023年)'!$F:$F,$AQ$2,'船长每月数据(2023年)'!$E:$E,$C:$C) -> 0 | AR4: =IFERROR(AQ4/SUMIF('船长每月数据(2023年)'!$E:$E,$C:$C,'船长每月数据(2023年)'!$R:$R),0) -> 0 | AS4: =SUMIFS('船长每月数据(2023年)'!$P:$P,'船长每月数据(2023年)'!$F:$F,$AS$2,'船长每月数据(2023年)'!$E:$E,$C:$C) -> 0 | AT4: =IFERROR(AS4/SUMIF('船长每月数据(2023年)'!$E:$E,$C:$C,'船长每月数据(2023年)'!$P:$P),0) -> 0 | AU4: =SUMIFS('船长每月数据(2023年)'!$R:$R,'船长每月数据(2023年)'!$F:$F,$AU$2,'船长每月数据(2023年)'!$E:$E,$C:$C) -> 0 | AV4: =IFERROR(AU4/SUMIF('船长每月数据(2023年)'!$E:$E,$C:$C,'船长每月数据(2023年)'!$R:$R),0) -> 0 | AW4: =SUMIFS('船长每月数据(2023年)'!$P:$P,'船长每月数据(2023年)'!$F:$F,$AW$2,'船长每月数据(2023年)'!$E:$E,$C:$C) -> 0 | AX4: =IFERROR(AW4/SUMIF('船长每月数据(2023年)'!$E:$E,$C:$C,'船长每月数据(2023年)'!$P:$P),0) -> 0 | AY4: =SUMIFS('船长每月数据(2023年)'!$R:$R,'船长每月数据(2023年)'!$F:$F,$AY$2,'船长每月数据(2023年)'!$E:$E,$C:$C) -> 0 | AZ4: =IFERROR(AY4/SUMIF('船长每月数据(2023年)'!$E:$E,$C:$C,'船长每月数据(2023年)'!$R:$R),0) -> 0 | BA4: =SUMIFS('船长每月数据(2023年)'!$P:$P,'船长每月数据(2023年)'!$F:$F,$BA$2,'船长每月数据(2023年)'!$E:$E,$C:$C) -> 0 | BB4: =IFERROR(BA4/SUMIF('船长每月数据(2023年)'!$E:$E,$C:$C,'船长每月数据(2023年)'!$P:$P),0) -> 0 | BC4: =SUMIFS('船长每月数据(2023年)'!$R:$R,'船长每月数据(2023年)'!$F:$F,$BC$2,'船长每月数据(2023年)'!$E:$E,$C:$C) -> 0 | BD4: =IFERROR(BC4/SUMIF('船长每月数据(2023年)'!$E:$E,$C:$C,'船长每月数据(2023年)'!$R:$R),0) -> 0 | BE4: =SUMIFS('船长每月数据(2023年)'!$P:$P,'船长每月数据(2023年)'!$F:$F,$BE$2,'船长每月数据(2023年)'!$E:$E,$C:$C) -> 0 | BF4: =IFERROR(BE4/SUMIF('船长每月数据(2023年)'!$E:$E,$C:$C,'船长每月数据(2023年)'!$P:$P),0) -> 0 | BG4: =SUMIFS('船长每月数据(2023年)'!$R:$R,'船长每月数据(2023年)'!$F:$F,$BG$2,'船长每月数据(2023年)'!$E:$E,$C:$C) -> 0 | BH4: =IFERROR(BG4/SUMIF('船长每月数据(2023年)'!$E:$E,$C:$C,'船长每月数据(2023年)'!$R:$R),0) -> 0 | BI4: =SUMIFS('船长每月数据(2023年)'!$P:$P,'船长每月数据(2023年)'!$F:$F,$BI$2,'船长每月数据(2023年)'!$E:$E,$C:$C) -> 0 | BJ4: =IFERROR(BI4/SUMIF('船长每月数据(2023年)'!$E:$E,$C:$C,'船长每月数据(2023年)'!$P:$P),0) -> 0 | BK4: =SUMIFS('船长每月数据(2023年)'!$R:$R,'船长每月数据(2023年)'!$F:$F,$BK$2,'船长每月数据(2023年)'!$E:$E,$C:$C) -> 0 | BL4: =IFERROR(BK4/SUMIF('船长每月数据(2023年)'!$E:$E,$C:$C,'船长每月数据(2023年)'!$R:$R),0) -> 0 | BM4: =SUMIFS('船长每月数据(2023年)'!$P:$P,'船长每月数据(2023年)'!$F:$F,$BM$2,'船长每月数据(2023年)'!$E:$E,$C:$C) -> 0 | BN4: =IFERROR(BM4/SUMIF('船长每月数据(2023年)'!$E:$E,$C:$C,'船长每月数据(2023年)'!$P:$P),0) -> 0 | BO4: =SUMIFS('船长每月数据(2023年)'!$R:$R,'船长每月数据(2023年)'!$F:$F,$BO$2,'船长每月数据(2023年)'!$E:$E,$C:$C) -> 0 | BP4: =IFERROR(BO4/SUMIF('船长每月数据(2023年)'!$E:$E,$C:$C,'船长每月数据(2023年)'!$R:$R),0) -> 0 | BQ4: =SUMIFS('船长每月数据(2023年)'!$P:$P,'船长每月数据(2023年)'!$F:$F,$BQ$2,'船长每月数据(2023年)'!$E:$E,$C:$C) -> 0 | BR4: =IFERROR(BQ4/SUMIF('船长每月数据(2023年)'!$E:$E,$C:$C,'船长每月数据(2023年)'!$P:$P),0) -> 0 | BS4: =SUMIFS('船长每月数据(2023年)'!$R:$R,'船长每月数据(2023年)'!$F:$F,$BS$2,'船长每月数据(2023年)'!$E:$E,$C:$C) -> 0 | BT4: =IFERROR(BS4/SUMIF('船长每月数据(2023年)'!$E:$E,$C:$C,'船长每月数据(2023年)'!$R:$R),0) -> 0 | BU4: =SUMIFS('船长每月数据(2023年)'!$P:$P,'船长每月数据(2023年)'!$F:$F,$BU$2,'船长每月数据(2023年)'!$E:$E,$C:$C) -> 0 | BV4: =IFERROR(BU4/SUMIF('船长每月数据(2023年)'!$E:$E,$C:$C,'船长每月数据(2023年)'!$P:$P),0) -> 0 | BW4: =SUMIFS('船长每月数据(2023年)'!$R:$R,'船长每月数据(2023年)'!$F:$F,$BW$2,'船长每月数据(2023年)'!$E:$E,$C:$C) -> 0 | BX4: =IFERROR(BW4/SUMIF('船长每月数据(2023年)'!$E:$E,$C:$C,'船长每月数据(2023年)'!$R:$R),0) -> 0
E5: =SUMIFS('船长每月数据(2022年)'!$P:$P,'船长每月数据(2022年)'!$F:$F,$E$2,'船长每月数据(2022年)'!E:E,C:C) -> 0 | F5: =SUMIFS('船长每月数据(2022年)'!$R:$R,'船长每月数据(2022年)'!$F:$F,$F$2,'船长每月数据(2022年)'!E:E,C:C) -> 0 | G5: =SUMIFS('船长每月数据(2022年)'!$P:$P,'船长每月数据(2022年)'!$F:$F,$G$2,'船长每月数据(2022年)'!$E:$E,$C:$C) -> 0 | H5: =SUMIFS('船长每月数据(2022年)'!$R:$R,'船长每月数据(2022年)'!$F:$F,$H$2,'船长每月数据(2022年)'!$E:$E,$C:$C) -> 0 | I5: =SUMIFS('船长每月数据(2022年)'!$P:$P,'船长每月数据(2022年)'!$F:$F,$I$2,'船长每月数据(2022年)'!$E:$E,$C:$C) -> 0 | J5: =SUMIFS('船长每月数据(2022年)'!$R:$R,'船长每月数据(2022年)'!$F:$F,$J$2,'船长每月数据(2022年)'!$E:$E,$C:$C) -> 0 | K5: =SUMIFS('船长每月数据(2022年)'!$P:$P,'船长每月数据(2022年)'!$F:$F,$K$2,'船长每月数据(2022年)'!$E:$E,$C:$C) -> 0 | L5: =SUMIFS('船长每月数据(2022年)'!$R:$R,'船长每月数据(2022年)'!$F:$F,$L$2,'船长每月数据(2022年)'!$E:$E,$C:$C) -> 0 | M5: =SUMIFS('船长每月数据(2022年)'!$P:$P,'船长每月数据(2022年)'!$F:$F,$M$2,'船长每月数据(2022年)'!$E:$E,$C:$C) -> 0 | N5: =SUMIFS('船长每月数据(2022年)'!$R:$R,'船长每月数据(2022年)'!$F:$F,$N$2,'船长每月数据(2022年)'!$E:$E,$C:$C) -> 0 | O5: =SUMIFS('船长每月数据(2022年)'!$P:$P,'船长每月数据(2022年)'!$F:$F,$O$2,'船长每月数据(2022年)'!$E:$E,$C:$C) -> 0 | P5: =SUMIFS('船长每月数据(2022年)'!$R:$R,'船长每月数据(2022年)'!$F:$F,$P$2,'船长每月数据(2022年)'!$E:$E,$C:$C) -> 0 | Q5: =SUMIFS('船长每月数据(2022年)'!$P:$P,'船长每月数据(2022年)'!$F:$F,$Q$2,'船长每月数据(2022年)'!$E:$E,$C:$C) -> 0 | R5: =SUMIFS('船长每月数据(2022年)'!$R:$R,'船长每月数据(2022年)'!$F:$F,$R$2,'船长每月数据(2022年)'!$E:$E,$C:$C) -> 0 | S5: =SUMIFS('船长每月数据(2022年)'!$P:$P,'船长每月数据(2022年)'!$F:$F,$S$2,'船长每月数据(2022年)'!$E:$E,$C:$C) -> 0 | T5: =SUMIFS('船长每月数据(2022年)'!$R:$R,'船长每月数据(2022年)'!$F:$F,$T$2,'船长每月数据(2022年)'!$E:$E,$C:$C) -> 0 | U5: =SUMIFS('船长每月数据(2022年)'!$P:$P,'船长每月数据(2022年)'!$F:$F,$U$2,'船长每月数据(2022年)'!$E:$E,$C:$C) -> 0 | V5: =SUMIFS('船长每月数据(2022年)'!$R:$R,'船长每月数据(2022年)'!$F:$F,$V$2,'船长每月数据(2022年)'!$E:$E,$C:$C) -> 0 | W5: =SUMIFS('船长每月数据(2022年)'!$P:$P,'船长每月数据(2022年)'!$F:$F,$W$2,'船长每月数据(2022年)'!$E:$E,$C:$C) -> 0 | X5: =SUMIFS('船长每月数据(2022年)'!$R:$R,'船长每月数据(2022年)'!$F:$F,$X$2,'船长每月数据(2022年)'!$E:$E,$C:$C) -> 0 | Y5: =SUMIFS('船长每月数据(2022年)'!$P:$P,'船长每月数据(2022年)'!$F:$F,$Y$2,'船长每月数据(2022年)'!$E:$E,$C:$C) -> 0 | Z5: =SUMIFS('船长每月数据(2022年)'!$R:$R,'船长每月数据(2022年)'!$F:$F,$Z$2,'船长每月数据(2022年)'!$E:$E,$C:$C) -> 0 | AA5: =SUMIFS('船长每月数据(2022年)'!$P:$P,'船长每月数据(2022年)'!$F:$F,$AA$2,'船长每月数据(2022年)'!$E:$E,$C:$C) -> 0 | AB5: =SUMIFS('船长每月数据(2022年)'!$R:$R,'船长每月数据(2022年)'!$F:$F,$AB$2,'船长每月数据(2022年)'!$E:$E,$C:$C) -> 0 | AC5: =SUMIFS('船长每月数据(2023年)'!P:P,'船长每月数据(2023年)'!F:F,$AC$2,'船长每月数据(2023年)'!E:E,C:C) -> 0 | AD5: =IFERROR(AC5/SUMIF('船长每月数据(2023年)'!$E:$E,C:C,'船长每月数据(2023年)'!P:P),0) -> 0 | AE5: =SUMIFS('船长每月数据(2023年)'!$R:$R,'船长每月数据(2023年)'!$F:$F,$AE$2,'船长每月数据(2023年)'!$E:$E,$C:$C) -> 0 | AF5: =IFERROR(AE5/SUMIF('船长每月数据(2023年)'!E:E,C:C,'船长每月数据(2023年)'!R:R),0) -> 0 | AG5: =SUMIFS('船长每月数据(2023年)'!P:P,'船长每月数据(2023年)'!F:F,$AG$2,'船长每月数据(2023年)'!E:E,C:C) -> 0 | AH5: =IFERROR(AG5/SUMIF('船长每月数据(2023年)'!$E:$E,$C:$C,'船长每月数据(2023年)'!$P:$P),0) -> 0 | AI5: =SUMIFS('船长每月数据(2023年)'!$R:$R,'船长每月数据(2023年)'!$F:$F,$AI$2,'船长每月数据(2023年)'!$E:$E,$C:$C) -> 0 | AJ5: =IFERROR(AI5/SUMIF('船长每月数据(2023年)'!$E:$E,$C:$C,'船长每月数据(2023年)'!$R:$R),0) -> 0 | AK5: =SUMIFS('船长每月数据(2023年)'!P:P,'船长每月数据(2023年)'!F:F,$AK$2,'船长每月数据(2023年)'!E:E,C:C) -> 0 | AL5: =IFERROR(AK5/SUMIF('船长每月数据(2023年)'!$E:$E,$C:$C,'船长每月数据(2023年)'!$P:$P),0) -> 0 | AM5: =SUMIFS('船长每月数据(2023年)'!$R:$R,'船长每月数据(2023年)'!$F:$F,$AM$2,'船长每月数据(2023年)'!$E:$E,$C:$C) -> 0 | AN5: =IFERROR(AM5/SUMIF('船长每月数据(2023年)'!$E:$E,$C:$C,'船长每月数据(2023年)'!$R:$R),0) -> 0 | AO5: =SUMIFS('船长每月数据(2023年)'!P:P,'船长每月数据(2023年)'!F:F,$AO$2,'船长每月数据(2023年)'!E:E,C:C) -> 0 | AP5: =IFERROR(AO5/SUMIF('船长每月数据(2023年)'!$E:$E,$C:$C,'船长每月数据(2023年)'!$P:$P),0) -> 0 | AQ5: =SUMIFS('船长每月数据(2023年)'!$R:$R,'船长每月数据(2023年)'!$F:$F,$AQ$2,'船长每月数据(2023年)'!$E:$E,$C:$C) -> 0 | AR5: =IFERROR(AQ5/SUMIF('船长每月数据(2023年)'!$E:$E,$C:$C,'船长每月数据(2023年)'!$R:$R),0) -> 0 | AS5: =SUMIFS('船长每月数据(2023年)'!$P:$P,'船长每月数据(2023年)'!$F:$F,$AS$2,'船长每月数据(2023年)'!$E:$E,$C:$C) -> 0 | AT5: =IFERROR(AS5/SUMIF('船长每月数据(2023年)'!$E:$E,$C:$C,'船长每月数据(2023年)'!$P:$P),0) -> 0 | AU5: =SUMIFS('船长每月数据(2023年)'!$R:$R,'船长每月数据(2023年)'!$F:$F,$AU$2,'船长每月数据(2023年)'!$E:$E,$C:$C) -> 0 | AV5: =IFERROR(AU5/SUMIF('船长每月数据(2023年)'!$E:$E,$C:$C,'船长每月数据(2023年)'!$R:$R),0) -> 0 | AW5: =SUMIFS('船长每月数据(2023年)'!$P:$P,'船长每月数据(2023年)'!$F:$F,$AW$2,'船长每月数据(2023年)'!$E:$E,$C:$C) -> 0 | AX5: =IFERROR(AW5/SUMIF('船长每月数据(2023年)'!$E:$E,$C:$C,'船长每月数据(2023年)'!$P:$P),0) -> 0 | AY5: =SUMIFS('船长每月数据(2023年)'!$R:$R,'船长每月数据(2023年)'!$F:$F,$AY$2,'船长每月数据(2023年)'!$E:$E,$C:$C) -> 0 | AZ5: =IFERROR(AY5/SUMIF('船长每月数据(2023年)'!$E:$E,$C:$C,'船长每月数据(2023年)'!$R:$R),0) -> 0 | BA5: =SUMIFS('船长每月数据(2023年)'!$P:$P,'船长每月数据(2023年)'!$F:$F,$BA$2,'船长每月数据(2023年)'!$E:$E,$C:$C) -> 0 | BB5: =IFERROR(BA5/SUMIF('船长每月数据(2023年)'!$E:$E,$C:$C,'船长每月数据(2023年)'!$P:$P),0) -> 0 | BC5: =SUMIFS('船长每月数据(2023年)'!$R:$R,'船长每月数据(2023年)'!$F:$F,$BC$2,'船长每月数据(2023年)'!$E:$E,$C:$C) -> 0 | BD5: =IFERROR(BC5/SUMIF('船长每月数据(2023年)'!$E:$E,$C:$C,'船长每月数据(2023年)'!$R:$R),0) -> 0 | BE5: =SUMIFS('船长每月数据(2023年)'!$P:$P,'船长每月数据(2023年)'!$F:$F,$BE$2,'船长每月数据(2023年)'!$E:$E,$C:$C) -> 0 | BF5: =IFERROR(BE5/SUMIF('船长每月数据(2023年)'!$E:$E,$C:$C,'船长每月数据(2023年)'!$P:$P),0) -> 0 | BG5: =SUMIFS('船长每月数据(2023年)'!$R:$R,'船长每月数据(2023年)'!$F:$F,$BG$2,'船长每月数据(2023年)'!$E:$E,$C:$C) -> 0 | BH5: =IFERROR(BG5/SUMIF('船长每月数据(2023年)'!$E:$E,$C:$C,'船长每月数据(2023年)'!$R:$R),0) -> 0 | BI5: =SUMIFS('船长每月数据(2023年)'!$P:$P,'船长每月数据(2023年)'!$F:$F,$BI$2,'船长每月数据(2023年)'!$E:$E,$C:$C) -> 0 | BJ5: =IFERROR(BI5/SUMIF('船长每月数据(2023年)'!$E:$E,$C:$C,'船长每月数据(2023年)'!$P:$P),0) -> 0 | BK5: =SUMIFS('船长每月数据(2023年)'!$R:$R,'船长每月数据(2023年)'!$F:$F,$BK$2,'船长每月数据(2023年)'!$E:$E,$C:$C) -> 0 | BL5: =IFERROR(BK5/SUMIF('船长每月数据(2023年)'!$E:$E,$C:$C,'船长每月数据(2023年)'!$R:$R),0) -> 0 | BM5: =SUMIFS('船长每月数据(2023年)'!$P:$P,'船长每月数据(2023年)'!$F:$F,$BM$2,'船长每月数据(2023年)'!$E:$E,$C:$C) -> 0 | BN5: =IFERROR(BM5/SUMIF('船长每月数据(2023年)'!$E:$E,$C:$C,'船长每月数据(2023年)'!$P:$P),0) -> 0 | BO5: =SUMIFS('船长每月数据(2023年)'!$R:$R,'船长每月数据(2023年)'!$F:$F,$BO$2,'船长每月数据(2023年)'!$E:$E,$C:$C) -> 0 | BP5: =IFERROR(BO5/SUMIF('船长每月数据(2023年)'!$E:$E,$C:$C,'船长每月数据(2023年)'!$R:$R),0) -> 0 | BQ5: =SUMIFS('船长每月数据(2023年)'!$P:$P,'船长每月数据(2023年)'!$F:$F,$BQ$2,'船长每月数据(2023年)'!$E:$E,$C:$C) -> 0 | BR5: =IFERROR(BQ5/SUMIF('船长每月数据(2023年)'!$E:$E,$C:$C,'船长每月数据(2023年)'!$P:$P),0) -> 0 | BS5: =SUMIFS('船长每月数据(2023年)'!$R:$R,'船长每月数据(2023年)'!$F:$F,$BS$2,'船长每月数据(2023年)'!$E:$E,$C:$C) -> 0 | BT5: =IFERROR(BS5/SUMIF('船长每月数据(2023年)'!$E:$E,$C:$C,'船长每月数据(2023年)'!$R:$R),0) -> 0 | BU5: =SUMIFS('船长每月数据(2023年)'!$P:$P,'船长每月数据(2023年)'!$F:$F,$BU$2,'船长每月数据(2023年)'!$E:$E,$C:$C) -> 0 | BV5: =IFERROR(BU5/SUMIF('船长每月数据(2023年)'!$E:$E,$C:$C,'船长每月数据(2023年)'!$P:$P),0) -> 0 | BW5: =SUMIFS('船长每月数据(2023年)'!$R:$R,'船长每月数据(2023年)'!$F:$F,$BW$2,'船长每月数据(2023年)'!$E:$E,$C:$C) -> 0 | BX5: =IFERROR(BW5/SUMIF('船长每月数据(2023年)'!$E:$E,$C:$C,'船长每月数据(2023年)'!$R:$R),0) -> 0
E6: =SUMIFS('船长每月数据(2022年)'!$P:$P,'船长每月数据(2022年)'!$F:$F,$E$2,'船长每月数据(2022年)'!E:E,C:C) -> 0 | F6: =SUMIFS('船长每月数据(2022年)'!$R:$R,'船长每月数据(2022年)'!$F:$F,$F$2,'船长每月数据(2022年)'!E:E,C:C) -> 0 | G6: =SUMIFS('船长每月数据(2022年)'!$P:$P,'船长每月数据(2022年)'!$F:$F,$G$2,'船长每月数据(2022年)'!$E:$E,$C:$C) -> 0 | H6: =SUMIFS('船长每月数据(2022年)'!$R:$R,'船长每月数据(2022年)'!$F:$F,$H$2,'船长每月数据(2022年)'!$E:$E,$C:$C) -> 0 | I6: =SUMIFS('船长每月数据(2022年)'!$P:$P,'船长每月数据(2022年)'!$F:$F,$I$2,'船长每月数据(2022年)'!$E:$E,$C:$C) -> 0 | J6: =SUMIFS('船长每月数据(2022年)'!$R:$R,'船长每月数据(2022年)'!$F:$F,$J$2,'船长每月数据(2022年)'!$E:$E,$C:$C) -> 0 | K6: =SUMIFS('船长每月数据(2022年)'!$P:$P,'船长每月数据(2022年)'!$F:$F,$K$2,'船长每月数据(2022年)'!$E:$E,$C:$C) -> 0 | L6: =SUMIFS('船长每月数据(2022年)'!$R:$R,'船长每月数据(2022年)'!$F:$F,$L$2,'船长每月数据(2022年)'!$E:$E,$C:$C) -> 0 | M6: =SUMIFS('船长每月数据(2022年)'!$P:$P,'船长每月数据(2022年)'!$F:$F,$M$2,'船长每月数据(2022年)'!$E:$E,$C:$C) -> 0 | N6: =SUMIFS('船长每月数据(2022年)'!$R:$R,'船长每月数据(2022年)'!$F:$F,$N$2,'船长每月数据(2022年)'!$E:$E,$C:$C) -> 0 | O6: =SUMIFS('船长每月数据(2022年)'!$P:$P,'船长每月数据(2022年)'!$F:$F,$O$2,'船长每月数据(2022年)'!$E:$E,$C:$C) -> 0 | P6: =SUMIFS('船长每月数据(2022年)'!$R:$R,'船长每月数据(2022年)'!$F:$F,$P$2,'船长每月数据(2022年)'!$E:$E,$C:$C) -> 0 | Q6: =SUMIFS('船长每月数据(2022年)'!$P:$P,'船长每月数据(2022年)'!$F:$F,$Q$2,'船长每月数据(2022年)'!$E:$E,$C:$C) -> 0 | R6: =SUMIFS('船长每月数据(2022年)'!$R:$R,'船长每月数据(2022年)'!$F:$F,$R$2,'船长每月数据(2022年)'!$E:$E,$C:$C) -> 0 | S6: =SUMIFS('船长每月数据(2022年)'!$P:$P,'船长每月数据(2022年)'!$F:$F,$S$2,'船长每月数据(2022年)'!$E:$E,$C:$C) -> 0 | T6: =SUMIFS('船长每月数据(2022年)'!$R:$R,'船长每月数据(2022年)'!$F:$F,$T$2,'船长每月数据(2022年)'!$E:$E,$C:$C) -> 0 | U6: =SUMIFS('船长每月数据(2022年)'!$P:$P,'船长每月数据(2022年)'!$F:$F,$U$2,'船长每月数据(2022年)'!$E:$E,$C:$C) -> 0 | V6: =SUMIFS('船长每月数据(2022年)'!$R:$R,'船长每月数据(2022年)'!$F:$F,$V$2,'船长每月数据(2022年)'!$E:$E,$C:$C) -> 0 | W6: =SUMIFS('船长每月数据(2022年)'!$P:$P,'船长每月数据(2022年)'!$F:$F,$W$2,'船长每月数据(2022年)'!$E:$E,$C:$C) -> 0 | X6: =SUMIFS('船长每月数据(2022年)'!$R:$R,'船长每月数据(2022年)'!$F:$F,$X$2,'船长每月数据(2022年)'!$E:$E,$C:$C) -> 0 | Y6: =SUMIFS('船长每月数据(2022年)'!$P:$P,'船长每月数据(2022年)'!$F:$F,$Y$2,'船长每月数据(2022年)'!$E:$E,$C:$C) -> 0 | Z6: =SUMIFS('船长每月数据(2022年)'!$R:$R,'船长每月数据(2022年)'!$F:$F,$Z$2,'船长每月数据(2022年)'!$E:$E,$C:$C) -> 0 | AA6: =SUMIFS('船长每月数据(2022年)'!$P:$P,'船长每月数据(2022年)'!$F:$F,$AA$2,'船长每月数据(2022年)'!$E:$E,$C:$C) -> 0 | AB6: =SUMIFS('船长每月数据(2022年)'!$R:$R,'船长每月数据(2022年)'!$F:$F,$AB$2,'船长每月数据(2022年)'!$E:$E,$C:$C) -> 0 | AC6: =SUMIFS('船长每月数据(2023年)'!P:P,'船长每月数据(2023年)'!F:F,$AC$2,'船长每月数据(2023年)'!E:E,C:C) -> 0 | AD6: =IFERROR(AC6/SUMIF('船长每月数据(2023年)'!$E:$E,C:C,'船长每月数据(2023年)'!P:P),0) -> 0 | AE6: =SUMIFS('船长每月数据(2023年)'!$R:$R,'船长每月数据(2023年)'!$F:$F,$AE$2,'船长每月数据(2023年)'!$E:$E,$C:$C) -> 0 | AF6: =IFERROR(AE6/SUMIF('船长每月数据(2023年)'!E:E,C:C,'船长每月数据(2023年)'!R:R),0) -> 0 | AG6: =SUMIFS('船长每月数据(2023年)'!P:P,'船长每月数据(2023年)'!F:F,$AG$2,'船长每月数据(2023年)'!E:E,C:C) -> 0 | AH6: =IFERROR(AG6/SUMIF('船长每月数据(2023年)'!$E:$E,$C:$C,'船长每月数据(2023年)'!$P:$P),0) -> 0 | AI6: =SUMIFS('船长每月数据(2023年)'!$R:$R,'船长每月数据(2023年)'!$F:$F,$AI$2,'船长每月数据(2023年)'!$E:$E,$C:$C) -> 0 | AJ6: =IFERROR(AI6/SUMIF('船长每月数据(2023年)'!$E:$E,$C:$C,'船长每月数据(2023年)'!$R:$R),0) -> 0 | AK6: =SUMIFS('船长每月数据(2023年)'!P:P,'船长每月数据(2023年)'!F:F,$AK$2,'船长每月数据(2023年)'!E:E,C:C) -> 0 | AL6: =IFERROR(AK6/SUMIF('船长每月数据(2023年)'!$E:$E,$C:$C,'船长每月数据(2023年)'!$P:$P),0) -> 0 | AM6: =SUMIFS('船长每月数据(2023年)'!$R:$R,'船长每月数据(2023年)'!$F:$F,$AM$2,'船长每月数据(2023年)'!$E:$E,$C:$C) -> 0 | AN6: =IFERROR(AM6/SUMIF('船长每月数据(2023年)'!$E:$E,$C:$C,'船长每月数据(2023年)'!$R:$R),0) -> 0 | AO6: =SUMIFS('船长每月数据(2023年)'!P:P,'船长每月数据(2023年)'!F:F,$AO$2,'船长每月数据(2023年)'!E:E,C:C) -> 0 | AP6: =IFERROR(AO6/SUMIF('船长每月数据(2023年)'!$E:$E,$C:$C,'船长每月数据(2023年)'!$P:$P),0) -> 0 | AQ6: =SUMIFS('船长每月数据(2023年)'!$R:$R,'船长每月数据(2023年)'!$F:$F,$AQ$2,'船长每月数据(2023年)'!$E:$E,$C:$C) -> 0 | AR6: =IFERROR(AQ6/SUMIF('船长每月数据(2023年)'!$E:$E,$C:$C,'船长每月数据(2023年)'!$R:$R),0) -> 0 | AS6: =SUMIFS('船长每月数据(2023年)'!$P:$P,'船长每月数据(2023年)'!$F:$F,$AS$2,'船长每月数据(2023年)'!$E:$E,$C:$C) -> 0 | AT6: =IFERROR(AS6/SUMIF('船长每月数据(2023年)'!$E:$E,$C:$C,'船长每月数据(2023年)'!$P:$P),0) -> 0 | AU6: =SUMIFS('船长每月数据(2023年)'!$R:$R,'船长每月数据(2023年)'!$F:$F,$AU$2,'船长每月数据(2023年)'!$E:$E,$C:$C) -> 0 | AV6: =IFERROR(AU6/SUMIF('船长每月数据(2023年)'!$E:$E,$C:$C,'船长每月数据(2023年)'!$R:$R),0) -> 0 | AW6: =SUMIFS('船长每月数据(2023年)'!$P:$P,'船长每月数据(2023年)'!$F:$F,$AW$2,'船长每月数据(2023年)'!$E:$E,$C:$C) -> 0 | AX6: =IFERROR(AW6/SUMIF('船长每月数据(2023年)'!$E:$E,$C:$C,'船长每月数据(2023年)'!$P:$P),0) -> 0 | AY6: =SUMIFS('船长每月数据(2023年)'!$R:$R,'船长每月数据(2023年)'!$F:$F,$AY$2,'船长每月数据(2023年)'!$E:$E,$C:$C) -> 0 | AZ6: =IFERROR(AY6/SUMIF('船长每月数据(2023年)'!$E:$E,$C:$C,'船长每月数据(2023年)'!$R:$R),0) -> 0 | BA6: =SUMIFS('船长每月数据(2023年)'!$P:$P,'船长每月数据(2023年)'!$F:$F,$BA$2,'船长每月数据(2023年)'!$E:$E,$C:$C) -> 0 | BB6: =IFERROR(BA6/SUMIF('船长每月数据(2023年)'!$E:$E,$C:$C,'船长每月数据(2023年)'!$P:$P),0) -> 0 | BC6: =SUMIFS('船长每月数据(2023年)'!$R:$R,'船长每月数据(2023年)'!$F:$F,$BC$2,'船长每月数据(2023年)'!$E:$E,$C:$C) -> 0 | BD6: =IFERROR(BC6/SUMIF('船长每月数据(2023年)'!$E:$E,$C:$C,'船长每月数据(2023年)'!$R:$R),0) -> 0 | BE6: =SUMIFS('船长每月数据(2023年)'!$P:$P,'船长每月数据(2023年)'!$F:$F,$BE$2,'船长每月数据(2023年)'!$E:$E,$C:$C) -> 0 | BF6: =IFERROR(BE6/SUMIF('船长每月数据(2023年)'!$E:$E,$C:$C,'船长每月数据(2023年)'!$P:$P),0) -> 0 | BG6: =SUMIFS('船长每月数据(2023年)'!$R:$R,'船长每月数据(2023年)'!$F:$F,$BG$2,'船长每月数据(2023年)'!$E:$E,$C:$C) -> 0 | BH6: =IFERROR(BG6/SUMIF('船长每月数据(2023年)'!$E:$E,$C:$C,'船长每月数据(2023年)'!$R:$R),0) -> 0 | BI6: =SUMIFS('船长每月数据(2023年)'!$P:$P,'船长每月数据(2023年)'!$F:$F,$BI$2,'船长每月数据(2023年)'!$E:$E,$C:$C) -> 0 | BJ6: =IFERROR(BI6/SUMIF('船长每月数据(2023年)'!$E:$E,$C:$C,'船长每月数据(2023年)'!$P:$P),0) -> 0 | BK6: =SUMIFS('船长每月数据(2023年)'!$R:$R,'船长每月数据(2023年)'!$F:$F,$BK$2,'船长每月数据(2023年)'!$E:$E,$C:$C) -> 0 | BL6: =IFERROR(BK6/SUMIF('船长每月数据(2023年)'!$E:$E,$C:$C,'船长每月数据(2023年)'!$R:$R),0) -> 0 | BM6: =SUMIFS('船长每月数据(2023年)'!$P:$P,'船长每月数据(2023年)'!$F:$F,$BM$2,'船长每月数据(2023年)'!$E:$E,$C:$C) -> 0 | BN6: =IFERROR(BM6/SUMIF('船长每月数据(2023年)'!$E:$E,$C:$C,'船长每月数据(2023年)'!$P:$P),0) -> 0 | BO6: =SUMIFS('船长每月数据(2023年)'!$R:$R,'船长每月数据(2023年)'!$F:$F,$BO$2,'船长每月数据(2023年)'!$E:$E,$C:$C) -> 0 | BP6: =IFERROR(BO6/SUMIF('船长每月数据(2023年)'!$E:$E,$C:$C,'船长每月数据(2023年)'!$R:$R),0) -> 0 | BQ6: =SUMIFS('船长每月数据(2023年)'!$P:$P,'船长每月数据(2023年)'!$F:$F,$BQ$2,'船长每月数据(2023年)'!$E:$E,$C:$C) -> 0 | BR6: =IFERROR(BQ6/SUMIF('船长每月数据(2023年)'!$E:$E,$C:$C,'船长每月数据(2023年)'!$P:$P),0) -> 0 | BS6: =SUMIFS('船长每月数据(2023年)'!$R:$R,'船长每月数据(2023年)'!$F:$F,$BS$2,'船长每月数据(2023年)'!$E:$E,$C:$C) -> 0 | BT6: =IFERROR(BS6/SUMIF('船长每月数据(2023年)'!$E:$E,$C:$C,'船长每月数据(2023年)'!$R:$R),0) -> 0 | BU6: =SUMIFS('船长每月数据(2023年)'!$P:$P,'船长每月数据(2023年)'!$F:$F,$BU$2,'船长每月数据(2023年)'!$E:$E,$C:$C) -> 0 | BV6: =IFERROR(BU6/SUMIF('船长每月数据(2023年)'!$E:$E,$C:$C,'船长每月数据(2023年)'!$P:$P),0) -> 0 | BW6: =SUMIFS('船长每月数据(2023年)'!$R:$R,'船长每月数据(2023年)'!$F:$F,$BW$2,'船长每月数据(2023年)'!$E:$E,$C:$C) -> 0 | BX6: =IFERROR(BW6/SUMIF('船长每月数据(2023年)'!$E:$E,$C:$C,'船长每月数据(2023年)'!$R:$R),0) -> 0
E7: =SUMIFS('船长每月数据(2022年)'!$P:$P,'船长每月数据(2022年)'!$F:$F,$E$2,'船长每月数据(2022年)'!E:E,C:C) -> 0 | F7: =SUMIFS('船长每月数据(2022年)'!$R:$R,'船长每月数据(2022年)'!$F:$F,$F$2,'船长每月数据(2022年)'!E:E,C:C) -> 0 | G7: =SUMIFS('船长每月数据(2022年)'!$P:$P,'船长每月数据(2022年)'!$F:$F,$G$2,'船长每月数据(2022年)'!$E:$E,$C:$C) -> 0 | H7: =SUMIFS('船长每月数据(2022年)'!$R:$R,'船长每月数据(2022年)'!$F:$F,$H$2,'船长每月数据(2022年)'!$E:$E,$C:$C) -> 0 | I7: =SUMIFS('船长每月数据(2022年)'!$P:$P,'船长每月数据(2022年)'!$F:$F,$I$2,'船长每月数据(2022年)'!$E:$E,$C:$C) -> 0 | J7: =SUMIFS('船长每月数据(2022年)'!$R:$R,'船长每月数据(2022年)'!$F:$F,$J$2,'船长每月数据(2022年)'!$E:$E,$C:$C) -> 0 | K7: =SUMIFS('船长每月数据(2022年)'!$P:$P,'船长每月数据(2022年)'!$F:$F,$K$2,'船长每月数据(2022年)'!$E:$E,$C:$C) -> 0 | L7: =SUMIFS('船长每月数据(2022年)'!$R:$R,'船长每月数据(2022年)'!$F:$F,$L$2,'船长每月数据(2022年)'!$E:$E,$C:$C) -> 0 | M7: =SUMIFS('船长每月数据(2022年)'!$P:$P,'船长每月数据(2022年)'!$F:$F,$M$2,'船长每月数据(2022年)'!$E:$E,$C:$C) -> 0 | N7: =SUMIFS('船长每月数据(2022年)'!$R:$R,'船长每月数据(2022年)'!$F:$F,$N$2,'船长每月数据(2022年)'!$E:$E,$C:$C) -> 0 | O7: =SUMIFS('船长每月数据(2022年)'!$P:$P,'船长每月数据(2022年)'!$F:$F,$O$2,'船长每月数据(2022年)'!$E:$E,$C:$C) -> 0 | P7: =SUMIFS('船长每月数据(2022年)'!$R:$R,'船长每月数据(2022年)'!$F:$F,$P$2,'船长每月数据(2022年)'!$E:$E,$C:$C) -> 0 | Q7: =SUMIFS('船长每月数据(2022年)'!$P:$P,'船长每月数据(2022年)'!$F:$F,$Q$2,'船长每月数据(2022年)'!$E:$E,$C:$C) -> 0 | R7: =SUMIFS('船长每月数据(2022年)'!$R:$R,'船长每月数据(2022年)'!$F:$F,$R$2,'船长每月数据(2022年)'!$E:$E,$C:$C) -> 0 | S7: =SUMIFS('船长每月数据(2022年)'!$P:$P,'船长每月数据(2022年)'!$F:$F,$S$2,'船长每月数据(2022年)'!$E:$E,$C:$C) -> 0 | T7: =SUMIFS('船长每月数据(2022年)'!$R:$R,'船长每月数据(2022年)'!$F:$F,$T$2,'船长每月数据(2022年)'!$E:$E,$C:$C) -> 0 | U7: =SUMIFS('船长每月数据(2022年)'!$P:$P,'船长每月数据(2022年)'!$F:$F,$U$2,'船长每月数据(2022年)'!$E:$E,$C:$C) -> 0 | V7: =SUMIFS('船长每月数据(2022年)'!$R:$R,'船长每月数据(2022年)'!$F:$F,$V$2,'船长每月数据(2022年)'!$E:$E,$C:$C) -> 0 | W7: =SUMIFS('船长每月数据(2022年)'!$P:$P,'船长每月数据(2022年)'!$F:$F,$W$2,'船长每月数据(2022年)'!$E:$E,$C:$C) -> 0 | X7: =SUMIFS('船长每月数据(2022年)'!$R:$R,'船长每月数据(2022年)'!$F:$F,$X$2,'船长每月数据(2022年)'!$E:$E,$C:$C) -> 0 | Y7: =SUMIFS('船长每月数据(2022年)'!$P:$P,'船长每月数据(2022年)'!$F:$F,$Y$2,'船长每月数据(2022年)'!$E:$E,$C:$C) -> 0 | Z7: =SUMIFS('船长每月数据(2022年)'!$R:$R,'船长每月数据(2022年)'!$F:$F,$Z$2,'船长每月数据(2022年)'!$E:$E,$C:$C) -> 0 | AA7: =SUMIFS('船长每月数据(2022年)'!$P:$P,'船长每月数据(2022年)'!$F:$F,$AA$2,'船长每月数据(2022年)'!$E:$E,$C:$C) -> 0 | AB7: =SUMIFS('船长每月数据(2022年)'!$R:$R,'船长每月数据(2022年)'!$F:$F,$AB$2,'船长每月数据(2022年)'!$E:$E,$C:$C) -> 0 | AC7: =SUMIFS('船长每月数据(2023年)'!P:P,'船长每月数据(2023年)'!F:F,$AC$2,'船长每月数据(2023年)'!E:E,C:C) -> 0 | AD7: =IFERROR(AC7/SUMIF('船长每月数据(2023年)'!$E:$E,C:C,'船长每月数据(2023年)'!P:P),0) -> 0 | AE7: =SUMIFS('船长每月数据(2023年)'!$R:$R,'船长每月数据(2023年)'!$F:$F,$AE$2,'船长每月数据(2023年)'!$E:$E,$C:$C) -> 0 | AF7: =IFERROR(AE7/SUMIF('船长每月数据(2023年)'!E:E,C:C,'船长每月数据(2023年)'!R:R),0) -> 0 | AG7: =SUMIFS('船长每月数据(2023年)'!P:P,'船长每月数据(2023年)'!F:F,$AG$2,'船长每月数据(2023年)'!E:E,C:C) -> 0 | AH7: =IFERROR(AG7/SUMIF('船长每月数据(2023年)'!$E:$E,$C:$C,'船长每月数据(2023年)'!$P:$P),0) -> 0 | AI7: =SUMIFS('船长每月数据(2023年)'!$R:$R,'船长每月数据(2023年)'!$F:$F,$AI$2,'船长每月数据(2023年)'!$E:$E,$C:$C) -> 0 | AJ7: =IFERROR(AI7/SUMIF('船长每月数据(2023年)'!$E:$E,$C:$C,'船长每月数据(2023年)'!$R:$R),0) -> 0 | AK7: =SUMIFS('船长每月数据(2023年)'!P:P,'船长每月数据(2023年)'!F:F,$AK$2,'船长每月数据(2023年)'!E:E,C:C) -> 0 | AL7: =IFERROR(AK7/SUMIF('船长每月数据(2023年)'!$E:$E,$C:$C,'船长每月数据(2023年)'!$P:$P),0) -> 0 | AM7: =SUMIFS('船长每月数据(2023年)'!$R:$R,'船长每月数据(2023年)'!$F:$F,$AM$2,'船长每月数据(2023年)'!$E:$E,$C:$C) -> 0 | AN7: =IFERROR(AM7/SUMIF('船长每月数据(2023年)'!$E:$E,$C:$C,'船长每月数据(2023年)'!$R:$R),0) -> 0 | AO7: =SUMIFS('船长每月数据(2023年)'!P:P,'船长每月数据(2023年)'!F:F,$AO$2,'船长每月数据(2023年)'!E:E,C:C) -> 0 | AP7: =IFERROR(AO7/SUMIF('船长每月数据(2023年)'!$E:$E,$C:$C,'船长每月数据(2023年)'!$P:$P),0) -> 0 | AQ7: =SUMIFS('船长每月数据(2023年)'!$R:$R,'船长每月数据(2023年)'!$F:$F,$AQ$2,'船长每月数据(2023年)'!$E:$E,$C:$C) -> 0 | AR7: =IFERROR(AQ7/SUMIF('船长每月数据(2023年)'!$E:$E,$C:$C,'船长每月数据(2023年)'!$R:$R),0) -> 0 | AS7: =SUMIFS('船长每月数据(2023年)'!$P:$P,'船长每月数据(2023年)'!$F:$F,$AS$2,'船长每月数据(2023年)'!$E:$E,$C:$C) -> 0 | AT7: =IFERROR(AS7/SUMIF('船长每月数据(2023年)'!$E:$E,$C:$C,'船长每月数据(2023年)'!$P:$P),0) -> 0 | AU7: =SUMIFS('船长每月数据(2023年)'!$R:$R,'船长每月数据(2023年)'!$F:$F,$AU$2,'船长每月数据(2023年)'!$E:$E,$C:$C) -> 0 | AV7: =IFERROR(AU7/SUMIF('船长每月数据(2023年)'!$E:$E,$C:$C,'船长每月数据(2023年)'!$R:$R),0) -> 0 | AW7: =SUMIFS('船长每月数据(2023年)'!$P:$P,'船长每月数据(2023年)'!$F:$F,$AW$2,'船长每月数据(2023年)'!$E:$E,$C:$C) -> 0 | AX7: =IFERROR(AW7/SUMIF('船长每月数据(2023年)'!$E:$E,$C:$C,'船长每月数据(2023年)'!$P:$P),0) -> 0 | AY7: =SUMIFS('船长每月数据(2023年)'!$R:$R,'船长每月数据(2023年)'!$F:$F,$AY$2,'船长每月数据(2023年)'!$E:$E,$C:$C) -> 0 | AZ7: =IFERROR(AY7/SUMIF('船长每月数据(2023年)'!$E:$E,$C:$C,'船长每月数据(2023年)'!$R:$R),0) -> 0 | BA7: =SUMIFS('船长每月数据(2023年)'!$P:$P,'船长每月数据(2023年)'!$F:$F,$BA$2,'船长每月数据(2023年)'!$E:$E,$C:$C) -> 0 | BB7: =IFERROR(BA7/SUMIF('船长每月数据(2023年)'!$E:$E,$C:$C,'船长每月数据(2023年)'!$P:$P),0) -> 0 | BC7: =SUMIFS('船长每月数据(2023年)'!$R:$R,'船长每月数据(2023年)'!$F:$F,$BC$2,'船长每月数据(2023年)'!$E:$E,$C:$C) -> 0 | BD7: =IFERROR(BC7/SUMIF('船长每月数据(2023年)'!$E:$E,$C:$C,'船长每月数据(2023年)'!$R:$R),0) -> 0 | BE7: =SUMIFS('船长每月数据(2023年)'!$P:$P,'船长每月数据(2023年)'!$F:$F,$BE$2,'船长每月数据(2023年)'!$E:$E,$C:$C) -> 0 | BF7: =IFERROR(BE7/SUMIF('船长每月数据(2023年)'!$E:$E,$C:$C,'船长每月数据(2023年)'!$P:$P),0) -> 0 | BG7: =SUMIFS('船长每月数据(2023年)'!$R:$R,'船长每月数据(2023年)'!$F:$F,$BG$2,'船长每月数据(2023年)'!$E:$E,$C:$C) -> 0 | BH7: =IFERROR(BG7/SUMIF('船长每月数据(2023年)'!$E:$E,$C:$C,'船长每月数据(2023年)'!$R:$R),0) -> 0 | BI7: =SUMIFS('船长每月数据(2023年)'!$P:$P,'船长每月数据(2023年)'!$F:$F,$BI$2,'船长每月数据(2023年)'!$E:$E,$C:$C) -> 0 | BJ7: =IFERROR(BI7/SUMIF('船长每月数据(2023年)'!$E:$E,$C:$C,'船长每月数据(2023年)'!$P:$P),0) -> 0 | BK7: =SUMIFS('船长每月数据(2023年)'!$R:$R,'船长每月数据(2023年)'!$F:$F,$BK$2,'船长每月数据(2023年)'!$E:$E,$C:$C) -> 0 | BL7: =IFERROR(BK7/SUMIF('船长每月数据(2023年)'!$E:$E,$C:$C,'船长每月数据(2023年)'!$R:$R),0) -> 0 | BM7: =SUMIFS('船长每月数据(2023年)'!$P:$P,'船长每月数据(2023年)'!$F:$F,$BM$2,'船长每月数据(2023年)'!$E:$E,$C:$C) -> 0 | BN7: =IFERROR(BM7/SUMIF('船长每月数据(2023年)'!$E:$E,$C:$C,'船长每月数据(2023年)'!$P:$P),0) -> 0 | BO7: =SUMIFS('船长每月数据(2023年)'!$R:$R,'船长每月数据(2023年)'!$F:$F,$BO$2,'船长每月数据(2023年)'!$E:$E,$C:$C) -> 0 | BP7: =IFERROR(BO7/SUMIF('船长每月数据(2023年)'!$E:$E,$C:$C,'船长每月数据(2023年)'!$R:$R),0) -> 0 | BQ7: =SUMIFS('船长每月数据(2023年)'!$P:$P,'船长每月数据(2023年)'!$F:$F,$BQ$2,'船长每月数据(2023年)'!$E:$E,$C:$C) -> 0 | BR7: =IFERROR(BQ7/SUMIF('船长每月数据(2023年)'!$E:$E,$C:$C,'船长每月数据(2023年)'!$P:$P),0) -> 0 | BS7: =SUMIFS('船长每月数据(2023年)'!$R:$R,'船长每月数据(2023年)'!$F:$F,$BS$2,'船长每月数据(2023年)'!$E:$E,$C:$C) -> 0 | BT7: =IFERROR(BS7/SUMIF('船长每月数据(2023年)'!$E:$E,$C:$C,'船长每月数据(2023年)'!$R:$R),0) -> 0 | BU7: =SUMIFS('船长每月数据(2023年)'!$P:$P,'船长每月数据(2023年)'!$F:$F,$BU$2,'船长每月数据(2023年)'!$E:$E,$C:$C) -> 0 | BV7: =IFERROR(BU7/SUMIF('船长每月数据(2023年)'!$E:$E,$C:$C,'船长每月数据(2023年)'!$P:$P),0) -> 0 | BW7: =SUMIFS('船长每月数据(2023年)'!$R:$R,'船长每月数据(2023年)'!$F:$F,$BW$2,'船长每月数据(2023年)'!$E:$E,$C:$C) -> 0 | BX7: =IFERROR(BW7/SUMIF('船长每月数据(2023年)'!$E:$E,$C:$C,'船长每月数据(2023年)'!$R:$R),0) -> 0
E8: =SUMIFS('船长每月数据(2022年)'!$P:$P,'船长每月数据(2022年)'!$F:$F,$E$2,'船长每月数据(2022年)'!E:E,C:C) -> 0 | F8: =SUMIFS('船长每月数据(2022年)'!$R:$R,'船长每月数据(2022年)'!$F:$F,$F$2,'船长每月数据(2022年)'!E:E,C:C) -> 0 | G8: =SUMIFS('船长每月数据(2022年)'!$P:$P,'船长每月数据(2022年)'!$F:$F,$G$2,'船长每月数据(2022年)'!$E:$E,$C:$C) -> 0 | H8: =SUMIFS('船长每月数据(2022年)'!$R:$R,'船长每月数据(2022年)'!$F:$F,$H$2,'船长每月数据(2022年)'!$E:$E,$C:$C) -> 0 | I8: =SUMIFS('船长每月数据(2022年)'!$P:$P,'船长每月数据(2022年)'!$F:$F,$I$2,'船长每月数据(2022年)'!$E:$E,$C:$C) -> 0 | J8: =SUMIFS('船长每月数据(2022年)'!$R:$R,'船长每月数据(2022年)'!$F:$F,$J$2,'船长每月数据(2022年)'!$E:$E,$C:$C) -> 0 | K8: =SUMIFS('船长每月数据(2022年)'!$P:$P,'船长每月数据(2022年)'!$F:$F,$K$2,'船长每月数据(2022年)'!$E:$E,$C:$C) -> 0 | L8: =SUMIFS('船长每月数据(2022年)'!$R:$R,'船长每月数据(2022年)'!$F:$F,$L$2,'船长每月数据(2022年)'!$E:$E,$C:$C) -> 0 | M8: =SUMIFS('船长每月数据(2022年)'!$P:$P,'船长每月数据(2022年)'!$F:$F,$M$2,'船长每月数据(2022年)'!$E:$E,$C:$C) -> 0 | N8: =SUMIFS('船长每月数据(2022年)'!$R:$R,'船长每月数据(2022年)'!$F:$F,$N$2,'船长每月数据(2022年)'!$E:$E,$C:$C) -> 0 | O8: =SUMIFS('船长每月数据(2022年)'!$P:$P,'船长每月数据(2022年)'!$F:$F,$O$2,'船长每月数据(2022年)'!$E:$E,$C:$C) -> 0 | P8: =SUMIFS('船长每月数据(2022年)'!$R:$R,'船长每月数据(2022年)'!$F:$F,$P$2,'船长每月数据(2022年)'!$E:$E,$C:$C) -> 0 | Q8: =SUMIFS('船长每月数据(2022年)'!$P:$P,'船长每月数据(2022年)'!$F:$F,$Q$2,'船长每月数据(2022年)'!$E:$E,$C:$C) -> 0 | R8: =SUMIFS('船长每月数据(2022年)'!$R:$R,'船长每月数据(2022年)'!$F:$F,$R$2,'船长每月数据(2022年)'!$E:$E,$C:$C) -> 0 | S8: =SUMIFS('船长每月数据(2022年)'!$P:$P,'船长每月数据(2022年)'!$F:$F,$S$2,'船长每月数据(2022年)'!$E:$E,$C:$C) -> 0 | T8: =SUMIFS('船长每月数据(2022年)'!$R:$R,'船长每月数据(2022年)'!$F:$F,$T$2,'船长每月数据(2022年)'!$E:$E,$C:$C) -> 0 | U8: =SUMIFS('船长每月数据(2022年)'!$P:$P,'船长每月数据(2022年)'!$F:$F,$U$2,'船长每月数据(2022年)'!$E:$E,$C:$C) -> 0 | V8: =SUMIFS('船长每月数据(2022年)'!$R:$R,'船长每月数据(2022年)'!$F:$F,$V$2,'船长每月数据(2022年)'!$E:$E,$C:$C) -> 0 | W8: =SUMIFS('船长每月数据(2022年)'!$P:$P,'船长每月数据(2022年)'!$F:$F,$W$2,'船长每月数据(2022年)'!$E:$E,$C:$C) -> 0 | X8: =SUMIFS('船长每月数据(2022年)'!$R:$R,'船长每月数据(2022年)'!$F:$F,$X$2,'船长每月数据(2022年)'!$E:$E,$C:$C) -> 0 | Y8: =SUMIFS('船长每月数据(2022年)'!$P:$P,'船长每月数据(2022年)'!$F:$F,$Y$2,'船长每月数据(2022年)'!$E:$E,$C:$C) -> 0 | Z8: =SUMIFS('船长每月数据(2022年)'!$R:$R,'船长每月数据(2022年)'!$F:$F,$Z$2,'船长每月数据(2022年)'!$E:$E,$C:$C) -> 0 | AA8: =SUMIFS('船长每月数据(2022年)'!$P:$P,'船长每月数据(2022年)'!$F:$F,$AA$2,'船长每月数据(2022年)'!$E:$E,$C:$C) -> 0 | AB8: =SUMIFS('船长每月数据(2022年)'!$R:$R,'船长每月数据(2022年)'!$F:$F,$AB$2,'船长每月数据(2022年)'!$E:$E,$C:$C) -> 0 | AC8: =SUMIFS('船长每月数据(2023年)'!P:P,'船长每月数据(2023年)'!F:F,$AC$2,'船长每月数据(2023年)'!E:E,C:C) -> 0 | AD8: =IFERROR(AC8/SUMIF('船长每月数据(2023年)'!$E:$E,C:C,'船长每月数据(2023年)'!P:P),0) -> 0 | AE8: =SUMIFS('船长每月数据(2023年)'!$R:$R,'船长每月数据(2023年)'!$F:$F,$AE$2,'船长每月数据(2023年)'!$E:$E,$C:$C) -> 0 | AF8: =IFERROR(AE8/SUMIF('船长每月数据(2023年)'!E:E,C:C,'船长每月数据(2023年)'!R:R),0) -> 0 | AG8: =SUMIFS('船长每月数据(2023年)'!P:P,'船长每月数据(2023年)'!F:F,$AG$2,'船长每月数据(2023年)'!E:E,C:C) -> 0 | AH8: =IFERROR(AG8/SUMIF('船长每月数据(2023年)'!$E:$E,$C:$C,'船长每月数据(2023年)'!$P:$P),0) -> 0 | AI8: =SUMIFS('船长每月数据(2023年)'!$R:$R,'船长每月数据(2023年)'!$F:$F,$AI$2,'船长每月数据(2023年)'!$E:$E,$C:$C) -> 0 | AJ8: =IFERROR(AI8/SUMIF('船长每月数据(2023年)'!$E:$E,$C:$C,'船长每月数据(2023年)'!$R:$R),0) -> 0 | AK8: =SUMIFS('船长每月数据(2023年)'!P:P,'船长每月数据(2023年)'!F:F,$AK$2,'船长每月数据(2023年)'!E:E,C:C) -> 0 | AL8: =IFERROR(AK8/SUMIF('船长每月数据(2023年)'!$E:$E,$C:$C,'船长每月数据(2023年)'!$P:$P),0) -> 0 | AM8: =SUMIFS('船长每月数据(2023年)'!$R:$R,'船长每月数据(2023年)'!$F:$F,$AM$2,'船长每月数据(2023年)'!$E:$E,$C:$C) -> 0 | AN8: =IFERROR(AM8/SUMIF('船长每月数据(2023年)'!$E:$E,$C:$C,'船长每月数据(2023年)'!$R:$R),0) -> 0 | AO8: =SUMIFS('船长每月数据(2023年)'!P:P,'船长每月数据(2023年)'!F:F,$AO$2,'船长每月数据(2023年)'!E:E,C:C) -> 0 | AP8: =IFERROR(AO8/SUMIF('船长每月数据(2023年)'!$E:$E,$C:$C,'船长每月数据(2023年)'!$P:$P),0) -> 0 | AQ8: =SUMIFS('船长每月数据(2023年)'!$R:$R,'船长每月数据(2023年)'!$F:$F,$AQ$2,'船长每月数据(2023年)'!$E:$E,$C:$C) -> 0 | AR8: =IFERROR(AQ8/SUMIF('船长每月数据(2023年)'!$E:$E,$C:$C,'船长每月数据(2023年)'!$R:$R),0) -> 0 | AS8: =SUMIFS('船长每月数据(2023年)'!$P:$P,'船长每月数据(2023年)'!$F:$F,$AS$2,'船长每月数据(2023年)'!$E:$E,$C:$C) -> 0 | AT8: =IFERROR(AS8/SUMIF('船长每月数据(2023年)'!$E:$E,$C:$C,'船长每月数据(2023年)'!$P:$P),0) -> 0 | AU8: =SUMIFS('船长每月数据(2023年)'!$R:$R,'船长每月数据(2023年)'!$F:$F,$AU$2,'船长每月数据(2023年)'!$E:$E,$C:$C) -> 0 | AV8: =IFERROR(AU8/SUMIF('船长每月数据(2023年)'!$E:$E,$C:$C,'船长每月数据(2023年)'!$R:$R),0) -> 0 | AW8: =SUMIFS('船长每月数据(2023年)'!$P:$P,'船长每月数据(2023年)'!$F:$F,$AW$2,'船长每月数据(2023年)'!$E:$E,$C:$C) -> 0 | AX8: =IFERROR(AW8/SUMIF('船长每月数据(2023年)'!$E:$E,$C:$C,'船长每月数据(2023年)'!$P:$P),0) -> 0 | AY8: =SUMIFS('船长每月数据(2023年)'!$R:$R,'船长每月数据(2023年)'!$F:$F,$AY$2,'船长每月数据(2023年)'!$E:$E,$C:$C) -> 0 | AZ8: =IFERROR(AY8/SUMIF('船长每月数据(2023年)'!$E:$E,$C:$C,'船长每月数据(2023年)'!$R:$R),0) -> 0 | BA8: =SUMIFS('船长每月数据(2023年)'!$P:$P,'船长每月数据(2023年)'!$F:$F,$BA$2,'船长每月数据(2023年)'!$E:$E,$C:$C) -> 0 | BB8: =IFERROR(BA8/SUMIF('船长每月数据(2023年)'!$E:$E,$C:$C,'船长每月数据(2023年)'!$P:$P),0) -> 0 | BC8: =SUMIFS('船长每月数据(2023年)'!$R:$R,'船长每月数据(2023年)'!$F:$F,$BC$2,'船长每月数据(2023年)'!$E:$E,$C:$C) -> 0 | BD8: =IFERROR(BC8/SUMIF('船长每月数据(2023年)'!$E:$E,$C:$C,'船长每月数据(2023年)'!$R:$R),0) -> 0 | BE8: =SUMIFS('船长每月数据(2023年)'!$P:$P,'船长每月数据(2023年)'!$F:$F,$BE$2,'船长每月数据(2023年)'!$E:$E,$C:$C) -> 0 | BF8: =IFERROR(BE8/SUMIF('船长每月数据(2023年)'!$E:$E,$C:$C,'船长每月数据(2023年)'!$P:$P),0) -> 0 | BG8: =SUMIFS('船长每月数据(2023年)'!$R:$R,'船长每月数据(2023年)'!$F:$F,$BG$2,'船长每月数据(2023年)'!$E:$E,$C:$C) -> 0 | BH8: =IFERROR(BG8/SUMIF('船长每月数据(2023年)'!$E:$E,$C:$C,'船长每月数据(2023年)'!$R:$R),0) -> 0 | BI8: =SUMIFS('船长每月数据(2023年)'!$P:$P,'船长每月数据(2023年)'!$F:$F,$BI$2,'船长每月数据(2023年)'!$E:$E,$C:$C) -> 0 | BJ8: =IFERROR(BI8/SUMIF('船长每月数据(2023年)'!$E:$E,$C:$C,'船长每月数据(2023年)'!$P:$P),0) -> 0 | BK8: =SUMIFS('船长每月数据(2023年)'!$R:$R,'船长每月数据(2023年)'!$F:$F,$BK$2,'船长每月数据(2023年)'!$E:$E,$C:$C) -> 0 | BL8: =IFERROR(BK8/SUMIF('船长每月数据(2023年)'!$E:$E,$C:$C,'船长每月数据(2023年)'!$R:$R),0) -> 0 | BM8: =SUMIFS('船长每月数据(2023年)'!$P:$P,'船长每月数据(2023年)'!$F:$F,$BM$2,'船长每月数据(2023年)'!$E:$E,$C:$C) -> 0 | BN8: =IFERROR(BM8/SUMIF('船长每月数据(2023年)'!$E:$E,$C:$C,'船长每月数据(2023年)'!$P:$P),0) -> 0 | BO8: =SUMIFS('船长每月数据(2023年)'!$R:$R,'船长每月数据(2023年)'!$F:$F,$BO$2,'船长每月数据(2023年)'!$E:$E,$C:$C) -> 0 | BP8: =IFERROR(BO8/SUMIF('船长每月数据(2023年)'!$E:$E,$C:$C,'船长每月数据(2023年)'!$R:$R),0) -> 0 | BQ8: =SUMIFS('船长每月数据(2023年)'!$P:$P,'船长每月数据(2023年)'!$F:$F,$BQ$2,'船长每月数据(2023年)'!$E:$E,$C:$C) -> 0 | BR8: =IFERROR(BQ8/SUMIF('船长每月数据(2023年)'!$E:$E,$C:$C,'船长每月数据(2023年)'!$P:$P),0) -> 0 | BS8: =SUMIFS('船长每月数据(2023年)'!$R:$R,'船长每月数据(2023年)'!$F:$F,$BS$2,'船长每月数据(2023年)'!$E:$E,$C:$C) -> 0 | BT8: =IFERROR(BS8/SUMIF('船长每月数据(2023年)'!$E:$E,$C:$C,'船长每月数据(2023年)'!$R:$R),0) -> 0 | BU8: =SUMIFS('船长每月数据(2023年)'!$P:$P,'船长每月数据(2023年)'!$F:$F,$BU$2,'船长每月数据(2023年)'!$E:$E,$C:$C) -> 0 | BV8: =IFERROR(BU8/SUMIF('船长每月数据(2023年)'!$E:$E,$C:$C,'船长每月数据(2023年)'!$P:$P),0) -> 0 | BW8: =SUMIFS('船长每月数据(2023年)'!$R:$R,'船长每月数据(2023年)'!$F:$F,$BW$2,'船长每月数据(2023年)'!$E:$E,$C:$C) -> 0 | BX8: =IFERROR(BW8/SUMIF('船长每月数据(2023年)'!$E:$E,$C:$C,'船长每月数据(2023年)'!$R:$R),0) -> 0
